Workbook
Name PC_Products: 'Card Lists'!$A$1:$A$1
Name PC_D_1: 'Card Lists'!$B$1:$B$11
Name PC_N_1: 'Card Lists'!$D$1:$D$1
Name PC_I_1: 'Card Lists'!$E$1:$E$1
Name PC_N_2: 'Card Lists'!$D$2:$D$2
Name PC_I_2: 'Card Lists'!$E$2:$E$2
Name PC_N_3: 'Card Lists'!$D$3:$D$3
Name PC_I_3: 'Card Lists'!$E$3:$E$3
Name PC_N_4: 'Card Lists'!$D$4:$D$27
Name PC_I_4: 'Card Lists'!$E$4:$E$27
Name PC_N_5: 'Card Lists'!$D$28:$D$41
Name PC_I_5: 'Card Lists'!$E$28:$E$41
Name PC_N_6: 'Card Lists'!$D$42:$D$72
Name PC_I_6: 'Card Lists'!$E$42:$E$72
Name PC_N_7: 'Card Lists'!$D$73:$D$80
Name PC_I_7: 'Card Lists'!$E$73:$E$80
Name PC_N_8: 'Card Lists'!$D$81:$D$86
Name PC_I_8: 'Card Lists'!$E$81:$E$86
Name PC_N_9: 'Card Lists'!$D$87:$D$146
Name PC_I_9: 'Card Lists'!$E$87:$E$146
Name PC_N_10: 'Card Lists'!$D$147:$D$168
Name PC_I_10: 'Card Lists'!$E$147:$E$168
Name PC_N_11: 'Card Lists'!$D$169:$D$215
Name PC_I_11: 'Card Lists'!$E$169:$E$215
Name PC_Keys: 'Card Lists'!$F$1:$F$11
Name PC_NK: 'Card Lists'!$H$1:$H$215
Name PC_NKIds: 'Card Lists'!$I$1:$I$215
Name PC_NKRow: 'Card Lists'!$J$1:$J$215
Name PC_ProdF: OFFSET('Card Lists'!$M$1,0,0,MAX(1,'Card Lists'!$L$1),1)
Name PC_DeptF: OFFSET('Card Lists'!$O$1,0,0,MAX(1,'Card Lists'!$N$11),1)
Name PC_NameF: OFFSET('Card Lists'!$Q$1,0,0,MAX(1,'Card Lists'!$P$215),1)
Name WM_EXP_AB: '1d. Weightage Matrix'!$B$6
Name WM_EXP_CE: '1d. Weightage Matrix'!$B$7
Name WM_C: '1d. Weightage Matrix'!$N$17:$N$46
Name WM_AU: '1d. Weightage Matrix'!$O$17:$O$46
Name WM_AC: '1d. Weightage Matrix'!$P$17:$P$46
Name WM_L: '1d. Weightage Matrix'!$Q$17:$Q$46
Name WM_E: '1d. Weightage Matrix'!$R$17:$R$46
Name WM_BI: '1d. Weightage Matrix'!$S$17:$S$46
Name WM_KEY: '1d. Weightage Matrix'!$A$17:$A$46

Sheet Start — How It Works
A1: How this exercise works — from a base framework to the final job architecture | E1: ◂ Contents
A2: Read this first: what we did step by step, what is happening now, how the model works, what it produced, the impact — then our framework, the Job Architecture process and the Job Design process. The same page opens every file. The full master for one product: every person, the reasoning, the role catalogue, insights and the career ladder.
A3: IRIS · Job Architecture & Job Design · Final v1.12 · October 2026 · Internal — Confidential
A5: 1. What we did — step by step
A6: # | B6: Step | C6: What we did | D6: What came out of it
A7: 1 | B7: Created a base framework | C7: Built IRIS's job architecture from established market methods — Aon Radford / Mercer career levels, Korn Ferry Hay factors, WTW banding and SFIA — with job families anchored to the ILO occupation standard. | D7: 19 job families, 61 sub-families, a 12-level ladder plus two Player-Coach steps · B+, C+, six factors, individual-contributor and manager tracks
A8: 2 | B8: Designed a survey around it | C8: The 'How We Grow' survey: 20 questions, each tied to the framework's factors — purpose of the role, what it delivers, what it is accountable for, what it can decide, the skills and tools it needs, and learning needs. | D8: One evidence form for every role, so each rating can be traced to an answer
A9: 3 | B9: Conducted 60–65 workshops | C9: Ran 60–65 workshops with teams across the six products and Corporate: explained the framework, walked through the questions and collected answers in the room. | D9: Survey responses from 520 people
A10: 4 | B10: Gathered the data | C10: Combined the survey with the HRIS employee master, KRAs · self and manager-set, the managers' talent mapping · rating, potential, 9-box and the reporting lines. | D10: One record per person — 586 people; KRAs on file for 453
A11: 5 | B11: Cleaned and protected it | C11: Matched responses to people · with consent where needed, removed personal data, and showed survey content only where three or more role-holders answered — never one person's words against a name. | D11: Privacy-safe evidence
A12: 6 | B12: Mapped every role | C12: Placed each person in a job family, a sub-family · the work they actually do and a track. | D12: 267 distinct employee roles; one IRIS-wide role catalogue
A13: 7 | B13: Rated and scored | C13: Rated six factors — Complexity, Autonomy, Accountability, Leadership, Experience & Qualification, Business Impact — on the ladder scale from the evidence; rating × weight = points; points add up to a score; the score points to a level. | D13: A score and an indicated level for 540 employees
A14: 8 | B14: Applied the rules | C14: Gates, limits and Player-Coach steps where the evidence calls for them, and leadership decisions for the top bands — each one written down with its numbers. | D14: A final level and designation for everyone, every move explained
A15: 9 | B15: Benchmarked to the market | C15: Matched every level to Aon Radford / Mercer codes and SFIA, and to competitor, regtech and SaaS ladders; every source re-read and corrected. | D15: A market code and a typical market title for every level
A16: 10 | B16: Built the file set | C16: One build produces every file from the same data, so they always agree: the HR Super Master, product masters and simplified editions, the framework & model master, the calibration panel pack, the ladder master and draft letters. | D16: Files by audience, rebuilt and re-checked in minutes
A17: 11 | B17: Reviewed and corrected | C17: Business-head review, independent reviews, and 100+ automated checks on every build · placements, privacy, formulas, links, counts. | D17: Corrections fed back as validated inputs, never as hand edits
A19: 2. What we are doing now
A20: Now | C20: What happens | D20: Who
A21: Calibration | C21: The panel rates anchor roles blind and compares them with the model; close calls and moves down are decided. | D21: Calibration panel
A22: Decisions and data | C22: Open decisions and critical data requests are worked in the HR Super Master's tracker. | D22: HR, managers, business heads
A23: Business-head review | C23: Each business head marks Agree / Change / Discuss in their simplified edition; responses are imported and tracked. | D23: Business heads
A24: Sign-off | C24: The executive sponsor approves the structure; then the draft letters are issued. | D24: Executive sponsor, HR
A25: Pay · later | C25: Buy one India pay survey and price each level; pay columns stay blank until then. | D25: HR, Finance
A27: 3. How it works — in one minute
A28: Step | C28: In plain words
A29: 1 · A building with 12 floors | C29: IRIS is a building: floor 1 = first job, floor 12 = CEO; two half floors · B+, C+ for player-coaches. Every job lives on one floor.
A30: 2 · Six judges | C30: Six judges look at the job — How hard? Decides alone? Answers for? Leads? Experience? Business impact? — and each holds up a floor number · the rating, using the evidence: survey, KRAs, HRIS, reporting line.
A31: 3 · Some count more | C31: Starting out, the quality of the work counts most; for leaders, results, leading and business impact count most. Experience counts little. All six add to 100%, and leaders can edit them on the Weightage Matrix.
A32: 4 · Add up = the floor | C32: Card × how much it counts = points; add the points = the score; round it = the floor · 5.05 → 5 → B2. Fair-play checks can hold it — each one written down.
A34: The HR Super Master's sheet '1c. Scoring Made Simple' and the Process Explainer tell this story in full, with three worked examples.
A35: 4. What it produced — the output
A36: Output | D36: Count
A37: People mapped · employees + consultants | D37: 586
A38: Job families · sub-families | D38: 19 · 61
A39: Ladder steps in use · employees | D39: 13
A40: Designations on the new ladder · employees | D40: 184
A41: Distinct employee roles | D41: 267
A42: Products and Corporate | D42: 6
A43: People in leadership bands D–E | D43: 11
A45: 5. The impact
A46: Impact | C46: What it means
A47: One architecture for all of IRIS | C47: The same families, the same ladder and the same method in every product — titles mean the same thing everywhere.
A48: Transparent, explainable levels | C48: Every level traces to evidence, ratings, weights and named rules; anyone can see why a role sits where it does.
A49: Clear career paths | C49: Individual-contributor and manager tracks with a ladder in every sub-family, and the competencies needed for the next step.
A50: Duplication made visible | C50: 53 family × sub-family × level combinations are held in more than one product — candidates for common role definitions and shared pools.
A51: Leadership consistency | C51: No one in Bands D–E sits above their reporting manager, anyone in Band D reporting to an E1 / E2 sits at D2, and leadership levels are set by approved decisions.
A52: Ready for pay and planning | C52: Each level carries a market code, so pay ranges, succession and workforce planning can be built on it.
A54: 6. Our framework at a glance
A55: Element | B55: What it is
A56: Job families | B56: 19 families of work, each anchored to the ILO occupation standard — the same in every product.
A57: Sub-families | B57: 61 sub-families: the work a person actually does inside a family. One definition each, used everywhere.
A58: Career ladder | B58: One ladder from intern to CEO: A1–A3 practitioner · B1–B3 specialist / manager · B+ Player-Coach · C1–C2 principal / head · C+ Player-Coach · D1–D2 business leadership · E1–E2 enterprise leadership; X1–X3 for consultants · outside the ladder.
A59: Tracks | B59: Individual contributor, POD Lead · leads 1–3 while doing the work, Player-Coach · leads and delivers, People Manager, Consultant — experts progress without having to manage.
A60: Six factors | B60: Complexity & Expertise · Autonomy & Decision · Accountability & Impact · Leadership & Strategy · Experience & Qualification · Business Impact — each gets a rating: the floor of the ladder that part of the job looks like.
A61: Weights | B61: How much each factor counts, by band and track · junior roles: skill and experience; senior roles: accountability and leadership, fine-tuned ±5 by type of work.
A62: Rules | B62: R1–R13: category rules, provisional holds, work-substance and structure gates, experience limits, track minimums, Player-Coach steps, leadership decisions and the D–E reporting-line rules — each written on the person's row with its numbers.
A63: Titles | B63: Level marker + role noun; market titles where the market has its own ladder · Product Manager, Account Executive.
A64: Competencies | B64: 6 core and 4 future-ready for everyone, 4 leadership for leaders, and functional competencies for each family — each with a 1–5 skill level required at every career level.
A65: Market link | B65: Every level maps to Aon Radford / Mercer codes and SFIA, with competitor, regtech and SaaS equivalents — the base for pay ranges later.
A67: 7. The Job Architecture process — how the structure was built
A68: # | B68: Step | C68: What happens
A69: 1 | B69: Define families | C69: Group all work into job families anchored to ISCO-08, so the same work has the same name everywhere.
A70: 2 | B70: Define sub-families | C70: Split each family into the distinct kinds of work people do, from the survey and role data.
A71: 3 | B71: Set the ladder and bands | C71: One 12-level ladder with five bands and two Player-Coach steps; what each level owns, its experience range and span.
A72: 4 | B72: Set the tracks | C72: IC, POD Lead, Player-Coach, People Manager, Consultant — and the rules for each.
A73: 5 | B73: Level every role | C73: Six ratings × weights → score → level, then the rules; leadership levels by approved decision.
A74: 6 | B74: Name every role | C74: Designation = level marker + role noun; title protection for anyone moving down.
A75: 7 | B75: Benchmark | C75: Crosswalk every level to Radford / Mercer and SFIA; compare with competitor and peer ladders.
A76: 8 | B76: Govern | C76: Calibration panel, business-head review, a decision tracker and change rules · who can change a level, and how.
A78: 8. The Job Design process — how each role is described
A79: # | B79: Step | C79: What happens
A80: 1 | B80: Purpose | C80: Why the role exists — from the sub-family definition and the level standard.
A81: 2 | B81: Responsibilities and deliverables | C81: What the role does and produces — from role-holders' survey answers · as counted themes and KRAs.
A82: 3 | B82: Accountability and decision rights | C82: What the role answers for, what it can decide alone, and what happens if the work is missed.
A83: 4 | B83: Measures | C83: Manager-set KRAs: how the role is judged.
A84: 5 | B84: Competencies and skill level | C84: The core, future-ready, functional and leadership competencies the role needs, each at a 1–5 level.
A85: 6 | B85: Role profile and catalogue | C85: One IRIS-wide catalogue entry per family × sub-family × level × track — the shared description of the job.
A86: 7 | B86: Career ladder | C86: Where the role sits in its sub-family's ladder, the next step and what it takes.
A87: 8 | B87: Recruitment profile | C87: The hire equivalent in the market, the competencies to hire for and the interview questions — on every person card.

Sheet Contents
A1: IRIS Job Architecture — CARBON Product Master — contents
A2: Click a sheet name to go there; every sheet has a '◂ Contents' link at the top right to come back.
A3: IRIS · Job Architecture & Job Design · Final v1.12 · October 2026 · Internal — Confidential
A5: # | B5: Sheet | C5: What it holds
A6: 1 | B6: Start — How It Works | C6: Read this first: what we did step by step, what is happening now, how the model works, what it produced, the impact — then our framework, the Job Architecture process and the Job Design process.
A7: 2 | B7: 1. Overview | C7: The whole picture on one page: how many people, families, sub-families and roles; what changed from the old structure; where everyone sits by band, track and department; the Player-Coach transition steps; what each sheet in this workbook is for; and, at the end, how a role's level is worked out.
A8: 3 | B8: 1a. Placements | C8: Who sits where, before → after, the score as built, the six ratings · bars, what set the level and any flag; after a leader edits the Weightage Matrix, the live score is on sheet 2. The full reasoning for one person is on sheet 1b · choose the Emp ID; every column for everyone is on sheet 2. Filter by business, department, family or level with the header arrows.
A9: 4 | B9: 1b. Person Card | C9: Find a person: paste or type an Emp ID, or pick Department → Name from the yellow drop-downs — type part of a word in the Search box beside a drop-down to shorten its list.
A10: 5 | B10: 1d. Weightage Matrix | C10: 1d · Leaders: change the yellow weights. Sheet 2 recalculates points, score and 'Level the score indicates' at once.
A11: 6 | B11: 1e. Weight Benchmark | C11: 1e · The published point-factor plans, how weights shift with seniority, the evidence on experience and on business impact, and IRIS's defaults set against them.
A12: 7 | B12: 2. Talent Mapping | C12: Read left to right: the person → their role before and after → what the role does · responsibilities and competencies required → six ratings × weights = points → the score and the level it points to → any rule that changed the level → why each rating was given · starting point, evidence, market standard → the data used.
A13: 8 | B13: 3. Raw Data & Market Standards | C13: Left: the person and their final role. Middle: the market standard for that role and level.
A14: 9 | B14: 4. Role Competency Framework | C14: For every role · designation × level × track and the sub-family it sits in: the proficiency required in each cluster and exactly what that proficiency looks like — the six core and four future-ready competencies, the leadership expected, the family's must-have and other functional competencies, the department's technical competencies, how to assess them, the credentials, and where today's role-holders stand.
A15: 10 | B15: 5. Capability Framework | C15: The level sizes the role; the capability framework defines what a person in it must be able to do, and how well · proficiency 1–5, aligned to SFIA 9.
A16: 11 | B16: 6. Role Catalogue | C16: One row per catalogue role · job family × sub-family × level × track that someone here holds.
A17: 12 | B17: 7. Role Requirements | C17: One row per role · designation × level × track inside each department, lowest level first.
... A29: 24 | B29: 18. Career Ladder | C29: 215 people in 11 departments. One row per designation at a level in a department, ordered department → band → level · bottom to top: earlier rows are lower levels. 'Same work' = same job family, sub-family and level; overlap within the product is shaded orange, overlap across IRIS blue.

Sheet 1. Overview
A1: Overview — CARBON | O1: ◂ Contents
A2: Sheet 1 · The whole picture on one page: how many people, families, sub-families and roles; what changed from the old structure; where everyone sits by band, track and department; the Player-Coach transition steps; what each sheet in this workbook is for; and, at the end, how a role's level is worked out.
A3: IRIS · Job Architecture & Job Design · Final v1.12 · October 2026 · Internal — Confidential
A5: 1. Headline numbers
A6: People | C6: Departments | E6: Job families | G6: Sub-families | I6: Roles | K6: Ladder steps in use | M6: Player-Coaches
A7: 215 | C7: 11 | E7: 14 | G7: 38 | I7: 92 | K7: 11 | M7: 0
A8: Level up vs current | C8: Level down · protected | E8: Same level | G8: Newly mapped | I8: Close calls / near a gate | K8: Consultants
A9: 131 | C9: 14 | E9: 53 | G9: 17 | I9: 17 / 8 | K9: 2
A10: Job families and sub-families exclude 'Unassigned' · consultants with no role on record. Career levels: 12 levels A1–E2 plus 2 Player-Coach Player-Coach transition steps · B+, C+ = 14; consultants sit outside the ladder at X1–X3. Departments are counted per business line.
A12: 2. What changed — old structure → new structure
A13: Measure | D13: Old · count | F13: New · count | H13: People whose value changed | J13: People unchanged | L13: What it means
A14: Job families | D14: 13 | F14: 14 | H14: 108 | J14: 107 | L14: Families are now disciplines, the same across businesses
A15: Sub-families | D15: 39 | F15: 38 | H15: 208 | J15: 7 | L15: Sub-families now name the actual work done
A16: Designations | D16: 70 | F16: 85 | H16: 189 | J16: 26 | L16: Title = level marker + role noun
A17: Career levels | D17: 9 | F17: 11 | H17: 162 | J17: 53 | L17: New ladder: 12 levels + 2 Player-Coach transition steps; consultants counted separately
A19: 2a. Job families — old → new
A20: Old job family | F20: New job family | K20: People | L20: What happened
A21: Professional Services | F21: Consulting & Professional Services | K21: 57 | L21: Split into several
A22: Engineering & Development | F22: Engineering & Development | K22: 42 | L22: Unchanged; others joined it
A23: Professional Services | F23: Data Operations & Digitization | K23: 23 | L23: Split into several
A24: Sales & Business Development | F24: Sales & Business Development | K24: 21 | L24: Unchanged; part of it moved elsewhere
A25: Customer Success & Support | F25: Customer Success & Support | K25: 17 | L25: Unchanged; others joined it
A26: Marketing & Communications | F26: Marketing & Communications | K26: 13 | L26: Unchanged; part of it moved elsewhere; others joined it
A27: Quality Assurance | F27: Quality Assurance | K27: 8 | L27: Unchanged; part of it moved elsewhere; others joined it
A28: Consulting | F28: Solution Consulting & Implementation | K28: 6 | L28: Split and regrouped
A29: Consulting | F29: Product Management | K29: 5 | L29: Split into several
A30: Business Analysis | F30: Business Analysis | K30: 3 | L30: Unchanged
A31: Executive Leadership | F31: Executive Leadership | K31: 3 | L31: Unchanged
A32: Consulting | F32: Customer Success & Support | K32: 2 | L32: Split and regrouped
... A44: Sales & Business Development | F44: Data & Analytics | K44: 1 | L44: Split into several
A46: 2b. Sub-families — old → new · the 30 largest moves; sheet 10 §2 lists every sub-family
A47: Old sub-family | F47: New sub-family | K47: People | L47: What happened
A48: XBRL / Regulatory Reporting | F48: XBRL Tagging, Conversion & Filing | K48: 52 | L48: Split into several
A49: Digitization & Image Processing | F49: Document Conversion, Formatting & Web Publishing | K49: 22 | L49: Split into several
A50: Sales Development · SDR | F50: Sales Development & Prospecting | K50: 15 | L50: Renamed
A51: Full-Stack Engineering | F51: Backend Development | K51: 9 | L51: Split and regrouped
A52: Customer Success | F52: Customer Success & Account Management | K52: 8 | L52: Split and regrouped
A53: AI / ML Engineering | F53: AI / ML & GenAI Engineering | K53: 7 | L53: Split into several
A54: Customer Success | F54: Application & Product Support | K54: 7 | L54: Split and regrouped
A55: Full-Stack Engineering | F55: Full-Stack Development | K55: 6 | L55: Split and regrouped
A56: Frontend / UI Engineering | F56: Front-End / UI Development | K56: 5 | L56: Split and regrouped
A57: Implementation & Solutions Consulting | F57: Solution Consulting & Implementation | K57: 5 | L57: Split and regrouped
A58: Quality Testing | F58: Functional & Domain Testing | K58: 5 | L58: Split and regrouped
A59: Content Marketing | F59: Content Marketing | K59: 4 | L59: Unchanged; others joined it
... A77: Customer Support | F77: Application & Product Support | K77: 1 | L77: Merged with others
A79: 3. Where people sit — band × track
A80: Band | D80: IC | F80: POD Lead | H80: Player-Coach | J80: People Manager | L80: Consultant | N80: Total
A81: A | D81: 136 | N81: 136
A82: B | D82: 26 | F82: 24 | J82: 18 | N82: 68
A83: B+ | N83: 0
A84: C | D84: 1 | J84: 5 | N84: 6
A85: C+ | N85: 0
A86: D | J86: 2 | N86: 2
A87: E | J87: 1 | N87: 1
A88: X | L88: 2 | N88: 2
A89: Total | D89: 163 | F89: 24 | H89: 0 | J89: 26 | L89: 2 | N89: 215
A91: 4. Levels by department · bottom to top, left to right
A92: Department | B92: A1 | C92: A2 | D92: A3 | E92: B1 | F92: B2 | G92: B3 | H92: C1 | I92: C2 | J92: D1 | K92: D2 | L92: E1 | M92: X1 | N92: X3 | O92: Total
A93: CARBON Business Head | K93: 1 | O93: 1
A94: CRO - Carbon | L94: 1 | O94: 1
A95: Customer Experience | J95: 1 | O95: 1
A96: Digitizing | C96: 3 | D96: 14 | E96: 5 | F96: 1 | H96: 1 | O96: 24
A97: Functional | D97: 2 | E97: 10 | F97: 2 | O97: 14
A98: Marketing | B98: 3 | C98: 13 | D98: 7 | E98: 4 | F98: 3 | G98: 1 | O98: 31
A99: Quality Assurance | D99: 7 | F99: 1 | O99: 8
A100: Sales | D100: 1 | E100: 1 | F100: 1 | G100: 1 | H100: 1 | N100: 1 | O100: 6
A101: Services | C101: 1 | D101: 37 | E101: 13 | F101: 7 | H101: 2 | O101: 60
A102: Support | D102: 12 | E102: 2 | F102: 6 | H102: 1 | M102: 1 | O102: 22
A103: Technology | B103: 2 | C103: 5 | D103: 29 | E103: 4 | F103: 5 | G103: 1 | I103: 1 | O103: 47
A104: Total | B104: 5 | C104: 22 | D104: 109 | E104: 39 | F104: 26 | G104: 3 | H104: 5 | I104: 1 | J104: 1 | K104: 1 | L104: 1 | M104: 1 | N104: 1 | O104: 215
A106: 5. Job families × band
A107: Job family | E107: A | F107: B | G107: B+ | H107: C | I107: C+ | J107: D | K107: E | L107: X | M107: Total | N107: Sub-families
A108: Consulting & Professional Services | E108: 37 | F108: 18 | H108: 2 | M108: 57 | N108: 3
A109: Engineering & Development | E109: 36 | F109: 8 | H109: 1 | M109: 45 | N109: 7
A110: Data Operations & Digitization | E110: 17 | F110: 5 | H110: 1 | M110: 23 | N110: 2
A111: Customer Success & Support | E111: 9 | F111: 10 | H111: 1 | L111: 1 | M111: 21 | N111: 4
A112: Sales & Business Development | E112: 12 | F112: 7 | H112: 1 | L112: 1 | M112: 21 | N112: 4
A113: Marketing & Communications | E113: 11 | F113: 3 | M113: 14 | N113: 5
A114: Quality Assurance | E114: 8 | F114: 2 | M114: 10 | N114: 3
A115: Solution Consulting & Implementation | E115: 1 | F115: 6 | M115: 7 | N115: 1
A116: Product Management | E116: 1 | F116: 4 | M116: 5 | N116: 1
A117: Executive Leadership | J117: 2 | K117: 1 | M117: 3 | N117: 2
A118: Design & Creative | E118: 2 | F118: 1 | M118: 3 | N118: 2
A119: Business Analysis | E119: 1 | F119: 2 | M119: 3 | N119: 1
A120: Project & Program Management | F120: 2 | M120: 2 | N120: 2
A121: Data & Analytics | E121: 1 | M121: 1 | N121: 1
A123: 6. Player-Coach transition steps · new — between Bands B and C, and C and D
A124: A Player-Coach leads people AND still delivers hands-on expert work. Placed on evidence only; candidates go to the manager and the calibration panel.
A125: Person | C125: Department | E125: Before | F125: Now | G125: Designation | J125: Why
A126: Saahit Togaru | C126: Marketing | E126: B3 | F126: Watch list | G126: Senior Marketing Manager | J126: B+ watch: leads people, Player-Coach score 5.93 · needs 6.25, C–A average 6.00 · needs 5.5
A127: Ashish Singhvi | C127: Technology | E127: C2 | F127: Watch list | G127: Head – Product Engineering | J127: C+ watch: leads people, Player-Coach score 8.07 · needs 8.25, C–A average 8.00 · needs 7.5
A129: 7. Critical inputs needed — who must supply what · red cells across the workbook
A130: Input needed | H130: Who provides it | L130: People
A131: Confirm the reporting line | H131: Manager | L131: 34
A132: Survey response or KRAs describing the work · nothing on file | H132: Employee + manager | L132: 5
A133: Correct the experience record | H133: HR | L133: 5
A134: Resolve conflicting role records | H134: Business head | L134: 3
A135: Confirm structure behind the senior title · org chart | H135: Business head | L135: 2
A137: 44 of 215 people need at least one critical input · one that could change or confirm the placement; pay is set later. The full list by person is on sheet 9, section J.
A138: 8. What the colours mean
...

Sheet 1a. Placements
A1: Placements — one line per person · the slim view | W1: ◂ Contents
A2: Sheet 1a · Who sits where, before → after, the score as built, the six ratings · bars, what set the level and any flag; after a leader edits the Weightage Matrix, the live score is on sheet 2. The full reasoning for one person is on sheet 1b · choose the Emp ID; every column for everyone is on sheet 2. Filter by business, department, family or level with the header arrows.
A3: IRIS · Job Architecture & Job Design · Final v1.12 · October 2026 · Internal — Confidential
A6: Emp ID | B6: Employee name | C6: Business | D6: Department | E6: Job family | F6: Sub-family | G6: Current designation | H6: Final designation | I6: Current level | J6: FINAL LEVEL | K6: Track | L6: Change | M6: Score | N6: Complexity | O6: Autonomy | P6: Accountability | Q6: Leadership | R6: Exp & Qual | S6: Bus. Impact | T6: What set the level | U6: Flags | V6: Confidence
A7: IRIS0391 | B7: Anuradha RK | C7: CARBON | D7: CARBON Business Head | E7: Executive Leadership | F7: Business & Functional Leadership | G7: Business Head | H7: Business Head | I7: Not mapped | J7: D2 | K7: People Manager | L7: Newly mapped | M7: 9.03 | N7: 9 | O7: 9 | P7: 9 | Q7: 9 | R7: 9.5 | S7: 9 | T7: Rule: R11 leadership decision | U7: Input needed | V7: Low
A8: IRIS2478 | B8: Dixit Jasani | C8: CARBON | D8: CRO - Carbon | E8: Executive Leadership | F8: Enterprise Leadership | G8: Chief Revenue Officer- Enterprise Division | H8: Chief Revenue Officer | I8: Not mapped | J8: E1 | K8: People Manager | L8: Newly mapped | M8: 11.05 | N8: 11 | O8: 11 | P8: 11 | Q8: 11 | R8: 12 | S8: 11 | T8: The score decided the level | U8: Input needed | V8: Low
A9: IRIS2359 | B9: Suman Adhikary | C9: CARBON | D9: Customer Experience | E9: Executive Leadership | F9: Business & Functional Leadership | G9: Senior Vice President - Customer Experience | H9: Senior Vice President – Customer Experience | I9: Not mapped | J9: D1 | K9: People Manager | L9: Newly mapped | M9: 10.1 | N9: 10 | O9: 10 | P9: 10 | Q9: 10 | R9: 12 | S9: 10 | T9: Rule: R11 leadership decision | U9: Input needed | V9: Low
A10: IRIS0055 | B10: Vijay Parulekar | C10: CARBON | D10: Digitizing | E10: Data Operations & Digitization | F10: Digitization Leadership | G10: Head Image Processing | H10: Associate Head – Digitization | I10: L7 | J10: C1 | K10: People Manager | L10: Down | M10: 7 | N10: 7 | O10: 7 | P10: 6.5 | Q10: 6 | R10: 11.5 | S10: 7 | T10: The score decided the level | U10: Down — protected | V10: High
A11: IRIS0470 | B11: Janardan Bale | C11: CARBON | D11: Digitizing | E11: Data Operations & Digitization | F11: Document Conversion, Formatting & Web Publishing | G11: Image Processing Specialist | H11: Digitization Manager | I11: L3 | J11: B2 | K11: People Manager | L11: Up | M11: 4.95 | N11: 3.5 | O11: 4.5 | P11: 5 | Q11: 5.5 | R11: 9 | S11: 5.5 | T11: The score decided the level | U11: Input needed | V11: Medium
A12: IRIS1005 | B12: Datta Hatagale | C12: CARBON | D12: Digitizing | E12: Customer Success & Support | F12: Customer Training & Enablement | G12: Image Processing Specialist | H12: Customer Enablement Specialist – POD Lead | I12: L3 | J12: B1 | K12: POD Lead | L12: Up | M12: 3.67 | N12: 3 | O12: 3 | P12: 3.5 | Q12: 3.5 | R12: 8 | S12: 4 | T12: The score decided the level | U12: — | V12: Low
A13: IRIS1204 | B13: Dinesh Sharma | C13: CARBON | D13: Digitizing | E13: Data Operations & Digitization | F13: Document Conversion, Formatting & Web Publishing | G13: Image Processing Specialist | H13: Team Lead – Digitization | I13: L3 | J13: B1 | K13: People Manager | L13: Up | M13: 4.01 | N13: 3 | O13: 3.5 | P13: 3.5 | Q13: 4 | R13: 9 | S13: 4 | T13: The score decided the level | U13: — | V13: Medium
A14: IRIS0117 | B14: Prajakta Mokal | C14: CARBON | D14: Digitizing | E14: Data Operations & Digitization | F14: Document Conversion, Formatting & Web Publishing | G14: Image Processing Specialist | H14: Digitization Specialist – POD Lead | I14: L3 | J14: B1 | K14: POD Lead | L14: Up | M14: 3.69 | N14: 3 | O14: 3 | P14: 3 | Q14: 3 | R14: 9.5 | S14: 3.5 | T14: The score decided the level | U14: — | V14: High
A15: IRIS0171 | B15: Ritesh Yeram | C15: CARBON | D15: Digitizing | E15: Data Operations & Digitization | F15: Document Conversion, Formatting & Web Publishing | G15: Image Processing Specialist | H15: Digitization Specialist – POD Lead | I15: L3 | J15: B1 | K15: POD Lead | L15: Up | M15: 3.74 | N15: 3 | O15: 2.5 | P15: 3.5 | Q15: 3.5 | R15: 9.5 | S15: 4 | T15: The score decided the level | U15: — | V15: Medium
A16: IRIS1210 | B16: Tejas Kat | C16: CARBON | D16: Digitizing | E16: Data Operations & Digitization | F16: Document Conversion, Formatting & Web Publishing | G16: Image Processing Specialist | H16: Digitization Specialist – POD Lead | I16: L3 | J16: B1 | K16: POD Lead | L16: Up | M16: 3.72 | N16: 3 | O16: 3 | P16: 3.5 | Q16: 3.5 | R16: 8.5 | S16: 4 | T16: The score decided the level | U16: — | V16: High
A17: IRISC238 | B17: Aishwarya Chaulkar | C17: CARBON | D17: Digitizing | E17: Data Operations & Digitization | F17: Document Conversion, Formatting & Web Publishing | G17: Consultant | H17: Senior Digitization Associate | I17: L3 | J17: A3 | K17: IC | L17: Up | M17: 2.53 | N17: 2.5 | O17: 2.5 | P17: 2 | Q17: 2 | R17: 3.5 | S17: 2.5 | T17: The score decided the level | U17: Close call · Input needed | V17: Medium
A18: IRISC286 | B18: Bhavesh Gusain | C18: CARBON | D18: Digitizing | E18: Data Operations & Digitization | F18: Document Conversion, Formatting & Web Publishing | G18: Consultant | H18: Senior Digitization Associate | I18: L3 | J18: A3 | K18: IC | L18: Up | M18: 2.13 | N18: 2 | O18: 2 | P18: 2 | Q18: 1 | R18: 3 | S18: 2.5 | T18: Rule: R7 Band A experience | U18: — | V18: Medium
... A75: IRIS2534 | B75: Vishal | C75: CARBON | D75: Marketing | E75: Marketing & Communications | F75: Marketing Operations & Automation | G75: Associate- MarkOps | H75: Marketing Operations Associate | I75: L1 | J75: A2 | K75: IC | L75: Up | M75: 1.95 | N75: 2 | O75: 2 | P75: 2 | Q75: 1 | R75: 1.5 | S75: 2 | T75: The score decided the level | U75: — | V75: High
A76: INTN0287 | B76: Anika Mariam | C76: CARBON | D76: Marketing | E76: Sales & Business Development | F76: Sales Development & Prospecting | G76: Intern | H76: Intern – Sales Development & Prospecting | I76: L1 | J76: A1 | K76: IC | L76: Same level | T76: Placed by rule | U76: — | V76: Medium
A77: INTN0285 | B77: Deblina Chatterjee | C77: CARBON | D77: Marketing | E77: Sales & Business Development | F77: Sales Development & Prospecting | G77: Intern | H77: Intern – Sales Development & Prospecting | I77: L1 | J77: A1 | K77: IC | L77: Same level | T77: Placed by rule | U77: — | V77: Medium
A78: INTN0286 | B78: Samriddhi Kundu | C78: CARBON | D78: Marketing | E78: Sales & Business Development | F78: Sales Development & Prospecting | G78: Intern | H78: Intern – Sales Development & Prospecting | I78: L1 | J78: A1 | K78: IC | L78: Same level | T78: Placed by rule | U78: — | V78: Medium
A79: IRIS0591 | B79: Vinod Katekar | C79: CARBON | D79: Quality Assurance | E79: Quality Assurance | F79: Test Management & QA Leadership | G79: QA-Lead | H79: QA Manager | I79: L5 | J79: B2 | K79: People Manager | L79: Down | M79: 4.84 | N79: 4 | O79: 4.5 | P79: 5 | Q79: 5 | R79: 8.5 | S79: 5 | T79: The score decided the level | U79: Input needed · Down — protected | V79: Medium
A80: IRIS1672 | B80: Brehmjit Gopalkrishnan | C80: CARBON | D80: Quality Assurance | E80: Quality Assurance | F80: Functional & Domain Testing | G80: Client Solutions Executive | H80: Senior QA Engineer | I80: L3 | J80: A3 | K80: IC | L80: Up | M80: 2.75 | N80: 2 | O80: 2 | P80: 2.5 | Q80: 1 | R80: 9 | S80: 2.5 | T80: The score decided the level | U80: — | V80: High
A81: IRIS2388 | B81: Hrishikesh Thombare | C81: CARBON | D81: Quality Assurance | E81: Quality Assurance | F81: Functional & Domain Testing | G81: QA Engineer | H81: Senior QA Engineer | I81: L3 | J81: A3 | K81: IC | L81: Up | M81: 2.15 | N81: 2 | O81: 2 | P81: 2 | Q81: 1 | R81: 3.5 | S81: 2 | T81: Rule: R7 Band A experience | U81: — | V81: Medium
A82: IRIS0625 | B82: Pooja Gawas | C82: CARBON | D82: Quality Assurance | E82: Quality Assurance | F82: Functional & Domain Testing | G82: QA Engineer | H82: Senior QA Engineer | I82: L3 | J82: A3 | K82: IC | L82: Up | M82: 2.78 | N82: 2 | O82: 2 | P82: 3 | Q82: 3 | R82: 8.5 | S82: 3.5 | T82: The score decided the level | U82: Input needed | V82: Medium
A83: IRIS2107 | B83: Pratikkumar Mistry | C83: CARBON | D83: Quality Assurance | E83: Quality Assurance | F83: Functional & Domain Testing | G83: QA Engineer | H83: Senior QA Engineer | I83: L3 | J83: A3 | K83: IC | L83: Up | M83: 2.25 | N83: 2 | O83: 2 | P83: 2 | Q83: 1 | R83: 4.5 | S83: 2 | T83: Rule: R7 Band A experience | U83: — | V83: Medium
A84: IRIS2405 | B84: Tasmiyah Patni | C84: CARBON | D84: Quality Assurance | E84: Quality Assurance | F84: Functional & Domain Testing | G84: QA Engineer | H84: Senior QA Engineer | I84: L3 | J84: A3 | K84: IC | L84: Up | M84: 2.15 | N84: 2 | O84: 2 | P84: 2 | Q84: 1 | R84: 3.5 | S84: 2 | T84: Rule: R7 Band A experience | U84: — | V84: Medium
A85: IRIS2014 | B85: Vishal Panchal | C85: CARBON | D85: Quality Assurance | E85: Quality Assurance | F85: Functional & Domain Testing | G85: QA Engineer | H85: Senior QA Engineer | I85: L3 | J85: A3 | K85: IC | L85: Up | M85: 2.9 | N85: 2.5 | O85: 2.5 | P85: 3.5 | Q85: 3.5 | R85: 5.5 | S85: 3.5 | T85: The score decided the level | U85: Input needed | V85: Low
A86: IRIS2112 | B86: Vitiksha Gamit | C86: CARBON | D86: Quality Assurance | E86: Quality Assurance | F86: Test Automation | G86: QA Automation Engineer | H86: Senior QA Automation Engineer | I86: L3 | J86: A3 | K86: IC | L86: Up | M86: 2.6 | N86: 2.5 | O86: 2.5 | P86: 2.5 | Q86: 1.5 | R86: 3.5 | S86: 2.5 | T86: The score decided the level | U86: — | V86: Medium
A87: IRIS2489 | B87: Sreyash Duragkar | C87: CARBON | D87: Sales | E87: Sales & Business Development | F87: Sales Leadership | G87: Director- Enterprise Sales | H87: Principal – Enterprise Sales | I87: Not mapped | J87: C1 | K87: IC | L87: Newly mapped | M87: 8.72 | N87: 9 | O87: 9 | P87: 9 | Q87: 9 | R87: 3.5 | S87: 9 | T87: Rule: R5 structural gate | U87: Input needed | V87: Low
A88: IRIS1783 | B88: Swapnil Trikane | C88: CARBON | D88: Sales | E88: Sales & Business Development | F88: Sales Leadership | G88: Senior Manager Sales | H88: Lead Account Executive | I88: Not mapped | J88: B3 | K88: IC | L88: Newly mapped | M88: 5.8 | N88: 5.5 | O88: 5.5 | P88: 5.5 | Q88: 4.5 | R88: 9 | S88: 5.5 | T88: The score decided the level | U88: — | V88: Medium
A89: IRIS1734 | B89: Rohit Bansal | C89: CARBON | D89: Sales | E89: Sales & Business Development | F89: Sales Leadership | G89: Senior Manager Sales | H89: Lead Account Executive | I89: Not mapped | J89: B2 | K89: IC | L89: Newly mapped | M89: 5.44 | N89: 5 | O89: 5 | P89: 5.5 | Q89: 4 | R89: 9 | S89: 5.5 | T89: The score decided the level | U89: — | V89: High
A90: IRIS2351 | B90: Aniket Das | C90: CARBON | D90: Sales | E90: Sales & Business Development | F90: Bids, RFP & Sales Operations | G90: Senior Analyst, Strategy and Operations | H90: Sales Operations Specialist – POD Lead | I90: Not mapped | J90: B1 | K90: POD Lead | L90: Newly mapped | M90: 3.55 | N90: 3.5 | O90: 3 | P90: 4 | Q90: 3 | R90: 4.5 | S90: 4 | T90: The score decided the level | U90: — | V90: High
A91: IRIS2308 | B91: Smriti Priya | C91: CARBON | D91: Sales | E91: Sales & Business Development | F91: Bids, RFP & Sales Operations | G91: Senior Analyst, Strategy and Operations | H91: Senior Sales Operations Analyst | I91: L4 | J91: A3 | K91: IC | L91: Same level | M91: 3.1 | N91: 3 | O91: 3 | P91: 3 | Q91: 1.5 | R91: 4 | S91: 3 | T91: The score decided the level | U91: — | V91: High
A92: IRISC345 | B92: Andrea Messiga | C92: CARBON | D92: Sales | E92: Sales & Business Development | F92: Enterprise Sales & Account Management | G92: Regional Manager- Business Development | H92: Senior Consultant – Enterprise Sales & Account Management | I92: Not mapped | J92: X3 | K92: Consultant | L92: Same level | T92: Placed by rule | U92: — | V92: —
A93: IRIS0018 | B93: K Ashok Kumar | C93: CARBON | D93: Services | E93: Consulting & Professional Services | F93: Professional Services Leadership | G93: Manager Financial Analyst | H93: Associate Head – Assisted Services | I93: L5 | J93: C1 | K93: People Manager | L93: Up | M93: 6.81 | N93: 5.5 | O93: 6.5 | P93: 7.5 | Q93: 7.5 | R93: 11 | S93: 8.5 | T93: The score decided the level | U93: Input needed | V93: Medium
A94: IRIS0786 | B94: Shashikant Mudaliar | C94: CARBON | D94: Services | E94: Consulting & Professional Services | F94: Professional Services Leadership | G94: Head - XBRL Assisted Services | H94: Associate Head – XBRL Assisted Services | I94: L7 | J94: C1 | K94: People Manager | L94: Down | M94: 7.14 | N94: 7 | O94: 7 | P94: 7 | Q94: 7 | R94: 9 | S94: 7.5 | T94: The score decided the level | U94: Down — protected | V94: High
A95: IRIS0511 | B95: Jinesh Kumar S | C95: CARBON | D95: Services | E95: Consulting & Professional Services | F95: XBRL Tagging, Conversion & Filing | G95: Lead - Assisted Services | H95: Manager – Assisted Services | I95: L5 | J95: B2 | K95: People Manager | L95: Down | M95: 5.04 | N95: 4 | O95: 4.5 | P95: 5 | Q95: 5 | R95: 9 | S95: 5.5 | T95: The score decided the level | U95: Down — protected | V95: Medium
A96: IRIS0393 | B96: Mayur Zope | C96: CARBON | D96: Services | E96: Consulting & Professional Services | F96: XBRL Tagging, Conversion & Filing | G96: Lead Financial Analyst | H96: Senior Manager – Assisted Services | I96: L5 | J96: B2 | K96: People Manager | L96: Same level | M96: 5.28 | N96: 4 | O96: 5 | P96: 5 | Q96: 5 | R96: 10.5 | S96: 5.5 | T96: The score decided the level | U96: Input needed | V96: High
A97: IRIS0977 | B97: Mohammed Dholkawala | C97: CARBON | D97: Services | E97: Consulting & Professional Services | F97: XBRL Tagging, Conversion & Filing | G97: Lead - Assisted Services | H97: Manager – Assisted Services | I97: L5 | J97: B2 | K97: People Manager | L97: Down | M97: 4.54 | N97: 4 | O97: 4.5 | P97: 4 | Q97: 4 | R97: 8 | S97: 4.5 | T97: The score decided the level | U97: Close call · Down — protected | V97: High
A98: IRIS0589 | B98: Mohammed Sameer Shamsudin | C98: CARBON | D98: Services | E98: Quality Assurance | F98: Functional & Domain Testing | G98: Lead - Assisted Services | H98: Senior QA Specialist – POD Lead | I98: L5 | J98: B2 | K98: POD Lead | L98: Down | M98: 4.57 | N98: 4 | O98: 4.5 | P98: 4 | Q98: 4 | R98: 8.5 | S98: 4.5 | T98: The score decided the level | U98: Down — protected | V98: Low
A99: IRIS0616 | B99: Priyanka Jadhav | C99: CARBON | D99: Services | E99: Consulting & Professional Services | F99: XBRL Tagging, Conversion & Filing | G99: Lead - Assisted Services | H99: Manager – Assisted Services | I99: L5 | J99: B2 | K99: People Manager | L99: Down | M99: 5.14 | N99: 4.5 | O99: 4.5 | P99: 5 | Q99: 5 | R99: 8.5 | S99: 5.5 | T99: The score decided the level | U99: Down — protected | V99: Medium
A100: IRIS2071 | B100: Priyanka Mehra | C100: CARBON | D100: Services | E100: Project & Program Management | F100: PMO & Delivery Excellence | G100: Project Manager Officer | H100: PMO Manager | I100: L5 | J100: B2 | K100: People Manager | L100: Same level | M100: 5 | N100: 4.5 | O100: 4.5 | P100: 4.5 | Q100: 4.5 | R100: 9 | S100: 5 | T100: The score decided the level | U100: — | V100: Medium
A101: IRIS0506 | B101: Shailesh Kumar Sharma | C101: CARBON | D101: Services | E101: Consulting & Professional Services | F101: Service Delivery Operations | G101: Process Manager | H101: Senior Manager – Service Delivery | I101: L5 | J101: B2 | K101: People Manager | L101: Up | M101: 5.2 | N101: 4 | O101: 5 | P101: 5.5 | Q101: 5 | R101: 8.5 | S101: 6 | T101: The score decided the level | U101: — | V101: Medium
A102: IRIS0567 | B102: Amruta Mirashi | C102: CARBON | D102: Services | E102: Consulting & Professional Services | F102: XBRL Tagging, Conversion & Filing | G102: Financial Analyst | H102: XBRL Specialist | I102: L3 | J102: B1 | K102: IC | L102: Up | M102: 3.58 | N102: 3 | O102: 3 | P102: 3 | Q102: 2 | R102: 9 | S102: 3.5 | T102: The score decided the level | U102: Input needed | V102: High
A103: IRIS2169 | B103: Chetan Newase | C103: CARBON | D103: Services | E103: Consulting & Professional Services | F103: XBRL Tagging, Conversion & Filing | G103: Senior Financial Analyst | H103: XBRL Specialist | I103: L4 | J103: B1 | K103: IC | L103: Up | M103: 3.81 | N103: 3.5 | O103: 3 | P103: 3 | Q103: 2 | R103: 9 | S103: 3.5 | T103: The score decided the level | U103: — | V103: High
A104: IRIS0558 | B104: Jayaprakash Arumugam | C104: CARBON | D104: Services | E104: Consulting & Professional Services | F104: XBRL Tagging, Conversion & Filing | G104: Senior Financial Analyst | H104: XBRL Specialist | I104: L4 | J104: B1 | K104: IC | L104: Up | M104: 4.23 | N104: 4 | O104: 3.5 | P104: 3 | Q104: 3 | R104: 9.5 | S104: 3.5 | T104: The score decided the level | U104: — | V104: Medium
... A173: IRISC184 | B173: Tanya Dhere | C173: CARBON | D173: Support | E173: Customer Success & Support | F173: Customer Success & Account Management | G173: Consultant | H173: Senior Customer Success Executive | I173: L3 | J173: A3 | K173: IC | L173: Up | M173: 2.92 | N173: 2.5 | O173: 2 | P173: 2.5 | Q173: 1 | R173: 7.5 | S173: 2.5 | T173: The score decided the level | U173: — | V173: Medium
A174: No Emp ID · in-house consultant | B174: Kanika Jain | C174: CARBON | D174: Support | E174: Customer Success & Support | F174: Customer Success & Account Management | G174: Consultant | H174: Associate Consultant – Customer Success & Account Management | I174: L3 | J174: X1 | K174: Consultant | L174: Same level | T174: Placed by rule | U174: — | V174: —
A175: IRIS0249 | B175: Ashish Singhvi | C175: CARBON | D175: Technology | E175: Engineering & Development | F175: Engineering Leadership | G175: Product Engineering Head | H175: Head – Product Engineering | I175: Not mapped | J175: C2 | K175: People Manager | L175: Newly mapped | M175: 8.07 | N175: 8 | O175: 8 | P175: 8 | Q175: 8 | R175: 9.5 | S175: 8 | T175: The score decided the level | U175: Input needed | V175: Low
A176: IRIS1832 | B176: Chetan Kotwal | C176: CARBON | D176: Technology | E176: Engineering & Development | F176: Backend Development | G176: Lead Software Engineer | H176: Senior Engineering Manager | I176: L5 | J176: B3 | K176: People Manager | L176: Same level | M176: 5.7 | N176: 5.5 | O176: 5.5 | P176: 5.5 | Q176: 5.5 | R176: 7.5 | S176: 5.5 | T176: The score decided the level | U176: — | V176: Medium
A177: IRIS1272 | B177: Aaron Michael | C177: CARBON | D177: Technology | E177: Project & Program Management | F177: Project & Program Delivery | G177: Project Manager | H177: Project Manager | I177: L5 | J177: B2 | K177: IC | L177: Same level | M177: 5.06 | N177: 4.5 | O177: 5 | P177: 5 | Q177: 4 | R177: 8.5 | S177: 5.5 | T177: The score decided the level | U177: Input needed | V177: Medium
A178: IRIS1477 | B178: Dhiraj Suryawanshi | C178: CARBON | D178: Technology | E178: Engineering & Development | F178: Full-Stack Development | G178: Lead Software Engineer | H178: Lead Software Engineer – POD Lead | I178: L5 | J178: B2 | K178: POD Lead | L178: Same level | M178: 5.5 | N178: 5.5 | O178: 5 | P178: 4.5 | Q178: 4.5 | R178: 8 | S178: 4.5 | T178: The score decided the level | U178: Close call | V178: Medium
A179: IRIS0622 | B179: Prasad Shirke | C179: CARBON | D179: Technology | E179: Business Analysis | F179: Business Analysis | G179: Senior Business Analyst | H179: Senior Business Analysis Specialist – POD Lead | I179: L4 | J179: B2 | K179: POD Lead | L179: Up | M179: 4.51 | N179: 3.5 | O179: 4.5 | P179: 5.5 | Q179: 5.5 | R179: 8.5 | S179: 5.5 | T179: The score decided the level | U179: Close call · Input needed | V179: Medium
A180: IRIS1986 | B180: Sarfaraz Badi | C180: CARBON | D180: Technology | E180: Engineering & Development | F180: Backend Development | G180: Lead Software Engineer | H180: Lead Software Engineer – POD Lead | I180: L5 | J180: B2 | K180: POD Lead | L180: Same level | M180: 5.5 | N180: 5.5 | O180: 5 | P180: 4.5 | Q180: 4.5 | R180: 8 | S180: 4.5 | T180: The score decided the level | U180: Close call | V180: Medium
A181: IRIS1535 | B181: Siddhesh Kadam | C181: CARBON | D181: Technology | E181: Engineering & Development | F181: Backend Development | G181: Senior Software Engineer | H181: Senior Technical Specialist – POD Lead | I181: L4 | J181: B2 | K181: POD Lead | L181: Up | M181: 4.76 | N181: 4 | O181: 5 | P181: 6 | Q181: 6 | R181: 6.5 | S181: 6 | T181: The score decided the level | U181: Input needed | V181: Low
A182: IRIS2153 | B182: Dhaval Lotwala | C182: CARBON | D182: Technology | E182: Business Analysis | F182: Business Analysis | G182: Senior Business Analyst | H182: Business Analysis Specialist | I182: L4 | J182: B1 | K182: IC | L182: Up | M182: 3.8 | N182: 3.5 | O182: 3.5 | P182: 3.5 | Q182: 2.5 | R182: 7 | S182: 3.5 | T182: The score decided the level | U182: — | V182: High
A183: IRIS1890 | B183: Hetal Chauhan | C183: CARBON | D183: Technology | E183: Engineering & Development | F183: Backend Development | G183: Software Engineer | H183: Technical Specialist – POD Lead | I183: L3 | J183: B1 | K183: POD Lead | L183: Up | M183: 3.46 | N183: 2.5 | O183: 3 | P183: 3.5 | Q183: 3.5 | R183: 9.5 | S183: 3.5 | T183: Rule: R9 POD Lead / manager minimum | U183: Input needed | V183: Medium
A184: IRIS2374 | B184: Huzefa Petit | C184: CARBON | D184: Technology | E184: Engineering & Development | F184: Backend Development | G184: Technical Support Lead | H184: Technical Specialist | I184: L5 | J184: B1 | K184: IC | L184: Down | M184: 4.03 | N184: 3.5 | O184: 3.5 | P184: 3.5 | Q184: 3 | R184: 9 | S184: 3.5 | T184: The score decided the level | U184: Input needed · Down — protected | V184: Medium
A185: IRIS2495 | B185: Manasvi Sharma | C185: CARBON | D185: Technology | E185: Engineering & Development | F185: AI / ML & GenAI Engineering | G185: Senior Software Engineer - AI/ML | H185: AI/ML Specialist – POD Lead | I185: L4 | J185: B1 | K185: POD Lead | L185: Up | M185: 3.52 | N185: 3.5 | O185: 3 | P185: 3 | Q185: 3 | R185: 5 | S185: 3.5 | T185: The score decided the level | U185: Close call | V185: Medium
A186: IRIS2021 | B186: Alpesh Chaudhari | C186: CARBON | D186: Technology | E186: Engineering & Development | F186: Backend Development | G186: Software Engineer | H186: Senior Software Engineer | I186: L3 | J186: A3 | K186: IC | L186: Up | M186: 3.15 | N186: 3 | O186: 3 | P186: 3.5 | Q186: 4 | R186: 4 | S186: 3.5 | T186: The score decided the level | U186: Input needed | V186: Low
... A219: IRIS2284 | B219: Saniya Baxi | C219: CARBON | D219: Technology | E219: Business Analysis | F219: Business Analysis | G219: Trainee Business Analyst | H219: Business Analyst | I219: L2 | J219: A2 | K219: IC | L219: Up | M219: 1.92 | N219: 2 | O219: 1.5 | P219: 1.5 | Q219: 1 | R219: 2.5 | S219: 1.5 | T219: Rule: R4 work-substance cap, R7 Band A experience | U219: Near a gate | V219: High
A220: IRIS2454 | B220: Ayush Sharma | C220: CARBON | D220: Technology | E220: Engineering & Development | F220: Backend Development | G220: Trainee Software Engineer | H220: Trainee Software Engineer | I220: L2 | J220: A1 | K220: IC | L220: Same level | T220: Placed by rule | U220: — | V220: Low
A221: IRIS2455 | B221: Soniya Paliwal | C221: CARBON | D221: Technology | E221: Engineering & Development | F221: Full-Stack Development | G221: Trainee Software Engineer | H221: Trainee Software Engineer | I221: L2 | J221: A1 | K221: IC | L221: Same level | T221: Placed by rule | U221: — | V221: Medium

Sheet 1b. Person Card
A1: Person card — one person's placement on one page | I1: ◂ Contents
A2: Sheet 1b · Find a person: paste or type an Emp ID, or pick Department → Name from the yellow drop-downs — type part of a word in the Search box beside a drop-down to shorten its list. Everything below fills in from sheet 2: the role before and after, the six ratings as bars with weights and points, the score and the level, the rules applied, the justification for each rating and the evidence.
A3: IRIS · Job Architecture & Job Design · Final v1.12 · October 2026 · Internal — Confidential
A5: Department | B5: CARBON Business Head | E5: Search ▸ | G5: Showing ▸ | H5: =IFERROR(INDEX('2. Talent Mapping'!$B$7:$B$221,$J$7),"") -> Anuradha RK | J5: CARBON
A6: Name | B6: Anuradha RK | E6: Search ▸ | H6: =IF($J$7="","No match — check the Emp ID" & IF(COUNTA(PC_Products)=1," · this file holds one product only","") & ", or clear it and pick a name",IF(LEFT($J$6,3)="No ",$J$6,"Emp ID "&$J$6)&IF($B$7<>""," · by Emp ID"," · by name")) -> Emp ID IRIS0391 · by name | J6: =IF(TRIM($B$7)<>"",TRIM($B$7),IFERROR(INDEX(PC_NKIds,MATCH($J$5&"|"&$B$5&"|"&$B$6,PC_NK,0)),"")) -> IRIS0391
A7: Emp ID — paste or type | J7: =IFERROR(INDEX(PC_NKRow,MATCH($J$6,PC_NKIds,0)),"") -> 1
A8: Paste or type an Emp ID — any person, any product, upper or lower case — or leave it blank and pick Department → Name. To shorten a drop-down, type part of a word in its Search box first. A typed Emp ID wins — clear it to pick by name.
A10: WHO
A11: Business | C11: CARBON | E11: Department | G11: =IFERROR(INDEX('2. Talent Mapping'!$C$7:$C$221,$J$7),"") -> CARBON Business Head
A12: Reporting manager | C12: =IFERROR(INDEX('2. Talent Mapping'!$D$7:$D$221,$J$7),"") -> Dixit Jasani | E12: Qualification | G12: =IFERROR(INDEX('2. Talent Mapping'!$G$7:$G$221,$J$7),"") -> MBA
A13: Total experience · yrs | C13: =IFERROR(INDEX('2. Talent Mapping'!$E$7:$E$221,$J$7),"") -> 17.1 | E13: Experience at IRIS · yrs | G13: =IFERROR(INDEX('2. Talent Mapping'!$F$7:$F$221,$J$7),"") -> 16.4
A15: ROLE — BEFORE → AFTER
A16: Current designation | C16: =IFERROR(INDEX('2. Talent Mapping'!$H$7:$H$221,$J$7),"") -> Business Head | E16: Final designation | G16: =IFERROR(INDEX('2. Talent Mapping'!$I$7:$I$221,$J$7),"") -> Business Head
A17: Current level | C17: =IFERROR(INDEX('2. Talent Mapping'!$L$7:$L$221,$J$7),"") -> Not in current mapping files | E17: FINAL LEVEL | G17: =IFERROR(INDEX('2. Talent Mapping'!$M$7:$M$221,$J$7),"") -> D2
A18: Level title | C18: =IFERROR(INDEX('2. Talent Mapping'!$N$7:$N$221,$J$7),"") -> Vice President | E18: Band | G18: =IFERROR(INDEX('2. Talent Mapping'!$O$7:$O$221,$J$7),"") -> D
A19: Job family | C19: =IFERROR(INDEX('2. Talent Mapping'!$J$7:$J$221,$J$7),"") -> Executive Leadership | E19: Sub-family | G19: =IFERROR(INDEX('2. Talent Mapping'!$K$7:$K$221,$J$7),"") -> Business & Functional Leadership
A20: Track | C20: =IFERROR(INDEX('2. Talent Mapping'!$P$7:$P$221,$J$7),"") -> People Manager | E20: Change vs current | G20: =IFERROR(INDEX('2. Talent Mapping'!$Q$7:$Q$221,$J$7),"") -> ● Newly mapped
A22: WHAT THEY DO — role, responsibilities & competencies required | B22: =IFERROR(IF(INDEX('2. Talent Mapping'!$R$7:$R$221,$J$7)="","—",INDEX('2. Talent Mapping'!$R$7:$R$221,$J$7)),"") -> WHAT THE ROLE DOES: Owns a business line or enterprise function end to end. At D2: several business lines or an executive-scope enterprise function. KEY RESPONSIBILITIES: Owns a business line or enterprise function end to end; Portfolio-level strategic, financial and regulatory trade-offs; Multi-business results DELIVERS: Multi-business results DECIDES ALONE: Sets direction across business lines SKILLS & KNOWLEDGE · role-holders: Product Management COMPETENCIES REQUIRED — must-have ★: Strategic Thinking & Business Acumen · People Leadership & Mentoring OTHER FUNCTIONAL COMPETENCIES: Stakeholder & Client Management · Product, Platform & Domain Knowledge · Regulatory & BFSI Domain · Communication & Presentation PROFICIENCY NEEDED AT THIS LEVEL: Core 5 · Future-ready 4 · Functional 4 · Leadership 5 CREDENTIALS: MBA / PGDM · preferred at C+ SOURCE: Framework only · fewer than 3 answered — 3 holders, 0 answered the survey; sub-family 0 answered; catalogue RC-091
A23: BUSINESS IMPACT — from survey and data | B23: =IFERROR(IF(INDEX('2. Talent Mapping'!$S$7:$S$221,$J$7)="","—",INDEX('2. Talent Mapping'!$S$7:$S$221,$J$7)),"") -> What the role answers for: Multi-business results. Accountability & Impact rating: 9 of 12 · D1-level impact. Leads 9 direct reports. Manager talent mapping — Latest rating: Not rated · manager · 9-Box Grid placement: Not placed · manager.
A24: BUSINESS IMPACT — from manager / head | B24: =IFERROR(IF(INDEX('2. Talent Mapping'!$T$7:$T$221,$J$7)="","—",INDEX('2. Talent Mapping'!$T$7:$T$221,$J$7)),"") -> —
A25: RECRUITMENT — FIND A REPLACEMENT FOR THIS ROLE
A26: What they do · simple | B26: =IFERROR(IF(INDEX('2. Talent Mapping'!$U$7:$U$221,$J$7)="","—",INDEX('2. Talent Mapping'!$U$7:$U$221,$J$7)),"") -> Business Head in CARBON Business Head · CARBON, D2 — People Manager. The work: Owns a business line or enterprise function end to end. At this level the role owns several business lines or an executive-scope enterprise function. Key responsibilities: Owns a business line or enterprise function end to end; Portfolio-level strategic, financial and regulatory trade-offs; Multi-business results. Leads 9 direct reports.
A27: Hire equivalent · external market | B27: =IFERROR(IF(INDEX('2. Talent Mapping'!$V$7:$V$221,$J$7)="","—",INDEX('2. Talent Mapping'!$V$7:$V$221,$J$7)),"") -> Hire as: Associate Vice President / Business Head — IRIS D2 Vice President · People Manager Market level: E3–E4 · SFIA 7 Set strategy Experience: 18–24 yrs · Education: Postgraduate / professional qualification Team size at this level: 5–8 AVPs / heads Equivalent titles at peers: IRIS Vs Market Benchmark — Aon Radford / Mercer executive codes – E3–E4 SVP · IRIS Vs Competitor Benchmark — regtech / SaaS executive titles – SVP Credentials: MBA / PGDM · preferred at C+ Must already know: Governance, risk and regulatory accountability
A28: Competencies & skill level to hire for | B28: =IFERROR(IF(INDEX('2. Talent Mapping'!$W$7:$W$221,$J$7)="","—",INDEX('2. Talent Mapping'!$W$7:$W$221,$J$7)),"") -> FUNCTIONAL — skill level 4 of 5 · Advanced ★ Strategic Thinking & Business Acumen: Shapes strategy, pricing or investment choices ★ People Leadership & Mentoring: Leads leaders; builds succession • Stakeholder & Client Management: Owns key relationships; resolves escalations • Product, Platform & Domain Knowledge: Recognised product / domain expert; trains others • Regulatory & BFSI Domain: Interprets new regulation; advises clients and product • Communication & Presentation: Presents to senior stakeholders; shapes messaging CORE — skill level 5 of 5 · Expert • Ownership & Accountability: Owns business outcomes; builds a culture of accountability • Problem Solving & Critical Thinking: Frames enterprise-level problems; sets the approach for others • Communication & Collaboration: Represents IRIS externally; builds cross-business partnerships • Client & Quality Focus: Defines client and quality strategy for a business • Learning Agility & Adaptability: Anticipates change; builds a learning organisation • Integrity, Compliance & Information Security: Sets ethical and compliance standards for the business FUTURE-READY — skill level 4 of 5 · Advanced • AI Literacy & Augmentation: Designs AI-enabled processes for a team; sets safe-use practices • Data Literacy & Analytics: Defines metrics and dashboards for a team • Digital Fluency & Automation: Automates team processes; selects tools • Innovation & Continuous Improvement: Leads improvement initiatives for a team LEADERSHIP — skill level 5 of 5 · Expert • Leading & Developing People: Builds the leadership pipeline and culture • Decision Making & Delegation: Makes enterprise / business-line decisions • Strategic & Business Acumen: Sets business strategy and P&L direction • Influence & Change Leadership: Leads enterprise change; influences clients, regulators and partners SKILLS · from role-holders and HRIS: Product Management ★ = must-have for the family. Scale: 1 Awareness · 2 Working · 3 Practitioner · 4 Advanced · 5 Expert.
A29: Interview questions for the perfect fit | B29: =IFERROR(IF(INDEX('2. Talent Mapping'!$X$7:$X$221,$J$7)="","—",INDEX('2. Talent Mapping'!$X$7:$X$221,$J$7)),"") -> Draft — generated from the framework; hiring-manager review pending · HR Super Master, sheet T5. 1. [Strategic Thinking & Business Acumen · level 4] Tell me about recent work that shows this: "Shapes strategy, pricing or investment choices". What exactly did you do, how, and what was the result? Assess with: Case interview. 2. [People Leadership & Mentoring · level 4] Tell me about recent work that shows this: "Leads leaders; builds succession". What exactly did you do, how, and what was the result? Assess with: Behavioural interview. 3. [Stakeholder & Client Management · level 4] Give an example that shows you can do this: "Owns key relationships; resolves escalations". Assess with: Role play / behavioural interview. 4. [Product, Platform & Domain Knowledge · level 4] Give an example that shows you can do this: "Recognised product / domain expert; trains others". Assess with: Scenario interview. 5. [Regulatory & BFSI Domain · level 4] Give an example that shows you can do this: "Interprets new regulation; advises clients and product". Assess with: Domain interview. 6. [Ownership & Accountability · level 5] Describe a time you held a team to a standard on an outcome that mattered to the business. How did you make ownership stick? Listen for: "Owns business outcomes; builds a culture of accountability". 7. [Problem Solving & Critical Thinking · level 5] Tell me about an ambiguous, high-stakes problem with no clear answer. How did you frame it and decide? Listen for: "Frames enterprise-level problems; sets the approach for others". 8. [Client & Quality Focus · level 5] Describe how you raised quality or client outcomes across a team or service. How did you measure it? Listen for: "Defines client and quality strategy for a business". 9. [AI Literacy & Augmentation · level 4] Where have you introduced AI or automation into a team's work, and how did you manage the risks? Listen for: "Designs AI-enabled processes for a team; sets safe-use practices". 10. [Leading & Developing People · level 5] Tell me about building a team: who you hired, how you developed them, and a difficult people decision you made. Listen for: "Builds the leadership pipeline and culture". 11. [Decision Making & Delegation · level 5] Tell me about a decision you delegated and one you kept. Why, and what happened? Listen for: "Makes enterprise / business-line decisions". 12. [Strategic & Business Acumen · level 5] Tell me about a strategy or plan you shaped. What trade-offs did you make, and what was the business result? Listen for: "Sets business strategy and P&L direction". 13. [Influence & Change Leadership · level 5] Describe a change you led across teams or the business. How did you deal with resistance? Listen for: "Leads enterprise change; influences clients, regulators and partners". Fit check: Why this role, why IRIS · regulatory reporting / XBRL / regtech, and what would you change in your first 90 days?
A30: HOW THE LEVEL IS WORKED OUT
A31: Factor | B31: Rating | C31: Bar | E31: Weight | F31: Points
A32: Complexity & Expertise | B32: =IFERROR(INDEX('2. Talent Mapping'!$Z$7:$Z$221,$J$7),"") -> 9 | C32: =IF(B32="","",REPT("█",ROUND(B32,0))&REPT("░",12-ROUND(B32,0))) -> █████████░░░ | E32: =IFERROR(INDEX('2. Talent Mapping'!$AA$7:$AA$221,$J$7),"") -> 0.37 | F32: =IF(OR(B32="",E32=""),"",B32*E32) -> 3.33
A33: Autonomy & Decision | B33: =IFERROR(INDEX('2. Talent Mapping'!$AC$7:$AC$221,$J$7),"") -> 9 | C33: =IF(B33="","",REPT("█",ROUND(B33,0))&REPT("░",12-ROUND(B33,0))) -> █████████░░░ | E33: =IFERROR(INDEX('2. Talent Mapping'!$AD$7:$AD$221,$J$7),"") -> 0.19 | F33: =IF(OR(B33="",E33=""),"",B33*E33) -> 1.71
A34: Accountability & Impact | B34: =IFERROR(INDEX('2. Talent Mapping'!$AF$7:$AF$221,$J$7),"") -> 9 | C34: =IF(B34="","",REPT("█",ROUND(B34,0))&REPT("░",12-ROUND(B34,0))) -> █████████░░░ | E34: =IFERROR(INDEX('2. Talent Mapping'!$AG$7:$AG$221,$J$7),"") -> 0.11 | F34: =IF(OR(B34="",E34=""),"",B34*E34) -> 0.99
A35: Leadership & Strategy | B35: =IFERROR(INDEX('2. Talent Mapping'!$AI$7:$AI$221,$J$7),"") -> 9 | C35: =IF(B35="","",REPT("█",ROUND(B35,0))&REPT("░",12-ROUND(B35,0))) -> █████████░░░ | E35: =IFERROR(INDEX('2. Talent Mapping'!$AJ$7:$AJ$221,$J$7),"") -> 0.2 | F35: =IF(OR(B35="",E35=""),"",B35*E35) -> 1.8
A36: Experience & Qualification | B36: =IFERROR(INDEX('2. Talent Mapping'!$AL$7:$AL$221,$J$7),"") -> 9.5 | C36: =IF(B36="","",REPT("█",ROUND(B36,0))&REPT("░",12-ROUND(B36,0))) -> ██████████░░ | E36: =IFERROR(INDEX('2. Talent Mapping'!$AM$7:$AM$221,$J$7),"") -> 0.05 | F36: =IF(OR(B36="",E36=""),"",B36*E36) -> 0.475
A37: Business Impact | B37: =IFERROR(INDEX('2. Talent Mapping'!$AO$7:$AO$221,$J$7),"") -> 9 | C37: =IF(B37="","",REPT("█",ROUND(B37,0))&REPT("░",12-ROUND(B37,0))) -> █████████░░░ | E37: =IFERROR(INDEX('2. Talent Mapping'!$AP$7:$AP$221,$J$7),"") -> 0.08 | F37: =IF(OR(B37="",E37=""),"",B37*E37) -> 0.72
A38: Weighted score | F38: =IF(COUNT(F32:F37)=6,SUM(F32:F37),"Placed by rule") -> 9.025
A39: Level the score indicates | F39: =IFERROR(INDEX('2. Talent Mapping'!$AS$7:$AS$221,$J$7),"") -> D1
A40: FINAL LEVEL | F40: =IFERROR(INDEX('2. Talent Mapping'!$M$7:$M$221,$J$7),"") -> D2
A42: Why these weights | B42: =IFERROR(IF(INDEX('2. Talent Mapping'!$AT$7:$AT$221,$J$7)="","—",INDEX('2. Talent Mapping'!$AT$7:$AT$221,$J$7)),"") -> Weights: Complexity 37% · Leadership 20% · Autonomy 19% · Accountability 11% · Business impact 8% · Experience 5% Why: leaders are judged on the hardest problems, on leading — 20% — and on the decisions, scope and business impact of the job. Type of work in the department: no adjustment at this level. Live: change the department's row on the Weightage Matrix and these weights, the points and the score update.
A43: Calculation | B43: =IFERROR(IF(INDEX('2. Talent Mapping'!$AU$7:$AU$221,$J$7)="","—",INDEX('2. Talent Mapping'!$AU$7:$AU$221,$J$7)),"") -> At build: Complexity 3.33 + Autonomy 1.71 + Accountability 0.99 + Leadership 1.80 + Experience 0.48 + Business impact 0.72 = 9.03 points → nearest level 9 = D1 Final level: D2 · a rule applied: see the next column
A44: Rules applied — with the numbers | B44: =IFERROR(IF(INDEX('2. Talent Mapping'!$AV$7:$AV$221,$J$7)="","—",INDEX('2. Talent Mapping'!$AV$7:$AV$221,$J$7)),"") -> • Set at D2 by leadership decision · the model indicated D1: Leadership structure: CARBON Business Head at D2. Final level: D2.
A45: JUSTIFICATION FOR EACH RATING
A46: Complexity & Expertise | B46: =IFERROR(IF(INDEX('2. Talent Mapping'!$AW$7:$AW$221,$J$7)="","—",INDEX('2. Talent Mapping'!$AW$7:$AW$221,$J$7)),"") -> Rated 9 of 12 Start: 9.0 · business head / director title Evidence: no survey answers or KRAs on file → rating stays at the start Market: D1 = Competing strategic, financial and regulatory priorities
A47: Autonomy & Decision | B47: =IFERROR(IF(INDEX('2. Talent Mapping'!$AX$7:$AX$221,$J$7)="","—",INDEX('2. Talent Mapping'!$AX$7:$AX$221,$J$7)),"") -> Rated 9 of 12 Start: 9.0 · business head / director title Evidence: no survey answers or KRAs on file → rating stays at the start Market: D1 = Sets business-line direction, pricing and investment
A48: Accountability & Impact | B48: =IFERROR(IF(INDEX('2. Talent Mapping'!$AY$7:$AY$221,$J$7)="","—",INDEX('2. Talent Mapping'!$AY$7:$AY$221,$J$7)),"") -> Rated 9 of 12 Start: 9.0 · business head / director title; 9 direct reports, 166 people in the organisation Evidence: no survey answers or KRAs on file → rating stays at the start Market: D1 = Business-line P&L and market position
A49: Leadership & Strategy | B49: =IFERROR(IF(INDEX('2. Talent Mapping'!$AZ$7:$AZ$221,$J$7)="","—",INDEX('2. Talent Mapping'!$AZ$7:$AZ$221,$J$7)),"") -> Rated 9 of 12 Start: 9.0 Evidence: no survey answers or KRAs on file → rating stays at the start Team: 9 direct reports · People Manager Market: D1 = Defines business strategy; builds the leadership bench
A50: Experience & Qualification | B50: =IFERROR(IF(INDEX('2. Talent Mapping'!$BA$7:$BA$221,$J$7)="","—",INDEX('2. Talent Mapping'!$BA$7:$BA$221,$J$7)),"") -> Rated 9.5 of 12 · between D1 and D2 Experience: 17.1 yrs total · 0.7 before IRIS + 16.4 at IRIS = 8.9 on the experience scale Qualification: MBA · postgraduate, relevant to the work → +0.5
A51: Business Impact | B51: =IFERROR(IF(INDEX('2. Talent Mapping'!$BB$7:$BB$221,$J$7)="","—",INDEX('2. Talent Mapping'!$BB$7:$BB$221,$J$7)),"") -> Rated 9 of 12 — a starting estimate. Start: 9, the role's accountability scope — what it answers for. No survey or manager-mapping signal on criticality: kept at the start point. Managers and heads: overwrite this rating on the Weightage sheet with the business impact you see — the score updates at once. Ladder: D1 = Owns a business line's P&L and growth, or a company-wide function
A52: EVIDENCE, MARKET AND POINTS TO CONFIRM
A53: Data used | B53: =IFERROR(IF(INDEX('2. Talent Mapping'!$BD$7:$BD$221,$J$7)="","—",INDEX('2. Talent Mapping'!$BD$7:$BD$221,$J$7)),"") -> ✓ HRIS: 17.1 yrs, MBA, 9 direct reports ✗ Survey: no response ✗ KRAs: none on file ✓ Manager mapping: rating, 9-box ✗ Job description: not on file ✓ Validated inputs: Approved level: D1 → D2 · Leadership structure: CARBON Business Head at D2 · Leadership decision · HR review of 9 Oct 2026 · 2026-10-09
A54: Market standard | B54: =IFERROR(IF(INDEX('2. Talent Mapping'!$BE$7:$BE$221,$J$7)="","—",INDEX('2. Talent Mapping'!$BE$7:$BE$221,$J$7)),"") -> Market level: E3–E4 · SFIA 7 Set strategy Typical title: Associate Vice President / Business Head At peers: IRIS Vs Market Benchmark — Aon Radford / Mercer executive codes: E3–E4 SVP · IRIS Vs Competitor Benchmark — regtech / SaaS executive titles: SVP Standard: Aon Radford executive levels E1–E6; Mercer ET1–ET3
A55: Confidence | B55: =IFERROR(IF(INDEX('2. Talent Mapping'!$BF$7:$BF$221,$J$7)="","—",INDEX('2. Talent Mapping'!$BF$7:$BF$221,$J$7)),"") -> Low
A56: Points to confirm | B56: =IFERROR(IF(INDEX('2. Talent Mapping'!$BG$7:$BG$221,$J$7)="","—",INDEX('2. Talent Mapping'!$BG$7:$BG$221,$J$7)),"") -> • CARBON Leadership Scorecard row 6 describes sales/implementation ownership for Anuradha, while the master says Business Head. Confirm full-business versus commercial-capability mandate and identity of the abbreviated reference • No survey answers or KRA — the role factors rest on designation and reporting lines only
A57: Inputs still needed | B57: =IFERROR(IF(INDEX('2. Talent Mapping'!$BC$7:$BC$221,$J$7)="","—",INDEX('2. Talent Mapping'!$BC$7:$BC$221,$J$7)),"") -> • Survey response or KRAs describing the work · nothing on file — Employee + manager • Resolve conflicting role records — Business head

Sheet 1d. Weightage Matrix
A1: Weightage Matrix — how much each factor counts, by department and role group · editable | U1: ◂ Contents
A2: 1d · Leaders: change the yellow weights. Sheet 2 recalculates points, score and 'Level the score indicates' at once. Below the matrix: what each factor means, what a weight means, and what each rating means.
A3: IRIS · Job Architecture & Job Design · Final v1.12 · October 2026 · Internal — Confidential
A5: SETTINGS — Experience & Qualification weight · kept low by design; change it here for everyone
A6: Experience & Qualification weight — Bands A–B | B6: 10 | C6: Band A, Band B and B+ · Corporate functions rows add 5 for professional qualifications
A7: Experience & Qualification weight — Bands C–E | B7: 5 | C7: Band C, C+ and Bands D–E · Corporate functions rows add 5 for professional qualifications
A8: Why it is low: Sources: S05, S49 Hay know-how includes experience however acquired · S04, S52 Mercer IPE knowledge · S07 WTW GGS · S58 McKinsey · S59 Deloitte · S60 WEF · S61 EY India, 2026 — skills over tenure. The 10% / 5% level is an IRIS leadership decision.
A10: HOW TO USE IT — in four steps
A11: 1. Find your department and role group in the matrix below · filter the Department column.
A12: 2. Change the yellow weights in steps of 5%. Each row should add up to about 100% — the 'Used' columns show the weights actually applied.
A13: 3. Look at sheet 2: points, the score and 'Level the score indicates' have already changed for everyone in that department and role group.
A14: 4. Write why you changed a row in the last column and send the file back; HR imports it and the final levels follow on the next run.
A15: THE MATRIX — one row per department × role group in this file
A16: Weight row | B16: Business | C16: Department | D16: Role group | E16: People | F16: Main type of work | G16: How hard % | H16: Decides alone % | I16: Answers for % | J16: Leads % | K16: Experience % | L16: Business impact % | M16: Entered total | N16: Used · How hard | O16: Used · Decides alone | P16: Used · Answers for | Q16: Used · Leads | R16: Used · Experience | S16: Used · Business impact | T16: Why changed · leader | U16: Default · How hard | V16: Default · Decides alone | W16: Default · Answers for | X16: Default · Leads | Y16: Default · Experience | Z16: Default · Business impact
A17: CARBON · CARBON Business Head · Bands D–E · Leadership | B17: CARBON | C17: CARBON Business Head | D17: Bands D–E · Leadership | E17: 1 | F17: General management | G17: 37 | H17: 19 | I17: 11 | J17: 20 | K17: =WM_EXP_CE -> 5 | L17: 8 | M17: =SUM(G17:L17) -> 100 | N17: =IF((G17+H17+I17+J17+L17)=0,0,G17*(100-MAX(0,MIN(100,K17)))/(G17+H17+I17+J17+L17))/100 -> 0.37 | O17: =IF((G17+H17+I17+J17+L17)=0,0,H17*(100-MAX(0,MIN(100,K17)))/(G17+H17+I17+J17+L17))/100 -> 0.19 | P17: =IF((G17+H17+I17+J17+L17)=0,0,I17*(100-MAX(0,MIN(100,K17)))/(G17+H17+I17+J17+L17))/100 -> 0.11 | Q17: =IF((G17+H17+I17+J17+L17)=0,0,J17*(100-MAX(0,MIN(100,K17)))/(G17+H17+I17+J17+L17))/100 -> 0.2 | R17: =MAX(0,MIN(100,K17))/100 -> 0.05 | S17: =IF((G17+H17+I17+J17+L17)=0,0,L17*(100-MAX(0,MIN(100,K17)))/(G17+H17+I17+J17+L17))/100 -> 0.08 | U17: 37 | V17: 19 | W17: 11 | X17: 20 | Y17: 5 | Z17: 8
A18: CARBON · CRO - Carbon · Bands D–E · Leadership | B18: CARBON | C18: CRO - Carbon | D18: Bands D–E · Leadership | E18: 1 | F18: Sales & marketing | G18: 37 | H18: 19 | I18: 11 | J18: 20 | K18: =WM_EXP_CE -> 5 | L18: 8 | M18: =SUM(G18:L18) -> 100 | N18: =IF((G18+H18+I18+J18+L18)=0,0,G18*(100-MAX(0,MIN(100,K18)))/(G18+H18+I18+J18+L18))/100 -> 0.37 | O18: =IF((G18+H18+I18+J18+L18)=0,0,H18*(100-MAX(0,MIN(100,K18)))/(G18+H18+I18+J18+L18))/100 -> 0.19 | P18: =IF((G18+H18+I18+J18+L18)=0,0,I18*(100-MAX(0,MIN(100,K18)))/(G18+H18+I18+J18+L18))/100 -> 0.11 | Q18: =IF((G18+H18+I18+J18+L18)=0,0,J18*(100-MAX(0,MIN(100,K18)))/(G18+H18+I18+J18+L18))/100 -> 0.2 | R18: =MAX(0,MIN(100,K18))/100 -> 0.05 | S18: =IF((G18+H18+I18+J18+L18)=0,0,L18*(100-MAX(0,MIN(100,K18)))/(G18+H18+I18+J18+L18))/100 -> 0.08 | U18: 37 | V18: 19 | W18: 11 | X18: 20 | Y18: 5 | Z18: 8
A19: CARBON · Customer Experience · Bands D–E · Leadership | B19: CARBON | C19: Customer Experience | D19: Bands D–E · Leadership | E19: 1 | F19: Customer support & success | G19: 37 | H19: 19 | I19: 11 | J19: 20 | K19: =WM_EXP_CE -> 5 | L19: 8 | M19: =SUM(G19:L19) -> 100 | N19: =IF((G19+H19+I19+J19+L19)=0,0,G19*(100-MAX(0,MIN(100,K19)))/(G19+H19+I19+J19+L19))/100 -> 0.37 | O19: =IF((G19+H19+I19+J19+L19)=0,0,H19*(100-MAX(0,MIN(100,K19)))/(G19+H19+I19+J19+L19))/100 -> 0.19 | P19: =IF((G19+H19+I19+J19+L19)=0,0,I19*(100-MAX(0,MIN(100,K19)))/(G19+H19+I19+J19+L19))/100 -> 0.11 | Q19: =IF((G19+H19+I19+J19+L19)=0,0,J19*(100-MAX(0,MIN(100,K19)))/(G19+H19+I19+J19+L19))/100 -> 0.2 | R19: =MAX(0,MIN(100,K19))/100 -> 0.05 | S19: =IF((G19+H19+I19+J19+L19)=0,0,L19*(100-MAX(0,MIN(100,K19)))/(G19+H19+I19+J19+L19))/100 -> 0.08 | U19: 37 | V19: 19 | W19: 11 | X19: 20 | Y19: 5 | Z19: 8
A20: CARBON · Digitizing · Band A · Early career | B20: CARBON | C20: Digitizing | D20: Band A · Early career | E20: 17 | F20: Service delivery & data operations | G20: 54 | H20: 16 | I20: 14 | J20: 0 | K20: =WM_EXP_AB -> 10 | L20: 6 | M20: =SUM(G20:L20) -> 100 | N20: =IF((G20+H20+I20+J20+L20)=0,0,G20*(100-MAX(0,MIN(100,K20)))/(G20+H20+I20+J20+L20))/100 -> 0.54 | O20: =IF((G20+H20+I20+J20+L20)=0,0,H20*(100-MAX(0,MIN(100,K20)))/(G20+H20+I20+J20+L20))/100 -> 0.16 | P20: =IF((G20+H20+I20+J20+L20)=0,0,I20*(100-MAX(0,MIN(100,K20)))/(G20+H20+I20+J20+L20))/100 -> 0.14 | Q20: =IF((G20+H20+I20+J20+L20)=0,0,J20*(100-MAX(0,MIN(100,K20)))/(G20+H20+I20+J20+L20))/100 -> 0 | R20: =MAX(0,MIN(100,K20))/100 -> 0.1 | S20: =IF((G20+H20+I20+J20+L20)=0,0,L20*(100-MAX(0,MIN(100,K20)))/(G20+H20+I20+J20+L20))/100 -> 0.06 | U20: 54 | V20: 16 | W20: 14 | X20: 0 | Y20: 10 | Z20: 6
A21: CARBON · Digitizing · Band B · Expert / POD Lead | B21: CARBON | C21: Digitizing | D21: Band B · Expert / POD Lead | E21: 4 | F21: Service delivery & data operations | G21: 46 | H21: 17 | I21: 15 | J21: 5 | K21: =WM_EXP_AB -> 10 | L21: 7 | M21: =SUM(G21:L21) -> 100 | N21: =IF((G21+H21+I21+J21+L21)=0,0,G21*(100-MAX(0,MIN(100,K21)))/(G21+H21+I21+J21+L21))/100 -> 0.46 | O21: =IF((G21+H21+I21+J21+L21)=0,0,H21*(100-MAX(0,MIN(100,K21)))/(G21+H21+I21+J21+L21))/100 -> 0.17 | P21: =IF((G21+H21+I21+J21+L21)=0,0,I21*(100-MAX(0,MIN(100,K21)))/(G21+H21+I21+J21+L21))/100 -> 0.15 | Q21: =IF((G21+H21+I21+J21+L21)=0,0,J21*(100-MAX(0,MIN(100,K21)))/(G21+H21+I21+J21+L21))/100 -> 0.05 | R21: =MAX(0,MIN(100,K21))/100 -> 0.1 | S21: =IF((G21+H21+I21+J21+L21)=0,0,L21*(100-MAX(0,MIN(100,K21)))/(G21+H21+I21+J21+L21))/100 -> 0.07 | U21: 46 | V21: 17 | W21: 15 | X21: 5 | Y21: 10 | Z21: 7
A22: CARBON · Digitizing · Band B · People Manager | B22: CARBON | C22: Digitizing | D22: Band B · People Manager | E22: 2 | F22: Service delivery & data operations | G22: 32 | H22: 18 | I22: 16 | J22: 15 | K22: =WM_EXP_AB -> 10 | L22: 9 | M22: =SUM(G22:L22) -> 100 | N22: =IF((G22+H22+I22+J22+L22)=0,0,G22*(100-MAX(0,MIN(100,K22)))/(G22+H22+I22+J22+L22))/100 -> 0.32 | O22: =IF((G22+H22+I22+J22+L22)=0,0,H22*(100-MAX(0,MIN(100,K22)))/(G22+H22+I22+J22+L22))/100 -> 0.18 | P22: =IF((G22+H22+I22+J22+L22)=0,0,I22*(100-MAX(0,MIN(100,K22)))/(G22+H22+I22+J22+L22))/100 -> 0.16 | Q22: =IF((G22+H22+I22+J22+L22)=0,0,J22*(100-MAX(0,MIN(100,K22)))/(G22+H22+I22+J22+L22))/100 -> 0.15 | R22: =MAX(0,MIN(100,K22))/100 -> 0.1 | S22: =IF((G22+H22+I22+J22+L22)=0,0,L22*(100-MAX(0,MIN(100,K22)))/(G22+H22+I22+J22+L22))/100 -> 0.09 | U22: 32 | V22: 18 | W22: 16 | X22: 15 | Y22: 10 | Z22: 9
A23: CARBON · Digitizing · Band C · Head / Manager | B23: CARBON | C23: Digitizing | D23: Band C · Head / Manager | E23: 1 | F23: Service delivery & data operations | G23: 38 | H23: 18 | I23: 16 | J23: 15 | K23: =WM_EXP_CE -> 5 | L23: 8 | M23: =SUM(G23:L23) -> 100 | N23: =IF((G23+H23+I23+J23+L23)=0,0,G23*(100-MAX(0,MIN(100,K23)))/(G23+H23+I23+J23+L23))/100 -> 0.38 | O23: =IF((G23+H23+I23+J23+L23)=0,0,H23*(100-MAX(0,MIN(100,K23)))/(G23+H23+I23+J23+L23))/100 -> 0.18 | P23: =IF((G23+H23+I23+J23+L23)=0,0,I23*(100-MAX(0,MIN(100,K23)))/(G23+H23+I23+J23+L23))/100 -> 0.16 | Q23: =IF((G23+H23+I23+J23+L23)=0,0,J23*(100-MAX(0,MIN(100,K23)))/(G23+H23+I23+J23+L23))/100 -> 0.15 | R23: =MAX(0,MIN(100,K23))/100 -> 0.05 | S23: =IF((G23+H23+I23+J23+L23)=0,0,L23*(100-MAX(0,MIN(100,K23)))/(G23+H23+I23+J23+L23))/100 -> 0.08 | U23: 38 | V23: 18 | W23: 16 | X23: 15 | Y23: 5 | Z23: 8
A24: CARBON · Functional · Band A · Early career | B24: CARBON | C24: Functional | D24: Band A · Early career | E24: 2 | F24: Regulatory & domain consulting | G24: 59 | H24: 16 | I24: 9 | J24: 0 | K24: =WM_EXP_AB -> 10 | L24: 6 | M24: =SUM(G24:L24) -> 100 | N24: =IF((G24+H24+I24+J24+L24)=0,0,G24*(100-MAX(0,MIN(100,K24)))/(G24+H24+I24+J24+L24))/100 -> 0.59 | O24: =IF((G24+H24+I24+J24+L24)=0,0,H24*(100-MAX(0,MIN(100,K24)))/(G24+H24+I24+J24+L24))/100 -> 0.16 | P24: =IF((G24+H24+I24+J24+L24)=0,0,I24*(100-MAX(0,MIN(100,K24)))/(G24+H24+I24+J24+L24))/100 -> 0.09 | Q24: =IF((G24+H24+I24+J24+L24)=0,0,J24*(100-MAX(0,MIN(100,K24)))/(G24+H24+I24+J24+L24))/100 -> 0 | R24: =MAX(0,MIN(100,K24))/100 -> 0.1 | S24: =IF((G24+H24+I24+J24+L24)=0,0,L24*(100-MAX(0,MIN(100,K24)))/(G24+H24+I24+J24+L24))/100 -> 0.06 | U24: 59 | V24: 16 | W24: 9 | X24: 0 | Y24: 10 | Z24: 6
A25: CARBON · Functional · Band B · Expert / POD Lead | B25: CARBON | C25: Functional | D25: Band B · Expert / POD Lead | E25: 11 | F25: Regulatory & domain consulting | G25: 51 | H25: 17 | I25: 10 | J25: 5 | K25: =WM_EXP_AB -> 10 | L25: 7 | M25: =SUM(G25:L25) -> 100 | N25: =IF((G25+H25+I25+J25+L25)=0,0,G25*(100-MAX(0,MIN(100,K25)))/(G25+H25+I25+J25+L25))/100 -> 0.51 | O25: =IF((G25+H25+I25+J25+L25)=0,0,H25*(100-MAX(0,MIN(100,K25)))/(G25+H25+I25+J25+L25))/100 -> 0.17 | P25: =IF((G25+H25+I25+J25+L25)=0,0,I25*(100-MAX(0,MIN(100,K25)))/(G25+H25+I25+J25+L25))/100 -> 0.1 | Q25: =IF((G25+H25+I25+J25+L25)=0,0,J25*(100-MAX(0,MIN(100,K25)))/(G25+H25+I25+J25+L25))/100 -> 0.05 | R25: =MAX(0,MIN(100,K25))/100 -> 0.1 | S25: =IF((G25+H25+I25+J25+L25)=0,0,L25*(100-MAX(0,MIN(100,K25)))/(G25+H25+I25+J25+L25))/100 -> 0.07 | U25: 51 | V25: 17 | W25: 10 | X25: 5 | Y25: 10 | Z25: 7
A26: CARBON · Functional · Band B · People Manager | B26: CARBON | C26: Functional | D26: Band B · People Manager | E26: 1 | F26: Regulatory & domain consulting | G26: 37 | H26: 18 | I26: 11 | J26: 15 | K26: =WM_EXP_AB -> 10 | L26: 9 | M26: =SUM(G26:L26) -> 100 | N26: =IF((G26+H26+I26+J26+L26)=0,0,G26*(100-MAX(0,MIN(100,K26)))/(G26+H26+I26+J26+L26))/100 -> 0.37 | O26: =IF((G26+H26+I26+J26+L26)=0,0,H26*(100-MAX(0,MIN(100,K26)))/(G26+H26+I26+J26+L26))/100 -> 0.18 | P26: =IF((G26+H26+I26+J26+L26)=0,0,I26*(100-MAX(0,MIN(100,K26)))/(G26+H26+I26+J26+L26))/100 -> 0.11 | Q26: =IF((G26+H26+I26+J26+L26)=0,0,J26*(100-MAX(0,MIN(100,K26)))/(G26+H26+I26+J26+L26))/100 -> 0.15 | R26: =MAX(0,MIN(100,K26))/100 -> 0.1 | S26: =IF((G26+H26+I26+J26+L26)=0,0,L26*(100-MAX(0,MIN(100,K26)))/(G26+H26+I26+J26+L26))/100 -> 0.09 | U26: 37 | V26: 18 | W26: 11 | X26: 15 | Y26: 10 | Z26: 9
A27: CARBON · Marketing · Band A · Early career | B27: CARBON | C27: Marketing | D27: Band A · Early career | E27: 20 | F27: Sales & marketing | G27: 54 | H27: 21 | I27: 4 | J27: 0 | K27: =WM_EXP_AB -> 10 | L27: 11 | M27: =SUM(G27:L27) -> 100 | N27: =IF((G27+H27+I27+J27+L27)=0,0,G27*(100-MAX(0,MIN(100,K27)))/(G27+H27+I27+J27+L27))/100 -> 0.54 | O27: =IF((G27+H27+I27+J27+L27)=0,0,H27*(100-MAX(0,MIN(100,K27)))/(G27+H27+I27+J27+L27))/100 -> 0.21 | P27: =IF((G27+H27+I27+J27+L27)=0,0,I27*(100-MAX(0,MIN(100,K27)))/(G27+H27+I27+J27+L27))/100 -> 0.04 | Q27: =IF((G27+H27+I27+J27+L27)=0,0,J27*(100-MAX(0,MIN(100,K27)))/(G27+H27+I27+J27+L27))/100 -> 0 | R27: =MAX(0,MIN(100,K27))/100 -> 0.1 | S27: =IF((G27+H27+I27+J27+L27)=0,0,L27*(100-MAX(0,MIN(100,K27)))/(G27+H27+I27+J27+L27))/100 -> 0.11 | U27: 54 | V27: 21 | W27: 4 | X27: 0 | Y27: 10 | Z27: 11
A28: CARBON · Marketing · Band B · Expert / POD Lead | B28: CARBON | C28: Marketing | D28: Band B · Expert / POD Lead | E28: 4 | F28: Sales & marketing | G28: 46 | H28: 22 | I28: 5 | J28: 5 | K28: =WM_EXP_AB -> 10 | L28: 12 | M28: =SUM(G28:L28) -> 100 | N28: =IF((G28+H28+I28+J28+L28)=0,0,G28*(100-MAX(0,MIN(100,K28)))/(G28+H28+I28+J28+L28))/100 -> 0.46 | O28: =IF((G28+H28+I28+J28+L28)=0,0,H28*(100-MAX(0,MIN(100,K28)))/(G28+H28+I28+J28+L28))/100 -> 0.22 | P28: =IF((G28+H28+I28+J28+L28)=0,0,I28*(100-MAX(0,MIN(100,K28)))/(G28+H28+I28+J28+L28))/100 -> 0.05 | Q28: =IF((G28+H28+I28+J28+L28)=0,0,J28*(100-MAX(0,MIN(100,K28)))/(G28+H28+I28+J28+L28))/100 -> 0.05 | R28: =MAX(0,MIN(100,K28))/100 -> 0.1 | S28: =IF((G28+H28+I28+J28+L28)=0,0,L28*(100-MAX(0,MIN(100,K28)))/(G28+H28+I28+J28+L28))/100 -> 0.12 | U28: 46 | V28: 22 | W28: 5 | X28: 5 | Y28: 10 | Z28: 12
A29: CARBON · Marketing · Band B · People Manager | B29: CARBON | C29: Marketing | D29: Band B · People Manager | E29: 4 | F29: Sales & marketing | G29: 32 | H29: 23 | I29: 6 | J29: 15 | K29: =WM_EXP_AB -> 10 | L29: 14 | M29: =SUM(G29:L29) -> 100 | N29: =IF((G29+H29+I29+J29+L29)=0,0,G29*(100-MAX(0,MIN(100,K29)))/(G29+H29+I29+J29+L29))/100 -> 0.32 | O29: =IF((G29+H29+I29+J29+L29)=0,0,H29*(100-MAX(0,MIN(100,K29)))/(G29+H29+I29+J29+L29))/100 -> 0.23 | P29: =IF((G29+H29+I29+J29+L29)=0,0,I29*(100-MAX(0,MIN(100,K29)))/(G29+H29+I29+J29+L29))/100 -> 0.06 | Q29: =IF((G29+H29+I29+J29+L29)=0,0,J29*(100-MAX(0,MIN(100,K29)))/(G29+H29+I29+J29+L29))/100 -> 0.15 | R29: =MAX(0,MIN(100,K29))/100 -> 0.1 | S29: =IF((G29+H29+I29+J29+L29)=0,0,L29*(100-MAX(0,MIN(100,K29)))/(G29+H29+I29+J29+L29))/100 -> 0.14 | U29: 32 | V29: 23 | W29: 6 | X29: 15 | Y29: 10 | Z29: 14
A30: CARBON · Quality Assurance · Band A · Early career | B30: CARBON | C30: Quality Assurance | D30: Band A · Early career | E30: 7 | F30: Technology & engineering | G30: 64 | H30: 16 | I30: 4 | J30: 0 | K30: =WM_EXP_AB -> 10 | L30: 6 | M30: =SUM(G30:L30) -> 100 | N30: =IF((G30+H30+I30+J30+L30)=0,0,G30*(100-MAX(0,MIN(100,K30)))/(G30+H30+I30+J30+L30))/100 -> 0.64 | O30: =IF((G30+H30+I30+J30+L30)=0,0,H30*(100-MAX(0,MIN(100,K30)))/(G30+H30+I30+J30+L30))/100 -> 0.16 | P30: =IF((G30+H30+I30+J30+L30)=0,0,I30*(100-MAX(0,MIN(100,K30)))/(G30+H30+I30+J30+L30))/100 -> 0.04 | Q30: =IF((G30+H30+I30+J30+L30)=0,0,J30*(100-MAX(0,MIN(100,K30)))/(G30+H30+I30+J30+L30))/100 -> 0 | R30: =MAX(0,MIN(100,K30))/100 -> 0.1 | S30: =IF((G30+H30+I30+J30+L30)=0,0,L30*(100-MAX(0,MIN(100,K30)))/(G30+H30+I30+J30+L30))/100 -> 0.06 | U30: 64 | V30: 16 | W30: 4 | X30: 0 | Y30: 10 | Z30: 6
A31: CARBON · Quality Assurance · Band B · People Manager | B31: CARBON | C31: Quality Assurance | D31: Band B · People Manager | E31: 1 | F31: Technology & engineering | G31: 42 | H31: 18 | I31: 6 | J31: 15 | K31: =WM_EXP_AB -> 10 | L31: 9 | M31: =SUM(G31:L31) -> 100 | N31: =IF((G31+H31+I31+J31+L31)=0,0,G31*(100-MAX(0,MIN(100,K31)))/(G31+H31+I31+J31+L31))/100 -> 0.42 | O31: =IF((G31+H31+I31+J31+L31)=0,0,H31*(100-MAX(0,MIN(100,K31)))/(G31+H31+I31+J31+L31))/100 -> 0.18 | P31: =IF((G31+H31+I31+J31+L31)=0,0,I31*(100-MAX(0,MIN(100,K31)))/(G31+H31+I31+J31+L31))/100 -> 0.06 | Q31: =IF((G31+H31+I31+J31+L31)=0,0,J31*(100-MAX(0,MIN(100,K31)))/(G31+H31+I31+J31+L31))/100 -> 0.15 | R31: =MAX(0,MIN(100,K31))/100 -> 0.1 | S31: =IF((G31+H31+I31+J31+L31)=0,0,L31*(100-MAX(0,MIN(100,K31)))/(G31+H31+I31+J31+L31))/100 -> 0.09 | U31: 42 | V31: 18 | W31: 6 | X31: 15 | Y31: 10 | Z31: 9
A32: CARBON · Sales · Band A · Early career | B32: CARBON | C32: Sales | D32: Band A · Early career | E32: 1 | F32: Sales & marketing | G32: 54 | H32: 21 | I32: 4 | J32: 0 | K32: =WM_EXP_AB -> 10 | L32: 11 | M32: =SUM(G32:L32) -> 100 | N32: =IF((G32+H32+I32+J32+L32)=0,0,G32*(100-MAX(0,MIN(100,K32)))/(G32+H32+I32+J32+L32))/100 -> 0.54 | O32: =IF((G32+H32+I32+J32+L32)=0,0,H32*(100-MAX(0,MIN(100,K32)))/(G32+H32+I32+J32+L32))/100 -> 0.21 | P32: =IF((G32+H32+I32+J32+L32)=0,0,I32*(100-MAX(0,MIN(100,K32)))/(G32+H32+I32+J32+L32))/100 -> 0.04 | Q32: =IF((G32+H32+I32+J32+L32)=0,0,J32*(100-MAX(0,MIN(100,K32)))/(G32+H32+I32+J32+L32))/100 -> 0 | R32: =MAX(0,MIN(100,K32))/100 -> 0.1 | S32: =IF((G32+H32+I32+J32+L32)=0,0,L32*(100-MAX(0,MIN(100,K32)))/(G32+H32+I32+J32+L32))/100 -> 0.11 | U32: 54 | V32: 21 | W32: 4 | X32: 0 | Y32: 10 | Z32: 11
A33: CARBON · Sales · Band B · Expert / POD Lead | B33: CARBON | C33: Sales | D33: Band B · Expert / POD Lead | E33: 3 | F33: Sales & marketing | G33: 46 | H33: 22 | I33: 5 | J33: 5 | K33: =WM_EXP_AB -> 10 | L33: 12 | M33: =SUM(G33:L33) -> 100 | N33: =IF((G33+H33+I33+J33+L33)=0,0,G33*(100-MAX(0,MIN(100,K33)))/(G33+H33+I33+J33+L33))/100 -> 0.46 | O33: =IF((G33+H33+I33+J33+L33)=0,0,H33*(100-MAX(0,MIN(100,K33)))/(G33+H33+I33+J33+L33))/100 -> 0.22 | P33: =IF((G33+H33+I33+J33+L33)=0,0,I33*(100-MAX(0,MIN(100,K33)))/(G33+H33+I33+J33+L33))/100 -> 0.05 | Q33: =IF((G33+H33+I33+J33+L33)=0,0,J33*(100-MAX(0,MIN(100,K33)))/(G33+H33+I33+J33+L33))/100 -> 0.05 | R33: =MAX(0,MIN(100,K33))/100 -> 0.1 | S33: =IF((G33+H33+I33+J33+L33)=0,0,L33*(100-MAX(0,MIN(100,K33)))/(G33+H33+I33+J33+L33))/100 -> 0.12 | U33: 46 | V33: 22 | W33: 5 | X33: 5 | Y33: 10 | Z33: 12
A34: CARBON · Sales · Band C · Principal expert | B34: CARBON | C34: Sales | D34: Band C · Principal expert | E34: 1 | F34: Sales & marketing | G34: 49 | H34: 23 | I34: 5 | J34: 5 | K34: =WM_EXP_CE -> 5 | L34: 13 | M34: =SUM(G34:L34) -> 100 | N34: =IF((G34+H34+I34+J34+L34)=0,0,G34*(100-MAX(0,MIN(100,K34)))/(G34+H34+I34+J34+L34))/100 -> 0.49 | O34: =IF((G34+H34+I34+J34+L34)=0,0,H34*(100-MAX(0,MIN(100,K34)))/(G34+H34+I34+J34+L34))/100 -> 0.23 | P34: =IF((G34+H34+I34+J34+L34)=0,0,I34*(100-MAX(0,MIN(100,K34)))/(G34+H34+I34+J34+L34))/100 -> 0.05 | Q34: =IF((G34+H34+I34+J34+L34)=0,0,J34*(100-MAX(0,MIN(100,K34)))/(G34+H34+I34+J34+L34))/100 -> 0.05 | R34: =MAX(0,MIN(100,K34))/100 -> 0.05 | S34: =IF((G34+H34+I34+J34+L34)=0,0,L34*(100-MAX(0,MIN(100,K34)))/(G34+H34+I34+J34+L34))/100 -> 0.13 | U34: 49 | V34: 23 | W34: 5 | X34: 5 | Y34: 5 | Z34: 13
A35: CARBON · Services · Band A · Early career | B35: CARBON | C35: Services | D35: Band A · Early career | E35: 38 | F35: Service delivery & data operations | G35: 54 | H35: 16 | I35: 14 | J35: 0 | K35: =WM_EXP_AB -> 10 | L35: 6 | M35: =SUM(G35:L35) -> 100 | N35: =IF((G35+H35+I35+J35+L35)=0,0,G35*(100-MAX(0,MIN(100,K35)))/(G35+H35+I35+J35+L35))/100 -> 0.54 | O35: =IF((G35+H35+I35+J35+L35)=0,0,H35*(100-MAX(0,MIN(100,K35)))/(G35+H35+I35+J35+L35))/100 -> 0.16 | P35: =IF((G35+H35+I35+J35+L35)=0,0,I35*(100-MAX(0,MIN(100,K35)))/(G35+H35+I35+J35+L35))/100 -> 0.14 | Q35: =IF((G35+H35+I35+J35+L35)=0,0,J35*(100-MAX(0,MIN(100,K35)))/(G35+H35+I35+J35+L35))/100 -> 0 | R35: =MAX(0,MIN(100,K35))/100 -> 0.1 | S35: =IF((G35+H35+I35+J35+L35)=0,0,L35*(100-MAX(0,MIN(100,K35)))/(G35+H35+I35+J35+L35))/100 -> 0.06 | U35: 54 | V35: 16 | W35: 14 | X35: 0 | Y35: 10 | Z35: 6
A36: CARBON · Services · Band B · Expert / POD Lead | B36: CARBON | C36: Services | D36: Band B · Expert / POD Lead | E36: 12 | F36: Service delivery & data operations | G36: 46 | H36: 17 | I36: 15 | J36: 5 | K36: =WM_EXP_AB -> 10 | L36: 7 | M36: =SUM(G36:L36) -> 100 | N36: =IF((G36+H36+I36+J36+L36)=0,0,G36*(100-MAX(0,MIN(100,K36)))/(G36+H36+I36+J36+L36))/100 -> 0.46 | O36: =IF((G36+H36+I36+J36+L36)=0,0,H36*(100-MAX(0,MIN(100,K36)))/(G36+H36+I36+J36+L36))/100 -> 0.17 | P36: =IF((G36+H36+I36+J36+L36)=0,0,I36*(100-MAX(0,MIN(100,K36)))/(G36+H36+I36+J36+L36))/100 -> 0.15 | Q36: =IF((G36+H36+I36+J36+L36)=0,0,J36*(100-MAX(0,MIN(100,K36)))/(G36+H36+I36+J36+L36))/100 -> 0.05 | R36: =MAX(0,MIN(100,K36))/100 -> 0.1 | S36: =IF((G36+H36+I36+J36+L36)=0,0,L36*(100-MAX(0,MIN(100,K36)))/(G36+H36+I36+J36+L36))/100 -> 0.07 | U36: 46 | V36: 17 | W36: 15 | X36: 5 | Y36: 10 | Z36: 7
A37: CARBON · Services · Band B · People Manager | B37: CARBON | C37: Services | D37: Band B · People Manager | E37: 8 | F37: Service delivery & data operations | G37: 32 | H37: 18 | I37: 16 | J37: 15 | K37: =WM_EXP_AB -> 10 | L37: 9 | M37: =SUM(G37:L37) -> 100 | N37: =IF((G37+H37+I37+J37+L37)=0,0,G37*(100-MAX(0,MIN(100,K37)))/(G37+H37+I37+J37+L37))/100 -> 0.32 | O37: =IF((G37+H37+I37+J37+L37)=0,0,H37*(100-MAX(0,MIN(100,K37)))/(G37+H37+I37+J37+L37))/100 -> 0.18 | P37: =IF((G37+H37+I37+J37+L37)=0,0,I37*(100-MAX(0,MIN(100,K37)))/(G37+H37+I37+J37+L37))/100 -> 0.16 | Q37: =IF((G37+H37+I37+J37+L37)=0,0,J37*(100-MAX(0,MIN(100,K37)))/(G37+H37+I37+J37+L37))/100 -> 0.15 | R37: =MAX(0,MIN(100,K37))/100 -> 0.1 | S37: =IF((G37+H37+I37+J37+L37)=0,0,L37*(100-MAX(0,MIN(100,K37)))/(G37+H37+I37+J37+L37))/100 -> 0.09 | U37: 32 | V37: 18 | W37: 16 | X37: 15 | Y37: 10 | Z37: 9
A38: CARBON · Services · Band C · Head / Manager | B38: CARBON | C38: Services | D38: Band C · Head / Manager | E38: 2 | F38: Service delivery & data operations | G38: 38 | H38: 18 | I38: 16 | J38: 15 | K38: =WM_EXP_CE -> 5 | L38: 8 | M38: =SUM(G38:L38) -> 100 | N38: =IF((G38+H38+I38+J38+L38)=0,0,G38*(100-MAX(0,MIN(100,K38)))/(G38+H38+I38+J38+L38))/100 -> 0.38 | O38: =IF((G38+H38+I38+J38+L38)=0,0,H38*(100-MAX(0,MIN(100,K38)))/(G38+H38+I38+J38+L38))/100 -> 0.18 | P38: =IF((G38+H38+I38+J38+L38)=0,0,I38*(100-MAX(0,MIN(100,K38)))/(G38+H38+I38+J38+L38))/100 -> 0.16 | Q38: =IF((G38+H38+I38+J38+L38)=0,0,J38*(100-MAX(0,MIN(100,K38)))/(G38+H38+I38+J38+L38))/100 -> 0.15 | R38: =MAX(0,MIN(100,K38))/100 -> 0.05 | S38: =IF((G38+H38+I38+J38+L38)=0,0,L38*(100-MAX(0,MIN(100,K38)))/(G38+H38+I38+J38+L38))/100 -> 0.08 | U38: 38 | V38: 18 | W38: 16 | X38: 15 | Y38: 5 | Z38: 8
A39: CARBON · Support · Band A · Early career | B39: CARBON | C39: Support | D39: Band A · Early career | E39: 12 | F39: Customer support & success | G39: 54 | H39: 16 | I39: 9 | J39: 0 | K39: =WM_EXP_AB -> 10 | L39: 11 | M39: =SUM(G39:L39) -> 100 | N39: =IF((G39+H39+I39+J39+L39)=0,0,G39*(100-MAX(0,MIN(100,K39)))/(G39+H39+I39+J39+L39))/100 -> 0.54 | O39: =IF((G39+H39+I39+J39+L39)=0,0,H39*(100-MAX(0,MIN(100,K39)))/(G39+H39+I39+J39+L39))/100 -> 0.16 | P39: =IF((G39+H39+I39+J39+L39)=0,0,I39*(100-MAX(0,MIN(100,K39)))/(G39+H39+I39+J39+L39))/100 -> 0.09 | Q39: =IF((G39+H39+I39+J39+L39)=0,0,J39*(100-MAX(0,MIN(100,K39)))/(G39+H39+I39+J39+L39))/100 -> 0 | R39: =MAX(0,MIN(100,K39))/100 -> 0.1 | S39: =IF((G39+H39+I39+J39+L39)=0,0,L39*(100-MAX(0,MIN(100,K39)))/(G39+H39+I39+J39+L39))/100 -> 0.11 | U39: 54 | V39: 16 | W39: 9 | X39: 0 | Y39: 10 | Z39: 11
A40: CARBON · Support · Band B · Expert / POD Lead | B40: CARBON | C40: Support | D40: Band B · Expert / POD Lead | E40: 7 | F40: Customer support & success | G40: 46 | H40: 17 | I40: 10 | J40: 5 | K40: =WM_EXP_AB -> 10 | L40: 12 | M40: =SUM(G40:L40) -> 100 | N40: =IF((G40+H40+I40+J40+L40)=0,0,G40*(100-MAX(0,MIN(100,K40)))/(G40+H40+I40+J40+L40))/100 -> 0.46 | O40: =IF((G40+H40+I40+J40+L40)=0,0,H40*(100-MAX(0,MIN(100,K40)))/(G40+H40+I40+J40+L40))/100 -> 0.17 | P40: =IF((G40+H40+I40+J40+L40)=0,0,I40*(100-MAX(0,MIN(100,K40)))/(G40+H40+I40+J40+L40))/100 -> 0.1 | Q40: =IF((G40+H40+I40+J40+L40)=0,0,J40*(100-MAX(0,MIN(100,K40)))/(G40+H40+I40+J40+L40))/100 -> 0.05 | R40: =MAX(0,MIN(100,K40))/100 -> 0.1 | S40: =IF((G40+H40+I40+J40+L40)=0,0,L40*(100-MAX(0,MIN(100,K40)))/(G40+H40+I40+J40+L40))/100 -> 0.12 | U40: 46 | V40: 17 | W40: 10 | X40: 5 | Y40: 10 | Z40: 12
A41: CARBON · Support · Band B · People Manager | B41: CARBON | C41: Support | D41: Band B · People Manager | E41: 1 | F41: Customer support & success | G41: 32 | H41: 18 | I41: 11 | J41: 15 | K41: =WM_EXP_AB -> 10 | L41: 14 | M41: =SUM(G41:L41) -> 100 | N41: =IF((G41+H41+I41+J41+L41)=0,0,G41*(100-MAX(0,MIN(100,K41)))/(G41+H41+I41+J41+L41))/100 -> 0.32 | O41: =IF((G41+H41+I41+J41+L41)=0,0,H41*(100-MAX(0,MIN(100,K41)))/(G41+H41+I41+J41+L41))/100 -> 0.18 | P41: =IF((G41+H41+I41+J41+L41)=0,0,I41*(100-MAX(0,MIN(100,K41)))/(G41+H41+I41+J41+L41))/100 -> 0.11 | Q41: =IF((G41+H41+I41+J41+L41)=0,0,J41*(100-MAX(0,MIN(100,K41)))/(G41+H41+I41+J41+L41))/100 -> 0.15 | R41: =MAX(0,MIN(100,K41))/100 -> 0.1 | S41: =IF((G41+H41+I41+J41+L41)=0,0,L41*(100-MAX(0,MIN(100,K41)))/(G41+H41+I41+J41+L41))/100 -> 0.14 | U41: 32 | V41: 18 | W41: 11 | X41: 15 | Y41: 10 | Z41: 14
A42: CARBON · Support · Band C · Head / Manager | B42: CARBON | C42: Support | D42: Band C · Head / Manager | E42: 1 | F42: Customer support & success | G42: 38 | H42: 18 | I42: 11 | J42: 15 | K42: =WM_EXP_CE -> 5 | L42: 13 | M42: =SUM(G42:L42) -> 100 | N42: =IF((G42+H42+I42+J42+L42)=0,0,G42*(100-MAX(0,MIN(100,K42)))/(G42+H42+I42+J42+L42))/100 -> 0.38 | O42: =IF((G42+H42+I42+J42+L42)=0,0,H42*(100-MAX(0,MIN(100,K42)))/(G42+H42+I42+J42+L42))/100 -> 0.18 | P42: =IF((G42+H42+I42+J42+L42)=0,0,I42*(100-MAX(0,MIN(100,K42)))/(G42+H42+I42+J42+L42))/100 -> 0.11 | Q42: =IF((G42+H42+I42+J42+L42)=0,0,J42*(100-MAX(0,MIN(100,K42)))/(G42+H42+I42+J42+L42))/100 -> 0.15 | R42: =MAX(0,MIN(100,K42))/100 -> 0.05 | S42: =IF((G42+H42+I42+J42+L42)=0,0,L42*(100-MAX(0,MIN(100,K42)))/(G42+H42+I42+J42+L42))/100 -> 0.13 | U42: 38 | V42: 18 | W42: 11 | X42: 15 | Y42: 5 | Z42: 13
A43: CARBON · Technology · Band A · Early career | B43: CARBON | C43: Technology | D43: Band A · Early career | E43: 34 | F43: Technology & engineering | G43: 64 | H43: 16 | I43: 4 | J43: 0 | K43: =WM_EXP_AB -> 10 | L43: 6 | M43: =SUM(G43:L43) -> 100 | N43: =IF((G43+H43+I43+J43+L43)=0,0,G43*(100-MAX(0,MIN(100,K43)))/(G43+H43+I43+J43+L43))/100 -> 0.64 | O43: =IF((G43+H43+I43+J43+L43)=0,0,H43*(100-MAX(0,MIN(100,K43)))/(G43+H43+I43+J43+L43))/100 -> 0.16 | P43: =IF((G43+H43+I43+J43+L43)=0,0,I43*(100-MAX(0,MIN(100,K43)))/(G43+H43+I43+J43+L43))/100 -> 0.04 | Q43: =IF((G43+H43+I43+J43+L43)=0,0,J43*(100-MAX(0,MIN(100,K43)))/(G43+H43+I43+J43+L43))/100 -> 0 | R43: =MAX(0,MIN(100,K43))/100 -> 0.1 | S43: =IF((G43+H43+I43+J43+L43)=0,0,L43*(100-MAX(0,MIN(100,K43)))/(G43+H43+I43+J43+L43))/100 -> 0.06 | U43: 64 | V43: 16 | W43: 4 | X43: 0 | Y43: 10 | Z43: 6
A44: CARBON · Technology · Band B · Expert / POD Lead | B44: CARBON | C44: Technology | D44: Band B · Expert / POD Lead | E44: 9 | F44: Technology & engineering | G44: 56 | H44: 17 | I44: 5 | J44: 5 | K44: =WM_EXP_AB -> 10 | L44: 7 | M44: =SUM(G44:L44) -> 100 | N44: =IF((G44+H44+I44+J44+L44)=0,0,G44*(100-MAX(0,MIN(100,K44)))/(G44+H44+I44+J44+L44))/100 -> 0.56 | O44: =IF((G44+H44+I44+J44+L44)=0,0,H44*(100-MAX(0,MIN(100,K44)))/(G44+H44+I44+J44+L44))/100 -> 0.17 | P44: =IF((G44+H44+I44+J44+L44)=0,0,I44*(100-MAX(0,MIN(100,K44)))/(G44+H44+I44+J44+L44))/100 -> 0.05 | Q44: =IF((G44+H44+I44+J44+L44)=0,0,J44*(100-MAX(0,MIN(100,K44)))/(G44+H44+I44+J44+L44))/100 -> 0.05 | R44: =MAX(0,MIN(100,K44))/100 -> 0.1 | S44: =IF((G44+H44+I44+J44+L44)=0,0,L44*(100-MAX(0,MIN(100,K44)))/(G44+H44+I44+J44+L44))/100 -> 0.07 | U44: 56 | V44: 17 | W44: 5 | X44: 5 | Y44: 10 | Z44: 7
A45: CARBON · Technology · Band B · People Manager | B45: CARBON | C45: Technology | D45: Band B · People Manager | E45: 1 | F45: Technology & engineering | G45: 42 | H45: 18 | I45: 6 | J45: 15 | K45: =WM_EXP_AB -> 10 | L45: 9 | M45: =SUM(G45:L45) -> 100 | N45: =IF((G45+H45+I45+J45+L45)=0,0,G45*(100-MAX(0,MIN(100,K45)))/(G45+H45+I45+J45+L45))/100 -> 0.42 | O45: =IF((G45+H45+I45+J45+L45)=0,0,H45*(100-MAX(0,MIN(100,K45)))/(G45+H45+I45+J45+L45))/100 -> 0.18 | P45: =IF((G45+H45+I45+J45+L45)=0,0,I45*(100-MAX(0,MIN(100,K45)))/(G45+H45+I45+J45+L45))/100 -> 0.06 | Q45: =IF((G45+H45+I45+J45+L45)=0,0,J45*(100-MAX(0,MIN(100,K45)))/(G45+H45+I45+J45+L45))/100 -> 0.15 | R45: =MAX(0,MIN(100,K45))/100 -> 0.1 | S45: =IF((G45+H45+I45+J45+L45)=0,0,L45*(100-MAX(0,MIN(100,K45)))/(G45+H45+I45+J45+L45))/100 -> 0.09 | U45: 42 | V45: 18 | W45: 6 | X45: 15 | Y45: 10 | Z45: 9
A46: CARBON · Technology · Band C · Head / Manager | B46: CARBON | C46: Technology | D46: Band C · Head / Manager | E46: 1 | F46: Technology & engineering | G46: 48 | H46: 18 | I46: 6 | J46: 15 | K46: =WM_EXP_CE -> 5 | L46: 8 | M46: =SUM(G46:L46) -> 100 | N46: =IF((G46+H46+I46+J46+L46)=0,0,G46*(100-MAX(0,MIN(100,K46)))/(G46+H46+I46+J46+L46))/100 -> 0.48 | O46: =IF((G46+H46+I46+J46+L46)=0,0,H46*(100-MAX(0,MIN(100,K46)))/(G46+H46+I46+J46+L46))/100 -> 0.18 | P46: =IF((G46+H46+I46+J46+L46)=0,0,I46*(100-MAX(0,MIN(100,K46)))/(G46+H46+I46+J46+L46))/100 -> 0.06 | Q46: =IF((G46+H46+I46+J46+L46)=0,0,J46*(100-MAX(0,MIN(100,K46)))/(G46+H46+I46+J46+L46))/100 -> 0.15 | R46: =MAX(0,MIN(100,K46))/100 -> 0.05 | S46: =IF((G46+H46+I46+J46+L46)=0,0,L46*(100-MAX(0,MIN(100,K46)))/(G46+H46+I46+J46+L46))/100 -> 0.08 | U46: 48 | V46: 18 | W46: 6 | X46: 15 | Y46: 5 | Z46: 8
A48: WHAT EACH FACTOR MEANS — and when to give it more weight
A49: Factor | C49: What it measures | I49: Give it more weight when…
A50: Complexity & Expertise | C50: How hard and how specialised the work is | I50: The job's value is deep expertise: architecture, actuarial, taxonomy design
A51: Autonomy & Decision | C51: What the person decides without asking | I51: The job is trusted to act alone: product calls, deals, client decisions
A52: Accountability & Impact | C52: What the job answers for — its scope | I52: Results, risk or quality of an area rest on this job
A53: Leadership & Strategy | C53: Leading people or setting direction | I53: The job's results come through a team or through direction it sets
A54: Experience & Qualification | C54: Years in the field and qualifications | I54: A licence or long experience is itself the requirement — kept low by design
A55: Business Impact | C55: The difference the job makes to revenue, clients, compliance or cost | I55: Results are visible in business numbers: sales, client retention, filings, savings
A57: Leadership weights: Sources: S05, S46, S47 Hay managerial know-how by level · S04 Mercer IPE communication · S09 McKinsey spans of control. The 0 / 5 / 10 / 15 / 20% steps by role group are an IRIS design rule.
A58: Business Impact: Sources: S05 Hay accountability, nature of impact · S04 Mercer IPE impact · S07 WTW GGS nature and area of impact · S53–S57 public plans' financial or consequences factor, 7–10% of points.
A59: Type-of-work shift: Basis: S06 Hay short profile — A-type delivery jobs weight accountability, P-type thinking jobs weight problem solving, L-type are balanced. The ±5 size is an IRIS design rule, kept small so the market defaults stay in control.
A60: WHAT A WEIGHT MEANS
A61: Weight | C61: What it means for the score
A62: 0% | C62: Ignored for this role group — the rating does not count at all
A63: 5% | C63: Minor — a tie-breaker; a 1-point change in the rating moves the score by 0.05
A64: 10% | C64: Counts a little — a 1-point change moves the score by 0.10
A65: 15–20% | C65: Important — one of the main things this role is judged on
A66: 25–30% | C66: Leading factor — this is what the role is mostly about
A67: 35%+ | C67: Dominant — use rarely; one factor then decides most of the score
A69: How a weight works: points = rating × weight, and the score is the sum of the six points. So a weight is simply how much one point of rating on that factor is worth. Moving 5% from one factor to another changes a person's score by 0.05 × the difference between their two ratings — usually less than 0.2, which is why small changes rarely move a level.
A70: RULES OF THUMB
A71: • Start from the default row and change it in steps of 5%; small changes are safer than big ones.
A72: • Keep each row's six weights adding up to about 100%. If they don't, the sheet scales the five non-Experience weights so they do — the 'Used' columns show the real weights.
A73: • Experience & Qualification is set once for everyone in the Settings block above · Bands A–B and Bands C–E. Change it there, not row by row; a number typed in a row's Experience cell overrides the setting for that row.
A74: • Leaders of the same role group in different departments should differ only for a real reason · for example, sales roles count Business Impact more. Note the reason in the last column.
A75: • Your edits change points, the score and 'Level the score indicates' on sheet 2 at once. The final level — with the fair-play checks — is confirmed when HR imports your edits and re-runs the model.
A76: WHERE THE DEFAULT WEIGHTS COME FROM
A77: Each role group's default row is the average of three published sources, given equal weight: Korn Ferry Hay, Mercer IPE and five public point-factor plans — NHS Agenda for Change, UK local-government 13-factor, GLPC, Scottish Joint Council, US OPM FES. Sources: S46–S51 Korn Ferry Hay evaluations · S04, S52 Mercer IPE · S53–S57 NHS, UK NJC/PSC, GLPC, SJC and US OPM point-factor plans. The per-source figures: HR Super Master sheet 1e, section 0. Full links: source register, HR Super Master sheet 11 and Framework Master M16.
A78: Factor | G78: This file — average of its scored roles | K78: Published plans — average | O78: Published plans — range
A79: Complexity & Expertise | G79: 52.4% | K79: 42.8% | O79: 38–52%
A80: Autonomy & Decision | G80: 17.3% | K80: 14.9% | O80: 7–30%
A81: Accountability & Impact | G81: 9.4% | K81: 15.1% | O81: 6–20%
A82: Leadership & Strategy | G82: 3.2% | K82: 20.6% | O82: 8–30%
A83: Business Impact | G83: 7.9% | K83: 6.7% | O83: 0–10%
A84: Experience & Qualification | G84: 9.8% | K84: not scored separately | O84: Hay, Mercer IPE and WTW fold experience into knowledge
A86: WHAT A RATING MEANS — the same 1-to-12 scale for every factor, every department, every band
A87: A rating is the floor of the ladder that this side of the job looks like: 4 = B1-level, 8 = C2-level. Managers can change a person's Business Impact rating on sheet 2 · yellow; the other ratings are set from the evidence and changed through validation.
A88: Rating · level | C88: Complexity | F88: Autonomy | I88: Accountability | L88: Leadership | O88: Experience | R88: Business impact
A89: 12 · E2 | C89: Enterprise-wide uncertainty, transformation and external forces | F89: Accountable to the board | I89: Enterprise results, risk, culture and long-term viability | L89: Sets enterprise strategy; leads the executive team | O89: About 28 yrs | R89: Answers for the whole company's results and long-term value
A90: 11 · E1 | C90: Enterprise-level functional strategy | F90: Sets enterprise priorities for the function | I90: Enterprise-wide functional results | L90: Shapes enterprise strategy | O90: About 24 yrs | R90: Shapes company-wide results through a function
A91: 10 · D2 | C91: Portfolio-level strategic, financial and regulatory trade-offs | F91: Sets direction across business lines | I91: Multi-business results | L91: Builds the leadership team across businesses | O91: About 21 yrs | R91: Owns the results of several business lines
A92: 9 · D1 | C92: Competing strategic, financial and regulatory priorities | F92: Sets business-line direction, pricing and investment | I92: Business-line P&L and market position | L92: Defines business strategy; builds the leadership bench | O92: About 17.5 yrs | R92: Owns a business line's P&L and growth, or a company-wide function
A93: 8.5 · C+ | C93: Function-wide and cross-product problems; personally handles the most critical client or technical work | F93: Sets direction for the function; business-line trade-offs go to the Business Head | I93: Function results, budget and key-client outcomes; carries own book or principal delivery | L93: Leads managers and leads and 10+ people in the function while staying hands-on | O93: About 16 yrs | R93: Drives a function's results and personally wins or delivers key work
A94: 8 · C2 | C94: Function-wide or company-wide problems; creates methods and standards | F94: Sets direction for a function | I94: Function results, budget and risk | L94: Leads a function; shapes functional strategy | O94: About 14.5 yrs | R94: Drives a function's or department's results and costs
A95: 7 · C1 | C95: Ambiguous, cross-product problems | F95: Sets direction for a sub-function or domain | I95: Sub-function results or domain quality across products | L95: Leads managers or a community of practice | O95: About 12 yrs | R95: Changes results across a sub-function or across products
A96: 6.5 · B+ | C96: Principal-level problems in own domain; sets technical or quality standards and still builds | F96: Decides approach and priorities for the practice; escalates only cross-function trade-offs | I96: Practice outcomes plus own deliverables; quality and delivery of the team | L96: Leads 3–6 people · or a pod while remaining a hands-on expert; coaches, allocates, reviews | O96: About 11–12 yrs | R96: Drives a practice's results while delivering the hardest work
A97: 6 · B3 | C97: Sets standards for a practice; cross-team problems | F97: Commercial / strategic calls for the unit | I97: Several teams or a practice | L97: IC: leads a practice · People: team leads / managers report in | O97: About 10 yrs | R97: Shapes the results of a practice or several teams
A98: 5 · B2 | C98: Hardest problems in the domain | F98: Allocates people and sets team priorities | I98: One team or a client portfolio | L98: IC: guides others in the domain · People: manages a team of 6+ | O98: About 7.5 yrs | R98: Visible effect on a team's or client portfolio's revenue, quality or compliance
A99: 4 · B1 | C99: Domain specialist work | F99: Technical / QC / client calls for the domain | I99: A domain or a small team | L99: IC: mentors and reviews · People: hands-on team lead of 3–5 | O99: About 5.5 yrs | R99: Moves a module's, product area's or client account's results
... A102: 1 · A1 | C102: Learning; follows worked examples | F102: Needs approval / close guidance | I102: Learning tasks | L102: Not scored in Band A | O102: No experience yet | R102: Learning; little direct effect on business results yet
A104: The ladder scale: Sources: S01, S02 Aon Radford and Pave level codes · S08 SFIA levels of responsibility. Full links: source register, HR Super Master sheet 11 and Framework Master M16.

Sheet 1e. Weight Benchmark
A1: Weight benchmark — where the default weights come from | I1: ◂ Contents
A2: 1e · The published point-factor plans, how weights shift with seniority, the evidence on experience and on business impact, and IRIS's defaults set against them. Every figure has its source.
A3: IRIS · Job Architecture & Job Design · Final v1.12 · October 2026 · Internal — Confidential
A5: 0. How the default weights were derived — in one table
A6: Three published sources, given equal weight: Korn Ferry Hay — the most widely used private-sector method, with verified point evaluations by level; Mercer IPE — its published point table; and the five public point-factor plans. Each is mapped to the six IRIS factors by the same rules, then the three are averaged and rounded to whole numbers. The three sources agree within a few points for every role group.
A7: Role group · source | B7: Complexity | C7: Autonomy | D7: Accountability | E7: Leadership | F7: Experience | G7: Business impact | H7: Note
A8: Band A · Korn Ferry Hay | B8: 71% | C8: 11% | D8: 4% | E8: 0% | F8: 10% | G8: 4%
A9: Band A · Mercer IPE | B9: 51% | C9: 22% | D9: 8% | E9: 0% | F9: 10% | G9: 8%
A10: Band A · Public plans | B10: 53% | C10: 15% | D10: 15% | E10: 0% | F10: 10% | G10: 7%
A11: Band A · IRIS default | B11: 59% | C11: 16% | D11: 9% | E11: 0% | F11: 10% | G11: 6% | H11: Average of the three, whole numbers
A12: Band B · IC / POD Lead · Korn Ferry Hay | B12: 54% | C12: 19% | D12: 6% | E12: 5% | F12: 10% | G12: 6%
A13: Band B · IC / POD Lead · Mercer IPE | B13: 52% | C13: 18% | D13: 8% | E13: 5% | F13: 10% | G13: 8%
A14: Band B · IC / POD Lead · Public plans | B14: 48% | C14: 15% | D14: 15% | E14: 5% | F14: 10% | G14: 7%
A15: Band B · IC / POD Lead · IRIS default | B15: 51% | C15: 17% | D15: 10% | E15: 5% | F15: 10% | G15: 7% | H15: Average of the three, whole numbers
A16: Band B · People Manager · Korn Ferry Hay | B16: 35% | C16: 21% | D16: 10% | E16: 15% | F16: 10% | G16: 10%
A17: Band B · People Manager · Mercer IPE | B17: 38% | C17: 19% | D17: 9% | E17: 15% | F17: 10% | G17: 9%
A18: Band B · People Manager · Public plans | B18: 38% | C18: 15% | D18: 15% | E18: 15% | F18: 10% | G18: 7%
A19: Band B · People Manager · IRIS default | B19: 37% | C19: 18% | D19: 11% | E19: 15% | F19: 10% | G19: 9% | H19: Average of the three, whole numbers
A20: Player-Coach · B+ · Korn Ferry Hay | B20: 44% | C20: 20% | D20: 8% | E20: 10% | F20: 10% | G20: 8%
A21: Player-Coach · B+ · Mercer IPE | B21: 45% | C21: 18% | D21: 8% | E21: 10% | F21: 10% | G21: 8%
A22: Player-Coach · B+ · Public plans | B22: 43% | C22: 15% | D22: 15% | E22: 10% | F22: 10% | G22: 7%
A23: Player-Coach · B+ · IRIS default | B23: 44% | C23: 18% | D23: 10% | E23: 10% | F23: 10% | G23: 8% | H23: Average of the three, whole numbers
A24: Band C · Principal specialist · Korn Ferry Hay | B24: 55% | C24: 20% | D24: 8% | E24: 5% | F24: 5% | G24: 8%
A25: Band C · Principal specialist · Mercer IPE | B25: 55% | C25: 18% | D25: 8% | E25: 5% | F25: 5% | G25: 8%
A26: Band C · Principal specialist · Public plans | B26: 53% | C26: 15% | D26: 15% | E26: 5% | F26: 5% | G26: 7%
A27: Band C · Principal specialist · IRIS default | B27: 54% | C27: 18% | D27: 10% | E27: 5% | F27: 5% | G27: 8% | H27: Average of the three, whole numbers
A28: Band C · Head / manager · Korn Ferry Hay | B28: 44% | C28: 20% | D28: 8% | E28: 15% | F28: 5% | G28: 8%
A29: Band C · Head / manager · Mercer IPE | B29: 43% | C29: 19% | D29: 9% | E29: 15% | F29: 5% | G29: 9%
A30: Band C · Head / manager · Public plans | B30: 43% | C30: 15% | D30: 15% | E30: 15% | F30: 5% | G30: 7%
A31: Band C · Head / manager · IRIS default | B31: 43% | C31: 18% | D31: 11% | E31: 15% | F31: 5% | G31: 8% | H31: Average of the three, whole numbers
A32: Player-Coach · C+ · Korn Ferry Hay | B32: 38% | C32: 21% | D32: 8% | E32: 20% | F32: 5% | G32: 8%
A33: Player-Coach · C+ · Mercer IPE | B33: 37% | C33: 19% | D33: 9% | E33: 20% | F33: 5% | G33: 9%
A34: Player-Coach · C+ · Public plans | B34: 38% | C34: 15% | D34: 15% | E34: 20% | F34: 5% | G34: 7%
A35: Player-Coach · C+ · IRIS default | B35: 38% | C35: 18% | D35: 11% | E35: 20% | F35: 5% | G35: 8% | H35: Average of the three, whole numbers
A36: Bands D–E · Korn Ferry Hay | B36: 36% | C36: 22% | D36: 9% | E36: 20% | F36: 5% | G36: 9%
A37: Bands D–E · Mercer IPE | B37: 35% | C37: 20% | D37: 10% | E37: 20% | F37: 5% | G37: 10%
A38: Bands D–E · Public plans | B38: 38% | C38: 15% | D38: 15% | E38: 20% | F38: 5% | G38: 7%
A39: Bands D–E · IRIS default | B39: 37% | C39: 19% | D39: 11% | E39: 20% | F39: 5% | G39: 8% | H39: Average of the three, whole numbers
A41: Sources: S46–S51 Korn Ferry Hay evaluations · S04, S52 Mercer IPE · S53–S57 NHS, UK NJC/PSC, GLPC, SJC and US OPM point-factor plans. Full links: source register, HR Super Master sheet 11 and Framework Master M16.
A42: 0b. Mapping rules — the same for every source
A43: IRIS factor | C43: Taken from
A44: Experience & Qualification | C44: Held at the leadership's policy weight — 10% in Bands A–B, 5% in Bands C–E — and taken out of each method's knowledge factor first
A45: Leadership & Strategy | C45: People leadership expected at the level: 0% Band A, 5% experts, 10% B+, 15% managers and heads, 20% C+ and Bands D–E — taken from Hay know-how · managerial and human-relations know-how, Mercer IPE communication, or the plans' leadership and relationships factors
A46: Complexity & Expertise | C46: The rest of the knowledge factor, plus 60% of problem solving / innovation · the thinking challenge
A47: Autonomy & Decision | C47: 40% of problem solving / innovation · the thinking environment plus 40% of accountability / impact · freedom to act, Hay's heaviest element; the plans' own autonomy factor
A48: Accountability & Impact | C48: 30% of accountability / impact — the area or magnitude of the job's scope; the plans' responsibility factors
A49: Business Impact | C49: 30% of accountability / impact — the nature of the job's impact on results; the plans' financial / consequences factor
A51: Sources: S05, S46–S52 for the Hay and IPE factor definitions; the split percentages are IRIS mapping rules applied to every source alike. Experience: Sources: S05, S49 Hay know-how includes experience however acquired · S04, S52 Mercer IPE knowledge · S07 WTW GGS · S58 McKinsey · S59 Deloitte · S60 WEF · S61 EY India, 2026 — skills over tenure. The 10% / 5% level is an IRIS leadership decision. Leadership: Sources: S05, S46, S47 Hay managerial know-how by level · S04 Mercer IPE communication · S09 McKinsey spans of control. The 0 / 5 / 10 / 15 / 20% steps by role group are an IRIS design rule.
A52: 0c. Korn Ferry Hay — verified evaluations by level
A53: Know-How / Problem Solving / Accountability points and shares. Canada's executive plan scores public-service jobs on the Hay guide charts, which makes these the best public evidence of Hay shares by level.
A54: Job and level | B54: Know-How | C54: Problem Solving | D54: Accountability | E54: Shares KH / PS / AC | H54: Source
A55: Junior · clerical typical profile | B55: — | C55: — | D55: — | E55: 72.7 / 13.6 / 13.6 | H55: Hay summary deck, typical profile 64/12/12 + 12% working conditions
A56: Supervisor typical profile | B56: — | C56: — | D56: — | E56: 47.4 / 20.6 / 32.0 | H56: Hay summary deck, typical profile 46/20/31 + 3% working conditions
A57: Professional · research scientist | B57: 460 | C57: 230 | D57: 132 | E57: 56.0 / 28.0 / 16.1 | H57: Hay summary deck
A58: Manager · Regional Manager Finance & Admin | B58: 460 | C58: 200 | D58: 230 | E58: 51.7 / 22.5 / 25.8 | H58: Canada TBS EX plan, 4-O-3
A59: Director EX-1 · Director Financial Policies | B59: 460 | C59: 230 | D59: 264 | E59: 48.2 / 24.1 / 27.7 | H59: Canada TBS EX plan
A60: Director EX-1 · Director Financial Management | B60: 528 | C60: 264 | D60: 264 | E60: 50.0 / 25.0 / 25.0 | H60: Canada TBS EX plan, 5-M-1
A61: Director EX-1 · Regional Director | B61: 528 | C61: 264 | D61: 304 | E61: 48.2 / 24.1 / 27.7 | H61: Canada TBS EX plan, 5-A-1
A62: Senior executive EX-2 · ADC Operations | B62: 608 | C62: 304 | D62: 350 | E62: 48.2 / 24.1 / 27.7 | H62: Canada TBS EX plan, 6-A-2
A63: Senior executive EX-2 · DG Resource Management | B63: 608 | C63: 350 | D63: 350 | E63: 46.5 / 26.8 / 26.8 | H63: Canada TBS EX plan, 6-O-2
A64: Executive EX-3 · DG Regional Operations | B64: 700 | C64: 400 | D64: 528 | E64: 43.0 / 24.6 / 32.4 | H64: Canada TBS EX plan, 7-A-2
A66: Sources: S46, S47 Canada TBS Executive Group plans 2005 and 2022 · S48 Hay summary deck · S50 Western University Hay overview.
A67: 0d. Mercer IPE — the published point table
A68: Maximum points per factor are verified from the IPE v3.1 manual; the level rows apply that table to typical ratings for a company of IRIS's size, so they are illustrative. Impact's share grows with seniority and with company size.
A69: Row | B69: Impact | C69: Communication | D69: Innovation | E69: Knowledge | H69: Shares
A70: Maximum points per factor · Mercer IPE v3.1 | B70: 705 | C70: 115 | D70: 130 | E70: 260 | H70: Impact 58.3% · Communication 9.5% · Innovation 10.7% · Knowledge 21.5% at the maximum
A71: Junior · illustrative rating, organisation size 5 | B71: 25 | C71: 10 | D71: 25 | E71: 30 | H71: 27.8 / 11.1 / 27.8 / 33.3%
A72: Professional · illustrative | B72: 60 | C72: 40 | D72: 45 | E72: 90 | H72: 25.5 / 17.0 / 19.1 / 38.3%
A73: Manager · illustrative | B73: 131 | C73: 60 | D73: 75 | E73: 173 | H73: 29.8 / 13.7 / 17.1 / 39.4%
A74: Executive · illustrative | B74: 207 | C74: 100 | D74: 105 | E74: 218 | H74: 32.9 / 15.9 / 16.7 / 34.6%
A76: Sources: S52 Mercer IPE manual and factor sheet, third-party copies · S04 Mercer IPE.
A77: 1. Published point-factor plans — share of points by factor
A78: Effort and working-conditions factors removed and the rest scaled to 100%. Major vendors — Korn Ferry Hay, Mercer IPE, WTW, Aon Radford — do not publish their factor weights, so public schemes with published points are the hard benchmark.
A79: Plan | B79: Complexity & Expertise | C79: Autonomy & Decision | D79: Accountability & Impact | E79: Leadership & Strategy | F79: Business Impact | G79: Effort and conditions removed | H79: Source
A80: NHS Agenda for Change Job Evaluation Scheme · 16 factors, 1,000 points | B80: 40.0% | C80: 6.7% | D80: 20.0% | E80: 26.7% | F80: 6.7% | G80: 10.0% | H80: NHS Job Evaluation Handbook, ch. 6 para 1.5 — nhsemployers.org/sites/default/files/pdf/22/165.pdf
A81: UK local government 13-factor scheme · Police Staff Council version of the NJC scheme, 1,000 points | B81: 38.3% | C81: 13.0% | D81: 19.5% | E81: 19.5% | F81: 9.8% | G81: 20.0% | H81: PSC Handbook pp. 47–48 — lb2.local.gov.uk/sites/default/files/documents/police-staff-council-13-f-342.pdf · NJC's own table sits behind the LGA log-in · Exact for PSC; NJC assumed equal
A82: Greater London Provincial Council scheme · 11 factors, 948 points | B82: 45.0% | C82: 12.1% | D82: 6.0% | E82: 29.7% | F82: 7.2% | G82: 12.7% | H82: GLPC points weighting — sirddinbych.gov.uk/en/documents/jobs-and-employees/my-employment/reorganisation-and-change/glpc-points-weighting.pdf
A83: Scottish Joint Council scheme · 13 factors, 1,000 points | B83: 38.3% | C83: 13.0% | D83: 19.5% | E83: 19.5% | F83: 9.8% | G83: 20.0% | H83: Highland Council SJC scoring matrix — highland.gov.uk/download/downloads/id/3889/scoring_matrix.pdf
A84: US OPM Factor Evaluation System · 9 factors, 4,480 points | B84: 52.5% | C84: 29.7% | D84: 10.3% | E84: 7.5% | F84: 0.0% | G84: 2.2% | H84: OPM Introduction to the Position Classification Standards, Appendix 3 — opm.gov/…/positionclassificationintro.pdf
A85: Average of the five plans | B85: 42.8% | C85: 14.9% | D85: 15.1% | E85: 20.6% | F85: 6.7% | H85: Experience as a separate factor: none of the five
A86: Range | B86: 38–52% | C86: 7–30% | D86: 6–20% | E86: 8–30% | F86: 0–10%
A88: Plan | B88: How its factors were mapped to the IRIS factors
A89: NHS Agenda for Change Job Evaluation Scheme · 16 factors, 1,000 points | B89: Knowledge, training & experience 240 + analytical and physical skills 120 → Complexity; freedom to act 60; patient care, information, R&D 180; communication, planning, HR, policy 240; financial & physical resources 60
A90: UK local government 13-factor scheme · Police Staff Council version of the NJC scheme, 1,000 points | B90: Knowledge 163 + mental and physical skills 143; initiative & independence 104; responsibility for people and physical resources 156; interpersonal and supervision 156; financial resources 78
A91: Greater London Provincial Council scheme · 11 factors, 948 points | B91: Knowledge & skill 272 + creativity 100; discretion 100; resources 50; contacts and supervision 246; consequences 60
A92: Scottish Joint Council scheme · 13 factors, 1,000 points | B92: Knowledge 163 + mental skills and physical co-ordination 143; initiative 104; services to others and resources 156; communication and employees 156; financial 78
A93: US OPM Factor Evaluation System · 9 factors, 4,480 points | B93: Knowledge required 1,850 + complexity 450; supervisory controls and guidelines 1,300; scope & effect 450; personal contacts and purpose 330
A95: Sources: S53 NHS · S54 Police Staff Council / NJC · S55 GLPC · S56 SJC · S57 US OPM.
A96: 2. How weights shift with seniority — the Korn Ferry Hay profile
A97: Share of Hay points by job type. Secondary source, used to set the slope by level only; the direction matches the official Canada TBS guidance: operations and line roles score relatively high in Accountability, thinking roles in Problem Solving.
A98: Job type | B98: Know-How | C98: Problem Solving | D98: Accountability | H98: Read as
A99: Clerical | B99: 73% | C99: 14% | D99: 14% | H99: Junior: the work itself is almost everything
A100: Trade / technical | B100: 66% | C100: 15% | D100: 19% | H100: Junior: mostly know-how
A101: Specialist · research scientist | B101: 56% | C101: 28% | D101: 16% | H101: Expert: know-how and problem solving
A102: 'Level' profile · staff functions | B102: 50% | C102: 25% | D102: 25% | H102: Professional: balanced
A103: Supervisory / line manager | B103: 47% | C103: 21% | D103: 32% | H103: Manager: accountability rises to a third
A105: Sources: S46, S47 Canada TBS Hay evaluations · S48, S50 Hay typical profiles. S06 Hay short profile · 'Level' profile. Type-of-work shift: Basis: S06 Hay short profile — A-type delivery jobs weight accountability, P-type thinking jobs weight problem solving, L-type are balanced. The ±5 size is an IRIS design rule, kept small so the market defaults stay in control.
A106: 3. Experience & Qualification — why it can be kept low
A107: Method or study | C107: What it says | G107: Source
A108: Korn Ferry Hay | C108: Experience sits inside Know-How: 'the sum total of every kind of knowledge and skill, however acquired' — no separate experience factor | G108: S05, S46, S49 · Canada TBS Executive Group plan; Lincolnshire CC Hay guide
...

Sheet 2. Talent Mapping
A1: Talent Mapping — role, weightage, score → level, and the justification for every rating | AA1: ◂ Contents
A2: Sheet 2 · Read left to right: the person → their role before and after → what the role does · responsibilities and competencies required → six ratings × weights = points → the score and the level it points to → any rule that changed the level → why each rating was given · starting point, evidence, market standard → the data used. Ratings use the ladder scale: A1 = 1 … E2 = 12. Weights come live from the Weightage Matrix; points, score and indicated level recalculate when a leader edits it. Managers can overwrite the Business Impact rating, in yellow. Pay columns are left blank for HR.
A3: IRIS · Job Architecture & Job Design · Final v1.12 · October 2026 · Internal — Confidential
A4: Section colours: each column group has its own header colour and a matching light tint | E4: Changed vs current · designation or level | H4: Level up | I4: Level down — pay & title protected | J4: Newly mapped | K4: Player-Coach · B+ · C+ | L4: RED = critical input needed · could change or confirm the level | P4: YELLOW = to complete in validation
A5: PERSON | H5: ROLE — BEFORE → AFTER | R5: ROLE PROFILE — what they do · role-holders' survey themes + catalogue | S5: BUSINESS IMPACT — what the person's role means for the business | U5: RECRUITMENT — REPLACEMENT PROFILE · to hire a like-for-like replacement | Y5: WEIGHTAGE — rating × weight = points · weights live from the Weightage Matrix | AT5: HOW THE SCORE BECOMES THE LEVEL | AW5: JUSTIFICATION FOR EACH RATING — start point, evidence, market standard | BC5: DATA SOURCES, INPUTS NEEDED & MARKET STANDARD | BI5: PAY — set later from the pay survey · left blank | BN5: VALIDATION — manager & HR
A6: Emp ID | B6: Employee name | C6: Department | D6: Reporting manager | E6: Total exp. · yrs | F6: Exp. at IRIS · yrs | G6: Qualification | H6: Current designation | I6: Final designation | J6: Job family | K6: Sub-family · what they do | L6: Current level | M6: FINAL LEVEL | N6: Level title | O6: Band | P6: Track | Q6: Change vs current | R6: Role profile — what they do, responsibilities & competencies required | S6: Business impact — from survey and data | T6: Business impact — from manager / head · to complete | U6: Replacement — what they do · simple | V6: Hire equivalent · external market | W6: Competencies & skill level to hire for | X6: Interview questions for the perfect fit | Y6: Weight row — Weightage Matrix | Z6: Complexity rating | AA6: Complexity weight | AB6: Complexity points | AC6: Autonomy rating | AD6: Autonomy weight | AE6: Autonomy points | AF6: Accountab. rating | AG6: Accountab. weight | AH6: Accountab. points | AI6: Leadership rating | AJ6: Leadership weight | AK6: Leadership points | AL6: Exp + Qual rating | AM6: Exp + Qual weight | AN6: Exp + Qual points | AO6: Bus. Impact rating | AP6: Bus. Impact weight | AQ6: Bus. Impact points | AR6: WEIGHTED SCORE = Σ points | AS6: Level the score indicates | AT6: Why these weights | AU6: Calculation | AV6: Gates, limits & Player-Coach transition steps applied — with the numbers | AW6: Complexity & Expertise — justification | AX6: Autonomy & Decision — justification | AY6: Accountability & Impact — justification | AZ6: Leadership & Strategy — justification | BA6: Experience & Qualification — justification | BB6: Business Impact — justification | BC6: ADDITIONAL INPUTS NEEDED — what, and who provides it | BD6: Data used for this person | BE6: Market standard for this role and level | BF6: Confidence | BG6: Points to confirm | BH6: Player-Coach / calibration flag | BI6: Current fixed pay · annual CTC | BJ6: Proposed range — minimum | BK6: Proposed range — midpoint | BL6: Proposed range — maximum | BM6: Compa-ratio | BN6: Manager validation | BO6: Manager comment / proposed change | BP6: HR decision | BQ6: Approved level | BR6: Approved designation | BS6: Pay / title protection · Y/N | BT6: Reviewer | BU6: Decision date | BV6: Bus. Impact — model start
A7: IRIS0391 | B7: Anuradha RK | C7: CARBON Business Head | D7: Dixit Jasani | E7: 17.1 | F7: 16.4 | G7: MBA | H7: Business Head | I7: Business Head | J7: Executive Leadership | K7: Business & Functional Leadership | L7: Not in current mapping files | M7: D2 | N7: Vice President | O7: D | P7: People Manager | Q7: ● Newly mapped | R7: WHAT THE ROLE DOES: Owns a business line or enterprise function end to end. At D2: several business lines or an executive-scope enterprise function. KEY RESPONSIBILITIES: Owns a business line or enterprise function end to end; Portfolio-level strategic, financial and regulatory trade-offs; Multi-business results DELIVERS: Multi-business results DECIDES ALONE: Sets direction across business lines SKILLS & KNOWLEDGE · role-holders: Product Management COMPETENCIES REQUIRED — must-have ★: Strategic Thinking & Business Acumen · People Leadership & Mentoring OTHER FUNCTIONAL COMPETENCIES: Stakeholder & Client Management · Product, Platform & Domain Knowledge · Regulatory & BFSI Domain · Communication & Presentation PROFICIENCY NEEDED AT THIS LEVEL: Core 5 · Future-ready 4 · Functional 4 · Leadership 5 CREDENTIALS: MBA / PGDM · preferred at C+ SOURCE: Framework only · fewer than 3 answered — 3 holders, 0 answered the survey; sub-family 0 answered; catalogue RC-091 | S7: What the role answers for: Multi-business results. Accountability & Impact rating: 9 of 12 · D1-level impact. Leads 9 direct reports. Manager talent mapping — Latest rating: Not rated · manager · 9-Box Grid placement: Not placed · manager. | U7: Business Head in CARBON Business Head · CARBON, D2 — People Manager. The work: Owns a business line or enterprise function end to end. At this level the role owns several business lines or an executive-scope enterprise function. Key responsibilities: Owns a business line or enterprise function end to end; Portfolio-level strategic, financial and regulatory trade-offs; Multi-business results. Leads 9 direct reports. | V7: Hire as: Associate Vice President / Business Head — IRIS D2 Vice President · People Manager Market level: E3–E4 · SFIA 7 Set strategy Experience: 18–24 yrs · Education: Postgraduate / professional qualification Team size at this level: 5–8 AVPs / heads Equivalent titles at peers: IRIS Vs Market Benchmark — Aon Radford / Mercer executive codes – E3–E4 SVP · IRIS Vs Competitor Benchmark — regtech / SaaS executive titles – SVP Credentials: MBA / PGDM · preferred at C+ Must already know: Governance, risk and regulatory accountability | W7: FUNCTIONAL — skill level 4 of 5 · Advanced ★ Strategic Thinking & Business Acumen: Shapes strategy, pricing or investment choices ★ People Leadership & Mentoring: Leads leaders; builds succession • Stakeholder & Client Management: Owns key relationships; resolves escalations • Product, Platform & Domain Knowledge: Recognised product / domain expert; trains others • Regulatory & BFSI Domain: Interprets new regulation; advises clients and product • Communication & Presentation: Presents to senior stakeholders; shapes messaging CORE — skill level 5 of 5 · Expert • Ownership & Accountability: Owns business outcomes; builds a culture of accountability • Problem Solving & Critical Thinking: Frames enterprise-level problems; sets the approach for others • Communication & Collaboration: Represents IRIS externally; builds cross-business partnerships • Client & Quality Focus: Defines client and quality strategy for a business • Learning Agility & Adaptability: Anticipates change; builds a learning organisation • Integrity, Compliance & Information Security: Sets ethical and compliance standards for the business FUTURE-READY — skill level 4 of 5 · Advanced • AI Literacy & Augmentation: Designs AI-enabled processes for a team; sets safe-use practices • Data Literacy & Analytics: Defines metrics and dashboards for a team • Digital Fluency & Automation: Automates team processes; selects tools • Innovation & Continuous Improvement: Leads improvement initiatives for a team LEADERSHIP — skill level 5 of 5 · Expert • Leading & Developing People: Builds the leadership pipeline and culture • Decision Making & Delegation: Makes enterprise / business-line decisions • Strategic & Business Acumen: Sets business strategy and P&L direction • Influence & Change Leadership: Leads enterprise change; influences clients, regulators and partners SKILLS · from role-holders and HRIS: Product Management ★ = must-have for the family. Scale: 1 Awareness · 2 Working · 3 Practitioner · 4 Advanced · 5 Expert. | X7: Draft — generated from the framework; hiring-manager review pending · HR Super Master, sheet T5. 1. [Strategic Thinking & Business Acumen · level 4] Tell me about recent work that shows this: "Shapes strategy, pricing or investment choices". What exactly did you do, how, and what was the result? Assess with: Case interview. 2. [People Leadership & Mentoring · level 4] Tell me about recent work that shows this: "Leads leaders; builds succession". What exactly did you do, how, and what was the result? Assess with: Behavioural interview. 3. [Stakeholder & Client Management · level 4] Give an example that shows you can do this: "Owns key relationships; resolves escalations". Assess with: Role play / behavioural interview. 4. [Product, Platform & Domain Knowledge · level 4] Give an example that shows you can do this: "Recognised product / domain expert; trains others". Assess with: Scenario interview. 5. [Regulatory & BFSI Domain · level 4] Give an example that shows you can do this: "Interprets new regulation; advises clients and product". Assess with: Domain interview. 6. [Ownership & Accountability · level 5] Describe a time you held a team to a standard on an outcome that mattered to the business. How did you make ownership stick? Listen for: "Owns business outcomes; builds a culture of accountability". 7. [Problem Solving & Critical Thinking · level 5] Tell me about an ambiguous, high-stakes problem with no clear answer. How did you frame it and decide? Listen for: "Frames enterprise-level problems; sets the approach for others". 8. [Client & Quality Focus · level 5] Describe how you raised quality or client outcomes across a team or service. How did you measure it? Listen for: "Defines client and quality strategy for a business". 9. [AI Literacy & Augmentation · level 4] Where have you introduced AI or automation into a team's work, and how did you manage the risks? Listen for: "Designs AI-enabled processes for a team; sets safe-use practices". 10. [Leading & Developing People · level 5] Tell me about building a team: who you hired, how you developed them, and a difficult people decision you made. Listen for: "Builds the leadership pipeline and culture". 11. [Decision Making & Delegation · level 5] Tell me about a decision you delegated and one you kept. Why, and what happened? Listen for: "Makes enterprise / business-line decisions". 12. [Strategic & Business Acumen · level 5] Tell me about a strategy or plan you shaped. What trade-offs did you make, and what was the business result? Listen for: "Sets business strategy and P&L direction". 13. [Influence & Change Leadership · level 5] Describe a change you led across teams or the business. How did you deal with resistance? Listen for: "Leads enterprise change; influences clients, regulators and partners". Fit check: Why this role, why IRIS · regulatory reporting / XBRL / regtech, and what would you change in your first 90 days? | Y7: CARBON · CARBON Business Head · Bands D–E · Leadership | Z7: 9 | AA7: =IFERROR(INDEX(WM_C,MATCH($Y7,WM_KEY,0)),"") -> 0.37 | AB7: =IF(Z7="","",Z7*AA7) -> 3.33 | AC7: 9 | AD7: =IFERROR(INDEX(WM_AU,MATCH($Y7,WM_KEY,0)),"") -> 0.19 | AE7: =IF(AC7="","",AC7*AD7) -> 1.71 | AF7: 9 | AG7: =IFERROR(INDEX(WM_AC,MATCH($Y7,WM_KEY,0)),"") -> 0.11 | AH7: =IF(AF7="","",AF7*AG7) -> 0.99 | AI7: 9 | AJ7: =IFERROR(INDEX(WM_L,MATCH($Y7,WM_KEY,0)),"") -> 0.2 | AK7: =IF(AI7="","",AI7*AJ7) -> 1.8 | AL7: 9.5 | AM7: =IFERROR(INDEX(WM_E,MATCH($Y7,WM_KEY,0)),"") -> 0.05 | AN7: =IF(AL7="","",AL7*AM7) -> 0.475 | AO7: 9 | AP7: =IFERROR(INDEX(WM_BI,MATCH($Y7,WM_KEY,0)),"") -> 0.08 | AQ7: =IF(AO7="","",AO7*AP7) -> 0.72 | AR7: =IF(COUNT(AB7,AE7,AH7,AK7,AN7,AQ7)<6,"",SUM(AB7,AE7,AH7,AK7,AN7,AQ7)) -> 9.025 | AS7: =IF(AR7="","",INDEX({"A1","A2","A3","B1","B2","B3","C1","C2","D1","D2","E1","E2"},MAX(1,MIN(12,ROUND(AR7,0))))) -> D1 | AT7: Weights: Complexity 37% · Leadership 20% · Autonomy 19% · Accountability 11% · Business impact 8% · Experience 5% Why: leaders are judged on the hardest problems, on leading — 20% — and on the decisions, scope and business impact of the job. Type of work in the department: no adjustment at this level. Live: change the department's row on the Weightage Matrix and these weights, the points and the score update. | AU7: At build: Complexity 3.33 + Autonomy 1.71 + Accountability 0.99 + Leadership 1.80 + Experience 0.48 + Business impact 0.72 = 9.03 points → nearest level 9 = D1 Final level: D2 · a rule applied: see the next column | AV7: • Set at D2 by leadership decision · the model indicated D1: Leadership structure: CARBON Business Head at D2. Final level: D2. | AW7: Rated 9 of 12 Start: 9.0 · business head / director title Evidence: no survey answers or KRAs on file → rating stays at the start Market: D1 = Competing strategic, financial and regulatory priorities | AX7: Rated 9 of 12 Start: 9.0 · business head / director title Evidence: no survey answers or KRAs on file → rating stays at the start Market: D1 = Sets business-line direction, pricing and investment | AY7: Rated 9 of 12 Start: 9.0 · business head / director title; 9 direct reports, 166 people in the organisation Evidence: no survey answers or KRAs on file → rating stays at the start Market: D1 = Business-line P&L and market position | AZ7: Rated 9 of 12 Start: 9.0 Evidence: no survey answers or KRAs on file → rating stays at the start Team: 9 direct reports · People Manager Market: D1 = Defines business strategy; builds the leadership bench | BA7: Rated 9.5 of 12 · between D1 and D2 Experience: 17.1 yrs total · 0.7 before IRIS + 16.4 at IRIS = 8.9 on the experience scale Qualification: MBA · postgraduate, relevant to the work → +0.5 | BB7: Rated 9 of 12 — a starting estimate. Start: 9, the role's accountability scope — what it answers for. No survey or manager-mapping signal on criticality: kept at the start point. Managers and heads: overwrite this rating on the Weightage sheet with the business impact you see — the score updates at once. Ladder: D1 = Owns a business line's P&L and growth, or a company-wide function | BC7: • Survey response or KRAs describing the work · nothing on file — Employee + manager • Resolve conflicting role records — Business head | BD7: ✓ HRIS: 17.1 yrs, MBA, 9 direct reports ✗ Survey: no response ✗ KRAs: none on file ✓ Manager mapping: rating, 9-box ✗ Job description: not on file ✓ Validated inputs: Approved level: D1 → D2 · Leadership structure: CARBON Business Head at D2 · Leadership decision · HR review of 9 Oct 2026 · 2026-10-09 | BE7: Market level: E3–E4 · SFIA 7 Set strategy Typical title: Associate Vice President / Business Head At peers: IRIS Vs Market Benchmark — Aon Radford / Mercer executive codes: E3–E4 SVP · IRIS Vs Competitor Benchmark — regtech / SaaS executive titles: SVP Standard: Aon Radford executive levels E1–E6; Mercer ET1–ET3 | BF7: Low | BG7: • CARBON Leadership Scorecard row 6 describes sales/implementation ownership for Anuradha, while the master says Business Head. Confirm full-business versus commercial-capability mandate and identity of the abbreviated reference • No survey answers or KRA — the role factors rest on designation and reporting lines only | BV7: 9
A8: IRIS2478 | B8: Dixit Jasani | C8: CRO - Carbon | D8: Balachandran K | E8: 27.9 | F8: 0.6 | G8: PGDM | H8: Chief Revenue Officer- Enterprise Division | I8: Chief Revenue Officer | J8: Executive Leadership | K8: Enterprise Leadership | L8: Not in current mapping files | M8: E1 | N8: CXO / President | O8: E | P8: People Manager | Q8: ● Newly mapped | R8: WHAT THE ROLE DOES: Sets enterprise strategy; leads the executive team. At E1: an enterprise-wide function. KEY RESPONSIBILITIES: Sets enterprise strategy; leads the executive team; Enterprise-level functional strategy; Enterprise-wide functional results DELIVERS: Enterprise-wide functional results DECIDES ALONE: Sets enterprise priorities for the function SKILLS & KNOWLEDGE · role-holders: Management · Sales COMPETENCIES REQUIRED — must-have ★: Strategic Thinking & Business Acumen · People Leadership & Mentoring OTHER FUNCTIONAL COMPETENCIES: Stakeholder & Client Management · Product, Platform & Domain Knowledge · Regulatory & BFSI Domain · Communication & Presentation PROFICIENCY NEEDED AT THIS LEVEL: Core 5 · Future-ready 5 · Functional 4 · Leadership 5 CREDENTIALS: MBA / PGDM · preferred at C+ SOURCE: Framework only · fewer than 3 answered — 4 holders, 0 answered the survey; sub-family 0 answered; catalogue RC-092 | S8: What the role answers for: Enterprise-wide functional results. Accountability & Impact rating: 11 of 12 · E1-level impact. Leads 1 direct report. Manager talent mapping — Latest rating: Not rated · manager · 9-Box Grid placement: Not placed · manager. | U8: Chief Revenue Officer in CRO - Carbon · CARBON, E1 — People Manager. The work: Sets enterprise strategy; leads the executive team. At this level the role owns an enterprise-wide function. Key responsibilities: Sets enterprise strategy; leads the executive team; Enterprise-level functional strategy; Enterprise-wide functional results. Leads 1 direct report. | V8: Hire as: CXO · functional chief — IRIS E1 CXO / President · People Manager Market level: E5 · SFIA 7 Experience: 20+ yrs · Education: Postgraduate / professional qualification Team size at this level: 5–8 function heads Equivalent titles at peers: IRIS Vs Market Benchmark — Aon Radford / Mercer executive codes – E5 C-level · functional · IRIS Vs Competitor Benchmark — regtech / SaaS executive titles – CTO · CFO · CRO · CCO · COO Credentials: MBA / PGDM · preferred at C+ Must already know: Governance, risk and regulatory accountability | W8: FUNCTIONAL — skill level 4 of 5 · Advanced ★ Strategic Thinking & Business Acumen: Shapes strategy, pricing or investment choices ★ People Leadership & Mentoring: Leads leaders; builds succession • Stakeholder & Client Management: Owns key relationships; resolves escalations • Product, Platform & Domain Knowledge: Recognised product / domain expert; trains others • Regulatory & BFSI Domain: Interprets new regulation; advises clients and product • Communication & Presentation: Presents to senior stakeholders; shapes messaging CORE — skill level 5 of 5 · Expert • Ownership & Accountability: Owns business outcomes; builds a culture of accountability • Problem Solving & Critical Thinking: Frames enterprise-level problems; sets the approach for others • Communication & Collaboration: Represents IRIS externally; builds cross-business partnerships • Client & Quality Focus: Defines client and quality strategy for a business • Learning Agility & Adaptability: Anticipates change; builds a learning organisation • Integrity, Compliance & Information Security: Sets ethical and compliance standards for the business FUTURE-READY — skill level 5 of 5 · Expert • AI Literacy & Augmentation: Leads AI strategy and governance for a function or IRIS • Data Literacy & Analytics: Sets data strategy and data-driven decisions for a business • Digital Fluency & Automation: Drives digital transformation across a business • Innovation & Continuous Improvement: Creates new products, methods or business models LEADERSHIP — skill level 5 of 5 · Expert • Leading & Developing People: Builds the leadership pipeline and culture • Decision Making & Delegation: Makes enterprise / business-line decisions • Strategic & Business Acumen: Sets business strategy and P&L direction • Influence & Change Leadership: Leads enterprise change; influences clients, regulators and partners SKILLS · from role-holders and HRIS: Management · Sales ★ = must-have for the family. Scale: 1 Awareness · 2 Working · 3 Practitioner · 4 Advanced · 5 Expert. | X8: Draft — generated from the framework; hiring-manager review pending · HR Super Master, sheet T5. 1. [Strategic Thinking & Business Acumen · level 4] Tell me about recent work that shows this: "Shapes strategy, pricing or investment choices". What exactly did you do, how, and what was the result? Assess with: Case interview. 2. [People Leadership & Mentoring · level 4] Tell me about recent work that shows this: "Leads leaders; builds succession". What exactly did you do, how, and what was the result? Assess with: Behavioural interview. 3. [Stakeholder & Client Management · level 4] Give an example that shows you can do this: "Owns key relationships; resolves escalations". Assess with: Role play / behavioural interview. 4. [Product, Platform & Domain Knowledge · level 4] Give an example that shows you can do this: "Recognised product / domain expert; trains others". Assess with: Scenario interview. 5. [Regulatory & BFSI Domain · level 4] Give an example that shows you can do this: "Interprets new regulation; advises clients and product". Assess with: Domain interview. 6. [Ownership & Accountability · level 5] Describe a time you held a team to a standard on an outcome that mattered to the business. How did you make ownership stick? Listen for: "Owns business outcomes; builds a culture of accountability". 7. [Problem Solving & Critical Thinking · level 5] Tell me about an ambiguous, high-stakes problem with no clear answer. How did you frame it and decide? Listen for: "Frames enterprise-level problems; sets the approach for others". 8. [Client & Quality Focus · level 5] Describe how you raised quality or client outcomes across a team or service. How did you measure it? Listen for: "Defines client and quality strategy for a business". 9. [AI Literacy & Augmentation · level 5] Where have you introduced AI or automation into a team's work, and how did you manage the risks? Listen for: "Leads AI strategy and governance for a function or IRIS". 10. [Leading & Developing People · level 5] Tell me about building a team: who you hired, how you developed them, and a difficult people decision you made. Listen for: "Builds the leadership pipeline and culture". 11. [Decision Making & Delegation · level 5] Tell me about a decision you delegated and one you kept. Why, and what happened? Listen for: "Makes enterprise / business-line decisions". 12. [Strategic & Business Acumen · level 5] Tell me about a strategy or plan you shaped. What trade-offs did you make, and what was the business result? Listen for: "Sets business strategy and P&L direction". 13. [Influence & Change Leadership · level 5] Describe a change you led across teams or the business. How did you deal with resistance? Listen for: "Leads enterprise change; influences clients, regulators and partners". Fit check: Why this role, why IRIS · regulatory reporting / XBRL / regtech, and what would you change in your first 90 days? | Y8: CARBON · CRO - Carbon · Bands D–E · Leadership | Z8: 11 | AA8: =IFERROR(INDEX(WM_C,MATCH($Y8,WM_KEY,0)),"") -> 0.37 | AB8: =IF(Z8="","",Z8*AA8) -> 4.07 | AC8: 11 | AD8: =IFERROR(INDEX(WM_AU,MATCH($Y8,WM_KEY,0)),"") -> 0.19 | AE8: =IF(AC8="","",AC8*AD8) -> 2.09 | AF8: 11 | AG8: =IFERROR(INDEX(WM_AC,MATCH($Y8,WM_KEY,0)),"") -> 0.11 | AH8: =IF(AF8="","",AF8*AG8) -> 1.21 | AI8: 11 | AJ8: =IFERROR(INDEX(WM_L,MATCH($Y8,WM_KEY,0)),"") -> 0.2 | AK8: =IF(AI8="","",AI8*AJ8) -> 2.2 | AL8: 12 | AM8: =IFERROR(INDEX(WM_E,MATCH($Y8,WM_KEY,0)),"") -> 0.05 | AN8: =IF(AL8="","",AL8*AM8) -> 0.6 | AO8: 11 | AP8: =IFERROR(INDEX(WM_BI,MATCH($Y8,WM_KEY,0)),"") -> 0.08 | AQ8: =IF(AO8="","",AO8*AP8) -> 0.88 | AR8: =IF(COUNT(AB8,AE8,AH8,AK8,AN8,AQ8)<6,"",SUM(AB8,AE8,AH8,AK8,AN8,AQ8)) -> 11.05 | AS8: =IF(AR8="","",INDEX({"A1","A2","A3","B1","B2","B3","C1","C2","D1","D2","E1","E2"},MAX(1,MIN(12,ROUND(AR8,0))))) -> E1 | AT8: Weights: Complexity 37% · Leadership 20% · Autonomy 19% · Accountability 11% · Business impact 8% · Experience 5% Why: leaders are judged on the hardest problems, on leading — 20% — and on the decisions, scope and business impact of the job. Type of work in the department: no adjustment at this level. Live: change the department's row on the Weightage Matrix and these weights, the points and the score update. | AU8: At build: Complexity 4.07 + Autonomy 2.09 + Accountability 1.21 + Leadership 2.20 + Experience 0.60 + Business impact 0.88 = 11.05 points → nearest level 11 = E1 Final level: E1 · same as the score | AV8: No rule applied: the score decides. | AW8: Rated 11 of 12 Start: 11.0 · CXO title Evidence: no survey answers or KRAs on file → rating stays at the start Market: E1 = Enterprise-level functional strategy | AX8: Rated 11 of 12 Start: 11.0 · CXO title Evidence: no survey answers or KRAs on file → rating stays at the start Market: E1 = Sets enterprise priorities for the function | AY8: Rated 11 of 12 Start: 11.0 · CXO title; 1 direct report, 167 people in the organisation Evidence: no survey answers or KRAs on file → rating stays at the start Market: E1 = Enterprise-wide functional results | AZ8: Rated 11 of 12 Start: 11.0 Evidence: no survey answers or KRAs on file → rating stays at the start Team: 1 direct report · People Manager Market: E1 = Shapes enterprise strategy | BA8: Rated 12 of 12 Experience: 27.9 yrs total · 27.3 before IRIS + 0.6 at IRIS = 12.0 on the experience scale Qualification: PGDM · postgraduate, relevant to the work → +0.5 | BB8: Rated 11 of 12 — a starting estimate. Start: 11, the role's accountability scope — what it answers for. No survey or manager-mapping signal on criticality: kept at the start point. Managers and heads: overwrite this rating on the Weightage sheet with the business impact you see — the score updates at once. Ladder: E1 = Shapes company-wide results through a function | BC8: • Survey response or KRAs describing the work · nothing on file — Employee + manager • Resolve conflicting role records — Business head | BD8: ✓ HRIS: 27.9 yrs, PGDM, 1 direct report ✗ Survey: no response ✗ KRAs: none on file ✓ Manager mapping: rating, 9-box ✗ Job description: not on file | BE8: Market level: E5 · SFIA 7 Typical title: CXO · functional chief At peers: IRIS Vs Market Benchmark — Aon Radford / Mercer executive codes: E5 C-level · functional · IRIS Vs Competitor Benchmark — regtech / SaaS executive titles: CTO · CFO · CRO · CCO · COO Standard: Aon Radford executive levels E1–E6; Mercer ET1–ET3 | BF8: Low | BG8: • CARBON Leadership Scorecard row 8 describes marketing/partnerships with no ARR ownership for Dixit, unlike the CRO designation. Confirm actual mandate and identity of the abbreviated reference • No survey answers or KRA — the role factors rest on designation and reporting lines only | BV8: 11
A9: IRIS2359 | B9: Suman Adhikary | C9: Customer Experience | D9: Anuradha RK | E9: 28.7 | F9: 1.5 | G9: B.E | H9: Senior Vice President - Customer Experience | I9: Senior Vice President – Customer Experience | J9: Executive Leadership | K9: Business & Functional Leadership | L9: Not in current mapping files | M9: D1 | N9: Associate Vice President / Business Head | O9: D | P9: People Manager | Q9: ● Newly mapped | R9: WHAT THE ROLE DOES: Owns a business line or enterprise function end to end. At D1: a business line P&L, region or enterprise function. KEY RESPONSIBILITIES: Owns a business line or enterprise function end to end; Competing strategic, financial and regulatory priorities; Business-line P&L and market position DELIVERS: Business-line P&L and market position DECIDES ALONE: Sets business-line direction, pricing and investment SKILLS & KNOWLEDGE · role-holders: Product Management COMPETENCIES REQUIRED — must-have ★: Strategic Thinking & Business Acumen · People Leadership & Mentoring OTHER FUNCTIONAL COMPETENCIES: Stakeholder & Client Management · Product, Platform & Domain Knowledge · Regulatory & BFSI Domain · Communication & Presentation PROFICIENCY NEEDED AT THIS LEVEL: Core 5 · Future-ready 4 · Functional 4 · Leadership 5 CREDENTIALS: MBA / PGDM · preferred at C+ SOURCE: Framework only · fewer than 3 answered — 2 holders, 0 answered the survey; sub-family 0 answered; catalogue RC-090 | S9: What the role answers for: Business-line P&L and market position. Accountability & Impact rating: 10 of 12 · D2-level impact. Leads 8 direct reports. From the survey and manager mapping — successor named: yes. Manager talent mapping — Latest rating: Not rated · manager · 9-Box Grid placement: Underperformer / Exit Risk. | U9: Senior Vice President – Customer Experience in Customer Experience · CARBON, D1 — People Manager. The work: Owns a business line or enterprise function end to end. At this level the role owns a business line P&L, region or enterprise function. Key responsibilities: Owns a business line or enterprise function end to end; Competing strategic, financial and regulatory priorities; Business-line P&L and market position. Leads 8 direct reports. | V9: Hire as: Vice President / Senior Vice President / Senior Vice President — IRIS D1 Associate Vice President / Business Head · People Manager Market level: E1–E2 · SFIA 6–7 Experience: 15–20 yrs · Education: Postgraduate / professional qualification Team size at this level: 5–8 heads Equivalent titles at peers: IRIS Vs Market Benchmark — Aon Radford / Mercer executive codes – E1–E2 VP / Business Head · IRIS Vs Competitor Benchmark — regtech / SaaS executive titles – General Manager / VP Credentials: MBA / PGDM · preferred at C+ Must already know: Governance, risk and regulatory accountability | W9: FUNCTIONAL — skill level 4 of 5 · Advanced ★ Strategic Thinking & Business Acumen: Shapes strategy, pricing or investment choices ★ People Leadership & Mentoring: Leads leaders; builds succession • Stakeholder & Client Management: Owns key relationships; resolves escalations • Product, Platform & Domain Knowledge: Recognised product / domain expert; trains others • Regulatory & BFSI Domain: Interprets new regulation; advises clients and product • Communication & Presentation: Presents to senior stakeholders; shapes messaging CORE — skill level 5 of 5 · Expert • Ownership & Accountability: Owns business outcomes; builds a culture of accountability • Problem Solving & Critical Thinking: Frames enterprise-level problems; sets the approach for others • Communication & Collaboration: Represents IRIS externally; builds cross-business partnerships • Client & Quality Focus: Defines client and quality strategy for a business • Learning Agility & Adaptability: Anticipates change; builds a learning organisation • Integrity, Compliance & Information Security: Sets ethical and compliance standards for the business FUTURE-READY — skill level 4 of 5 · Advanced • AI Literacy & Augmentation: Designs AI-enabled processes for a team; sets safe-use practices • Data Literacy & Analytics: Defines metrics and dashboards for a team • Digital Fluency & Automation: Automates team processes; selects tools • Innovation & Continuous Improvement: Leads improvement initiatives for a team LEADERSHIP — skill level 5 of 5 · Expert • Leading & Developing People: Builds the leadership pipeline and culture • Decision Making & Delegation: Makes enterprise / business-line decisions • Strategic & Business Acumen: Sets business strategy and P&L direction • Influence & Change Leadership: Leads enterprise change; influences clients, regulators and partners SKILLS · from role-holders and HRIS: Product Management ★ = must-have for the family. Scale: 1 Awareness · 2 Working · 3 Practitioner · 4 Advanced · 5 Expert. | X9: Draft — generated from the framework; hiring-manager review pending · HR Super Master, sheet T5. 1. [Strategic Thinking & Business Acumen · level 4] Tell me about recent work that shows this: "Shapes strategy, pricing or investment choices". What exactly did you do, how, and what was the result? Assess with: Case interview. 2. [People Leadership & Mentoring · level 4] Tell me about recent work that shows this: "Leads leaders; builds succession". What exactly did you do, how, and what was the result? Assess with: Behavioural interview. 3. [Stakeholder & Client Management · level 4] Give an example that shows you can do this: "Owns key relationships; resolves escalations". Assess with: Role play / behavioural interview. 4. [Product, Platform & Domain Knowledge · level 4] Give an example that shows you can do this: "Recognised product / domain expert; trains others". Assess with: Scenario interview. 5. [Regulatory & BFSI Domain · level 4] Give an example that shows you can do this: "Interprets new regulation; advises clients and product". Assess with: Domain interview. 6. [Ownership & Accountability · level 5] Describe a time you held a team to a standard on an outcome that mattered to the business. How did you make ownership stick? Listen for: "Owns business outcomes; builds a culture of accountability". 7. [Problem Solving & Critical Thinking · level 5] Tell me about an ambiguous, high-stakes problem with no clear answer. How did you frame it and decide? Listen for: "Frames enterprise-level problems; sets the approach for others". 8. [Client & Quality Focus · level 5] Describe how you raised quality or client outcomes across a team or service. How did you measure it? Listen for: "Defines client and quality strategy for a business". 9. [AI Literacy & Augmentation · level 4] Where have you introduced AI or automation into a team's work, and how did you manage the risks? Listen for: "Designs AI-enabled processes for a team; sets safe-use practices". 10. [Leading & Developing People · level 5] Tell me about building a team: who you hired, how you developed them, and a difficult people decision you made. Listen for: "Builds the leadership pipeline and culture". 11. [Decision Making & Delegation · level 5] Tell me about a decision you delegated and one you kept. Why, and what happened? Listen for: "Makes enterprise / business-line decisions". 12. [Strategic & Business Acumen · level 5] Tell me about a strategy or plan you shaped. What trade-offs did you make, and what was the business result? Listen for: "Sets business strategy and P&L direction". 13. [Influence & Change Leadership · level 5] Describe a change you led across teams or the business. How did you deal with resistance? Listen for: "Leads enterprise change; influences clients, regulators and partners". Fit check: Why this role, why IRIS · regulatory reporting / XBRL / regtech, and what would you change in your first 90 days? | Y9: CARBON · Customer Experience · Bands D–E · Leadership | Z9: 10 | AA9: =IFERROR(INDEX(WM_C,MATCH($Y9,WM_KEY,0)),"") -> 0.37 | AB9: =IF(Z9="","",Z9*AA9) -> 3.7 | AC9: 10 | AD9: =IFERROR(INDEX(WM_AU,MATCH($Y9,WM_KEY,0)),"") -> 0.19 | AE9: =IF(AC9="","",AC9*AD9) -> 1.9 | AF9: 10 | AG9: =IFERROR(INDEX(WM_AC,MATCH($Y9,WM_KEY,0)),"") -> 0.11 | AH9: =IF(AF9="","",AF9*AG9) -> 1.1 | AI9: 10 | AJ9: =IFERROR(INDEX(WM_L,MATCH($Y9,WM_KEY,0)),"") -> 0.2 | AK9: =IF(AI9="","",AI9*AJ9) -> 2 | AL9: 12 | AM9: =IFERROR(INDEX(WM_E,MATCH($Y9,WM_KEY,0)),"") -> 0.05 | AN9: =IF(AL9="","",AL9*AM9) -> 0.6 | AO9: 10 | AP9: =IFERROR(INDEX(WM_BI,MATCH($Y9,WM_KEY,0)),"") -> 0.08 | AQ9: =IF(AO9="","",AO9*AP9) -> 0.8 | AR9: =IF(COUNT(AB9,AE9,AH9,AK9,AN9,AQ9)<6,"",SUM(AB9,AE9,AH9,AK9,AN9,AQ9)) -> 10.1 | AS9: =IF(AR9="","",INDEX({"A1","A2","A3","B1","B2","B3","C1","C2","D1","D2","E1","E2"},MAX(1,MIN(12,ROUND(AR9,0))))) -> D2 | AT9: Weights: Complexity 37% · Leadership 20% · Autonomy 19% · Accountability 11% · Business impact 8% · Experience 5% Why: leaders are judged on the hardest problems, on leading — 20% — and on the decisions, scope and business impact of the job. Type of work in the department: no adjustment at this level. Live: change the department's row on the Weightage Matrix and these weights, the points and the score update. | AU9: At build: Complexity 3.70 + Autonomy 1.90 + Accountability 1.10 + Leadership 2.00 + Experience 0.60 + Business impact 0.80 = 10.10 points → nearest level 10 = D2 Final level: D1 · a rule applied: see the next column | AV9: • Set at D1 by leadership decision · the model indicated D2: Leadership structure: one level below her manager, the CARBON Business Head. Final level: D1. | AW9: Rated 10 of 12 Start: 10.0 · vice president title Evidence: no survey answers or KRAs on file → rating stays at the start Market: D2 = Portfolio-level strategic, financial and regulatory trade-offs | AX9: Rated 10 of 12 Start: 10.0 · vice president title Evidence: no survey answers or KRAs on file → rating stays at the start Market: D2 = Sets direction across business lines | AY9: Rated 10 of 12 Start: 10.0 · vice president title; 8 direct reports, 121 people in the organisation Evidence: no survey answers or KRAs on file → rating stays at the start Market: D2 = Multi-business results | AZ9: Rated 10 of 12 Start: 10.0 Evidence: no survey answers or KRAs on file → rating stays at the start Team: 8 direct reports · People Manager Market: D2 = Builds the leadership team across businesses | BA9: Rated 12 of 12 Experience: 28.7 yrs total · 27.2 before IRIS + 1.5 at IRIS = 12.0 on the experience scale Qualification: B.E · graduate → no change | BB9: Rated 10 of 12 — a starting estimate. Start: 10, the role's accountability scope — what it answers for. No survey or manager-mapping signal on criticality: kept at the start point. Managers and heads: overwrite this rating on the Weightage sheet with the business impact you see — the score updates at once. Ladder: D2 = Owns the results of several business lines | BC9: • Survey response or KRAs describing the work · nothing on file — Employee + manager • Resolve conflicting role records — Business head | BD9: ✓ HRIS: 28.7 yrs, B.E, 8 direct reports ✗ Survey: no response ✗ KRAs: none on file ✓ Manager mapping: rating, 9-box — filled from talent-mapping files: 9-box · CARBON grid ✗ Job description: not on file ✓ Validated inputs: Approved level: D2 → D1 · Leadership structure: one level below her manager, the CARBON Business Head · Leadership decision · HR review of 9 Oct 2026 · 2026-10-09 | BE9: Market level: E1–E2 · SFIA 6–7 Typical title: Vice President / Senior Vice President / Senior Vice President At peers: IRIS Vs Market Benchmark — Aon Radford / Mercer executive codes: E1–E2 VP / Business Head · IRIS Vs Competitor Benchmark — regtech / SaaS executive titles: General Manager / VP Standard: Aon Radford executive levels E1–E6; Mercer ET1–ET3 | BF9: Low | BG9: • CARBON Leadership Scorecard row 7 assigns services/customer-success revenue to Suman. Confirm identity, accountable functions and delegated resources/decision limits before choosing C2/C3/D1 • No survey answers or KRA — the role factors rest on designation and reporting lines only | BV9: 10
A10: IRIS0055 | B10: Vijay Parulekar | C10: Digitizing | D10: K Ashok Kumar | E10: 26.4 | F10: 19.9 | G10: B.Com | H10: Head Image Processing | I10: Associate Head – Digitization | J10: Data Operations & Digitization | K10: Digitization Leadership | L10: L7 – Head / Sr Director | M10: C1 | N10: Associate Head | O10: C | P10: People Manager | Q10: ▼ Down · protected | R10: WHAT THE ROLE DOES: Leads the data operations & digitization function. At C1: a sub-function, or principal authority across products. KEY RESPONSIBILITIES: Leads the data operations & digitization function; Ambiguous, cross-product problems; Sub-function results or domain quality across products DELIVERS: Sub-function results or domain quality across products DECIDES ALONE: Sets direction for a sub-function or domain COMPETENCIES REQUIRED — must-have ★: Advanced Excel & Productivity Tools · Process Improvement & Quality Mindset OTHER FUNCTIONAL COMPETENCIES: Regulatory & BFSI Domain · XBRL, iXBRL & Taxonomy · AI, GenAI & Prompt Engineering · Time, Priority & Self-Management PROFICIENCY NEEDED AT THIS LEVEL: Core 4 · Future-ready 4 · Functional 4 · Leadership 4 CREDENTIALS: MOS Excel · optional; Lean / Six Sigma · optional SOURCE: Framework only · fewer than 3 answered — 1 holder, 1 answered the survey; sub-family 1 answered; catalogue RC-045 | S10: What the role answers for: Sub-function results or domain quality across products. Accountability & Impact rating: 6.5 of 12 · B3-level impact. Leads 6 direct reports. From the survey and manager mapping — critical role: yes; successor named: no. Manager talent mapping — Latest rating: 4 · Potential: High · 9-Box Grid placement: Core Contributor. | U10: Associate Head – Digitization in Digitizing · CARBON, C1 — People Manager. The work: Leads the data operations & digitization function. At this level the role owns a sub-function, or principal authority across products. Key responsibilities: Leads the data operations & digitization function; Ambiguous, cross-product problems; Sub-function results or domain quality across products. Leads 6 direct reports. | V10: Hire as: Head of Function / AGM — IRIS C1 Associate Head · People Manager Market level: P6 / M5 · SFIA 5–6 Experience: 10–14 yrs · Education: Graduate · commerce preferred Team size at this level: 5–8, mostly managers Equivalent titles at peers: Accenture Operations – L6 Senior Manager · IRIS Vs Competitor Benchmark — operations roles – Head of Delivery Credentials: MOS Excel · optional; Lean / Six Sigma · optional Must already know: Accuracy and SLA discipline; data confidentiality | W10: FUNCTIONAL — skill level 4 of 5 · Advanced ★ Advanced Excel & Productivity Tools: Builds templates and automation used by the team ★ Process Improvement & Quality Mindset: Redesigns team processes; reduces error rates measurably • Regulatory & BFSI Domain: Interprets new regulation; advises clients and product • XBRL, iXBRL & Taxonomy: Resolves complex tagging and taxonomy issues; builds extensions; reviews others • AI, GenAI & Prompt Engineering: Builds AI features or AI-enabled processes; sets safe-use practice • Time, Priority & Self-Management: Plans team capacity and peak-season loads CORE — skill level 4 of 5 · Advanced • Ownership & Accountability: Owns team / practice outcomes; holds others to standards • Problem Solving & Critical Thinking: Solves complex, ambiguous problems; designs new approaches • Communication & Collaboration: Influences through communication; resolves conflict • Client & Quality Focus: Sets quality standards; improves client experience for a team • Learning Agility & Adaptability: Leads others through change; builds team capability • Integrity, Compliance & Information Security: Embeds compliance and security in team processes FUTURE-READY — skill level 4 of 5 · Advanced • AI Literacy & Augmentation: Designs AI-enabled processes for a team; sets safe-use practices • Data Literacy & Analytics: Defines metrics and dashboards for a team • Digital Fluency & Automation: Automates team processes; selects tools • Innovation & Continuous Improvement: Leads improvement initiatives for a team LEADERSHIP — skill level 4 of 5 · Advanced • Leading & Developing People: Leads leaders; builds bench strength • Decision Making & Delegation: Makes cross-team trade-offs; delegates authority • Strategic & Business Acumen: Shapes functional strategy, budget and market approach • Influence & Change Leadership: Influences senior stakeholders; leads function-wide change ★ = must-have for the family. Scale: 1 Awareness · 2 Working · 3 Practitioner · 4 Advanced · 5 Expert. | X10: Draft — generated from the framework; hiring-manager review pending · HR Super Master, sheet T5. 1. [Advanced Excel & Productivity Tools · level 4] Tell me about recent work that shows this: "Builds templates and automation used by the team". What exactly did you do, how, and what was the result? Assess with: Practical test. 2. [Process Improvement & Quality Mindset · level 4] Tell me about recent work that shows this: "Redesigns team processes; reduces error rates measurably". What exactly did you do, how, and what was the result? Assess with: Work sample / case. 3. [Regulatory & BFSI Domain · level 4] Give an example that shows you can do this: "Interprets new regulation; advises clients and product". Assess with: Domain interview. 4. [XBRL, iXBRL & Taxonomy · level 4] Give an example that shows you can do this: "Resolves complex tagging and taxonomy issues; builds extensions; reviews others". Assess with: Tagging test on a real filing. 5. [AI, GenAI & Prompt Engineering · level 4] Give an example that shows you can do this: "Builds AI features or AI-enabled processes; sets safe-use practice". Assess with: Work sample / portfolio. 6. [Ownership & Accountability · level 4] Describe a time you held a team to a standard on an outcome that mattered to the business. How did you make ownership stick? Listen for: "Owns team / practice outcomes; holds others to standards". 7. [Problem Solving & Critical Thinking · level 4] Tell me about an ambiguous, high-stakes problem with no clear answer. How did you frame it and decide? Listen for: "Solves complex, ambiguous problems; designs new approaches". 8. [Client & Quality Focus · level 4] Describe how you raised quality or client outcomes across a team or service. How did you measure it? Listen for: "Sets quality standards; improves client experience for a team". 9. [AI Literacy & Augmentation · level 4] Where have you introduced AI or automation into a team's work, and how did you manage the risks? Listen for: "Designs AI-enabled processes for a team; sets safe-use practices". 10. [Leading & Developing People · level 4] Tell me about building a team: who you hired, how you developed them, and a difficult people decision you made. Listen for: "Leads leaders; builds bench strength". 11. [Decision Making & Delegation · level 4] Tell me about a decision you delegated and one you kept. Why, and what happened? Listen for: "Makes cross-team trade-offs; delegates authority". 12. [Strategic & Business Acumen · level 4] Tell me about a strategy or plan you shaped. What trade-offs did you make, and what was the business result? Listen for: "Shapes functional strategy, budget and market approach". 13. [Influence & Change Leadership · level 4] Describe a change you led across teams or the business. How did you deal with resistance? Listen for: "Influences senior stakeholders; leads function-wide change". Fit check: Why this role, why IRIS · regulatory reporting / XBRL / regtech, and what would you change in your first 90 days? | Y10: CARBON · Digitizing · Band C · Head / Manager | Z10: 7 | AA10: =IFERROR(INDEX(WM_C,MATCH($Y10,WM_KEY,0)),"") -> 0.38 | AB10: =IF(Z10="","",Z10*AA10) -> 2.66 | AC10: 7 | AD10: =IFERROR(INDEX(WM_AU,MATCH($Y10,WM_KEY,0)),"") -> 0.18 | AE10: =IF(AC10="","",AC10*AD10) -> 1.26 | AF10: 6.5 | AG10: =IFERROR(INDEX(WM_AC,MATCH($Y10,WM_KEY,0)),"") -> 0.16 | AH10: =IF(AF10="","",AF10*AG10) -> 1.04 | AI10: 6 | AJ10: =IFERROR(INDEX(WM_L,MATCH($Y10,WM_KEY,0)),"") -> 0.15 | AK10: =IF(AI10="","",AI10*AJ10) -> 0.9 | AL10: 11.5 | AM10: =IFERROR(INDEX(WM_E,MATCH($Y10,WM_KEY,0)),"") -> 0.05 | AN10: =IF(AL10="","",AL10*AM10) -> 0.575 | AO10: 7 | AP10: =IFERROR(INDEX(WM_BI,MATCH($Y10,WM_KEY,0)),"") -> 0.08 | AQ10: =IF(AO10="","",AO10*AP10) -> 0.56 | AR10: =IF(COUNT(AB10,AE10,AH10,AK10,AN10,AQ10)<6,"",SUM(AB10,AE10,AH10,AK10,AN10,AQ10)) -> 6.995 | AS10: =IF(AR10="","",INDEX({"A1","A2","A3","B1","B2","B3","C1","C2","D1","D2","E1","E2"},MAX(1,MIN(12,ROUND(AR10,0))))) -> C1 | AT10: Weights: Complexity 38% · Autonomy 18% · Accountability 16% · Leadership 15% · Business impact 8% · Experience 5% Why: a head answers for a function through managers: Leadership 15%, with autonomy, accountability and impact rising; expertise still counts most. Type of work in the department: delivery work is judged on accuracy and turnaround, so Accountability +5 and Complexity −5. Live: change the department's row on the Weightage Matrix and these weights, the points and the score update. | AU10: At build: Complexity 2.66 + Autonomy 1.26 + Accountability 1.04 + Leadership 0.90 + Experience 0.58 + Business impact 0.56 = 7.00 points → nearest level 7 = C1 Final level: C1 · same as the score | AV10: No rule applied: the score decides. | AW10: Rated 7 of 12 Start: 8.0 · head-of-function title Evidence reads like B1: Plans formatting deliveries across all markets and two teams; process improvement; InDesign demos → moved down 1 KRA: “1. Ensure files processed by team with >=99% accuracy · zero critical errors. 2. Meet 100% of regulatory / client filing deadlines (no SLA…” Market: C1 = Ambiguous, cross-product problems | AX10: Rated 7 of 12 Start: 8.0 · head-of-function title Evidence reads like B2: Allocates workload and priority files; operational decisions on routine work → moved down 1 Market: C1 = Sets direction for a sub-function or domain | AY10: Rated 6.5 of 12 · between B3 and C1 Start: 7.5 · head-of-function title; 6 direct reports, 32 people below, 4 of them lead teams Evidence reads like B2: Accountable for all work of the Carbon Formatting and RBI CMS team → moved down 1 KRA: “1. Ensure files processed by team with >=99% accuracy · zero critical errors. 2. Meet 100% of regulatory / client filing deadlines (no SLA…” Market: B3 = Several teams or a practice · C1 = Sub-function results or domain quality across products | AZ10: Rated 6 of 12 Start: 7.0 Evidence reads like B2: Manages team with 6 reports: allocation, monitoring, guiding and training → moved down 1 Team: 6 direct reports · People Manager Market: B3 = IC: leads a practice · People: team leads / managers report in | BA10: Rated 11.5 of 12 · between E1 and E2 Experience: 26.4 yrs total · 6.5 before IRIS + 19.9 at IRIS = 11.6 on the experience scale Qualification: B.Com · graduate, relevant to the work → no change Market: C1 roles typically have 12–17 yrs · IRIS guide 10–14 | BB10: Rated 7 of 12 — a starting estimate. Start: 6.5, the role's accountability scope — what it answers for. Moved +0.5: the survey / manager mapping marks it business-critical. Managers and heads: overwrite this rating on the Weightage sheet with the business impact you see — the score updates at once. Ladder: C1 = Changes results across a sub-function or across products | BD10: ✓ HRIS: 26.4 yrs, B.Com, 6 direct reports ✓ Survey: 20 of 20 questions answered ✓ KRAs: submitted, reported deliverables ✓ Manager mapping: rating, potential, 9-box ✗ Job description: not on file | BE10: Market level: P6 / M5 · SFIA 5–6 Typical title: Head of Function / AGM At peers: Accenture Operations – L6 Senior Manager · IRIS Vs Competitor Benchmark — operations roles: Head of Delivery Typical experience: 12–17 yrs · IRIS guide 10–14 Standard: COPC CX Standard; ISO 9001 | BF10: High | BG10: • Work described is smaller than the current designation suggests — manager to confirm the actual role • Final level C1 is below the current level · L7 ≈ C2 — manager to confirm the scope of the role; pay and title are protected for one cycle | BV10: 7
A11: IRIS0470 | B11: Janardan Bale | C11: Digitizing | D11: Vijay Parulekar | E11: 18 | F11: 18 | G11: B.Com | H11: Image Processing Specialist | I11: Digitization Manager | J11: Data Operations & Digitization | K11: Document Conversion, Formatting & Web Publishing | L11: L3 – Professional / Associate | M11: B2 | N11: Manager | O11: B | P11: People Manager | Q11: ▲ Up | R11: WHAT THE ROLE DOES: Converts and formats documents into HTML/PDF/Word to filing or web standards, and publishes content · incl. RBI website. At B2: deep domain expertise, or one team. Common themes in sub-family holders, all levels' answers: purpose · core · formatting · quality · rbi · website KEY RESPONSIBILITIES: Converts and formats documents into HTML/PDF/Word to filing or web standards, and publishes content · incl. RBI website; Hardest problems in the domain; One team or a client portfolio Common themes in sub-family holders, all levels' answers: quality · document · formatting · html · accuracy · conversion DELIVERS: One team or a client portfolio Common themes in sub-family holders, all levels' answers: html · pdf · word · deliver · formatted · documents ACCOUNTABLE FOR: One team or a client portfolio Common themes in sub-family holders, all levels' answers: am · accountable · accuracy · quality · every · formatting DECIDES ALONE: Allocates people and sets team priorities Common themes in sub-family holders, all levels' answers: formatting · independently · html · validate · allocate · cipc SKILLS & KNOWLEDGE · role-holders: OCR/Image procesing · attention to detail · quality checking · Excel · timely delivery · HTML · Word · ABYYY Fine Reader TOOLS & SYSTEMS: Excel · Office 365 word · Carbon applications · Abby FineReader · Web Expression HTML editor · DM · HTML Editor · US DM - Carbon COMPETENCIES REQUIRED — must-have ★: Advanced Excel & Productivity Tools · Process Improvement & Quality Mindset OTHER FUNCTIONAL COMPETENCIES: Regulatory & BFSI Domain · XBRL, iXBRL & Taxonomy · AI, GenAI & Prompt Engineering · Time, Priority & Self-Management PROFICIENCY NEEDED AT THIS LEVEL: Core 3 · Future-ready 3 · Functional 4 · Leadership 3 CREDENTIALS: MOS Excel · optional; Lean / Six Sigma · optional SOURCE: Framework + sub-family themes · 3+ answered — 2 holders, 2 answered the survey; sub-family 30 answered; catalogue RC-050 | S11: What the role answers for: One team or a client portfolio. Accountability & Impact rating: 5 of 12 · B2-level impact. Leads 6 direct reports. From the survey and manager mapping — critical role: yes; successor named: no. If the work is missed · role-holders' themes: rework · delays · errors · quality · incorrect. Manager talent mapping — Latest rating: 5 · Potential: High · 9-Box Grid placement: Core Contributor. | U11: Digitization Manager in Digitizing · CARBON, B2 — People Manager. The work: Converts and formats documents into HTML/PDF/Word to filing or web standards, and publishes content · incl. RBI website. At this level the role owns deep domain expertise, or one team. Key responsibilities: Converts and formats documents into HTML/PDF/Word to filing or web standards, and publishes content · incl. RBI website; Hardest problems in the domain; One team or a client portfolio. Holders describe it with: quality · document · formatting · html · accuracy · conversion. Leads 6 direct reports. | V11: Hire as: Manager — IRIS B2 Manager · People Manager Market level: P4 / M3 · SFIA 4–5 Experience: 6–9 yrs · Education: Graduate · commerce preferred Team size at this level: IC: none · People: 6–8 knowledge work, 8–12 standardised delivery Equivalent titles at peers: Accenture Operations – L8 Associate Manager · IRIS Vs Competitor Benchmark — operations roles – Operations Manager Credentials: MOS Excel · optional; Lean / Six Sigma · optional Must already know: Accuracy and SLA discipline; data confidentiality | W11: FUNCTIONAL — skill level 4 of 5 · Advanced ★ Advanced Excel & Productivity Tools: Builds templates and automation used by the team ★ Process Improvement & Quality Mindset: Redesigns team processes; reduces error rates measurably • Regulatory & BFSI Domain: Interprets new regulation; advises clients and product • XBRL, iXBRL & Taxonomy: Resolves complex tagging and taxonomy issues; builds extensions; reviews others • AI, GenAI & Prompt Engineering: Builds AI features or AI-enabled processes; sets safe-use practice • Time, Priority & Self-Management: Plans team capacity and peak-season loads CORE — skill level 3 of 5 · Practitioner • Ownership & Accountability: Owns a module, client or process end to end; fixes root causes • Problem Solving & Critical Thinking: Analyses non-routine problems; finds root causes • Communication & Collaboration: Communicates with clients / stakeholders; collaborates across teams • Client & Quality Focus: Anticipates client needs; prevents errors in own area • Learning Agility & Adaptability: Adapts to changing priorities; learns independently • Integrity, Compliance & Information Security: Spots and escalates compliance / security risks FUTURE-READY — skill level 3 of 5 · Practitioner • AI Literacy & Augmentation: Builds AI into own workflow; evaluates accuracy and bias • Data Literacy & Analytics: Analyses data · SQL, BI, advanced Excel to find insight • Digital Fluency & Automation: Automates own repetitive work · macros, scripts, workflows • Innovation & Continuous Improvement: Delivers measurable improvements in own area LEADERSHIP — skill level 3 of 5 · Practitioner • Leading & Developing People: Leads a team; coaches and gives feedback • Decision Making & Delegation: Decides team priorities and resourcing • Strategic & Business Acumen: Plans team work against business goals and budgets • Influence & Change Leadership: Influences across teams; leads local change SKILLS · from role-holders and HRIS: OCR/Image procesing · attention to detail · quality checking · Excel · timely delivery · HTML · Word · ABYYY Fine Reader TOOLS: Excel · Office 365 word · Carbon applications · Abby FineReader · Web Expression HTML editor · DM · HTML Editor · US DM - Carbon ★ = must-have for the family. Scale: 1 Awareness · 2 Working · 3 Practitioner · 4 Advanced · 5 Expert. | X11: Draft — generated from the framework; hiring-manager review pending · HR Super Master, sheet T5. 1. [Advanced Excel & Productivity Tools · level 4] Tell me about recent work that shows this: "Builds templates and automation used by the team". What exactly did you do, how, and what was the result? Assess with: Practical test. 2. [Process Improvement & Quality Mindset · level 4] Tell me about recent work that shows this: "Redesigns team processes; reduces error rates measurably". What exactly did you do, how, and what was the result? Assess with: Work sample / case. 3. [Regulatory & BFSI Domain · level 4] Give an example that shows you can do this: "Interprets new regulation; advises clients and product". Assess with: Domain interview. 4. [XBRL, iXBRL & Taxonomy · level 4] Give an example that shows you can do this: "Resolves complex tagging and taxonomy issues; builds extensions; reviews others". Assess with: Tagging test on a real filing. 5. [AI, GenAI & Prompt Engineering · level 4] Give an example that shows you can do this: "Builds AI features or AI-enabled processes; sets safe-use practice". Assess with: Work sample / portfolio. 6. [Ownership & Accountability · level 3] Tell me about a piece of work you owned from start to finish. What went wrong, and what did you do about it? Listen for: "Owns a module, client or process end to end; fixes root causes". 7. [Problem Solving & Critical Thinking · level 3] Walk me through a problem you solved recently: how did you find the root cause and choose the fix? Listen for: "Analyses non-routine problems; finds root causes". 8. [Client & Quality Focus · level 3] Tell me about a time a client or user was unhappy with your work. What did you do? Listen for: "Anticipates client needs; prevents errors in own area". 9. [AI Literacy & Augmentation · level 3] Show me how you have used an AI tool in your work. How did you check its output? Listen for: "Builds AI into own workflow; evaluates accuracy and bias". 10. [Leading & Developing People · level 3] Tell me about helping a colleague or junior get better at something. Listen for: "Leads a team; coaches and gives feedback". 11. [Decision Making & Delegation · level 3] Give an example of a decision you made on your own. How did you know it was yours to make? Listen for: "Decides team priorities and resourcing". 12. [Strategic & Business Acumen · level 3] How does your work connect to how IRIS makes money or serves regulators and clients? Listen for: "Plans team work against business goals and budgets". 13. [Influence & Change Leadership · level 3] Tell me about persuading someone to change how they worked, without authority over them. Listen for: "Influences across teams; leads local change". Fit check: Why this role, why IRIS · regulatory reporting / XBRL / regtech, and what would you change in your first 90 days? | Y11: CARBON · Digitizing · Band B · People Manager | Z11: 3.5 | AA11: =IFERROR(INDEX(WM_C,MATCH($Y11,WM_KEY,0)),"") -> 0.32 | AB11: =IF(Z11="","",Z11*AA11) -> 1.12 | AC11: 4.5 | AD11: =IFERROR(INDEX(WM_AU,MATCH($Y11,WM_KEY,0)),"") -> 0.18 | AE11: =IF(AC11="","",AC11*AD11) -> 0.81 | AF11: 5 | AG11: =IFERROR(INDEX(WM_AC,MATCH($Y11,WM_KEY,0)),"") -> 0.16 | AH11: =IF(AF11="","",AF11*AG11) -> 0.8 | AI11: 5.5 | AJ11: =IFERROR(INDEX(WM_L,MATCH($Y11,WM_KEY,0)),"") -> 0.15 | AK11: =IF(AI11="","",AI11*AJ11) -> 0.825 | AL11: 9 | AM11: =IFERROR(INDEX(WM_E,MATCH($Y11,WM_KEY,0)),"") -> 0.1 | AN11: =IF(AL11="","",AL11*AM11) -> 0.9 | AO11: 5.5 | AP11: =IFERROR(INDEX(WM_BI,MATCH($Y11,WM_KEY,0)),"") -> 0.09 | AQ11: =IF(AO11="","",AO11*AP11) -> 0.495 | AR11: =IF(COUNT(AB11,AE11,AH11,AK11,AN11,AQ11)<6,"",SUM(AB11,AE11,AH11,AK11,AN11,AQ11)) -> 4.95 | AS11: =IF(AR11="","",INDEX({"A1","A2","A3","B1","B2","B3","C1","C2","D1","D2","E1","E2"},MAX(1,MIN(12,ROUND(AR11,0))))) -> B2 | AT11: Weights: Complexity 32% · Autonomy 18% · Accountability 16% · Leadership 15% · Experience 10% · Business impact 9% Why: a manager's results come through the team, so Leadership rises to 15% and Complexity falls; autonomy, accountability and impact rise. Type of work in the department: delivery work is judged on accuracy and turnaround, so Accountability +5 and Complexity −5. Live: change the department's row on the Weightage Matrix and these weights, the points and the score update. | AU11: At build: Complexity 1.12 + Autonomy 0.81 + Accountability 0.80 + Leadership 0.82 + Experience 0.90 + Business impact 0.49 = 4.95 points → nearest level 5 = B2 Final level: B2 · same as the score | AV11: No rule applied: the score decides. | AW11: Rated 3.5 of 12 · between A3 and B1 Start: 4.0 · senior practitioner title; reporting lines show a bigger role: 6 direct reports, 8 people below, 1 of them leads a team Evidence reads like A3: Go-to for US DM / HTML Editor: solves unsolved issues, QCs HMRC, CIPC, MCA → moved down 0.5 KRA: “1. Complete assigned conversion/formatting tasks with >=99% accuracy · zero critical errors 2. Meet 100% of client filing deadlines (no SLA…” Market: A3 = Varied and non-standard work; handles exceptions · B1 = Domain specialist work | AX11: Rated 4.5 of 12 · between B1 and B2 Start: 5.0 · senior practitioner title; reporting lines show a bigger role: 6 direct reports, 8 people below, 1 of them leads a team Evidence reads like B1: Allocates HMRC and CIPC documents among team members and delivers → moved down 0.5 Market: B1 = Technical / QC / client calls for the domain · B2 = Allocates people and sets team priorities | AY11: Rated 5 of 12 Start: 6.0 · senior practitioner title; 6 direct reports, 8 people below, 1 of them leads a team Evidence reads like B1: Leads US formatting team's output as team leader; own answer cites document confidentiality → moved down 1 KRA: “1. Complete assigned conversion/formatting tasks with >=99% accuracy · zero critical errors 2. Meet 100% of client filing deadlines (no SLA…” Market: B2 = One team or a client portfolio | AZ11: Rated 5.5 of 12 · between B2 and B3 Start: 6.0 Evidence reads like B2: Team leader of US formatting team with 6 reports; trains new joiners → moved down 0.5 Team: 6 direct reports · People Manager Market: B2 = IC: guides others in the domain · People: manages a team of 6+ · B3 = IC: leads a practice · People: team leads / managers report in | BA11: Rated 9 of 12 Experience: 18.0 yrs total · 18.0 at IRIS; none recorded before IRIS = 9.1 on the experience scale Qualification: B.Com · graduate, relevant to the work → no change Market: B2 roles typically have 6–10 yrs · IRIS guide 6–9 | BB11: Rated 5.5 of 12 — a starting estimate. Start: 5, the role's accountability scope — what it answers for. Moved +0.5: the survey / manager mapping marks it business-critical. Managers and heads: overwrite this rating on the Weightage sheet with the business impact you see — the score updates at once. Ladder: B2 = Visible effect on a team's or client portfolio's revenue, quality or compliance · B3 = Shapes the results of a practice or several teams | BC11: • Confirm the reporting line — Manager | BD11: ✓ HRIS: 18.0 yrs, B.Com, 6 direct reports ✓ Survey: 20 of 20 questions answered ✓ KRAs: submitted, reported deliverables ✓ Manager mapping: rating, potential, 9-box ✗ Job description: not on file | BE11: Market level: P4 / M3 · SFIA 4–5 Typical title: Manager At peers: Accenture Operations – L8 Associate Manager · IRIS Vs Competitor Benchmark — operations roles: Operations Manager Typical experience: 6–10 yrs · IRIS guide 6–9 Standard: COPC CX Standard; ISO 9001 | BF11: Medium | BG11: • Reporting lines show a much bigger role than the designation suggests — confirm the mandate; the designation may need to change • Final level B2 is 3 levels above the current level on record · L3 ≈ A2 — the record looks out of date; HR to confirm | BV11: 5.5
A12: IRIS1005 | B12: Datta Hatagale | C12: Digitizing | D12: Vijay Parulekar | E12: 14.9 | F12: 14.9 | G12: BA | H12: Image Processing Specialist | I12: Customer Enablement Specialist – POD Lead | J12: Customer Success & Support | K12: Customer Training & Enablement | L12: L3 – Professional / Associate | M12: B1 | N12: Specialist · POD Lead | O12: B | P12: POD Lead | Q12: ▲ Up | R12: WHAT THE ROLE DOES: Trains clients and drives product adoption. At B1: a domain / module, or a small team. KEY RESPONSIBILITIES: Trains clients and drives product adoption; Domain specialist work; A domain or a small team DELIVERS: A domain or a small team DECIDES ALONE: Technical / QC / client calls for the domain COMPETENCIES REQUIRED — must-have ★: Product, Platform & Domain Knowledge · Stakeholder & Client Management OTHER FUNCTIONAL COMPETENCIES: Communication & Presentation · Database, SQL & Data Engineering · Regulatory & BFSI Domain · Process Improvement & Quality Mindset PROFICIENCY NEEDED AT THIS LEVEL: Core 3 · Future-ready 3 · Functional 3 · Leadership 1 CREDENTIALS: Internal product certification SOURCE: Framework only · fewer than 3 answered — 1 holder, 1 answered the survey; sub-family 1 answered; catalogue RC-039 | S12: What the role answers for: A domain or a small team. Accountability & Impact rating: 3.5 of 12 · B1-level impact. Leads 3 direct reports. From the survey and manager mapping — critical role: yes; successor named: no. Manager talent mapping — Latest rating: 4 · Potential: High · 9-Box Grid placement: Core Contributor. | U12: Customer Enablement Specialist – POD Lead in Digitizing · CARBON, B1 — POD Lead. The work: Trains clients and drives product adoption. At this level the role owns a domain / module, or a small team. Key responsibilities: Trains clients and drives product adoption; Domain specialist work; A domain or a small team. Leads 3 direct reports. | V12: Hire as: Senior Executive / CSM — IRIS B1 Specialist · POD Lead · POD Lead Market level: P3 / M2 · SFIA 4 Enable Experience: 4–7 yrs · Education: Graduate Equivalent titles at peers: Workiva – Customer Success Manager · IRIS Vs Competitor Benchmark — SaaS customer-success ladder – CSM · IRIS Vs Competitor Benchmark — support tiers – L3 / Problem Analyst Credentials: Internal product certification Must already know: ITIL / service-desk practice; SLA management | W12: FUNCTIONAL — skill level 3 of 5 · Practitioner ★ Product, Platform & Domain Knowledge: Handles most product and domain scenarios ★ Stakeholder & Client Management: Manages client communication and expectations for own work • Communication & Presentation: Writes and presents clearly to clients and teams • Database, SQL & Data Engineering: Writes and tunes queries, procedures and ETL • Regulatory & BFSI Domain: Knows the relevant regulators, returns and rules • Process Improvement & Quality Mindset: Delivers right-first-time; improves own checklists CORE — skill level 3 of 5 · Practitioner • Ownership & Accountability: Owns a module, client or process end to end; fixes root causes • Problem Solving & Critical Thinking: Analyses non-routine problems; finds root causes • Communication & Collaboration: Communicates with clients / stakeholders; collaborates across teams • Client & Quality Focus: Anticipates client needs; prevents errors in own area • Learning Agility & Adaptability: Adapts to changing priorities; learns independently • Integrity, Compliance & Information Security: Spots and escalates compliance / security risks FUTURE-READY — skill level 3 of 5 · Practitioner • AI Literacy & Augmentation: Builds AI into own workflow; evaluates accuracy and bias • Data Literacy & Analytics: Analyses data · SQL, BI, advanced Excel to find insight • Digital Fluency & Automation: Automates own repetitive work · macros, scripts, workflows • Innovation & Continuous Improvement: Delivers measurable improvements in own area LEADERSHIP — skill level 1 of 5 · Awareness • Leading & Developing People: Not required • Decision Making & Delegation: Not required • Strategic & Business Acumen: Not required • Influence & Change Leadership: Not required ★ = must-have for the family. Scale: 1 Awareness · 2 Working · 3 Practitioner · 4 Advanced · 5 Expert. | X12: Draft — generated from the framework; hiring-manager review pending · HR Super Master, sheet T5. 1. [Product, Platform & Domain Knowledge · level 3] Tell me about recent work that shows this: "Handles most product and domain scenarios". What exactly did you do, how, and what was the result? Assess with: Scenario interview. 2. [Stakeholder & Client Management · level 3] Tell me about recent work that shows this: "Manages client communication and expectations for own work". What exactly did you do, how, and what was the result? Assess with: Role play / behavioural interview. 3. [Communication & Presentation · level 3] Give an example that shows you can do this: "Writes and presents clearly to clients and teams". Assess with: Presentation / writing test. 4. [Database, SQL & Data Engineering · level 3] Give an example that shows you can do this: "Writes and tunes queries, procedures and ETL". Assess with: SQL test / case. 5. [Regulatory & BFSI Domain · level 3] Give an example that shows you can do this: "Knows the relevant regulators, returns and rules". Assess with: Domain interview. 6. [Ownership & Accountability · level 3] Tell me about a piece of work you owned from start to finish. What went wrong, and what did you do about it? Listen for: "Owns a module, client or process end to end; fixes root causes". 7. [Problem Solving & Critical Thinking · level 3] Walk me through a problem you solved recently: how did you find the root cause and choose the fix? Listen for: "Analyses non-routine problems; finds root causes". 8. [Client & Quality Focus · level 3] Tell me about a time a client or user was unhappy with your work. What did you do? Listen for: "Anticipates client needs; prevents errors in own area". 9. [AI Literacy & Augmentation · level 3] Show me how you have used an AI tool in your work. How did you check its output? Listen for: "Builds AI into own workflow; evaluates accuracy and bias". Fit check: Why this role, why IRIS · regulatory reporting / XBRL / regtech, and what would you change in your first 90 days? | Y12: CARBON · Digitizing · Band B · Expert / POD Lead | Z12: 3 | AA12: =IFERROR(INDEX(WM_C,MATCH($Y12,WM_KEY,0)),"") -> 0.46 | AB12: =IF(Z12="","",Z12*AA12) -> 1.38 | AC12: 3 | AD12: =IFERROR(INDEX(WM_AU,MATCH($Y12,WM_KEY,0)),"") -> 0.17 | AE12: =IF(AC12="","",AC12*AD12) -> 0.51 | AF12: 3.5 | AG12: =IFERROR(INDEX(WM_AC,MATCH($Y12,WM_KEY,0)),"") -> 0.15 | AH12: =IF(AF12="","",AF12*AG12) -> 0.525 | AI12: 3.5 | AJ12: =IFERROR(INDEX(WM_L,MATCH($Y12,WM_KEY,0)),"") -> 0.05 | AK12: =IF(AI12="","",AI12*AJ12) -> 0.175 | AL12: 8 | AM12: =IFERROR(INDEX(WM_E,MATCH($Y12,WM_KEY,0)),"") -> 0.1 | AN12: =IF(AL12="","",AL12*AM12) -> 0.8 | AO12: 4 | AP12: =IFERROR(INDEX(WM_BI,MATCH($Y12,WM_KEY,0)),"") -> 0.07 | AQ12: =IF(AO12="","",AO12*AP12) -> 0.28 | AR12: =IF(COUNT(AB12,AE12,AH12,AK12,AN12,AQ12)<6,"",SUM(AB12,AE12,AH12,AK12,AN12,AQ12)) -> 3.67 | AS12: =IF(AR12="","",INDEX({"A1","A2","A3","B1","B2","B3","C1","C2","D1","D2","E1","E2"},MAX(1,MIN(12,ROUND(AR12,0))))) -> B1 | AT12: Weights: Complexity 46% · Autonomy 17% · Accountability 15% · Experience 10% · Business impact 7% · Leadership 5% Why: specialists are judged mainly on depth of expertise, then on what they decide alone, what they answer for and their impact. Type of work in the department: delivery work is judged on accuracy and turnaround, so Accountability +5 and Complexity −5. Live: change the department's row on the Weightage Matrix and these weights, the points and the score update. | AU12: At build: Complexity 1.38 + Autonomy 0.51 + Accountability 0.53 + Leadership 0.18 + Experience 0.80 + Business impact 0.28 = 3.67 points → nearest level 4 = B1 Final level: B1 · same as the score | AV12: No rule applied: the score decides. | AW12: Rated 3 of 12 Start: 3.0 · senior practitioner title Evidence: rated like 8 colleagues in the same role and department · own answers too general to rate → no change KRA: “1. Complete assigned conversion/formatting tasks with >=99% accuracy · zero critical errors 2. Meet 100% of client filing deadlines (no SLA…” Market: A3 = Varied and non-standard work; handles exceptions | AX12: Rated 3 of 12 Start: 3.0 · senior practitioner title Evidence: rated like 8 colleagues in the same role and department · own answers too general to rate → no change Market: A3 = Technical / QC / client calls on own work | AY12: Rated 3.5 of 12 · between A3 and B1 Start: 4.0 · senior practitioner title; 3 direct reports Evidence: rated like 8 colleagues in the same role and department · own answers too general to rate → moved −0.5 KRA: “1. Complete assigned conversion/formatting tasks with >=99% accuracy · zero critical errors 2. Meet 100% of client filing deadlines (no SLA…” Market: A3 = A module / process, or work with client or regulatory consequences · B1 = A domain or a small team | AZ12: Rated 3.5 of 12 · between A3 and B1 Start: 4.0 Evidence: rated like 8 colleagues in the same role and department · own answers too general to rate → moved −0.5 Team: 3 direct reports · POD Lead Market: A3 = Not scored in Band A · B1 = IC: mentors and reviews · People: hands-on team lead of 3–5 | BA12: Rated 8 of 12 Experience: 14.9 yrs total · 14.9 at IRIS; none recorded before IRIS = 8.1 on the experience scale Qualification: BA · graduate → no change Market: B1 roles typically have 4–8 yrs · IRIS guide 4–7 | BB12: Rated 4 of 12 — a starting estimate. Start: 3.5, the role's accountability scope — what it answers for. Moved +0.5: the survey / manager mapping marks it business-critical. Managers and heads: overwrite this rating on the Weightage sheet with the business impact you see — the score updates at once. Ladder: B1 = Moves a module's, product area's or client account's results | BD12: ✓ HRIS: 14.9 yrs, BA, 3 direct reports ✓ Survey: 20 of 20 questions answered ✓ KRAs: submitted, reported deliverables ✓ Manager mapping: rating, potential, 9-box ✗ Job description: not on file | BE12: Market level: P3 / M2 · SFIA 4 Enable Typical title: Senior Executive / CSM At peers: Workiva – Customer Success Manager · IRIS Vs Competitor Benchmark — SaaS customer-success ladder: CSM · IRIS Vs Competitor Benchmark — support tiers: L3 / Problem Analyst Typical experience: 4–8 yrs · IRIS guide 4–7 Standard: TSIA frameworks and benchmarks; ITIL 4 service desk | BF12: Low | BG12: • Survey answers are generic or do not match the role — not used as evidence; manager input needed | BV12: 4
