Workbook
Name WM_EXP_AB: '1. Framework & Model'!$B$1123
Name WM_EXP_CE: '1. Framework & Model'!$B$1124
Name WM_KEY: '1. Framework & Model'!$A$1134:$A$1240
Name WM_C: '1. Framework & Model'!$N$1134:$N$1240
Name WM_AU: '1. Framework & Model'!$O$1134:$O$1240
Name WM_AC: '1. Framework & Model'!$P$1134:$P$1240
Name WM_L: '1. Framework & Model'!$Q$1134:$Q$1240
Name WM_E: '1. Framework & Model'!$R$1134:$R$1240
Name WM_BI: '1. Framework & Model'!$S$1134:$S$1240
Name PC_Products: Lists!$A$1:$A$6
Name L_CARBON: Lists!$D$1:$D$215
Name L_iFile: Lists!$D$216:$D$433
Name L_iDEAL: Lists!$D$434:$D$480
Name L_Datatech: Lists!$D$481:$D$514
Name L_Consume: Lists!$D$515:$D$537
Name L_Corporate: Lists!$D$538:$D$586

Sheet 1. Framework & Model
A1: HR Master — Simplified · Framework & Model
A2: Sheet 1 of 5 · The whole method on one page, top to bottom: how the job architecture works, how every number is calculated, how to track open items, and the references for each part. Then sheet 2 Talent Mapping, 3 Raw Data, 4 Person Card and 5 Role Profiles.
A3: IRIS · Job Architecture & Job Design · Final v1.14 · October 2026 · Internal — Confidential · HR only
A5: HOW TO USE THIS FILE
A6: This file | B6: HR Master — Simplified: five sheets that hold every person, every number and every reason from the HR Super Master v1.14, laid out in one line from the method to the person to the role. HR edits it; the other files are rebuilt from it.
A7: Sheet 2 · Talent Mapping | B7: One row per person · 586 people · every column grouped left to right: who → role before and after → the live score → how the level was set → the reasons for each rating → KRAs received from the manager → what the employee shared in the survey → role profile and business impact → talent, competencies, learning, mobility → recruitment → market → inputs, decisions and data quality → pay, blank → validation → HR update.
A8: Sheet 3 · Raw Data | B8: Every raw field as received from HRIS, the survey count, the manager talent-mapping files and the CARBON Mapping Master · values the earlier clean-up lost are restored from the source files · 20 people found in the source files but not yet mapped are added at the bottom, marked.
A9: Sheet 4 · Person Card | B9: Type or paste an Emp ID, or pick Product, then Name: every column of sheet 2 for that person, with their role profile from sheet 5 and a ratings chart.
A10: Sheet 5 · Role Profiles | B10: One row per role in the IRIS role catalogue · 181 roles · what the role is for, does, decides and needs; its weightage, live from the matrix in section 4; the step below and above on the ladder; market equivalents; references.
A11: Live numbers | B11: Weights, points, the score and 'Level the score indicates' are Excel formulas. Change a yellow weight in section 4 or a Business Impact rating on sheet 2 and they recalculate. FINAL LEVEL is a decision, not a formula: it moves through the rules R1–R13 or an approved leadership decision.
A12: How to update | B12: Write changes in the yellow HR UPDATE columns at the right of sheet 2 · field, new value, reason, source, who, date · or in the validation columns. Each change is read back on the next rebuild, so every number stays traceable.
A13: v1.14 decisions | B13: HR, 12 October 2026: D2 = Senior Vice President / Business Head · D1 = Associate Vice President / Distinguished Principal · B1 = Team Lead / Specialist / Asst Manager. The 18 department and function heads sit in Executive Leadership · Business Head. HR PROPOSED on sheet 2 applies the top-down manager rule: under a head at C1 or above a reportee sits in a lower band; below C1 at least one level below the manager. The business-head workbook takes the HR proposed level from here.
A14: Privacy | B14: HR only. Survey content is shown against names by HR's decision of 12 October 2026. Gender, date of birth, age, e-mail, mobile, resignation and relieving dates are never written. Pay columns stay blank until a pay survey is bought.
A16: CONTENTS OF THIS SHEET — click a section
A17: 0 | B17: How this exercise works — the journey from a base framework to today
A18: 1 | B18: The model the simple way — the 1–12 scale, six factors, weights, points, score → level, worked examples
A19: 2 | B19: The Master Framework M0–M17 — principles, architecture, families, levels, tracks, titles, factors, weights, rules, competencies, crosswalk, pay principles, governance, sources
A20: 3 | B20: Where the default weights come from — the market benchmark and its derivation
A21: 4 | B21: Weightage Matrix — LIVE: change a yellow weight and sheets 2, 4 and 5 recalculate
A22: 5 | B22: How to calculate and how to track
A23: 5b | B23: The end-to-end workflow and the review loop
A24: 5c | B24: Governance, data rules, validation and pay principles
A25: 6 | B25: References & benchmarks — evidence grades, peer universe, professional standards, department × level benchmarks, source register S01–S72
A26: 7 | B26: Decision log — every decision, its version and its effect
A27: 7b | B27: Glossary
A28: 8 | B28: Where everything in the HR Super Master lives in this file
A30: 0 · How this exercise works — the journey from a base framework to today
A31: References: S40 Employee Master HRIS · S41 How We Grow survey · S42 manager talent-mapping files · S43 IRIS talent-mapping workbooks
A32: 1. What we did — step by step
A33: # | B33: Step | C33: What we did | D33: What came out of it
A34: 1 | B34: Created a base framework | C34: Built IRIS's job architecture from established market methods — Aon Radford / Mercer career levels, Korn Ferry Hay factors, WTW banding and SFIA — with job families anchored to the ILO occupation standard. | D34: 19 job families, 61 sub-families, a 12-level ladder plus two Player-Coach steps · B+, C+, six factors, individual-contributor and manager tracks
A35: 2 | B35: Designed a survey around it | C35: The 'How We Grow' survey: 20 questions, each tied to the framework's factors — purpose of the role, what it delivers, what it is accountable for, what it can decide, the skills and tools it needs, and learning needs. | D35: One evidence form for every role, so each rating can be traced to an answer
A36: 3 | B36: Conducted 60–65 workshops | C36: Ran 60–65 workshops with teams across the six products and Corporate: explained the framework, walked through the questions and collected answers in the room. | D36: Survey responses from 520 people
A37: 4 | B37: Gathered the data | C37: Combined the survey with the HRIS employee master, KRAs · self and manager-set, the managers' talent mapping · rating, potential, 9-box and the reporting lines. | D37: One record per person — 586 people; KRAs on file for 453
A38: 5 | B38: Cleaned and protected it | C38: Matched responses to people · with consent where needed, removed personal data, and showed survey content only where three or more role-holders answered — never one person's words against a name. | D38: Privacy-safe evidence
A39: 6 | B39: Mapped every role | C39: Placed each person in a job family, a sub-family · the work they actually do and a track. | D39: 267 distinct employee roles; one IRIS-wide role catalogue
A40: 7 | B40: Rated and scored | C40: Rated six factors — Complexity, Autonomy, Accountability, Leadership, Experience & Qualification, Business Impact — on the ladder scale from the evidence; rating × weight = points; points add up to a score; the score points to a level. | D40: A score and an indicated level for 540 employees
A41: 8 | B41: Applied the rules | C41: Gates, limits and Player-Coach steps where the evidence calls for them, and leadership decisions for the top bands — each one written down with its numbers. | D41: A final level and designation for everyone, every move explained
A42: 9 | B42: Benchmarked to the market | C42: Matched every level to Aon Radford / Mercer codes and SFIA, and to competitor, regtech and SaaS ladders; every source re-read and corrected. | D42: A market code and a typical market title for every level
A43: 10 | B43: Built the file set | C43: One build produces every file from the same data, so they always agree: the HR Super Master, product masters and simplified editions, the framework & model master, the calibration panel pack, the ladder master and draft letters. | D43: Files by audience, rebuilt and re-checked in minutes
A44: 11 | B44: Reviewed and corrected | C44: Business-head review, independent reviews, and 100+ automated checks on every build · placements, privacy, formulas, links, counts. | D44: Corrections fed back as validated inputs, never as hand edits
A46: 2. What we are doing now
A47: Now | C47: What happens | D47: Who
A48: Calibration | C48: The panel rates anchor roles blind and compares them with the model; close calls and moves down are decided. | D48: Calibration panel
A49: Decisions and data | C49: Open decisions and critical data requests are worked in the HR Super Master's tracker. | D49: HR, managers, business heads
A50: Business-head review | C50: Each business head marks Agree / Change / Discuss in their simplified edition; responses are imported and tracked. | D50: Business heads
A51: Sign-off | C51: The executive sponsor approves the structure; then the draft letters are issued. | D51: Executive sponsor, HR
A52: Pay · later | C52: Buy one India pay survey and price each level; pay columns stay blank until then. | D52: HR, Finance
A54: 3. How it works — in one minute
A55: Step | C55: In plain words
A56: 1 · A building with 12 floors | C56: IRIS is a building: floor 1 = first job, floor 12 = CEO; two half floors · B+, C+ for player-coaches. Every job lives on one floor.
A57: 2 · Six judges | C57: Six judges look at the job — How hard? Decides alone? Answers for? Leads? Experience? Business impact? — and each holds up a floor number · the rating, using the evidence: survey, KRAs, HRIS, reporting line.
A58: 3 · Some count more | C58: Starting out, the quality of the work counts most; for leaders, results, leading and business impact count most. Experience counts little. All six add to 100%, and leaders can edit them on the Weightage Matrix.
A59: 4 · Add up = the floor | C59: Card × how much it counts = points; add the points = the score; round it = the floor · 5.05 → 5 → B2. Fair-play checks can hold it — each one written down.
A61: The HR Super Master's sheet '1c. Scoring Made Simple' and the Process Explainer tell this story in full, with three worked examples.
A62: 4. What it produced — the output
A63: Output | D63: Count
A64: People mapped · employees + consultants | D64: 586
A65: Job families · sub-families | D65: 19 · 61
A66: Ladder steps in use · employees | D66: 13
A67: Designations on the new ladder · employees | D67: 184
A68: Distinct employee roles | D68: 267
A69: Products and Corporate | D69: 6
A70: People in leadership bands D–E | D70: 11
A72: 5. The impact
A73: Impact | C73: What it means
A74: One architecture for all of IRIS | C74: The same families, the same ladder and the same method in every product — titles mean the same thing everywhere.
A75: Transparent, explainable levels | C75: Every level traces to evidence, ratings, weights and named rules; anyone can see why a role sits where it does.
A76: Clear career paths | C76: Individual-contributor and manager tracks with a ladder in every sub-family, and the competencies needed for the next step.
A77: Duplication made visible | C77: 53 family × sub-family × level combinations are held in more than one product — candidates for common role definitions and shared pools.
A78: Leadership consistency | C78: No one in Bands D–E sits above their reporting manager, anyone in Band D reporting to an E1 / E2 sits at D2, and leadership levels are set by approved decisions.
A79: Ready for pay and planning | C79: Each level carries a market code, so pay ranges, succession and workforce planning can be built on it.
A81: 6. Our framework at a glance
A82: Element | B82: What it is
A83: Job families | B83: 19 families of work, each anchored to the ILO occupation standard — the same in every product.
A84: Sub-families | B84: 61 sub-families: the work a person actually does inside a family. One definition each, used everywhere.
A85: Career ladder | B85: One ladder from intern to CEO: A1–A3 practitioner · B1–B3 specialist / manager · B+ Player-Coach · C1–C2 principal / head · C+ Player-Coach · D1–D2 business leadership · E1–E2 enterprise leadership; X1–X3 for consultants · outside the ladder.
A86: Tracks | B86: Individual contributor, POD Lead · leads 1–3 while doing the work, Player-Coach · leads and delivers, People Manager, Consultant — experts progress without having to manage.
A87: Six factors | B87: Complexity & Expertise · Autonomy & Decision · Accountability & Impact · Leadership & Strategy · Experience & Qualification · Business Impact — each gets a rating: the floor of the ladder that part of the job looks like.
A88: Weights | B88: How much each factor counts, by band and track · junior roles: skill and experience; senior roles: accountability and leadership, fine-tuned ±5 by type of work.
A89: Rules | B89: R1–R13: category rules, provisional holds, work-substance and structure gates, experience limits, track minimums, Player-Coach steps, leadership decisions and the D–E reporting-line rules — each written on the person's row with its numbers.
A90: Titles | B90: Level marker + role noun; market titles where the market has its own ladder · Product Manager, Account Executive.
A91: Competencies | B91: 6 core and 4 future-ready for everyone, 4 leadership for leaders, and functional competencies for each family — each with a 1–5 skill level required at every career level.
A92: Market link | B92: Every level maps to Aon Radford / Mercer codes and SFIA, with competitor, regtech and SaaS equivalents — the base for pay ranges later.
A94: 7. The Job Architecture process — how the structure was built
A95: # | B95: Step | C95: What happens
A96: 1 | B96: Define families | C96: Group all work into job families anchored to ISCO-08, so the same work has the same name everywhere.
A97: 2 | B97: Define sub-families | C97: Split each family into the distinct kinds of work people do, from the survey and role data.
A98: 3 | B98: Set the ladder and bands | C98: One 12-level ladder with five bands and two Player-Coach steps; what each level owns, its experience range and span.
A99: 4 | B99: Set the tracks | C99: IC, POD Lead, Player-Coach, People Manager, Consultant — and the rules for each.
A100: 5 | B100: Level every role | C100: Six ratings × weights → score → level, then the rules; leadership levels by approved decision.
A101: 6 | B101: Name every role | C101: Designation = level marker + role noun; title protection for anyone moving down.
A102: 7 | B102: Benchmark | C102: Crosswalk every level to Radford / Mercer and SFIA; compare with competitor and peer ladders.
A103: 8 | B103: Govern | C103: Calibration panel, business-head review, a decision tracker and change rules · who can change a level, and how.
A105: 8. The Job Design process — how each role is described
A106: # | B106: Step | C106: What happens
A107: 1 | B107: Purpose | C107: Why the role exists — from the sub-family definition and the level standard.
A108: 2 | B108: Responsibilities and deliverables | C108: What the role does and produces — from role-holders' survey answers · as counted themes and KRAs.
A109: 3 | B109: Accountability and decision rights | C109: What the role answers for, what it can decide alone, and what happens if the work is missed.
A110: 4 | B110: Measures | C110: Manager-set KRAs: how the role is judged.
...

Sheet 2. Talent Mapping
A1: Talent Mapping — every person, every column, in one line | Q1: ◂ Start
A2: Sheet 2 of 5 · One row per person. Read left to right: who → role before and after → the live score → how the level was set → the reasons → KRAs from the manager → what the employee shared in the survey → role profile and business impact → talent, competencies, learning, mobility → recruitment → market → inputs, decisions and data quality → pay, blank → validation → HR update. Filter any column; the weights are live from sheet 1 section 4.
A3: IRIS · Job Architecture & Job Design · Final v1.14 · October 2026 · Internal — Confidential · HR only
A4: Section colours: each column group has its own header colour and a matching light tint | E4: Changed vs current | G4: Level up | H4: Level down · pay & title protected | J4: Newly mapped | K4: Player-Coach · B+ · C+ | M4: RED = critical input needed · says what and who | P4: YELLOW = to complete or edit | R4: GREY = pay · set later
A5: PERSON & KEYS | N5: ROLE — BEFORE → AFTER | AA5: HR PROPOSED — v1.14 · top-down manager rule · department heads in Executive Leadership | AJ5: SCORE — rating × weight = points · weights live from sheet 1 section 4 | BF5: HOW THE LEVEL WAS SET | BO5: JUSTIFICATION FOR EACH RATING — start point, evidence, market standard | BU5: KRAs RECEIVED FROM MANAGERS — as submitted | CB5: WHAT THE EMPLOYEE SHARED IN THE SURVEY — per person | CL5: ROLE PROFILE & BUSINESS IMPACT | CP5: TALENT · manager mapping, succession, critical roles | DA5: COMPETENCY RESULT | DJ5: LEARNING NEEDS | DO5: MOBILITY, OVERLAP & STRUCTURE | DU5: RECRUITMENT — REPLACEMENT PROFILE | DY5: MARKET STANDARD | EF5: INPUTS, DECISIONS & DATA QUALITY | EL5: PAY — set later from the pay survey · left blank | EQ5: VALIDATION — manager & HR | EY5: HR UPDATE — write a change here; it is read back on the next rebuild
A6: Business | B6: Emp ID | C6: Employee name | D6: Department | E6: Role ID · catalogue | F6: Reporting manager | G6: Reporting manager · Emp ID | H6: Reporting manager · final level | I6: Direct reports | J6: Total exp. · yrs | K6: Exp. at IRIS · yrs | L6: Qualification | M6: Emp ID in the source files · where different | N6: Current designation | O6: Final designation | P6: Job family | Q6: Sub-family · what they do | R6: Current level | S6: FINAL LEVEL | T6: Level title | U6: Band | V6: Track | W6: Change vs current | X6: Radford / Mercer code | Y6: Pave level | Z6: SFIA 9 | AA6: HR proposed level · v1.14 | AB6: HR proposed band | AC6: HR proposed level title | AD6: Move vs v1.13 model level | AE6: Manager's HR proposed level | AF6: Manager rule check | AG6: How the HR proposed level was set | AH6: Layer from the CEO | AI6: Job family & sub-family · v1.14 change | AJ6: Weight row — Weightage Matrix | AK6: Complexity rating | AL6: Complexity weight | AM6: Complexity points | AN6: Autonomy rating | AO6: Autonomy weight | AP6: Autonomy points | AQ6: Accountab. rating | AR6: Accountab. weight | AS6: Accountab. points | AT6: Leadership rating | AU6: Leadership weight | AV6: Leadership points | AW6: Exp + Qual rating | AX6: Exp + Qual weight | AY6: Exp + Qual points | AZ6: Bus. Impact rating | BA6: Bus. Impact weight | BB6: Bus. Impact points | BC6: WEIGHTED SCORE = Σ points | BD6: Level the score indicates | BE6: FINAL LEVEL · after the rules | BF6: What set the level | BG6: Why these weights | BH6: Calculation | BI6: Gates, limits & Player-Coach transition steps applied — with the numbers | BJ6: Flags | BK6: Player-Coach / calibration flag | BL6: Confidence | BM6: Points to confirm | BN6: Weight sensitivity | BO6: Complexity & Expertise — justification | BP6: Autonomy & Decision — justification | BQ6: Accountability & Impact — justification | BR6: Leadership & Strategy — justification | BS6: Experience & Qualification — justification | BT6: Business Impact — justification | BU6: KRAs set by manager · annual | BV6: KRAs · quarterly | BW6: KRAs · self-reported annual | BX6: Q1 tentative rating · scale 1-5 | BY6: Actual JD · from manager | BZ6: KRA status | CA6: KRA source | CB6: Survey questions answered · of 20 | CC6: Role mandate & core purpose · as shared | CD6: Deliverables, responsibilities & accountability · as shared | CE6: Capabilities, tools, workload & way of working · as shared | CF6: Development priorities & learning needs · as shared | CG6: Challenges & support required · as shared | CH6: Survey & KRA evidence used for each rating | CI6: Survey themes for this role · role-holders | CJ6: Learning topics named in the survey | CK6: Survey status | CL6: Role profile — what they do, responsibilities & competencies required | CM6: Business impact — from survey and data | CN6: Business impact — from manager / head · to complete | CO6: Bus. Impact — model start | CP6: Latest rating | CQ6: Potential | CR6: 9-box | CS6: Readiness | CT6: Top performer | CU6: Critical role · Y/N | CV6: Successor named | CW6: Succession · C–E roles | CX6: Critical-role risk | CY6: Possible cover · same sub-family | CZ6: Risk action | DA6: Competency index % | DB6: Fit | DC6: Core % | DD6: Future-ready % | DE6: Functional % | DF6: Leadership % | DG6: Top gaps | DH6: Readiness for next level | DI6: Ratings by competency · rating / required | DJ6: Self-identified — topics · survey; not quoted | DK6: Manager-identified | DL6: Role-based priorities | DM6: To move to the next role — topics · survey; not quoted | DN6: Training for next role | DO6: Lateral move options | DP6: Duplication — same business | DQ6: Alternate talent pool — other businesses | DR6: Span status | DS6: Span action | DT6: Org health & A3 notes | DU6: Replacement — what they do · simple | DV6: Hire equivalent · external market | DW6: Competencies & skill level to hire for | DX6: Interview questions for the perfect fit | DY6: Market standard for this role and level | DZ6: IRIS experience guide | EA6: Market experience · Accenture · Infosys | EB6: Typical market title based on competitor/market benchmark | EC6: Competitors, regtech & SaaS leaders | ED6: Professional standard | EE6: Required capability · Core · Future · Functional · Leadership | EF6: ADDITIONAL INPUTS NEEDED — what, and who provides it | EG6: Data used for this person | EH6: Open decisions | EI6: Data requests | EJ6: Data gaps | EK6: Data quality | EL6: Current fixed pay · annual CTC | EM6: Proposed range — minimum | EN6: Proposed range — midpoint | EO6: Proposed range — maximum | EP6: Compa-ratio | EQ6: Manager validation | ER6: Manager comment / proposed change | ES6: HR decision | ET6: Approved level | EU6: Approved designation | EV6: Pay / title protection · Y/N | EW6: Reviewer | EX6: Decision date | EY6: Field to update | EZ6: New value | FA6: Reason | FB6: Source | FC6: Updated by | FD6: Date
A7: CARBON | B7: IRIS0391 | C7: Anuradha RK | D7: CARBON Business Head | E7: RC-EL-BH-D2 | F7: Dixit Jasani | G7: IRIS2478 | H7: E1 | I7: 9 | J7: 17.1 | K7: 16.4 | L7: MBA | N7: Business Head | O7: Business Head | P7: Executive Leadership | Q7: Business Head | R7: Not in current mapping files | S7: D2 | T7: Senior Vice President / Business Head | U7: D | V7: People Manager | W7: ● Newly mapped | X7: E3–E4 | Y7: SVP | Z7: 7 Set strategy | AA7: D2 | AB7: Band D · Business leadership | AC7: Senior Vice President / Business Head | AD7: • Same as the model | AE7: E1 | AF7: OK | AG7: No change · already below the manager | AH7: 2 | AI7: Department head · moved to Executive Leadership · Business Head; was Executive Leadership · Business & Functional Leadership | AJ7: CARBON · CARBON Business Head · Bands D–E · Leadership | AK7: 9 | AL7: =IFERROR(INDEX(WM_C,MATCH($AJ7,WM_KEY,0)),"") -> 0.37 | AM7: =IF(OR(AK7="",AL7=""),"",AK7*AL7) -> 3.33 | AN7: 9 | AO7: =IFERROR(INDEX(WM_AU,MATCH($AJ7,WM_KEY,0)),"") -> 0.19 | AP7: =IF(OR(AN7="",AO7=""),"",AN7*AO7) -> 1.71 | AQ7: 9 | AR7: =IFERROR(INDEX(WM_AC,MATCH($AJ7,WM_KEY,0)),"") -> 0.11 | AS7: =IF(OR(AQ7="",AR7=""),"",AQ7*AR7) -> 0.99 | AT7: 9 | AU7: =IFERROR(INDEX(WM_L,MATCH($AJ7,WM_KEY,0)),"") -> 0.2 | AV7: =IF(OR(AT7="",AU7=""),"",AT7*AU7) -> 1.8 | AW7: 9.5 | AX7: =IFERROR(INDEX(WM_E,MATCH($AJ7,WM_KEY,0)),"") -> 0.05 | AY7: =IF(OR(AW7="",AX7=""),"",AW7*AX7) -> 0.475 | AZ7: 9 | BA7: =IFERROR(INDEX(WM_BI,MATCH($AJ7,WM_KEY,0)),"") -> 0.08 | BB7: =IF(OR(AZ7="",BA7=""),"",AZ7*BA7) -> 0.72 | BC7: =IF(COUNT(AM7,AP7,AS7,AV7,AY7,BB7)<6,"",SUM(AM7,AP7,AS7,AV7,AY7,BB7)) -> 9.025 | BD7: =IF(BC7="","",INDEX({"A1","A2","A3","B1","B2","B3","C1","C2","D1","D2","E1","E2"},MAX(1,MIN(12,ROUND(BC7,0))))) -> D1 | BE7: D2 | BF7: Rule: R11 leadership decision | BG7: Weights: Complexity 37% · Leadership 20% · Autonomy 19% · Accountability 11% · Business impact 8% · Experience 5% Why: leaders are judged on the hardest problems, on leading — 20% — and on the decisions, scope and business impact of the job. Type of work in the department: no adjustment at this level. Live: change the department's row on the Weightage Matrix and these weights, the points and the score update. | BH7: At build: Complexity 3.33 + Autonomy 1.71 + Accountability 0.99 + Leadership 1.80 + Experience 0.48 + Business impact 0.72 = 9.03 points → nearest level 9 = D1 Final level: D2 · a rule applied: see the next column | BI7: • Set at D2 by leadership decision · the model indicated D1: Leadership structure: CARBON Business Head at D2. Final level: D2. | BJ7: Input needed | BL7: Low | BM7: • CARBON Leadership Scorecard row 6 describes sales/implementation ownership for Anuradha, while the master says Business Head. Confirm full-business versus commercial-capability mandate and identity of the abbreviated reference • No survey answers or KRA — the role factors rest on designation and reporting lines only | BN7: Moves in 30 of 30 weight tests · calibrate first | BO7: Rated 9 of 12 Start: 9.0 · business head / director title Evidence: no survey answers or KRAs on file → rating stays at the start Market: D1 = Competing strategic, financial and regulatory priorities | BP7: Rated 9 of 12 Start: 9.0 · business head / director title Evidence: no survey answers or KRAs on file → rating stays at the start Market: D1 = Sets business-line direction, pricing and investment | BQ7: Rated 9 of 12 Start: 9.0 · business head / director title; 9 direct reports, 166 people in the organisation Evidence: no survey answers or KRAs on file → rating stays at the start Market: D1 = Business-line P&L and market position | BR7: Rated 9 of 12 Start: 9.0 Evidence: no survey answers or KRAs on file → rating stays at the start Team: 9 direct reports · People Manager Market: D1 = Defines business strategy; builds the leadership bench | BS7: Rated 9.5 of 12 · between D1 and D2 Experience: 17.1 yrs total · 0.7 before IRIS + 16.4 at IRIS = 8.9 on the experience scale Qualification: MBA · postgraduate, relevant to the work → +0.5 | BT7: Rated 9 of 12 — a starting estimate. Start: 9, the role's accountability scope — what it answers for. No survey or manager-mapping signal on criticality: kept at the start point. Managers and heads: overwrite this rating on the Weightage sheet with the business impact you see — the score updates at once. Ladder: D1 = Owns a business line's P&L and growth, or a company-wide function | BU7: KRAs not received · manager to supply | BZ7: KRAs not received · manager to supply | CB7: 0 | CC7: No survey response on file | CD7: — | CE7: — | CF7: — | CG7: — | CH7: Complexity: Evidence: no survey answers or KRAs on file → rating stays at the start Autonomy: Evidence: no survey answers or KRAs on file → rating stays at the start Accountability: Evidence: no survey answers or KRAs on file → rating stays at the start Leadership: Evidence: no survey answers or KRAs on file → rating stays at the start Business Impact: No survey or manager-mapping signal on criticality: kept at the start point. | CK7: No survey response on file | CL7: WHAT THE ROLE DOES: Owns a business line or enterprise function end to end. At D2: several business lines or an executive-scope enterprise function. KEY RESPONSIBILITIES: Owns a business line or enterprise function end to end; Portfolio-level strategic, financial and regulatory trade-offs; Multi-business results DELIVERS: Multi-business results DECIDES ALONE: Sets direction across business lines SKILLS & KNOWLEDGE · role-holders: Product Management COMPETENCIES REQUIRED — must-have ★: Strategic Thinking & Business Acumen · People Leadership & Mentoring OTHER FUNCTIONAL COMPETENCIES: Stakeholder & Client Management · Product, Platform & Domain Knowledge · Regulatory & BFSI Domain · Communication & Presentation PROFICIENCY NEEDED AT THIS LEVEL: Core 5 · Future-ready 4 · Functional 4 · Leadership 5 CREDENTIALS: MBA / PGDM · preferred at C+ SOURCE: Framework only · fewer than 3 answered — 3 holders, 0 answered the survey; sub-family 0 answered; catalogue RC-091 | CM7: What the role answers for: Multi-business results. Accountability & Impact rating: 9 of 12 · D1-level impact. Leads 9 direct reports. Manager talent mapping — Latest rating: Not rated · manager · 9-Box Grid placement: Not placed · manager. | CO7: 9 | CP7: Not rated · manager | CQ7: — | CR7: Not placed · manager | CS7: No rating data | CW7: Succession: Ready-now successor · ready now Vijay Parulekar · C1, CARBON, Shashikant Mudaliar · C1, CARBON · in 6–12 months Anushree Aparajit · C1, CARBON · high potential — | DB7: Not assessed — no survey or KRA evidence | DI7: Required at D1: Core 5 · Future-ready 4 · Functional Business acumen 4 · People leadership 4 · Stakeholder mgmt 4 · Product & domain 4 · Regulatory domain 4 · Communication 4 · Leadership 5 — rate in manager validation using sheet 4. | DL7: Strategic Thinking & Business Acumen | DP7: No survey text | DQ7: No survey text | DR7: Within norm | DU7: Business Head in CARBON Business Head · CARBON, D2 — People Manager. The work: Owns a business line or enterprise function end to end. At this level the role owns several business lines or an executive-scope enterprise function. Key responsibilities: Owns a business line or enterprise function end to end; Portfolio-level strategic, financial and regulatory trade-offs; Multi-business results. Leads 9 direct reports. | DV7: Hire as: Associate Vice President — IRIS D2 Vice President · People Manager Market level: E3–E4 · SFIA 7 Set strategy Experience: 18–24 yrs · Education: Postgraduate / professional qualification Team size at this level: 5–8 AVPs / heads Equivalent titles at peers: IRIS Vs Market Benchmark — Aon Radford / Mercer executive codes – E3–E4 SVP · IRIS Vs Competitor Benchmark — regtech / SaaS executive titles – SVP Credentials: MBA / PGDM · preferred at C+ Must already know: Governance, risk and regulatory accountability | DW7: FUNCTIONAL — skill level 4 of 5 · Advanced ★ Strategic Thinking & Business Acumen: Shapes strategy, pricing or investment choices ★ People Leadership & Mentoring: Leads leaders; builds succession • Stakeholder & Client Management: Owns key relationships; resolves escalations • Product, Platform & Domain Knowledge: Recognised product / domain expert; trains others • Regulatory & BFSI Domain: Interprets new regulation; advises clients and product • Communication & Presentation: Presents to senior stakeholders; shapes messaging CORE — skill level 5 of 5 · Expert • Ownership & Accountability: Owns business outcomes; builds a culture of accountability • Problem Solving & Critical Thinking: Frames enterprise-level problems; sets the approach for others • Communication & Collaboration: Represents IRIS externally; builds cross-business partnerships • Client & Quality Focus: Defines client and quality strategy for a business • Learning Agility & Adaptability: Anticipates change; builds a learning organisation • Integrity, Compliance & Information Security: Sets ethical and compliance standards for the business FUTURE-READY — skill level 4 of 5 · Advanced • AI Literacy & Augmentation: Designs AI-enabled processes for a team; sets safe-use practices • Data Literacy & Analytics: Defines metrics and dashboards for a team • Digital Fluency & Automation: Automates team processes; selects tools • Innovation & Continuous Improvement: Leads improvement initiatives for a team LEADERSHIP — skill level 5 of 5 · Expert • Leading & Developing People: Builds the leadership pipeline and culture • Decision Making & Delegation: Makes enterprise / business-line decisions • Strategic & Business Acumen: Sets business strategy and P&L direction • Influence & Change Leadership: Leads enterprise change; influences clients, regulators and partners SKILLS · from role-holders and HRIS: Product Management ★ = must-have for the family. Scale: 1 Awareness · 2 Working · 3 Practitioner · 4 Advanced · 5 Expert. | DX7: Draft — generated from the framework; hiring-manager review pending · HR Super Master, sheet T5. 1. [Strategic Thinking & Business Acumen · level 4] Tell me about recent work that shows this: "Shapes strategy, pricing or investment choices". What exactly did you do, how, and what was the result? Assess with: Case interview. 2. [People Leadership & Mentoring · level 4] Tell me about recent work that shows this: "Leads leaders; builds succession". What exactly did you do, how, and what was the result? Assess with: Behavioural interview. 3. [Stakeholder & Client Management · level 4] Give an example that shows you can do this: "Owns key relationships; resolves escalations". Assess with: Role play / behavioural interview. 4. [Product, Platform & Domain Knowledge · level 4] Give an example that shows you can do this: "Recognised product / domain expert; trains others". Assess with: Scenario interview. 5. [Regulatory & BFSI Domain · level 4] Give an example that shows you can do this: "Interprets new regulation; advises clients and product". Assess with: Domain interview. 6. [Ownership & Accountability · level 5] Describe a time you held a team to a standard on an outcome that mattered to the business. How did you make ownership stick? Listen for: "Owns business outcomes; builds a culture of accountability". 7. [Problem Solving & Critical Thinking · level 5] Tell me about an ambiguous, high-stakes problem with no clear answer. How did you frame it and decide? Listen for: "Frames enterprise-level problems; sets the approach for others". 8. [Client & Quality Focus · level 5] Describe how you raised quality or client outcomes across a team or service. How did you measure it? Listen for: "Defines client and quality strategy for a business". 9. [AI Literacy & Augmentation · level 4] Where have you introduced AI or automation into a team's work, and how did you manage the risks? Listen for: "Designs AI-enabled processes for a team; sets safe-use practices". 10. [Leading & Developing People · level 5] Tell me about building a team: who you hired, how you developed them, and a difficult people decision you made. Listen for: "Builds the leadership pipeline and culture". 11. [Decision Making & Delegation · level 5] Tell me about a decision you delegated and one you kept. Why, and what happened? Listen for: "Makes enterprise / business-line decisions". 12. [Strategic & Business Acumen · level 5] Tell me about a strategy or plan you shaped. What trade-offs did you make, and what was the business result? Listen for: "Sets business strategy and P&L direction". 13. [Influence & Change Leadership · level 5] Describe a change you led across teams or the business. How did you deal with resistance? Listen for: "Leads enterprise change; influences clients, regulators and partners". Fit check: Why this role, why IRIS · regulatory reporting / XBRL / regtech, and what would you change in your first 90 days? | DY7: Market level: E3–E4 · SFIA 7 Set strategy Typical title: Associate Vice President At peers: IRIS Vs Market Benchmark — Aon Radford / Mercer executive codes: E3–E4 SVP · IRIS Vs Competitor Benchmark — regtech / SaaS executive titles: SVP Standard: Aon Radford executive levels E1–E6; Mercer ET1–ET3 | DZ7: 18–24 yrs | EA7: — | EB7: Associate Vice President | EC7: IRIS Vs Market Benchmark — Aon Radford / Mercer executive codes: E3–E4 SVP · IRIS Vs Competitor Benchmark — regtech / SaaS executive titles: SVP | ED7: Aon Radford executive levels E1–E6; Mercer ET1–ET3; Korn Ferry Leadership Architect | EE7: Core 5 · Future 4 · Functional 4 · Leadership 5 | EF7: • Survey response or KRAs describing the work · nothing on file — Employee + manager • Resolve conflicting role records — Business head | EG7: ✓ HRIS: 17.1 yrs, MBA, 9 direct reports ✗ Survey: no response ✗ KRAs: none on file ✓ Manager mapping: rating, 9-box ✗ Job description: not on file ✓ Validated inputs: Approved level: D1 → D2 · Leadership structure: CARBON Business Head at D2 · Leadership decision · HR review of 9 Oct 2026 · 2026-10-09 | EH7: D129 · Title to review · Low: Check title against ladder · owner HR · D287 · Input needed · Medium: • Survey response or KRAs describing the work · nothing on file — Employee + manager • Resolve conflicting role records — Business head · owner Employee + manager · Business head · | EI7: R001 · Survey response or KRAs describing the work · nothing on file · Employee + manager · Open R002 · Resolve conflicting role records · Business head · Open | EJ7: Survey response or KRAs describing the work · nothing on file · Employee + manager Resolve conflicting role records · Business head | EK7: Survey: no response · KRAs: not received · Experience: on file
A8: CARBON | B8: IRIS2478 | C8: Dixit Jasani | D8: CRO - Carbon | E8: RC-EL-BH-E1 | F8: Balachandran K | G8: IRIS0001 | H8: E2 | I8: 1 | J8: 27.9 | K8: 0.6 | L8: PGDM | N8: Chief Revenue Officer- Enterprise Division | O8: Chief Revenue Officer | P8: Executive Leadership | Q8: Business Head | R8: Not in current mapping files | S8: E1 | T8: CXO / President | U8: E | V8: People Manager | W8: ● Newly mapped | X8: E5 | Y8: C-Level | Z8: 7 | AA8: E1 | AB8: Band E · Enterprise leadership | AC8: CXO / President | AD8: • Same as the model | AE8: E2 | AF8: Exception · Band E | AG8: Band E with Band E · agreed exception · manager E2 | AH8: 1 | AI8: Department head · moved to Executive Leadership · Business Head; was Executive Leadership · Enterprise Leadership | AJ8: CARBON · CRO - Carbon · Bands D–E · Leadership | AK8: 11 | AL8: =IFERROR(INDEX(WM_C,MATCH($AJ8,WM_KEY,0)),"") -> 0.37 | AM8: =IF(OR(AK8="",AL8=""),"",AK8*AL8) -> 4.07 | AN8: 11 | AO8: =IFERROR(INDEX(WM_AU,MATCH($AJ8,WM_KEY,0)),"") -> 0.19 | AP8: =IF(OR(AN8="",AO8=""),"",AN8*AO8) -> 2.09 | AQ8: 11 | AR8: =IFERROR(INDEX(WM_AC,MATCH($AJ8,WM_KEY,0)),"") -> 0.11 | AS8: =IF(OR(AQ8="",AR8=""),"",AQ8*AR8) -> 1.21 | AT8: 11 | AU8: =IFERROR(INDEX(WM_L,MATCH($AJ8,WM_KEY,0)),"") -> 0.2 | AV8: =IF(OR(AT8="",AU8=""),"",AT8*AU8) -> 2.2 | AW8: 12 | AX8: =IFERROR(INDEX(WM_E,MATCH($AJ8,WM_KEY,0)),"") -> 0.05 | AY8: =IF(OR(AW8="",AX8=""),"",AW8*AX8) -> 0.6 | AZ8: 11 | BA8: =IFERROR(INDEX(WM_BI,MATCH($AJ8,WM_KEY,0)),"") -> 0.08 | BB8: =IF(OR(AZ8="",BA8=""),"",AZ8*BA8) -> 0.88 | BC8: =IF(COUNT(AM8,AP8,AS8,AV8,AY8,BB8)<6,"",SUM(AM8,AP8,AS8,AV8,AY8,BB8)) -> 11.05 | BD8: =IF(BC8="","",INDEX({"A1","A2","A3","B1","B2","B3","C1","C2","D1","D2","E1","E2"},MAX(1,MIN(12,ROUND(BC8,0))))) -> E1 | BE8: E1 | BF8: The score decided the level | BG8: Weights: Complexity 37% · Leadership 20% · Autonomy 19% · Accountability 11% · Business impact 8% · Experience 5% Why: leaders are judged on the hardest problems, on leading — 20% — and on the decisions, scope and business impact of the job. Type of work in the department: no adjustment at this level. Live: change the department's row on the Weightage Matrix and these weights, the points and the score update. | BH8: At build: Complexity 4.07 + Autonomy 2.09 + Accountability 1.21 + Leadership 2.20 + Experience 0.60 + Business impact 0.88 = 11.05 points → nearest level 11 = E1 Final level: E1 · same as the score | BI8: No rule applied: the score decides. | BJ8: Input needed | BL8: Low | BM8: • CARBON Leadership Scorecard row 8 describes marketing/partnerships with no ARR ownership for Dixit, unlike the CRO designation. Confirm actual mandate and identity of the abbreviated reference • No survey answers or KRA — the role factors rest on designation and reporting lines only | BN8: Stable · moves in fewer than 5 of 30 weight tests | BO8: Rated 11 of 12 Start: 11.0 · CXO title Evidence: no survey answers or KRAs on file → rating stays at the start Market: E1 = Enterprise-level functional strategy | BP8: Rated 11 of 12 Start: 11.0 · CXO title Evidence: no survey answers or KRAs on file → rating stays at the start Market: E1 = Sets enterprise priorities for the function | BQ8: Rated 11 of 12 Start: 11.0 · CXO title; 1 direct report, 167 people in the organisation Evidence: no survey answers or KRAs on file → rating stays at the start Market: E1 = Enterprise-wide functional results | BR8: Rated 11 of 12 Start: 11.0 Evidence: no survey answers or KRAs on file → rating stays at the start Team: 1 direct report · People Manager Market: E1 = Shapes enterprise strategy | BS8: Rated 12 of 12 Experience: 27.9 yrs total · 27.3 before IRIS + 0.6 at IRIS = 12.0 on the experience scale Qualification: PGDM · postgraduate, relevant to the work → +0.5 | BT8: Rated 11 of 12 — a starting estimate. Start: 11, the role's accountability scope — what it answers for. No survey or manager-mapping signal on criticality: kept at the start point. Managers and heads: overwrite this rating on the Weightage sheet with the business impact you see — the score updates at once. Ladder: E1 = Shapes company-wide results through a function | BU8: KRAs not received · manager to supply | BZ8: KRAs not received · manager to supply | CB8: 0 | CC8: No survey response on file | CD8: — | CE8: — | CF8: — | CG8: — | CH8: Complexity: Evidence: no survey answers or KRAs on file → rating stays at the start Autonomy: Evidence: no survey answers or KRAs on file → rating stays at the start Accountability: Evidence: no survey answers or KRAs on file → rating stays at the start Leadership: Evidence: no survey answers or KRAs on file → rating stays at the start Business Impact: No survey or manager-mapping signal on criticality: kept at the start point. | CK8: No survey response on file | CL8: WHAT THE ROLE DOES: Sets enterprise strategy; leads the executive team. At E1: an enterprise-wide function. KEY RESPONSIBILITIES: Sets enterprise strategy; leads the executive team; Enterprise-level functional strategy; Enterprise-wide functional results DELIVERS: Enterprise-wide functional results DECIDES ALONE: Sets enterprise priorities for the function SKILLS & KNOWLEDGE · role-holders: Management · Sales COMPETENCIES REQUIRED — must-have ★: Strategic Thinking & Business Acumen · People Leadership & Mentoring OTHER FUNCTIONAL COMPETENCIES: Stakeholder & Client Management · Product, Platform & Domain Knowledge · Regulatory & BFSI Domain · Communication & Presentation PROFICIENCY NEEDED AT THIS LEVEL: Core 5 · Future-ready 5 · Functional 4 · Leadership 5 CREDENTIALS: MBA / PGDM · preferred at C+ SOURCE: Framework only · fewer than 3 answered — 4 holders, 0 answered the survey; sub-family 0 answered; catalogue RC-092 | CM8: What the role answers for: Enterprise-wide functional results. Accountability & Impact rating: 11 of 12 · E1-level impact. Leads 1 direct report. Manager talent mapping — Latest rating: Not rated · manager · 9-Box Grid placement: Not placed · manager. | CO8: 11 | CP8: Not rated · manager | CQ8: — | CR8: Not placed · manager | CS8: No rating data | CW8: Succession: No successor identified · ready now — · in 6–12 months — · high potential — | DB8: Not assessed — no survey or KRA evidence | DI8: Required at E1: Core 5 · Future-ready 5 · Functional Business acumen 4 · People leadership 4 · Stakeholder mgmt 4 · Product & domain 4 · Regulatory domain 4 · Communication 4 · Leadership 5 — rate in manager validation using sheet 4. | DL8: Strategic Thinking & Business Acumen | DP8: No survey text | DQ8: No survey text | DR8: Below norm | DT8: Span: 1 direct reports · layer 2 · Very small team: merge with a neighbouring team or make a POD Lead role | DU8: Chief Revenue Officer in CRO - Carbon · CARBON, E1 — People Manager. The work: Sets enterprise strategy; leads the executive team. At this level the role owns an enterprise-wide function. Key responsibilities: Sets enterprise strategy; leads the executive team; Enterprise-level functional strategy; Enterprise-wide functional results. Leads 1 direct report. | DV8: Hire as: CXO · functional chief — IRIS E1 CXO / President · People Manager Market level: E5 · SFIA 7 Experience: 20+ yrs · Education: Postgraduate / professional qualification Team size at this level: 5–8 function heads Equivalent titles at peers: IRIS Vs Market Benchmark — Aon Radford / Mercer executive codes – E5 C-level · functional · IRIS Vs Competitor Benchmark — regtech / SaaS executive titles – CTO · CFO · CRO · CCO · COO Credentials: MBA / PGDM · preferred at C+ Must already know: Governance, risk and regulatory accountability | DW8: FUNCTIONAL — skill level 4 of 5 · Advanced ★ Strategic Thinking & Business Acumen: Shapes strategy, pricing or investment choices ★ People Leadership & Mentoring: Leads leaders; builds succession • Stakeholder & Client Management: Owns key relationships; resolves escalations • Product, Platform & Domain Knowledge: Recognised product / domain expert; trains others • Regulatory & BFSI Domain: Interprets new regulation; advises clients and product • Communication & Presentation: Presents to senior stakeholders; shapes messaging CORE — skill level 5 of 5 · Expert • Ownership & Accountability: Owns business outcomes; builds a culture of accountability • Problem Solving & Critical Thinking: Frames enterprise-level problems; sets the approach for others • Communication & Collaboration: Represents IRIS externally; builds cross-business partnerships • Client & Quality Focus: Defines client and quality strategy for a business • Learning Agility & Adaptability: Anticipates change; builds a learning organisation • Integrity, Compliance & Information Security: Sets ethical and compliance standards for the business FUTURE-READY — skill level 5 of 5 · Expert • AI Literacy & Augmentation: Leads AI strategy and governance for a function or IRIS • Data Literacy & Analytics: Sets data strategy and data-driven decisions for a business • Digital Fluency & Automation: Drives digital transformation across a business • Innovation & Continuous Improvement: Creates new products, methods or business models LEADERSHIP — skill level 5 of 5 · Expert • Leading & Developing People: Builds the leadership pipeline and culture • Decision Making & Delegation: Makes enterprise / business-line decisions • Strategic & Business Acumen: Sets business strategy and P&L direction • Influence & Change Leadership: Leads enterprise change; influences clients, regulators and partners SKILLS · from role-holders and HRIS: Management · Sales ★ = must-have for the family. Scale: 1 Awareness · 2 Working · 3 Practitioner · 4 Advanced · 5 Expert. | DX8: Draft — generated from the framework; hiring-manager review pending · HR Super Master, sheet T5. 1. [Strategic Thinking & Business Acumen · level 4] Tell me about recent work that shows this: "Shapes strategy, pricing or investment choices". What exactly did you do, how, and what was the result? Assess with: Case interview. 2. [People Leadership & Mentoring · level 4] Tell me about recent work that shows this: "Leads leaders; builds succession". What exactly did you do, how, and what was the result? Assess with: Behavioural interview. 3. [Stakeholder & Client Management · level 4] Give an example that shows you can do this: "Owns key relationships; resolves escalations". Assess with: Role play / behavioural interview. 4. [Product, Platform & Domain Knowledge · level 4] Give an example that shows you can do this: "Recognised product / domain expert; trains others". Assess with: Scenario interview. 5. [Regulatory & BFSI Domain · level 4] Give an example that shows you can do this: "Interprets new regulation; advises clients and product". Assess with: Domain interview. 6. [Ownership & Accountability · level 5] Describe a time you held a team to a standard on an outcome that mattered to the business. How did you make ownership stick? Listen for: "Owns business outcomes; builds a culture of accountability". 7. [Problem Solving & Critical Thinking · level 5] Tell me about an ambiguous, high-stakes problem with no clear answer. How did you frame it and decide? Listen for: "Frames enterprise-level problems; sets the approach for others". 8. [Client & Quality Focus · level 5] Describe how you raised quality or client outcomes across a team or service. How did you measure it? Listen for: "Defines client and quality strategy for a business". 9. [AI Literacy & Augmentation · level 5] Where have you introduced AI or automation into a team's work, and how did you manage the risks? Listen for: "Leads AI strategy and governance for a function or IRIS". 10. [Leading & Developing People · level 5] Tell me about building a team: who you hired, how you developed them, and a difficult people decision you made. Listen for: "Builds the leadership pipeline and culture". 11. [Decision Making & Delegation · level 5] Tell me about a decision you delegated and one you kept. Why, and what happened? Listen for: "Makes enterprise / business-line decisions". 12. [Strategic & Business Acumen · level 5] Tell me about a strategy or plan you shaped. What trade-offs did you make, and what was the business result? Listen for: "Sets business strategy and P&L direction". 13. [Influence & Change Leadership · level 5] Describe a change you led across teams or the business. How did you deal with resistance? Listen for: "Leads enterprise change; influences clients, regulators and partners". Fit check: Why this role, why IRIS · regulatory reporting / XBRL / regtech, and what would you change in your first 90 days? | DY8: Market level: E5 · SFIA 7 Typical title: CXO · functional chief At peers: IRIS Vs Market Benchmark — Aon Radford / Mercer executive codes: E5 C-level · functional · IRIS Vs Competitor Benchmark — regtech / SaaS executive titles: CTO · CFO · CRO · CCO · COO Standard: Aon Radford executive levels E1–E6; Mercer ET1–ET3 | DZ8: 20+ yrs | EA8: — | EB8: CXO · functional chief | EC8: IRIS Vs Market Benchmark — Aon Radford / Mercer executive codes: E5 C-level · functional · IRIS Vs Competitor Benchmark — regtech / SaaS executive titles: CTO · CFO · CRO · CCO · COO | ED8: Aon Radford executive levels E1–E6; Mercer ET1–ET3; Korn Ferry Leadership Architect | EE8: Core 5 · Future 5 · Functional 4 · Leadership 5 | EF8: • Survey response or KRAs describing the work · nothing on file — Employee + manager • Resolve conflicting role records — Business head | EG8: ✓ HRIS: 27.9 yrs, PGDM, 1 direct report ✗ Survey: no response ✗ KRAs: none on file ✓ Manager mapping: rating, 9-box ✗ Job description: not on file | EH8: D288 · Input needed · Medium: • Survey response or KRAs describing the work · nothing on file — Employee + manager • Resolve conflicting role records — Business head · owner Employee + manager · Business head · | EI8: R003 · Survey response or KRAs describing the work · nothing on file · Employee + manager · Open R004 · Resolve conflicting role records · Business head · Open | EJ8: Survey response or KRAs describing the work · nothing on file · Employee + manager Resolve conflicting role records · Business head | EK8: Survey: no response · KRAs: not received · Experience: on file
A9: CARBON | B9: IRIS2359 | C9: Suman Adhikary | D9: Customer Experience | E9: RC-EL-BH-D1 | F9: Anuradha RK | G9: IRIS0391 | H9: D2 | I9: 8 | J9: 28.7 | K9: 1.5 | L9: B.E | N9: Senior Vice President - Customer Experience | O9: Senior Vice President – Customer Experience | P9: Executive Leadership | Q9: Business Head | R9: Not in current mapping files | S9: D1 | T9: Associate Vice President | U9: D | V9: People Manager | W9: ● Newly mapped | X9: E1–E2 | Y9: VP | Z9: 6–7 | AA9: C2 | AB9: Band C · Principal / Head | AC9: Head of Function | AD9: ▼ Down · pay and title protected | AE9: D2 | AF9: OK | AG9: Band rule: manager D2 is a head in Band D · Business leadership; a reportee sits in a lower band · D1 → C2 · move down · pay and title protected for one cycle | AH9: 3 | AI9: Department head · moved to Executive Leadership · Business Head; was Executive Leadership · Business & Functional Leadership | AJ9: CARBON · Customer Experience · Bands D–E · Leadership | AK9: 10 | AL9: =IFERROR(INDEX(WM_C,MATCH($AJ9,WM_KEY,0)),"") -> 0.37 | AM9: =IF(OR(AK9="",AL9=""),"",AK9*AL9) -> 3.7 | AN9: 10 | AO9: =IFERROR(INDEX(WM_AU,MATCH($AJ9,WM_KEY,0)),"") -> 0.19 | AP9: =IF(OR(AN9="",AO9=""),"",AN9*AO9) -> 1.9 | AQ9: 10 | AR9: =IFERROR(INDEX(WM_AC,MATCH($AJ9,WM_KEY,0)),"") -> 0.11 | AS9: =IF(OR(AQ9="",AR9=""),"",AQ9*AR9) -> 1.1 | AT9: 10 | AU9: =IFERROR(INDEX(WM_L,MATCH($AJ9,WM_KEY,0)),"") -> 0.2 | AV9: =IF(OR(AT9="",AU9=""),"",AT9*AU9) -> 2 | AW9: 12 | AX9: =IFERROR(INDEX(WM_E,MATCH($AJ9,WM_KEY,0)),"") -> 0.05 | AY9: =IF(OR(AW9="",AX9=""),"",AW9*AX9) -> 0.6 | AZ9: 10 | BA9: =IFERROR(INDEX(WM_BI,MATCH($AJ9,WM_KEY,0)),"") -> 0.08 | BB9: =IF(OR(AZ9="",BA9=""),"",AZ9*BA9) -> 0.8 | BC9: =IF(COUNT(AM9,AP9,AS9,AV9,AY9,BB9)<6,"",SUM(AM9,AP9,AS9,AV9,AY9,BB9)) -> 10.1 | BD9: =IF(BC9="","",INDEX({"A1","A2","A3","B1","B2","B3","C1","C2","D1","D2","E1","E2"},MAX(1,MIN(12,ROUND(BC9,0))))) -> D2 | BE9: D1 | BF9: Rule: R11 leadership decision | BG9: Weights: Complexity 37% · Leadership 20% · Autonomy 19% · Accountability 11% · Business impact 8% · Experience 5% Why: leaders are judged on the hardest problems, on leading — 20% — and on the decisions, scope and business impact of the job. Type of work in the department: no adjustment at this level. Live: change the department's row on the Weightage Matrix and these weights, the points and the score update. | BH9: At build: Complexity 3.70 + Autonomy 1.90 + Accountability 1.10 + Leadership 2.00 + Experience 0.60 + Business impact 0.80 = 10.10 points → nearest level 10 = D2 Final level: D1 · a rule applied: see the next column | BI9: • Set at D1 by leadership decision · the model indicated D2: Leadership structure: one level below her manager, the CARBON Business Head. Final level: D1. | BJ9: Input needed | BL9: Low | BM9: • CARBON Leadership Scorecard row 7 assigns services/customer-success revenue to Suman. Confirm identity, accountable functions and delegated resources/decision limits before choosing C2/C3/D1 • No survey answers or KRA — the role factors rest on designation and reporting lines only | BN9: Moves in 30 of 30 weight tests · calibrate first | BO9: Rated 10 of 12 Start: 10.0 · vice president title Evidence: no survey answers or KRAs on file → rating stays at the start Market: D2 = Portfolio-level strategic, financial and regulatory trade-offs | BP9: Rated 10 of 12 Start: 10.0 · vice president title Evidence: no survey answers or KRAs on file → rating stays at the start Market: D2 = Sets direction across business lines | BQ9: Rated 10 of 12 Start: 10.0 · vice president title; 8 direct reports, 121 people in the organisation Evidence: no survey answers or KRAs on file → rating stays at the start Market: D2 = Multi-business results | BR9: Rated 10 of 12 Start: 10.0 Evidence: no survey answers or KRAs on file → rating stays at the start Team: 8 direct reports · People Manager Market: D2 = Builds the leadership team across businesses | BS9: Rated 12 of 12 Experience: 28.7 yrs total · 27.2 before IRIS + 1.5 at IRIS = 12.0 on the experience scale Qualification: B.E · graduate → no change | BT9: Rated 10 of 12 — a starting estimate. Start: 10, the role's accountability scope — what it answers for. No survey or manager-mapping signal on criticality: kept at the start point. Managers and heads: overwrite this rating on the Weightage sheet with the business impact you see — the score updates at once. Ladder: D2 = Owns the results of several business lines | BU9: KRAs not received · manager to supply | BZ9: KRAs not received · manager to supply | CB9: 0 | CC9: No survey response on file | CD9: — | CE9: — | CF9: — | CG9: — | CH9: Complexity: Evidence: no survey answers or KRAs on file → rating stays at the start Autonomy: Evidence: no survey answers or KRAs on file → rating stays at the start Accountability: Evidence: no survey answers or KRAs on file → rating stays at the start Leadership: Evidence: no survey answers or KRAs on file → rating stays at the start Business Impact: No survey or manager-mapping signal on criticality: kept at the start point. | CK9: No survey response on file | CL9: WHAT THE ROLE DOES: Owns a business line or enterprise function end to end. At D1: a business line P&L, region or enterprise function. KEY RESPONSIBILITIES: Owns a business line or enterprise function end to end; Competing strategic, financial and regulatory priorities; Business-line P&L and market position DELIVERS: Business-line P&L and market position DECIDES ALONE: Sets business-line direction, pricing and investment SKILLS & KNOWLEDGE · role-holders: Product Management COMPETENCIES REQUIRED — must-have ★: Strategic Thinking & Business Acumen · People Leadership & Mentoring OTHER FUNCTIONAL COMPETENCIES: Stakeholder & Client Management · Product, Platform & Domain Knowledge · Regulatory & BFSI Domain · Communication & Presentation PROFICIENCY NEEDED AT THIS LEVEL: Core 5 · Future-ready 4 · Functional 4 · Leadership 5 CREDENTIALS: MBA / PGDM · preferred at C+ SOURCE: Framework only · fewer than 3 answered — 2 holders, 0 answered the survey; sub-family 0 answered; catalogue RC-090 | CM9: What the role answers for: Business-line P&L and market position. Accountability & Impact rating: 10 of 12 · D2-level impact. Leads 8 direct reports. From the survey and manager mapping — successor named: yes. Manager talent mapping — Latest rating: Not rated · manager · 9-Box Grid placement: Underperformer / Exit Risk. | CO9: 10 | CP9: Not rated · manager | CQ9: — | CR9: Underperformer / Exit Risk | CS9: No rating data | CU9: CARBON | CV9: Customer Experience | CW9: Succession: Ready-now successor · ready now Vijay Parulekar · C1, CARBON, Shashikant Mudaliar · C1, CARBON · in 6–12 months Anushree Aparajit · C1, CARBON · high potential — | DB9: Not assessed — no survey or KRA evidence | DI9: Required at D2: Core 5 · Future-ready 4 · Functional Business acumen 4 · People leadership 4 · Stakeholder mgmt 4 · Product & domain 4 · Regulatory domain 4 · Communication 4 · Leadership 5 — rate in manager validation using sheet 4. | DK9: Client Engagement | DL9: Strategic Thinking & Business Acumen | DN9: No | DP9: No survey text | DQ9: No survey text | DR9: Within norm | DU9: Senior Vice President – Customer Experience in Customer Experience · CARBON, D1 — People Manager. The work: Owns a business line or enterprise function end to end. At this level the role owns a business line P&L, region or enterprise function. Key responsibilities: Owns a business line or enterprise function end to end; Competing strategic, financial and regulatory priorities; Business-line P&L and market position. Leads 8 direct reports. | DV9: Hire as: Vice President / Senior Vice President / Senior Vice President — IRIS D1 Associate Vice President · People Manager Market level: E1–E2 · SFIA 6–7 Experience: 15–20 yrs · Education: Postgraduate / professional qualification Team size at this level: 5–8 heads Equivalent titles at peers: IRIS Vs Market Benchmark — Aon Radford / Mercer executive codes – E1–E2 VP / Business Head · IRIS Vs Competitor Benchmark — regtech / SaaS executive titles – General Manager / VP Credentials: MBA / PGDM · preferred at C+ Must already know: Governance, risk and regulatory accountability | DW9: FUNCTIONAL — skill level 4 of 5 · Advanced ★ Strategic Thinking & Business Acumen: Shapes strategy, pricing or investment choices ★ People Leadership & Mentoring: Leads leaders; builds succession • Stakeholder & Client Management: Owns key relationships; resolves escalations • Product, Platform & Domain Knowledge: Recognised product / domain expert; trains others • Regulatory & BFSI Domain: Interprets new regulation; advises clients and product • Communication & Presentation: Presents to senior stakeholders; shapes messaging CORE — skill level 5 of 5 · Expert • Ownership & Accountability: Owns business outcomes; builds a culture of accountability • Problem Solving & Critical Thinking: Frames enterprise-level problems; sets the approach for others • Communication & Collaboration: Represents IRIS externally; builds cross-business partnerships • Client & Quality Focus: Defines client and quality strategy for a business • Learning Agility & Adaptability: Anticipates change; builds a learning organisation • Integrity, Compliance & Information Security: Sets ethical and compliance standards for the business FUTURE-READY — skill level 4 of 5 · Advanced • AI Literacy & Augmentation: Designs AI-enabled processes for a team; sets safe-use practices • Data Literacy & Analytics: Defines metrics and dashboards for a team • Digital Fluency & Automation: Automates team processes; selects tools • Innovation & Continuous Improvement: Leads improvement initiatives for a team LEADERSHIP — skill level 5 of 5 · Expert • Leading & Developing People: Builds the leadership pipeline and culture • Decision Making & Delegation: Makes enterprise / business-line decisions • Strategic & Business Acumen: Sets business strategy and P&L direction • Influence & Change Leadership: Leads enterprise change; influences clients, regulators and partners SKILLS · from role-holders and HRIS: Product Management ★ = must-have for the family. Scale: 1 Awareness · 2 Working · 3 Practitioner · 4 Advanced · 5 Expert. | DX9: Draft — generated from the framework; hiring-manager review pending · HR Super Master, sheet T5. 1. [Strategic Thinking & Business Acumen · level 4] Tell me about recent work that shows this: "Shapes strategy, pricing or investment choices". What exactly did you do, how, and what was the result? Assess with: Case interview. 2. [People Leadership & Mentoring · level 4] Tell me about recent work that shows this: "Leads leaders; builds succession". What exactly did you do, how, and what was the result? Assess with: Behavioural interview. 3. [Stakeholder & Client Management · level 4] Give an example that shows you can do this: "Owns key relationships; resolves escalations". Assess with: Role play / behavioural interview. 4. [Product, Platform & Domain Knowledge · level 4] Give an example that shows you can do this: "Recognised product / domain expert; trains others". Assess with: Scenario interview. 5. [Regulatory & BFSI Domain · level 4] Give an example that shows you can do this: "Interprets new regulation; advises clients and product". Assess with: Domain interview. 6. [Ownership & Accountability · level 5] Describe a time you held a team to a standard on an outcome that mattered to the business. How did you make ownership stick? Listen for: "Owns business outcomes; builds a culture of accountability". 7. [Problem Solving & Critical Thinking · level 5] Tell me about an ambiguous, high-stakes problem with no clear answer. How did you frame it and decide? Listen for: "Frames enterprise-level problems; sets the approach for others". 8. [Client & Quality Focus · level 5] Describe how you raised quality or client outcomes across a team or service. How did you measure it? Listen for: "Defines client and quality strategy for a business". 9. [AI Literacy & Augmentation · level 4] Where have you introduced AI or automation into a team's work, and how did you manage the risks? Listen for: "Designs AI-enabled processes for a team; sets safe-use practices". 10. [Leading & Developing People · level 5] Tell me about building a team: who you hired, how you developed them, and a difficult people decision you made. Listen for: "Builds the leadership pipeline and culture". 11. [Decision Making & Delegation · level 5] Tell me about a decision you delegated and one you kept. Why, and what happened? Listen for: "Makes enterprise / business-line decisions". 12. [Strategic & Business Acumen · level 5] Tell me about a strategy or plan you shaped. What trade-offs did you make, and what was the business result? Listen for: "Sets business strategy and P&L direction". 13. [Influence & Change Leadership · level 5] Describe a change you led across teams or the business. How did you deal with resistance? Listen for: "Leads enterprise change; influences clients, regulators and partners". Fit check: Why this role, why IRIS · regulatory reporting / XBRL / regtech, and what would you change in your first 90 days? | DY9: Market level: E1–E2 · SFIA 6–7 Typical title: Vice President / Senior Vice President / Senior Vice President At peers: IRIS Vs Market Benchmark — Aon Radford / Mercer executive codes: E1–E2 VP / Business Head · IRIS Vs Competitor Benchmark — regtech / SaaS executive titles: General Manager / VP Standard: Aon Radford executive levels E1–E6; Mercer ET1–ET3 | DZ9: 15–20 yrs | EA9: — | EB9: Vice President / Senior Vice President / Senior Vice President | EC9: IRIS Vs Market Benchmark — Aon Radford / Mercer executive codes: E1–E2 VP / Business Head · IRIS Vs Competitor Benchmark — regtech / SaaS executive titles: General Manager / VP | ED9: Aon Radford executive levels E1–E6; Mercer ET1–ET3; Korn Ferry Leadership Architect | EE9: Core 5 · Future 4 · Functional 4 · Leadership 5 | EF9: • Survey response or KRAs describing the work · nothing on file — Employee + manager • Resolve conflicting role records — Business head | EG9: ✓ HRIS: 28.7 yrs, B.E, 8 direct reports ✗ Survey: no response ✗ KRAs: none on file ✓ Manager mapping: rating, 9-box — filled from talent-mapping files: 9-box · CARBON grid ✗ Job description: not on file ✓ Validated inputs: Approved level: D2 → D1 · Leadership structure: one level below her manager, the CARBON Business Head · Leadership decision · HR review of 9 Oct 2026 · 2026-10-09 | EH9: D130 · Title to review · Low: Check title against ladder · owner HR · D289 · Input needed · Medium: • Survey response or KRAs describing the work · nothing on file — Employee + manager • Resolve conflicting role records — Business head · owner Employee + manager · Business head · | EI9: R005 · Survey response or KRAs describing the work · nothing on file · Employee + manager · Open R006 · Resolve conflicting role records · Business head · Open | EJ9: Survey response or KRAs describing the work · nothing on file · Employee + manager Resolve conflicting role records · Business head | EK9: Survey: no response · KRAs: not received · Experience: on file
A10: CARBON | B10: IRIS0055 | C10: Vijay Parulekar | D10: Digitizing | E10: RC-EL-BH-C1 | F10: K Ashok Kumar | G10: IRIS0018 | H10: C1 | I10: 6 | J10: 26.4 | K10: 19.9 | L10: B.Com | N10: Head Image Processing | O10: Associate Head – Digitization | P10: Executive Leadership | Q10: Business Head | R10: L7 – Head / Sr Director | S10: C1 | T10: Associate Head | U10: C | V10: People Manager | W10: ▼ Down · protected | X10: P6 / M5 | Y10: Principal / Director | Z10: 5–6 | AA10: B2 | AB10: Band B · Specialist / Manager | AC10: Manager | AD10: ▼ Down · pay and title protected | AE10: B3 | AF10: OK | AG10: Level rule: manager B3; a reportee sits at least one level below · C1 → B2 · move down · pay and title protected for one cycle | AH10: 5 | AI10: Department head · moved to Executive Leadership · Business Head; was Data Operations & Digitization · Digitization Leadership | AJ10: CARBON · Digitizing · Band C · Head / Manager | AK10: 7 | AL10: =IFERROR(INDEX(WM_C,MATCH($AJ10,WM_KEY,0)),"") -> 0.38 | AM10: =IF(OR(AK10="",AL10=""),"",AK10*AL10) -> 2.66 | AN10: 7 | AO10: =IFERROR(INDEX(WM_AU,MATCH($AJ10,WM_KEY,0)),"") -> 0.18 | AP10: =IF(OR(AN10="",AO10=""),"",AN10*AO10) -> 1.26 | AQ10: 6.5 | AR10: =IFERROR(INDEX(WM_AC,MATCH($AJ10,WM_KEY,0)),"") -> 0.16 | AS10: =IF(OR(AQ10="",AR10=""),"",AQ10*AR10) -> 1.04 | AT10: 6 | AU10: =IFERROR(INDEX(WM_L,MATCH($AJ10,WM_KEY,0)),"") -> 0.15 | AV10: =IF(OR(AT10="",AU10=""),"",AT10*AU10) -> 0.9 | AW10: 11.5 | AX10: =IFERROR(INDEX(WM_E,MATCH($AJ10,WM_KEY,0)),"") -> 0.05 | AY10: =IF(OR(AW10="",AX10=""),"",AW10*AX10) -> 0.575 | AZ10: 7 | BA10: =IFERROR(INDEX(WM_BI,MATCH($AJ10,WM_KEY,0)),"") -> 0.08 | BB10: =IF(OR(AZ10="",BA10=""),"",AZ10*BA10) -> 0.56 | BC10: =IF(COUNT(AM10,AP10,AS10,AV10,AY10,BB10)<6,"",SUM(AM10,AP10,AS10,AV10,AY10,BB10)) -> 6.995 | BD10: =IF(BC10="","",INDEX({"A1","A2","A3","B1","B2","B3","C1","C2","D1","D2","E1","E2"},MAX(1,MIN(12,ROUND(BC10,0))))) -> C1 | BE10: C1 | BF10: The score decided the level | BG10: Weights: Complexity 38% · Autonomy 18% · Accountability 16% · Leadership 15% · Business impact 8% · Experience 5% Why: a head answers for a function through managers: Leadership 15%, with autonomy, accountability and impact rising; expertise still counts most. Type of work in the department: delivery work is judged on accuracy and turnaround, so Accountability +5 and Complexity −5. Live: change the department's row on the Weightage Matrix and these weights, the points and the score update. | BH10: At build: Complexity 2.66 + Autonomy 1.26 + Accountability 1.04 + Leadership 0.90 + Experience 0.58 + Business impact 0.56 = 7.00 points → nearest level 7 = C1 Final level: C1 · same as the score | BI10: No rule applied: the score decides. | BJ10: Down — protected | BL10: High | BM10: • Work described is smaller than the current designation suggests — manager to confirm the actual role • Final level C1 is below the current level · L7 ≈ C2 — manager to confirm the scope of the role; pay and title are protected for one cycle | BN10: Stable · moves in fewer than 5 of 30 weight tests | BO10: Rated 7 of 12 Start: 8.0 · head-of-function title Evidence reads like B1: Plans formatting deliveries across all markets and two teams; process improvement; InDesign demos → moved down 1 KRA: “1. Ensure files processed by team with >=99% accuracy · zero critical errors. 2. Meet 100% of regulatory / client filing deadlines · no SLA…” Market: C1 = Ambiguous, cross-product problems | BP10: Rated 7 of 12 Start: 8.0 · head-of-function title Evidence reads like B2: Allocates workload and priority files; operational decisions on routine work → moved down 1 Market: C1 = Sets direction for a sub-function or domain | BQ10: Rated 6.5 of 12 · between B3 and C1 Start: 7.5 · head-of-function title; 6 direct reports, 32 people below, 4 of them lead teams Evidence reads like B2: Accountable for all work of the Carbon Formatting and RBI CMS team → moved down 1 KRA: “1. Ensure files processed by team with >=99% accuracy · zero critical errors. 2. Meet 100% of regulatory / client filing deadlines · no SLA…” Market: B3 = Several teams or a practice · C1 = Sub-function results or domain quality across products | BR10: Rated 6 of 12 Start: 7.0 Evidence reads like B2: Manages team with 6 reports: allocation, monitoring, guiding and training → moved down 1 Team: 6 direct reports · People Manager Market: B3 = IC: leads a practice · People: team leads / managers report in | BS10: Rated 11.5 of 12 · between E1 and E2 Experience: 26.4 yrs total · 6.5 before IRIS + 19.9 at IRIS = 11.6 on the experience scale Qualification: B.Com · graduate, relevant to the work → no change Market: C1 roles typically have 12–17 yrs · IRIS guide 10–14 | BT10: Rated 7 of 12 — a starting estimate. Start: 6.5, the role's accountability scope — what it answers for. Moved +0.5: the survey / manager mapping marks it business-critical. Managers and heads: overwrite this rating on the Weightage sheet with the business impact you see — the score updates at once. Ladder: C1 = Changes results across a sub-function or across products | BU10: 1. Ensure files processed by team with >=99% accuracy · zero critical errors. 2. Meet 100% of regulatory / client filing deadlines · no SLA breaches 3. Reduce average filing turnaround time by 10-20% by this year. 4. Identify and develop future team leads. 5. Deliver zero escalations from key clients. 6. Launch AI-assisted formatting/tagging and review suggestion engine · Give Logic to Engineering Team and Test it whenever developed | BZ10: Received · manager annual | CA10: CARBON Mapping Master | CB10: 20 | CC10: • Role / sub-team: Digitizing Assisted Services. | CD10: • Key responsibilities include: Monitoring deliveries of all Markets. Preparing demos in InDesign if any. Checking resource allocation. Making sure timely delivery. • Reported deliverables and outcomes include: Daily Status Tracker, Allocation of Priority Files. • Additional duties outside usual job: Inter department Inter Team work.; Data extraction for Datatech team. Reports downloading for AI Testing team. | CE10: • Current capabilities: Use of AI for problem sol; Team management skiil; Tools / software used: Both | InDesign, Abbyy FineReader, Microsoft Web Expression. | CF10: • Development priorities: AI promoting. • Learning and Development Need: Communication and Presentation. XBRL Tagging Process and Domain Knowledge. • AI Enablement Need: AI prompt engineering and using AI to increase efficiency, given their reported use of AI. | CG10: • Key challenges: Quality of report. • Support required: No input received. | CH10: Complexity: Evidence reads like B1: Plans formatting deliveries across all markets and two teams; process improvement; InDesign demos → moved down 1 Autonomy: Evidence reads like B2: Allocates workload and priority files; operational decisions on routine work → moved down 1 Accountability: Evidence reads like B2: Accountable for all work of the Carbon Formatting and RBI CMS team → moved down 1 Leadership: Evidence reads like B2: Manages team with 6 reports: allocation, monitoring, guiding and training → moved down 1 Business Impact: Moved +0.5: the survey / manager mapping marks it business-critical. | CJ10: Self-identified: Product & tool knowledge · Broader exposure & ownership For the next role: Product & tool knowledge · Broader exposure & ownership | CK10: Per-person summary · CARBON Mapping Master | CL10: WHAT THE ROLE DOES: Leads the data operations & digitization function. At C1: a sub-function, or principal authority across products. KEY RESPONSIBILITIES: Leads the data operations & digitization function; Ambiguous, cross-product problems; Sub-function results or domain quality across products DELIVERS: Sub-function results or domain quality across products DECIDES ALONE: Sets direction for a sub-function or domain COMPETENCIES REQUIRED — must-have ★: Advanced Excel & Productivity Tools · Process Improvement & Quality Mindset OTHER FUNCTIONAL COMPETENCIES: Regulatory & BFSI Domain · XBRL, iXBRL & Taxonomy · AI, GenAI & Prompt Engineering · Time, Priority & Self-Management PROFICIENCY NEEDED AT THIS LEVEL: Core 4 · Future-ready 4 · Functional 4 · Leadership 4 CREDENTIALS: MOS Excel · optional; Lean / Six Sigma · optional SOURCE: Framework only · fewer than 3 answered — 1 holder, 1 answered the survey; sub-family 1 answered; catalogue RC-045 | CM10: What the role answers for: Sub-function results or domain quality across products. Accountability & Impact rating: 6.5 of 12 · B3-level impact. Leads 6 direct reports. From the survey and manager mapping — critical role: yes; successor named: no. Manager talent mapping — Latest rating: 4 · Potential: High · 9-Box Grid placement: Core Contributor. | CO10: 7 | CP10: 4 | CQ10: High | CR10: Core Contributor | CS10: Ready now | CU10: Yes | CW10: Succession: Ready-now successor · ready now Janardan Bale · B2, CARBON, Dinesh Sharma · B1, CARBON, Prajakta Mokal · B1, CARBON, Tejas Kat · B1, CARBON, Ritesh Yeram · B1, CARBON, Shraddha Patil · B2, Consume · in 6–12 months — · high potential — | CX10: High · critical role Yes · only this person — · successor named No | CY10: No one in the same sub-family at or near this level — external hire or develop | CZ10: Name a successor this quarter; document the process; start cross-training the cover listed | DA10: 102 | DB10: Meets the level | DC10: 106 | DD10: 105 | DE10: 95 | DF10: 105 | DG10: XBRL & taxonomy, Prioritisation, Problem solving | DH10: C2: 97% of profile — ready on competencies | DI10: Evidence: Survey + KRAs | Core: Ownership 5/4, Problem solving 3/4, Communication & collaboration 5/4, Client & quality focus 5/4, Learning agility 4/4, Integrity & compliance 4/4 | Future-ready: AI literacy 4/4, Data literacy 5/4, Digital fluency 4/4, Innovation 4/4 | Functional: Excel & tools 5/4, Quality & process 4/4, Regulatory domain 4/4, XBRL & taxonomy 3/4, AI / GenAI 4/4, Prioritisation 3/4 | Leadership: Developing people 5/4, Decision making 4/4, Strategic acumen 4/4, Influence & change 4/4 | DJ10: Product & tool knowledge · Broader exposure & ownership | DL10: AI, GenAI & Prompt Engineering; People Leadership & Mentoring; Strategic Thinking & Business Acumen | DM10: Product & tool knowledge · Broader exposure & ownership | DO10: No strong match from survey evidence | DP10: Justeen Koola · Digitization Associate — 0.43: abby, finereader, improvement, expression; Saurav Nirmal · Senior Digitization Associate — 0.34: applications., formatting, abby, finereader; Aishwarya Chaulkar · Senior Digitization Associate — 0.34: applications., abby, finereader, expression | DQ10: No close match in other businesses | DR10: Within norm | DU10: Associate Head – Digitization in Digitizing · CARBON, C1 — People Manager. The work: Leads the data operations & digitization function. At this level the role owns a sub-function, or principal authority across products. Key responsibilities: Leads the data operations & digitization function; Ambiguous, cross-product problems; Sub-function results or domain quality across products. Leads 6 direct reports. | DV10: Hire as: Head of Function / AGM — IRIS C1 Associate Head · People Manager Market level: P6 / M5 · SFIA 5–6 Experience: 10–14 yrs · Education: Graduate · commerce preferred Team size at this level: 5–8, mostly managers Equivalent titles at peers: Accenture Operations – L6 Senior Manager · IRIS Vs Competitor Benchmark — operations roles – Head of Delivery Credentials: MOS Excel · optional; Lean / Six Sigma · optional Must already know: Accuracy and SLA discipline; data confidentiality | DW10: FUNCTIONAL — skill level 4 of 5 · Advanced ★ Advanced Excel & Productivity Tools: Builds templates and automation used by the team ★ Process Improvement & Quality Mindset: Redesigns team processes; reduces error rates measurably • Regulatory & BFSI Domain: Interprets new regulation; advises clients and product • XBRL, iXBRL & Taxonomy: Resolves complex tagging and taxonomy issues; builds extensions; reviews others • AI, GenAI & Prompt Engineering: Builds AI features or AI-enabled processes; sets safe-use practice • Time, Priority & Self-Management: Plans team capacity and peak-season loads CORE — skill level 4 of 5 · Advanced • Ownership & Accountability: Owns team / practice outcomes; holds others to standards • Problem Solving & Critical Thinking: Solves complex, ambiguous problems; designs new approaches • Communication & Collaboration: Influences through communication; resolves conflict • Client & Quality Focus: Sets quality standards; improves client experience for a team • Learning Agility & Adaptability: Leads others through change; builds team capability • Integrity, Compliance & Information Security: Embeds compliance and security in team processes FUTURE-READY — skill level 4 of 5 · Advanced • AI Literacy & Augmentation: Designs AI-enabled processes for a team; sets safe-use practices • Data Literacy & Analytics: Defines metrics and dashboards for a team • Digital Fluency & Automation: Automates team processes; selects tools • Innovation & Continuous Improvement: Leads improvement initiatives for a team LEADERSHIP — skill level 4 of 5 · Advanced • Leading & Developing People: Leads leaders; builds bench strength • Decision Making & Delegation: Makes cross-team trade-offs; delegates authority • Strategic & Business Acumen: Shapes functional strategy, budget and market approach • Influence & Change Leadership: Influences senior stakeholders; leads function-wide change ★ = must-have for the family. Scale: 1 Awareness · 2 Working · 3 Practitioner · 4 Advanced · 5 Expert. | DX10: Draft — generated from the framework; hiring-manager review pending · HR Super Master, sheet T5. 1. [Advanced Excel & Productivity Tools · level 4] Tell me about recent work that shows this: "Builds templates and automation used by the team". What exactly did you do, how, and what was the result? Assess with: Practical test. 2. [Process Improvement & Quality Mindset · level 4] Tell me about recent work that shows this: "Redesigns team processes; reduces error rates measurably". What exactly did you do, how, and what was the result? Assess with: Work sample / case. 3. [Regulatory & BFSI Domain · level 4] Give an example that shows you can do this: "Interprets new regulation; advises clients and product". Assess with: Domain interview. 4. [XBRL, iXBRL & Taxonomy · level 4] Give an example that shows you can do this: "Resolves complex tagging and taxonomy issues; builds extensions; reviews others". Assess with: Tagging test on a real filing. 5. [AI, GenAI & Prompt Engineering · level 4] Give an example that shows you can do this: "Builds AI features or AI-enabled processes; sets safe-use practice". Assess with: Work sample / portfolio. 6. [Ownership & Accountability · level 4] Describe a time you held a team to a standard on an outcome that mattered to the business. How did you make ownership stick? Listen for: "Owns team / practice outcomes; holds others to standards". 7. [Problem Solving & Critical Thinking · level 4] Tell me about an ambiguous, high-stakes problem with no clear answer. How did you frame it and decide? Listen for: "Solves complex, ambiguous problems; designs new approaches". 8. [Client & Quality Focus · level 4] Describe how you raised quality or client outcomes across a team or service. How did you measure it? Listen for: "Sets quality standards; improves client experience for a team". 9. [AI Literacy & Augmentation · level 4] Where have you introduced AI or automation into a team's work, and how did you manage the risks? Listen for: "Designs AI-enabled processes for a team; sets safe-use practices". 10. [Leading & Developing People · level 4] Tell me about building a team: who you hired, how you developed them, and a difficult people decision you made. Listen for: "Leads leaders; builds bench strength". 11. [Decision Making & Delegation · level 4] Tell me about a decision you delegated and one you kept. Why, and what happened? Listen for: "Makes cross-team trade-offs; delegates authority". 12. [Strategic & Business Acumen · level 4] Tell me about a strategy or plan you shaped. What trade-offs did you make, and what was the business result? Listen for: "Shapes functional strategy, budget and market approach". 13. [Influence & Change Leadership · level 4] Describe a change you led across teams or the business. How did you deal with resistance? Listen for: "Influences senior stakeholders; leads function-wide change". Fit check: Why this role, why IRIS · regulatory reporting / XBRL / regtech, and what would you change in your first 90 days? | DY10: Market level: P6 / M5 · SFIA 5–6 Typical title: Head of Function / AGM At peers: Accenture Operations – L6 Senior Manager · IRIS Vs Competitor Benchmark — operations roles: Head of Delivery Typical experience: 12–17 yrs · IRIS guide 10–14 Standard: COPC CX Standard; ISO 9001 | DZ10: 10–14 yrs | EA10: 12–16 · 12–18 | EB10: Head of Function / AGM | EC10: Accenture Operations: L6 Senior Manager · IRIS Vs Competitor Benchmark — operations roles: Head of Delivery | ED10: COPC CX Standard · leadership & planning, people, processes, performance; ISO 9001; Lean / Six Sigma | EE10: Core 4 · Future 4 · Functional 4 · Leadership 4 | EG10: ✓ HRIS: 26.4 yrs, B.Com, 6 direct reports ✓ Survey: 20 of 20 questions answered ✓ KRAs: submitted, reported deliverables ✓ Manager mapping: rating, potential, 9-box ✗ Job description: not on file | EH10: D081 · Move down · protected · High: Current L7 – Head / Sr Director → C1. No rule changed the level: the score decides. · owner HR · | EK10: Survey: summary on file · KRAs: received · Experience: on file
A11: CARBON | B11: IRIS0470 | C11: Janardan Bale | D11: Digitizing | E11: RC-050 | F11: Vijay Parulekar | G11: IRIS0055 | H11: C1 | I11: 6 | J11: 18 | K11: 18 | L11: B.Com | N11: Image Processing Specialist | O11: Digitization Manager | P11: Data Operations & Digitization | Q11: Document Conversion, Formatting & Web Publishing | R11: L3 – Professional / Associate | S11: B2 | T11: Manager | U11: B | V11: People Manager | W11: ▲ Up | X11: P4 / M3 | Y11: Senior / Manager | Z11: 4–5 | AA11: B1 | AB11: Band B · Specialist / Manager | AC11: Team Lead / Asst Manager | AD11: ▼ Down · pay and title protected | AE11: B2 | AF11: OK | AG11: Level rule: manager B2; a reportee sits at least one level below · B2 → B1 · move down · pay and title protected for one cycle | AH11: 6 | AJ11: CARBON · Digitizing · Band B · People Manager | AK11: 3.5 | AL11: =IFERROR(INDEX(WM_C,MATCH($AJ11,WM_KEY,0)),"") -> 0.32 | AM11: =IF(OR(AK11="",AL11=""),"",AK11*AL11) -> 1.12 | AN11: 4.5 | AO11: =IFERROR(INDEX(WM_AU,MATCH($AJ11,WM_KEY,0)),"") -> 0.18 | AP11: =IF(OR(AN11="",AO11=""),"",AN11*AO11) -> 0.81 | AQ11: 5 | AR11: =IFERROR(INDEX(WM_AC,MATCH($AJ11,WM_KEY,0)),"") -> 0.16 | AS11: =IF(OR(AQ11="",AR11=""),"",AQ11*AR11) -> 0.8 | AT11: 5.5 | AU11: =IFERROR(INDEX(WM_L,MATCH($AJ11,WM_KEY,0)),"") -> 0.15 | AV11: =IF(OR(AT11="",AU11=""),"",AT11*AU11) -> 0.825 | AW11: 9 | AX11: =IFERROR(INDEX(WM_E,MATCH($AJ11,WM_KEY,0)),"") -> 0.1 | AY11: =IF(OR(AW11="",AX11=""),"",AW11*AX11) -> 0.9 | AZ11: 5.5 | BA11: =IFERROR(INDEX(WM_BI,MATCH($AJ11,WM_KEY,0)),"") -> 0.09 | BB11: =IF(OR(AZ11="",BA11=""),"",AZ11*BA11) -> 0.495 | BC11: =IF(COUNT(AM11,AP11,AS11,AV11,AY11,BB11)<6,"",SUM(AM11,AP11,AS11,AV11,AY11,BB11)) -> 4.95 | BD11: =IF(BC11="","",INDEX({"A1","A2","A3","B1","B2","B3","C1","C2","D1","D2","E1","E2"},MAX(1,MIN(12,ROUND(BC11,0))))) -> B2 | BE11: B2 | BF11: The score decided the level | BG11: Weights: Complexity 32% · Autonomy 18% · Accountability 16% · Leadership 15% · Experience 10% · Business impact 9% Why: a manager's results come through the team, so Leadership rises to 15% and Complexity falls; autonomy, accountability and impact rise. Type of work in the department: delivery work is judged on accuracy and turnaround, so Accountability +5 and Complexity −5. Live: change the department's row on the Weightage Matrix and these weights, the points and the score update. | BH11: At build: Complexity 1.12 + Autonomy 0.81 + Accountability 0.80 + Leadership 0.82 + Experience 0.90 + Business impact 0.49 = 4.95 points → nearest level 5 = B2 Final level: B2 · same as the score | BI11: No rule applied: the score decides. | BJ11: Input needed | BL11: Medium | BM11: • Reporting lines show a much bigger role than the designation suggests — confirm the mandate; the designation may need to change • Final level B2 is 3 levels above the current level on record · L3 ≈ A2 — the record looks out of date; HR to confirm | BN11: Stable · moves in fewer than 5 of 30 weight tests | BO11: Rated 3.5 of 12 · between A3 and B1 Start: 4.0 · senior practitioner title; reporting lines show a bigger role: 6 direct reports, 8 people below, 1 of them leads a team Evidence reads like A3: Go-to for US DM / HTML Editor: solves unsolved issues, QCs HMRC, CIPC, MCA → moved down 0.5 KRA: “1. Complete assigned conversion/formatting tasks with >=99% accuracy · zero critical errors 2. Meet 100% of client filing deadlines · no SLA…” Market: A3 = Varied and non-standard work; handles exceptions · B1 = Domain specialist work | BP11: Rated 4.5 of 12 · between B1 and B2 Start: 5.0 · senior practitioner title; reporting lines show a bigger role: 6 direct reports, 8 people below, 1 of them leads a team Evidence reads like B1: Allocates HMRC and CIPC documents among team members and delivers → moved down 0.5 Market: B1 = Technical / QC / client calls for the domain · B2 = Allocates people and sets team priorities | BQ11: Rated 5 of 12 Start: 6.0 · senior practitioner title; 6 direct reports, 8 people below, 1 of them leads a team Evidence reads like B1: Leads US formatting team's output as team leader; own answer cites document confidentiality → moved down 1 KRA: “1. Complete assigned conversion/formatting tasks with >=99% accuracy · zero critical errors 2. Meet 100% of client filing deadlines · no SLA…” Market: B2 = One team or a client portfolio | BR11: Rated 5.5 of 12 · between B2 and B3 Start: 6.0 Evidence reads like B2: Team leader of US formatting team with 6 reports; trains new joiners → moved down 0.5 Team: 6 direct reports · People Manager Market: B2 = IC: guides others in the domain · People: manages a team of 6+ · B3 = IC: leads a practice · People: team leads / managers report in | BS11: Rated 9 of 12 Experience: 18.0 yrs total · 18.0 at IRIS; none recorded before IRIS = 9.1 on the experience scale Qualification: B.Com · graduate, relevant to the work → no change Market: B2 roles typically have 6–10 yrs · IRIS guide 6–9 | BT11: Rated 5.5 of 12 — a starting estimate. Start: 5, the role's accountability scope — what it answers for. Moved +0.5: the survey / manager mapping marks it business-critical. Managers and heads: overwrite this rating on the Weightage sheet with the business impact you see — the score updates at once. Ladder: B2 = Visible effect on a team's or client portfolio's revenue, quality or compliance · B3 = Shapes the results of a practice or several teams | BU11: 1. Complete assigned conversion/formatting tasks with >=99% accuracy · zero critical errors 2. Meet 100% of client filing deadlines · no SLA breaches 3. Maintain average turnaround per assignment within agreed TAT 4. Handle assigned client edits within agreed TAT with client. 5. Develop capabilities to work in more than 2 mandates/products. Ultimate goal should be able to work in all OCR/Formatting mandates. 6. Conduct monthly knowledge sessions in order to Cross-skill team: >=70% capable on at least more than two OCR/Formatting mandates | BZ11: Received · manager annual | CA11: CARBON Mapping Master | CB11: 20 | CC11: • Role / sub-team: Digitalizing Assisted Services Team. | CD11: • Key responsibilities include: Formatting & Review in US DM & Carbon Editor Allocation & Query Solving HTML QC of HMRC project QC of CIPC & MCA project. • Reported deliverables and outcomes include: US files go to the US Assisted Service Team after final formatting and review; MCA, CIPC and UK files go for tagging after QC. | CE11: • Current capabilities: Typing; Ai tool - Copilot Chat GP; Tools / software used: Both. | CF11: • Communications skills. • Presentation skills. | CG11: • Key challenges: Quality of report, RDP issue. • Support required: No input received. | CH11: Complexity: Evidence reads like A3: Go-to for US DM / HTML Editor: solves unsolved issues, QCs HMRC, CIPC, MCA → moved down 0.5 Autonomy: Evidence reads like B1: Allocates HMRC and CIPC documents among team members and delivers → moved down 0.5 Accountability: Evidence reads like B1: Leads US formatting team's output as team leader; own answer cites document confidentiality → moved down 1 Leadership: Evidence reads like B2: Team leader of US formatting team with 6 reports; trains new joiners → moved down 0.5 Business Impact: Moved +0.5: the survey / manager mapping marks it business-critical. | CI11: Common themes in sub-family holders, all levels' answers: purpose · core · formatting · quality · rbi · website Common themes in sub-family holders, all levels' answers: quality · document · formatting · html · accuracy · conversion Common themes in sub-family holders, all levels' answers: html · pdf · word · deliver · formatted · documents Common themes in sub-family holders, all levels' answers: am · accountable · accuracy · quality · every · formatting Common themes in sub-family holders, all levels' answers: formatting · independently · html · validate · allocate · cipc If the work is missed · role-holders' themes: rework · delays · errors · quality · incorrect. | CJ11: Self-identified: Product & tool knowledge · Communication & presentation · Certification / formal course For the next role: Product & tool knowledge · Communication & presentation · Certification / formal course | CK11: Per-person summary · CARBON Mapping Master | CL11: WHAT THE ROLE DOES: Converts and formats documents into HTML/PDF/Word to filing or web standards, and publishes content · incl. RBI website. At B2: deep domain expertise, or one team. Common themes in sub-family holders, all levels' answers: purpose · core · formatting · quality · rbi · website KEY RESPONSIBILITIES: Converts and formats documents into HTML/PDF/Word to filing or web standards, and publishes content · incl. RBI website; Hardest problems in the domain; One team or a client portfolio Common themes in sub-family holders, all levels' answers: quality · document · formatting · html · accuracy · conversion DELIVERS: One team or a client portfolio Common themes in sub-family holders, all levels' answers: html · pdf · word · deliver · formatted · documents ACCOUNTABLE FOR: One team or a client portfolio Common themes in sub-family holders, all levels' answers: am · accountable · accuracy · quality · every · formatting DECIDES ALONE: Allocates people and sets team priorities Common themes in sub-family holders, all levels' answers: formatting · independently · html · validate · allocate · cipc SKILLS & KNOWLEDGE · role-holders: OCR/Image procesing · attention to detail · quality checking · Excel · timely delivery · HTML · Word · ABYYY Fine Reader TOOLS & SYSTEMS: Excel · Office 365 word · Carbon applications · Abby FineReader · Web Expression HTML editor · DM · HTML Editor · US DM - Carbon COMPETENCIES REQUIRED — must-have ★: Advanced Excel & Productivity Tools · Process Improvement & Quality Mindset OTHER FUNCTIONAL COMPETENCIES: Regulatory & BFSI Domain · XBRL, iXBRL & Taxonomy · AI, GenAI & Prompt Engineering · Time, Priority & Self-Management PROFICIENCY NEEDED AT THIS LEVEL: Core 3 · Future-ready 3 · Functional 4 · Leadership 3 CREDENTIALS: MOS Excel · optional; Lean / Six Sigma · optional SOURCE: Framework + sub-family themes · 3+ answered — 2 holders, 2 answered the survey; sub-family 30 answered; catalogue RC-050 | CM11: What the role answers for: One team or a client portfolio. Accountability & Impact rating: 5 of 12 · B2-level impact. Leads 6 direct reports. From the survey and manager mapping — critical role: yes; successor named: no. If the work is missed · role-holders' themes: rework · delays · errors · quality · incorrect. Manager talent mapping — Latest rating: 5 · Potential: High · 9-Box Grid placement: Core Contributor. | CO11: 5.5 | CP11: 5 | CQ11: High | CR11: Core Contributor | CS11: Ready now | CT11: Yes | CU11: Yes | CX11: Medium · critical role Yes · only this person — · successor named No | CY11: Dinesh Sharma · B1, CARBON · Prajakta Mokal · B1, CARBON · Ritesh Yeram · B1, CARBON | CZ11: Name a successor; document the key process; cross-train one person | DA11: 104 | DB11: Meets the level | DC11: 113 | DD11: 105 | DE11: 102 | DF11: 97 | DG11: AI / GenAI, Prioritisation, Strategic acumen | DH11: B3: 93% of profile — ready on competencies | DI11: Evidence: Survey + KRAs | Core: Ownership 5/3, Problem solving 4/3, Communication & collaboration 4/3, Client & quality focus 5/3, Learning agility 3/3, Integrity & compliance 3/3 | Future-ready: AI literacy 3/3, Data literacy 4/3, Digital fluency 3/3, Innovation 3/3 | Functional: Excel & tools 5/4, Quality & process 5/4, Regulatory domain 5/4, XBRL & taxonomy 4/4, AI / GenAI 3/4, Prioritisation 3/4 | Leadership: Developing people 4/3, Decision making 3/3, Strategic acumen 2/3, Influence & change 3/3 | DJ11: Product & tool knowledge · Communication & presentation · Certification / formal course | DL11: XBRL, iXBRL & Taxonomy; Product, Platform & Domain Knowledge | DM11: Product & tool knowledge · Communication & presentation · Certification / formal course | DO11: No strong match from survey evidence | DP11: Dhanraj Patil · Senior Digitization Associate — 0.77: abyyy, accuracy., hmrc, expression; Snehal Kardekar · Senior Digitization Associate — 0.48: formatting, html, expression, editor; Ritesh Yeram · Digitization Associate — 0.43: html, expression, hmrc, formatting | DQ11: Siddhesh Harishchandra Mali · Consume, Digitization Associate — 0.27 | DR11: Below norm | DS11: Team smaller than the norm for this level — merge with a peer team, widen scope, or treat as a POD Lead. | DU11: Digitization Manager in Digitizing · CARBON, B2 — People Manager. The work: Converts and formats documents into HTML/PDF/Word to filing or web standards, and publishes content · incl. RBI website. At this level the role owns deep domain expertise, or one team. Key responsibilities: Converts and formats documents into HTML/PDF/Word to filing or web standards, and publishes content · incl. RBI website; Hardest problems in the domain; One team or a client portfolio. Holders describe it with: quality · document · formatting · html · accuracy · conversion. Leads 6 direct reports. | DV11: Hire as: Manager — IRIS B2 Manager · People Manager Market level: P4 / M3 · SFIA 4–5 Experience: 6–9 yrs · Education: Graduate · commerce preferred Team size at this level: IC: none · People: 6–8 knowledge work, 8–12 standardised delivery Equivalent titles at peers: Accenture Operations – L8 Associate Manager · IRIS Vs Competitor Benchmark — operations roles – Operations Manager Credentials: MOS Excel · optional; Lean / Six Sigma · optional Must already know: Accuracy and SLA discipline; data confidentiality | DW11: FUNCTIONAL — skill level 4 of 5 · Advanced ★ Advanced Excel & Productivity Tools: Builds templates and automation used by the team ★ Process Improvement & Quality Mindset: Redesigns team processes; reduces error rates measurably • Regulatory & BFSI Domain: Interprets new regulation; advises clients and product • XBRL, iXBRL & Taxonomy: Resolves complex tagging and taxonomy issues; builds extensions; reviews others • AI, GenAI & Prompt Engineering: Builds AI features or AI-enabled processes; sets safe-use practice • Time, Priority & Self-Management: Plans team capacity and peak-season loads CORE — skill level 3 of 5 · Practitioner • Ownership & Accountability: Owns a module, client or process end to end; fixes root causes • Problem Solving & Critical Thinking: Analyses non-routine problems; finds root causes • Communication & Collaboration: Communicates with clients / stakeholders; collaborates across teams • Client & Quality Focus: Anticipates client needs; prevents errors in own area • Learning Agility & Adaptability: Adapts to changing priorities; learns independently • Integrity, Compliance & Information Security: Spots and escalates compliance / security risks FUTURE-READY — skill level 3 of 5 · Practitioner • AI Literacy & Augmentation: Builds AI into own workflow; evaluates accuracy and bias • Data Literacy & Analytics: Analyses data · SQL, BI, advanced Excel to find insight • Digital Fluency & Automation: Automates own repetitive work · macros, scripts, workflows • Innovation & Continuous Improvement: Delivers measurable improvements in own area LEADERSHIP — skill level 3 of 5 · Practitioner • Leading & Developing People: Leads a team; coaches and gives feedback • Decision Making & Delegation: Decides team priorities and resourcing • Strategic & Business Acumen: Plans team work against business goals and budgets • Influence & Change Leadership: Influences across teams; leads local change SKILLS · from role-holders and HRIS: OCR/Image procesing · attention to detail · quality checking · Excel · timely delivery · HTML · Word · ABYYY Fine Reader TOOLS: Excel · Office 365 word · Carbon applications · Abby FineReader · Web Expression HTML editor · DM · HTML Editor · US DM - Carbon ★ = must-have for the family. Scale: 1 Awareness · 2 Working · 3 Practitioner · 4 Advanced · 5 Expert. | DX11: Draft — generated from the framework; hiring-manager review pending · HR Super Master, sheet T5. 1. [Advanced Excel & Productivity Tools · level 4] Tell me about recent work that shows this: "Builds templates and automation used by the team". What exactly did you do, how, and what was the result? Assess with: Practical test. 2. [Process Improvement & Quality Mindset · level 4] Tell me about recent work that shows this: "Redesigns team processes; reduces error rates measurably". What exactly did you do, how, and what was the result? Assess with: Work sample / case. 3. [Regulatory & BFSI Domain · level 4] Give an example that shows you can do this: "Interprets new regulation; advises clients and product". Assess with: Domain interview. 4. [XBRL, iXBRL & Taxonomy · level 4] Give an example that shows you can do this: "Resolves complex tagging and taxonomy issues; builds extensions; reviews others". Assess with: Tagging test on a real filing. 5. [AI, GenAI & Prompt Engineering · level 4] Give an example that shows you can do this: "Builds AI features or AI-enabled processes; sets safe-use practice". Assess with: Work sample / portfolio. 6. [Ownership & Accountability · level 3] Tell me about a piece of work you owned from start to finish. What went wrong, and what did you do about it? Listen for: "Owns a module, client or process end to end; fixes root causes". 7. [Problem Solving & Critical Thinking · level 3] Walk me through a problem you solved recently: how did you find the root cause and choose the fix? Listen for: "Analyses non-routine problems; finds root causes". 8. [Client & Quality Focus · level 3] Tell me about a time a client or user was unhappy with your work. What did you do? Listen for: "Anticipates client needs; prevents errors in own area". 9. [AI Literacy & Augmentation · level 3] Show me how you have used an AI tool in your work. How did you check its output? Listen for: "Builds AI into own workflow; evaluates accuracy and bias". 10. [Leading & Developing People · level 3] Tell me about helping a colleague or junior get better at something. Listen for: "Leads a team; coaches and gives feedback". 11. [Decision Making & Delegation · level 3] Give an example of a decision you made on your own. How did you know it was yours to make? Listen for: "Decides team priorities and resourcing". 12. [Strategic & Business Acumen · level 3] How does your work connect to how IRIS makes money or serves regulators and clients? Listen for: "Plans team work against business goals and budgets". 13. [Influence & Change Leadership · level 3] Tell me about persuading someone to change how they worked, without authority over them. Listen for: "Influences across teams; leads local change". Fit check: Why this role, why IRIS · regulatory reporting / XBRL / regtech, and what would you change in your first 90 days? | DY11: Market level: P4 / M3 · SFIA 4–5 Typical title: Manager At peers: Accenture Operations – L8 Associate Manager · IRIS Vs Competitor Benchmark — operations roles: Operations Manager Typical experience: 6–10 yrs · IRIS guide 6–9 Standard: COPC CX Standard; ISO 9001 | DZ11: 6–9 yrs | EA11: 7–10 · 6–11 | EB11: Manager | EC11: Accenture Operations: L8 Associate Manager · IRIS Vs Competitor Benchmark — operations roles: Operations Manager | ED11: COPC CX Standard · leadership & planning, people, processes, performance; ISO 9001; Lean / Six Sigma | EE11: Core 3 · Future 3 · Functional 4 · Leadership 3 | EF11: • Confirm the reporting line — Manager | EG11: ✓ HRIS: 18.0 yrs, B.Com, 6 direct reports ✓ Survey: 20 of 20 questions answered ✓ KRAs: submitted, reported deliverables ✓ Manager mapping: rating, potential, 9-box ✗ Job description: not on file | EH11: D291 · Input needed · Medium: • Confirm the reporting line — Manager · owner Manager · | EI11: R007 · Confirm the reporting line · Manager · Open | EJ11: Confirm the reporting line · Manager | EK11: Survey: summary on file · KRAs: received · Experience: on file
A12: CARBON | B12: IRIS1005 | C12: Datta Hatagale | D12: Digitizing | E12: RC-039 | F12: Vijay Parulekar | G12: IRIS0055 | H12: C1 | I12: 3 | J12: 14.9 | K12: 14.9 | L12: BA | N12: Image Processing Specialist | O12: Customer Enablement Specialist – POD Lead | P12: Customer Success & Support | Q12: Customer Training & Enablement | R12: L3 – Professional / Associate | S12: B1 | T12: Specialist · POD Lead | U12: B | V12: POD Lead | W12: ▲ Up | X12: P3 / M2 | Y12: Career / · Team Lead | Z12: 4 Enable | AA12: B1 | AB12: Band B · Specialist / Manager | AC12: Team Lead / Asst Manager | AD12: • Same as the model | AE12: B2 | AF12: OK | AG12: No change · already below the manager | AH12: 6 | AJ12: CARBON · Digitizing · Band B · Expert / POD Lead | AK12: 3 | AL12: =IFERROR(INDEX(WM_C,MATCH($AJ12,WM_KEY,0)),"") -> 0.46 | AM12: =IF(OR(AK12="",AL12=""),"",AK12*AL12) -> 1.38 | AN12: 3 | AO12: =IFERROR(INDEX(WM_AU,MATCH($AJ12,WM_KEY,0)),"") -> 0.17 | AP12: =IF(OR(AN12="",AO12=""),"",AN12*AO12) -> 0.51 | AQ12: 3.5 | AR12: =IFERROR(INDEX(WM_AC,MATCH($AJ12,WM_KEY,0)),"") -> 0.15 | AS12: =IF(OR(AQ12="",AR12=""),"",AQ12*AR12) -> 0.525 | AT12: 3.5 | AU12: =IFERROR(INDEX(WM_L,MATCH($AJ12,WM_KEY,0)),"") -> 0.05 | AV12: =IF(OR(AT12="",AU12=""),"",AT12*AU12) -> 0.175 | AW12: 8 | AX12: =IFERROR(INDEX(WM_E,MATCH($AJ12,WM_KEY,0)),"") -> 0.1 | AY12: =IF(OR(AW12="",AX12=""),"",AW12*AX12) -> 0.8 | AZ12: 4 | BA12: =IFERROR(INDEX(WM_BI,MATCH($AJ12,WM_KEY,0)),"") -> 0.07 | BB12: =IF(OR(AZ12="",BA12=""),"",AZ12*BA12) -> 0.28 | BC12: =IF(COUNT(AM12,AP12,AS12,AV12,AY12,BB12)<6,"",SUM(AM12,AP12,AS12,AV12,AY12,BB12)) -> 3.67 | BD12: =IF(BC12="","",INDEX({"A1","A2","A3","B1","B2","B3","C1","C2","D1","D2","E1","E2"},MAX(1,MIN(12,ROUND(BC12,0))))) -> B1 | BE12: B1 | BF12: The score decided the level | BG12: Weights: Complexity 46% · Autonomy 17% · Accountability 15% · Experience 10% · Business impact 7% · Leadership 5% Why: specialists are judged mainly on depth of expertise, then on what they decide alone, what they answer for and their impact. Type of work in the department: delivery work is judged on accuracy and turnaround, so Accountability +5 and Complexity −5. Live: change the department's row on the Weightage Matrix and these weights, the points and the score update. | BH12: At build: Complexity 1.38 + Autonomy 0.51 + Accountability 0.53 + Leadership 0.18 + Experience 0.80 + Business impact 0.28 = 3.67 points → nearest level 4 = B1 Final level: B1 · same as the score | BI12: No rule applied: the score decides. | BJ12: — | BL12: Low | BM12: • Survey answers are generic or do not match the role — not used as evidence; manager input needed | BN12: Stable · moves in fewer than 5 of 30 weight tests | BO12: Rated 3 of 12 Start: 3.0 · senior practitioner title Evidence: rated like 8 colleagues in the same role and department · own answers too general to rate → no change KRA: “1. Complete assigned conversion/formatting tasks with >=99% accuracy · zero critical errors 2. Meet 100% of client filing deadlines · no SLA…” Market: A3 = Varied and non-standard work; handles exceptions | BP12: Rated 3 of 12 Start: 3.0 · senior practitioner title Evidence: rated like 8 colleagues in the same role and department · own answers too general to rate → no change Market: A3 = Technical / QC / client calls on own work | BQ12: Rated 3.5 of 12 · between A3 and B1 Start: 4.0 · senior practitioner title; 3 direct reports Evidence: rated like 8 colleagues in the same role and department · own answers too general to rate → moved −0.5 KRA: “1. Complete assigned conversion/formatting tasks with >=99% accuracy · zero critical errors 2. Meet 100% of client filing deadlines · no SLA…” Market: A3 = A module / process, or work with client or regulatory consequences · B1 = A domain or a small team | BR12: Rated 3.5 of 12 · between A3 and B1 Start: 4.0 Evidence: rated like 8 colleagues in the same role and department · own answers too general to rate → moved −0.5 Team: 3 direct reports · POD Lead Market: A3 = Not scored in Band A · B1 = IC: mentors and reviews · People: hands-on team lead of 3–5 | BS12: Rated 8 of 12 Experience: 14.9 yrs total · 14.9 at IRIS; none recorded before IRIS = 8.1 on the experience scale Qualification: BA · graduate → no change Market: B1 roles typically have 4–8 yrs · IRIS guide 4–7 | BT12: Rated 4 of 12 — a starting estimate. Start: 3.5, the role's accountability scope — what it answers for. Moved +0.5: the survey / manager mapping marks it business-critical. Managers and heads: overwrite this rating on the Weightage sheet with the business impact you see — the score updates at once. Ladder: B1 = Moves a module's, product area's or client account's results | BU12: 1. Complete assigned conversion/formatting tasks with >=99% accuracy · zero critical errors 2. Meet 100% of client filing deadlines · no SLA breaches 3. Maintain average turnaround per assignment within agreed TAT 4. Handle assigned client edits within agreed TAT with client. 5. Develop capabilities to work in more than 2 mandates/products. Ultimate goal should be able to work in all OCR/Formatting mandates. 6. Conduct monthly knowledge sessions in order to Cross-skill team: Capable on at least more than two OCR/Formatting mandates | BZ12: Received · manager annual | CA12: CARBON Mapping Master | CB12: 20 | CC12: • Role / sub-team: Digitizing assisted services. | CD12: • Key responsibilities include: Formatting check ESEF and EU DM, UK HTML conversion, Data analyst; Formatting check & Review, mail to service team. • Reported deliverables and outcomes include: Completed DM files go to the service team after a formatting check, along with client feedback; work is carried out under the guidance of the service and support teams. | CE12: • Current capabilities: AI tool skills; Copilot; Tools / software used: Both. | CF12: • Communications skills. • Presentation skills. | CG12: • Key challenges: Quality of report, RDP issue. • Support required: No input received. | CH12: Business Impact: Moved +0.5: the survey / manager mapping marks it business-critical. | CJ12: Self-identified: AI / automation · Leadership & people management · Project / programme management For the next role: AI / automation · Leadership & people management · Project / programme management | CK12: Per-person summary · CARBON Mapping Master | CL12: WHAT THE ROLE DOES: Trains clients and drives product adoption. At B1: a domain / module, or a small team. KEY RESPONSIBILITIES: Trains clients and drives product adoption; Domain specialist work; A domain or a small team DELIVERS: A domain or a small team DECIDES ALONE: Technical / QC / client calls for the domain COMPETENCIES REQUIRED — must-have ★: Product, Platform & Domain Knowledge · Stakeholder & Client Management OTHER FUNCTIONAL COMPETENCIES: Communication & Presentation · Database, SQL & Data Engineering · Regulatory & BFSI Domain · Process Improvement & Quality Mindset PROFICIENCY NEEDED AT THIS LEVEL: Core 3 · Future-ready 3 · Functional 3 · Leadership 1 CREDENTIALS: Internal product certification SOURCE: Framework only · fewer than 3 answered — 1 holder, 1 answered the survey; sub-family 1 answered; catalogue RC-039 | CM12: What the role answers for: A domain or a small team. Accountability & Impact rating: 3.5 of 12 · B1-level impact. Leads 3 direct reports. From the survey and manager mapping — critical role: yes; successor named: no. Manager talent mapping — Latest rating: 4 · Potential: High · 9-Box Grid placement: Core Contributor. | CO12: 4 | CP12: 4 | CQ12: High | CR12: Core Contributor | CS12: Ready now | CU12: Yes | CX12: Medium · critical role Yes · only this person — · successor named No | CY12: No one in the same sub-family at or near this level — external hire or develop | CZ12: Name a successor; document the key process; cross-train one person | DA12: 106 | DB12: Exceeds — ready for stretch | DC12: 113 | DD12: 100 | DE12: 107 | DF12: 100 | DG12: None — maintain and stretch | DH12: B2: 90% of profile — ready on competencies | DI12: Evidence: Survey + KRAs | Core: Ownership 5/3, Problem solving 4/3, Communication & collaboration 4/3, Client & quality focus 5/3, Learning agility 3/3, Integrity & compliance 3/3 | Future-ready: AI literacy 3/3, Data literacy 3/3, Digital fluency 3/3, Innovation 3/3 | Functional: Product & domain 3/3, Stakeholder mgmt 3/3, Communication 4/3, SQL & data 3/3, Regulatory domain 3/3, Quality & process 4/3 | Leadership: Developing people 2/2, Decision making 2/2, Strategic acumen 2/2, Influence & change 2/2 | DJ12: AI / automation · Leadership & people management · Project / programme management | DL12: AI, GenAI & Prompt Engineering; Stakeholder & Client Management | DM12: AI / automation · Leadership & people management · Project / programme management | DO12: No strong match from survey evidence | DP12: Ritesh Yeram · Digitization Associate — 0.32: microsoft, reader, fine, delivery. | DQ12: No close match in other businesses | DR12: POD Lead | DU12: Customer Enablement Specialist – POD Lead in Digitizing · CARBON, B1 — POD Lead. The work: Trains clients and drives product adoption. At this level the role owns a domain / module, or a small team. Key responsibilities: Trains clients and drives product adoption; Domain specialist work; A domain or a small team. Leads 3 direct reports. | DV12: Hire as: Senior Executive / CSM — IRIS B1 Specialist · POD Lead · POD Lead Market level: P3 / M2 · SFIA 4 Enable Experience: 4–7 yrs · Education: Graduate Equivalent titles at peers: Workiva – Customer Success Manager · IRIS Vs Competitor Benchmark — SaaS customer-success ladder – CSM · IRIS Vs Competitor Benchmark — support tiers – L3 / Problem Analyst Credentials: Internal product certification Must already know: ITIL / service-desk practice; SLA management | DW12: FUNCTIONAL — skill level 3 of 5 · Practitioner ★ Product, Platform & Domain Knowledge: Handles most product and domain scenarios ★ Stakeholder & Client Management: Manages client communication and expectations for own work • Communication & Presentation: Writes and presents clearly to clients and teams • Database, SQL & Data Engineering: Writes and tunes queries, procedures and ETL • Regulatory & BFSI Domain: Knows the relevant regulators, returns and rules • Process Improvement & Quality Mindset: Delivers right-first-time; improves own checklists CORE — skill level 3 of 5 · Practitioner • Ownership & Accountability: Owns a module, client or process end to end; fixes root causes • Problem Solving & Critical Thinking: Analyses non-routine problems; finds root causes • Communication & Collaboration: Communicates with clients / stakeholders; collaborates across teams • Client & Quality Focus: Anticipates client needs; prevents errors in own area • Learning Agility & Adaptability: Adapts to changing priorities; learns independently • Integrity, Compliance & Information Security: Spots and escalates compliance / security risks FUTURE-READY — skill level 3 of 5 · Practitioner • AI Literacy & Augmentation: Builds AI into own workflow; evaluates accuracy and bias • Data Literacy & Analytics: Analyses data · SQL, BI, advanced Excel to find insight • Digital Fluency & Automation: Automates own repetitive work · macros, scripts, workflows • Innovation & Continuous Improvement: Delivers measurable improvements in own area LEADERSHIP — skill level 1 of 5 · Awareness • Leading & Developing People: Not required • Decision Making & Delegation: Not required • Strategic & Business Acumen: Not required • Influence & Change Leadership: Not required ★ = must-have for the family. Scale: 1 Awareness · 2 Working · 3 Practitioner · 4 Advanced · 5 Expert. | DX12: Draft — generated from the framework; hiring-manager review pending · HR Super Master, sheet T5. 1. [Product, Platform & Domain Knowledge · level 3] Tell me about recent work that shows this: "Handles most product and domain scenarios". What exactly did you do, how, and what was the result? Assess with: Scenario interview. 2. [Stakeholder & Client Management · level 3] Tell me about recent work that shows this: "Manages client communication and expectations for own work". What exactly did you do, how, and what was the result? Assess with: Role play / behavioural interview. 3. [Communication & Presentation · level 3] Give an example that shows you can do this: "Writes and presents clearly to clients and teams". Assess with: Presentation / writing test. 4. [Database, SQL & Data Engineering · level 3] Give an example that shows you can do this: "Writes and tunes queries, procedures and ETL". Assess with: SQL test / case. 5. [Regulatory & BFSI Domain · level 3] Give an example that shows you can do this: "Knows the relevant regulators, returns and rules". Assess with: Domain interview. 6. [Ownership & Accountability · level 3] Tell me about a piece of work you owned from start to finish. What went wrong, and what did you do about it? Listen for: "Owns a module, client or process end to end; fixes root causes". 7. [Problem Solving & Critical Thinking · level 3] Walk me through a problem you solved recently: how did you find the root cause and choose the fix? Listen for: "Analyses non-routine problems; finds root causes". 8. [Client & Quality Focus · level 3] Tell me about a time a client or user was unhappy with your work. What did you do? Listen for: "Anticipates client needs; prevents errors in own area". 9. [AI Literacy & Augmentation · level 3] Show me how you have used an AI tool in your work. How did you check its output? Listen for: "Builds AI into own workflow; evaluates accuracy and bias". Fit check: Why this role, why IRIS · regulatory reporting / XBRL / regtech, and what would you change in your first 90 days? | DY12: Market level: P3 / M2 · SFIA 4 Enable Typical title: Senior Executive / CSM At peers: Workiva – Customer Success Manager · IRIS Vs Competitor Benchmark — SaaS customer-success ladder: CSM · IRIS Vs Competitor Benchmark — support tiers: L3 / Problem Analyst Typical experience: 4–8 yrs · IRIS guide 4–7 Standard: TSIA frameworks and benchmarks; ITIL 4 service desk | DZ12: 4–7 yrs | EA12: 5–8 · 4–8 | EB12: Senior Executive / CSM | EC12: Workiva: Customer Success Manager · IRIS Vs Competitor Benchmark — SaaS customer-success ladder: CSM · IRIS Vs Competitor Benchmark — support tiers: L3 / Problem Analyst | ED12: TSIA frameworks and benchmarks; ITIL 4 service desk; Gainsight customer-success practice | EE12: Core 3 · Future 3 · Functional 3 · Leadership 2 | EG12: ✓ HRIS: 14.9 yrs, BA, 3 direct reports ✓ Survey: 20 of 20 questions answered ✓ KRAs: submitted, reported deliverables ✓ Manager mapping: rating, potential, 9-box ✗ Job description: not on file | EK12: Survey: summary on file · KRAs: received · Experience: on file
A13: CARBON | B13: IRIS1204 | C13: Dinesh Sharma | D13: Digitizing | E13: RC-049 | F13: Vijay Parulekar | G13: IRIS0055 | H13: C1 | I13: 4 | J13: 18 | K13: 18 | L13: B.Com | N13: Image Processing Specialist | O13: Team Lead – Digitization | P13: Data Operations & Digitization | Q13: Document Conversion, Formatting & Web Publishing | R13: L3 – Professional / Associate | S13: B1 | T13: Team Lead / Asst Manager | U13: B | V13: People Manager | W13: ▲ Up | X13: P3 / M2 | Y13: Career / · Team Lead | Z13: 4 Enable | AA13: B1 | AB13: Band B · Specialist / Manager | AC13: Team Lead / Asst Manager | AD13: • Same as the model | AE13: B2 | AF13: OK | AG13: No change · already below the manager | AH13: 6 | AJ13: CARBON · Digitizing · Band B · People Manager | AK13: 3 | AL13: =IFERROR(INDEX(WM_C,MATCH($AJ13,WM_KEY,0)),"") -> 0.32 | AM13: =IF(OR(AK13="",AL13=""),"",AK13*AL13) -> 0.96 | AN13: 3.5 | AO13: =IFERROR(INDEX(WM_AU,MATCH($AJ13,WM_KEY,0)),"") -> 0.18 | AP13: =IF(OR(AN13="",AO13=""),"",AN13*AO13) -> 0.63 | AQ13: 3.5 | AR13: =IFERROR(INDEX(WM_AC,MATCH($AJ13,WM_KEY,0)),"") -> 0.16 | AS13: =IF(OR(AQ13="",AR13=""),"",AQ13*AR13) -> 0.56 | AT13: 4 | AU13: =IFERROR(INDEX(WM_L,MATCH($AJ13,WM_KEY,0)),"") -> 0.15 | AV13: =IF(OR(AT13="",AU13=""),"",AT13*AU13) -> 0.6 | AW13: 9 | AX13: =IFERROR(INDEX(WM_E,MATCH($AJ13,WM_KEY,0)),"") -> 0.1 | AY13: =IF(OR(AW13="",AX13=""),"",AW13*AX13) -> 0.9 | AZ13: 4 | BA13: =IFERROR(INDEX(WM_BI,MATCH($AJ13,WM_KEY,0)),"") -> 0.09 | BB13: =IF(OR(AZ13="",BA13=""),"",AZ13*BA13) -> 0.36 | BC13: =IF(COUNT(AM13,AP13,AS13,AV13,AY13,BB13)<6,"",SUM(AM13,AP13,AS13,AV13,AY13,BB13)) -> 4.01 | BD13: =IF(BC13="","",INDEX({"A1","A2","A3","B1","B2","B3","C1","C2","D1","D2","E1","E2"},MAX(1,MIN(12,ROUND(BC13,0))))) -> B1 | BE13: B1 | BF13: The score decided the level | BG13: Weights: Complexity 32% · Autonomy 18% · Accountability 16% · Leadership 15% · Experience 10% · Business impact 9% Why: a manager's results come through the team, so Leadership rises to 15% and Complexity falls; autonomy, accountability and impact rise. Type of work in the department: delivery work is judged on accuracy and turnaround, so Accountability +5 and Complexity −5. Live: change the department's row on the Weightage Matrix and these weights, the points and the score update. | BH13: At build: Complexity 0.96 + Autonomy 0.63 + Accountability 0.56 + Leadership 0.60 + Experience 0.90 + Business impact 0.36 = 4.01 points → nearest level 4 = B1 Final level: B1 · same as the score | BI13: No rule applied: the score decides. | BJ13: — | BL13: Medium | BN13: Stable · moves in fewer than 5 of 30 weight tests | BO13: Rated 3 of 12 Start: 3.0 · senior practitioner title Evidence reads like A3: Reviews client edit requests, resolves team doubts, formatting checks across ESEF, KVK, ESRS → matches the start KRA: “1. Complete assigned conversion/formatting tasks with >=99% accuracy · zero critical errors 2. Meet 100% of client filing deadlines · no SLA…” Market: A3 = Varied and non-standard work; handles exceptions | BP13: Rated 3.5 of 12 · between A3 and B1 Start: 3.0 · senior practitioner title Evidence reads like B1: Decides to correct or reject client edit requests; manages task allocation → moved up 0.5 Market: A3 = Technical / QC / client calls on own work · B1 = Technical / QC / client calls for the domain | BQ13: Rated 3.5 of 12 · between A3 and B1 Start: 4.0 · senior practitioner title; 4 direct reports, 6 people below, 1 of them leads a team Evidence reads like A3: States accountability for tasks handled; quality-checked files delivered to clients on time → moved down 0.5 KRA: “1. Complete assigned conversion/formatting tasks with >=99% accuracy · zero critical errors 2. Meet 100% of client filing deadlines · no SLA…” Market: A3 = A module / process, or work with client or regulatory consequences · B1 = A domain or a small team | BR13: Rated 4 of 12 Start: 4.0 Evidence reads like B1: Team leadership, task allocation, doubt resolution; 4 reports → matches the start Team: 4 direct reports · People Manager Market: B1 = IC: mentors and reviews · People: hands-on team lead of 3–5 | BS13: Rated 9 of 12 Experience: 18.0 yrs total · 18.0 at IRIS; none recorded before IRIS = 9.1 on the experience scale Qualification: B.Com · graduate, relevant to the work → no change Market: B1 roles typically have 4–8 yrs · IRIS guide 4–7 | BT13: Rated 4 of 12 — a starting estimate. Start: 3.5, the role's accountability scope — what it answers for. Moved +0.5: the survey / manager mapping marks it business-critical. Managers and heads: overwrite this rating on the Weightage sheet with the business impact you see — the score updates at once. Ladder: B1 = Moves a module's, product area's or client account's results | BU13: 1. Complete assigned conversion/formatting tasks with >=99% accuracy · zero critical errors 2. Meet 100% of client filing deadlines · no SLA breaches 3. Maintain average turnaround per assignment within agreed TAT 4. Handle assigned client edits within agreed TAT with client. 5. Develop capabilities to work in more than 2 mandates/products. Ultimate goal should be able to work in all OCR/Formatting mandates. 6. Conduct monthly knowledge sessions in order to Cross-skill team: Capable on at least more than two OCR/Formatting mandates | BZ13: Received · manager annual | CA13: CARBON Mapping Master | CB13: 20 | CC13: • Role / sub-team: Digitizing assited service. | CD13: • Key responsibilities include: ESEF and EU DM GRI, KVK, CBN and ESRS Formatting check ALLOCATION QUERY SOLVE HMRC UK html conversion. • Reported deliverables and outcomes include: Once file Formatting and conversion completed will send the file to service team. | CE13: • Current capabilities: Copilot; Tools / software used: Both | Carbon tool [Teams chat]. | CF13: • Communications skills. • Presentation skills. | CG13: • Key challenges: Quality of report, RDP issue. • Support required: No input received. | CH13: Complexity: Evidence reads like A3: Reviews client edit requests, resolves team doubts, formatting checks across ESEF, KVK, ESRS → matches the start Autonomy: Evidence reads like B1: Decides to correct or reject client edit requests; manages task allocation → moved up 0.5 Accountability: Evidence reads like A3: States accountability for tasks handled; quality-checked files delivered to clients on time → moved down 0.5 Leadership: Evidence reads like B1: Team leadership, task allocation, doubt resolution; 4 reports → matches the start Business Impact: Moved +0.5: the survey / manager mapping marks it business-critical. | CI13: Common themes in sub-family holders, all levels' answers: purpose · core · formatting · quality · rbi · website Common themes in sub-family holders, all levels' answers: quality · document · formatting · html · accuracy · conversion Common themes in sub-family holders, all levels' answers: html · pdf · word · deliver · formatted · documents Common themes in sub-family holders, all levels' answers: am · accountable · accuracy · quality · every · formatting Common themes in sub-family holders, all levels' answers: formatting · independently · html · validate · allocate · cipc If the work is missed · role-holders' themes: rework · delays · errors · quality · incorrect. | CJ13: Self-identified: Leadership & people management · Communication & presentation For the next role: Leadership & people management · Communication & presentation | CK13: Per-person summary · CARBON Mapping Master | CL13: WHAT THE ROLE DOES: Converts and formats documents into HTML/PDF/Word to filing or web standards, and publishes content · incl. RBI website. At B1: a domain / module, or a small team. Common themes in sub-family holders, all levels' answers: purpose · core · formatting · quality · rbi · website KEY RESPONSIBILITIES: Converts and formats documents into HTML/PDF/Word to filing or web standards, and publishes content · incl. RBI website; Domain specialist work; A domain or a small team Common themes in sub-family holders, all levels' answers: quality · document · formatting · html · accuracy · conversion DELIVERS: A domain or a small team Common themes in sub-family holders, all levels' answers: html · pdf · word · deliver · formatted · documents ACCOUNTABLE FOR: A domain or a small team Common themes in sub-family holders, all levels' answers: am · accountable · accuracy · quality · every · formatting DECIDES ALONE: Technical / QC / client calls for the domain Common themes in sub-family holders, all levels' answers: formatting · independently · html · validate · allocate · cipc SKILLS & KNOWLEDGE · role-holders: OCR/Image procesing · attention to detail · quality checking · Excel · timely delivery · HTML · Word · ABYYY Fine Reader TOOLS & SYSTEMS: Excel · Office 365 word · Carbon applications · Abby FineReader · Web Expression HTML editor · DM · HTML Editor · US DM - Carbon COMPETENCIES REQUIRED — must-have ★: Advanced Excel & Productivity Tools · Process Improvement & Quality Mindset OTHER FUNCTIONAL COMPETENCIES: Regulatory & BFSI Domain · XBRL, iXBRL & Taxonomy · AI, GenAI & Prompt Engineering · Time, Priority & Self-Management PROFICIENCY NEEDED AT THIS LEVEL: Core 3 · Future-ready 3 · Functional 3 · Leadership 2 CREDENTIALS: MOS Excel · optional; Lean / Six Sigma · optional SOURCE: Framework + sub-family themes · 3+ answered — 1 holder, 1 answered the survey; sub-family 30 answered; catalogue RC-049 | CM13: What the role answers for: A domain or a small team. Accountability & Impact rating: 3.5 of 12 · B1-level impact. Leads 4 direct reports. From the survey and manager mapping — critical role: yes; successor named: no. If the work is missed · role-holders' themes: rework · delays · errors · quality · incorrect. Manager talent mapping — Latest rating: 5 · Potential: High · 9-Box Grid placement: Core Contributor. | CO13: 4 | CP13: 5 | CQ13: High | CR13: Core Contributor | CS13: Ready now | CT13: Yes | CU13: Yes | CX13: Medium · critical role Yes · only this person — · successor named No | CY13: Janardan Bale · B2, CARBON · Prajakta Mokal · B1, CARBON · Ritesh Yeram · B1, CARBON | CZ13: Name a successor; document the key process; cross-train one person | DA13: 101 | DB13: Meets the level | DC13: 110 | DD13: 92 | DE13: 98 | DF13: 102 | DG13: Prioritisation, Innovation, Strategic acumen | DH13: B2: 89% of profile — close | DI13: Evidence: Survey + KRAs | Core: Ownership 5/3, Problem solving 3/3, Communication & collaboration 4/3, Client & quality focus 5/3, Learning agility 3/3, Integrity & compliance 3/3 | Future-ready: AI literacy 3/3, Data literacy 3/3, Digital fluency 3/3, Innovation 2/3 | Functional: Excel & tools 3/3, Quality & process 4/3, Regulatory domain 3/3, XBRL & taxonomy 3/3, AI / GenAI 3/3, Prioritisation 2/3 | Leadership: Developing people 3/2, Decision making 3/2, Strategic acumen 1/2, Influence & change 3/2 | DJ13: Leadership & people management · Communication & presentation | DL13: AI, GenAI & Prompt Engineering; Stakeholder & Client Management | DM13: Leadership & people management · Communication & presentation | DN13: Leadership development: strategic thinking, cross-functional influence, financial/business acumen, succession & talent development, change management, executive communication | DO13: No strong match from survey evidence | DP13: Prajakta Mokal · Senior Digitization Associate — 0.45: finereader, expression, web, abbyy; Ritesh Yeram · Digitization Associate — 0.37: expression, microsoft, abbyy, files.; Justeen Koola · Digitization Associate — 0.34: finereader, expression, web, carbon | DQ13: No close match in other businesses | DR13: Within norm | DU13: Team Lead – Digitization in Digitizing · CARBON, B1 — People Manager. The work: Converts and formats documents into HTML/PDF/Word to filing or web standards, and publishes content · incl. RBI website. At this level the role owns a domain / module, or a small team. Key responsibilities: Converts and formats documents into HTML/PDF/Word to filing or web standards, and publishes content · incl. RBI website; Domain specialist work; A domain or a small team. Holders describe it with: quality · document · formatting · html · accuracy · conversion. Leads 4 direct reports. | DV13: Hire as: Team Lead / Assistant Manager — IRIS B1 Team Lead · People Manager Market level: P3 / M2 · SFIA 4 Enable Experience: 4–7 yrs · Education: Graduate · commerce preferred Team size at this level: IC: none · Team Lead: 3–5 Equivalent titles at peers: Accenture Operations – L9 Team Lead · IRIS Vs Competitor Benchmark — operations roles – Team Lead / Quality Lead Credentials: MOS Excel · optional; Lean / Six Sigma · optional Must already know: Accuracy and SLA discipline; data confidentiality | DW13: FUNCTIONAL — skill level 3 of 5 · Practitioner ★ Advanced Excel & Productivity Tools: Uses advanced Excel, Word, HTML and conversion tools fluently ★ Process Improvement & Quality Mindset: Delivers right-first-time; improves own checklists • Regulatory & BFSI Domain: Knows the relevant regulators, returns and rules • XBRL, iXBRL & Taxonomy: Tags and validates filings accurately for a market • AI, GenAI & Prompt Engineering: Uses AI / LLM tools in own work and validates output • Time, Priority & Self-Management: Manages volume and deadlines without slippage CORE — skill level 3 of 5 · Practitioner • Ownership & Accountability: Owns a module, client or process end to end; fixes root causes • Problem Solving & Critical Thinking: Analyses non-routine problems; finds root causes • Communication & Collaboration: Communicates with clients / stakeholders; collaborates across teams • Client & Quality Focus: Anticipates client needs; prevents errors in own area • Learning Agility & Adaptability: Adapts to changing priorities; learns independently • Integrity, Compliance & Information Security: Spots and escalates compliance / security risks FUTURE-READY — skill level 3 of 5 · Practitioner • AI Literacy & Augmentation: Builds AI into own workflow; evaluates accuracy and bias • Data Literacy & Analytics: Analyses data · SQL, BI, advanced Excel to find insight • Digital Fluency & Automation: Automates own repetitive work · macros, scripts, workflows • Innovation & Continuous Improvement: Delivers measurable improvements in own area LEADERSHIP — skill level 2 of 5 · Working • Leading & Developing People: Guides and reviews 1–3 people · POD Lead • Decision Making & Delegation: Decides allocation within a pod • Strategic & Business Acumen: Understands how own work drives client and business results • Influence & Change Leadership: Influences peers in own area SKILLS · from role-holders and HRIS: OCR/Image procesing · attention to detail · quality checking · Excel · timely delivery · HTML · Word · ABYYY Fine Reader TOOLS: Excel · Office 365 word · Carbon applications · Abby FineReader · Web Expression HTML editor · DM · HTML Editor · US DM - Carbon ★ = must-have for the family. Scale: 1 Awareness · 2 Working · 3 Practitioner · 4 Advanced · 5 Expert. | DX13: Draft — generated from the framework; hiring-manager review pending · HR Super Master, sheet T5. 1. [Advanced Excel & Productivity Tools · level 3] Tell me about recent work that shows this: "Uses advanced Excel, Word, HTML and conversion tools fluently". What exactly did you do, how, and what was the result? Assess with: Practical test. 2. [Process Improvement & Quality Mindset · level 3] Tell me about recent work that shows this: "Delivers right-first-time; improves own checklists". What exactly did you do, how, and what was the result? Assess with: Work sample / case. 3. [Regulatory & BFSI Domain · level 3] Give an example that shows you can do this: "Knows the relevant regulators, returns and rules". Assess with: Domain interview. 4. [XBRL, iXBRL & Taxonomy · level 3] Give an example that shows you can do this: "Tags and validates filings accurately for a market". Assess with: Tagging test on a real filing. 5. [AI, GenAI & Prompt Engineering · level 3] Give an example that shows you can do this: "Uses AI / LLM tools in own work and validates output". Assess with: Work sample / portfolio. 6. [Ownership & Accountability · level 3] Tell me about a piece of work you owned from start to finish. What went wrong, and what did you do about it? Listen for: "Owns a module, client or process end to end; fixes root causes". 7. [Problem Solving & Critical Thinking · level 3] Walk me through a problem you solved recently: how did you find the root cause and choose the fix? Listen for: "Analyses non-routine problems; finds root causes". 8. [Client & Quality Focus · level 3] Tell me about a time a client or user was unhappy with your work. What did you do? Listen for: "Anticipates client needs; prevents errors in own area". 9. [AI Literacy & Augmentation · level 3] Show me how you have used an AI tool in your work. How did you check its output? Listen for: "Builds AI into own workflow; evaluates accuracy and bias". Fit check: Why this role, why IRIS · regulatory reporting / XBRL / regtech, and what would you change in your first 90 days? | DY13: Market level: P3 / M2 · SFIA 4 Enable Typical title: Team Lead / Assistant Manager At peers: Accenture Operations – L9 Team Lead · IRIS Vs Competitor Benchmark — operations roles: Team Lead / Quality Lead Typical experience: 4–8 yrs · IRIS guide 4–7 Standard: COPC CX Standard; ISO 9001 | DZ13: 4–7 yrs | EA13: 5–8 · 4–8 | EB13: Team Lead / Assistant Manager | EC13: Accenture Operations: L9 Team Lead · IRIS Vs Competitor Benchmark — operations roles: Team Lead / Quality Lead | ED13: COPC CX Standard · leadership & planning, people, processes, performance; ISO 9001; Lean / Six Sigma | EE13: Core 3 · Future 3 · Functional 3 · Leadership 2 | EG13: ✓ HRIS: 18.0 yrs, B.Com, 4 direct reports ✓ Survey: 20 of 20 questions answered ✓ KRAs: submitted, reported deliverables ✓ Manager mapping: rating, potential, 9-box ✗ Job description: not on file | EK13: Survey: summary on file · KRAs: received · Experience: on file
A14: CARBON | B14: IRIS0117 | C14: Prajakta Mokal | D14: Digitizing | E14: RC-048 | F14: Vijay Parulekar | G14: IRIS0055 | H14: C1 | I14: 1 | J14: 19.5 | K14: 19.1 | L14: BA | N14: Image Processing Specialist | O14: Digitization Specialist – POD Lead | P14: Data Operations & Digitization | Q14: Document Conversion, Formatting & Web Publishing | R14: L3 – Professional / Associate | S14: B1 | T14: Specialist · POD Lead | U14: B | V14: POD Lead | W14: ▲ Up | X14: P3 / M2 | Y14: Career / · Team Lead | Z14: 4 Enable | AA14: B1 | AB14: Band B · Specialist / Manager | AC14: Team Lead / Asst Manager | AD14: • Same as the model | AE14: B2 | AF14: OK | AG14: No change · already below the manager | AH14: 6 | AJ14: CARBON · Digitizing · Band B · Expert / POD Lead | AK14: 3 | AL14: =IFERROR(INDEX(WM_C,MATCH($AJ14,WM_KEY,0)),"") -> 0.46 | AM14: =IF(OR(AK14="",AL14=""),"",AK14*AL14) -> 1.38 | AN14: 3 | AO14: =IFERROR(INDEX(WM_AU,MATCH($AJ14,WM_KEY,0)),"") -> 0.17 | AP14: =IF(OR(AN14="",AO14=""),"",AN14*AO14) -> 0.51 | AQ14: 3 | AR14: =IFERROR(INDEX(WM_AC,MATCH($AJ14,WM_KEY,0)),"") -> 0.15 | AS14: =IF(OR(AQ14="",AR14=""),"",AQ14*AR14) -> 0.45 | AT14: 3 | AU14: =IFERROR(INDEX(WM_L,MATCH($AJ14,WM_KEY,0)),"") -> 0.05 | AV14: =IF(OR(AT14="",AU14=""),"",AT14*AU14) -> 0.15 | AW14: 9.5 | AX14: =IFERROR(INDEX(WM_E,MATCH($AJ14,WM_KEY,0)),"") -> 0.1 | AY14: =IF(OR(AW14="",AX14=""),"",AW14*AX14) -> 0.95 | AZ14: 3.5 | BA14: =IFERROR(INDEX(WM_BI,MATCH($AJ14,WM_KEY,0)),"") -> 0.07 | BB14: =IF(OR(AZ14="",BA14=""),"",AZ14*BA14) -> 0.245 | BC14: =IF(COUNT(AM14,AP14,AS14,AV14,AY14,BB14)<6,"",SUM(AM14,AP14,AS14,AV14,AY14,BB14)) -> 3.685 | BD14: =IF(BC14="","",INDEX({"A1","A2","A3","B1","B2","B3","C1","C2","D1","D2","E1","E2"},MAX(1,MIN(12,ROUND(BC14,0))))) -> B1 | BE14: B1 | BF14: The score decided the level | BG14: Weights: Complexity 46% · Autonomy 17% · Accountability 15% · Experience 10% · Business impact 7% · Leadership 5% Why: specialists are judged mainly on depth of expertise, then on what they decide alone, what they answer for and their impact. Type of work in the department: delivery work is judged on accuracy and turnaround, so Accountability +5 and Complexity −5. Live: change the department's row on the Weightage Matrix and these weights, the points and the score update. | BH14: At build: Complexity 1.38 + Autonomy 0.51 + Accountability 0.45 + Leadership 0.15 + Experience 0.95 + Business impact 0.25 = 3.69 points → nearest level 4 = B1 Final level: B1 · same as the score | BI14: No rule applied: the score decides. | BJ14: — | BL14: High | BN14: Stable · moves in fewer than 5 of 30 weight tests | BO14: Rated 3 of 12 Start: 3.0 · senior practitioner title Evidence reads like A3: Checks received files, allocates by skill, OCR with AI app, QC, query solving → matches the start KRA: “1. Complete assigned conversion/formatting tasks with >=99% accuracy · zero critical errors 2. Meet 100% of client filing deadlines · no SLA…” Market: A3 = Varied and non-standard work; handles exceptions | BP14: Rated 3 of 12 Start: 3.0 · senior practitioner title Evidence reads like A3: Independent file allocation only in urgent or peak situations → matches the start Market: A3 = Technical / QC / client calls on own work | BQ14: Rated 3 of 12 Start: 3.5 · senior practitioner title; 1 direct report Evidence reads like A3: File allocation and on-time conversion and delivery process → moved down 0.5 KRA: “1. Complete assigned conversion/formatting tasks with >=99% accuracy · zero critical errors 2. Meet 100% of client filing deadlines · no SLA…” Market: A3 = A module / process, or work with client or regulatory consequences | BR14: Rated 3 of 12 Start: 3.5 Evidence reads like A3: Assigns files to team members and solves queries; 1 report → moved down 0.5 Team: 1 direct report · POD Lead Market: A3 = Not scored in Band A | BS14: Rated 9.5 of 12 · between D1 and D2 Experience: 19.5 yrs total · 0.4 before IRIS + 19.1 at IRIS = 9.6 on the experience scale Qualification: BA · graduate → no change Market: B1 roles typically have 4–8 yrs · IRIS guide 4–7 | BT14: Rated 3.5 of 12 — a starting estimate. Start: 3, the role's accountability scope — what it answers for. Moved +0.5: the survey / manager mapping marks it business-critical. Managers and heads: overwrite this rating on the Weightage sheet with the business impact you see — the score updates at once. Ladder: A3 = A process or client deliverable depends on this work · B1 = Moves a module's, product area's or client account's results | BU14: 1. Complete assigned conversion/formatting tasks with >=99% accuracy · zero critical errors 2. Meet 100% of client filing deadlines · no SLA breaches 3. Maintain average turnaround per assignment within agreed TAT 4. Handle assigned client edits within agreed TAT with client. 5. Develop capabilities to work in more than 2 mandates/products. Ultimate goal should be able to work in all OCR/Formatting mandates. 6. Conduct monthly knowledge sessions in order to Cross-skill team: >=70% capable on at least more than two OCR/Formatting mandates | BZ14: Received · manager annual | CA14: CARBON Mapping Master | CB14: 20 | CC14: • Role / sub-team: Digitizing Assisted Services. | CD14: • Key responsibilities include: ESEF, Cipc, Mca Allocation, Ocr & Qc, Cipc Html conversion, Uk h Conversion, quality check of pdf and word file, Brsr download, Quality cheking, Solving quries & Other inter Department work. • Reported deliverables and outcomes include: For Cipc and Mca files send to tagging team. • Additional duties outside usual job: Brsr download. | CE14: • Current capabilities: Inter department communic; Tools / software used: HTML - Editor; Microsoft Web Expression; Abbyy FineReader. | CF14: • Communications skills. • Presentation skills. | CG14: • Key challenges: Quality of Report. • Support required: No input received. | CH14: Complexity: Evidence reads like A3: Checks received files, allocates by skill, OCR with AI app, QC, query solving → matches the start Autonomy: Evidence reads like A3: Independent file allocation only in urgent or peak situations → matches the start Accountability: Evidence reads like A3: File allocation and on-time conversion and delivery process → moved down 0.5 Leadership: Evidence reads like A3: Assigns files to team members and solves queries; 1 report → moved down 0.5 Business Impact: Moved +0.5: the survey / manager mapping marks it business-critical. | CI14: Common themes in role-holders' answers: am · formatting · processing · specialist · checker · image Common themes in role-holders' answers: files · quality · html · received · correctly · checking Common themes in role-holders' answers: word · pdf · html Common themes in role-holders' answers: accountable · am · every If the work is missed · role-holders' themes: dissatisfied · customers become · affected · company growth. | CJ14: Self-identified: Data, SQL & analytics · Product & tool knowledge · Communication & presentation For the next role: Data, SQL & analytics · Product & tool knowledge · Communication & presentation | CK14: Per-person summary · CARBON Mapping Master | CL14: WHAT THE ROLE DOES: Converts and formats documents into HTML/PDF/Word to filing or web standards, and publishes content · incl. RBI website. At B1: a domain / module, or a small team. Common themes in role-holders' answers: am · formatting · processing · specialist · checker · image KEY RESPONSIBILITIES: Converts and formats documents into HTML/PDF/Word to filing or web standards, and publishes content · incl. RBI website; Domain specialist work; A domain or a small team Common themes in role-holders' answers: files · quality · html · received · correctly · checking DELIVERS: A domain or a small team Common themes in role-holders' answers: word · pdf · html ACCOUNTABLE FOR: A domain or a small team Common themes in role-holders' answers: accountable · am · every DECIDES ALONE: Technical / QC / client calls for the domain SKILLS & KNOWLEDGE · role-holders: OCR/Image procesing TOOLS & SYSTEMS: Carbon applications · Office 365 word · Excel · Abby FineReader · Web Expression HTML Editor COMPETENCIES REQUIRED — must-have ★: Advanced Excel & Productivity Tools · Process Improvement & Quality Mindset OTHER FUNCTIONAL COMPETENCIES: Regulatory & BFSI Domain · XBRL, iXBRL & Taxonomy · AI, GenAI & Prompt Engineering · Time, Priority & Self-Management PROFICIENCY NEEDED AT THIS LEVEL: Core 3 · Future-ready 3 · Functional 3 · Leadership 1 CREDENTIALS: MOS Excel · optional; Lean / Six Sigma · optional SOURCE: Framework + role-holders' themes · 3+ answered — 4 holders, 4 answered the survey; sub-family 30 answered; catalogue RC-048 | CM14: What the role answers for: A domain or a small team. Accountability & Impact rating: 3 of 12 · A3-level impact. Leads 1 direct report. From the survey and manager mapping — critical role: yes; successor named: no. If the work is missed · role-holders' themes: dissatisfied · customers become · affected · company growth. Manager talent mapping — Latest rating: 4 · Potential: High · 9-Box Grid placement: Core Contributor. | CO14: 3.5 | CP14: 4 | CQ14: High | CR14: Core Contributor | CS14: Ready now | CU14: Yes | CX14: Medium · critical role Yes · only this person — · successor named No | CY14: Janardan Bale · B2, CARBON · Dinesh Sharma · B1, CARBON · Ritesh Yeram · B1, CARBON | CZ14: Name a successor; document the key process; cross-train one person | DA14: 104 | DB14: Meets the level | DC14: 110 | DD14: 105 | DE14: 103 | DF14: 98 | DG14: Strategic acumen | DH14: B2: 90% of profile — close | DI14: Evidence: Survey + KRAs | Core: Ownership 5/3, Problem solving 3/3, Communication & collaboration 4/3, Client & quality focus 5/3, Learning agility 3/3, Integrity & compliance 3/3 | Future-ready: AI literacy 3/3, Data literacy 4/3, Digital fluency 3/3, Innovation 3/3 | Functional: Excel & tools 4/3, Quality & process 3/3, Regulatory domain 3/3, XBRL & taxonomy 3/3, AI / GenAI 3/3, Prioritisation 3/3 | Leadership: Developing people 3/2, Decision making 3/2, Strategic acumen 1/2, Influence & change 2/2 | DJ14: Data, SQL & analytics · Product & tool knowledge · Communication & presentation | DL14: AI, GenAI & Prompt Engineering; Stakeholder & Client Management | DM14: Data, SQL & analytics · Product & tool knowledge · Communication & presentation | DO14: No strong match from survey evidence | DP14: Farina Pathan · Senior Digitization Associate — 0.57: html, word, ocr, finereader; Ritesh Yeram · Digitization Associate — 0.57: expression, html, files., received; Justeen Koola · Digitization Associate — 0.51: html, word, finereader, excel | DQ14: No close match in other businesses | DR14: POD Lead | DT14: Span: 1 direct reports · layer 7 · Very small team: merge with a neighbouring team or make a POD Lead role | DU14: Digitization Specialist – POD Lead in Digitizing · CARBON, B1 — POD Lead. The work: Converts and formats documents into HTML/PDF/Word to filing or web standards, and publishes content · incl. RBI website. At this level the role owns a domain / module, or a small team. Key responsibilities: Converts and formats documents into HTML/PDF/Word to filing or web standards, and publishes content · incl. RBI website; Domain specialist work; A domain or a small team. Holders describe it with: files · quality · html · received · correctly · checking. Leads 1 direct report. | DV14: Hire as: Specialist / QC Analyst — IRIS B1 Specialist · POD Lead · POD Lead Market level: P3 / M2 · SFIA 4 Enable Experience: 4–7 yrs · Education: Graduate · commerce preferred Equivalent titles at peers: Accenture Operations – L9 Team Lead · IRIS Vs Competitor Benchmark — operations roles – Team Lead / Quality Lead Credentials: MOS Excel · optional; Lean / Six Sigma · optional Must already know: Accuracy and SLA discipline; data confidentiality | DW14: FUNCTIONAL — skill level 3 of 5 · Practitioner ★ Advanced Excel & Productivity Tools: Uses advanced Excel, Word, HTML and conversion tools fluently ★ Process Improvement & Quality Mindset: Delivers right-first-time; improves own checklists • Regulatory & BFSI Domain: Knows the relevant regulators, returns and rules • XBRL, iXBRL & Taxonomy: Tags and validates filings accurately for a market • AI, GenAI & Prompt Engineering: Uses AI / LLM tools in own work and validates output • Time, Priority & Self-Management: Manages volume and deadlines without slippage CORE — skill level 3 of 5 · Practitioner • Ownership & Accountability: Owns a module, client or process end to end; fixes root causes • Problem Solving & Critical Thinking: Analyses non-routine problems; finds root causes • Communication & Collaboration: Communicates with clients / stakeholders; collaborates across teams • Client & Quality Focus: Anticipates client needs; prevents errors in own area • Learning Agility & Adaptability: Adapts to changing priorities; learns independently • Integrity, Compliance & Information Security: Spots and escalates compliance / security risks FUTURE-READY — skill level 3 of 5 · Practitioner • AI Literacy & Augmentation: Builds AI into own workflow; evaluates accuracy and bias • Data Literacy & Analytics: Analyses data · SQL, BI, advanced Excel to find insight • Digital Fluency & Automation: Automates own repetitive work · macros, scripts, workflows • Innovation & Continuous Improvement: Delivers measurable improvements in own area LEADERSHIP — skill level 1 of 5 · Awareness • Leading & Developing People: Not required • Decision Making & Delegation: Not required • Strategic & Business Acumen: Not required • Influence & Change Leadership: Not required SKILLS · from role-holders and HRIS: OCR/Image procesing TOOLS: Carbon applications · Office 365 word · Excel · Abby FineReader · Web Expression HTML Editor ★ = must-have for the family. Scale: 1 Awareness · 2 Working · 3 Practitioner · 4 Advanced · 5 Expert. | DX14: Draft — generated from the framework; hiring-manager review pending · HR Super Master, sheet T5. 1. [Advanced Excel & Productivity Tools · level 3] Tell me about recent work that shows this: "Uses advanced Excel, Word, HTML and conversion tools fluently". What exactly did you do, how, and what was the result? Assess with: Practical test. 2. [Process Improvement & Quality Mindset · level 3] Tell me about recent work that shows this: "Delivers right-first-time; improves own checklists". What exactly did you do, how, and what was the result? Assess with: Work sample / case. 3. [Regulatory & BFSI Domain · level 3] Give an example that shows you can do this: "Knows the relevant regulators, returns and rules". Assess with: Domain interview. 4. [XBRL, iXBRL & Taxonomy · level 3] Give an example that shows you can do this: "Tags and validates filings accurately for a market". Assess with: Tagging test on a real filing. 5. [AI, GenAI & Prompt Engineering · level 3] Give an example that shows you can do this: "Uses AI / LLM tools in own work and validates output". Assess with: Work sample / portfolio. 6. [Ownership & Accountability · level 3] Tell me about a piece of work you owned from start to finish. What went wrong, and what did you do about it? Listen for: "Owns a module, client or process end to end; fixes root causes". 7. [Problem Solving & Critical Thinking · level 3] Walk me through a problem you solved recently: how did you find the root cause and choose the fix? Listen for: "Analyses non-routine problems; finds root causes". 8. [Client & Quality Focus · level 3] Tell me about a time a client or user was unhappy with your work. What did you do? Listen for: "Anticipates client needs; prevents errors in own area". 9. [AI Literacy & Augmentation · level 3] Show me how you have used an AI tool in your work. How did you check its output? Listen for: "Builds AI into own workflow; evaluates accuracy and bias". Fit check: Why this role, why IRIS · regulatory reporting / XBRL / regtech, and what would you change in your first 90 days? | DY14: Market level: P3 / M2 · SFIA 4 Enable Typical title: Specialist / QC Analyst At peers: Accenture Operations – L9 Team Lead · IRIS Vs Competitor Benchmark — operations roles: Team Lead / Quality Lead Typical experience: 4–8 yrs · IRIS guide 4–7 Standard: COPC CX Standard; ISO 9001 | DZ14: 4–7 yrs | EA14: 5–8 · 4–8 | EB14: Specialist / QC Analyst | EC14: Accenture Operations: L9 Team Lead · IRIS Vs Competitor Benchmark — operations roles: Team Lead / Quality Lead | ED14: COPC CX Standard · leadership & planning, people, processes, performance; ISO 9001; Lean / Six Sigma | EE14: Core 3 · Future 3 · Functional 3 · Leadership 2 | EG14: ✓ HRIS: 19.5 yrs, BA, 1 direct report ✓ Survey: 20 of 20 questions answered ✓ KRAs: submitted, reported deliverables ✓ Manager mapping: rating, potential, 9-box ✗ Job description: not on file | EK14: Survey: summary on file · KRAs: received · Experience: on file
A15: CARBON | B15: IRIS0171 | C15: Ritesh Yeram | D15: Digitizing | E15: RC-048 | F15: Dinesh Sharma | G15: IRIS1204 | H15: B1 | I15: 2 | J15: 20.7 | K15: 18.7 | L15: Undergraduate | N15: Image Processing Specialist | O15: Digitization Specialist – POD Lead | P15: Data Operations & Digitization | Q15: Document Conversion, Formatting & Web Publishing | R15: L3 – Professional / Associate | S15: B1 | T15: Specialist · POD Lead | U15: B | V15: POD Lead | W15: ▲ Up | X15: P3 / M2 | Y15: Career / · Team Lead | Z15: 4 Enable | AA15: A3 | AB15: Band A · Practitioner | AC15: Senior Associate | AD15: ▼ Down · pay and title protected | AE15: B1 | AF15: OK | AG15: Level rule: manager B1; a reportee sits at least one level below · B1 → A3 · move down · pay and title protected for one cycle | AH15: 7 | AJ15: CARBON · Digitizing · Band B · Expert / POD Lead | AK15: 3 | AL15: =IFERROR(INDEX(WM_C,MATCH($AJ15,WM_KEY,0)),"") -> 0.46 | AM15: =IF(OR(AK15="",AL15=""),"",AK15*AL15) -> 1.38 | AN15: 2.5 | AO15: =IFERROR(INDEX(WM_AU,MATCH($AJ15,WM_KEY,0)),"") -> 0.17 | AP15: =IF(OR(AN15="",AO15=""),"",AN15*AO15) -> 0.425 | AQ15: 3.5 | AR15: =IFERROR(INDEX(WM_AC,MATCH($AJ15,WM_KEY,0)),"") -> 0.15 | AS15: =IF(OR(AQ15="",AR15=""),"",AQ15*AR15) -> 0.525 | AT15: 3.5 | AU15: =IFERROR(INDEX(WM_L,MATCH($AJ15,WM_KEY,0)),"") -> 0.05 | AV15: =IF(OR(AT15="",AU15=""),"",AT15*AU15) -> 0.175 | AW15: 9.5 | AX15: =IFERROR(INDEX(WM_E,MATCH($AJ15,WM_KEY,0)),"") -> 0.1 | AY15: =IF(OR(AW15="",AX15=""),"",AW15*AX15) -> 0.95 | AZ15: 4 | BA15: =IFERROR(INDEX(WM_BI,MATCH($AJ15,WM_KEY,0)),"") -> 0.07 | BB15: =IF(OR(AZ15="",BA15=""),"",AZ15*BA15) -> 0.28 | BC15: =IF(COUNT(AM15,AP15,AS15,AV15,AY15,BB15)<6,"",SUM(AM15,AP15,AS15,AV15,AY15,BB15)) -> 3.735 | BD15: =IF(BC15="","",INDEX({"A1","A2","A3","B1","B2","B3","C1","C2","D1","D2","E1","E2"},MAX(1,MIN(12,ROUND(BC15,0))))) -> B1 | BE15: B1 | BF15: The score decided the level | BG15: Weights: Complexity 46% · Autonomy 17% · Accountability 15% · Experience 10% · Business impact 7% · Leadership 5% Why: specialists are judged mainly on depth of expertise, then on what they decide alone, what they answer for and their impact. Type of work in the department: delivery work is judged on accuracy and turnaround, so Accountability +5 and Complexity −5. Live: change the department's row on the Weightage Matrix and these weights, the points and the score update. | BH15: At build: Complexity 1.38 + Autonomy 0.43 + Accountability 0.53 + Leadership 0.18 + Experience 0.95 + Business impact 0.28 = 3.74 points → nearest level 4 = B1 Final level: B1 · same as the score | BI15: No rule applied: the score decides. | BJ15: — | BL15: Medium | BN15: Stable · moves in fewer than 5 of 30 weight tests | BO15: Rated 3 of 12 Start: 3.0 · senior practitioner title Evidence reads like A3: QCs received files, solves formatting queries, HTML conversion and HTML QC across HMRC/CIPC/MCA/ESMA jobs → matches the start KRA: “1. Complete assigned conversion/formatting tasks with >=99% accuracy · zero critical errors 2. Meet 100% of client filing deadlines · no SLA…” Market: A3 = Varied and non-standard work; handles exceptions | BP15: Rated 2.5 of 12 · between A2 and A3 Start: 3.0 · senior practitioner title Evidence reads like A2: States 'Not applicable' for independent decisions; only routine file allocation shown → moved down 0.5 Market: A2 = Chooses own approach within standards · A3 = Technical / QC / client calls on own work | BQ15: Rated 3.5 of 12 · between A3 and B1 Start: 4.0 · senior practitioner title; 2 direct reports Evidence reads like A3: Assigns files, ensures timely delivery and QC of conversions before handover to services team → moved down 0.5 KRA: “1. Complete assigned conversion/formatting tasks with >=99% accuracy · zero critical errors 2. Meet 100% of client filing deadlines · no SLA…” Market: A3 = A module / process, or work with client or regulatory consequences · B1 = A domain or a small team | BR15: Rated 3.5 of 12 · between A3 and B1 Start: 4.0 Evidence reads like A3: Allocates files and resolves formatting queries for others; 2 direct reports → moved down 0.5 Team: 2 direct reports · POD Lead Market: A3 = Not scored in Band A · B1 = IC: mentors and reviews · People: hands-on team lead of 3–5 | BS15: Rated 9.5 of 12 · between D1 and D2 Experience: 20.7 yrs total · 2.0 before IRIS + 18.7 at IRIS = 9.9 on the experience scale Qualification: Undergraduate · below graduate → −0.5 Market: B1 roles typically have 4–8 yrs · IRIS guide 4–7 | BT15: Rated 4 of 12 — a starting estimate. Start: 3.5, the role's accountability scope — what it answers for. Moved +0.5: the survey / manager mapping marks it business-critical. Managers and heads: overwrite this rating on the Weightage sheet with the business impact you see — the score updates at once. Ladder: B1 = Moves a module's, product area's or client account's results | BU15: 1. Complete assigned conversion/formatting tasks with >=99% accuracy · zero critical errors 2. Meet 100% of client filing deadlines · no SLA breaches 3. Maintain average turnaround per assignment within agreed TAT 4. Handle assigned client edits within agreed TAT with client. 5. Develop capabilites to work in more than 2 mandates/products. Ultimate goal should be able to work in all OCR/Formatting mandates. | BZ15: Received · manager annual | CA15: CARBON Mapping Master | CB15: 19 | CC15: • Role / sub-team: Digitizing Assited service. | CD15: • Key responsibilities include: ESEF QC, EU DM, Cipc , mca , uk Html Qc , cipc Html conversion, Formating check allocation query solving, quality check of pdf/ word. • Reported deliverables and outcomes include: Once file formatting and conversion complted will send the file Services Team. | CE15: • Current capabilities: Communication skills; Tools / software used: Both | Abbyy FineReader, Microsoft Web Expression · CIPC HTML conversion [Teams chat]. | CF15: • Communications skills. • Presentation skills. | CG15: • Key challenges: Quality of Report. • Support required: No input received. | CH15: Complexity: Evidence reads like A3: QCs received files, solves formatting queries, HTML conversion and HTML QC across HMRC/CIPC/MCA/ESMA jobs → matches the start Autonomy: Evidence reads like A2: States 'Not applicable' for independent decisions; only routine file allocation shown → moved down 0.5 Accountability: Evidence reads like A3: Assigns files, ensures timely delivery and QC of conversions before handover to services team → moved down 0.5 Leadership: Evidence reads like A3: Allocates files and resolves formatting queries for others; 2 direct reports → moved down 0.5 Business Impact: Moved +0.5: the survey / manager mapping marks it business-critical. | CI15: Common themes in role-holders' answers: am · formatting · processing · specialist · checker · image Common themes in role-holders' answers: files · quality · html · received · correctly · checking Common themes in role-holders' answers: word · pdf · html Common themes in role-holders' answers: accountable · am · every If the work is missed · role-holders' themes: dissatisfied · customers become · affected · company growth. | CJ15: Self-identified: Data, SQL & analytics · Product & tool knowledge · Communication & presentation For the next role: Data, SQL & analytics · Product & tool knowledge · Communication & presentation | CK15: Per-person summary · CARBON Mapping Master | CL15: WHAT THE ROLE DOES: Converts and formats documents into HTML/PDF/Word to filing or web standards, and publishes content · incl. RBI website. At B1: a domain / module, or a small team. Common themes in role-holders' answers: am · formatting · processing · specialist · checker · image KEY RESPONSIBILITIES: Converts and formats documents into HTML/PDF/Word to filing or web standards, and publishes content · incl. RBI website; Domain specialist work; A domain or a small team Common themes in role-holders' answers: files · quality · html · received · correctly · checking DELIVERS: A domain or a small team Common themes in role-holders' answers: word · pdf · html ACCOUNTABLE FOR: A domain or a small team Common themes in role-holders' answers: accountable · am · every DECIDES ALONE: Technical / QC / client calls for the domain SKILLS & KNOWLEDGE · role-holders: OCR/Image procesing TOOLS & SYSTEMS: Carbon applications · Office 365 word · Excel · Abby FineReader · Web Expression HTML Editor COMPETENCIES REQUIRED — must-have ★: Advanced Excel & Productivity Tools · Process Improvement & Quality Mindset OTHER FUNCTIONAL COMPETENCIES: Regulatory & BFSI Domain · XBRL, iXBRL & Taxonomy · AI, GenAI & Prompt Engineering · Time, Priority & Self-Management PROFICIENCY NEEDED AT THIS LEVEL: Core 3 · Future-ready 3 · Functional 3 · Leadership 1 CREDENTIALS: MOS Excel · optional; Lean / Six Sigma · optional SOURCE: Framework + role-holders' themes · 3+ answered — 4 holders, 4 answered the survey; sub-family 30 answered; catalogue RC-048 | CM15: What the role answers for: A domain or a small team. Accountability & Impact rating: 3.5 of 12 · B1-level impact. Leads 2 direct reports. From the survey and manager mapping — critical role: yes; successor named: no. If the work is missed · role-holders' themes: dissatisfied · customers become · affected · company growth. Manager talent mapping — Latest rating: 4 · Potential: High · 9-Box Grid placement: Core Contributor. | CO15: 4 | CP15: 4 | CQ15: High | CR15: Core Contributor | CS15: Ready now | CU15: Yes | CX15: Medium · critical role Yes · only this person — · successor named No | CY15: Janardan Bale · B2, CARBON · Dinesh Sharma · B1, CARBON · Prajakta Mokal · B1, CARBON | CZ15: Name a successor; document the key process; cross-train one person | DA15: 105 | DB15: Meets the level | DC15: 113 | DD15: 105 | DE15: 101 | DF15: 100 | DG15: AI / GenAI | DH15: B2: 89% of profile — close | DI15: Evidence: Survey + KRAs | Core: Ownership 5/3, Problem solving 4/3, Communication & collaboration 4/3, Client & quality focus 5/3, Learning agility 3/3, Integrity & compliance 3/3 | Future-ready: AI literacy 3/3, Data literacy 4/3, Digital fluency 3/3, Innovation 3/3 | Functional: Excel & tools 4/3, Quality & process 4/3, Regulatory domain 3/3, XBRL & taxonomy 3/3, AI / GenAI 2/3, Prioritisation 3/3 | Leadership: Developing people 2/2, Decision making 2/2, Strategic acumen 2/2, Influence & change 2/2 | DJ15: Data, SQL & analytics · Product & tool knowledge · Communication & presentation | DL15: AI, GenAI & Prompt Engineering; Stakeholder & Client Management | DM15: Data, SQL & analytics · Product & tool knowledge · Communication & presentation | DO15: No strong match from survey evidence | DP15: Prajakta Mokal · Senior Digitization Associate — 0.57: expression, html, files., received; Janardan Bale · Digitization Manager — 0.43: html, expression, hmrc, formatting; Dhanraj Patil · Senior Digitization Associate — 0.42: expression, cipc, hmrc, reader | DQ15: No close match in other businesses | DR15: POD Lead | DT15: Span: 2 direct reports · layer 8 · Very small team: merge with a neighbouring team or make a POD Lead role | DU15: Digitization Specialist – POD Lead in Digitizing · CARBON, B1 — POD Lead. The work: Converts and formats documents into HTML/PDF/Word to filing or web standards, and publishes content · incl. RBI website. At this level the role owns a domain / module, or a small team. Key responsibilities: Converts and formats documents into HTML/PDF/Word to filing or web standards, and publishes content · incl. RBI website; Domain specialist work; A domain or a small team. Holders describe it with: files · quality · html · received · correctly · checking. Leads 2 direct reports. | DV15: Hire as: Specialist / QC Analyst — IRIS B1 Specialist · POD Lead · POD Lead Market level: P3 / M2 · SFIA 4 Enable Experience: 4–7 yrs · Education: Graduate · commerce preferred Equivalent titles at peers: Accenture Operations – L9 Team Lead · IRIS Vs Competitor Benchmark — operations roles – Team Lead / Quality Lead Credentials: MOS Excel · optional; Lean / Six Sigma · optional Must already know: Accuracy and SLA discipline; data confidentiality | DW15: FUNCTIONAL — skill level 3 of 5 · Practitioner ★ Advanced Excel & Productivity Tools: Uses advanced Excel, Word, HTML and conversion tools fluently ★ Process Improvement & Quality Mindset: Delivers right-first-time; improves own checklists • Regulatory & BFSI Domain: Knows the relevant regulators, returns and rules • XBRL, iXBRL & Taxonomy: Tags and validates filings accurately for a market • AI, GenAI & Prompt Engineering: Uses AI / LLM tools in own work and validates output • Time, Priority & Self-Management: Manages volume and deadlines without slippage CORE — skill level 3 of 5 · Practitioner • Ownership & Accountability: Owns a module, client or process end to end; fixes root causes • Problem Solving & Critical Thinking: Analyses non-routine problems; finds root causes • Communication & Collaboration: Communicates with clients / stakeholders; collaborates across teams • Client & Quality Focus: Anticipates client needs; prevents errors in own area • Learning Agility & Adaptability: Adapts to changing priorities; learns independently • Integrity, Compliance & Information Security: Spots and escalates compliance / security risks FUTURE-READY — skill level 3 of 5 · Practitioner • AI Literacy & Augmentation: Builds AI into own workflow; evaluates accuracy and bias • Data Literacy & Analytics: Analyses data · SQL, BI, advanced Excel to find insight • Digital Fluency & Automation: Automates own repetitive work · macros, scripts, workflows • Innovation & Continuous Improvement: Delivers measurable improvements in own area LEADERSHIP — skill level 1 of 5 · Awareness • Leading & Developing People: Not required • Decision Making & Delegation: Not required • Strategic & Business Acumen: Not required • Influence & Change Leadership: Not required SKILLS · from role-holders and HRIS: OCR/Image procesing TOOLS: Carbon applications · Office 365 word · Excel · Abby FineReader · Web Expression HTML Editor ★ = must-have for the family. Scale: 1 Awareness · 2 Working · 3 Practitioner · 4 Advanced · 5 Expert. | DX15: Draft — generated from the framework; hiring-manager review pending · HR Super Master, sheet T5. 1. [Advanced Excel & Productivity Tools · level 3] Tell me about recent work that shows this: "Uses advanced Excel, Word, HTML and conversion tools fluently". What exactly did you do, how, and what was the result? Assess with: Practical test. 2. [Process Improvement & Quality Mindset · level 3] Tell me about recent work that shows this: "Delivers right-first-time; improves own checklists". What exactly did you do, how, and what was the result? Assess with: Work sample / case. 3. [Regulatory & BFSI Domain · level 3] Give an example that shows you can do this: "Knows the relevant regulators, returns and rules". Assess with: Domain interview. 4. [XBRL, iXBRL & Taxonomy · level 3] Give an example that shows you can do this: "Tags and validates filings accurately for a market". Assess with: Tagging test on a real filing. 5. [AI, GenAI & Prompt Engineering · level 3] Give an example that shows you can do this: "Uses AI / LLM tools in own work and validates output". Assess with: Work sample / portfolio. 6. [Ownership & Accountability · level 3] Tell me about a piece of work you owned from start to finish. What went wrong, and what did you do about it? Listen for: "Owns a module, client or process end to end; fixes root causes". 7. [Problem Solving & Critical Thinking · level 3] Walk me through a problem you solved recently: how did you find the root cause and choose the fix? Listen for: "Analyses non-routine problems; finds root causes". 8. [Client & Quality Focus · level 3] Tell me about a time a client or user was unhappy with your work. What did you do? Listen for: "Anticipates client needs; prevents errors in own area". 9. [AI Literacy & Augmentation · level 3] Show me how you have used an AI tool in your work. How did you check its output? Listen for: "Builds AI into own workflow; evaluates accuracy and bias". Fit check: Why this role, why IRIS · regulatory reporting / XBRL / regtech, and what would you change in your first 90 days? | DY15: Market level: P3 / M2 · SFIA 4 Enable Typical title: Specialist / QC Analyst At peers: Accenture Operations – L9 Team Lead · IRIS Vs Competitor Benchmark — operations roles: Team Lead / Quality Lead Typical experience: 4–8 yrs · IRIS guide 4–7 Standard: COPC CX Standard; ISO 9001 | DZ15: 4–7 yrs | EA15: 5–8 · 4–8 | EB15: Specialist / QC Analyst | EC15: Accenture Operations: L9 Team Lead · IRIS Vs Competitor Benchmark — operations roles: Team Lead / Quality Lead | ED15: COPC CX Standard · leadership & planning, people, processes, performance; ISO 9001; Lean / Six Sigma | EE15: Core 3 · Future 3 · Functional 3 · Leadership 2 | EG15: ✓ HRIS: 20.7 yrs, Undergraduate, 2 direct reports ✓ Survey: 19 of 20 questions answered ✓ KRAs: submitted, reported deliverables ✓ Manager mapping: rating, potential, 9-box ✗ Job description: not on file | EK15: Survey: summary on file · KRAs: received · Experience: on file
A16: CARBON | B16: IRIS1210 | C16: Tejas Kat | D16: Digitizing | E16: RC-048 | F16: Janardan Bale | G16: IRIS0470 | H16: B2 | I16: 2 | J16: 17.4 | K16: 16.4 | L16: Undergraduate | N16: Image Processing Specialist | O16: Digitization Specialist – POD Lead | P16: Data Operations & Digitization | Q16: Document Conversion, Formatting & Web Publishing | R16: L3 – Professional / Associate | S16: B1 | T16: Specialist · POD Lead | U16: B | V16: POD Lead | W16: ▲ Up | X16: P3 / M2 | Y16: Career / · Team Lead | Z16: 4 Enable | AA16: A3 | AB16: Band A · Practitioner | AC16: Senior Associate | AD16: ▼ Down · pay and title protected | AE16: B1 | AF16: OK | AG16: Level rule: manager B1; a reportee sits at least one level below · B1 → A3 · move down · pay and title protected for one cycle | AH16: 7 | AJ16: CARBON · Digitizing · Band B · Expert / POD Lead | AK16: 3 | AL16: =IFERROR(INDEX(WM_C,MATCH($AJ16,WM_KEY,0)),"") -> 0.46 | AM16: =IF(OR(AK16="",AL16=""),"",AK16*AL16) -> 1.38 | AN16: 3 | AO16: =IFERROR(INDEX(WM_AU,MATCH($AJ16,WM_KEY,0)),"") -> 0.17 | AP16: =IF(OR(AN16="",AO16=""),"",AN16*AO16) -> 0.51 | AQ16: 3.5 | AR16: =IFERROR(INDEX(WM_AC,MATCH($AJ16,WM_KEY,0)),"") -> 0.15 | AS16: =IF(OR(AQ16="",AR16=""),"",AQ16*AR16) -> 0.525 | AT16: 3.5 | AU16: =IFERROR(INDEX(WM_L,MATCH($AJ16,WM_KEY,0)),"") -> 0.05 | AV16: =IF(OR(AT16="",AU16=""),"",AT16*AU16) -> 0.175 | AW16: 8.5 | AX16: =IFERROR(INDEX(WM_E,MATCH($AJ16,WM_KEY,0)),"") -> 0.1 | AY16: =IF(OR(AW16="",AX16=""),"",AW16*AX16) -> 0.85 | AZ16: 4 | BA16: =IFERROR(INDEX(WM_BI,MATCH($AJ16,WM_KEY,0)),"") -> 0.07 | BB16: =IF(OR(AZ16="",BA16=""),"",AZ16*BA16) -> 0.28 | BC16: =IF(COUNT(AM16,AP16,AS16,AV16,AY16,BB16)<6,"",SUM(AM16,AP16,AS16,AV16,AY16,BB16)) -> 3.72 | BD16: =IF(BC16="","",INDEX({"A1","A2","A3","B1","B2","B3","C1","C2","D1","D2","E1","E2"},MAX(1,MIN(12,ROUND(BC16,0))))) -> B1 | BE16: B1 | BF16: The score decided the level | BG16: Weights: Complexity 46% · Autonomy 17% · Accountability 15% · Experience 10% · Business impact 7% · Leadership 5% Why: specialists are judged mainly on depth of expertise, then on what they decide alone, what they answer for and their impact. Type of work in the department: delivery work is judged on accuracy and turnaround, so Accountability +5 and Complexity −5. Live: change the department's row on the Weightage Matrix and these weights, the points and the score update. | BH16: At build: Complexity 1.38 + Autonomy 0.51 + Accountability 0.53 + Leadership 0.18 + Experience 0.85 + Business impact 0.28 = 3.72 points → nearest level 4 = B1 Final level: B1 · same as the score | BI16: No rule applied: the score decides. | BJ16: — | BL16: High | BN16: Stable · moves in fewer than 5 of 30 weight tests | BO16: Rated 3 of 12 Start: 3.0 · senior practitioner title Evidence reads like A3: Document quality checks, query solving and CIPC/MCA HTML conversion across UK, CIPC, ESMA work → matches the start KRA: “1. Complete assigned conversion/formatting tasks with >=99% accuracy · zero critical errors 2. Meet 100% of client filing deadlines · no SLA…” Market: A3 = Varied and non-standard work; handles exceptions | BP16: Rated 3 of 12 Start: 3.0 · senior practitioner title Evidence reads like A3: Allocates UK/CIPC/ESMA files; says takes decisions without asking manager when needed → matches the start Market: A3 = Technical / QC / client calls on own work | BQ16: Rated 3.5 of 12 · between A3 and B1 Start: 4.0 · senior practitioner title; 2 direct reports Evidence reads like A3: Allocation, QC and on-time completion of formatting/conversion files sent on to services teams → moved down 0.5 KRA: “1. Complete assigned conversion/formatting tasks with >=99% accuracy · zero critical errors 2. Meet 100% of client filing deadlines · no SLA…” Market: A3 = A module / process, or work with client or regulatory consequences · B1 = A domain or a small team | BR16: Rated 3.5 of 12 · between A3 and B1 Start: 4.0 Evidence reads like A3: Allocates work and solves queries for the team; 2 direct reports → moved down 0.5 Team: 2 direct reports · POD Lead Market: A3 = Not scored in Band A · B1 = IC: mentors and reviews · People: hands-on team lead of 3–5 | BS16: Rated 8.5 of 12 · between C2 and D1 Experience: 17.4 yrs total · 1.0 before IRIS + 16.4 at IRIS = 9.0 on the experience scale Qualification: Undergraduate · below graduate → −0.5 Market: B1 roles typically have 4–8 yrs · IRIS guide 4–7 | BT16: Rated 4 of 12 — a starting estimate. Start: 3.5, the role's accountability scope — what it answers for. Moved +0.5: the survey / manager mapping marks it business-critical. Managers and heads: overwrite this rating on the Weightage sheet with the business impact you see — the score updates at once. Ladder: B1 = Moves a module's, product area's or client account's results | BU16: 1. Complete assigned conversion/formatting tasks with >=99% accuracy · zero critical errors 2. Meet 100% of client filing deadlines · no SLA breaches 3. Maintain average turnaround per assignment within agreed TAT 4. Handle assigned client edits within agreed TAT with client. 5. Develop capabilites to work in more than 2 mandates/products. Ultimate goal should be able to work in all OCR/Formatting mandates. 6. Conduct monthly knowledge sessions in order to Cross-skill team: >=70% capable on at least more than two OCR/Formatting mandates | BZ16: Received · manager annual | CA16: CARBON Mapping Master | CB16: 20 | CC16: • Role / sub-team: Digitizing Associte Service. | CD16: • Key responsibilities include: Cipc mca Uk Qc Eu esma and Eu Dm formatting, Cipc html converion, MCA conversion Allocation And solving quries quality check of word pdf after receiving. • Reported deliverables and outcomes include: UK, MCA and CIPC files are emailed to other services teams after QC; CIPC HTML work is also emailed to the service team. | CE16: • Current capabilities: Ai copilot tool skill; Tools / software used: Both | Abbyy FineReader, Microsoft Web Expression, Carbon tool [Teams chat]. | CF16: • Communications skills. • Presentation skills. | CG16: • Key challenges: Quality of report, RDP issue. • Support required: No input received. | CH16: Complexity: Evidence reads like A3: Document quality checks, query solving and CIPC/MCA HTML conversion across UK, CIPC, ESMA work → matches the start Autonomy: Evidence reads like A3: Allocates UK/CIPC/ESMA files; says takes decisions without asking manager when needed → matches the start Accountability: Evidence reads like A3: Allocation, QC and on-time completion of formatting/conversion files sent on to services teams → moved down 0.5 Leadership: Evidence reads like A3: Allocates work and solves queries for the team; 2 direct reports → moved down 0.5 Business Impact: Moved +0.5: the survey / manager mapping marks it business-critical. | CI16: Common themes in role-holders' answers: am · formatting · processing · specialist · checker · image Common themes in role-holders' answers: files · quality · html · received · correctly · checking Common themes in role-holders' answers: word · pdf · html Common themes in role-holders' answers: accountable · am · every If the work is missed · role-holders' themes: dissatisfied · customers become · affected · company growth. | CJ16: Self-identified: Data, SQL & analytics · Domain, regulatory & XBRL · Communication & presentation · Broader exposure & ownership For the next role: Data, SQL & analytics · Domain, regulatory & XBRL · Communication & presentation · Broader exposure & ownership | CK16: Per-person summary · CARBON Mapping Master | CL16: WHAT THE ROLE DOES: Converts and formats documents into HTML/PDF/Word to filing or web standards, and publishes content · incl. RBI website. At B1: a domain / module, or a small team. Common themes in role-holders' answers: am · formatting · processing · specialist · checker · image KEY RESPONSIBILITIES: Converts and formats documents into HTML/PDF/Word to filing or web standards, and publishes content · incl. RBI website; Domain specialist work; A domain or a small team Common themes in role-holders' answers: files · quality · html · received · correctly · checking DELIVERS: A domain or a small team Common themes in role-holders' answers: word · pdf · html ACCOUNTABLE FOR: A domain or a small team Common themes in role-holders' answers: accountable · am · every DECIDES ALONE: Technical / QC / client calls for the domain SKILLS & KNOWLEDGE · role-holders: OCR/Image procesing TOOLS & SYSTEMS: Carbon applications · Office 365 word · Excel · Abby FineReader · Web Expression HTML Editor COMPETENCIES REQUIRED — must-have ★: Advanced Excel & Productivity Tools · Process Improvement & Quality Mindset OTHER FUNCTIONAL COMPETENCIES: Regulatory & BFSI Domain · XBRL, iXBRL & Taxonomy · AI, GenAI & Prompt Engineering · Time, Priority & Self-Management PROFICIENCY NEEDED AT THIS LEVEL: Core 3 · Future-ready 3 · Functional 3 · Leadership 1 CREDENTIALS: MOS Excel · optional; Lean / Six Sigma · optional SOURCE: Framework + role-holders' themes · 3+ answered — 4 holders, 4 answered the survey; sub-family 30 answered; catalogue RC-048 | CM16: What the role answers for: A domain or a small team. Accountability & Impact rating: 3.5 of 12 · B1-level impact. Leads 2 direct reports. From the survey and manager mapping — critical role: yes; successor named: no. If the work is missed · role-holders' themes: dissatisfied · customers become · affected · company growth. Manager talent mapping — Latest rating: 4 · Potential: High · 9-Box Grid placement: Core Contributor. | CO16: 4 | CP16: 4 | CQ16: High | CR16: Core Contributor | CS16: Ready now | CU16: Yes | CX16: Medium · critical role Yes · only this person — · successor named No | CY16: Janardan Bale · B2, CARBON · Dinesh Sharma · B1, CARBON · Prajakta Mokal · B1, CARBON | CZ16: Name a successor; document the key process; cross-train one person | DA16: 101 | DB16: Meets the level | DC16: 110 | DD16: 105 | DE16: 96 | DF16: 100 | DG16: XBRL & taxonomy, AI / GenAI | DH16: B2: 87% of profile — close | DI16: Evidence: Survey + KRAs | Core: Ownership 4/3, Problem solving 4/3, Communication & collaboration 3/3, Client & quality focus 5/3, Learning agility 3/3, Integrity & compliance 3/3 | Future-ready: AI literacy 3/3, Data literacy 4/3, Digital fluency 3/3, Innovation 3/3 | Functional: Excel & tools 4/3, Quality & process 4/3, Regulatory domain 3/3, XBRL & taxonomy 2/3, AI / GenAI 2/3, Prioritisation 3/3 | Leadership: Developing people 2/2, Decision making 2/2, Strategic acumen 2/2, Influence & change 2/2 | DJ16: Data, SQL & analytics · Domain, regulatory & XBRL · Communication & presentation · Broader exposure & ownership | DL16: AI, GenAI & Prompt Engineering | DM16: Data, SQL & analytics · Domain, regulatory & XBRL · Communication & presentation · Broader exposure & ownership | DO16: No strong match from survey evidence | DP16: Aishwarya Chaulkar · Senior Digitization Associate — 0.87: document, basis., regular, responsibility; Saurav Nirmal · Senior Digitization Associate — 0.59: document, html, word, basis.; Farina Pathan · Senior Digitization Associate — 0.47: html, word, abby, finereader | DQ16: Siddhesh Harishchandra Mali · Consume, Digitization Associate — 0.26 | DR16: POD Lead | DT16: Span: 2 direct reports · layer 8 · Very small team: merge with a neighbouring team or make a POD Lead role | DU16: Digitization Specialist – POD Lead in Digitizing · CARBON, B1 — POD Lead. The work: Converts and formats documents into HTML/PDF/Word to filing or web standards, and publishes content · incl. RBI website. At this level the role owns a domain / module, or a small team. Key responsibilities: Converts and formats documents into HTML/PDF/Word to filing or web standards, and publishes content · incl. RBI website; Domain specialist work; A domain or a small team. Holders describe it with: files · quality · html · received · correctly · checking. Leads 2 direct reports. | DV16: Hire as: Specialist / QC Analyst — IRIS B1 Specialist · POD Lead · POD Lead Market level: P3 / M2 · SFIA 4 Enable Experience: 4–7 yrs · Education: Graduate · commerce preferred Equivalent titles at peers: Accenture Operations – L9 Team Lead · IRIS Vs Competitor Benchmark — operations roles – Team Lead / Quality Lead Credentials: MOS Excel · optional; Lean / Six Sigma · optional Must already know: Accuracy and SLA discipline; data confidentiality | DW16: FUNCTIONAL — skill level 3 of 5 · Practitioner ★ Advanced Excel & Productivity Tools: Uses advanced Excel, Word, HTML and conversion tools fluently ★ Process Improvement & Quality Mindset: Delivers right-first-time; improves own checklists • Regulatory & BFSI Domain: Knows the relevant regulators, returns and rules • XBRL, iXBRL & Taxonomy: Tags and validates filings accurately for a market • AI, GenAI & Prompt Engineering: Uses AI / LLM tools in own work and validates output • Time, Priority & Self-Management: Manages volume and deadlines without slippage CORE — skill level 3 of 5 · Practitioner • Ownership & Accountability: Owns a module, client or process end to end; fixes root causes • Problem Solving & Critical Thinking: Analyses non-routine problems; finds root causes • Communication & Collaboration: Communicates with clients / stakeholders; collaborates across teams • Client & Quality Focus: Anticipates client needs; prevents errors in own area • Learning Agility & Adaptability: Adapts to changing priorities; learns independently • Integrity, Compliance & Information Security: Spots and escalates compliance / security risks FUTURE-READY — skill level 3 of 5 · Practitioner • AI Literacy & Augmentation: Builds AI into own workflow; evaluates accuracy and bias • Data Literacy & Analytics: Analyses data · SQL, BI, advanced Excel to find insight • Digital Fluency & Automation: Automates own repetitive work · macros, scripts, workflows • Innovation & Continuous Improvement: Delivers measurable improvements in own area LEADERSHIP — skill level 1 of 5 · Awareness • Leading & Developing People: Not required • Decision Making & Delegation: Not required • Strategic & Business Acumen: Not required • Influence & Change Leadership: Not required SKILLS · from role-holders and HRIS: OCR/Image procesing TOOLS: Carbon applications · Office 365 word · Excel · Abby FineReader · Web Expression HTML Editor ★ = must-have for the family. Scale: 1 Awareness · 2 Working · 3 Practitioner · 4 Advanced · 5 Expert. | DX16: Draft — generated from the framework; hiring-manager review pending · HR Super Master, sheet T5. 1. [Advanced Excel & Productivity Tools · level 3] Tell me about recent work that shows this: "Uses advanced Excel, Word, HTML and conversion tools fluently". What exactly did you do, how, and what was the result? Assess with: Practical test. 2. [Process Improvement & Quality Mindset · level 3] Tell me about recent work that shows this: "Delivers right-first-time; improves own checklists". What exactly did you do, how, and what was the result? Assess with: Work sample / case. 3. [Regulatory & BFSI Domain · level 3] Give an example that shows you can do this: "Knows the relevant regulators, returns and rules". Assess with: Domain interview. 4. [XBRL, iXBRL & Taxonomy · level 3] Give an example that shows you can do this: "Tags and validates filings accurately for a market". Assess with: Tagging test on a real filing. 5. [AI, GenAI & Prompt Engineering · level 3] Give an example that shows you can do this: "Uses AI / LLM tools in own work and validates output". Assess with: Work sample / portfolio. 6. [Ownership & Accountability · level 3] Tell me about a piece of work you owned from start to finish. What went wrong, and what did you do about it? Listen for: "Owns a module, client or process end to end; fixes root causes". 7. [Problem Solving & Critical Thinking · level 3] Walk me through a problem you solved recently: how did you find the root cause and choose the fix? Listen for: "Analyses non-routine problems; finds root causes". 8. [Client & Quality Focus · level 3] Tell me about a time a client or user was unhappy with your work. What did you do? Listen for: "Anticipates client needs; prevents errors in own area". 9. [AI Literacy & Augmentation · level 3] Show me how you have used an AI tool in your work. How did you check its output? Listen for: "Builds AI into own workflow; evaluates accuracy and bias". Fit check: Why this role, why IRIS · regulatory reporting / XBRL / regtech, and what would you change in your first 90 days? | DY16: Market level: P3 / M2 · SFIA 4 Enable Typical title: Specialist / QC Analyst At peers: Accenture Operations – L9 Team Lead · IRIS Vs Competitor Benchmark — operations roles: Team Lead / Quality Lead Typical experience: 4–8 yrs · IRIS guide 4–7 Standard: COPC CX Standard; ISO 9001 | DZ16: 4–7 yrs | EA16: 5–8 · 4–8 | EB16: Specialist / QC Analyst | EC16: Accenture Operations: L9 Team Lead · IRIS Vs Competitor Benchmark — operations roles: Team Lead / Quality Lead | ED16: COPC CX Standard · leadership & planning, people, processes, performance; ISO 9001; Lean / Six Sigma | EE16: Core 3 · Future 3 · Functional 3 · Leadership 2 | EG16: ✓ HRIS: 17.4 yrs, Undergraduate, 2 direct reports ✓ Survey: 20 of 20 questions answered ✓ KRAs: submitted, reported deliverables ✓ Manager mapping: rating, potential, 9-box ✗ Job description: not on file | EK16: Survey: summary on file · KRAs: received · Experience: on file
