Workbook
Name LMH_KEY: 'Backend Data'!$A$7:$A$9
Name LMH_PTS: 'Backend Data'!$C$7:$C$9
Name LMH_STEP: 'Backend Data'!$D$7:$D$9
Name B_LVL: 'Backend Data'!$A$14:$A$30
Name B_VAL: 'Backend Data'!$B$14:$B$30
Name B_RANK: 'Backend Data'!$D$14:$D$30
Name LAD_STD: 'Backend Data'!$E$14:$E$25
Name LAD_PC: 'Backend Data'!$F$14:$F$27
Name LIST_LEVELS: 'Backend Data'!$A$14:$A$30
Name RBD_KEY: 'Backend Data'!$A$34:$A$413
Name RBD_C: 'Backend Data'!$E$34:$E$413
Name RBD_Au: 'Backend Data'!$F$34:$F$413
Name RBD_Ac: 'Backend Data'!$G$34:$G$413
Name RBD_L: 'Backend Data'!$H$34:$H$413
Name RBD_BI: 'Backend Data'!$I$34:$I$413
Name RBD_Exp: 'Backend Data'!$J$34:$J$413
Name RBD_Edu: 'Backend Data'!$K$34:$K$413
Name LIST_LMH: 'Backend Data'!$A$416:$A$418
Name DL_KEY: '5. Department Ladder'!$Y$7:$Y$297
Name DL_C: '5. Department Ladder'!$J$7:$J$297
Name DL_Au: '5. Department Ladder'!$K$7:$K$297
Name DL_Ac: '5. Department Ladder'!$L$7:$L$297
Name DL_L: '5. Department Ladder'!$M$7:$M$297
Name DL_BI: '5. Department Ladder'!$N$7:$N$297
Name DL_Exp: '5. Department Ladder'!$O$7:$O$297
Name DL_Edu: '5. Department Ladder'!$P$7:$P$297

Sheet 1. How to use
A1: Business-Head Workbook — how to use it
A2: Read this first · five minutes.
A3: IRIS · Job Architecture & Job Design · Final v1.14 · October 2026 · Internal — Confidential · HR only
A5: What this is | B5: Every person at IRIS, top down from the CEO, with the band HR proposes and the evidence behind it. You review it, weigh what matters for each role, assess each person, and the final proposed band updates itself.
A6: 1 · Read the row | B6: Core details, then what the employee and their manager told us. 'All their data ▸' opens everything we hold on the person in 3. Raw Data; '◂ Back' returns.
A7: 2 · Weightage · L / M / H | B7: How much each of the seven parameters counts for the role: Complexity & Expertise, Autonomy & Decision, Accountability & Impact, Leadership & Strategy, Business Impact, Experience, Education. It comes from 5. Department Ladder, which starts from the family's RB sheet. Change it there for a whole role, or type L, M or H on a person's row for that person only.
A8: 3 · Your assessment · L / M / H | B8: Against what the RB sheet describes for the HR proposed band: Medium = meets it, Low = works at the level below on that parameter, High = already works at the level above. Everything starts at Medium, so the final band equals HR's until you change something. 'What the data shows' gives our reading of the evidence to start from.
A9: 4 · The band moves live | B9: Weighted net = Σ weightage × assessment ÷ Σ weightage, from −1 to +1. At +0.5 or more the person moves one level up; at −0.5 or less one level down. Use the override for any other band, and say why in your comment.
A10: 5 · The manager check | B10: Shown live on every row: under a head at C1 or above a reportee sits in a lower band; below C1 a reportee sits at least one level below the manager; CEO with CXOs is the agreed exception. A ⚠ means your change breaks it — adjust the person or their manager.
A11: Market benchmark | B11: Each row shows the market weight of each parameter for the role group, the market experience range, the education and span norms and the market codes — sheet 4 has every source.
A12: HR proposed band | B12: From the model · six ratings × market-derived weights and rules R1–R13 · then the top-down manager rule HR agreed on 12 October 2026: 68 people move down, pay and title protected for one cycle, 8 move up. Department and function heads sit in Executive Leadership · Business Head.
A13: Input from benchmarking | B13: The same six ratings on the plain market-average weights, without IRIS's adjustments, rounded to a level, with the person's experience against the market range for it.
A14: Colours | B14: Yellow = yours to edit · red = something missing · band colours on levels.
A15: Privacy | B15: HR and business heads only. Survey content is shown against names by HR's decision. Pay is not in this file.
A17: Sheets
A18: 1. How to use
A19: 2. Talent Mapping
A20: 3. Raw Data
A21: 4. Market Benchmark
A22: 5. Department Ladder
A23: RB · Administration, Legal & Se
A24: RB · Business Analysis
A25: RB · Consulting & Professional
A26: RB · Customer Success & Support
A27: RB · Data & Analytics
A28: RB · Data Operations & Digitiza
... A43: Backend Data

Sheet 2. Talent Mapping
A1: Talent Mapping — business heads: review, weigh and propose the band | Q1: ◂ Start
A2: Sheet 2 · One row per person, top down from the CEO. Read left to right: who → what they and their manager told us, with a link to all their data → how much each parameter counts · L/M/H → your assessment against the band · L/M/H → the market benchmark → HR's proposed band → what benchmarking says → the final proposed band, which updates the moment you change any L, M or H. Yellow = yours to edit.
A3: IRIS · Job Architecture & Job Design · Final v1.14 · October 2026 · Internal — Confidential · HR only
A4: Section colours: each column group has its own header colour and a matching light tint | E4: Changed vs current | G4: Level up | H4: Level down · pay & title protected | J4: Newly mapped | K4: Player-Coach · B+ · C+ | M4: RED = critical input needed · says what and who | P4: YELLOW = to complete or edit | R4: GREY = pay · set later
A5: CORE EMPLOYEE DETAILS | S5: SUMMARY OF RESPONSES RECEIVED — full detail in 3. Raw Data | Y5: WEIGHTAGE · L / M / H — from 5. Department Ladder; overwrite for this person | AF5: YOUR ASSESSMENT · L / M / H against the band — Medium = meets it | AM5: MARKET BENCHMARK — this role group at the HR proposed level | AY5: PROPOSAL | BM5: ENGINE — points and steps, live
A6: Business | B6: Department | C6: Layer from the CEO | D6: Emp ID | E6: Employee name | F6: Current designation | G6: Proposed designation | H6: Job family · v1.14 | I6: Sub-family | J6: Track | K6: Role ID | L6: Reporting manager | M6: Manager Emp ID | N6: Total exp. · yrs | O6: Exp. at IRIS · yrs | P6: Qualification | Q6: Current level · as is | R6: Model level · v1.13 | S6: Survey · questions answered | T6: What they shared · summary | U6: KRAs received · summary | V6: Manager talent mapping · rating · potential · 9-box · readiness | W6: What the data shows · vs HR proposed band | X6: All their data ▸ | Y6: Complexity & Expertise · weightage | Z6: Autonomy & Decision · weightage | AA6: Accountability & Impact · weightage | AB6: Leadership & Strategy · weightage | AC6: Business Impact · weightage | AD6: Experience · weightage | AE6: Education · weightage | AF6: Complexity & Expertise · assessment | AG6: Autonomy & Decision · assessment | AH6: Accountability & Impact · assessment | AI6: Leadership & Strategy · assessment | AJ6: Business Impact · assessment | AK6: Experience · assessment | AL6: Education · assessment | AM6: Market weight · Complexity & Expertise % | AN6: Market weight · Autonomy & Decision % | AO6: Market weight · Accountability & Impact % | AP6: Market weight · Leadership & Strategy % | AQ6: Market weight · Business Impact % | AR6: Market weight · Experience % | AS6: Market weight · Education % | AT6: Market experience · yrs | AU6: Education norm | AV6: Span norm | AW6: Radford / Mercer · SFIA 9 | AX6: References | AY6: HR proposed band · market benchmark and people inputs | AZ6: HR proposed · band and title | BA6: How HR set it | BB6: Input from benchmarking | BC6: Benchmarking · how | BD6: Weighted net · −1 to +1, live | BE6: Final proposed band · business inputs, live | BF6: Business head override · optional | BG6: FINAL PROPOSED BAND | BH6: Band | BI6: Move vs HR proposed | BJ6: Manager's final proposed band | BK6: Manager rule check · live | BL6: Business head comment | BM6: C points | BN6: Au points | BO6: Ac points | BP6: L points | BQ6: BI points | BR6: Exp points | BS6: Edu points | BT6: C step | BU6: Au step | BV6: Ac step | BW6: L step | BX6: BI step | BY6: Exp step | BZ6: Edu step | CA6: Ladder key
A7: Corporate | B7: Management | C7: 0 | D7: IRIS0001 | E7: Balachandran K | F7: CEO | G7: Chief Executive Officer | H7: Executive Leadership | I7: Business Head | J7: People Manager | K7: RC-EL-BH-E2 | L7: — · top of the organisation | M7: Not in this file | N7: 32.1 | O7: 22.1 | P7: MBA | Q7: Not in current mapping files | R7: E2 | S7: 0 of 20 | T7: Complexity: Evidence: no survey answers or KRAs on file → rating stays at the start Autonomy: Evidence: no survey answers or KRAs on file → rating stays at the start Accountability: Evidence: no survey answers or KRAs on file → rating stays at the start Leadership: Evidence: no survey answers or KRAs on file → rating stays at the start Business Impact: No … | U7: KRAs not received · manager to supply | V7: Latest rating: Not rated · manager · 9-box: Not placed · manager · Readiness: No rating data | W7: C M · Au M · Ac M · L M · BI M · Exp M · 32.1 yrs vs 20+ yrs · Edu M · MBA | X7: Open ▸ | Y7: =IFERROR(INDEX(DL_C,MATCH($CA7,DL_KEY,0)),"M") -> H | Z7: =IFERROR(INDEX(DL_Au,MATCH($CA7,DL_KEY,0)),"M") -> M | AA7: =IFERROR(INDEX(DL_Ac,MATCH($CA7,DL_KEY,0)),"M") -> M | AB7: =IFERROR(INDEX(DL_L,MATCH($CA7,DL_KEY,0)),"M") -> M | AC7: =IFERROR(INDEX(DL_BI,MATCH($CA7,DL_KEY,0)),"M") -> L | AD7: =IFERROR(INDEX(DL_Exp,MATCH($CA7,DL_KEY,0)),"M") -> L | AE7: =IFERROR(INDEX(DL_Edu,MATCH($CA7,DL_KEY,0)),"M") -> L | AF7: M | AG7: M | AH7: M | AI7: M | AJ7: M | AK7: M | AL7: M | AM7: 0.363 | AN7: 0.19 | AO7: 0.113 | AP7: 0.2 | AQ7: 0.087 | AR7: 0.04 | AS7: 0.01 | AT7: 20+ yrs | AU7: Postgraduate / professional qualification; proven business leadership | AV7: Executive team | AW7: E6 · SFIA 7 | AX7: S46–S51 Korn Ferry Hay evaluations · S04, S52 Mercer IPE · S53–S57 NHS, UK NJC/PSC, GLPC, SJC, US OPM point-factor plans · S58 McKinsey skills-based hiring · S60 WEF skills-first · S61 EY India 2026 · the Experience / Education split is an IRIS rule · S32 Google, Microsoft, Amazon · S33 Infosys · S35 Accenture India · IRIS experience guide · S01 Aon Radford · S02 Pave · S08 SFIA 9 · S03 Mercer career levels | AY7: E2 | AZ7: Band E · Enterprise leadership · Chief Executive Officer | BA7: Model E2 from the six ratings, the market-derived weights and rules R1–R13 · then Top of the reporting line | BB7: E2 | BC7: The six ratings on the market-average weights of Bands D–E · Leadership score 12.00 → E2 · Hay, Mercer IPE and public plans · experience 32.1 yrs vs the E2 market range 20+ yrs | BD7: =IF(SUM(BM7,BN7,BO7,BP7,BQ7,BR7,BS7)=0,0,(BM7*BT7+BN7*BU7+BO7*BV7+BP7*BW7+BQ7*BX7+BR7*BY7+BS7*BZ7)/SUM(BM7,BN7,BO7,BP7,BQ7,BR7,BS7)) -> 0 | BE7: =IF(LEFT(AY7,1)="X",AY7,IF(OR(AY7="B+",AY7="C+"),INDEX(LAD_PC,MAX(1,MIN(14,MATCH(AY7,LAD_PC,0)+IF(BD7>=0.5,1,IF(BD7<=-0.5,-1,0))))),INDEX(LAD_STD,MAX(1,MIN(12,MATCH(AY7,LAD_STD,0)+IF(BD7>=0.5,1,IF(BD7<=-0.5,-1,0))))))) -> E2 | BG7: =IF(BF7<>"",BF7,BE7) -> E2 | BH7: =IFERROR(CHOOSE(INDEX(B_RANK,MATCH(BG7,B_LVL,0)),"Band A","Band B","B+ · Player-Coach","Band C","C+ · Player-Coach","Band D","Band E"),"Band X · Consultant") -> Band E | BI7: =IF(BG7=AY7,"• Same",IF(INDEX(B_VAL,MATCH(BG7,B_LVL,0))>INDEX(B_VAL,MATCH(AY7,B_LVL,0)),"▲ Up","▼ Down")) -> • Same | BJ7: =IF(OR($M7="",$M7="—",$M7="Not in this file"),"",IFERROR(INDEX($BG$7:$BG$592,MATCH($M7,$D$7:$D$592,0)),"")) | BK7: =IFERROR(IF(BJ7="","—",IF(OR(LEFT(BG7,1)="X",LEFT(BJ7,1)="X"),"—",IF(AND(LEFT(BG7,1)="E",LEFT(BJ7,1)="E"),"Exception · Band E",IF(AND(INDEX(B_VAL,MATCH(BJ7,B_LVL,0))>=7,INDEX(B_RANK,MATCH(BG7,B_LVL,0))>=INDEX(B_RANK,MATCH(BJ7,B_LVL,0))),"⚠ Same band as a head manager",IF(INDEX(B_VAL,MATCH(BG7,B_LVL,0))>=INDEX(B_VAL,MATCH(BJ7,B_LVL,0)),"⚠ At or above the manager's level","OK"))))),"—") -> — | BM7: =IFERROR(INDEX(LMH_PTS,MATCH(Y7,LMH_KEY,0)),0) -> 9 | BN7: =IFERROR(INDEX(LMH_PTS,MATCH(Z7,LMH_KEY,0)),0) -> 3 | BO7: =IFERROR(INDEX(LMH_PTS,MATCH(AA7,LMH_KEY,0)),0) -> 3 | BP7: =IFERROR(INDEX(LMH_PTS,MATCH(AB7,LMH_KEY,0)),0) -> 3 | BQ7: =IFERROR(INDEX(LMH_PTS,MATCH(AC7,LMH_KEY,0)),0) -> 1 | BR7: =IFERROR(INDEX(LMH_PTS,MATCH(AD7,LMH_KEY,0)),0) -> 1 | BS7: =IFERROR(INDEX(LMH_PTS,MATCH(AE7,LMH_KEY,0)),0) -> 1 | BT7: =IFERROR(INDEX(LMH_STEP,MATCH(AF7,LMH_KEY,0)),0) -> 0 | BU7: =IFERROR(INDEX(LMH_STEP,MATCH(AG7,LMH_KEY,0)),0) -> 0 | BV7: =IFERROR(INDEX(LMH_STEP,MATCH(AH7,LMH_KEY,0)),0) -> 0 | BW7: =IFERROR(INDEX(LMH_STEP,MATCH(AI7,LMH_KEY,0)),0) -> 0 | BX7: =IFERROR(INDEX(LMH_STEP,MATCH(AJ7,LMH_KEY,0)),0) -> 0 | BY7: =IFERROR(INDEX(LMH_STEP,MATCH(AK7,LMH_KEY,0)),0) -> 0 | BZ7: =IFERROR(INDEX(LMH_STEP,MATCH(AL7,LMH_KEY,0)),0) -> 0 | CA7: Corporate|Management|Chief Executive Officer|E2|DE
A8: CARBON | B8: CRO - Carbon | C8: 1 | D8: IRIS2478 | E8: Dixit Jasani | F8: Chief Revenue Officer- Enterprise Division | G8: Chief Revenue Officer | H8: Executive Leadership | I8: Business Head | J8: People Manager | K8: RC-EL-BH-E1 | L8: Balachandran K | M8: IRIS0001 | N8: 27.9 | O8: 0.6 | P8: PGDM | Q8: Not in current mapping files | R8: E1 | S8: 0 of 20 | T8: Complexity: Evidence: no survey answers or KRAs on file → rating stays at the start Autonomy: Evidence: no survey answers or KRAs on file → rating stays at the start Accountability: Evidence: no survey answers or KRAs on file → rating stays at the start Leadership: Evidence: no survey answers or KRAs on file → rating stays at the start Business Impact: No … | U8: KRAs not received · manager to supply | V8: Latest rating: Not rated · manager · 9-box: Not placed · manager · Readiness: No rating data | W8: C M · Au M · Ac M · L M · BI M · Exp M · 27.9 yrs vs 20+ yrs · Edu M · PGDM | X8: Open ▸ | Y8: =IFERROR(INDEX(DL_C,MATCH($CA8,DL_KEY,0)),"M") -> H | Z8: =IFERROR(INDEX(DL_Au,MATCH($CA8,DL_KEY,0)),"M") -> M | AA8: =IFERROR(INDEX(DL_Ac,MATCH($CA8,DL_KEY,0)),"M") -> M | AB8: =IFERROR(INDEX(DL_L,MATCH($CA8,DL_KEY,0)),"M") -> M | AC8: =IFERROR(INDEX(DL_BI,MATCH($CA8,DL_KEY,0)),"M") -> L | AD8: =IFERROR(INDEX(DL_Exp,MATCH($CA8,DL_KEY,0)),"M") -> L | AE8: =IFERROR(INDEX(DL_Edu,MATCH($CA8,DL_KEY,0)),"M") -> L | AF8: M | AG8: M | AH8: M | AI8: M | AJ8: M | AK8: M | AL8: M | AM8: 0.363 | AN8: 0.19 | AO8: 0.113 | AP8: 0.2 | AQ8: 0.087 | AR8: 0.04 | AS8: 0.01 | AT8: 20+ yrs | AU8: Postgraduate / professional qualification; business leadership record | AV8: 5–8 function heads | AW8: E5 · SFIA 7 | AX8: S46–S51 Korn Ferry Hay evaluations · S04, S52 Mercer IPE · S53–S57 NHS, UK NJC/PSC, GLPC, SJC, US OPM point-factor plans · S58 McKinsey skills-based hiring · S60 WEF skills-first · S61 EY India 2026 · the Experience / Education split is an IRIS rule · S32 Google, Microsoft, Amazon · S33 Infosys · S35 Accenture India · IRIS experience guide · S01 Aon Radford · S02 Pave · S08 SFIA 9 · S03 Mercer career levels | AY8: E1 | AZ8: Band E · Enterprise leadership · CXO / President | BA8: Model E1 from the six ratings, the market-derived weights and rules R1–R13 · then Band E with Band E · agreed exception · manager E2 | BB8: E1 | BC8: The six ratings on the market-average weights of Bands D–E · Leadership score 11.05 → E1 · Hay, Mercer IPE and public plans · experience 27.9 yrs vs the E1 market range 20+ yrs | BD8: =IF(SUM(BM8,BN8,BO8,BP8,BQ8,BR8,BS8)=0,0,(BM8*BT8+BN8*BU8+BO8*BV8+BP8*BW8+BQ8*BX8+BR8*BY8+BS8*BZ8)/SUM(BM8,BN8,BO8,BP8,BQ8,BR8,BS8)) -> 0 | BE8: =IF(LEFT(AY8,1)="X",AY8,IF(OR(AY8="B+",AY8="C+"),INDEX(LAD_PC,MAX(1,MIN(14,MATCH(AY8,LAD_PC,0)+IF(BD8>=0.5,1,IF(BD8<=-0.5,-1,0))))),INDEX(LAD_STD,MAX(1,MIN(12,MATCH(AY8,LAD_STD,0)+IF(BD8>=0.5,1,IF(BD8<=-0.5,-1,0))))))) -> E1 | BG8: =IF(BF8<>"",BF8,BE8) -> E1 | BH8: =IFERROR(CHOOSE(INDEX(B_RANK,MATCH(BG8,B_LVL,0)),"Band A","Band B","B+ · Player-Coach","Band C","C+ · Player-Coach","Band D","Band E"),"Band X · Consultant") -> Band E | BI8: =IF(BG8=AY8,"• Same",IF(INDEX(B_VAL,MATCH(BG8,B_LVL,0))>INDEX(B_VAL,MATCH(AY8,B_LVL,0)),"▲ Up","▼ Down")) -> • Same | BJ8: =IF(OR($M8="",$M8="—",$M8="Not in this file"),"",IFERROR(INDEX($BG$7:$BG$592,MATCH($M8,$D$7:$D$592,0)),"")) -> E2 | BK8: =IFERROR(IF(BJ8="","—",IF(OR(LEFT(BG8,1)="X",LEFT(BJ8,1)="X"),"—",IF(AND(LEFT(BG8,1)="E",LEFT(BJ8,1)="E"),"Exception · Band E",IF(AND(INDEX(B_VAL,MATCH(BJ8,B_LVL,0))>=7,INDEX(B_RANK,MATCH(BG8,B_LVL,0))>=INDEX(B_RANK,MATCH(BJ8,B_LVL,0))),"⚠ Same band as a head manager",IF(INDEX(B_VAL,MATCH(BG8,B_LVL,0))>=INDEX(B_VAL,MATCH(BJ8,B_LVL,0)),"⚠ At or above the manager's level","OK"))))),"—") -> Exception · Band E | BM8: =IFERROR(INDEX(LMH_PTS,MATCH(Y8,LMH_KEY,0)),0) -> 9 | BN8: =IFERROR(INDEX(LMH_PTS,MATCH(Z8,LMH_KEY,0)),0) -> 3 | BO8: =IFERROR(INDEX(LMH_PTS,MATCH(AA8,LMH_KEY,0)),0) -> 3 | BP8: =IFERROR(INDEX(LMH_PTS,MATCH(AB8,LMH_KEY,0)),0) -> 3 | BQ8: =IFERROR(INDEX(LMH_PTS,MATCH(AC8,LMH_KEY,0)),0) -> 1 | BR8: =IFERROR(INDEX(LMH_PTS,MATCH(AD8,LMH_KEY,0)),0) -> 1 | BS8: =IFERROR(INDEX(LMH_PTS,MATCH(AE8,LMH_KEY,0)),0) -> 1 | BT8: =IFERROR(INDEX(LMH_STEP,MATCH(AF8,LMH_KEY,0)),0) -> 0 | BU8: =IFERROR(INDEX(LMH_STEP,MATCH(AG8,LMH_KEY,0)),0) -> 0 | BV8: =IFERROR(INDEX(LMH_STEP,MATCH(AH8,LMH_KEY,0)),0) -> 0 | BW8: =IFERROR(INDEX(LMH_STEP,MATCH(AI8,LMH_KEY,0)),0) -> 0 | BX8: =IFERROR(INDEX(LMH_STEP,MATCH(AJ8,LMH_KEY,0)),0) -> 0 | BY8: =IFERROR(INDEX(LMH_STEP,MATCH(AK8,LMH_KEY,0)),0) -> 0 | BZ8: =IFERROR(INDEX(LMH_STEP,MATCH(AL8,LMH_KEY,0)),0) -> 0 | CA8: CARBON|CRO - Carbon|Chief Revenue Officer|E1|DE
A9: CARBON | B9: CARBON Business Head | C9: 2 | D9: IRIS0391 | E9: Anuradha RK | F9: Business Head | G9: Business Head | H9: Executive Leadership | I9: Business Head | J9: People Manager | K9: RC-EL-BH-D2 | L9: Dixit Jasani | M9: IRIS2478 | N9: 17.1 | O9: 16.4 | P9: MBA | Q9: Not in current mapping files | R9: D2 | S9: 0 of 20 | T9: Complexity: Evidence: no survey answers or KRAs on file → rating stays at the start Autonomy: Evidence: no survey answers or KRAs on file → rating stays at the start Accountability: Evidence: no survey answers or KRAs on file → rating stays at the start Leadership: Evidence: no survey answers or KRAs on file → rating stays at the start Business Impact: No … | U9: KRAs not received · manager to supply | V9: Latest rating: Not rated · manager · 9-box: Not placed · manager · Readiness: No rating data | W9: C L · Au L · Ac L · L L · BI L · Exp L · 17.1 yrs vs 18–24 yrs · Edu M · MBA | X9: Open ▸ | Y9: =IFERROR(INDEX(DL_C,MATCH($CA9,DL_KEY,0)),"M") -> H | Z9: =IFERROR(INDEX(DL_Au,MATCH($CA9,DL_KEY,0)),"M") -> M | AA9: =IFERROR(INDEX(DL_Ac,MATCH($CA9,DL_KEY,0)),"M") -> M | AB9: =IFERROR(INDEX(DL_L,MATCH($CA9,DL_KEY,0)),"M") -> M | AC9: =IFERROR(INDEX(DL_BI,MATCH($CA9,DL_KEY,0)),"M") -> L | AD9: =IFERROR(INDEX(DL_Exp,MATCH($CA9,DL_KEY,0)),"M") -> L | AE9: =IFERROR(INDEX(DL_Edu,MATCH($CA9,DL_KEY,0)),"M") -> L | AF9: M | AG9: M | AH9: M | AI9: M | AJ9: M | AK9: M | AL9: M | AM9: 0.363 | AN9: 0.19 | AO9: 0.113 | AP9: 0.2 | AQ9: 0.087 | AR9: 0.04 | AS9: 0.01 | AT9: 18–24 yrs | AU9: Postgraduate / professional qualification preferred | AV9: 5–8 AVPs / heads | AW9: E3–E4 · SFIA 7 Set strategy | AX9: S46–S51 Korn Ferry Hay evaluations · S04, S52 Mercer IPE · S53–S57 NHS, UK NJC/PSC, GLPC, SJC, US OPM point-factor plans · S58 McKinsey skills-based hiring · S60 WEF skills-first · S61 EY India 2026 · the Experience / Education split is an IRIS rule · S32 Google, Microsoft, Amazon · S33 Infosys · S35 Accenture India · IRIS experience guide · S01 Aon Radford · S02 Pave · S08 SFIA 9 · S03 Mercer career levels | AY9: D2 | AZ9: Band D · Business leadership · Senior Vice President / Business Head | BA9: Model D2 from the six ratings, the market-derived weights and rules R1–R13 · then No change · already below the manager | BB9: D1 | BC9: The six ratings on the market-average weights of Bands D–E · Leadership score 9.02 → D1 · Hay, Mercer IPE and public plans · experience 17.1 yrs vs the D1 market range 15–20 yrs | BD9: =IF(SUM(BM9,BN9,BO9,BP9,BQ9,BR9,BS9)=0,0,(BM9*BT9+BN9*BU9+BO9*BV9+BP9*BW9+BQ9*BX9+BR9*BY9+BS9*BZ9)/SUM(BM9,BN9,BO9,BP9,BQ9,BR9,BS9)) -> 0 | BE9: =IF(LEFT(AY9,1)="X",AY9,IF(OR(AY9="B+",AY9="C+"),INDEX(LAD_PC,MAX(1,MIN(14,MATCH(AY9,LAD_PC,0)+IF(BD9>=0.5,1,IF(BD9<=-0.5,-1,0))))),INDEX(LAD_STD,MAX(1,MIN(12,MATCH(AY9,LAD_STD,0)+IF(BD9>=0.5,1,IF(BD9<=-0.5,-1,0))))))) -> D2 | BG9: =IF(BF9<>"",BF9,BE9) -> D2 | BH9: =IFERROR(CHOOSE(INDEX(B_RANK,MATCH(BG9,B_LVL,0)),"Band A","Band B","B+ · Player-Coach","Band C","C+ · Player-Coach","Band D","Band E"),"Band X · Consultant") -> Band D | BI9: =IF(BG9=AY9,"• Same",IF(INDEX(B_VAL,MATCH(BG9,B_LVL,0))>INDEX(B_VAL,MATCH(AY9,B_LVL,0)),"▲ Up","▼ Down")) -> • Same | BJ9: =IF(OR($M9="",$M9="—",$M9="Not in this file"),"",IFERROR(INDEX($BG$7:$BG$592,MATCH($M9,$D$7:$D$592,0)),"")) -> E1 | BK9: =IFERROR(IF(BJ9="","—",IF(OR(LEFT(BG9,1)="X",LEFT(BJ9,1)="X"),"—",IF(AND(LEFT(BG9,1)="E",LEFT(BJ9,1)="E"),"Exception · Band E",IF(AND(INDEX(B_VAL,MATCH(BJ9,B_LVL,0))>=7,INDEX(B_RANK,MATCH(BG9,B_LVL,0))>=INDEX(B_RANK,MATCH(BJ9,B_LVL,0))),"⚠ Same band as a head manager",IF(INDEX(B_VAL,MATCH(BG9,B_LVL,0))>=INDEX(B_VAL,MATCH(BJ9,B_LVL,0)),"⚠ At or above the manager's level","OK"))))),"—") -> OK | BM9: =IFERROR(INDEX(LMH_PTS,MATCH(Y9,LMH_KEY,0)),0) -> 9 | BN9: =IFERROR(INDEX(LMH_PTS,MATCH(Z9,LMH_KEY,0)),0) -> 3 | BO9: =IFERROR(INDEX(LMH_PTS,MATCH(AA9,LMH_KEY,0)),0) -> 3 | BP9: =IFERROR(INDEX(LMH_PTS,MATCH(AB9,LMH_KEY,0)),0) -> 3 | BQ9: =IFERROR(INDEX(LMH_PTS,MATCH(AC9,LMH_KEY,0)),0) -> 1 | BR9: =IFERROR(INDEX(LMH_PTS,MATCH(AD9,LMH_KEY,0)),0) -> 1 | BS9: =IFERROR(INDEX(LMH_PTS,MATCH(AE9,LMH_KEY,0)),0) -> 1 | BT9: =IFERROR(INDEX(LMH_STEP,MATCH(AF9,LMH_KEY,0)),0) -> 0 | BU9: =IFERROR(INDEX(LMH_STEP,MATCH(AG9,LMH_KEY,0)),0) -> 0 | BV9: =IFERROR(INDEX(LMH_STEP,MATCH(AH9,LMH_KEY,0)),0) -> 0 | BW9: =IFERROR(INDEX(LMH_STEP,MATCH(AI9,LMH_KEY,0)),0) -> 0 | BX9: =IFERROR(INDEX(LMH_STEP,MATCH(AJ9,LMH_KEY,0)),0) -> 0 | BY9: =IFERROR(INDEX(LMH_STEP,MATCH(AK9,LMH_KEY,0)),0) -> 0 | BZ9: =IFERROR(INDEX(LMH_STEP,MATCH(AL9,LMH_KEY,0)),0) -> 0 | CA9: CARBON|CARBON Business Head|Business Head|D2|DE
A10: CARBON | B10: Customer Experience | C10: 3 | D10: IRIS2359 | E10: Suman Adhikary | F10: Senior Vice President - Customer Experience | G10: Senior Vice President – Customer Experience | H10: Executive Leadership | I10: Business Head | J10: People Manager | K10: RC-EL-BH-D1 | L10: Anuradha RK | M10: IRIS0391 | N10: 28.7 | O10: 1.5 | P10: B.E | Q10: Not in current mapping files | R10: D1 | S10: 0 of 20 | T10: Complexity: Evidence: no survey answers or KRAs on file → rating stays at the start Autonomy: Evidence: no survey answers or KRAs on file → rating stays at the start Accountability: Evidence: no survey answers or KRAs on file → rating stays at the start Leadership: Evidence: no survey answers or KRAs on file → rating stays at the start Business Impact: No … | U10: KRAs not received · manager to supply | V10: Latest rating: Not rated · manager · 9-box: Underperformer / Exit Risk · Readiness: No rating data | W10: C H · Au H · Ac H · L H · BI H · Exp H · 28.7 yrs vs 12–17 yrs · Edu L · B.E | X10: Open ▸ | Y10: =IFERROR(INDEX(DL_C,MATCH($CA10,DL_KEY,0)),"M") -> H | Z10: =IFERROR(INDEX(DL_Au,MATCH($CA10,DL_KEY,0)),"M") -> M | AA10: =IFERROR(INDEX(DL_Ac,MATCH($CA10,DL_KEY,0)),"M") -> M | AB10: =IFERROR(INDEX(DL_L,MATCH($CA10,DL_KEY,0)),"M") -> M | AC10: =IFERROR(INDEX(DL_BI,MATCH($CA10,DL_KEY,0)),"M") -> L | AD10: =IFERROR(INDEX(DL_Exp,MATCH($CA10,DL_KEY,0)),"M") -> L | AE10: =IFERROR(INDEX(DL_Edu,MATCH($CA10,DL_KEY,0)),"M") -> L | AF10: M | AG10: M | AH10: M | AI10: M | AJ10: M | AK10: M | AL10: M | AM10: 0.433 | AN10: 0.18 | AO10: 0.107 | AP10: 0.15 | AQ10: 0.08 | AR10: 0.04 | AS10: 0.01 | AT10: 12–17 yrs | AU10: Postgraduate / professional qualification preferred | AV10: 5–8 managers / associate heads | AW10: P7 / M6 · SFIA 6 Initiate, influence | AX10: S46–S51 Korn Ferry Hay evaluations · S04, S52 Mercer IPE · S53–S57 NHS, UK NJC/PSC, GLPC, SJC, US OPM point-factor plans · S58 McKinsey skills-based hiring · S60 WEF skills-first · S61 EY India 2026 · the Experience / Education split is an IRIS rule · S32 Google, Microsoft, Amazon · S33 Infosys · S35 Accenture India · IRIS experience guide · S01 Aon Radford · S02 Pave · S08 SFIA 9 · S03 Mercer career levels | AY10: C2 | AZ10: Band C · Principal / Head · Head of Function | BA10: Model D1 from the six ratings, the market-derived weights and rules R1–R13 · then Band rule: manager D2 is a head in Band D · Business leadership; a reportee sits in a lower band · D1 → C2 · move down · pay and title protected for one cycle | BB10: D2 | BC10: The six ratings on the market-average weights of Band C · Head / manager score 10.10 → D2 · Hay, Mercer IPE and public plans · experience 28.7 yrs vs the D2 market range 18–24 yrs | BD10: =IF(SUM(BM10,BN10,BO10,BP10,BQ10,BR10,BS10)=0,0,(BM10*BT10+BN10*BU10+BO10*BV10+BP10*BW10+BQ10*BX10+BR10*BY10+BS10*BZ10)/SUM(BM10,BN10,BO10,BP10,BQ10,BR10,BS10)) -> 0 | BE10: =IF(LEFT(AY10,1)="X",AY10,IF(OR(AY10="B+",AY10="C+"),INDEX(LAD_PC,MAX(1,MIN(14,MATCH(AY10,LAD_PC,0)+IF(BD10>=0.5,1,IF(BD10<=-0.5,-1,0))))),INDEX(LAD_STD,MAX(1,MIN(12,MATCH(AY10,LAD_STD,0)+IF(BD10>=0.5,1,IF(BD10<=-0.5,-1,0))))))) -> C2 | BG10: =IF(BF10<>"",BF10,BE10) -> C2 | BH10: =IFERROR(CHOOSE(INDEX(B_RANK,MATCH(BG10,B_LVL,0)),"Band A","Band B","B+ · Player-Coach","Band C","C+ · Player-Coach","Band D","Band E"),"Band X · Consultant") -> Band C | BI10: =IF(BG10=AY10,"• Same",IF(INDEX(B_VAL,MATCH(BG10,B_LVL,0))>INDEX(B_VAL,MATCH(AY10,B_LVL,0)),"▲ Up","▼ Down")) -> • Same | BJ10: =IF(OR($M10="",$M10="—",$M10="Not in this file"),"",IFERROR(INDEX($BG$7:$BG$592,MATCH($M10,$D$7:$D$592,0)),"")) -> D2 | BK10: =IFERROR(IF(BJ10="","—",IF(OR(LEFT(BG10,1)="X",LEFT(BJ10,1)="X"),"—",IF(AND(LEFT(BG10,1)="E",LEFT(BJ10,1)="E"),"Exception · Band E",IF(AND(INDEX(B_VAL,MATCH(BJ10,B_LVL,0))>=7,INDEX(B_RANK,MATCH(BG10,B_LVL,0))>=INDEX(B_RANK,MATCH(BJ10,B_LVL,0))),"⚠ Same band as a head manager",IF(INDEX(B_VAL,MATCH(BG10,B_LVL,0))>=INDEX(B_VAL,MATCH(BJ10,B_LVL,0)),"⚠ At or above the manager's level","OK"))))),"—") -> OK | BM10: =IFERROR(INDEX(LMH_PTS,MATCH(Y10,LMH_KEY,0)),0) -> 9 | BN10: =IFERROR(INDEX(LMH_PTS,MATCH(Z10,LMH_KEY,0)),0) -> 3 | BO10: =IFERROR(INDEX(LMH_PTS,MATCH(AA10,LMH_KEY,0)),0) -> 3 | BP10: =IFERROR(INDEX(LMH_PTS,MATCH(AB10,LMH_KEY,0)),0) -> 3 | BQ10: =IFERROR(INDEX(LMH_PTS,MATCH(AC10,LMH_KEY,0)),0) -> 1 | BR10: =IFERROR(INDEX(LMH_PTS,MATCH(AD10,LMH_KEY,0)),0) -> 1 | BS10: =IFERROR(INDEX(LMH_PTS,MATCH(AE10,LMH_KEY,0)),0) -> 1 | BT10: =IFERROR(INDEX(LMH_STEP,MATCH(AF10,LMH_KEY,0)),0) -> 0 | BU10: =IFERROR(INDEX(LMH_STEP,MATCH(AG10,LMH_KEY,0)),0) -> 0 | BV10: =IFERROR(INDEX(LMH_STEP,MATCH(AH10,LMH_KEY,0)),0) -> 0 | BW10: =IFERROR(INDEX(LMH_STEP,MATCH(AI10,LMH_KEY,0)),0) -> 0 | BX10: =IFERROR(INDEX(LMH_STEP,MATCH(AJ10,LMH_KEY,0)),0) -> 0 | BY10: =IFERROR(INDEX(LMH_STEP,MATCH(AK10,LMH_KEY,0)),0) -> 0 | BZ10: =IFERROR(INDEX(LMH_STEP,MATCH(AL10,LMH_KEY,0)),0) -> 0 | CA10: CARBON|Customer Experience|Senior Vice President – Customer Experience|C2|C-M
A11: CARBON | B11: Support | C11: 4 | D11: IRIS1335 | E11: Anushree Aparajit | F11: Global Customer Success Head | G11: Associate Head – Customer Success | H11: Executive Leadership | I11: Business Head | J11: People Manager | K11: RC-EL-BH-C1 | L11: Suman Adhikary | M11: IRIS2359 | N11: 14.6 | O11: 13.3 | P11: CA | Q11: L7 – Head / Sr Director | R11: C1 | S11: 0 of 20 | T11: Complexity: Evidence: no survey answers or KRAs on file → rating stays at the start Autonomy: Evidence: no survey answers or KRAs on file → rating stays at the start Accountability: Evidence: no survey answers or KRAs on file → rating stays at the start Leadership: Evidence: no survey answers or KRAs on file → rating stays at the start Business Impact: … | U11: Received · manager annual · Net Revenue Retention ≥100–105% Target ARR - to be achieved - INR 2.35 CR 90% reach value milestone in 90 days Develop advocates · Promoter per CEM Produce case studies annually CSAT ≥90% NPS ≥30 100% QBR coverage for accounts 100% CRM hygiene maintained Renewal forecast accuracy ≥95% Outstanding receivables ≤45 … | V11: Latest rating: 4 · Potential: Medium · 9-box: High Impact / Growth Talent · Readiness: Ready in 6–12 months | W11: C H · Au H · Ac M · L H · BI H · Exp H · 14.6 yrs vs 8–12 yrs · Edu H · CA | X11: Open ▸ | Y11: =IFERROR(INDEX(DL_C,MATCH($CA11,DL_KEY,0)),"M") -> H | Z11: =IFERROR(INDEX(DL_Au,MATCH($CA11,DL_KEY,0)),"M") -> M | AA11: =IFERROR(INDEX(DL_Ac,MATCH($CA11,DL_KEY,0)),"M") -> M | AB11: =IFERROR(INDEX(DL_L,MATCH($CA11,DL_KEY,0)),"M") -> M | AC11: =IFERROR(INDEX(DL_BI,MATCH($CA11,DL_KEY,0)),"M") -> L | AD11: =IFERROR(INDEX(DL_Exp,MATCH($CA11,DL_KEY,0)),"M") -> L | AE11: =IFERROR(INDEX(DL_Edu,MATCH($CA11,DL_KEY,0)),"M") -> L | AF11: M | AG11: M | AH11: M | AI11: M | AJ11: M | AK11: M | AL11: M | AM11: 0.37 | AN11: 0.183 | AO11: 0.113 | AP11: 0.15 | AQ11: 0.087 | AR11: 0.06 | AS11: 0.04 | AT11: 8–13 | AU11: Postgraduate or professional qualification preferred | AV11: IC: none · People: 5–8 incl. team leads | AW11: P5 / M4 · SFIA 5 Ensure, advise | AX11: S46–S51 Korn Ferry Hay evaluations · S04, S52 Mercer IPE · S53–S57 NHS, UK NJC/PSC, GLPC, SJC, US OPM point-factor plans · S58 McKinsey skills-based hiring · S60 WEF skills-first · S61 EY India 2026 · the Experience / Education split is an IRIS rule · S32 Google, Microsoft, Amazon · S33 Infosys · S35 Accenture India · IRIS experience guide · S01 Aon Radford · S02 Pave · S08 SFIA 9 · S03 Mercer career levels | AY11: B3 | AZ11: Band B · Specialist / Manager · Senior Manager | BA11: Model C1 from the six ratings, the market-derived weights and rules R1–R13 · then Band rule: manager C2 is a head in Band C · Principal / Head; a reportee sits in a lower band · C1 → B3 · move down · pay and title protected for one cycle | BB11: C2 | BC11: The six ratings on the market-average weights of Band B · People Manager score 7.69 → C2 · Hay, Mercer IPE and public plans · experience 14.6 yrs vs the C2 market range 12–17 yrs | BD11: =IF(SUM(BM11,BN11,BO11,BP11,BQ11,BR11,BS11)=0,0,(BM11*BT11+BN11*BU11+BO11*BV11+BP11*BW11+BQ11*BX11+BR11*BY11+BS11*BZ11)/SUM(BM11,BN11,BO11,BP11,BQ11,BR11,BS11)) -> 0 | BE11: =IF(LEFT(AY11,1)="X",AY11,IF(OR(AY11="B+",AY11="C+"),INDEX(LAD_PC,MAX(1,MIN(14,MATCH(AY11,LAD_PC,0)+IF(BD11>=0.5,1,IF(BD11<=-0.5,-1,0))))),INDEX(LAD_STD,MAX(1,MIN(12,MATCH(AY11,LAD_STD,0)+IF(BD11>=0.5,1,IF(BD11<=-0.5,-1,0))))))) -> B3 | BG11: =IF(BF11<>"",BF11,BE11) -> B3 | BH11: =IFERROR(CHOOSE(INDEX(B_RANK,MATCH(BG11,B_LVL,0)),"Band A","Band B","B+ · Player-Coach","Band C","C+ · Player-Coach","Band D","Band E"),"Band X · Consultant") -> Band B | BI11: =IF(BG11=AY11,"• Same",IF(INDEX(B_VAL,MATCH(BG11,B_LVL,0))>INDEX(B_VAL,MATCH(AY11,B_LVL,0)),"▲ Up","▼ Down")) -> • Same | BJ11: =IF(OR($M11="",$M11="—",$M11="Not in this file"),"",IFERROR(INDEX($BG$7:$BG$592,MATCH($M11,$D$7:$D$592,0)),"")) -> C2 | BK11: =IFERROR(IF(BJ11="","—",IF(OR(LEFT(BG11,1)="X",LEFT(BJ11,1)="X"),"—",IF(AND(LEFT(BG11,1)="E",LEFT(BJ11,1)="E"),"Exception · Band E",IF(AND(INDEX(B_VAL,MATCH(BJ11,B_LVL,0))>=7,INDEX(B_RANK,MATCH(BG11,B_LVL,0))>=INDEX(B_RANK,MATCH(BJ11,B_LVL,0))),"⚠ Same band as a head manager",IF(INDEX(B_VAL,MATCH(BG11,B_LVL,0))>=INDEX(B_VAL,MATCH(BJ11,B_LVL,0)),"⚠ At or above the manager's level","OK"))))),"—") -> OK | BM11: =IFERROR(INDEX(LMH_PTS,MATCH(Y11,LMH_KEY,0)),0) -> 9 | BN11: =IFERROR(INDEX(LMH_PTS,MATCH(Z11,LMH_KEY,0)),0) -> 3 | BO11: =IFERROR(INDEX(LMH_PTS,MATCH(AA11,LMH_KEY,0)),0) -> 3 | BP11: =IFERROR(INDEX(LMH_PTS,MATCH(AB11,LMH_KEY,0)),0) -> 3 | BQ11: =IFERROR(INDEX(LMH_PTS,MATCH(AC11,LMH_KEY,0)),0) -> 1 | BR11: =IFERROR(INDEX(LMH_PTS,MATCH(AD11,LMH_KEY,0)),0) -> 1 | BS11: =IFERROR(INDEX(LMH_PTS,MATCH(AE11,LMH_KEY,0)),0) -> 1 | BT11: =IFERROR(INDEX(LMH_STEP,MATCH(AF11,LMH_KEY,0)),0) -> 0 | BU11: =IFERROR(INDEX(LMH_STEP,MATCH(AG11,LMH_KEY,0)),0) -> 0 | BV11: =IFERROR(INDEX(LMH_STEP,MATCH(AH11,LMH_KEY,0)),0) -> 0 | BW11: =IFERROR(INDEX(LMH_STEP,MATCH(AI11,LMH_KEY,0)),0) -> 0 | BX11: =IFERROR(INDEX(LMH_STEP,MATCH(AJ11,LMH_KEY,0)),0) -> 0 | BY11: =IFERROR(INDEX(LMH_STEP,MATCH(AK11,LMH_KEY,0)),0) -> 0 | BZ11: =IFERROR(INDEX(LMH_STEP,MATCH(AL11,LMH_KEY,0)),0) -> 0 | CA11: CARBON|Support|Associate Head – Customer Success|B3|B-M
A12: CARBON | B12: Support | C12: 5 | D12: IRIS1935 | E12: Chinmayi Patil | F12: Customer Success Manager | G12: Customer Success Specialist | H12: Customer Success & Support | I12: Customer Success & Account Management | J12: IC | K12: RC-036 | L12: Anushree Aparajit | M12: IRIS1335 | N12: 5.2 | O12: 5.2 | P12: MMS | Q12: L5 – Manager | R12: B2 | S12: 20 of 20 | T12: • Role / sub-team: Support — Customer Success Manager. • Core purpose: Post sales customer journey, retention and renewal, up sell and cross sell of other products for account expansion and revenue growth. • Decision-making autonomy: Can independently product training material. • Is this something only they do: Most of us. • What's different about this … | U12: Received · manager annual · Net Revenue Retention ≥100–105% Target ARR - to be achieved: INR 3000000 90% reach value milestone in 90 days Develop advocates · Promoter per CEM Produce case studies annually CSAT ≥90% NPS ≥30 100% QBR coverage for accounts 100% CRM hygiene maintained Renewal forecast accuracy ≥95% Outstanding receivables ≤45 … | V12: Latest rating: 4 · Potential: High · 9-box: Future Leader · Readiness: Ready now | W12: C M · Au M · Ac M · L L · BI M · Exp L · 5.2 yrs vs 6–9 yrs · Edu H · MMS | X12: Open ▸ | Y12: =IFERROR(INDEX(DL_C,MATCH($CA12,DL_KEY,0)),"M") -> H | Z12: =IFERROR(INDEX(DL_Au,MATCH($CA12,DL_KEY,0)),"M") -> M | AA12: =IFERROR(INDEX(DL_Ac,MATCH($CA12,DL_KEY,0)),"M") -> M | AB12: =IFERROR(INDEX(DL_L,MATCH($CA12,DL_KEY,0)),"M") -> L | AC12: =IFERROR(INDEX(DL_BI,MATCH($CA12,DL_KEY,0)),"M") -> M | AD12: =IFERROR(INDEX(DL_Exp,MATCH($CA12,DL_KEY,0)),"M") -> L | AE12: =IFERROR(INDEX(DL_Edu,MATCH($CA12,DL_KEY,0)),"M") -> L | AF12: M | AG12: M | AH12: M | AI12: M | AJ12: M | AK12: M | AL12: M | AM12: 0.513 | AN12: 0.173 | AO12: 0.097 | AP12: 0.05 | AQ12: 0.07 | AR12: 0.06 | AS12: 0.04 | AT12: 6–10 | AU12: Graduate or postgraduate; professional qualification preferred | AV12: IC: none · People: 6–8 knowledge work, 8–12 standardised delivery | AW12: P4 / M3 · SFIA 4–5 | AX12: S46–S51 Korn Ferry Hay evaluations · S04, S52 Mercer IPE · S53–S57 NHS, UK NJC/PSC, GLPC, SJC, US OPM point-factor plans · S58 McKinsey skills-based hiring · S60 WEF skills-first · S61 EY India 2026 · the Experience / Education split is an IRIS rule · S32 Google, Microsoft, Amazon · S33 Infosys · S35 Accenture India · IRIS experience guide · S01 Aon Radford · S02 Pave · S08 SFIA 9 · S03 Mercer career levels | AY12: B2 | AZ12: Band B · Specialist / Manager · Senior Specialist | BA12: Model B2 from the six ratings, the market-derived weights and rules R1–R13 · then No change · already below the manager | BB12: B1 | BC12: The six ratings on the market-average weights of Band B · Specialist / POD Lead score 4.49 → B1 · Hay, Mercer IPE and public plans · experience 5.2 yrs vs the B1 market range 4–8 | BD12: =IF(SUM(BM12,BN12,BO12,BP12,BQ12,BR12,BS12)=0,0,(BM12*BT12+BN12*BU12+BO12*BV12+BP12*BW12+BQ12*BX12+BR12*BY12+BS12*BZ12)/SUM(BM12,BN12,BO12,BP12,BQ12,BR12,BS12)) -> 0 | BE12: =IF(LEFT(AY12,1)="X",AY12,IF(OR(AY12="B+",AY12="C+"),INDEX(LAD_PC,MAX(1,MIN(14,MATCH(AY12,LAD_PC,0)+IF(BD12>=0.5,1,IF(BD12<=-0.5,-1,0))))),INDEX(LAD_STD,MAX(1,MIN(12,MATCH(AY12,LAD_STD,0)+IF(BD12>=0.5,1,IF(BD12<=-0.5,-1,0))))))) -> B2 | BG12: =IF(BF12<>"",BF12,BE12) -> B2 | BH12: =IFERROR(CHOOSE(INDEX(B_RANK,MATCH(BG12,B_LVL,0)),"Band A","Band B","B+ · Player-Coach","Band C","C+ · Player-Coach","Band D","Band E"),"Band X · Consultant") -> Band B | BI12: =IF(BG12=AY12,"• Same",IF(INDEX(B_VAL,MATCH(BG12,B_LVL,0))>INDEX(B_VAL,MATCH(AY12,B_LVL,0)),"▲ Up","▼ Down")) -> • Same | BJ12: =IF(OR($M12="",$M12="—",$M12="Not in this file"),"",IFERROR(INDEX($BG$7:$BG$592,MATCH($M12,$D$7:$D$592,0)),"")) -> B3 | BK12: =IFERROR(IF(BJ12="","—",IF(OR(LEFT(BG12,1)="X",LEFT(BJ12,1)="X"),"—",IF(AND(LEFT(BG12,1)="E",LEFT(BJ12,1)="E"),"Exception · Band E",IF(AND(INDEX(B_VAL,MATCH(BJ12,B_LVL,0))>=7,INDEX(B_RANK,MATCH(BG12,B_LVL,0))>=INDEX(B_RANK,MATCH(BJ12,B_LVL,0))),"⚠ Same band as a head manager",IF(INDEX(B_VAL,MATCH(BG12,B_LVL,0))>=INDEX(B_VAL,MATCH(BJ12,B_LVL,0)),"⚠ At or above the manager's level","OK"))))),"—") -> OK | BM12: =IFERROR(INDEX(LMH_PTS,MATCH(Y12,LMH_KEY,0)),0) -> 9 | BN12: =IFERROR(INDEX(LMH_PTS,MATCH(Z12,LMH_KEY,0)),0) -> 3 | BO12: =IFERROR(INDEX(LMH_PTS,MATCH(AA12,LMH_KEY,0)),0) -> 3 | BP12: =IFERROR(INDEX(LMH_PTS,MATCH(AB12,LMH_KEY,0)),0) -> 1 | BQ12: =IFERROR(INDEX(LMH_PTS,MATCH(AC12,LMH_KEY,0)),0) -> 3 | BR12: =IFERROR(INDEX(LMH_PTS,MATCH(AD12,LMH_KEY,0)),0) -> 1 | BS12: =IFERROR(INDEX(LMH_PTS,MATCH(AE12,LMH_KEY,0)),0) -> 1 | BT12: =IFERROR(INDEX(LMH_STEP,MATCH(AF12,LMH_KEY,0)),0) -> 0 | BU12: =IFERROR(INDEX(LMH_STEP,MATCH(AG12,LMH_KEY,0)),0) -> 0 | BV12: =IFERROR(INDEX(LMH_STEP,MATCH(AH12,LMH_KEY,0)),0) -> 0 | BW12: =IFERROR(INDEX(LMH_STEP,MATCH(AI12,LMH_KEY,0)),0) -> 0 | BX12: =IFERROR(INDEX(LMH_STEP,MATCH(AJ12,LMH_KEY,0)),0) -> 0 | BY12: =IFERROR(INDEX(LMH_STEP,MATCH(AK12,LMH_KEY,0)),0) -> 0 | BZ12: =IFERROR(INDEX(LMH_STEP,MATCH(AL12,LMH_KEY,0)),0) -> 0 | CA12: CARBON|Support|Customer Success Specialist|B2|B-IC
A13: CARBON | B13: Support | C13: 5 | D13: IRIS1963 | E13: Neha Gajbhiye | F13: Manager- Customer Engagement | G13: Senior Customer Success Specialist – POD Lead | H13: Customer Success & Support | I13: Customer Success & Account Management | J13: POD Lead | K13: RC-036 | L13: Anushree Aparajit | M13: IRIS1335 | N13: 16.2 | O13: 4.9 | P13: MBA | Q13: L5 – Manager | R13: B2 | S13: 20 of 20 | T13: • Role / sub-team: Support — Manager- Customer Engagement. • Core purpose: Client interaction, Domain expertise, Go live, platform enablement, training and end to end hypercare. • Decision-making autonomy: Can independently trainings only. • Is this something only they do: Everyone does the same but in different geos. • What's different about this role: … | U13: Received · manager annual · Net Revenue Retention ≥100–105% Target ARR - to be achieved: INR 1700000 90% reach value milestone in 90 days Develop advocates · Promoter per CEM Produce case studies annually CSAT ≥90% NPS ≥30 100% QBR coverage for accounts 100% CRM hygiene maintained Renewal forecast accuracy ≥95% Outstanding receivables ≤45 … | V13: Latest rating: 4 · Potential: High · 9-box: High Impact / Growth Talent · Readiness: Ready now | W13: C L · Au L · Ac M · L L · BI M · Exp H · 16.2 yrs vs 6–9 yrs · Edu H · MBA | X13: Open ▸ | Y13: =IFERROR(INDEX(DL_C,MATCH($CA13,DL_KEY,0)),"M") -> H | Z13: =IFERROR(INDEX(DL_Au,MATCH($CA13,DL_KEY,0)),"M") -> M | AA13: =IFERROR(INDEX(DL_Ac,MATCH($CA13,DL_KEY,0)),"M") -> M | AB13: =IFERROR(INDEX(DL_L,MATCH($CA13,DL_KEY,0)),"M") -> L | AC13: =IFERROR(INDEX(DL_BI,MATCH($CA13,DL_KEY,0)),"M") -> M | AD13: =IFERROR(INDEX(DL_Exp,MATCH($CA13,DL_KEY,0)),"M") -> L | AE13: =IFERROR(INDEX(DL_Edu,MATCH($CA13,DL_KEY,0)),"M") -> L | AF13: M | AG13: M | AH13: M | AI13: M | AJ13: M | AK13: M | AL13: M | AM13: 0.513 | AN13: 0.173 | AO13: 0.097 | AP13: 0.05 | AQ13: 0.07 | AR13: 0.06 | AS13: 0.04 | AT13: 6–10 | AU13: Graduate or postgraduate; professional qualification preferred | AV13: IC: none · People: 6–8 knowledge work, 8–12 standardised delivery | AW13: P4 / M3 · SFIA 4–5 | AX13: S46–S51 Korn Ferry Hay evaluations · S04, S52 Mercer IPE · S53–S57 NHS, UK NJC/PSC, GLPC, SJC, US OPM point-factor plans · S58 McKinsey skills-based hiring · S60 WEF skills-first · S61 EY India 2026 · the Experience / Education split is an IRIS rule · S32 Google, Microsoft, Amazon · S33 Infosys · S35 Accenture India · IRIS experience guide · S01 Aon Radford · S02 Pave · S08 SFIA 9 · S03 Mercer career levels | AY13: B2 | AZ13: Band B · Specialist / Manager · Manager | BA13: Model B2 from the six ratings, the market-derived weights and rules R1–R13 · then No change · already below the manager | BB13: B2 | BC13: The six ratings on the market-average weights of Band B · Specialist / POD Lead score 4.57 → B2 · Hay, Mercer IPE and public plans · experience 16.2 yrs vs the B2 market range 6–10 | BD13: =IF(SUM(BM13,BN13,BO13,BP13,BQ13,BR13,BS13)=0,0,(BM13*BT13+BN13*BU13+BO13*BV13+BP13*BW13+BQ13*BX13+BR13*BY13+BS13*BZ13)/SUM(BM13,BN13,BO13,BP13,BQ13,BR13,BS13)) -> 0 | BE13: =IF(LEFT(AY13,1)="X",AY13,IF(OR(AY13="B+",AY13="C+"),INDEX(LAD_PC,MAX(1,MIN(14,MATCH(AY13,LAD_PC,0)+IF(BD13>=0.5,1,IF(BD13<=-0.5,-1,0))))),INDEX(LAD_STD,MAX(1,MIN(12,MATCH(AY13,LAD_STD,0)+IF(BD13>=0.5,1,IF(BD13<=-0.5,-1,0))))))) -> B2 | BG13: =IF(BF13<>"",BF13,BE13) -> B2 | BH13: =IFERROR(CHOOSE(INDEX(B_RANK,MATCH(BG13,B_LVL,0)),"Band A","Band B","B+ · Player-Coach","Band C","C+ · Player-Coach","Band D","Band E"),"Band X · Consultant") -> Band B | BI13: =IF(BG13=AY13,"• Same",IF(INDEX(B_VAL,MATCH(BG13,B_LVL,0))>INDEX(B_VAL,MATCH(AY13,B_LVL,0)),"▲ Up","▼ Down")) -> • Same | BJ13: =IF(OR($M13="",$M13="—",$M13="Not in this file"),"",IFERROR(INDEX($BG$7:$BG$592,MATCH($M13,$D$7:$D$592,0)),"")) -> B3 | BK13: =IFERROR(IF(BJ13="","—",IF(OR(LEFT(BG13,1)="X",LEFT(BJ13,1)="X"),"—",IF(AND(LEFT(BG13,1)="E",LEFT(BJ13,1)="E"),"Exception · Band E",IF(AND(INDEX(B_VAL,MATCH(BJ13,B_LVL,0))>=7,INDEX(B_RANK,MATCH(BG13,B_LVL,0))>=INDEX(B_RANK,MATCH(BJ13,B_LVL,0))),"⚠ Same band as a head manager",IF(INDEX(B_VAL,MATCH(BG13,B_LVL,0))>=INDEX(B_VAL,MATCH(BJ13,B_LVL,0)),"⚠ At or above the manager's level","OK"))))),"—") -> OK | BM13: =IFERROR(INDEX(LMH_PTS,MATCH(Y13,LMH_KEY,0)),0) -> 9 | BN13: =IFERROR(INDEX(LMH_PTS,MATCH(Z13,LMH_KEY,0)),0) -> 3 | BO13: =IFERROR(INDEX(LMH_PTS,MATCH(AA13,LMH_KEY,0)),0) -> 3 | BP13: =IFERROR(INDEX(LMH_PTS,MATCH(AB13,LMH_KEY,0)),0) -> 1 | BQ13: =IFERROR(INDEX(LMH_PTS,MATCH(AC13,LMH_KEY,0)),0) -> 3 | BR13: =IFERROR(INDEX(LMH_PTS,MATCH(AD13,LMH_KEY,0)),0) -> 1 | BS13: =IFERROR(INDEX(LMH_PTS,MATCH(AE13,LMH_KEY,0)),0) -> 1 | BT13: =IFERROR(INDEX(LMH_STEP,MATCH(AF13,LMH_KEY,0)),0) -> 0 | BU13: =IFERROR(INDEX(LMH_STEP,MATCH(AG13,LMH_KEY,0)),0) -> 0 | BV13: =IFERROR(INDEX(LMH_STEP,MATCH(AH13,LMH_KEY,0)),0) -> 0 | BW13: =IFERROR(INDEX(LMH_STEP,MATCH(AI13,LMH_KEY,0)),0) -> 0 | BX13: =IFERROR(INDEX(LMH_STEP,MATCH(AJ13,LMH_KEY,0)),0) -> 0 | BY13: =IFERROR(INDEX(LMH_STEP,MATCH(AK13,LMH_KEY,0)),0) -> 0 | BZ13: =IFERROR(INDEX(LMH_STEP,MATCH(AL13,LMH_KEY,0)),0) -> 0 | CA13: CARBON|Support|Senior Customer Success Specialist – POD Lead|B2|B-IC
A14: CARBON | B14: Support | C14: 6 | D14: IRISC184 | E14: Tanya Dhere | F14: Consultant | G14: Senior Customer Success Executive | H14: Customer Success & Support | I14: Customer Success & Account Management | J14: IC | K14: RC-034 | L14: Neha Gajbhiye | M14: IRIS1963 | N14: 13 | O14: 6 | P14: B.Com | Q14: L3 – Professional / Associate | R14: A3 | S14: 19 of 20 | T14: • Role / sub-team: PMO Activity, AI Testing. | U14: KRAs not received · manager to supply | V14: Latest rating: 3 · Potential: Low · 9-box: Reliable Specialist · Readiness: Develop in role | W14: C M · Au L · Ac M · L L · BI M · Exp H · 13 yrs vs 2–4 yrs · Edu M · B.Com | X14: Open ▸ | Y14: =IFERROR(INDEX(DL_C,MATCH($CA14,DL_KEY,0)),"M") -> H | Z14: =IFERROR(INDEX(DL_Au,MATCH($CA14,DL_KEY,0)),"M") -> M | AA14: =IFERROR(INDEX(DL_Ac,MATCH($CA14,DL_KEY,0)),"M") -> M | AB14: =IFERROR(INDEX(DL_L,MATCH($CA14,DL_KEY,0)),"M") -> L | AC14: =IFERROR(INDEX(DL_BI,MATCH($CA14,DL_KEY,0)),"M") -> M | AD14: =IFERROR(INDEX(DL_Exp,MATCH($CA14,DL_KEY,0)),"M") -> L | AE14: =IFERROR(INDEX(DL_Edu,MATCH($CA14,DL_KEY,0)),"M") -> L | AF14: M | AG14: M | AH14: M | AI14: M | AJ14: M | AK14: M | AL14: M | AM14: 0.583 | AN14: 0.16 | AO14: 0.09 | AP14: 0 | AQ14: 0.063 | AR14: 0.06 | AS14: 0.04 | AT14: 2–5 | AU14: Graduate; relevant certification preferred | AV14: None · guides 1–3 juniors informally | AW14: P2 · SFIA 3 Apply | AX14: S46–S51 Korn Ferry Hay evaluations · S04, S52 Mercer IPE · S53–S57 NHS, UK NJC/PSC, GLPC, SJC, US OPM point-factor plans · S58 McKinsey skills-based hiring · S60 WEF skills-first · S61 EY India 2026 · the Experience / Education split is an IRIS rule · S32 Google, Microsoft, Amazon · S33 Infosys · S35 Accenture India · IRIS experience guide · S01 Aon Radford · S02 Pave · S08 SFIA 9 · S03 Mercer career levels | AY14: A3 | AZ14: Band A · Practitioner · Senior Associate | BA14: Model A3 from the six ratings, the market-derived weights and rules R1–R13 · then No change · already below the manager | BB14: A3 | BC14: The six ratings on the market-average weights of Band A · all tracks score 2.92 → A3 · Hay, Mercer IPE and public plans · experience 13 yrs vs the A3 market range 2–5 | BD14: =IF(SUM(BM14,BN14,BO14,BP14,BQ14,BR14,BS14)=0,0,(BM14*BT14+BN14*BU14+BO14*BV14+BP14*BW14+BQ14*BX14+BR14*BY14+BS14*BZ14)/SUM(BM14,BN14,BO14,BP14,BQ14,BR14,BS14)) -> 0 | BE14: =IF(LEFT(AY14,1)="X",AY14,IF(OR(AY14="B+",AY14="C+"),INDEX(LAD_PC,MAX(1,MIN(14,MATCH(AY14,LAD_PC,0)+IF(BD14>=0.5,1,IF(BD14<=-0.5,-1,0))))),INDEX(LAD_STD,MAX(1,MIN(12,MATCH(AY14,LAD_STD,0)+IF(BD14>=0.5,1,IF(BD14<=-0.5,-1,0))))))) -> A3 | BG14: =IF(BF14<>"",BF14,BE14) -> A3 | BH14: =IFERROR(CHOOSE(INDEX(B_RANK,MATCH(BG14,B_LVL,0)),"Band A","Band B","B+ · Player-Coach","Band C","C+ · Player-Coach","Band D","Band E"),"Band X · Consultant") -> Band A | BI14: =IF(BG14=AY14,"• Same",IF(INDEX(B_VAL,MATCH(BG14,B_LVL,0))>INDEX(B_VAL,MATCH(AY14,B_LVL,0)),"▲ Up","▼ Down")) -> • Same | BJ14: =IF(OR($M14="",$M14="—",$M14="Not in this file"),"",IFERROR(INDEX($BG$7:$BG$592,MATCH($M14,$D$7:$D$592,0)),"")) -> B2 | BK14: =IFERROR(IF(BJ14="","—",IF(OR(LEFT(BG14,1)="X",LEFT(BJ14,1)="X"),"—",IF(AND(LEFT(BG14,1)="E",LEFT(BJ14,1)="E"),"Exception · Band E",IF(AND(INDEX(B_VAL,MATCH(BJ14,B_LVL,0))>=7,INDEX(B_RANK,MATCH(BG14,B_LVL,0))>=INDEX(B_RANK,MATCH(BJ14,B_LVL,0))),"⚠ Same band as a head manager",IF(INDEX(B_VAL,MATCH(BG14,B_LVL,0))>=INDEX(B_VAL,MATCH(BJ14,B_LVL,0)),"⚠ At or above the manager's level","OK"))))),"—") -> OK | BM14: =IFERROR(INDEX(LMH_PTS,MATCH(Y14,LMH_KEY,0)),0) -> 9 | BN14: =IFERROR(INDEX(LMH_PTS,MATCH(Z14,LMH_KEY,0)),0) -> 3 | BO14: =IFERROR(INDEX(LMH_PTS,MATCH(AA14,LMH_KEY,0)),0) -> 3 | BP14: =IFERROR(INDEX(LMH_PTS,MATCH(AB14,LMH_KEY,0)),0) -> 1 | BQ14: =IFERROR(INDEX(LMH_PTS,MATCH(AC14,LMH_KEY,0)),0) -> 3 | BR14: =IFERROR(INDEX(LMH_PTS,MATCH(AD14,LMH_KEY,0)),0) -> 1 | BS14: =IFERROR(INDEX(LMH_PTS,MATCH(AE14,LMH_KEY,0)),0) -> 1 | BT14: =IFERROR(INDEX(LMH_STEP,MATCH(AF14,LMH_KEY,0)),0) -> 0 | BU14: =IFERROR(INDEX(LMH_STEP,MATCH(AG14,LMH_KEY,0)),0) -> 0 | BV14: =IFERROR(INDEX(LMH_STEP,MATCH(AH14,LMH_KEY,0)),0) -> 0 | BW14: =IFERROR(INDEX(LMH_STEP,MATCH(AI14,LMH_KEY,0)),0) -> 0 | BX14: =IFERROR(INDEX(LMH_STEP,MATCH(AJ14,LMH_KEY,0)),0) -> 0 | BY14: =IFERROR(INDEX(LMH_STEP,MATCH(AK14,LMH_KEY,0)),0) -> 0 | BZ14: =IFERROR(INDEX(LMH_STEP,MATCH(AL14,LMH_KEY,0)),0) -> 0 | CA14: CARBON|Support|Senior Customer Success Executive|A3|A
A15: CARBON | B15: Support | C15: 5 | D15: IRIS1959 | E15: Praveen Kumar Rajpurohit | F15: Manager- Customer Engagement | G15: Senior Customer Success Specialist | H15: Customer Success & Support | I15: Customer Success & Account Management | J15: IC | K15: RC-036 | L15: Anushree Aparajit | M15: IRIS1335 | N15: 14.6 | O15: 5 | P15: MBA | Q15: L5 – Manager | R15: B2 | S15: 20 of 20 | T15: • Role / sub-team: Support — Manager- Customer Engagement. • Core purpose: Managing EU client portfolios to ensure timely ESEF filings, effective use of the Disclosure Management Platform, client retention and renewals, while supporting prospect demos and product feedback. • Decision-making autonomy: Can independently clients query handling. • Is this … | U15: Received · manager annual · Net Revenue Retention ≥100–105% Target ARR - to be achieved: INR 50,00,000 90% reach value milestone in 90 days Develop advocates · Promoter per CEM Produce case studies annually CSAT ≥90% NPS ≥30 100% QBR coverage for accounts 100% CRM hygiene maintained Renewal forecast accuracy ≥95% Outstanding receivables ≤45 … | V15: Latest rating: 3 · Potential: Medium · 9-box: Core Contributor · Readiness: Develop in role | W15: C L · Au L · Ac M · L L · BI M · Exp H · 14.6 yrs vs 6–9 yrs · Edu H · MBA | X15: Open ▸ | Y15: =IFERROR(INDEX(DL_C,MATCH($CA15,DL_KEY,0)),"M") -> H | Z15: =IFERROR(INDEX(DL_Au,MATCH($CA15,DL_KEY,0)),"M") -> M | AA15: =IFERROR(INDEX(DL_Ac,MATCH($CA15,DL_KEY,0)),"M") -> M | AB15: =IFERROR(INDEX(DL_L,MATCH($CA15,DL_KEY,0)),"M") -> L | AC15: =IFERROR(INDEX(DL_BI,MATCH($CA15,DL_KEY,0)),"M") -> M | AD15: =IFERROR(INDEX(DL_Exp,MATCH($CA15,DL_KEY,0)),"M") -> L | AE15: =IFERROR(INDEX(DL_Edu,MATCH($CA15,DL_KEY,0)),"M") -> L | AF15: M | AG15: M | AH15: M | AI15: M | AJ15: M | AK15: M | AL15: M | AM15: 0.513 | AN15: 0.173 | AO15: 0.097 | AP15: 0.05 | AQ15: 0.07 | AR15: 0.06 | AS15: 0.04 | AT15: 6–10 | AU15: Graduate or postgraduate; professional qualification preferred | AV15: IC: none · People: 6–8 knowledge work, 8–12 standardised delivery | AW15: P4 / M3 · SFIA 4–5 | AX15: S46–S51 Korn Ferry Hay evaluations · S04, S52 Mercer IPE · S53–S57 NHS, UK NJC/PSC, GLPC, SJC, US OPM point-factor plans · S58 McKinsey skills-based hiring · S60 WEF skills-first · S61 EY India 2026 · the Experience / Education split is an IRIS rule · S32 Google, Microsoft, Amazon · S33 Infosys · S35 Accenture India · IRIS experience guide · S01 Aon Radford · S02 Pave · S08 SFIA 9 · S03 Mercer career levels | AY15: B2 | AZ15: Band B · Specialist / Manager · Senior Specialist | BA15: Model B2 from the six ratings, the market-derived weights and rules R1–R13 · then No change · already below the manager | BB15: B2 | BC15: The six ratings on the market-average weights of Band B · Specialist / POD Lead score 4.60 → B2 · Hay, Mercer IPE and public plans · experience 14.6 yrs vs the B2 market range 6–10 | BD15: =IF(SUM(BM15,BN15,BO15,BP15,BQ15,BR15,BS15)=0,0,(BM15*BT15+BN15*BU15+BO15*BV15+BP15*BW15+BQ15*BX15+BR15*BY15+BS15*BZ15)/SUM(BM15,BN15,BO15,BP15,BQ15,BR15,BS15)) -> 0 | BE15: =IF(LEFT(AY15,1)="X",AY15,IF(OR(AY15="B+",AY15="C+"),INDEX(LAD_PC,MAX(1,MIN(14,MATCH(AY15,LAD_PC,0)+IF(BD15>=0.5,1,IF(BD15<=-0.5,-1,0))))),INDEX(LAD_STD,MAX(1,MIN(12,MATCH(AY15,LAD_STD,0)+IF(BD15>=0.5,1,IF(BD15<=-0.5,-1,0))))))) -> B2 | BG15: =IF(BF15<>"",BF15,BE15) -> B2 | BH15: =IFERROR(CHOOSE(INDEX(B_RANK,MATCH(BG15,B_LVL,0)),"Band A","Band B","B+ · Player-Coach","Band C","C+ · Player-Coach","Band D","Band E"),"Band X · Consultant") -> Band B | BI15: =IF(BG15=AY15,"• Same",IF(INDEX(B_VAL,MATCH(BG15,B_LVL,0))>INDEX(B_VAL,MATCH(AY15,B_LVL,0)),"▲ Up","▼ Down")) -> • Same | BJ15: =IF(OR($M15="",$M15="—",$M15="Not in this file"),"",IFERROR(INDEX($BG$7:$BG$592,MATCH($M15,$D$7:$D$592,0)),"")) -> B3 | BK15: =IFERROR(IF(BJ15="","—",IF(OR(LEFT(BG15,1)="X",LEFT(BJ15,1)="X"),"—",IF(AND(LEFT(BG15,1)="E",LEFT(BJ15,1)="E"),"Exception · Band E",IF(AND(INDEX(B_VAL,MATCH(BJ15,B_LVL,0))>=7,INDEX(B_RANK,MATCH(BG15,B_LVL,0))>=INDEX(B_RANK,MATCH(BJ15,B_LVL,0))),"⚠ Same band as a head manager",IF(INDEX(B_VAL,MATCH(BG15,B_LVL,0))>=INDEX(B_VAL,MATCH(BJ15,B_LVL,0)),"⚠ At or above the manager's level","OK"))))),"—") -> OK | BM15: =IFERROR(INDEX(LMH_PTS,MATCH(Y15,LMH_KEY,0)),0) -> 9 | BN15: =IFERROR(INDEX(LMH_PTS,MATCH(Z15,LMH_KEY,0)),0) -> 3 | BO15: =IFERROR(INDEX(LMH_PTS,MATCH(AA15,LMH_KEY,0)),0) -> 3 | BP15: =IFERROR(INDEX(LMH_PTS,MATCH(AB15,LMH_KEY,0)),0) -> 1 | BQ15: =IFERROR(INDEX(LMH_PTS,MATCH(AC15,LMH_KEY,0)),0) -> 3 | BR15: =IFERROR(INDEX(LMH_PTS,MATCH(AD15,LMH_KEY,0)),0) -> 1 | BS15: =IFERROR(INDEX(LMH_PTS,MATCH(AE15,LMH_KEY,0)),0) -> 1 | BT15: =IFERROR(INDEX(LMH_STEP,MATCH(AF15,LMH_KEY,0)),0) -> 0 | BU15: =IFERROR(INDEX(LMH_STEP,MATCH(AG15,LMH_KEY,0)),0) -> 0 | BV15: =IFERROR(INDEX(LMH_STEP,MATCH(AH15,LMH_KEY,0)),0) -> 0 | BW15: =IFERROR(INDEX(LMH_STEP,MATCH(AI15,LMH_KEY,0)),0) -> 0 | BX15: =IFERROR(INDEX(LMH_STEP,MATCH(AJ15,LMH_KEY,0)),0) -> 0 | BY15: =IFERROR(INDEX(LMH_STEP,MATCH(AK15,LMH_KEY,0)),0) -> 0 | BZ15: =IFERROR(INDEX(LMH_STEP,MATCH(AL15,LMH_KEY,0)),0) -> 0 | CA15: CARBON|Support|Senior Customer Success Specialist|B2|B-IC
A16: CARBON | B16: Support | C16: 5 | D16: IRIS1967 | E16: Pritam Agarwal | F16: Manager- Customer Engagement | G16: Senior Customer Success Specialist | H16: Customer Success & Support | I16: Customer Success & Account Management | J16: IC | K16: RC-036 | L16: Anushree Aparajit | M16: IRIS1335 | N16: 20.1 | O16: 4.8 | P16: PGDM | Q16: L5 – Manager | R16: B2 | S16: 20 of 20 | T16: • Role / sub-team: Support — Manager- Customer Engagement. • Core purpose: Client communication and Nurturing the client with training and enablement process to work independently. • Decision-making autonomy: Can independently none of the activity. • Is this something only they do: Most of us. • What's different about this role: Geo specific reporting; … | U16: Received · manager annual · "Net Revenue Retention ≥100–105% Target ARR - to be achieved: INR 30,00,000 90% reach value milestone in 90 days Develop advocates · Promoter per CEM Produce case studies annually CSAT ≥90% NPS ≥30 100% QBR coverage for accounts 100% CRM hygiene maintained Renewal forecast accuracy ≥95% Outstanding receivables ≤45 … | V16: Latest rating: 2 · Potential: Medium · 9-box: Core Contributor · Readiness: Performance first | W16: C M · Au M · Ac M · L L · BI M · Exp H · 20.1 yrs vs 6–9 yrs · Edu H · PGDM | X16: Open ▸ | Y16: =IFERROR(INDEX(DL_C,MATCH($CA16,DL_KEY,0)),"M") -> H | Z16: =IFERROR(INDEX(DL_Au,MATCH($CA16,DL_KEY,0)),"M") -> M | AA16: =IFERROR(INDEX(DL_Ac,MATCH($CA16,DL_KEY,0)),"M") -> M | AB16: =IFERROR(INDEX(DL_L,MATCH($CA16,DL_KEY,0)),"M") -> L | AC16: =IFERROR(INDEX(DL_BI,MATCH($CA16,DL_KEY,0)),"M") -> M | AD16: =IFERROR(INDEX(DL_Exp,MATCH($CA16,DL_KEY,0)),"M") -> L | AE16: =IFERROR(INDEX(DL_Edu,MATCH($CA16,DL_KEY,0)),"M") -> L | AF16: M | AG16: M | AH16: M | AI16: M | AJ16: M | AK16: M | AL16: M | AM16: 0.513 | AN16: 0.173 | AO16: 0.097 | AP16: 0.05 | AQ16: 0.07 | AR16: 0.06 | AS16: 0.04 | AT16: 6–10 | AU16: Graduate or postgraduate; professional qualification preferred | AV16: IC: none · People: 6–8 knowledge work, 8–12 standardised delivery | AW16: P4 / M3 · SFIA 4–5 | AX16: S46–S51 Korn Ferry Hay evaluations · S04, S52 Mercer IPE · S53–S57 NHS, UK NJC/PSC, GLPC, SJC, US OPM point-factor plans · S58 McKinsey skills-based hiring · S60 WEF skills-first · S61 EY India 2026 · the Experience / Education split is an IRIS rule · S32 Google, Microsoft, Amazon · S33 Infosys · S35 Accenture India · IRIS experience guide · S01 Aon Radford · S02 Pave · S08 SFIA 9 · S03 Mercer career levels | AY16: B2 | AZ16: Band B · Specialist / Manager · Senior Specialist | BA16: Model B2 from the six ratings, the market-derived weights and rules R1–R13 · then No change · already below the manager | BB16: B2 | BC16: The six ratings on the market-average weights of Band B · Specialist / POD Lead score 5.03 → B2 · Hay, Mercer IPE and public plans · experience 20.1 yrs vs the B2 market range 6–10 | BD16: =IF(SUM(BM16,BN16,BO16,BP16,BQ16,BR16,BS16)=0,0,(BM16*BT16+BN16*BU16+BO16*BV16+BP16*BW16+BQ16*BX16+BR16*BY16+BS16*BZ16)/SUM(BM16,BN16,BO16,BP16,BQ16,BR16,BS16)) -> 0 | BE16: =IF(LEFT(AY16,1)="X",AY16,IF(OR(AY16="B+",AY16="C+"),INDEX(LAD_PC,MAX(1,MIN(14,MATCH(AY16,LAD_PC,0)+IF(BD16>=0.5,1,IF(BD16<=-0.5,-1,0))))),INDEX(LAD_STD,MAX(1,MIN(12,MATCH(AY16,LAD_STD,0)+IF(BD16>=0.5,1,IF(BD16<=-0.5,-1,0))))))) -> B2 | BG16: =IF(BF16<>"",BF16,BE16) -> B2 | BH16: =IFERROR(CHOOSE(INDEX(B_RANK,MATCH(BG16,B_LVL,0)),"Band A","Band B","B+ · Player-Coach","Band C","C+ · Player-Coach","Band D","Band E"),"Band X · Consultant") -> Band B | BI16: =IF(BG16=AY16,"• Same",IF(INDEX(B_VAL,MATCH(BG16,B_LVL,0))>INDEX(B_VAL,MATCH(AY16,B_LVL,0)),"▲ Up","▼ Down")) -> • Same | BJ16: =IF(OR($M16="",$M16="—",$M16="Not in this file"),"",IFERROR(INDEX($BG$7:$BG$592,MATCH($M16,$D$7:$D$592,0)),"")) -> B3 | BK16: =IFERROR(IF(BJ16="","—",IF(OR(LEFT(BG16,1)="X",LEFT(BJ16,1)="X"),"—",IF(AND(LEFT(BG16,1)="E",LEFT(BJ16,1)="E"),"Exception · Band E",IF(AND(INDEX(B_VAL,MATCH(BJ16,B_LVL,0))>=7,INDEX(B_RANK,MATCH(BG16,B_LVL,0))>=INDEX(B_RANK,MATCH(BJ16,B_LVL,0))),"⚠ Same band as a head manager",IF(INDEX(B_VAL,MATCH(BG16,B_LVL,0))>=INDEX(B_VAL,MATCH(BJ16,B_LVL,0)),"⚠ At or above the manager's level","OK"))))),"—") -> OK | BM16: =IFERROR(INDEX(LMH_PTS,MATCH(Y16,LMH_KEY,0)),0) -> 9 | BN16: =IFERROR(INDEX(LMH_PTS,MATCH(Z16,LMH_KEY,0)),0) -> 3 | BO16: =IFERROR(INDEX(LMH_PTS,MATCH(AA16,LMH_KEY,0)),0) -> 3 | BP16: =IFERROR(INDEX(LMH_PTS,MATCH(AB16,LMH_KEY,0)),0) -> 1 | BQ16: =IFERROR(INDEX(LMH_PTS,MATCH(AC16,LMH_KEY,0)),0) -> 3 | BR16: =IFERROR(INDEX(LMH_PTS,MATCH(AD16,LMH_KEY,0)),0) -> 1 | BS16: =IFERROR(INDEX(LMH_PTS,MATCH(AE16,LMH_KEY,0)),0) -> 1 | BT16: =IFERROR(INDEX(LMH_STEP,MATCH(AF16,LMH_KEY,0)),0) -> 0 | BU16: =IFERROR(INDEX(LMH_STEP,MATCH(AG16,LMH_KEY,0)),0) -> 0 | BV16: =IFERROR(INDEX(LMH_STEP,MATCH(AH16,LMH_KEY,0)),0) -> 0 | BW16: =IFERROR(INDEX(LMH_STEP,MATCH(AI16,LMH_KEY,0)),0) -> 0 | BX16: =IFERROR(INDEX(LMH_STEP,MATCH(AJ16,LMH_KEY,0)),0) -> 0 | BY16: =IFERROR(INDEX(LMH_STEP,MATCH(AK16,LMH_KEY,0)),0) -> 0 | BZ16: =IFERROR(INDEX(LMH_STEP,MATCH(AL16,LMH_KEY,0)),0) -> 0 | CA16: CARBON|Support|Senior Customer Success Specialist|B2|B-IC
A17: CARBON | B17: Support | C17: 5 | D17: IRIS1911 | E17: Varun Bubna | F17: Customer Success Manager | G17: Senior Customer Success Specialist | H17: Customer Success & Support | I17: Customer Success & Account Management | J17: IC | K17: RC-036 | L17: Anushree Aparajit | M17: IRIS1335 | N17: 8.4 | O17: 5.4 | P17: B.Com | Q17: L5 – Manager | R17: B2 | S17: 20 of 20 | T17: • Role / sub-team: Support — Customer Success Manager. • Core purpose: Intersection of Customers, Business, product and technology, helping customers get enabled into the platform and meet their regulatory needs understanding the value of our offering so that they stay. • Decision-making autonomy: Can independently customer feedback. • Is this something … | U17: Received · manager annual · Net Revenue Retention ≥100–105% Target ARR - to be achieved Rs. 50,00,000 per year 90% reach value milestone in 90 days Develop advocates · Promoter per CEM Produce case studies annually CSAT ≥90% NPS ≥30 100% QBR coverage for accounts 100% CRM hygiene maintained Renewal forecast accuracy ≥95% Outstanding receivables … | V17: Latest rating: 4 · Potential: Medium · 9-box: High Impact / Growth Talent · Readiness: Ready in 6–12 months | W17: C M · Au L · Ac M · L L · BI M · Exp M · 8.4 yrs vs 6–9 yrs · Edu M · B.Com | X17: Open ▸ | Y17: =IFERROR(INDEX(DL_C,MATCH($CA17,DL_KEY,0)),"M") -> H | Z17: =IFERROR(INDEX(DL_Au,MATCH($CA17,DL_KEY,0)),"M") -> M | AA17: =IFERROR(INDEX(DL_Ac,MATCH($CA17,DL_KEY,0)),"M") -> M | AB17: =IFERROR(INDEX(DL_L,MATCH($CA17,DL_KEY,0)),"M") -> L | AC17: =IFERROR(INDEX(DL_BI,MATCH($CA17,DL_KEY,0)),"M") -> M | AD17: =IFERROR(INDEX(DL_Exp,MATCH($CA17,DL_KEY,0)),"M") -> L | AE17: =IFERROR(INDEX(DL_Edu,MATCH($CA17,DL_KEY,0)),"M") -> L | AF17: M | AG17: M | AH17: M | AI17: M | AJ17: M | AK17: M | AL17: M | AM17: 0.513 | AN17: 0.173 | AO17: 0.097 | AP17: 0.05 | AQ17: 0.07 | AR17: 0.06 | AS17: 0.04 | AT17: 6–10 | AU17: Graduate or postgraduate; professional qualification preferred | AV17: IC: none · People: 6–8 knowledge work, 8–12 standardised delivery | AW17: P4 / M3 · SFIA 4–5 | AX17: S46–S51 Korn Ferry Hay evaluations · S04, S52 Mercer IPE · S53–S57 NHS, UK NJC/PSC, GLPC, SJC, US OPM point-factor plans · S58 McKinsey skills-based hiring · S60 WEF skills-first · S61 EY India 2026 · the Experience / Education split is an IRIS rule · S32 Google, Microsoft, Amazon · S33 Infosys · S35 Accenture India · IRIS experience guide · S01 Aon Radford · S02 Pave · S08 SFIA 9 · S03 Mercer career levels | AY17: B2 | AZ17: Band B · Specialist / Manager · Senior Specialist | BA17: Model B2 from the six ratings, the market-derived weights and rules R1–R13 · then No change · already below the manager | BB17: B1 | BC17: The six ratings on the market-average weights of Band B · Specialist / POD Lead score 4.47 → B1 · Hay, Mercer IPE and public plans · experience 8.4 yrs vs the B1 market range 4–8 | BD17: =IF(SUM(BM17,BN17,BO17,BP17,BQ17,BR17,BS17)=0,0,(BM17*BT17+BN17*BU17+BO17*BV17+BP17*BW17+BQ17*BX17+BR17*BY17+BS17*BZ17)/SUM(BM17,BN17,BO17,BP17,BQ17,BR17,BS17)) -> 0 | BE17: =IF(LEFT(AY17,1)="X",AY17,IF(OR(AY17="B+",AY17="C+"),INDEX(LAD_PC,MAX(1,MIN(14,MATCH(AY17,LAD_PC,0)+IF(BD17>=0.5,1,IF(BD17<=-0.5,-1,0))))),INDEX(LAD_STD,MAX(1,MIN(12,MATCH(AY17,LAD_STD,0)+IF(BD17>=0.5,1,IF(BD17<=-0.5,-1,0))))))) -> B2 | BG17: =IF(BF17<>"",BF17,BE17) -> B2 | BH17: =IFERROR(CHOOSE(INDEX(B_RANK,MATCH(BG17,B_LVL,0)),"Band A","Band B","B+ · Player-Coach","Band C","C+ · Player-Coach","Band D","Band E"),"Band X · Consultant") -> Band B | BI17: =IF(BG17=AY17,"• Same",IF(INDEX(B_VAL,MATCH(BG17,B_LVL,0))>INDEX(B_VAL,MATCH(AY17,B_LVL,0)),"▲ Up","▼ Down")) -> • Same | BJ17: =IF(OR($M17="",$M17="—",$M17="Not in this file"),"",IFERROR(INDEX($BG$7:$BG$592,MATCH($M17,$D$7:$D$592,0)),"")) -> B3 | BK17: =IFERROR(IF(BJ17="","—",IF(OR(LEFT(BG17,1)="X",LEFT(BJ17,1)="X"),"—",IF(AND(LEFT(BG17,1)="E",LEFT(BJ17,1)="E"),"Exception · Band E",IF(AND(INDEX(B_VAL,MATCH(BJ17,B_LVL,0))>=7,INDEX(B_RANK,MATCH(BG17,B_LVL,0))>=INDEX(B_RANK,MATCH(BJ17,B_LVL,0))),"⚠ Same band as a head manager",IF(INDEX(B_VAL,MATCH(BG17,B_LVL,0))>=INDEX(B_VAL,MATCH(BJ17,B_LVL,0)),"⚠ At or above the manager's level","OK"))))),"—") -> OK | BM17: =IFERROR(INDEX(LMH_PTS,MATCH(Y17,LMH_KEY,0)),0) -> 9 | BN17: =IFERROR(INDEX(LMH_PTS,MATCH(Z17,LMH_KEY,0)),0) -> 3 | BO17: =IFERROR(INDEX(LMH_PTS,MATCH(AA17,LMH_KEY,0)),0) -> 3 | BP17: =IFERROR(INDEX(LMH_PTS,MATCH(AB17,LMH_KEY,0)),0) -> 1 | BQ17: =IFERROR(INDEX(LMH_PTS,MATCH(AC17,LMH_KEY,0)),0) -> 3 | BR17: =IFERROR(INDEX(LMH_PTS,MATCH(AD17,LMH_KEY,0)),0) -> 1 | BS17: =IFERROR(INDEX(LMH_PTS,MATCH(AE17,LMH_KEY,0)),0) -> 1 | BT17: =IFERROR(INDEX(LMH_STEP,MATCH(AF17,LMH_KEY,0)),0) -> 0 | BU17: =IFERROR(INDEX(LMH_STEP,MATCH(AG17,LMH_KEY,0)),0) -> 0 | BV17: =IFERROR(INDEX(LMH_STEP,MATCH(AH17,LMH_KEY,0)),0) -> 0 | BW17: =IFERROR(INDEX(LMH_STEP,MATCH(AI17,LMH_KEY,0)),0) -> 0 | BX17: =IFERROR(INDEX(LMH_STEP,MATCH(AJ17,LMH_KEY,0)),0) -> 0 | BY17: =IFERROR(INDEX(LMH_STEP,MATCH(AK17,LMH_KEY,0)),0) -> 0 | BZ17: =IFERROR(INDEX(LMH_STEP,MATCH(AL17,LMH_KEY,0)),0) -> 0 | CA17: CARBON|Support|Senior Customer Success Specialist|B2|B-IC
A18: CARBON | B18: Support | C18: 5 | D18: IRIS1939 | E18: Nupur Samantaray | F18: Manager- Customer Engagement | G18: Senior Customer Success Specialist | H18: Customer Success & Support | I18: Customer Success & Account Management | J18: IC | K18: RC-035 | L18: Anushree Aparajit | M18: IRIS1335 | N18: 9.1 | O18: 5.1 | P18: CA | Q18: L5 – Manager | R18: B1 | S18: 20 of 20 | T18: • Role / sub-team: Support — Manager- Customer Engagement. • Core purpose: Act as primary point of contact and understand customer requirements and pass on to product or service team Coordinate between internal teams Renewal and customer retention Upselling. • Decision-making autonomy: Can independently new logo. • Is this something only they do: Most of … | U18: Received · manager annual · Net Revenue Retention ≥100–105% Target ARR - to be achieved: INR 55,00,000 90% reach value milestone in 90 days Develop advocates · Promoter per CEM Produce case studies annually CSAT ≥90% NPS ≥30 100% QBR coverage for accounts 100% CRM hygiene maintained Renewal forecast accuracy ≥95% Outstanding receivables ≤45 … | V18: Latest rating: 3 · Potential: Medium · 9-box: Core Contributor · Readiness: Develop in role | W18: C M · Au M · Ac M · L L · BI H · Exp H · 9.1 yrs vs 4–7 yrs · Edu H · CA | X18: Open ▸ | Y18: =IFERROR(INDEX(DL_C,MATCH($CA18,DL_KEY,0)),"M") -> H | Z18: =IFERROR(INDEX(DL_Au,MATCH($CA18,DL_KEY,0)),"M") -> M | AA18: =IFERROR(INDEX(DL_Ac,MATCH($CA18,DL_KEY,0)),"M") -> M | AB18: =IFERROR(INDEX(DL_L,MATCH($CA18,DL_KEY,0)),"M") -> L | AC18: =IFERROR(INDEX(DL_BI,MATCH($CA18,DL_KEY,0)),"M") -> M | AD18: =IFERROR(INDEX(DL_Exp,MATCH($CA18,DL_KEY,0)),"M") -> L | AE18: =IFERROR(INDEX(DL_Edu,MATCH($CA18,DL_KEY,0)),"M") -> L | AF18: M | AG18: M | AH18: M | AI18: M | AJ18: M | AK18: M | AL18: M | AM18: 0.513 | AN18: 0.173 | AO18: 0.097 | AP18: 0.05 | AQ18: 0.07 | AR18: 0.06 | AS18: 0.04 | AT18: 4–8 | AU18: Graduate + relevant qualification or certification preferred | AV18: IC: none · Team Lead: 3–5 | AW18: P3 / M2 · SFIA 4 Enable | AX18: S46–S51 Korn Ferry Hay evaluations · S04, S52 Mercer IPE · S53–S57 NHS, UK NJC/PSC, GLPC, SJC, US OPM point-factor plans · S58 McKinsey skills-based hiring · S60 WEF skills-first · S61 EY India 2026 · the Experience / Education split is an IRIS rule · S32 Google, Microsoft, Amazon · S33 Infosys · S35 Accenture India · IRIS experience guide · S01 Aon Radford · S02 Pave · S08 SFIA 9 · S03 Mercer career levels | AY18: B1 | AZ18: Band B · Specialist / Manager · Specialist | BA18: Model B1 from the six ratings, the market-derived weights and rules R1–R13 · then No change · already below the manager | BB18: B1 | BC18: The six ratings on the market-average weights of Band B · Specialist / POD Lead score 4.32 → B1 · Hay, Mercer IPE and public plans · experience 9.1 yrs vs the B1 market range 4–8 | BD18: =IF(SUM(BM18,BN18,BO18,BP18,BQ18,BR18,BS18)=0,0,(BM18*BT18+BN18*BU18+BO18*BV18+BP18*BW18+BQ18*BX18+BR18*BY18+BS18*BZ18)/SUM(BM18,BN18,BO18,BP18,BQ18,BR18,BS18)) -> 0 | BE18: =IF(LEFT(AY18,1)="X",AY18,IF(OR(AY18="B+",AY18="C+"),INDEX(LAD_PC,MAX(1,MIN(14,MATCH(AY18,LAD_PC,0)+IF(BD18>=0.5,1,IF(BD18<=-0.5,-1,0))))),INDEX(LAD_STD,MAX(1,MIN(12,MATCH(AY18,LAD_STD,0)+IF(BD18>=0.5,1,IF(BD18<=-0.5,-1,0))))))) -> B1 | BG18: =IF(BF18<>"",BF18,BE18) -> B1 | BH18: =IFERROR(CHOOSE(INDEX(B_RANK,MATCH(BG18,B_LVL,0)),"Band A","Band B","B+ · Player-Coach","Band C","C+ · Player-Coach","Band D","Band E"),"Band X · Consultant") -> Band B | BI18: =IF(BG18=AY18,"• Same",IF(INDEX(B_VAL,MATCH(BG18,B_LVL,0))>INDEX(B_VAL,MATCH(AY18,B_LVL,0)),"▲ Up","▼ Down")) -> • Same | BJ18: =IF(OR($M18="",$M18="—",$M18="Not in this file"),"",IFERROR(INDEX($BG$7:$BG$592,MATCH($M18,$D$7:$D$592,0)),"")) -> B3 | BK18: =IFERROR(IF(BJ18="","—",IF(OR(LEFT(BG18,1)="X",LEFT(BJ18,1)="X"),"—",IF(AND(LEFT(BG18,1)="E",LEFT(BJ18,1)="E"),"Exception · Band E",IF(AND(INDEX(B_VAL,MATCH(BJ18,B_LVL,0))>=7,INDEX(B_RANK,MATCH(BG18,B_LVL,0))>=INDEX(B_RANK,MATCH(BJ18,B_LVL,0))),"⚠ Same band as a head manager",IF(INDEX(B_VAL,MATCH(BG18,B_LVL,0))>=INDEX(B_VAL,MATCH(BJ18,B_LVL,0)),"⚠ At or above the manager's level","OK"))))),"—") -> OK | BM18: =IFERROR(INDEX(LMH_PTS,MATCH(Y18,LMH_KEY,0)),0) -> 9 | BN18: =IFERROR(INDEX(LMH_PTS,MATCH(Z18,LMH_KEY,0)),0) -> 3 | BO18: =IFERROR(INDEX(LMH_PTS,MATCH(AA18,LMH_KEY,0)),0) -> 3 | BP18: =IFERROR(INDEX(LMH_PTS,MATCH(AB18,LMH_KEY,0)),0) -> 1 | BQ18: =IFERROR(INDEX(LMH_PTS,MATCH(AC18,LMH_KEY,0)),0) -> 3 | BR18: =IFERROR(INDEX(LMH_PTS,MATCH(AD18,LMH_KEY,0)),0) -> 1 | BS18: =IFERROR(INDEX(LMH_PTS,MATCH(AE18,LMH_KEY,0)),0) -> 1 | BT18: =IFERROR(INDEX(LMH_STEP,MATCH(AF18,LMH_KEY,0)),0) -> 0 | BU18: =IFERROR(INDEX(LMH_STEP,MATCH(AG18,LMH_KEY,0)),0) -> 0 | BV18: =IFERROR(INDEX(LMH_STEP,MATCH(AH18,LMH_KEY,0)),0) -> 0 | BW18: =IFERROR(INDEX(LMH_STEP,MATCH(AI18,LMH_KEY,0)),0) -> 0 | BX18: =IFERROR(INDEX(LMH_STEP,MATCH(AJ18,LMH_KEY,0)),0) -> 0 | BY18: =IFERROR(INDEX(LMH_STEP,MATCH(AK18,LMH_KEY,0)),0) -> 0 | BZ18: =IFERROR(INDEX(LMH_STEP,MATCH(AL18,LMH_KEY,0)),0) -> 0 | CA18: CARBON|Support|Senior Customer Success Specialist|B1|B-IC
... A174: CARBON | B174: Support | C174: 4 | D174: IRIS0118 | E174: Mayur Narvekar | F174: Image Processing Specialist | G174: MIS Specialist | H174: Data & Analytics | I174: MIS & Business Reporting | J174: IC | K174: RC-044 | L174: Aniket Das | M174: IRIS2351 | N174: 19.1 | O174: 19.1 | P174: B.Com | Q174: L3 – Professional / Associate | R174: A3 | S174: 18 of 20 | T174: • Role / sub-team: Client Success / Support — Image Processing Specialist. • Core purpose: Revenue and expenses operations and data analysis. • Decision-making autonomy: Can independently handle revenue forecasting, ARR forecasting, client interaction, raising invoices, IR data preparation, and OF updates. • Is this something only he does: Largely his … | U174: KRAs not received · manager to supply | V174: Latest rating: Not rated · manager · 9-box: Not placed · manager · Readiness: No rating data | W174: C M · Au M · Ac M · L L · BI M · Exp H · 19.1 yrs vs 2–4 yrs · Edu M · B.Com | X174: Open ▸ | Y174: =IFERROR(INDEX(DL_C,MATCH($CA174,DL_KEY,0)),"M") -> H | Z174: =IFERROR(INDEX(DL_Au,MATCH($CA174,DL_KEY,0)),"M") -> M | AA174: =IFERROR(INDEX(DL_Ac,MATCH($CA174,DL_KEY,0)),"M") -> M | AB174: =IFERROR(INDEX(DL_L,MATCH($CA174,DL_KEY,0)),"M") -> L | AC174: =IFERROR(INDEX(DL_BI,MATCH($CA174,DL_KEY,0)),"M") -> L | AD174: =IFERROR(INDEX(DL_Exp,MATCH($CA174,DL_KEY,0)),"M") -> L | AE174: =IFERROR(INDEX(DL_Edu,MATCH($CA174,DL_KEY,0)),"M") -> L | AF174: M | AG174: M | AH174: M | AI174: M | AJ174: M | AK174: M | AL174: M | AM174: 0.583 | AN174: 0.16 | AO174: 0.09 | AP174: 0 | AQ174: 0.063 | AR174: 0.06 | AS174: 0.04 | AT174: 2–5 | AU174: Graduate; relevant certification preferred | AV174: None · guides 1–3 juniors informally | AW174: P2 · SFIA 3 Apply | AX174: S46–S51 Korn Ferry Hay evaluations · S04, S52 Mercer IPE · S53–S57 NHS, UK NJC/PSC, GLPC, SJC, US OPM point-factor plans · S58 McKinsey skills-based hiring · S60 WEF skills-first · S61 EY India 2026 · the Experience / Education split is an IRIS rule · S32 Google, Microsoft, Amazon · S33 Infosys · S35 Accenture India · IRIS experience guide · S01 Aon Radford · S02 Pave · S08 SFIA 9 · S03 Mercer career levels | AY174: A3 | AZ174: Band A · Practitioner · Senior Associate | BA174: Model A3 from the six ratings, the market-derived weights and rules R1–R13 · then No change · already below the manager | BB174: B1 | BC174: The six ratings on the market-average weights of Band A · all tracks score 3.57 → B1 · Hay, Mercer IPE and public plans · experience 19.1 yrs vs the B1 market range 4–8 | BD174: =IF(SUM(BM174,BN174,BO174,BP174,BQ174,BR174,BS174)=0,0,(BM174*BT174+BN174*BU174+BO174*BV174+BP174*BW174+BQ174*BX174+BR174*BY174+BS174*BZ174)/SUM(BM174,BN174,BO174,BP174,BQ174,BR174,BS174)) -> 0 | BE174: =IF(LEFT(AY174,1)="X",AY174,IF(OR(AY174="B+",AY174="C+"),INDEX(LAD_PC,MAX(1,MIN(14,MATCH(AY174,LAD_PC,0)+IF(BD174>=0.5,1,IF(BD174<=-0.5,-1,0))))),INDEX(LAD_STD,MAX(1,MIN(12,MATCH(AY174,LAD_STD,0)+IF(BD174>=0.5,1,IF(BD174<=-0.5,-1,0))))))) -> A3 | BG174: =IF(BF174<>"",BF174,BE174) -> A3 | BH174: =IFERROR(CHOOSE(INDEX(B_RANK,MATCH(BG174,B_LVL,0)),"Band A","Band B","B+ · Player-Coach","Band C","C+ · Player-Coach","Band D","Band E"),"Band X · Consultant") -> Band A | BI174: =IF(BG174=AY174,"• Same",IF(INDEX(B_VAL,MATCH(BG174,B_LVL,0))>INDEX(B_VAL,MATCH(AY174,B_LVL,0)),"▲ Up","▼ Down")) -> • Same | BJ174: =IF(OR($M174="",$M174="—",$M174="Not in this file"),"",IFERROR(INDEX($BG$7:$BG$592,MATCH($M174,$D$7:$D$592,0)),"")) -> B1 | BK174: =IFERROR(IF(BJ174="","—",IF(OR(LEFT(BG174,1)="X",LEFT(BJ174,1)="X"),"—",IF(AND(LEFT(BG174,1)="E",LEFT(BJ174,1)="E"),"Exception · Band E",IF(AND(INDEX(B_VAL,MATCH(BJ174,B_LVL,0))>=7,INDEX(B_RANK,MATCH(BG174,B_LVL,0))>=INDEX(B_RANK,MATCH(BJ174,B_LVL,0))),"⚠ Same band as a head manager",IF(INDEX(B_VAL,MATCH(BG174,B_LVL,0))>=INDEX(B_VAL,MATCH(BJ174,B_LVL,0)),"⚠ At or above the manager's level","OK"))))),"—") -> OK | BM174: =IFERROR(INDEX(LMH_PTS,MATCH(Y174,LMH_KEY,0)),0) -> 9 | BN174: =IFERROR(INDEX(LMH_PTS,MATCH(Z174,LMH_KEY,0)),0) -> 3 | BO174: =IFERROR(INDEX(LMH_PTS,MATCH(AA174,LMH_KEY,0)),0) -> 3 | BP174: =IFERROR(INDEX(LMH_PTS,MATCH(AB174,LMH_KEY,0)),0) -> 1 | BQ174: =IFERROR(INDEX(LMH_PTS,MATCH(AC174,LMH_KEY,0)),0) -> 1 | BR174: =IFERROR(INDEX(LMH_PTS,MATCH(AD174,LMH_KEY,0)),0) -> 1 | BS174: =IFERROR(INDEX(LMH_PTS,MATCH(AE174,LMH_KEY,0)),0) -> 1 | BT174: =IFERROR(INDEX(LMH_STEP,MATCH(AF174,LMH_KEY,0)),0) -> 0 | BU174: =IFERROR(INDEX(LMH_STEP,MATCH(AG174,LMH_KEY,0)),0) -> 0 | BV174: =IFERROR(INDEX(LMH_STEP,MATCH(AH174,LMH_KEY,0)),0) -> 0 | BW174: =IFERROR(INDEX(LMH_STEP,MATCH(AI174,LMH_KEY,0)),0) -> 0 | BX174: =IFERROR(INDEX(LMH_STEP,MATCH(AJ174,LMH_KEY,0)),0) -> 0 | BY174: =IFERROR(INDEX(LMH_STEP,MATCH(AK174,LMH_KEY,0)),0) -> 0 | BZ174: =IFERROR(INDEX(LMH_STEP,MATCH(AL174,LMH_KEY,0)),0) -> 0 | CA174: CARBON|Support|MIS Specialist|A3|A
A175: CARBON | B175: Sales | C175: 3 | D175: IRISC345 | E175: Andrea Messiga | F175: Regional Manager- Business Development | G175: Senior Consultant – Enterprise Sales & Account Management | H175: Sales & Business Development | I175: Enterprise Sales & Account Management | J175: Consultant | K175: RC-154 | L175: Anuradha RK | M175: IRIS0391 | N175: Not provided · HRIS | O175: 0.5 | P175: Not provided · HRIS | Q175: — | R175: X3 | S175: 0 of 20 | T175: No survey response on file | U175: KRAs not received · manager to supply | V175: Latest rating: Not rated · manager · Readiness: n/a · consultant | W175: Consultant · outside the ladder | X175: Open ▸ | AW175: — | AX175: S46–S51 Korn Ferry Hay evaluations · S04, S52 Mercer IPE · S53–S57 NHS, UK NJC/PSC, GLPC, SJC, US OPM point-factor plans · S58 McKinsey skills-based hiring · S60 WEF skills-first · S61 EY India 2026 · the Experience / Education split is an IRIS rule · S32 Google, Microsoft, Amazon · S33 Infosys · S35 Accenture India · IRIS experience guide · S01 Aon Radford · S02 Pave · S08 SFIA 9 · S03 Mercer career levels | AY175: X3 | AZ175: Band X · Consultant · | BA175: Model X3 from the six ratings, the market-derived weights and rules R1–R13 · then Consultant · outside the ladder | BC175: Consultant · outside the ladder | BD175: =IF(SUM(BM175,BN175,BO175,BP175,BQ175,BR175,BS175)=0,0,(BM175*BT175+BN175*BU175+BO175*BV175+BP175*BW175+BQ175*BX175+BR175*BY175+BS175*BZ175)/SUM(BM175,BN175,BO175,BP175,BQ175,BR175,BS175)) -> 0 | BE175: =IF(LEFT(AY175,1)="X",AY175,IF(OR(AY175="B+",AY175="C+"),INDEX(LAD_PC,MAX(1,MIN(14,MATCH(AY175,LAD_PC,0)+IF(BD175>=0.5,1,IF(BD175<=-0.5,-1,0))))),INDEX(LAD_STD,MAX(1,MIN(12,MATCH(AY175,LAD_STD,0)+IF(BD175>=0.5,1,IF(BD175<=-0.5,-1,0))))))) -> X3 | BG175: =IF(BF175<>"",BF175,BE175) -> X3 | BH175: =IFERROR(CHOOSE(INDEX(B_RANK,MATCH(BG175,B_LVL,0)),"Band A","Band B","B+ · Player-Coach","Band C","C+ · Player-Coach","Band D","Band E"),"Band X · Consultant") -> Band X · Consultant | BI175: =IF(BG175=AY175,"• Same",IF(INDEX(B_VAL,MATCH(BG175,B_LVL,0))>INDEX(B_VAL,MATCH(AY175,B_LVL,0)),"▲ Up","▼ Down")) -> • Same | BJ175: =IF(OR($M175="",$M175="—",$M175="Not in this file"),"",IFERROR(INDEX($BG$7:$BG$592,MATCH($M175,$D$7:$D$592,0)),"")) -> D2 | BK175: =IFERROR(IF(BJ175="","—",IF(OR(LEFT(BG175,1)="X",LEFT(BJ175,1)="X"),"—",IF(AND(LEFT(BG175,1)="E",LEFT(BJ175,1)="E"),"Exception · Band E",IF(AND(INDEX(B_VAL,MATCH(BJ175,B_LVL,0))>=7,INDEX(B_RANK,MATCH(BG175,B_LVL,0))>=INDEX(B_RANK,MATCH(BJ175,B_LVL,0))),"⚠ Same band as a head manager",IF(INDEX(B_VAL,MATCH(BG175,B_LVL,0))>=INDEX(B_VAL,MATCH(BJ175,B_LVL,0)),"⚠ At or above the manager's level","OK"))))),"—") -> — | BM175: =IFERROR(INDEX(LMH_PTS,MATCH(Y175,LMH_KEY,0)),0) -> 0 | BN175: =IFERROR(INDEX(LMH_PTS,MATCH(Z175,LMH_KEY,0)),0) -> 0 | BO175: =IFERROR(INDEX(LMH_PTS,MATCH(AA175,LMH_KEY,0)),0) -> 0 | BP175: =IFERROR(INDEX(LMH_PTS,MATCH(AB175,LMH_KEY,0)),0) -> 0 | BQ175: =IFERROR(INDEX(LMH_PTS,MATCH(AC175,LMH_KEY,0)),0) -> 0 | BR175: =IFERROR(INDEX(LMH_PTS,MATCH(AD175,LMH_KEY,0)),0) -> 0 | BS175: =IFERROR(INDEX(LMH_PTS,MATCH(AE175,LMH_KEY,0)),0) -> 0 | BT175: =IFERROR(INDEX(LMH_STEP,MATCH(AF175,LMH_KEY,0)),0) -> 0 | BU175: =IFERROR(INDEX(LMH_STEP,MATCH(AG175,LMH_KEY,0)),0) -> 0 | BV175: =IFERROR(INDEX(LMH_STEP,MATCH(AH175,LMH_KEY,0)),0) -> 0 | BW175: =IFERROR(INDEX(LMH_STEP,MATCH(AI175,LMH_KEY,0)),0) -> 0 | BX175: =IFERROR(INDEX(LMH_STEP,MATCH(AJ175,LMH_KEY,0)),0) -> 0 | BY175: =IFERROR(INDEX(LMH_STEP,MATCH(AK175,LMH_KEY,0)),0) -> 0 | BZ175: =IFERROR(INDEX(LMH_STEP,MATCH(AL175,LMH_KEY,0)),0) -> 0 | CA175: CARBON|Sales|Senior Consultant – Enterprise Sales & Account Management|X3|X
A176: Corporate | B176: Finance | C176: 1 | D176: IRIS0919 | E176: Vineet Kandoi | F176: Chief Financial Officer | G176: Chief Financial Officer | H176: Executive Leadership | I176: Business Head | J176: People Manager | K176: RC-EL-BH-E1 | L176: Balachandran K | M176: IRIS0001 | N176: 15 | O176: 15 | P176: CA + Senior Management Program | Q176: Not in current mapping files | R176: E1 | S176: 0 of 20 | T176: Complexity: Evidence: no survey answers or KRAs on file → rating stays at the start Autonomy: Evidence: no survey answers or KRAs on file → rating stays at the start Accountability: Evidence: no survey answers or KRAs on file → rating stays at the start Leadership: Evidence: no survey answers or KRAs on file → rating stays at the start Business Impact: No … | U176: KRAs not received · manager to supply | V176: Latest rating: Not rated · manager · 9-box: Not placed · manager · Readiness: No rating data | W176: C M · Au M · Ac M · L M · BI M · Exp L · 15 yrs vs 20+ yrs · Edu H · CA + Senior Management Program | X176: Open ▸ | Y176: =IFERROR(INDEX(DL_C,MATCH($CA176,DL_KEY,0)),"M") -> H | Z176: =IFERROR(INDEX(DL_Au,MATCH($CA176,DL_KEY,0)),"M") -> M | AA176: =IFERROR(INDEX(DL_Ac,MATCH($CA176,DL_KEY,0)),"M") -> M | AB176: =IFERROR(INDEX(DL_L,MATCH($CA176,DL_KEY,0)),"M") -> M | AC176: =IFERROR(INDEX(DL_BI,MATCH($CA176,DL_KEY,0)),"M") -> L | AD176: =IFERROR(INDEX(DL_Exp,MATCH($CA176,DL_KEY,0)),"M") -> L | AE176: =IFERROR(INDEX(DL_Edu,MATCH($CA176,DL_KEY,0)),"M") -> L | AF176: M | AG176: M | AH176: M | AI176: M | AJ176: M | AK176: M | AL176: M | AM176: 0.363 | AN176: 0.19 | AO176: 0.113 | AP176: 0.2 | AQ176: 0.087 | AR176: 0.04 | AS176: 0.01 | AT176: 20+ yrs | AU176: Postgraduate / professional qualification; business leadership record | AV176: 5–8 function heads | AW176: E5 · SFIA 7 | AX176: S46–S51 Korn Ferry Hay evaluations · S04, S52 Mercer IPE · S53–S57 NHS, UK NJC/PSC, GLPC, SJC, US OPM point-factor plans · S58 McKinsey skills-based hiring · S60 WEF skills-first · S61 EY India 2026 · the Experience / Education split is an IRIS rule · S32 Google, Microsoft, Amazon · S33 Infosys · S35 Accenture India · IRIS experience guide · S01 Aon Radford · S02 Pave · S08 SFIA 9 · S03 Mercer career levels | AY176: E1 | AZ176: Band E · Enterprise leadership · CXO / President | BA176: Model E1 from the six ratings, the market-derived weights and rules R1–R13 · then Band E with Band E · agreed exception · manager E2 | BB176: E1 | BC176: The six ratings on the market-average weights of Bands D–E · Leadership score 10.90 → E1 · Hay, Mercer IPE and public plans · experience 15 yrs vs the E1 market range 20+ yrs | BD176: =IF(SUM(BM176,BN176,BO176,BP176,BQ176,BR176,BS176)=0,0,(BM176*BT176+BN176*BU176+BO176*BV176+BP176*BW176+BQ176*BX176+BR176*BY176+BS176*BZ176)/SUM(BM176,BN176,BO176,BP176,BQ176,BR176,BS176)) -> 0 | BE176: =IF(LEFT(AY176,1)="X",AY176,IF(OR(AY176="B+",AY176="C+"),INDEX(LAD_PC,MAX(1,MIN(14,MATCH(AY176,LAD_PC,0)+IF(BD176>=0.5,1,IF(BD176<=-0.5,-1,0))))),INDEX(LAD_STD,MAX(1,MIN(12,MATCH(AY176,LAD_STD,0)+IF(BD176>=0.5,1,IF(BD176<=-0.5,-1,0))))))) -> E1 | BG176: =IF(BF176<>"",BF176,BE176) -> E1 | BH176: =IFERROR(CHOOSE(INDEX(B_RANK,MATCH(BG176,B_LVL,0)),"Band A","Band B","B+ · Player-Coach","Band C","C+ · Player-Coach","Band D","Band E"),"Band X · Consultant") -> Band E | BI176: =IF(BG176=AY176,"• Same",IF(INDEX(B_VAL,MATCH(BG176,B_LVL,0))>INDEX(B_VAL,MATCH(AY176,B_LVL,0)),"▲ Up","▼ Down")) -> • Same | BJ176: =IF(OR($M176="",$M176="—",$M176="Not in this file"),"",IFERROR(INDEX($BG$7:$BG$592,MATCH($M176,$D$7:$D$592,0)),"")) -> E2 | BK176: =IFERROR(IF(BJ176="","—",IF(OR(LEFT(BG176,1)="X",LEFT(BJ176,1)="X"),"—",IF(AND(LEFT(BG176,1)="E",LEFT(BJ176,1)="E"),"Exception · Band E",IF(AND(INDEX(B_VAL,MATCH(BJ176,B_LVL,0))>=7,INDEX(B_RANK,MATCH(BG176,B_LVL,0))>=INDEX(B_RANK,MATCH(BJ176,B_LVL,0))),"⚠ Same band as a head manager",IF(INDEX(B_VAL,MATCH(BG176,B_LVL,0))>=INDEX(B_VAL,MATCH(BJ176,B_LVL,0)),"⚠ At or above the manager's level","OK"))))),"—") -> Exception · Band E | BM176: =IFERROR(INDEX(LMH_PTS,MATCH(Y176,LMH_KEY,0)),0) -> 9 | BN176: =IFERROR(INDEX(LMH_PTS,MATCH(Z176,LMH_KEY,0)),0) -> 3 | BO176: =IFERROR(INDEX(LMH_PTS,MATCH(AA176,LMH_KEY,0)),0) -> 3 | BP176: =IFERROR(INDEX(LMH_PTS,MATCH(AB176,LMH_KEY,0)),0) -> 3 | BQ176: =IFERROR(INDEX(LMH_PTS,MATCH(AC176,LMH_KEY,0)),0) -> 1 | BR176: =IFERROR(INDEX(LMH_PTS,MATCH(AD176,LMH_KEY,0)),0) -> 1 | BS176: =IFERROR(INDEX(LMH_PTS,MATCH(AE176,LMH_KEY,0)),0) -> 1 | BT176: =IFERROR(INDEX(LMH_STEP,MATCH(AF176,LMH_KEY,0)),0) -> 0 | BU176: =IFERROR(INDEX(LMH_STEP,MATCH(AG176,LMH_KEY,0)),0) -> 0 | BV176: =IFERROR(INDEX(LMH_STEP,MATCH(AH176,LMH_KEY,0)),0) -> 0 | BW176: =IFERROR(INDEX(LMH_STEP,MATCH(AI176,LMH_KEY,0)),0) -> 0 | BX176: =IFERROR(INDEX(LMH_STEP,MATCH(AJ176,LMH_KEY,0)),0) -> 0 | BY176: =IFERROR(INDEX(LMH_STEP,MATCH(AK176,LMH_KEY,0)),0) -> 0 | BZ176: =IFERROR(INDEX(LMH_STEP,MATCH(AL176,LMH_KEY,0)),0) -> 0 | CA176: Corporate|Finance|Chief Financial Officer|E1|DE
A177: Corporate | B177: Finance | C177: 2 | D177: IRIS1918 | E177: Nishant Gupta | F177: Head Finance & Accounts | G177: Associate Head – Finance & Accounts | H177: Finance & Accounts | I177: Finance Leadership | J177: People Manager | K177: RC-097 | L177: Vineet Kandoi | M177: IRIS0919 | N177: 7.3 | O177: 5.3 | P177: CA | Q177: Not in current mapping files | R177: C1 | S177: 0 of 20 | T177: Complexity: Evidence: no survey answers or KRAs on file → rating stays at the start Autonomy: Evidence: no survey answers or KRAs on file → rating stays at the start Accountability: Evidence: no survey answers or KRAs on file → rating stays at the start Leadership: Evidence: no survey answers or KRAs on file → rating stays at the start Business Impact: No … | U177: KRAs not received · manager to supply | V177: Latest rating: Not rated · manager · 9-box: Not placed · manager · Readiness: No rating data | W177: C H · Au H · Ac M · L M · BI M · Exp L · 7.3 yrs vs 10–14 yrs · Edu H · CA | X177: Open ▸ | Y177: =IFERROR(INDEX(DL_C,MATCH($CA177,DL_KEY,0)),"M") -> H | Z177: =IFERROR(INDEX(DL_Au,MATCH($CA177,DL_KEY,0)),"M") -> M | AA177: =IFERROR(INDEX(DL_Ac,MATCH($CA177,DL_KEY,0)),"M") -> M | AB177: =IFERROR(INDEX(DL_L,MATCH($CA177,DL_KEY,0)),"M") -> M | AC177: =IFERROR(INDEX(DL_BI,MATCH($CA177,DL_KEY,0)),"M") -> L | AD177: =IFERROR(INDEX(DL_Exp,MATCH($CA177,DL_KEY,0)),"M") -> L | AE177: =IFERROR(INDEX(DL_Edu,MATCH($CA177,DL_KEY,0)),"M") -> L | AF177: M | AG177: M | AH177: M | AI177: M | AJ177: M | AK177: M | AL177: M | AM177: 0.433 | AN177: 0.18 | AO177: 0.107 | AP177: 0.15 | AQ177: 0.08 | AR177: 0.04 | AS177: 0.01 | AT177: 12–17 | AU177: Postgraduate / professional qualification preferred | AV177: 5–8, mostly managers | AW177: P6 / M5 · SFIA 5–6 | AX177: S46–S51 Korn Ferry Hay evaluations · S04, S52 Mercer IPE · S53–S57 NHS, UK NJC/PSC, GLPC, SJC, US OPM point-factor plans · S58 McKinsey skills-based hiring · S60 WEF skills-first · S61 EY India 2026 · the Experience / Education split is an IRIS rule · S32 Google, Microsoft, Amazon · S33 Infosys · S35 Accenture India · IRIS experience guide · S01 Aon Radford · S02 Pave · S08 SFIA 9 · S03 Mercer career levels | AY177: C1 | AZ177: Band C · Principal / Head · Associate Head | BA177: Model C1 from the six ratings, the market-derived weights and rules R1–R13 · then No change · already below the manager | BB177: C1 | BC177: The six ratings on the market-average weights of Band C · Head / manager score 7.47 → C1 · Hay, Mercer IPE and public plans · experience 7.3 yrs vs the C1 market range 12–17 | BD177: =IF(SUM(BM177,BN177,BO177,BP177,BQ177,BR177,BS177)=0,0,(BM177*BT177+BN177*BU177+BO177*BV177+BP177*BW177+BQ177*BX177+BR177*BY177+BS177*BZ177)/SUM(BM177,BN177,BO177,BP177,BQ177,BR177,BS177)) -> 0 | BE177: =IF(LEFT(AY177,1)="X",AY177,IF(OR(AY177="B+",AY177="C+"),INDEX(LAD_PC,MAX(1,MIN(14,MATCH(AY177,LAD_PC,0)+IF(BD177>=0.5,1,IF(BD177<=-0.5,-1,0))))),INDEX(LAD_STD,MAX(1,MIN(12,MATCH(AY177,LAD_STD,0)+IF(BD177>=0.5,1,IF(BD177<=-0.5,-1,0))))))) -> C1 | BG177: =IF(BF177<>"",BF177,BE177) -> C1 | BH177: =IFERROR(CHOOSE(INDEX(B_RANK,MATCH(BG177,B_LVL,0)),"Band A","Band B","B+ · Player-Coach","Band C","C+ · Player-Coach","Band D","Band E"),"Band X · Consultant") -> Band C | BI177: =IF(BG177=AY177,"• Same",IF(INDEX(B_VAL,MATCH(BG177,B_LVL,0))>INDEX(B_VAL,MATCH(AY177,B_LVL,0)),"▲ Up","▼ Down")) -> • Same | BJ177: =IF(OR($M177="",$M177="—",$M177="Not in this file"),"",IFERROR(INDEX($BG$7:$BG$592,MATCH($M177,$D$7:$D$592,0)),"")) -> E1 | BK177: =IFERROR(IF(BJ177="","—",IF(OR(LEFT(BG177,1)="X",LEFT(BJ177,1)="X"),"—",IF(AND(LEFT(BG177,1)="E",LEFT(BJ177,1)="E"),"Exception · Band E",IF(AND(INDEX(B_VAL,MATCH(BJ177,B_LVL,0))>=7,INDEX(B_RANK,MATCH(BG177,B_LVL,0))>=INDEX(B_RANK,MATCH(BJ177,B_LVL,0))),"⚠ Same band as a head manager",IF(INDEX(B_VAL,MATCH(BG177,B_LVL,0))>=INDEX(B_VAL,MATCH(BJ177,B_LVL,0)),"⚠ At or above the manager's level","OK"))))),"—") -> OK | BM177: =IFERROR(INDEX(LMH_PTS,MATCH(Y177,LMH_KEY,0)),0) -> 9 | BN177: =IFERROR(INDEX(LMH_PTS,MATCH(Z177,LMH_KEY,0)),0) -> 3 | BO177: =IFERROR(INDEX(LMH_PTS,MATCH(AA177,LMH_KEY,0)),0) -> 3 | BP177: =IFERROR(INDEX(LMH_PTS,MATCH(AB177,LMH_KEY,0)),0) -> 3 | BQ177: =IFERROR(INDEX(LMH_PTS,MATCH(AC177,LMH_KEY,0)),0) -> 1 | BR177: =IFERROR(INDEX(LMH_PTS,MATCH(AD177,LMH_KEY,0)),0) -> 1 | BS177: =IFERROR(INDEX(LMH_PTS,MATCH(AE177,LMH_KEY,0)),0) -> 1 | BT177: =IFERROR(INDEX(LMH_STEP,MATCH(AF177,LMH_KEY,0)),0) -> 0 | BU177: =IFERROR(INDEX(LMH_STEP,MATCH(AG177,LMH_KEY,0)),0) -> 0 | BV177: =IFERROR(INDEX(LMH_STEP,MATCH(AH177,LMH_KEY,0)),0) -> 0 | BW177: =IFERROR(INDEX(LMH_STEP,MATCH(AI177,LMH_KEY,0)),0) -> 0 | BX177: =IFERROR(INDEX(LMH_STEP,MATCH(AJ177,LMH_KEY,0)),0) -> 0 | BY177: =IFERROR(INDEX(LMH_STEP,MATCH(AK177,LMH_KEY,0)),0) -> 0 | BZ177: =IFERROR(INDEX(LMH_STEP,MATCH(AL177,LMH_KEY,0)),0) -> 0 | CA177: Corporate|Finance|Associate Head – Finance & Accounts|C1|C-M
A178: Corporate | B178: Finance | C178: 3 | D178: IRIS1508 | E178: Winny Nair | F178: Manager - Finance and Accounts | G178: Senior Finance Specialist – POD Lead | H178: Finance & Accounts | I178: Financial Reporting, Compliance & Audit | J178: POD Lead | K178: RC-099 | L178: Nishant Gupta | M178: IRIS1918 | N178: 19.9 | O178: 11.7 | P178: PGDM | Q178: Not in current mapping files | R178: B2 | S178: 19 of 20 | T178: Complexity: Evidence reads like B2: Spans statutory compliance, subsidiary book closing, audits, banking, forex hedging and regulatory notices → matches the start Autonomy: Evidence reads like A2: States decides 'Nothing' independently, though approves entries and executes forex hedging → moved down 1 Accountability: Evidence reads like B2: own survey / KRA … | U178: KRAs not received · manager to supply | V178: Latest rating: Not rated · manager · 9-box: Not placed · manager · Readiness: No rating data | W178: C M · Au L · Ac M · L L · BI M · Exp H · 19.9 yrs vs 6–9 yrs · Edu H · PGDM | X178: Open ▸ | Y178: =IFERROR(INDEX(DL_C,MATCH($CA178,DL_KEY,0)),"M") -> H | Z178: =IFERROR(INDEX(DL_Au,MATCH($CA178,DL_KEY,0)),"M") -> M | AA178: =IFERROR(INDEX(DL_Ac,MATCH($CA178,DL_KEY,0)),"M") -> M | AB178: =IFERROR(INDEX(DL_L,MATCH($CA178,DL_KEY,0)),"M") -> L | AC178: =IFERROR(INDEX(DL_BI,MATCH($CA178,DL_KEY,0)),"M") -> L | AD178: =IFERROR(INDEX(DL_Exp,MATCH($CA178,DL_KEY,0)),"M") -> L | AE178: =IFERROR(INDEX(DL_Edu,MATCH($CA178,DL_KEY,0)),"M") -> L | AF178: M | AG178: M | AH178: M | AI178: M | AJ178: M | AK178: M | AL178: M | AM178: 0.513 | AN178: 0.173 | AO178: 0.097 | AP178: 0.05 | AQ178: 0.07 | AR178: 0.06 | AS178: 0.04 | AT178: 6–10 | AU178: Graduate or postgraduate; professional qualification preferred | AV178: IC: none · People: 6–8 knowledge work, 8–12 standardised delivery | AW178: P4 / M3 · SFIA 4–5 | AX178: S46–S51 Korn Ferry Hay evaluations · S04, S52 Mercer IPE · S53–S57 NHS, UK NJC/PSC, GLPC, SJC, US OPM point-factor plans · S58 McKinsey skills-based hiring · S60 WEF skills-first · S61 EY India 2026 · the Experience / Education split is an IRIS rule · S32 Google, Microsoft, Amazon · S33 Infosys · S35 Accenture India · IRIS experience guide · S01 Aon Radford · S02 Pave · S08 SFIA 9 · S03 Mercer career levels | AY178: B2 | AZ178: Band B · Specialist / Manager · Manager | BA178: Model B2 from the six ratings, the market-derived weights and rules R1–R13 · then No change · already below the manager | BB178: B2 | BC178: The six ratings on the market-average weights of Band B · Specialist / POD Lead score 5.17 → B2 · Hay, Mercer IPE and public plans · experience 19.9 yrs vs the B2 market range 6–10 | BD178: =IF(SUM(BM178,BN178,BO178,BP178,BQ178,BR178,BS178)=0,0,(BM178*BT178+BN178*BU178+BO178*BV178+BP178*BW178+BQ178*BX178+BR178*BY178+BS178*BZ178)/SUM(BM178,BN178,BO178,BP178,BQ178,BR178,BS178)) -> 0 | BE178: =IF(LEFT(AY178,1)="X",AY178,IF(OR(AY178="B+",AY178="C+"),INDEX(LAD_PC,MAX(1,MIN(14,MATCH(AY178,LAD_PC,0)+IF(BD178>=0.5,1,IF(BD178<=-0.5,-1,0))))),INDEX(LAD_STD,MAX(1,MIN(12,MATCH(AY178,LAD_STD,0)+IF(BD178>=0.5,1,IF(BD178<=-0.5,-1,0))))))) -> B2 | BG178: =IF(BF178<>"",BF178,BE178) -> B2 | BH178: =IFERROR(CHOOSE(INDEX(B_RANK,MATCH(BG178,B_LVL,0)),"Band A","Band B","B+ · Player-Coach","Band C","C+ · Player-Coach","Band D","Band E"),"Band X · Consultant") -> Band B | BI178: =IF(BG178=AY178,"• Same",IF(INDEX(B_VAL,MATCH(BG178,B_LVL,0))>INDEX(B_VAL,MATCH(AY178,B_LVL,0)),"▲ Up","▼ Down")) -> • Same | BJ178: =IF(OR($M178="",$M178="—",$M178="Not in this file"),"",IFERROR(INDEX($BG$7:$BG$592,MATCH($M178,$D$7:$D$592,0)),"")) -> C1 | BK178: =IFERROR(IF(BJ178="","—",IF(OR(LEFT(BG178,1)="X",LEFT(BJ178,1)="X"),"—",IF(AND(LEFT(BG178,1)="E",LEFT(BJ178,1)="E"),"Exception · Band E",IF(AND(INDEX(B_VAL,MATCH(BJ178,B_LVL,0))>=7,INDEX(B_RANK,MATCH(BG178,B_LVL,0))>=INDEX(B_RANK,MATCH(BJ178,B_LVL,0))),"⚠ Same band as a head manager",IF(INDEX(B_VAL,MATCH(BG178,B_LVL,0))>=INDEX(B_VAL,MATCH(BJ178,B_LVL,0)),"⚠ At or above the manager's level","OK"))))),"—") -> OK | BM178: =IFERROR(INDEX(LMH_PTS,MATCH(Y178,LMH_KEY,0)),0) -> 9 | BN178: =IFERROR(INDEX(LMH_PTS,MATCH(Z178,LMH_KEY,0)),0) -> 3 | BO178: =IFERROR(INDEX(LMH_PTS,MATCH(AA178,LMH_KEY,0)),0) -> 3 | BP178: =IFERROR(INDEX(LMH_PTS,MATCH(AB178,LMH_KEY,0)),0) -> 1 | BQ178: =IFERROR(INDEX(LMH_PTS,MATCH(AC178,LMH_KEY,0)),0) -> 1 | BR178: =IFERROR(INDEX(LMH_PTS,MATCH(AD178,LMH_KEY,0)),0) -> 1 | BS178: =IFERROR(INDEX(LMH_PTS,MATCH(AE178,LMH_KEY,0)),0) -> 1 | BT178: =IFERROR(INDEX(LMH_STEP,MATCH(AF178,LMH_KEY,0)),0) -> 0 | BU178: =IFERROR(INDEX(LMH_STEP,MATCH(AG178,LMH_KEY,0)),0) -> 0 | BV178: =IFERROR(INDEX(LMH_STEP,MATCH(AH178,LMH_KEY,0)),0) -> 0 | BW178: =IFERROR(INDEX(LMH_STEP,MATCH(AI178,LMH_KEY,0)),0) -> 0 | BX178: =IFERROR(INDEX(LMH_STEP,MATCH(AJ178,LMH_KEY,0)),0) -> 0 | BY178: =IFERROR(INDEX(LMH_STEP,MATCH(AK178,LMH_KEY,0)),0) -> 0 | BZ178: =IFERROR(INDEX(LMH_STEP,MATCH(AL178,LMH_KEY,0)),0) -> 0 | CA178: Corporate|Finance|Senior Finance Specialist – POD Lead|B2|B-IC
A179: Corporate | B179: Finance | C179: 4 | D179: IRIS2214 | E179: Shreya Singh | F179: Assistant Manager - Finance and Accounts | G179: Finance Specialist – POD Lead | H179: Finance & Accounts | I179: Financial Reporting, Compliance & Audit | J179: POD Lead | K179: RC-098 | L179: Winny Nair | M179: IRIS1508 | N179: 6.1 | O179: 2.8 | P179: B.Com | Q179: Not in current mapping files | R179: B1 | S179: 20 of 20 | T179: Complexity: Evidence reads like B1: Revenue report, standalone financial statements, statutory auditor queries, ERP phase 2 development, DM tool → matches the start Autonomy: Evidence reads like A3: Decides sales order renewals; approves sales orders and invoices → moved down 0.5 Accountability: Evidence reads like B1: own survey / KRA answers · summarised … | U179: KRAs not received · manager to supply | V179: Latest rating: Not rated · manager · 9-box: Not placed · manager · Readiness: No rating data | W179: C M · Au M · Ac M · L M · BI M · Exp M · 6.1 yrs vs 4–7 yrs · Edu M · B.Com | X179: Open ▸ | Y179: =IFERROR(INDEX(DL_C,MATCH($CA179,DL_KEY,0)),"M") -> H | Z179: =IFERROR(INDEX(DL_Au,MATCH($CA179,DL_KEY,0)),"M") -> M | AA179: =IFERROR(INDEX(DL_Ac,MATCH($CA179,DL_KEY,0)),"M") -> M | AB179: =IFERROR(INDEX(DL_L,MATCH($CA179,DL_KEY,0)),"M") -> L | AC179: =IFERROR(INDEX(DL_BI,MATCH($CA179,DL_KEY,0)),"M") -> L | AD179: =IFERROR(INDEX(DL_Exp,MATCH($CA179,DL_KEY,0)),"M") -> L | AE179: =IFERROR(INDEX(DL_Edu,MATCH($CA179,DL_KEY,0)),"M") -> L | AF179: M | AG179: M | AH179: M | AI179: M | AJ179: M | AK179: M | AL179: M | AM179: 0.513 | AN179: 0.173 | AO179: 0.097 | AP179: 0.05 | AQ179: 0.07 | AR179: 0.06 | AS179: 0.04 | AT179: 4–8 | AU179: Graduate + relevant qualification or certification preferred | AV179: IC: none · Team Lead: 3–5 | AW179: P3 / M2 · SFIA 4 Enable | AX179: S46–S51 Korn Ferry Hay evaluations · S04, S52 Mercer IPE · S53–S57 NHS, UK NJC/PSC, GLPC, SJC, US OPM point-factor plans · S58 McKinsey skills-based hiring · S60 WEF skills-first · S61 EY India 2026 · the Experience / Education split is an IRIS rule · S32 Google, Microsoft, Amazon · S33 Infosys · S35 Accenture India · IRIS experience guide · S01 Aon Radford · S02 Pave · S08 SFIA 9 · S03 Mercer career levels | AY179: B1 | AZ179: Band B · Specialist / Manager · Team Lead / Asst Manager | BA179: Model B1 from the six ratings, the market-derived weights and rules R1–R13 · then No change · already below the manager | BB179: B1 | BC179: The six ratings on the market-average weights of Band B · Specialist / POD Lead score 3.94 → B1 · Hay, Mercer IPE and public plans · experience 6.1 yrs vs the B1 market range 4–8 | BD179: =IF(SUM(BM179,BN179,BO179,BP179,BQ179,BR179,BS179)=0,0,(BM179*BT179+BN179*BU179+BO179*BV179+BP179*BW179+BQ179*BX179+BR179*BY179+BS179*BZ179)/SUM(BM179,BN179,BO179,BP179,BQ179,BR179,BS179)) -> 0 | BE179: =IF(LEFT(AY179,1)="X",AY179,IF(OR(AY179="B+",AY179="C+"),INDEX(LAD_PC,MAX(1,MIN(14,MATCH(AY179,LAD_PC,0)+IF(BD179>=0.5,1,IF(BD179<=-0.5,-1,0))))),INDEX(LAD_STD,MAX(1,MIN(12,MATCH(AY179,LAD_STD,0)+IF(BD179>=0.5,1,IF(BD179<=-0.5,-1,0))))))) -> B1 | BG179: =IF(BF179<>"",BF179,BE179) -> B1 | BH179: =IFERROR(CHOOSE(INDEX(B_RANK,MATCH(BG179,B_LVL,0)),"Band A","Band B","B+ · Player-Coach","Band C","C+ · Player-Coach","Band D","Band E"),"Band X · Consultant") -> Band B | BI179: =IF(BG179=AY179,"• Same",IF(INDEX(B_VAL,MATCH(BG179,B_LVL,0))>INDEX(B_VAL,MATCH(AY179,B_LVL,0)),"▲ Up","▼ Down")) -> • Same | BJ179: =IF(OR($M179="",$M179="—",$M179="Not in this file"),"",IFERROR(INDEX($BG$7:$BG$592,MATCH($M179,$D$7:$D$592,0)),"")) -> B2 | BK179: =IFERROR(IF(BJ179="","—",IF(OR(LEFT(BG179,1)="X",LEFT(BJ179,1)="X"),"—",IF(AND(LEFT(BG179,1)="E",LEFT(BJ179,1)="E"),"Exception · Band E",IF(AND(INDEX(B_VAL,MATCH(BJ179,B_LVL,0))>=7,INDEX(B_RANK,MATCH(BG179,B_LVL,0))>=INDEX(B_RANK,MATCH(BJ179,B_LVL,0))),"⚠ Same band as a head manager",IF(INDEX(B_VAL,MATCH(BG179,B_LVL,0))>=INDEX(B_VAL,MATCH(BJ179,B_LVL,0)),"⚠ At or above the manager's level","OK"))))),"—") -> OK | BM179: =IFERROR(INDEX(LMH_PTS,MATCH(Y179,LMH_KEY,0)),0) -> 9 | BN179: =IFERROR(INDEX(LMH_PTS,MATCH(Z179,LMH_KEY,0)),0) -> 3 | BO179: =IFERROR(INDEX(LMH_PTS,MATCH(AA179,LMH_KEY,0)),0) -> 3 | BP179: =IFERROR(INDEX(LMH_PTS,MATCH(AB179,LMH_KEY,0)),0) -> 1 | BQ179: =IFERROR(INDEX(LMH_PTS,MATCH(AC179,LMH_KEY,0)),0) -> 1 | BR179: =IFERROR(INDEX(LMH_PTS,MATCH(AD179,LMH_KEY,0)),0) -> 1 | BS179: =IFERROR(INDEX(LMH_PTS,MATCH(AE179,LMH_KEY,0)),0) -> 1 | BT179: =IFERROR(INDEX(LMH_STEP,MATCH(AF179,LMH_KEY,0)),0) -> 0 | BU179: =IFERROR(INDEX(LMH_STEP,MATCH(AG179,LMH_KEY,0)),0) -> 0 | BV179: =IFERROR(INDEX(LMH_STEP,MATCH(AH179,LMH_KEY,0)),0) -> 0 | BW179: =IFERROR(INDEX(LMH_STEP,MATCH(AI179,LMH_KEY,0)),0) -> 0 | BX179: =IFERROR(INDEX(LMH_STEP,MATCH(AJ179,LMH_KEY,0)),0) -> 0 | BY179: =IFERROR(INDEX(LMH_STEP,MATCH(AK179,LMH_KEY,0)),0) -> 0 | BZ179: =IFERROR(INDEX(LMH_STEP,MATCH(AL179,LMH_KEY,0)),0) -> 0 | CA179: Corporate|Finance|Finance Specialist – POD Lead|B1|B-IC
A180: Corporate | B180: Finance | C180: 5 | D180: IRIS1724 | E180: Anita Chavan | F180: Senior Executive Accounts | G180: Accounts Specialist – POD Lead | H180: Finance & Accounts | I180: Accounting & Transaction Processing | J180: POD Lead | K180: RC-096 | L180: Shreya Singh | M180: IRIS2214 | N180: 20.6 | O180: 8.3 | P180: B.Com | Q180: Not in current mapping files | R180: B1 | S180: 20 of 20 | T180: Complexity: Evidence reads like A3: Bank payments, TDS and GST compliance, reimbursements, ledger reconciliations, audit and reporting → matches the start Autonomy: Evidence reads like A2: Decides within compliance activities; routine → moved down 0.5 Accountability: Evidence reads like A3: Timely statutory and bank payments; delays bring penalties or … | U180: KRAs not received · manager to supply | V180: Latest rating: Not rated · manager · 9-box: Not placed · manager · Readiness: No rating data | W180: C M · Au M · Ac M · L M · BI M · Exp H · 20.6 yrs vs 2–4 yrs · Edu M · B.Com | X180: Open ▸ | Y180: =IFERROR(INDEX(DL_C,MATCH($CA180,DL_KEY,0)),"M") -> H | Z180: =IFERROR(INDEX(DL_Au,MATCH($CA180,DL_KEY,0)),"M") -> M | AA180: =IFERROR(INDEX(DL_Ac,MATCH($CA180,DL_KEY,0)),"M") -> M | AB180: =IFERROR(INDEX(DL_L,MATCH($CA180,DL_KEY,0)),"M") -> L | AC180: =IFERROR(INDEX(DL_BI,MATCH($CA180,DL_KEY,0)),"M") -> L | AD180: =IFERROR(INDEX(DL_Exp,MATCH($CA180,DL_KEY,0)),"M") -> L | AE180: =IFERROR(INDEX(DL_Edu,MATCH($CA180,DL_KEY,0)),"M") -> M | AF180: M | AG180: M | AH180: M | AI180: M | AJ180: M | AK180: M | AL180: M | AM180: 0.583 | AN180: 0.16 | AO180: 0.09 | AP180: 0 | AQ180: 0.063 | AR180: 0.06 | AS180: 0.04 | AT180: 2–5 | AU180: Graduate; relevant certification preferred | AV180: None · guides 1–3 juniors informally | AW180: P2 · SFIA 3 Apply | AX180: S46–S51 Korn Ferry Hay evaluations · S04, S52 Mercer IPE · S53–S57 NHS, UK NJC/PSC, GLPC, SJC, US OPM point-factor plans · S58 McKinsey skills-based hiring · S60 WEF skills-first · S61 EY India 2026 · the Experience / Education split is an IRIS rule · S32 Google, Microsoft, Amazon · S33 Infosys · S35 Accenture India · IRIS experience guide · S01 Aon Radford · S02 Pave · S08 SFIA 9 · S03 Mercer career levels | AY180: A3 | AZ180: Band A · Practitioner · Senior Associate | BA180: Model B1 from the six ratings, the market-derived weights and rules R1–R13 · then Level rule: manager B1; a reportee sits at least one level below · B1 → A3 · move down · pay and title protected for one cycle | BB180: B1 | BC180: The six ratings on the market-average weights of Band A · all tracks score 3.62 → B1 · Hay, Mercer IPE and public plans · experience 20.6 yrs vs the B1 market range 4–8 | BD180: =IF(SUM(BM180,BN180,BO180,BP180,BQ180,BR180,BS180)=0,0,(BM180*BT180+BN180*BU180+BO180*BV180+BP180*BW180+BQ180*BX180+BR180*BY180+BS180*BZ180)/SUM(BM180,BN180,BO180,BP180,BQ180,BR180,BS180)) -> 0 | BE180: =IF(LEFT(AY180,1)="X",AY180,IF(OR(AY180="B+",AY180="C+"),INDEX(LAD_PC,MAX(1,MIN(14,MATCH(AY180,LAD_PC,0)+IF(BD180>=0.5,1,IF(BD180<=-0.5,-1,0))))),INDEX(LAD_STD,MAX(1,MIN(12,MATCH(AY180,LAD_STD,0)+IF(BD180>=0.5,1,IF(BD180<=-0.5,-1,0))))))) -> A3 | BG180: =IF(BF180<>"",BF180,BE180) -> A3 | BH180: =IFERROR(CHOOSE(INDEX(B_RANK,MATCH(BG180,B_LVL,0)),"Band A","Band B","B+ · Player-Coach","Band C","C+ · Player-Coach","Band D","Band E"),"Band X · Consultant") -> Band A | BI180: =IF(BG180=AY180,"• Same",IF(INDEX(B_VAL,MATCH(BG180,B_LVL,0))>INDEX(B_VAL,MATCH(AY180,B_LVL,0)),"▲ Up","▼ Down")) -> • Same | BJ180: =IF(OR($M180="",$M180="—",$M180="Not in this file"),"",IFERROR(INDEX($BG$7:$BG$592,MATCH($M180,$D$7:$D$592,0)),"")) -> B1 | BK180: =IFERROR(IF(BJ180="","—",IF(OR(LEFT(BG180,1)="X",LEFT(BJ180,1)="X"),"—",IF(AND(LEFT(BG180,1)="E",LEFT(BJ180,1)="E"),"Exception · Band E",IF(AND(INDEX(B_VAL,MATCH(BJ180,B_LVL,0))>=7,INDEX(B_RANK,MATCH(BG180,B_LVL,0))>=INDEX(B_RANK,MATCH(BJ180,B_LVL,0))),"⚠ Same band as a head manager",IF(INDEX(B_VAL,MATCH(BG180,B_LVL,0))>=INDEX(B_VAL,MATCH(BJ180,B_LVL,0)),"⚠ At or above the manager's level","OK"))))),"—") -> OK | BM180: =IFERROR(INDEX(LMH_PTS,MATCH(Y180,LMH_KEY,0)),0) -> 9 | BN180: =IFERROR(INDEX(LMH_PTS,MATCH(Z180,LMH_KEY,0)),0) -> 3 | BO180: =IFERROR(INDEX(LMH_PTS,MATCH(AA180,LMH_KEY,0)),0) -> 3 | BP180: =IFERROR(INDEX(LMH_PTS,MATCH(AB180,LMH_KEY,0)),0) -> 1 | BQ180: =IFERROR(INDEX(LMH_PTS,MATCH(AC180,LMH_KEY,0)),0) -> 1 | BR180: =IFERROR(INDEX(LMH_PTS,MATCH(AD180,LMH_KEY,0)),0) -> 1 | BS180: =IFERROR(INDEX(LMH_PTS,MATCH(AE180,LMH_KEY,0)),0) -> 3 | BT180: =IFERROR(INDEX(LMH_STEP,MATCH(AF180,LMH_KEY,0)),0) -> 0 | BU180: =IFERROR(INDEX(LMH_STEP,MATCH(AG180,LMH_KEY,0)),0) -> 0 | BV180: =IFERROR(INDEX(LMH_STEP,MATCH(AH180,LMH_KEY,0)),0) -> 0 | BW180: =IFERROR(INDEX(LMH_STEP,MATCH(AI180,LMH_KEY,0)),0) -> 0 | BX180: =IFERROR(INDEX(LMH_STEP,MATCH(AJ180,LMH_KEY,0)),0) -> 0 | BY180: =IFERROR(INDEX(LMH_STEP,MATCH(AK180,LMH_KEY,0)),0) -> 0 | BZ180: =IFERROR(INDEX(LMH_STEP,MATCH(AL180,LMH_KEY,0)),0) -> 0 | CA180: Corporate|Finance|Accounts Specialist – POD Lead|A3|A
A181: Corporate | B181: Finance | C181: 6 | D181: IRIS2217 | E181: Bhushan Kashid | F181: Executive Accounts | G181: Senior Accounts Executive | H181: Finance & Accounts | I181: Accounting & Transaction Processing | J181: IC | K181: RC-095 | L181: Anita Chavan | M181: IRIS1724 | N181: 8.7 | O181: 2.7 | P181: B.Com | Q181: Not in current mapping files | R181: A3 | S181: 19 of 20 | T181: Complexity: Evidence reads like A2: Invoice verification and booking, payment processing, vendor reconciliation, supplier creation → matches the start Autonomy: Evidence reads like A2: Decides purchase booking; queries anomalies rather than deciding them → matches the start Accountability: Evidence reads like A2: Accuracy of own invoice bookings, payment … | U181: KRAs not received · manager to supply | V181: Latest rating: Not rated · manager · 9-box: Not placed · manager · Readiness: No rating data | W181: C M · Au M · Ac M · L L · BI M · Exp H · 8.7 yrs vs 0–2 yrs · Edu M · B.Com | X181: Open ▸ | Y181: =IFERROR(INDEX(DL_C,MATCH($CA181,DL_KEY,0)),"M") -> H | Z181: =IFERROR(INDEX(DL_Au,MATCH($CA181,DL_KEY,0)),"M") -> M | AA181: =IFERROR(INDEX(DL_Ac,MATCH($CA181,DL_KEY,0)),"M") -> M | AB181: =IFERROR(INDEX(DL_L,MATCH($CA181,DL_KEY,0)),"M") -> L | AC181: =IFERROR(INDEX(DL_BI,MATCH($CA181,DL_KEY,0)),"M") -> L | AD181: =IFERROR(INDEX(DL_Exp,MATCH($CA181,DL_KEY,0)),"M") -> L | AE181: =IFERROR(INDEX(DL_Edu,MATCH($CA181,DL_KEY,0)),"M") -> M | AF181: M | AG181: M | AH181: M | AI181: M | AJ181: M | AK181: M | AL181: M | AM181: 0.583 | AN181: 0.16 | AO181: 0.09 | AP181: 0 | AQ181: 0.063 | AR181: 0.06 | AS181: 0.04 | AT181: 0–3 | AU181: Graduate · or diploma with experience | AV181: No direct reports | AW181: P1–P2 · SFIA 2 Assist | AX181: S46–S51 Korn Ferry Hay evaluations · S04, S52 Mercer IPE · S53–S57 NHS, UK NJC/PSC, GLPC, SJC, US OPM point-factor plans · S58 McKinsey skills-based hiring · S60 WEF skills-first · S61 EY India 2026 · the Experience / Education split is an IRIS rule · S32 Google, Microsoft, Amazon · S33 Infosys · S35 Accenture India · IRIS experience guide · S01 Aon Radford · S02 Pave · S08 SFIA 9 · S03 Mercer career levels | AY181: A2 | AZ181: Band A · Practitioner · Associate | BA181: Model A3 from the six ratings, the market-derived weights and rules R1–R13 · then Level rule: manager A3; a reportee sits at least one level below · A3 → A2 · move down · pay and title protected for one cycle | BB181: A2 | BC181: The six ratings on the market-average weights of Band A · all tracks score 2.35 → A2 · Hay, Mercer IPE and public plans · experience 8.7 yrs vs the A2 market range 0–3 | BD181: =IF(SUM(BM181,BN181,BO181,BP181,BQ181,BR181,BS181)=0,0,(BM181*BT181+BN181*BU181+BO181*BV181+BP181*BW181+BQ181*BX181+BR181*BY181+BS181*BZ181)/SUM(BM181,BN181,BO181,BP181,BQ181,BR181,BS181)) -> 0 | BE181: =IF(LEFT(AY181,1)="X",AY181,IF(OR(AY181="B+",AY181="C+"),INDEX(LAD_PC,MAX(1,MIN(14,MATCH(AY181,LAD_PC,0)+IF(BD181>=0.5,1,IF(BD181<=-0.5,-1,0))))),INDEX(LAD_STD,MAX(1,MIN(12,MATCH(AY181,LAD_STD,0)+IF(BD181>=0.5,1,IF(BD181<=-0.5,-1,0))))))) -> A2 | BG181: =IF(BF181<>"",BF181,BE181) -> A2 | BH181: =IFERROR(CHOOSE(INDEX(B_RANK,MATCH(BG181,B_LVL,0)),"Band A","Band B","B+ · Player-Coach","Band C","C+ · Player-Coach","Band D","Band E"),"Band X · Consultant") -> Band A | BI181: =IF(BG181=AY181,"• Same",IF(INDEX(B_VAL,MATCH(BG181,B_LVL,0))>INDEX(B_VAL,MATCH(AY181,B_LVL,0)),"▲ Up","▼ Down")) -> • Same | BJ181: =IF(OR($M181="",$M181="—",$M181="Not in this file"),"",IFERROR(INDEX($BG$7:$BG$592,MATCH($M181,$D$7:$D$592,0)),"")) -> A3 | BK181: =IFERROR(IF(BJ181="","—",IF(OR(LEFT(BG181,1)="X",LEFT(BJ181,1)="X"),"—",IF(AND(LEFT(BG181,1)="E",LEFT(BJ181,1)="E"),"Exception · Band E",IF(AND(INDEX(B_VAL,MATCH(BJ181,B_LVL,0))>=7,INDEX(B_RANK,MATCH(BG181,B_LVL,0))>=INDEX(B_RANK,MATCH(BJ181,B_LVL,0))),"⚠ Same band as a head manager",IF(INDEX(B_VAL,MATCH(BG181,B_LVL,0))>=INDEX(B_VAL,MATCH(BJ181,B_LVL,0)),"⚠ At or above the manager's level","OK"))))),"—") -> OK | BM181: =IFERROR(INDEX(LMH_PTS,MATCH(Y181,LMH_KEY,0)),0) -> 9 | BN181: =IFERROR(INDEX(LMH_PTS,MATCH(Z181,LMH_KEY,0)),0) -> 3 | BO181: =IFERROR(INDEX(LMH_PTS,MATCH(AA181,LMH_KEY,0)),0) -> 3 | BP181: =IFERROR(INDEX(LMH_PTS,MATCH(AB181,LMH_KEY,0)),0) -> 1 | BQ181: =IFERROR(INDEX(LMH_PTS,MATCH(AC181,LMH_KEY,0)),0) -> 1 | BR181: =IFERROR(INDEX(LMH_PTS,MATCH(AD181,LMH_KEY,0)),0) -> 1 | BS181: =IFERROR(INDEX(LMH_PTS,MATCH(AE181,LMH_KEY,0)),0) -> 3 | BT181: =IFERROR(INDEX(LMH_STEP,MATCH(AF181,LMH_KEY,0)),0) -> 0 | BU181: =IFERROR(INDEX(LMH_STEP,MATCH(AG181,LMH_KEY,0)),0) -> 0 | BV181: =IFERROR(INDEX(LMH_STEP,MATCH(AH181,LMH_KEY,0)),0) -> 0 | BW181: =IFERROR(INDEX(LMH_STEP,MATCH(AI181,LMH_KEY,0)),0) -> 0 | BX181: =IFERROR(INDEX(LMH_STEP,MATCH(AJ181,LMH_KEY,0)),0) -> 0 | BY181: =IFERROR(INDEX(LMH_STEP,MATCH(AK181,LMH_KEY,0)),0) -> 0 | BZ181: =IFERROR(INDEX(LMH_STEP,MATCH(AL181,LMH_KEY,0)),0) -> 0 | CA181: Corporate|Finance|Senior Accounts Executive|A2|A
A182: Corporate | B182: Finance | C182: 5 | D182: IRIS1557 | E182: Gaurangee Gaurav Tawde | F182: Senior Executive Accounts | G182: Accounts Specialist – POD Lead | H182: Finance & Accounts | I182: Accounting & Transaction Processing | J182: POD Lead | K182: RC-096 | L182: Shreya Singh | M182: IRIS2214 | N182: 20.1 | O182: 11.1 | P182: PGDM | Q182: Not in current mapping files | R182: B1 | S182: 20 of 20 | T182: Complexity: Evidence reads like A3: GST compliance, bank guarantees, Softex settlement, forward contract booking, audit coordination, MIS → matches the start Autonomy: Evidence reads like A2: Decides within compliance work; nothing broader stated → moved down 0.5 Accountability: Evidence reads like A3: GST, bank guarantee and Softex compliance; late filing … | U182: KRAs not received · manager to supply | V182: Latest rating: Not rated · manager · 9-box: Not placed · manager · Readiness: No rating data | W182: C M · Au M · Ac M · L M · BI M · Exp H · 20.1 yrs vs 2–4 yrs · Edu H · PGDM | X182: Open ▸ | Y182: =IFERROR(INDEX(DL_C,MATCH($CA182,DL_KEY,0)),"M") -> H | Z182: =IFERROR(INDEX(DL_Au,MATCH($CA182,DL_KEY,0)),"M") -> M | AA182: =IFERROR(INDEX(DL_Ac,MATCH($CA182,DL_KEY,0)),"M") -> M | AB182: =IFERROR(INDEX(DL_L,MATCH($CA182,DL_KEY,0)),"M") -> L | AC182: =IFERROR(INDEX(DL_BI,MATCH($CA182,DL_KEY,0)),"M") -> L | AD182: =IFERROR(INDEX(DL_Exp,MATCH($CA182,DL_KEY,0)),"M") -> L | AE182: =IFERROR(INDEX(DL_Edu,MATCH($CA182,DL_KEY,0)),"M") -> M | AF182: M | AG182: M | AH182: M | AI182: M | AJ182: M | AK182: M | AL182: M | AM182: 0.583 | AN182: 0.16 | AO182: 0.09 | AP182: 0 | AQ182: 0.063 | AR182: 0.06 | AS182: 0.04 | AT182: 2–5 | AU182: Graduate; relevant certification preferred | AV182: None · guides 1–3 juniors informally | AW182: P2 · SFIA 3 Apply | AX182: S46–S51 Korn Ferry Hay evaluations · S04, S52 Mercer IPE · S53–S57 NHS, UK NJC/PSC, GLPC, SJC, US OPM point-factor plans · S58 McKinsey skills-based hiring · S60 WEF skills-first · S61 EY India 2026 · the Experience / Education split is an IRIS rule · S32 Google, Microsoft, Amazon · S33 Infosys · S35 Accenture India · IRIS experience guide · S01 Aon Radford · S02 Pave · S08 SFIA 9 · S03 Mercer career levels | AY182: A3 | AZ182: Band A · Practitioner · Senior Associate | BA182: Model B1 from the six ratings, the market-derived weights and rules R1–R13 · then Level rule: manager B1; a reportee sits at least one level below · B1 → A3 · move down · pay and title protected for one cycle | BB182: B1 | BC182: The six ratings on the market-average weights of Band A · all tracks score 3.62 → B1 · Hay, Mercer IPE and public plans · experience 20.1 yrs vs the B1 market range 4–8 | BD182: =IF(SUM(BM182,BN182,BO182,BP182,BQ182,BR182,BS182)=0,0,(BM182*BT182+BN182*BU182+BO182*BV182+BP182*BW182+BQ182*BX182+BR182*BY182+BS182*BZ182)/SUM(BM182,BN182,BO182,BP182,BQ182,BR182,BS182)) -> 0 | BE182: =IF(LEFT(AY182,1)="X",AY182,IF(OR(AY182="B+",AY182="C+"),INDEX(LAD_PC,MAX(1,MIN(14,MATCH(AY182,LAD_PC,0)+IF(BD182>=0.5,1,IF(BD182<=-0.5,-1,0))))),INDEX(LAD_STD,MAX(1,MIN(12,MATCH(AY182,LAD_STD,0)+IF(BD182>=0.5,1,IF(BD182<=-0.5,-1,0))))))) -> A3 | BG182: =IF(BF182<>"",BF182,BE182) -> A3 | BH182: =IFERROR(CHOOSE(INDEX(B_RANK,MATCH(BG182,B_LVL,0)),"Band A","Band B","B+ · Player-Coach","Band C","C+ · Player-Coach","Band D","Band E"),"Band X · Consultant") -> Band A | BI182: =IF(BG182=AY182,"• Same",IF(INDEX(B_VAL,MATCH(BG182,B_LVL,0))>INDEX(B_VAL,MATCH(AY182,B_LVL,0)),"▲ Up","▼ Down")) -> • Same | BJ182: =IF(OR($M182="",$M182="—",$M182="Not in this file"),"",IFERROR(INDEX($BG$7:$BG$592,MATCH($M182,$D$7:$D$592,0)),"")) -> B1 | BK182: =IFERROR(IF(BJ182="","—",IF(OR(LEFT(BG182,1)="X",LEFT(BJ182,1)="X"),"—",IF(AND(LEFT(BG182,1)="E",LEFT(BJ182,1)="E"),"Exception · Band E",IF(AND(INDEX(B_VAL,MATCH(BJ182,B_LVL,0))>=7,INDEX(B_RANK,MATCH(BG182,B_LVL,0))>=INDEX(B_RANK,MATCH(BJ182,B_LVL,0))),"⚠ Same band as a head manager",IF(INDEX(B_VAL,MATCH(BG182,B_LVL,0))>=INDEX(B_VAL,MATCH(BJ182,B_LVL,0)),"⚠ At or above the manager's level","OK"))))),"—") -> OK | BM182: =IFERROR(INDEX(LMH_PTS,MATCH(Y182,LMH_KEY,0)),0) -> 9 | BN182: =IFERROR(INDEX(LMH_PTS,MATCH(Z182,LMH_KEY,0)),0) -> 3 | BO182: =IFERROR(INDEX(LMH_PTS,MATCH(AA182,LMH_KEY,0)),0) -> 3 | BP182: =IFERROR(INDEX(LMH_PTS,MATCH(AB182,LMH_KEY,0)),0) -> 1 | BQ182: =IFERROR(INDEX(LMH_PTS,MATCH(AC182,LMH_KEY,0)),0) -> 1 | BR182: =IFERROR(INDEX(LMH_PTS,MATCH(AD182,LMH_KEY,0)),0) -> 1 | BS182: =IFERROR(INDEX(LMH_PTS,MATCH(AE182,LMH_KEY,0)),0) -> 3 | BT182: =IFERROR(INDEX(LMH_STEP,MATCH(AF182,LMH_KEY,0)),0) -> 0 | BU182: =IFERROR(INDEX(LMH_STEP,MATCH(AG182,LMH_KEY,0)),0) -> 0 | BV182: =IFERROR(INDEX(LMH_STEP,MATCH(AH182,LMH_KEY,0)),0) -> 0 | BW182: =IFERROR(INDEX(LMH_STEP,MATCH(AI182,LMH_KEY,0)),0) -> 0 | BX182: =IFERROR(INDEX(LMH_STEP,MATCH(AJ182,LMH_KEY,0)),0) -> 0 | BY182: =IFERROR(INDEX(LMH_STEP,MATCH(AK182,LMH_KEY,0)),0) -> 0 | BZ182: =IFERROR(INDEX(LMH_STEP,MATCH(AL182,LMH_KEY,0)),0) -> 0 | CA182: Corporate|Finance|Accounts Specialist – POD Lead|A3|A
A183: Corporate | B183: Finance | C183: 6 | D183: IRIS2062 | E183: Riddhi Narkar | F183: Executive Accounts | G183: Senior Accounts Executive | H183: Finance & Accounts | I183: Accounting & Transaction Processing | J183: IC | K183: RC-095 | L183: Gaurangee Gaurav Tawde | M183: IRIS1557 | N183: 9.8 | O183: 4 | P183: B.Com | Q183: Not in current mapping files | R183: A3 | S183: 19 of 20 | T183: Complexity: Evidence reads like A2: Creates sales orders and invoices, records daily bank transactions, fixed asset data → matches the start Autonomy: Evidence reads like A1: States 'No freedom' to decide independently → moved down 0.5 Accountability: Evidence reads like A2: Entry-level accuracy and reports feeding the revenue report → matches the … | U183: KRAs not received · manager to supply | V183: Latest rating: Not rated · manager · 9-box: Not placed · manager · Readiness: No rating data | W183: C M · Au M · Ac M · L L · BI M · Exp H · 9.8 yrs vs 0–2 yrs · Edu M · B.Com | X183: Open ▸ | Y183: =IFERROR(INDEX(DL_C,MATCH($CA183,DL_KEY,0)),"M") -> H | Z183: =IFERROR(INDEX(DL_Au,MATCH($CA183,DL_KEY,0)),"M") -> M | AA183: =IFERROR(INDEX(DL_Ac,MATCH($CA183,DL_KEY,0)),"M") -> M | AB183: =IFERROR(INDEX(DL_L,MATCH($CA183,DL_KEY,0)),"M") -> L | AC183: =IFERROR(INDEX(DL_BI,MATCH($CA183,DL_KEY,0)),"M") -> L | AD183: =IFERROR(INDEX(DL_Exp,MATCH($CA183,DL_KEY,0)),"M") -> L | AE183: =IFERROR(INDEX(DL_Edu,MATCH($CA183,DL_KEY,0)),"M") -> M | AF183: M | AG183: M | AH183: M | AI183: M | AJ183: M | AK183: M | AL183: M | AM183: 0.583 | AN183: 0.16 | AO183: 0.09 | AP183: 0 | AQ183: 0.063 | AR183: 0.06 | AS183: 0.04 | AT183: 0–3 | AU183: Graduate · or diploma with experience | AV183: No direct reports | AW183: P1–P2 · SFIA 2 Assist | AX183: S46–S51 Korn Ferry Hay evaluations · S04, S52 Mercer IPE · S53–S57 NHS, UK NJC/PSC, GLPC, SJC, US OPM point-factor plans · S58 McKinsey skills-based hiring · S60 WEF skills-first · S61 EY India 2026 · the Experience / Education split is an IRIS rule · S32 Google, Microsoft, Amazon · S33 Infosys · S35 Accenture India · IRIS experience guide · S01 Aon Radford · S02 Pave · S08 SFIA 9 · S03 Mercer career levels | AY183: A2 | AZ183: Band A · Practitioner · Associate | BA183: Model A3 from the six ratings, the market-derived weights and rules R1–R13 · then Level rule: manager A3; a reportee sits at least one level below · A3 → A2 · move down · pay and title protected for one cycle | BB183: A2 | BC183: The six ratings on the market-average weights of Band A · all tracks score 2.32 → A2 · Hay, Mercer IPE and public plans · experience 9.8 yrs vs the A2 market range 0–3 | BD183: =IF(SUM(BM183,BN183,BO183,BP183,BQ183,BR183,BS183)=0,0,(BM183*BT183+BN183*BU183+BO183*BV183+BP183*BW183+BQ183*BX183+BR183*BY183+BS183*BZ183)/SUM(BM183,BN183,BO183,BP183,BQ183,BR183,BS183)) -> 0 | BE183: =IF(LEFT(AY183,1)="X",AY183,IF(OR(AY183="B+",AY183="C+"),INDEX(LAD_PC,MAX(1,MIN(14,MATCH(AY183,LAD_PC,0)+IF(BD183>=0.5,1,IF(BD183<=-0.5,-1,0))))),INDEX(LAD_STD,MAX(1,MIN(12,MATCH(AY183,LAD_STD,0)+IF(BD183>=0.5,1,IF(BD183<=-0.5,-1,0))))))) -> A2 | BG183: =IF(BF183<>"",BF183,BE183) -> A2 | BH183: =IFERROR(CHOOSE(INDEX(B_RANK,MATCH(BG183,B_LVL,0)),"Band A","Band B","B+ · Player-Coach","Band C","C+ · Player-Coach","Band D","Band E"),"Band X · Consultant") -> Band A | BI183: =IF(BG183=AY183,"• Same",IF(INDEX(B_VAL,MATCH(BG183,B_LVL,0))>INDEX(B_VAL,MATCH(AY183,B_LVL,0)),"▲ Up","▼ Down")) -> • Same | BJ183: =IF(OR($M183="",$M183="—",$M183="Not in this file"),"",IFERROR(INDEX($BG$7:$BG$592,MATCH($M183,$D$7:$D$592,0)),"")) -> A3 | BK183: =IFERROR(IF(BJ183="","—",IF(OR(LEFT(BG183,1)="X",LEFT(BJ183,1)="X"),"—",IF(AND(LEFT(BG183,1)="E",LEFT(BJ183,1)="E"),"Exception · Band E",IF(AND(INDEX(B_VAL,MATCH(BJ183,B_LVL,0))>=7,INDEX(B_RANK,MATCH(BG183,B_LVL,0))>=INDEX(B_RANK,MATCH(BJ183,B_LVL,0))),"⚠ Same band as a head manager",IF(INDEX(B_VAL,MATCH(BG183,B_LVL,0))>=INDEX(B_VAL,MATCH(BJ183,B_LVL,0)),"⚠ At or above the manager's level","OK"))))),"—") -> OK | BM183: =IFERROR(INDEX(LMH_PTS,MATCH(Y183,LMH_KEY,0)),0) -> 9 | BN183: =IFERROR(INDEX(LMH_PTS,MATCH(Z183,LMH_KEY,0)),0) -> 3 | BO183: =IFERROR(INDEX(LMH_PTS,MATCH(AA183,LMH_KEY,0)),0) -> 3 | BP183: =IFERROR(INDEX(LMH_PTS,MATCH(AB183,LMH_KEY,0)),0) -> 1 | BQ183: =IFERROR(INDEX(LMH_PTS,MATCH(AC183,LMH_KEY,0)),0) -> 1 | BR183: =IFERROR(INDEX(LMH_PTS,MATCH(AD183,LMH_KEY,0)),0) -> 1 | BS183: =IFERROR(INDEX(LMH_PTS,MATCH(AE183,LMH_KEY,0)),0) -> 3 | BT183: =IFERROR(INDEX(LMH_STEP,MATCH(AF183,LMH_KEY,0)),0) -> 0 | BU183: =IFERROR(INDEX(LMH_STEP,MATCH(AG183,LMH_KEY,0)),0) -> 0 | BV183: =IFERROR(INDEX(LMH_STEP,MATCH(AH183,LMH_KEY,0)),0) -> 0 | BW183: =IFERROR(INDEX(LMH_STEP,MATCH(AI183,LMH_KEY,0)),0) -> 0 | BX183: =IFERROR(INDEX(LMH_STEP,MATCH(AJ183,LMH_KEY,0)),0) -> 0 | BY183: =IFERROR(INDEX(LMH_STEP,MATCH(AK183,LMH_KEY,0)),0) -> 0 | BZ183: =IFERROR(INDEX(LMH_STEP,MATCH(AL183,LMH_KEY,0)),0) -> 0 | CA183: Corporate|Finance|Senior Accounts Executive|A2|A
A184: Corporate | B184: Finance | C184: 3 | D184: IRIS2547 | E184: Lalit Choudhary | F184: Assistant Manager - Finance and Accounts | G184: Finance Specialist | H184: Finance & Accounts | I184: Financial Reporting, Compliance & Audit | J184: IC | K184: RC-098 | L184: Nishant Gupta | M184: IRIS1918 | N184: 4.8 | O184: 0.2 | P184: CA | Q184: Not in current mapping files | R184: B1 | S184: 19 of 20 | T184: Complexity: Evidence reads like B1: Expense variance analysis, subsidiary and consolidated financial statements, budget preparation, GST/MSME compliance → matches the start Autonomy: Evidence reads like A2: Independent decisions limited to how expenses are analysed → moved down 1 Accountability: Evidence reads like A3: Owns expense analysis and the Ideal … | U184: KRAs not received · manager to supply | V184: Latest rating: Not rated · manager · 9-box: Not placed · manager · Readiness: No rating data | W184: C M · Au L · Ac M · L L · BI M · Exp M · 4.8 yrs vs 4–7 yrs · Edu H · CA | X184: Open ▸ | Y184: =IFERROR(INDEX(DL_C,MATCH($CA184,DL_KEY,0)),"M") -> H | Z184: =IFERROR(INDEX(DL_Au,MATCH($CA184,DL_KEY,0)),"M") -> M | AA184: =IFERROR(INDEX(DL_Ac,MATCH($CA184,DL_KEY,0)),"M") -> M | AB184: =IFERROR(INDEX(DL_L,MATCH($CA184,DL_KEY,0)),"M") -> L | AC184: =IFERROR(INDEX(DL_BI,MATCH($CA184,DL_KEY,0)),"M") -> L | AD184: =IFERROR(INDEX(DL_Exp,MATCH($CA184,DL_KEY,0)),"M") -> L | AE184: =IFERROR(INDEX(DL_Edu,MATCH($CA184,DL_KEY,0)),"M") -> L | AF184: M | AG184: M | AH184: M | AI184: M | AJ184: M | AK184: M | AL184: M | AM184: 0.513 | AN184: 0.173 | AO184: 0.097 | AP184: 0.05 | AQ184: 0.07 | AR184: 0.06 | AS184: 0.04 | AT184: 4–8 | AU184: Graduate + relevant qualification or certification preferred | AV184: IC: none · Team Lead: 3–5 | AW184: P3 / M2 · SFIA 4 Enable | AX184: S46–S51 Korn Ferry Hay evaluations · S04, S52 Mercer IPE · S53–S57 NHS, UK NJC/PSC, GLPC, SJC, US OPM point-factor plans · S58 McKinsey skills-based hiring · S60 WEF skills-first · S61 EY India 2026 · the Experience / Education split is an IRIS rule · S32 Google, Microsoft, Amazon · S33 Infosys · S35 Accenture India · IRIS experience guide · S01 Aon Radford · S02 Pave · S08 SFIA 9 · S03 Mercer career levels | AY184: B1 | AZ184: Band B · Specialist / Manager · Specialist | BA184: Model B1 from the six ratings, the market-derived weights and rules R1–R13 · then No change · already below the manager | BB184: B1 | BC184: The six ratings on the market-average weights of Band B · Specialist / POD Lead score 3.69 → B1 · Hay, Mercer IPE and public plans · experience 4.8 yrs vs the B1 market range 4–8 | BD184: =IF(SUM(BM184,BN184,BO184,BP184,BQ184,BR184,BS184)=0,0,(BM184*BT184+BN184*BU184+BO184*BV184+BP184*BW184+BQ184*BX184+BR184*BY184+BS184*BZ184)/SUM(BM184,BN184,BO184,BP184,BQ184,BR184,BS184)) -> 0 | BE184: =IF(LEFT(AY184,1)="X",AY184,IF(OR(AY184="B+",AY184="C+"),INDEX(LAD_PC,MAX(1,MIN(14,MATCH(AY184,LAD_PC,0)+IF(BD184>=0.5,1,IF(BD184<=-0.5,-1,0))))),INDEX(LAD_STD,MAX(1,MIN(12,MATCH(AY184,LAD_STD,0)+IF(BD184>=0.5,1,IF(BD184<=-0.5,-1,0))))))) -> B1 | BG184: =IF(BF184<>"",BF184,BE184) -> B1 | BH184: =IFERROR(CHOOSE(INDEX(B_RANK,MATCH(BG184,B_LVL,0)),"Band A","Band B","B+ · Player-Coach","Band C","C+ · Player-Coach","Band D","Band E"),"Band X · Consultant") -> Band B | BI184: =IF(BG184=AY184,"• Same",IF(INDEX(B_VAL,MATCH(BG184,B_LVL,0))>INDEX(B_VAL,MATCH(AY184,B_LVL,0)),"▲ Up","▼ Down")) -> • Same | BJ184: =IF(OR($M184="",$M184="—",$M184="Not in this file"),"",IFERROR(INDEX($BG$7:$BG$592,MATCH($M184,$D$7:$D$592,0)),"")) -> C1 | BK184: =IFERROR(IF(BJ184="","—",IF(OR(LEFT(BG184,1)="X",LEFT(BJ184,1)="X"),"—",IF(AND(LEFT(BG184,1)="E",LEFT(BJ184,1)="E"),"Exception · Band E",IF(AND(INDEX(B_VAL,MATCH(BJ184,B_LVL,0))>=7,INDEX(B_RANK,MATCH(BG184,B_LVL,0))>=INDEX(B_RANK,MATCH(BJ184,B_LVL,0))),"⚠ Same band as a head manager",IF(INDEX(B_VAL,MATCH(BG184,B_LVL,0))>=INDEX(B_VAL,MATCH(BJ184,B_LVL,0)),"⚠ At or above the manager's level","OK"))))),"—") -> OK | BM184: =IFERROR(INDEX(LMH_PTS,MATCH(Y184,LMH_KEY,0)),0) -> 9 | BN184: =IFERROR(INDEX(LMH_PTS,MATCH(Z184,LMH_KEY,0)),0) -> 3 | BO184: =IFERROR(INDEX(LMH_PTS,MATCH(AA184,LMH_KEY,0)),0) -> 3 | BP184: =IFERROR(INDEX(LMH_PTS,MATCH(AB184,LMH_KEY,0)),0) -> 1 | BQ184: =IFERROR(INDEX(LMH_PTS,MATCH(AC184,LMH_KEY,0)),0) -> 1 | BR184: =IFERROR(INDEX(LMH_PTS,MATCH(AD184,LMH_KEY,0)),0) -> 1 | BS184: =IFERROR(INDEX(LMH_PTS,MATCH(AE184,LMH_KEY,0)),0) -> 1 | BT184: =IFERROR(INDEX(LMH_STEP,MATCH(AF184,LMH_KEY,0)),0) -> 0 | BU184: =IFERROR(INDEX(LMH_STEP,MATCH(AG184,LMH_KEY,0)),0) -> 0 | BV184: =IFERROR(INDEX(LMH_STEP,MATCH(AH184,LMH_KEY,0)),0) -> 0 | BW184: =IFERROR(INDEX(LMH_STEP,MATCH(AI184,LMH_KEY,0)),0) -> 0 | BX184: =IFERROR(INDEX(LMH_STEP,MATCH(AJ184,LMH_KEY,0)),0) -> 0 | BY184: =IFERROR(INDEX(LMH_STEP,MATCH(AK184,LMH_KEY,0)),0) -> 0 | BZ184: =IFERROR(INDEX(LMH_STEP,MATCH(AL184,LMH_KEY,0)),0) -> 0 | CA184: Corporate|Finance|Finance Specialist|B1|B-IC
A185: Corporate | B185: Finance | C185: 3 | D185: IRIS2561 | E185: Radhika Karnani | F185: Assistant Manager - Finance and Accounts | G185: Finance Specialist | H185: Finance & Accounts | I185: Financial Reporting, Compliance & Audit | J185: IC | K185: RC-098 | L185: Nishant Gupta | M185: IRIS1918 | N185: Not provided · HRIS | O185: 0.1 | P185: CA | Q185: Not in current mapping files | R185: B1 | S185: 19 of 20 | T185: Complexity: Evidence reads like B1: own survey / KRA answers · summarised by the rater; not quoted → matches the start Autonomy: Evidence reads like A2: Only 'process improvement' named as an independent decision → moved down 1 Accountability: Evidence reads like A3: own survey / KRA answers · summarised by the rater; not quoted → moved down 0.5 Leadership: … | U185: KRAs not received · manager to supply | V185: Latest rating: Not rated · manager · 9-box: Not placed · manager · Readiness: No rating data | W185: C M · Au L · Ac M · L L · BI M · Exp — · not on file · Edu H · CA | X185: Open ▸ | Y185: =IFERROR(INDEX(DL_C,MATCH($CA185,DL_KEY,0)),"M") -> H | Z185: =IFERROR(INDEX(DL_Au,MATCH($CA185,DL_KEY,0)),"M") -> M | AA185: =IFERROR(INDEX(DL_Ac,MATCH($CA185,DL_KEY,0)),"M") -> M | AB185: =IFERROR(INDEX(DL_L,MATCH($CA185,DL_KEY,0)),"M") -> L | AC185: =IFERROR(INDEX(DL_BI,MATCH($CA185,DL_KEY,0)),"M") -> L | AD185: =IFERROR(INDEX(DL_Exp,MATCH($CA185,DL_KEY,0)),"M") -> L | AE185: =IFERROR(INDEX(DL_Edu,MATCH($CA185,DL_KEY,0)),"M") -> L | AF185: M | AG185: M | AH185: M | AI185: M | AJ185: M | AK185: M | AL185: M | AM185: 0.513 | AN185: 0.173 | AO185: 0.097 | AP185: 0.05 | AQ185: 0.07 | AR185: 0.06 | AS185: 0.04 | AT185: 4–8 | AU185: Graduate + relevant qualification or certification preferred | AV185: IC: none · Team Lead: 3–5 | AW185: P3 / M2 · SFIA 4 Enable | AX185: S46–S51 Korn Ferry Hay evaluations · S04, S52 Mercer IPE · S53–S57 NHS, UK NJC/PSC, GLPC, SJC, US OPM point-factor plans · S58 McKinsey skills-based hiring · S60 WEF skills-first · S61 EY India 2026 · the Experience / Education split is an IRIS rule · S32 Google, Microsoft, Amazon · S33 Infosys · S35 Accenture India · IRIS experience guide · S01 Aon Radford · S02 Pave · S08 SFIA 9 · S03 Mercer career levels | AY185: B1 | AZ185: Band B · Specialist / Manager · Specialist | BA185: Model B1 from the six ratings, the market-derived weights and rules R1–R13 · then No change · already below the manager | BB185: B1 | BC185: The six ratings on the market-average weights of Band B · Specialist / POD Lead score 3.77 → B1 · Hay, Mercer IPE and public plans · experience Not provided · HRIS yrs vs the B1 market range 4–8 | BD185: =IF(SUM(BM185,BN185,BO185,BP185,BQ185,BR185,BS185)=0,0,(BM185*BT185+BN185*BU185+BO185*BV185+BP185*BW185+BQ185*BX185+BR185*BY185+BS185*BZ185)/SUM(BM185,BN185,BO185,BP185,BQ185,BR185,BS185)) -> 0 | BE185: =IF(LEFT(AY185,1)="X",AY185,IF(OR(AY185="B+",AY185="C+"),INDEX(LAD_PC,MAX(1,MIN(14,MATCH(AY185,LAD_PC,0)+IF(BD185>=0.5,1,IF(BD185<=-0.5,-1,0))))),INDEX(LAD_STD,MAX(1,MIN(12,MATCH(AY185,LAD_STD,0)+IF(BD185>=0.5,1,IF(BD185<=-0.5,-1,0))))))) -> B1 | BG185: =IF(BF185<>"",BF185,BE185) -> B1 | BH185: =IFERROR(CHOOSE(INDEX(B_RANK,MATCH(BG185,B_LVL,0)),"Band A","Band B","B+ · Player-Coach","Band C","C+ · Player-Coach","Band D","Band E"),"Band X · Consultant") -> Band B | BI185: =IF(BG185=AY185,"• Same",IF(INDEX(B_VAL,MATCH(BG185,B_LVL,0))>INDEX(B_VAL,MATCH(AY185,B_LVL,0)),"▲ Up","▼ Down")) -> • Same | BJ185: =IF(OR($M185="",$M185="—",$M185="Not in this file"),"",IFERROR(INDEX($BG$7:$BG$592,MATCH($M185,$D$7:$D$592,0)),"")) -> C1 | BK185: =IFERROR(IF(BJ185="","—",IF(OR(LEFT(BG185,1)="X",LEFT(BJ185,1)="X"),"—",IF(AND(LEFT(BG185,1)="E",LEFT(BJ185,1)="E"),"Exception · Band E",IF(AND(INDEX(B_VAL,MATCH(BJ185,B_LVL,0))>=7,INDEX(B_RANK,MATCH(BG185,B_LVL,0))>=INDEX(B_RANK,MATCH(BJ185,B_LVL,0))),"⚠ Same band as a head manager",IF(INDEX(B_VAL,MATCH(BG185,B_LVL,0))>=INDEX(B_VAL,MATCH(BJ185,B_LVL,0)),"⚠ At or above the manager's level","OK"))))),"—") -> OK | BM185: =IFERROR(INDEX(LMH_PTS,MATCH(Y185,LMH_KEY,0)),0) -> 9 | BN185: =IFERROR(INDEX(LMH_PTS,MATCH(Z185,LMH_KEY,0)),0) -> 3 | BO185: =IFERROR(INDEX(LMH_PTS,MATCH(AA185,LMH_KEY,0)),0) -> 3 | BP185: =IFERROR(INDEX(LMH_PTS,MATCH(AB185,LMH_KEY,0)),0) -> 1 | BQ185: =IFERROR(INDEX(LMH_PTS,MATCH(AC185,LMH_KEY,0)),0) -> 1 | BR185: =IFERROR(INDEX(LMH_PTS,MATCH(AD185,LMH_KEY,0)),0) -> 1 | BS185: =IFERROR(INDEX(LMH_PTS,MATCH(AE185,LMH_KEY,0)),0) -> 1 | BT185: =IFERROR(INDEX(LMH_STEP,MATCH(AF185,LMH_KEY,0)),0) -> 0 | BU185: =IFERROR(INDEX(LMH_STEP,MATCH(AG185,LMH_KEY,0)),0) -> 0 | BV185: =IFERROR(INDEX(LMH_STEP,MATCH(AH185,LMH_KEY,0)),0) -> 0 | BW185: =IFERROR(INDEX(LMH_STEP,MATCH(AI185,LMH_KEY,0)),0) -> 0 | BX185: =IFERROR(INDEX(LMH_STEP,MATCH(AJ185,LMH_KEY,0)),0) -> 0 | BY185: =IFERROR(INDEX(LMH_STEP,MATCH(AK185,LMH_KEY,0)),0) -> 0 | BZ185: =IFERROR(INDEX(LMH_STEP,MATCH(AL185,LMH_KEY,0)),0) -> 0 | CA185: Corporate|Finance|Finance Specialist|B1|B-IC
A186: Corporate | B186: Finance | C186: 2 | D186: IRIS0006 | E186: Sudhakar Sawant | F186: Head – Admin & Internal Audit | G186: Associate Head – Admin & Internal Audit | H186: Finance & Accounts | I186: Finance Leadership | J186: People Manager | K186: RC-097 | L186: Vineet Kandoi | M186: IRIS0919 | N186: 28.3 | O186: 22.1 | P186: B.Com | Q186: Not in current mapping files | R186: C1 | S186: 0 of 20 | T186: Complexity: Evidence: no survey answers or KRAs on file → rating stays at the start Autonomy: Evidence: no survey answers or KRAs on file → rating stays at the start Accountability: Evidence: no survey answers or KRAs on file → rating stays at the start Leadership: Evidence: no survey answers or KRAs on file → rating stays at the start Business Impact: No … | U186: KRAs not received · manager to supply | V186: Latest rating: Not rated · manager · 9-box: Not placed · manager · Readiness: No rating data | W186: C H · Au H · Ac L · L M · BI L · Exp H · 28.3 yrs vs 10–14 yrs · Edu L · B.Com | X186: Open ▸ | Y186: =IFERROR(INDEX(DL_C,MATCH($CA186,DL_KEY,0)),"M") -> H | Z186: =IFERROR(INDEX(DL_Au,MATCH($CA186,DL_KEY,0)),"M") -> M | AA186: =IFERROR(INDEX(DL_Ac,MATCH($CA186,DL_KEY,0)),"M") -> M | AB186: =IFERROR(INDEX(DL_L,MATCH($CA186,DL_KEY,0)),"M") -> M | AC186: =IFERROR(INDEX(DL_BI,MATCH($CA186,DL_KEY,0)),"M") -> L | AD186: =IFERROR(INDEX(DL_Exp,MATCH($CA186,DL_KEY,0)),"M") -> L | AE186: =IFERROR(INDEX(DL_Edu,MATCH($CA186,DL_KEY,0)),"M") -> L | AF186: M | AG186: M | AH186: M | AI186: M | AJ186: M | AK186: M | AL186: M | AM186: 0.433 | AN186: 0.18 | AO186: 0.107 | AP186: 0.15 | AQ186: 0.08 | AR186: 0.04 | AS186: 0.01 | AT186: 12–17 | AU186: Postgraduate / professional qualification preferred | AV186: 5–8, mostly managers | AW186: P6 / M5 · SFIA 5–6 | AX186: S46–S51 Korn Ferry Hay evaluations · S04, S52 Mercer IPE · S53–S57 NHS, UK NJC/PSC, GLPC, SJC, US OPM point-factor plans · S58 McKinsey skills-based hiring · S60 WEF skills-first · S61 EY India 2026 · the Experience / Education split is an IRIS rule · S32 Google, Microsoft, Amazon · S33 Infosys · S35 Accenture India · IRIS experience guide · S01 Aon Radford · S02 Pave · S08 SFIA 9 · S03 Mercer career levels | AY186: C1 | AZ186: Band C · Principal / Head · Associate Head | BA186: Model C1 from the six ratings, the market-derived weights and rules R1–R13 · then No change · already below the manager | BB186: C2 | BC186: The six ratings on the market-average weights of Band C · Head / manager score 7.68 → C2 · Hay, Mercer IPE and public plans · experience 28.3 yrs vs the C2 market range 12–17 yrs | BD186: =IF(SUM(BM186,BN186,BO186,BP186,BQ186,BR186,BS186)=0,0,(BM186*BT186+BN186*BU186+BO186*BV186+BP186*BW186+BQ186*BX186+BR186*BY186+BS186*BZ186)/SUM(BM186,BN186,BO186,BP186,BQ186,BR186,BS186)) -> 0 | BE186: =IF(LEFT(AY186,1)="X",AY186,IF(OR(AY186="B+",AY186="C+"),INDEX(LAD_PC,MAX(1,MIN(14,MATCH(AY186,LAD_PC,0)+IF(BD186>=0.5,1,IF(BD186<=-0.5,-1,0))))),INDEX(LAD_STD,MAX(1,MIN(12,MATCH(AY186,LAD_STD,0)+IF(BD186>=0.5,1,IF(BD186<=-0.5,-1,0))))))) -> C1 | BG186: =IF(BF186<>"",BF186,BE186) -> C1 | BH186: =IFERROR(CHOOSE(INDEX(B_RANK,MATCH(BG186,B_LVL,0)),"Band A","Band B","B+ · Player-Coach","Band C","C+ · Player-Coach","Band D","Band E"),"Band X · Consultant") -> Band C | BI186: =IF(BG186=AY186,"• Same",IF(INDEX(B_VAL,MATCH(BG186,B_LVL,0))>INDEX(B_VAL,MATCH(AY186,B_LVL,0)),"▲ Up","▼ Down")) -> • Same | BJ186: =IF(OR($M186="",$M186="—",$M186="Not in this file"),"",IFERROR(INDEX($BG$7:$BG$592,MATCH($M186,$D$7:$D$592,0)),"")) -> E1 | BK186: =IFERROR(IF(BJ186="","—",IF(OR(LEFT(BG186,1)="X",LEFT(BJ186,1)="X"),"—",IF(AND(LEFT(BG186,1)="E",LEFT(BJ186,1)="E"),"Exception · Band E",IF(AND(INDEX(B_VAL,MATCH(BJ186,B_LVL,0))>=7,INDEX(B_RANK,MATCH(BG186,B_LVL,0))>=INDEX(B_RANK,MATCH(BJ186,B_LVL,0))),"⚠ Same band as a head manager",IF(INDEX(B_VAL,MATCH(BG186,B_LVL,0))>=INDEX(B_VAL,MATCH(BJ186,B_LVL,0)),"⚠ At or above the manager's level","OK"))))),"—") -> OK | BM186: =IFERROR(INDEX(LMH_PTS,MATCH(Y186,LMH_KEY,0)),0) -> 9 | BN186: =IFERROR(INDEX(LMH_PTS,MATCH(Z186,LMH_KEY,0)),0) -> 3 | BO186: =IFERROR(INDEX(LMH_PTS,MATCH(AA186,LMH_KEY,0)),0) -> 3 | BP186: =IFERROR(INDEX(LMH_PTS,MATCH(AB186,LMH_KEY,0)),0) -> 3 | BQ186: =IFERROR(INDEX(LMH_PTS,MATCH(AC186,LMH_KEY,0)),0) -> 1 | BR186: =IFERROR(INDEX(LMH_PTS,MATCH(AD186,LMH_KEY,0)),0) -> 1 | BS186: =IFERROR(INDEX(LMH_PTS,MATCH(AE186,LMH_KEY,0)),0) -> 1 | BT186: =IFERROR(INDEX(LMH_STEP,MATCH(AF186,LMH_KEY,0)),0) -> 0 | BU186: =IFERROR(INDEX(LMH_STEP,MATCH(AG186,LMH_KEY,0)),0) -> 0 | BV186: =IFERROR(INDEX(LMH_STEP,MATCH(AH186,LMH_KEY,0)),0) -> 0 | BW186: =IFERROR(INDEX(LMH_STEP,MATCH(AI186,LMH_KEY,0)),0) -> 0 | BX186: =IFERROR(INDEX(LMH_STEP,MATCH(AJ186,LMH_KEY,0)),0) -> 0 | BY186: =IFERROR(INDEX(LMH_STEP,MATCH(AK186,LMH_KEY,0)),0) -> 0 | BZ186: =IFERROR(INDEX(LMH_STEP,MATCH(AL186,LMH_KEY,0)),0) -> 0 | CA186: Corporate|Finance|Associate Head – Admin & Internal Audit|C1|C-M
A187: Corporate | B187: Administration | C187: 3 | D187: IRIS1326 | E187: Sujit Acharya | F187: Manager Administration | G187: Manager – Administration | H187: Administration, Legal & Secretarial | I187: Administration & Facilities | J187: People Manager | K187: RC-002 | L187: Sudhakar Sawant | M187: IRIS0006 | N187: 21.7 | O187: 13.5 | P187: B.Com | Q187: Not in current mapping files | R187: B2 | S187: 20 of 20 | T187: Complexity: Evidence reads like A3: Runs travel, facilities, vendor contracts, billing and procurement; negotiates routine rates within policy → moved down 1 Autonomy: Evidence reads like A3: Selects from approved vendors, negotiates routine rates, schedules maintenance within delegated authority → moved down 1 Accountability: Evidence reads like B1: Owns … | U187: KRAs not received · manager to supply | V187: Latest rating: Not rated · manager · 9-box: Not placed · manager · Readiness: No rating data | W187: C L · Au L · Ac L · L L · BI L · Exp H · 21.7 yrs vs 6–9 yrs · Edu M · B.Com | X187: Open ▸ | Y187: =IFERROR(INDEX(DL_C,MATCH($CA187,DL_KEY,0)),"M") -> H | Z187: =IFERROR(INDEX(DL_Au,MATCH($CA187,DL_KEY,0)),"M") -> M | AA187: =IFERROR(INDEX(DL_Ac,MATCH($CA187,DL_KEY,0)),"M") -> M | AB187: =IFERROR(INDEX(DL_L,MATCH($CA187,DL_KEY,0)),"M") -> M | AC187: =IFERROR(INDEX(DL_BI,MATCH($CA187,DL_KEY,0)),"M") -> L | AD187: =IFERROR(INDEX(DL_Exp,MATCH($CA187,DL_KEY,0)),"M") -> L | AE187: =IFERROR(INDEX(DL_Edu,MATCH($CA187,DL_KEY,0)),"M") -> L | AF187: M | AG187: M | AH187: M | AI187: M | AJ187: M | AK187: M | AL187: M | AM187: 0.37 | AN187: 0.183 | AO187: 0.113 | AP187: 0.15 | AQ187: 0.087 | AR187: 0.06 | AS187: 0.04 | AT187: 6–10 | AU187: Graduate or postgraduate; professional qualification preferred | AV187: IC: none · People: 6–8 knowledge work, 8–12 standardised delivery | AW187: P4 / M3 · SFIA 4–5 | AX187: S46–S51 Korn Ferry Hay evaluations · S04, S52 Mercer IPE · S53–S57 NHS, UK NJC/PSC, GLPC, SJC, US OPM point-factor plans · S58 McKinsey skills-based hiring · S60 WEF skills-first · S61 EY India 2026 · the Experience / Education split is an IRIS rule · S32 Google, Microsoft, Amazon · S33 Infosys · S35 Accenture India · IRIS experience guide · S01 Aon Radford · S02 Pave · S08 SFIA 9 · S03 Mercer career levels | AY187: B2 | AZ187: Band B · Specialist / Manager · Manager | BA187: Model B2 from the six ratings, the market-derived weights and rules R1–R13 · then No change · already below the manager | BB187: B2 | BC187: The six ratings on the market-average weights of Band B · People Manager score 4.52 → B2 · Hay, Mercer IPE and public plans · experience 21.7 yrs vs the B2 market range 6–10 | BD187: =IF(SUM(BM187,BN187,BO187,BP187,BQ187,BR187,BS187)=0,0,(BM187*BT187+BN187*BU187+BO187*BV187+BP187*BW187+BQ187*BX187+BR187*BY187+BS187*BZ187)/SUM(BM187,BN187,BO187,BP187,BQ187,BR187,BS187)) -> 0 | BE187: =IF(LEFT(AY187,1)="X",AY187,IF(OR(AY187="B+",AY187="C+"),INDEX(LAD_PC,MAX(1,MIN(14,MATCH(AY187,LAD_PC,0)+IF(BD187>=0.5,1,IF(BD187<=-0.5,-1,0))))),INDEX(LAD_STD,MAX(1,MIN(12,MATCH(AY187,LAD_STD,0)+IF(BD187>=0.5,1,IF(BD187<=-0.5,-1,0))))))) -> B2 | BG187: =IF(BF187<>"",BF187,BE187) -> B2 | BH187: =IFERROR(CHOOSE(INDEX(B_RANK,MATCH(BG187,B_LVL,0)),"Band A","Band B","B+ · Player-Coach","Band C","C+ · Player-Coach","Band D","Band E"),"Band X · Consultant") -> Band B | BI187: =IF(BG187=AY187,"• Same",IF(INDEX(B_VAL,MATCH(BG187,B_LVL,0))>INDEX(B_VAL,MATCH(AY187,B_LVL,0)),"▲ Up","▼ Down")) -> • Same | BJ187: =IF(OR($M187="",$M187="—",$M187="Not in this file"),"",IFERROR(INDEX($BG$7:$BG$592,MATCH($M187,$D$7:$D$592,0)),"")) -> C1 | BK187: =IFERROR(IF(BJ187="","—",IF(OR(LEFT(BG187,1)="X",LEFT(BJ187,1)="X"),"—",IF(AND(LEFT(BG187,1)="E",LEFT(BJ187,1)="E"),"Exception · Band E",IF(AND(INDEX(B_VAL,MATCH(BJ187,B_LVL,0))>=7,INDEX(B_RANK,MATCH(BG187,B_LVL,0))>=INDEX(B_RANK,MATCH(BJ187,B_LVL,0))),"⚠ Same band as a head manager",IF(INDEX(B_VAL,MATCH(BG187,B_LVL,0))>=INDEX(B_VAL,MATCH(BJ187,B_LVL,0)),"⚠ At or above the manager's level","OK"))))),"—") -> OK | BM187: =IFERROR(INDEX(LMH_PTS,MATCH(Y187,LMH_KEY,0)),0) -> 9 | BN187: =IFERROR(INDEX(LMH_PTS,MATCH(Z187,LMH_KEY,0)),0) -> 3 | BO187: =IFERROR(INDEX(LMH_PTS,MATCH(AA187,LMH_KEY,0)),0) -> 3 | BP187: =IFERROR(INDEX(LMH_PTS,MATCH(AB187,LMH_KEY,0)),0) -> 3 | BQ187: =IFERROR(INDEX(LMH_PTS,MATCH(AC187,LMH_KEY,0)),0) -> 1 | BR187: =IFERROR(INDEX(LMH_PTS,MATCH(AD187,LMH_KEY,0)),0) -> 1 | BS187: =IFERROR(INDEX(LMH_PTS,MATCH(AE187,LMH_KEY,0)),0) -> 1 | BT187: =IFERROR(INDEX(LMH_STEP,MATCH(AF187,LMH_KEY,0)),0) -> 0 | BU187: =IFERROR(INDEX(LMH_STEP,MATCH(AG187,LMH_KEY,0)),0) -> 0 | BV187: =IFERROR(INDEX(LMH_STEP,MATCH(AH187,LMH_KEY,0)),0) -> 0 | BW187: =IFERROR(INDEX(LMH_STEP,MATCH(AI187,LMH_KEY,0)),0) -> 0 | BX187: =IFERROR(INDEX(LMH_STEP,MATCH(AJ187,LMH_KEY,0)),0) -> 0 | BY187: =IFERROR(INDEX(LMH_STEP,MATCH(AK187,LMH_KEY,0)),0) -> 0 | BZ187: =IFERROR(INDEX(LMH_STEP,MATCH(AL187,LMH_KEY,0)),0) -> 0 | CA187: Corporate|Administration|Manager – Administration|B2|B-M
A188: Corporate | B188: Administration | C188: 4 | D188: IRIS2431 | E188: Ashish Pawar | F188: Executive Administration | G188: Senior Administration Executive | H188: Administration, Legal & Secretarial | I188: Administration & Facilities | J188: IC | K188: RC-001 | L188: Sujit Acharya | M188: IRIS1326 | N188: 13.2 | O188: 1 | P188: BA | Q188: Not in current mapping files | R188: A3 | S188: 19 of 20 | T188: Complexity: Evidence reads like A2: own survey / KRA answers · summarised by the rater; not quoted → matches the start Autonomy: Evidence reads like A2: States 'routine decisions' only → matches the start Accountability: Evidence reads like A2: Own admin support and vendor coordination; errors cause delays or extra cost → matches the start Leadership: … | U188: KRAs not received · manager to supply | V188: Latest rating: Not rated · manager · 9-box: Not placed · manager · Readiness: No rating data | W188: C L · Au L · Ac L · L L · BI L · Exp H · 13.2 yrs vs 2–4 yrs · Edu M · BA | X188: Open ▸ | Y188: =IFERROR(INDEX(DL_C,MATCH($CA188,DL_KEY,0)),"M") -> H | Z188: =IFERROR(INDEX(DL_Au,MATCH($CA188,DL_KEY,0)),"M") -> M | AA188: =IFERROR(INDEX(DL_Ac,MATCH($CA188,DL_KEY,0)),"M") -> M | AB188: =IFERROR(INDEX(DL_L,MATCH($CA188,DL_KEY,0)),"M") -> L | AC188: =IFERROR(INDEX(DL_BI,MATCH($CA188,DL_KEY,0)),"M") -> L | AD188: =IFERROR(INDEX(DL_Exp,MATCH($CA188,DL_KEY,0)),"M") -> L | AE188: =IFERROR(INDEX(DL_Edu,MATCH($CA188,DL_KEY,0)),"M") -> M | AF188: M | AG188: M | AH188: M | AI188: M | AJ188: M | AK188: M | AL188: M | AM188: 0.583 | AN188: 0.16 | AO188: 0.09 | AP188: 0 | AQ188: 0.063 | AR188: 0.06 | AS188: 0.04 | AT188: 2–5 | AU188: Graduate; relevant certification preferred | AV188: None · guides 1–3 juniors informally | AW188: P2 · SFIA 3 Apply | AX188: S46–S51 Korn Ferry Hay evaluations · S04, S52 Mercer IPE · S53–S57 NHS, UK NJC/PSC, GLPC, SJC, US OPM point-factor plans · S58 McKinsey skills-based hiring · S60 WEF skills-first · S61 EY India 2026 · the Experience / Education split is an IRIS rule · S32 Google, Microsoft, Amazon · S33 Infosys · S35 Accenture India · IRIS experience guide · S01 Aon Radford · S02 Pave · S08 SFIA 9 · S03 Mercer career levels | AY188: A3 | AZ188: Band A · Practitioner · Senior Associate | BA188: Model A3 from the six ratings, the market-derived weights and rules R1–R13 · then No change · already below the manager | BB188: A3 | BC188: The six ratings on the market-average weights of Band A · all tracks score 2.55 → A3 · Hay, Mercer IPE and public plans · experience 13.2 yrs vs the A3 market range 2–5 | BD188: =IF(SUM(BM188,BN188,BO188,BP188,BQ188,BR188,BS188)=0,0,(BM188*BT188+BN188*BU188+BO188*BV188+BP188*BW188+BQ188*BX188+BR188*BY188+BS188*BZ188)/SUM(BM188,BN188,BO188,BP188,BQ188,BR188,BS188)) -> 0 | BE188: =IF(LEFT(AY188,1)="X",AY188,IF(OR(AY188="B+",AY188="C+"),INDEX(LAD_PC,MAX(1,MIN(14,MATCH(AY188,LAD_PC,0)+IF(BD188>=0.5,1,IF(BD188<=-0.5,-1,0))))),INDEX(LAD_STD,MAX(1,MIN(12,MATCH(AY188,LAD_STD,0)+IF(BD188>=0.5,1,IF(BD188<=-0.5,-1,0))))))) -> A3 | BG188: =IF(BF188<>"",BF188,BE188) -> A3 | BH188: =IFERROR(CHOOSE(INDEX(B_RANK,MATCH(BG188,B_LVL,0)),"Band A","Band B","B+ · Player-Coach","Band C","C+ · Player-Coach","Band D","Band E"),"Band X · Consultant") -> Band A | BI188: =IF(BG188=AY188,"• Same",IF(INDEX(B_VAL,MATCH(BG188,B_LVL,0))>INDEX(B_VAL,MATCH(AY188,B_LVL,0)),"▲ Up","▼ Down")) -> • Same | BJ188: =IF(OR($M188="",$M188="—",$M188="Not in this file"),"",IFERROR(INDEX($BG$7:$BG$592,MATCH($M188,$D$7:$D$592,0)),"")) -> B2 | BK188: =IFERROR(IF(BJ188="","—",IF(OR(LEFT(BG188,1)="X",LEFT(BJ188,1)="X"),"—",IF(AND(LEFT(BG188,1)="E",LEFT(BJ188,1)="E"),"Exception · Band E",IF(AND(INDEX(B_VAL,MATCH(BJ188,B_LVL,0))>=7,INDEX(B_RANK,MATCH(BG188,B_LVL,0))>=INDEX(B_RANK,MATCH(BJ188,B_LVL,0))),"⚠ Same band as a head manager",IF(INDEX(B_VAL,MATCH(BG188,B_LVL,0))>=INDEX(B_VAL,MATCH(BJ188,B_LVL,0)),"⚠ At or above the manager's level","OK"))))),"—") -> OK | BM188: =IFERROR(INDEX(LMH_PTS,MATCH(Y188,LMH_KEY,0)),0) -> 9 | BN188: =IFERROR(INDEX(LMH_PTS,MATCH(Z188,LMH_KEY,0)),0) -> 3 | BO188: =IFERROR(INDEX(LMH_PTS,MATCH(AA188,LMH_KEY,0)),0) -> 3 | BP188: =IFERROR(INDEX(LMH_PTS,MATCH(AB188,LMH_KEY,0)),0) -> 1 | BQ188: =IFERROR(INDEX(LMH_PTS,MATCH(AC188,LMH_KEY,0)),0) -> 1 | BR188: =IFERROR(INDEX(LMH_PTS,MATCH(AD188,LMH_KEY,0)),0) -> 1 | BS188: =IFERROR(INDEX(LMH_PTS,MATCH(AE188,LMH_KEY,0)),0) -> 3 | BT188: =IFERROR(INDEX(LMH_STEP,MATCH(AF188,LMH_KEY,0)),0) -> 0 | BU188: =IFERROR(INDEX(LMH_STEP,MATCH(AG188,LMH_KEY,0)),0) -> 0 | BV188: =IFERROR(INDEX(LMH_STEP,MATCH(AH188,LMH_KEY,0)),0) -> 0 | BW188: =IFERROR(INDEX(LMH_STEP,MATCH(AI188,LMH_KEY,0)),0) -> 0 | BX188: =IFERROR(INDEX(LMH_STEP,MATCH(AJ188,LMH_KEY,0)),0) -> 0 | BY188: =IFERROR(INDEX(LMH_STEP,MATCH(AK188,LMH_KEY,0)),0) -> 0 | BZ188: =IFERROR(INDEX(LMH_STEP,MATCH(AL188,LMH_KEY,0)),0) -> 0 | CA188: Corporate|Administration|Senior Administration Executive|A3|A
A189: Corporate | B189: Administration | C189: 4 | D189: IRIS0020 | E189: Mangesh Kosty | F189: Executive Administration | G189: Senior Administration Executive | H189: Administration, Legal & Secretarial | I189: Administration & Facilities | J189: IC | K189: RC-001 | L189: Sujit Acharya | M189: IRIS1326 | N189: 21.7 | O189: 21.7 | P189: Undergraduate | Q189: Not in current mapping files | R189: A3 | S189: 0 of 20 | T189: Complexity: Evidence: no survey answers or KRAs on file → rating stays at the start Autonomy: Evidence: no survey answers or KRAs on file → rating stays at the start Accountability: Evidence: no survey answers or KRAs on file → rating stays at the start Leadership: Evidence: no survey answers or KRAs on file → rating stays at the start Business Impact: No … | U189: KRAs not received · manager to supply | V189: Latest rating: Not rated · manager · 9-box: Not placed · manager · Readiness: No rating data | W189: C L · Au L · Ac L · L L · BI L · Exp H · 21.7 yrs vs 2–4 yrs · Edu L · Undergraduate | X189: Open ▸ | Y189: =IFERROR(INDEX(DL_C,MATCH($CA189,DL_KEY,0)),"M") -> H | Z189: =IFERROR(INDEX(DL_Au,MATCH($CA189,DL_KEY,0)),"M") -> M | AA189: =IFERROR(INDEX(DL_Ac,MATCH($CA189,DL_KEY,0)),"M") -> M | AB189: =IFERROR(INDEX(DL_L,MATCH($CA189,DL_KEY,0)),"M") -> L | AC189: =IFERROR(INDEX(DL_BI,MATCH($CA189,DL_KEY,0)),"M") -> L | AD189: =IFERROR(INDEX(DL_Exp,MATCH($CA189,DL_KEY,0)),"M") -> L | AE189: =IFERROR(INDEX(DL_Edu,MATCH($CA189,DL_KEY,0)),"M") -> M | AF189: M | AG189: M | AH189: M | AI189: M | AJ189: M | AK189: M | AL189: M | AM189: 0.583 | AN189: 0.16 | AO189: 0.09 | AP189: 0 | AQ189: 0.063 | AR189: 0.06 | AS189: 0.04 | AT189: 2–5 | AU189: Graduate; relevant certification preferred | AV189: None · guides 1–3 juniors informally | AW189: P2 · SFIA 3 Apply | AX189: S46–S51 Korn Ferry Hay evaluations · S04, S52 Mercer IPE · S53–S57 NHS, UK NJC/PSC, GLPC, SJC, US OPM point-factor plans · S58 McKinsey skills-based hiring · S60 WEF skills-first · S61 EY India 2026 · the Experience / Education split is an IRIS rule · S32 Google, Microsoft, Amazon · S33 Infosys · S35 Accenture India · IRIS experience guide · S01 Aon Radford · S02 Pave · S08 SFIA 9 · S03 Mercer career levels | AY189: A3 | AZ189: Band A · Practitioner · Senior Associate | BA189: Model A3 from the six ratings, the market-derived weights and rules R1–R13 · then No change · already below the manager | BB189: A3 | BC189: The six ratings on the market-average weights of Band A · all tracks score 2.75 → A3 · Hay, Mercer IPE and public plans · experience 21.7 yrs vs the A3 market range 2–5 | BD189: =IF(SUM(BM189,BN189,BO189,BP189,BQ189,BR189,BS189)=0,0,(BM189*BT189+BN189*BU189+BO189*BV189+BP189*BW189+BQ189*BX189+BR189*BY189+BS189*BZ189)/SUM(BM189,BN189,BO189,BP189,BQ189,BR189,BS189)) -> 0 | BE189: =IF(LEFT(AY189,1)="X",AY189,IF(OR(AY189="B+",AY189="C+"),INDEX(LAD_PC,MAX(1,MIN(14,MATCH(AY189,LAD_PC,0)+IF(BD189>=0.5,1,IF(BD189<=-0.5,-1,0))))),INDEX(LAD_STD,MAX(1,MIN(12,MATCH(AY189,LAD_STD,0)+IF(BD189>=0.5,1,IF(BD189<=-0.5,-1,0))))))) -> A3 | BG189: =IF(BF189<>"",BF189,BE189) -> A3 | BH189: =IFERROR(CHOOSE(INDEX(B_RANK,MATCH(BG189,B_LVL,0)),"Band A","Band B","B+ · Player-Coach","Band C","C+ · Player-Coach","Band D","Band E"),"Band X · Consultant") -> Band A | BI189: =IF(BG189=AY189,"• Same",IF(INDEX(B_VAL,MATCH(BG189,B_LVL,0))>INDEX(B_VAL,MATCH(AY189,B_LVL,0)),"▲ Up","▼ Down")) -> • Same | BJ189: =IF(OR($M189="",$M189="—",$M189="Not in this file"),"",IFERROR(INDEX($BG$7:$BG$592,MATCH($M189,$D$7:$D$592,0)),"")) -> B2 | BK189: =IFERROR(IF(BJ189="","—",IF(OR(LEFT(BG189,1)="X",LEFT(BJ189,1)="X"),"—",IF(AND(LEFT(BG189,1)="E",LEFT(BJ189,1)="E"),"Exception · Band E",IF(AND(INDEX(B_VAL,MATCH(BJ189,B_LVL,0))>=7,INDEX(B_RANK,MATCH(BG189,B_LVL,0))>=INDEX(B_RANK,MATCH(BJ189,B_LVL,0))),"⚠ Same band as a head manager",IF(INDEX(B_VAL,MATCH(BG189,B_LVL,0))>=INDEX(B_VAL,MATCH(BJ189,B_LVL,0)),"⚠ At or above the manager's level","OK"))))),"—") -> OK | BM189: =IFERROR(INDEX(LMH_PTS,MATCH(Y189,LMH_KEY,0)),0) -> 9 | BN189: =IFERROR(INDEX(LMH_PTS,MATCH(Z189,LMH_KEY,0)),0) -> 3 | BO189: =IFERROR(INDEX(LMH_PTS,MATCH(AA189,LMH_KEY,0)),0) -> 3 | BP189: =IFERROR(INDEX(LMH_PTS,MATCH(AB189,LMH_KEY,0)),0) -> 1 | BQ189: =IFERROR(INDEX(LMH_PTS,MATCH(AC189,LMH_KEY,0)),0) -> 1 | BR189: =IFERROR(INDEX(LMH_PTS,MATCH(AD189,LMH_KEY,0)),0) -> 1 | BS189: =IFERROR(INDEX(LMH_PTS,MATCH(AE189,LMH_KEY,0)),0) -> 3 | BT189: =IFERROR(INDEX(LMH_STEP,MATCH(AF189,LMH_KEY,0)),0) -> 0 | BU189: =IFERROR(INDEX(LMH_STEP,MATCH(AG189,LMH_KEY,0)),0) -> 0 | BV189: =IFERROR(INDEX(LMH_STEP,MATCH(AH189,LMH_KEY,0)),0) -> 0 | BW189: =IFERROR(INDEX(LMH_STEP,MATCH(AI189,LMH_KEY,0)),0) -> 0 | BX189: =IFERROR(INDEX(LMH_STEP,MATCH(AJ189,LMH_KEY,0)),0) -> 0 | BY189: =IFERROR(INDEX(LMH_STEP,MATCH(AK189,LMH_KEY,0)),0) -> 0 | BZ189: =IFERROR(INDEX(LMH_STEP,MATCH(AL189,LMH_KEY,0)),0) -> 0 | CA189: Corporate|Administration|Senior Administration Executive|A3|A
A190: Corporate | B190: Administration | C190: 4 | D190: IRIS0021 | E190: Rajesh Khurambe | F190: Executive Administration | G190: Senior Administration Executive | H190: Administration, Legal & Secretarial | I190: Administration & Facilities | J190: IC | K190: RC-001 | L190: Sujit Acharya | M190: IRIS1326 | N190: 21.7 | O190: 21.7 | P190: Undergraduate | Q190: Not in current mapping files | R190: A3 | S190: 0 of 20 | T190: Complexity: Evidence: no survey answers or KRAs on file → rating stays at the start Autonomy: Evidence: no survey answers or KRAs on file → rating stays at the start Accountability: Evidence: no survey answers or KRAs on file → rating stays at the start Leadership: Evidence: no survey answers or KRAs on file → rating stays at the start Business Impact: No … | U190: KRAs not received · manager to supply | V190: Latest rating: Not rated · manager · 9-box: Not placed · manager · Readiness: No rating data | W190: C L · Au L · Ac L · L L · BI L · Exp H · 21.7 yrs vs 2–4 yrs · Edu L · Undergraduate | X190: Open ▸ | Y190: =IFERROR(INDEX(DL_C,MATCH($CA190,DL_KEY,0)),"M") -> H | Z190: =IFERROR(INDEX(DL_Au,MATCH($CA190,DL_KEY,0)),"M") -> M | AA190: =IFERROR(INDEX(DL_Ac,MATCH($CA190,DL_KEY,0)),"M") -> M | AB190: =IFERROR(INDEX(DL_L,MATCH($CA190,DL_KEY,0)),"M") -> L | AC190: =IFERROR(INDEX(DL_BI,MATCH($CA190,DL_KEY,0)),"M") -> L | AD190: =IFERROR(INDEX(DL_Exp,MATCH($CA190,DL_KEY,0)),"M") -> L | AE190: =IFERROR(INDEX(DL_Edu,MATCH($CA190,DL_KEY,0)),"M") -> M | AF190: M | AG190: M | AH190: M | AI190: M | AJ190: M | AK190: M | AL190: M | AM190: 0.583 | AN190: 0.16 | AO190: 0.09 | AP190: 0 | AQ190: 0.063 | AR190: 0.06 | AS190: 0.04 | AT190: 2–5 | AU190: Graduate; relevant certification preferred | AV190: None · guides 1–3 juniors informally | AW190: P2 · SFIA 3 Apply | AX190: S46–S51 Korn Ferry Hay evaluations · S04, S52 Mercer IPE · S53–S57 NHS, UK NJC/PSC, GLPC, SJC, US OPM point-factor plans · S58 McKinsey skills-based hiring · S60 WEF skills-first · S61 EY India 2026 · the Experience / Education split is an IRIS rule · S32 Google, Microsoft, Amazon · S33 Infosys · S35 Accenture India · IRIS experience guide · S01 Aon Radford · S02 Pave · S08 SFIA 9 · S03 Mercer career levels | AY190: A3 | AZ190: Band A · Practitioner · Senior Associate | BA190: Model A3 from the six ratings, the market-derived weights and rules R1–R13 · then No change · already below the manager | BB190: A3 | BC190: The six ratings on the market-average weights of Band A · all tracks score 2.75 → A3 · Hay, Mercer IPE and public plans · experience 21.7 yrs vs the A3 market range 2–5 | BD190: =IF(SUM(BM190,BN190,BO190,BP190,BQ190,BR190,BS190)=0,0,(BM190*BT190+BN190*BU190+BO190*BV190+BP190*BW190+BQ190*BX190+BR190*BY190+BS190*BZ190)/SUM(BM190,BN190,BO190,BP190,BQ190,BR190,BS190)) -> 0 | BE190: =IF(LEFT(AY190,1)="X",AY190,IF(OR(AY190="B+",AY190="C+"),INDEX(LAD_PC,MAX(1,MIN(14,MATCH(AY190,LAD_PC,0)+IF(BD190>=0.5,1,IF(BD190<=-0.5,-1,0))))),INDEX(LAD_STD,MAX(1,MIN(12,MATCH(AY190,LAD_STD,0)+IF(BD190>=0.5,1,IF(BD190<=-0.5,-1,0))))))) -> A3 | BG190: =IF(BF190<>"",BF190,BE190) -> A3 | BH190: =IFERROR(CHOOSE(INDEX(B_RANK,MATCH(BG190,B_LVL,0)),"Band A","Band B","B+ · Player-Coach","Band C","C+ · Player-Coach","Band D","Band E"),"Band X · Consultant") -> Band A | BI190: =IF(BG190=AY190,"• Same",IF(INDEX(B_VAL,MATCH(BG190,B_LVL,0))>INDEX(B_VAL,MATCH(AY190,B_LVL,0)),"▲ Up","▼ Down")) -> • Same | BJ190: =IF(OR($M190="",$M190="—",$M190="Not in this file"),"",IFERROR(INDEX($BG$7:$BG$592,MATCH($M190,$D$7:$D$592,0)),"")) -> B2 | BK190: =IFERROR(IF(BJ190="","—",IF(OR(LEFT(BG190,1)="X",LEFT(BJ190,1)="X"),"—",IF(AND(LEFT(BG190,1)="E",LEFT(BJ190,1)="E"),"Exception · Band E",IF(AND(INDEX(B_VAL,MATCH(BJ190,B_LVL,0))>=7,INDEX(B_RANK,MATCH(BG190,B_LVL,0))>=INDEX(B_RANK,MATCH(BJ190,B_LVL,0))),"⚠ Same band as a head manager",IF(INDEX(B_VAL,MATCH(BG190,B_LVL,0))>=INDEX(B_VAL,MATCH(BJ190,B_LVL,0)),"⚠ At or above the manager's level","OK"))))),"—") -> OK | BM190: =IFERROR(INDEX(LMH_PTS,MATCH(Y190,LMH_KEY,0)),0) -> 9 | BN190: =IFERROR(INDEX(LMH_PTS,MATCH(Z190,LMH_KEY,0)),0) -> 3 | BO190: =IFERROR(INDEX(LMH_PTS,MATCH(AA190,LMH_KEY,0)),0) -> 3 | BP190: =IFERROR(INDEX(LMH_PTS,MATCH(AB190,LMH_KEY,0)),0) -> 1 | BQ190: =IFERROR(INDEX(LMH_PTS,MATCH(AC190,LMH_KEY,0)),0) -> 1 | BR190: =IFERROR(INDEX(LMH_PTS,MATCH(AD190,LMH_KEY,0)),0) -> 1 | BS190: =IFERROR(INDEX(LMH_PTS,MATCH(AE190,LMH_KEY,0)),0) -> 3 | BT190: =IFERROR(INDEX(LMH_STEP,MATCH(AF190,LMH_KEY,0)),0) -> 0 | BU190: =IFERROR(INDEX(LMH_STEP,MATCH(AG190,LMH_KEY,0)),0) -> 0 | BV190: =IFERROR(INDEX(LMH_STEP,MATCH(AH190,LMH_KEY,0)),0) -> 0 | BW190: =IFERROR(INDEX(LMH_STEP,MATCH(AI190,LMH_KEY,0)),0) -> 0 | BX190: =IFERROR(INDEX(LMH_STEP,MATCH(AJ190,LMH_KEY,0)),0) -> 0 | BY190: =IFERROR(INDEX(LMH_STEP,MATCH(AK190,LMH_KEY,0)),0) -> 0 | BZ190: =IFERROR(INDEX(LMH_STEP,MATCH(AL190,LMH_KEY,0)),0) -> 0 | CA190: Corporate|Administration|Senior Administration Executive|A3|A
A191: Corporate | B191: Administration | C191: 4 | D191: IRIS1008 | E191: Sunil Pawar | F191: Executive Administration | G191: Senior Administration Executive | H191: Administration, Legal & Secretarial | I191: Administration & Facilities | J191: IC | K191: RC-001 | L191: Sujit Acharya | M191: IRIS1326 | N191: 14.9 | O191: 14.9 | P191: Undergraduate | Q191: Not in current mapping files | R191: A3 | S191: 0 of 20 | T191: Complexity: Evidence: no survey answers or KRAs on file → rating stays at the start Autonomy: Evidence: no survey answers or KRAs on file → rating stays at the start Accountability: Evidence: no survey answers or KRAs on file → rating stays at the start Leadership: Evidence: no survey answers or KRAs on file → rating stays at the start Business Impact: No … | U191: KRAs not received · manager to supply | V191: Latest rating: Not rated · manager · 9-box: Not placed · manager · Readiness: No rating data | W191: C L · Au L · Ac L · L L · BI L · Exp H · 14.9 yrs vs 2–4 yrs · Edu L · Undergraduate | X191: Open ▸ | Y191: =IFERROR(INDEX(DL_C,MATCH($CA191,DL_KEY,0)),"M") -> H | Z191: =IFERROR(INDEX(DL_Au,MATCH($CA191,DL_KEY,0)),"M") -> M | AA191: =IFERROR(INDEX(DL_Ac,MATCH($CA191,DL_KEY,0)),"M") -> M | AB191: =IFERROR(INDEX(DL_L,MATCH($CA191,DL_KEY,0)),"M") -> L | AC191: =IFERROR(INDEX(DL_BI,MATCH($CA191,DL_KEY,0)),"M") -> L | AD191: =IFERROR(INDEX(DL_Exp,MATCH($CA191,DL_KEY,0)),"M") -> L | AE191: =IFERROR(INDEX(DL_Edu,MATCH($CA191,DL_KEY,0)),"M") -> M | AF191: M | AG191: M | AH191: M | AI191: M | AJ191: M | AK191: M | AL191: M | AM191: 0.583 | AN191: 0.16 | AO191: 0.09 | AP191: 0 | AQ191: 0.063 | AR191: 0.06 | AS191: 0.04 | AT191: 2–5 | AU191: Graduate; relevant certification preferred | AV191: None · guides 1–3 juniors informally | AW191: P2 · SFIA 3 Apply | AX191: S46–S51 Korn Ferry Hay evaluations · S04, S52 Mercer IPE · S53–S57 NHS, UK NJC/PSC, GLPC, SJC, US OPM point-factor plans · S58 McKinsey skills-based hiring · S60 WEF skills-first · S61 EY India 2026 · the Experience / Education split is an IRIS rule · S32 Google, Microsoft, Amazon · S33 Infosys · S35 Accenture India · IRIS experience guide · S01 Aon Radford · S02 Pave · S08 SFIA 9 · S03 Mercer career levels | AY191: A3 | AZ191: Band A · Practitioner · Senior Associate | BA191: Model A3 from the six ratings, the market-derived weights and rules R1–R13 · then No change · already below the manager | BB191: A3 | BC191: The six ratings on the market-average weights of Band A · all tracks score 2.55 → A3 · Hay, Mercer IPE and public plans · experience 14.9 yrs vs the A3 market range 2–5 | BD191: =IF(SUM(BM191,BN191,BO191,BP191,BQ191,BR191,BS191)=0,0,(BM191*BT191+BN191*BU191+BO191*BV191+BP191*BW191+BQ191*BX191+BR191*BY191+BS191*BZ191)/SUM(BM191,BN191,BO191,BP191,BQ191,BR191,BS191)) -> 0 | BE191: =IF(LEFT(AY191,1)="X",AY191,IF(OR(AY191="B+",AY191="C+"),INDEX(LAD_PC,MAX(1,MIN(14,MATCH(AY191,LAD_PC,0)+IF(BD191>=0.5,1,IF(BD191<=-0.5,-1,0))))),INDEX(LAD_STD,MAX(1,MIN(12,MATCH(AY191,LAD_STD,0)+IF(BD191>=0.5,1,IF(BD191<=-0.5,-1,0))))))) -> A3 | BG191: =IF(BF191<>"",BF191,BE191) -> A3 | BH191: =IFERROR(CHOOSE(INDEX(B_RANK,MATCH(BG191,B_LVL,0)),"Band A","Band B","B+ · Player-Coach","Band C","C+ · Player-Coach","Band D","Band E"),"Band X · Consultant") -> Band A | BI191: =IF(BG191=AY191,"• Same",IF(INDEX(B_VAL,MATCH(BG191,B_LVL,0))>INDEX(B_VAL,MATCH(AY191,B_LVL,0)),"▲ Up","▼ Down")) -> • Same | BJ191: =IF(OR($M191="",$M191="—",$M191="Not in this file"),"",IFERROR(INDEX($BG$7:$BG$592,MATCH($M191,$D$7:$D$592,0)),"")) -> B2 | BK191: =IFERROR(IF(BJ191="","—",IF(OR(LEFT(BG191,1)="X",LEFT(BJ191,1)="X"),"—",IF(AND(LEFT(BG191,1)="E",LEFT(BJ191,1)="E"),"Exception · Band E",IF(AND(INDEX(B_VAL,MATCH(BJ191,B_LVL,0))>=7,INDEX(B_RANK,MATCH(BG191,B_LVL,0))>=INDEX(B_RANK,MATCH(BJ191,B_LVL,0))),"⚠ Same band as a head manager",IF(INDEX(B_VAL,MATCH(BG191,B_LVL,0))>=INDEX(B_VAL,MATCH(BJ191,B_LVL,0)),"⚠ At or above the manager's level","OK"))))),"—") -> OK | BM191: =IFERROR(INDEX(LMH_PTS,MATCH(Y191,LMH_KEY,0)),0) -> 9 | BN191: =IFERROR(INDEX(LMH_PTS,MATCH(Z191,LMH_KEY,0)),0) -> 3 | BO191: =IFERROR(INDEX(LMH_PTS,MATCH(AA191,LMH_KEY,0)),0) -> 3 | BP191: =IFERROR(INDEX(LMH_PTS,MATCH(AB191,LMH_KEY,0)),0) -> 1 | BQ191: =IFERROR(INDEX(LMH_PTS,MATCH(AC191,LMH_KEY,0)),0) -> 1 | BR191: =IFERROR(INDEX(LMH_PTS,MATCH(AD191,LMH_KEY,0)),0) -> 1 | BS191: =IFERROR(INDEX(LMH_PTS,MATCH(AE191,LMH_KEY,0)),0) -> 3 | BT191: =IFERROR(INDEX(LMH_STEP,MATCH(AF191,LMH_KEY,0)),0) -> 0 | BU191: =IFERROR(INDEX(LMH_STEP,MATCH(AG191,LMH_KEY,0)),0) -> 0 | BV191: =IFERROR(INDEX(LMH_STEP,MATCH(AH191,LMH_KEY,0)),0) -> 0 | BW191: =IFERROR(INDEX(LMH_STEP,MATCH(AI191,LMH_KEY,0)),0) -> 0 | BX191: =IFERROR(INDEX(LMH_STEP,MATCH(AJ191,LMH_KEY,0)),0) -> 0 | BY191: =IFERROR(INDEX(LMH_STEP,MATCH(AK191,LMH_KEY,0)),0) -> 0 | BZ191: =IFERROR(INDEX(LMH_STEP,MATCH(AL191,LMH_KEY,0)),0) -> 0 | CA191: Corporate|Administration|Senior Administration Executive|A3|A
A192: Corporate | B192: Administration | C192: 4 | D192: IRISC291 | E192: Ganesh Prabhakar Amrutsagar | F192: Consultant | G192: Associate Consultant – Administration & Facilities | H192: Administration, Legal & Secretarial | I192: Administration & Facilities | J192: Consultant | K192: RC-003 | L192: Sujit Acharya | M192: IRIS1326 | N192: 2.6 | O192: 2.6 | P192: Undergraduate | Q192: — | R192: X1 | S192: 0 of 20 | T192: No survey response on file | U192: KRAs not received · manager to supply | V192: Latest rating: Not rated · manager · Readiness: n/a · consultant | W192: Consultant · outside the ladder | X192: Open ▸ | AW192: — | AX192: S46–S51 Korn Ferry Hay evaluations · S04, S52 Mercer IPE · S53–S57 NHS, UK NJC/PSC, GLPC, SJC, US OPM point-factor plans · S58 McKinsey skills-based hiring · S60 WEF skills-first · S61 EY India 2026 · the Experience / Education split is an IRIS rule · S32 Google, Microsoft, Amazon · S33 Infosys · S35 Accenture India · IRIS experience guide · S01 Aon Radford · S02 Pave · S08 SFIA 9 · S03 Mercer career levels | AY192: X1 | AZ192: Band X · Consultant · | BA192: Model X1 from the six ratings, the market-derived weights and rules R1–R13 · then Consultant · outside the ladder | BC192: Consultant · outside the ladder | BD192: =IF(SUM(BM192,BN192,BO192,BP192,BQ192,BR192,BS192)=0,0,(BM192*BT192+BN192*BU192+BO192*BV192+BP192*BW192+BQ192*BX192+BR192*BY192+BS192*BZ192)/SUM(BM192,BN192,BO192,BP192,BQ192,BR192,BS192)) -> 0 | BE192: =IF(LEFT(AY192,1)="X",AY192,IF(OR(AY192="B+",AY192="C+"),INDEX(LAD_PC,MAX(1,MIN(14,MATCH(AY192,LAD_PC,0)+IF(BD192>=0.5,1,IF(BD192<=-0.5,-1,0))))),INDEX(LAD_STD,MAX(1,MIN(12,MATCH(AY192,LAD_STD,0)+IF(BD192>=0.5,1,IF(BD192<=-0.5,-1,0))))))) -> X1 | BG192: =IF(BF192<>"",BF192,BE192) -> X1 | BH192: =IFERROR(CHOOSE(INDEX(B_RANK,MATCH(BG192,B_LVL,0)),"Band A","Band B","B+ · Player-Coach","Band C","C+ · Player-Coach","Band D","Band E"),"Band X · Consultant") -> Band X · Consultant | BI192: =IF(BG192=AY192,"• Same",IF(INDEX(B_VAL,MATCH(BG192,B_LVL,0))>INDEX(B_VAL,MATCH(AY192,B_LVL,0)),"▲ Up","▼ Down")) -> • Same | BJ192: =IF(OR($M192="",$M192="—",$M192="Not in this file"),"",IFERROR(INDEX($BG$7:$BG$592,MATCH($M192,$D$7:$D$592,0)),"")) -> B2 | BK192: =IFERROR(IF(BJ192="","—",IF(OR(LEFT(BG192,1)="X",LEFT(BJ192,1)="X"),"—",IF(AND(LEFT(BG192,1)="E",LEFT(BJ192,1)="E"),"Exception · Band E",IF(AND(INDEX(B_VAL,MATCH(BJ192,B_LVL,0))>=7,INDEX(B_RANK,MATCH(BG192,B_LVL,0))>=INDEX(B_RANK,MATCH(BJ192,B_LVL,0))),"⚠ Same band as a head manager",IF(INDEX(B_VAL,MATCH(BG192,B_LVL,0))>=INDEX(B_VAL,MATCH(BJ192,B_LVL,0)),"⚠ At or above the manager's level","OK"))))),"—") -> — | BM192: =IFERROR(INDEX(LMH_PTS,MATCH(Y192,LMH_KEY,0)),0) -> 0 | BN192: =IFERROR(INDEX(LMH_PTS,MATCH(Z192,LMH_KEY,0)),0) -> 0 | BO192: =IFERROR(INDEX(LMH_PTS,MATCH(AA192,LMH_KEY,0)),0) -> 0 | BP192: =IFERROR(INDEX(LMH_PTS,MATCH(AB192,LMH_KEY,0)),0) -> 0 | BQ192: =IFERROR(INDEX(LMH_PTS,MATCH(AC192,LMH_KEY,0)),0) -> 0 | BR192: =IFERROR(INDEX(LMH_PTS,MATCH(AD192,LMH_KEY,0)),0) -> 0 | BS192: =IFERROR(INDEX(LMH_PTS,MATCH(AE192,LMH_KEY,0)),0) -> 0 | BT192: =IFERROR(INDEX(LMH_STEP,MATCH(AF192,LMH_KEY,0)),0) -> 0 | BU192: =IFERROR(INDEX(LMH_STEP,MATCH(AG192,LMH_KEY,0)),0) -> 0 | BV192: =IFERROR(INDEX(LMH_STEP,MATCH(AH192,LMH_KEY,0)),0) -> 0 | BW192: =IFERROR(INDEX(LMH_STEP,MATCH(AI192,LMH_KEY,0)),0) -> 0 | BX192: =IFERROR(INDEX(LMH_STEP,MATCH(AJ192,LMH_KEY,0)),0) -> 0 | BY192: =IFERROR(INDEX(LMH_STEP,MATCH(AK192,LMH_KEY,0)),0) -> 0 | BZ192: =IFERROR(INDEX(LMH_STEP,MATCH(AL192,LMH_KEY,0)),0) -> 0 | CA192: Corporate|Administration|Associate Consultant – Administration & Facilities|X1|X
A193: iFile | B193: Sales | C193: 1 | D193: IRIS0012 | E193: Shailesh Gupta | F193: Business Head – SupTech & Bank-RegTech | G193: Business Head – SupTech & Bank-RegTech | H193: Executive Leadership | I193: Business Head | J193: People Manager | K193: RC-EL-BH-D2 | L193: Balachandran K | M193: IRIS0001 | N193: 22 | O193: 22 | P193: MBA | Q193: Not in current mapping files | R193: D2 | S193: 0 of 20 | T193: Complexity: Evidence: no survey answers or KRAs on file → rating stays at the start Autonomy: Evidence: no survey answers or KRAs on file → rating stays at the start Accountability: Evidence: no survey answers or KRAs on file → rating stays at the start Leadership: Evidence: no survey answers or KRAs on file → rating stays at the start Business Impact: No … | U193: KRAs not received · manager to supply | V193: Latest rating: Not rated · manager · 9-box: Not placed · manager · Readiness: No rating data | W193: C L · Au L · Ac L · L L · BI L · Exp M · 22 yrs vs 18–24 yrs · Edu M · MBA | X193: Open ▸ | Y193: =IFERROR(INDEX(DL_C,MATCH($CA193,DL_KEY,0)),"M") -> H | Z193: =IFERROR(INDEX(DL_Au,MATCH($CA193,DL_KEY,0)),"M") -> M | AA193: =IFERROR(INDEX(DL_Ac,MATCH($CA193,DL_KEY,0)),"M") -> M | AB193: =IFERROR(INDEX(DL_L,MATCH($CA193,DL_KEY,0)),"M") -> M | AC193: =IFERROR(INDEX(DL_BI,MATCH($CA193,DL_KEY,0)),"M") -> L | AD193: =IFERROR(INDEX(DL_Exp,MATCH($CA193,DL_KEY,0)),"M") -> L | AE193: =IFERROR(INDEX(DL_Edu,MATCH($CA193,DL_KEY,0)),"M") -> L | AF193: M | AG193: M | AH193: M | AI193: M | AJ193: M | AK193: M | AL193: M | AM193: 0.363 | AN193: 0.19 | AO193: 0.113 | AP193: 0.2 | AQ193: 0.087 | AR193: 0.04 | AS193: 0.01 | AT193: 18–24 yrs | AU193: Postgraduate / professional qualification preferred | AV193: 5–8 AVPs / heads | AW193: E3–E4 · SFIA 7 Set strategy | AX193: S46–S51 Korn Ferry Hay evaluations · S04, S52 Mercer IPE · S53–S57 NHS, UK NJC/PSC, GLPC, SJC, US OPM point-factor plans · S58 McKinsey skills-based hiring · S60 WEF skills-first · S61 EY India 2026 · the Experience / Education split is an IRIS rule · S32 Google, Microsoft, Amazon · S33 Infosys · S35 Accenture India · IRIS experience guide · S01 Aon Radford · S02 Pave · S08 SFIA 9 · S03 Mercer career levels | AY193: D2 | AZ193: Band D · Business leadership · Senior Vice President / Business Head | BA193: Model D2 from the six ratings, the market-derived weights and rules R1–R13 · then No change · already below the manager | BB193: D1 | BC193: The six ratings on the market-average weights of Bands D–E · Leadership score 9.10 → D1 · Hay, Mercer IPE and public plans · experience 22 yrs vs the D1 market range 15–20 yrs | BD193: =IF(SUM(BM193,BN193,BO193,BP193,BQ193,BR193,BS193)=0,0,(BM193*BT193+BN193*BU193+BO193*BV193+BP193*BW193+BQ193*BX193+BR193*BY193+BS193*BZ193)/SUM(BM193,BN193,BO193,BP193,BQ193,BR193,BS193)) -> 0 | BE193: =IF(LEFT(AY193,1)="X",AY193,IF(OR(AY193="B+",AY193="C+"),INDEX(LAD_PC,MAX(1,MIN(14,MATCH(AY193,LAD_PC,0)+IF(BD193>=0.5,1,IF(BD193<=-0.5,-1,0))))),INDEX(LAD_STD,MAX(1,MIN(12,MATCH(AY193,LAD_STD,0)+IF(BD193>=0.5,1,IF(BD193<=-0.5,-1,0))))))) -> D2 | BG193: =IF(BF193<>"",BF193,BE193) -> D2 | BH193: =IFERROR(CHOOSE(INDEX(B_RANK,MATCH(BG193,B_LVL,0)),"Band A","Band B","B+ · Player-Coach","Band C","C+ · Player-Coach","Band D","Band E"),"Band X · Consultant") -> Band D | BI193: =IF(BG193=AY193,"• Same",IF(INDEX(B_VAL,MATCH(BG193,B_LVL,0))>INDEX(B_VAL,MATCH(AY193,B_LVL,0)),"▲ Up","▼ Down")) -> • Same | BJ193: =IF(OR($M193="",$M193="—",$M193="Not in this file"),"",IFERROR(INDEX($BG$7:$BG$592,MATCH($M193,$D$7:$D$592,0)),"")) -> E2 | BK193: =IFERROR(IF(BJ193="","—",IF(OR(LEFT(BG193,1)="X",LEFT(BJ193,1)="X"),"—",IF(AND(LEFT(BG193,1)="E",LEFT(BJ193,1)="E"),"Exception · Band E",IF(AND(INDEX(B_VAL,MATCH(BJ193,B_LVL,0))>=7,INDEX(B_RANK,MATCH(BG193,B_LVL,0))>=INDEX(B_RANK,MATCH(BJ193,B_LVL,0))),"⚠ Same band as a head manager",IF(INDEX(B_VAL,MATCH(BG193,B_LVL,0))>=INDEX(B_VAL,MATCH(BJ193,B_LVL,0)),"⚠ At or above the manager's level","OK"))))),"—") -> OK | BM193: =IFERROR(INDEX(LMH_PTS,MATCH(Y193,LMH_KEY,0)),0) -> 9 | BN193: =IFERROR(INDEX(LMH_PTS,MATCH(Z193,LMH_KEY,0)),0) -> 3 | BO193: =IFERROR(INDEX(LMH_PTS,MATCH(AA193,LMH_KEY,0)),0) -> 3 | BP193: =IFERROR(INDEX(LMH_PTS,MATCH(AB193,LMH_KEY,0)),0) -> 3 | BQ193: =IFERROR(INDEX(LMH_PTS,MATCH(AC193,LMH_KEY,0)),0) -> 1 | BR193: =IFERROR(INDEX(LMH_PTS,MATCH(AD193,LMH_KEY,0)),0) -> 1 | BS193: =IFERROR(INDEX(LMH_PTS,MATCH(AE193,LMH_KEY,0)),0) -> 1 | BT193: =IFERROR(INDEX(LMH_STEP,MATCH(AF193,LMH_KEY,0)),0) -> 0 | BU193: =IFERROR(INDEX(LMH_STEP,MATCH(AG193,LMH_KEY,0)),0) -> 0 | BV193: =IFERROR(INDEX(LMH_STEP,MATCH(AH193,LMH_KEY,0)),0) -> 0 | BW193: =IFERROR(INDEX(LMH_STEP,MATCH(AI193,LMH_KEY,0)),0) -> 0 | BX193: =IFERROR(INDEX(LMH_STEP,MATCH(AJ193,LMH_KEY,0)),0) -> 0 | BY193: =IFERROR(INDEX(LMH_STEP,MATCH(AK193,LMH_KEY,0)),0) -> 0 | BZ193: =IFERROR(INDEX(LMH_STEP,MATCH(AL193,LMH_KEY,0)),0) -> 0 | CA193: iFile|Sales|Business Head – SupTech & Bank-RegTech|D2|DE
A194: iDEAL | B194: iDEAL Business Head | C194: 2 | D194: IRIS1224 | E194: Hemant Karale | F194: Business Head IRIS iDEAL | G194: Business Head – iDEAL | H194: Executive Leadership | I194: Business Head | J194: People Manager | K194: RC-EL-BH-D1 | L194: Shailesh Gupta | M194: IRIS0012 | N194: 17.6 | O194: 14.2 | P194: MBA | Q194: L7 – Head / Sr Director | R194: D1 | S194: 0 of 20 | T194: Complexity: Evidence reads like C2: KRA only: business revenue, foreign-market partner onboarding, AI product launches, defect reduction → moved down 0.5 Autonomy: Evidence reads like C2: KRA only: commits business revenue, partner onboarding and product launches; no decisions stated directly → moved down 0.5 Accountability: Evidence reads like D1: KRA: … | U194: Received · self · KRAs not received · manager to supply | V194: Latest rating: Not rated · manager · 9-box: Not placed · manager · Readiness: No rating data | W194: C M · Au M · Ac H · L M · BI H · Exp H · 17.6 yrs vs 12–17 yrs · Edu M · MBA | X194: Open ▸ | Y194: =IFERROR(INDEX(DL_C,MATCH($CA194,DL_KEY,0)),"M") -> H | Z194: =IFERROR(INDEX(DL_Au,MATCH($CA194,DL_KEY,0)),"M") -> M | AA194: =IFERROR(INDEX(DL_Ac,MATCH($CA194,DL_KEY,0)),"M") -> M | AB194: =IFERROR(INDEX(DL_L,MATCH($CA194,DL_KEY,0)),"M") -> M | AC194: =IFERROR(INDEX(DL_BI,MATCH($CA194,DL_KEY,0)),"M") -> L | AD194: =IFERROR(INDEX(DL_Exp,MATCH($CA194,DL_KEY,0)),"M") -> L | AE194: =IFERROR(INDEX(DL_Edu,MATCH($CA194,DL_KEY,0)),"M") -> L | AF194: M | AG194: M | AH194: M | AI194: M | AJ194: M | AK194: M | AL194: M | AM194: 0.433 | AN194: 0.18 | AO194: 0.107 | AP194: 0.15 | AQ194: 0.08 | AR194: 0.04 | AS194: 0.01 | AT194: 12–17 yrs | AU194: Postgraduate / professional qualification preferred | AV194: 5–8 managers / associate heads | AW194: P7 / M6 · SFIA 6 Initiate, influence | AX194: S46–S51 Korn Ferry Hay evaluations · S04, S52 Mercer IPE · S53–S57 NHS, UK NJC/PSC, GLPC, SJC, US OPM point-factor plans · S58 McKinsey skills-based hiring · S60 WEF skills-first · S61 EY India 2026 · the Experience / Education split is an IRIS rule · S32 Google, Microsoft, Amazon · S33 Infosys · S35 Accenture India · IRIS experience guide · S01 Aon Radford · S02 Pave · S08 SFIA 9 · S03 Mercer career levels | AY194: C2 | AZ194: Band C · Principal / Head · Head of Function | BA194: Model D1 from the six ratings, the market-derived weights and rules R1–R13 · then Band rule: manager D2 is a head in Band D · Business leadership; a reportee sits in a lower band · D1 → C2 · move down · pay and title protected for one cycle | BB194: D1 | BC194: The six ratings on the market-average weights of Band C · Head / manager score 8.64 → D1 · Hay, Mercer IPE and public plans · experience 17.6 yrs vs the D1 market range 15–20 yrs | BD194: =IF(SUM(BM194,BN194,BO194,BP194,BQ194,BR194,BS194)=0,0,(BM194*BT194+BN194*BU194+BO194*BV194+BP194*BW194+BQ194*BX194+BR194*BY194+BS194*BZ194)/SUM(BM194,BN194,BO194,BP194,BQ194,BR194,BS194)) -> 0 | BE194: =IF(LEFT(AY194,1)="X",AY194,IF(OR(AY194="B+",AY194="C+"),INDEX(LAD_PC,MAX(1,MIN(14,MATCH(AY194,LAD_PC,0)+IF(BD194>=0.5,1,IF(BD194<=-0.5,-1,0))))),INDEX(LAD_STD,MAX(1,MIN(12,MATCH(AY194,LAD_STD,0)+IF(BD194>=0.5,1,IF(BD194<=-0.5,-1,0))))))) -> C2 | BG194: =IF(BF194<>"",BF194,BE194) -> C2 | BH194: =IFERROR(CHOOSE(INDEX(B_RANK,MATCH(BG194,B_LVL,0)),"Band A","Band B","B+ · Player-Coach","Band C","C+ · Player-Coach","Band D","Band E"),"Band X · Consultant") -> Band C | BI194: =IF(BG194=AY194,"• Same",IF(INDEX(B_VAL,MATCH(BG194,B_LVL,0))>INDEX(B_VAL,MATCH(AY194,B_LVL,0)),"▲ Up","▼ Down")) -> • Same | BJ194: =IF(OR($M194="",$M194="—",$M194="Not in this file"),"",IFERROR(INDEX($BG$7:$BG$592,MATCH($M194,$D$7:$D$592,0)),"")) -> D2 | BK194: =IFERROR(IF(BJ194="","—",IF(OR(LEFT(BG194,1)="X",LEFT(BJ194,1)="X"),"—",IF(AND(LEFT(BG194,1)="E",LEFT(BJ194,1)="E"),"Exception · Band E",IF(AND(INDEX(B_VAL,MATCH(BJ194,B_LVL,0))>=7,INDEX(B_RANK,MATCH(BG194,B_LVL,0))>=INDEX(B_RANK,MATCH(BJ194,B_LVL,0))),"⚠ Same band as a head manager",IF(INDEX(B_VAL,MATCH(BG194,B_LVL,0))>=INDEX(B_VAL,MATCH(BJ194,B_LVL,0)),"⚠ At or above the manager's level","OK"))))),"—") -> OK | BM194: =IFERROR(INDEX(LMH_PTS,MATCH(Y194,LMH_KEY,0)),0) -> 9 | BN194: =IFERROR(INDEX(LMH_PTS,MATCH(Z194,LMH_KEY,0)),0) -> 3 | BO194: =IFERROR(INDEX(LMH_PTS,MATCH(AA194,LMH_KEY,0)),0) -> 3 | BP194: =IFERROR(INDEX(LMH_PTS,MATCH(AB194,LMH_KEY,0)),0) -> 3 | BQ194: =IFERROR(INDEX(LMH_PTS,MATCH(AC194,LMH_KEY,0)),0) -> 1 | BR194: =IFERROR(INDEX(LMH_PTS,MATCH(AD194,LMH_KEY,0)),0) -> 1 | BS194: =IFERROR(INDEX(LMH_PTS,MATCH(AE194,LMH_KEY,0)),0) -> 1 | BT194: =IFERROR(INDEX(LMH_STEP,MATCH(AF194,LMH_KEY,0)),0) -> 0 | BU194: =IFERROR(INDEX(LMH_STEP,MATCH(AG194,LMH_KEY,0)),0) -> 0 | BV194: =IFERROR(INDEX(LMH_STEP,MATCH(AH194,LMH_KEY,0)),0) -> 0 | BW194: =IFERROR(INDEX(LMH_STEP,MATCH(AI194,LMH_KEY,0)),0) -> 0 | BX194: =IFERROR(INDEX(LMH_STEP,MATCH(AJ194,LMH_KEY,0)),0) -> 0 | BY194: =IFERROR(INDEX(LMH_STEP,MATCH(AK194,LMH_KEY,0)),0) -> 0 | BZ194: =IFERROR(INDEX(LMH_STEP,MATCH(AL194,LMH_KEY,0)),0) -> 0 | CA194: iDEAL|iDEAL Business Head|Business Head – iDEAL|C2|C-M
A195: iDEAL | B195: Technology | C195: 3 | D195: IRIS0810 | E195: Jitendra Kumar | F195: Technical Architect | G195: Practice Lead – Solution & Technical Architecture · Player-Coach | H195: Engineering & Architecture | I195: Solution & Technical Architecture | J195: Player-Coach | K195: RC-056 | L195: Hemant Karale | M195: IRIS1224 | N195: 16.6 | O195: 15.2 | P195: MCA | Q195: L3 – Professional / Associate | R195: B+ | S195: 20 of 20 | T195: Complexity: Evidence reads like B2: Runs all technical aspects of a bank XBRL reporting product: requirements,.NET development, delivery, client support → moved down 1 Autonomy: Evidence reads like B2: Decides application enhancements; coordinates a nine-person team; leads client discussions → moved down 1 Accountability: Evidence reads like B2: Accountable … | U195: Received · manager annual, quarterly, self · 1. Identify and develop AI-driven functionalities. At least 2 · fully developed New AI Features to be released with the year. Encourage the AI adoption in the team to improve Software development business efficiency and operational effectiveness. 2. Successfully launch iDEAL 6.0 with enhanced functionality and … | V195: Latest rating: 4 · 9-box: Not placed · manager · Readiness: Ready in 6–12 months | W195: C M · Au M · Ac M · L L · BI M · Exp H · 16.6 yrs vs 9–14 yrs · Edu M · MCA | X195: Open ▸ | Y195: =IFERROR(INDEX(DL_C,MATCH($CA195,DL_KEY,0)),"M") -> H | Z195: =IFERROR(INDEX(DL_Au,MATCH($CA195,DL_KEY,0)),"M") -> M | AA195: =IFERROR(INDEX(DL_Ac,MATCH($CA195,DL_KEY,0)),"M") -> L | AB195: =IFERROR(INDEX(DL_L,MATCH($CA195,DL_KEY,0)),"M") -> M | AC195: =IFERROR(INDEX(DL_BI,MATCH($CA195,DL_KEY,0)),"M") -> L | AD195: =IFERROR(INDEX(DL_Exp,MATCH($CA195,DL_KEY,0)),"M") -> L | AE195: =IFERROR(INDEX(DL_Edu,MATCH($CA195,DL_KEY,0)),"M") -> L | AF195: M | AG195: M | AH195: M | AI195: M | AJ195: M | AK195: M | AL195: M | AM195: 0.44 | AN195: 0.177 | AO195: 0.103 | AP195: 0.1 | AQ195: 0.077 | AR195: 0.06 | AS195: 0.04 | AT195: 9–14 | AU195: Postgraduate or professional qualification preferred | AV195: 3–6 direct reports with ≥ 40% of time on own delivery · McKinsey player/coach 3–5; Google Tech Lead Manager | AW195: P5–P6 / M4–M5 · SFIA 5 Ensure, advise | AX195: S46–S51 Korn Ferry Hay evaluations · S04, S52 Mercer IPE · S53–S57 NHS, UK NJC/PSC, GLPC, SJC, US OPM point-factor plans · S58 McKinsey skills-based hiring · S60 WEF skills-first · S61 EY India 2026 · the Experience / Education split is an IRIS rule · S32 Google, Microsoft, Amazon · S33 Infosys · S35 Accenture India · IRIS experience guide · S01 Aon Radford · S02 Pave · S08 SFIA 9 · S03 Mercer career levels | AY195: B+ | AZ195: B+ · Player-Coach · Practice Lead · Player-Coach | BA195: Model B+ from the six ratings, the market-derived weights and rules R1–R13 · then No change · already below the manager | BB195: B3 | BC195: The six ratings on the market-average weights of B+ · Player-Coach score 6.25 → B3 · Hay, Mercer IPE and public plans · experience 16.6 yrs vs the B3 market range 8–13 | BD195: =IF(SUM(BM195,BN195,BO195,BP195,BQ195,BR195,BS195)=0,0,(BM195*BT195+BN195*BU195+BO195*BV195+BP195*BW195+BQ195*BX195+BR195*BY195+BS195*BZ195)/SUM(BM195,BN195,BO195,BP195,BQ195,BR195,BS195)) -> 0 | BE195: =IF(LEFT(AY195,1)="X",AY195,IF(OR(AY195="B+",AY195="C+"),INDEX(LAD_PC,MAX(1,MIN(14,MATCH(AY195,LAD_PC,0)+IF(BD195>=0.5,1,IF(BD195<=-0.5,-1,0))))),INDEX(LAD_STD,MAX(1,MIN(12,MATCH(AY195,LAD_STD,0)+IF(BD195>=0.5,1,IF(BD195<=-0.5,-1,0))))))) -> B+ | BG195: =IF(BF195<>"",BF195,BE195) -> B+ | BH195: =IFERROR(CHOOSE(INDEX(B_RANK,MATCH(BG195,B_LVL,0)),"Band A","Band B","B+ · Player-Coach","Band C","C+ · Player-Coach","Band D","Band E"),"Band X · Consultant") -> B+ · Player-Coach | BI195: =IF(BG195=AY195,"• Same",IF(INDEX(B_VAL,MATCH(BG195,B_LVL,0))>INDEX(B_VAL,MATCH(AY195,B_LVL,0)),"▲ Up","▼ Down")) -> • Same | BJ195: =IF(OR($M195="",$M195="—",$M195="Not in this file"),"",IFERROR(INDEX($BG$7:$BG$592,MATCH($M195,$D$7:$D$592,0)),"")) -> C2 | BK195: =IFERROR(IF(BJ195="","—",IF(OR(LEFT(BG195,1)="X",LEFT(BJ195,1)="X"),"—",IF(AND(LEFT(BG195,1)="E",LEFT(BJ195,1)="E"),"Exception · Band E",IF(AND(INDEX(B_VAL,MATCH(BJ195,B_LVL,0))>=7,INDEX(B_RANK,MATCH(BG195,B_LVL,0))>=INDEX(B_RANK,MATCH(BJ195,B_LVL,0))),"⚠ Same band as a head manager",IF(INDEX(B_VAL,MATCH(BG195,B_LVL,0))>=INDEX(B_VAL,MATCH(BJ195,B_LVL,0)),"⚠ At or above the manager's level","OK"))))),"—") -> OK | BM195: =IFERROR(INDEX(LMH_PTS,MATCH(Y195,LMH_KEY,0)),0) -> 9 | BN195: =IFERROR(INDEX(LMH_PTS,MATCH(Z195,LMH_KEY,0)),0) -> 3 | BO195: =IFERROR(INDEX(LMH_PTS,MATCH(AA195,LMH_KEY,0)),0) -> 1 | BP195: =IFERROR(INDEX(LMH_PTS,MATCH(AB195,LMH_KEY,0)),0) -> 3 | BQ195: =IFERROR(INDEX(LMH_PTS,MATCH(AC195,LMH_KEY,0)),0) -> 1 | BR195: =IFERROR(INDEX(LMH_PTS,MATCH(AD195,LMH_KEY,0)),0) -> 1 | BS195: =IFERROR(INDEX(LMH_PTS,MATCH(AE195,LMH_KEY,0)),0) -> 1 | BT195: =IFERROR(INDEX(LMH_STEP,MATCH(AF195,LMH_KEY,0)),0) -> 0 | BU195: =IFERROR(INDEX(LMH_STEP,MATCH(AG195,LMH_KEY,0)),0) -> 0 | BV195: =IFERROR(INDEX(LMH_STEP,MATCH(AH195,LMH_KEY,0)),0) -> 0 | BW195: =IFERROR(INDEX(LMH_STEP,MATCH(AI195,LMH_KEY,0)),0) -> 0 | BX195: =IFERROR(INDEX(LMH_STEP,MATCH(AJ195,LMH_KEY,0)),0) -> 0 | BY195: =IFERROR(INDEX(LMH_STEP,MATCH(AK195,LMH_KEY,0)),0) -> 0 | BZ195: =IFERROR(INDEX(LMH_STEP,MATCH(AL195,LMH_KEY,0)),0) -> 0 | CA195: iDEAL|Technology|Practice Lead – Solution & Technical Architecture · Player-Coach|B+|B+
A196: iDEAL | B196: Technology | C196: 4 | D196: IRIS1809 | E196: Jignasha Sawla | F196: Database Lead | G196: Database Specialist – POD Lead | H196: Engineering & Development | I196: Data Engineering & Database Development | J196: POD Lead | K196: RC-075 | L196: Jitendra Kumar | M196: IRIS0810 | N196: 17 | O196: 7 | P196: B.E | Q196: L5 – Lead · IC | R196: B1 | S196: 20 of 20 | T196: Complexity: Evidence reads like A3: Database development of procedures and functions, ETL tools, resolves production database issues → moved down 0.5 Autonomy: Evidence reads like A3: Independently decides how to resolve database issues → moved down 0.5 Accountability: Evidence reads like A3: Accountable for any database issues, including out-of-hours … | U196: Received · manager annual, quarterly, self · 1. Deliver end-to-end database development and project deliverables with high quality, timely execution, and adherence to business requirements. 2. Lead technical execution, coordinate with stakeholders, and mentor team members to ensure successful project delivery and knowledge sharing. 3. Ensure application … | V196: Latest rating: 2 · Potential: Low · 9-box: Performance Risk · Readiness: Performance first | W196: C M · Au M · Ac M · L L · BI M · Exp H · 17 yrs vs 4–7 yrs · Edu M · B.E | X196: Open ▸ | Y196: =IFERROR(INDEX(DL_C,MATCH($CA196,DL_KEY,0)),"M") -> H | Z196: =IFERROR(INDEX(DL_Au,MATCH($CA196,DL_KEY,0)),"M") -> M | AA196: =IFERROR(INDEX(DL_Ac,MATCH($CA196,DL_KEY,0)),"M") -> L | AB196: =IFERROR(INDEX(DL_L,MATCH($CA196,DL_KEY,0)),"M") -> L | AC196: =IFERROR(INDEX(DL_BI,MATCH($CA196,DL_KEY,0)),"M") -> L | AD196: =IFERROR(INDEX(DL_Exp,MATCH($CA196,DL_KEY,0)),"M") -> L | AE196: =IFERROR(INDEX(DL_Edu,MATCH($CA196,DL_KEY,0)),"M") -> L | AF196: M | AG196: M | AH196: M | AI196: M | AJ196: M | AK196: M | AL196: M | AM196: 0.513 | AN196: 0.173 | AO196: 0.097 | AP196: 0.05 | AQ196: 0.07 | AR196: 0.06 | AS196: 0.04 | AT196: 4–8 | AU196: Graduate + relevant qualification or certification preferred | AV196: IC: none · Team Lead: 3–5 | AW196: P3 / M2 · SFIA 4 Enable | AX196: S46–S51 Korn Ferry Hay evaluations · S04, S52 Mercer IPE · S53–S57 NHS, UK NJC/PSC, GLPC, SJC, US OPM point-factor plans · S58 McKinsey skills-based hiring · S60 WEF skills-first · S61 EY India 2026 · the Experience / Education split is an IRIS rule · S32 Google, Microsoft, Amazon · S33 Infosys · S35 Accenture India · IRIS experience guide · S01 Aon Radford · S02 Pave · S08 SFIA 9 · S03 Mercer career levels | AY196: B1 | AZ196: Band B · Specialist / Manager · Team Lead / Asst Manager | BA196: Model B1 from the six ratings, the market-derived weights and rules R1–R13 · then No change · already below the manager | BB196: B1 | BC196: The six ratings on the market-average weights of Band B · Specialist / POD Lead score 4.06 → B1 · Hay, Mercer IPE and public plans · experience 17 yrs vs the B1 market range 4–8 | BD196: =IF(SUM(BM196,BN196,BO196,BP196,BQ196,BR196,BS196)=0,0,(BM196*BT196+BN196*BU196+BO196*BV196+BP196*BW196+BQ196*BX196+BR196*BY196+BS196*BZ196)/SUM(BM196,BN196,BO196,BP196,BQ196,BR196,BS196)) -> 0 | BE196: =IF(LEFT(AY196,1)="X",AY196,IF(OR(AY196="B+",AY196="C+"),INDEX(LAD_PC,MAX(1,MIN(14,MATCH(AY196,LAD_PC,0)+IF(BD196>=0.5,1,IF(BD196<=-0.5,-1,0))))),INDEX(LAD_STD,MAX(1,MIN(12,MATCH(AY196,LAD_STD,0)+IF(BD196>=0.5,1,IF(BD196<=-0.5,-1,0))))))) -> B1 | BG196: =IF(BF196<>"",BF196,BE196) -> B1 | BH196: =IFERROR(CHOOSE(INDEX(B_RANK,MATCH(BG196,B_LVL,0)),"Band A","Band B","B+ · Player-Coach","Band C","C+ · Player-Coach","Band D","Band E"),"Band X · Consultant") -> Band B | BI196: =IF(BG196=AY196,"• Same",IF(INDEX(B_VAL,MATCH(BG196,B_LVL,0))>INDEX(B_VAL,MATCH(AY196,B_LVL,0)),"▲ Up","▼ Down")) -> • Same | BJ196: =IF(OR($M196="",$M196="—",$M196="Not in this file"),"",IFERROR(INDEX($BG$7:$BG$592,MATCH($M196,$D$7:$D$592,0)),"")) -> B+ | BK196: =IFERROR(IF(BJ196="","—",IF(OR(LEFT(BG196,1)="X",LEFT(BJ196,1)="X"),"—",IF(AND(LEFT(BG196,1)="E",LEFT(BJ196,1)="E"),"Exception · Band E",IF(AND(INDEX(B_VAL,MATCH(BJ196,B_LVL,0))>=7,INDEX(B_RANK,MATCH(BG196,B_LVL,0))>=INDEX(B_RANK,MATCH(BJ196,B_LVL,0))),"⚠ Same band as a head manager",IF(INDEX(B_VAL,MATCH(BG196,B_LVL,0))>=INDEX(B_VAL,MATCH(BJ196,B_LVL,0)),"⚠ At or above the manager's level","OK"))))),"—") -> OK | BM196: =IFERROR(INDEX(LMH_PTS,MATCH(Y196,LMH_KEY,0)),0) -> 9 | BN196: =IFERROR(INDEX(LMH_PTS,MATCH(Z196,LMH_KEY,0)),0) -> 3 | BO196: =IFERROR(INDEX(LMH_PTS,MATCH(AA196,LMH_KEY,0)),0) -> 1 | BP196: =IFERROR(INDEX(LMH_PTS,MATCH(AB196,LMH_KEY,0)),0) -> 1 | BQ196: =IFERROR(INDEX(LMH_PTS,MATCH(AC196,LMH_KEY,0)),0) -> 1 | BR196: =IFERROR(INDEX(LMH_PTS,MATCH(AD196,LMH_KEY,0)),0) -> 1 | BS196: =IFERROR(INDEX(LMH_PTS,MATCH(AE196,LMH_KEY,0)),0) -> 1 | BT196: =IFERROR(INDEX(LMH_STEP,MATCH(AF196,LMH_KEY,0)),0) -> 0 | BU196: =IFERROR(INDEX(LMH_STEP,MATCH(AG196,LMH_KEY,0)),0) -> 0 | BV196: =IFERROR(INDEX(LMH_STEP,MATCH(AH196,LMH_KEY,0)),0) -> 0 | BW196: =IFERROR(INDEX(LMH_STEP,MATCH(AI196,LMH_KEY,0)),0) -> 0 | BX196: =IFERROR(INDEX(LMH_STEP,MATCH(AJ196,LMH_KEY,0)),0) -> 0 | BY196: =IFERROR(INDEX(LMH_STEP,MATCH(AK196,LMH_KEY,0)),0) -> 0 | BZ196: =IFERROR(INDEX(LMH_STEP,MATCH(AL196,LMH_KEY,0)),0) -> 0 | CA196: iDEAL|Technology|Database Specialist – POD Lead|B1|B-IC
A197: iDEAL | B197: Technology | C197: 5 | D197: IRIS1858 | E197: Prasad Bhoite | F197: Software Engineer | G197: Senior Database Engineer | H197: Engineering & Development | I197: Data Engineering & Database Development | J197: IC | K197: RC-074 | L197: Jignasha Sawla | M197: IRIS1809 | N197: 6.9 | O197: 6.3 | P197: BCA | Q197: L3 – Professional / Associate | R197: A3 | S197: 20 of 20 | T197: Complexity: Evidence reads like A3: Data models, stored procedures, query optimisation, performance monitoring and production issue support → moved up 0.5 Autonomy: Evidence reads like A2: own survey / KRA answers · summarised by the rater; not quoted → matches the start Accountability: Evidence reads like A3: Data integrity and database performance; errors … | U197: Received · manager annual, quarterly, self · 1.Ensure timely and high-quality delivery of database development tasks across Oracle and SQL Server 2.Ensure continuous skill development in advanced database technologies and tools within the team 3.Promote best practices in database development, code quality, and performance optimization 4. Learn ETL tools like … | V197: Latest rating: 3 · Potential: Medium · 9-box: Emerging Talent · Readiness: Develop in role | W197: C M · Au L · Ac M · L L · BI M · Exp H · 6.9 yrs vs 2–4 yrs · Edu M · BCA | X197: Open ▸ | Y197: =IFERROR(INDEX(DL_C,MATCH($CA197,DL_KEY,0)),"M") -> H | Z197: =IFERROR(INDEX(DL_Au,MATCH($CA197,DL_KEY,0)),"M") -> M | AA197: =IFERROR(INDEX(DL_Ac,MATCH($CA197,DL_KEY,0)),"M") -> L | AB197: =IFERROR(INDEX(DL_L,MATCH($CA197,DL_KEY,0)),"M") -> L | AC197: =IFERROR(INDEX(DL_BI,MATCH($CA197,DL_KEY,0)),"M") -> L | AD197: =IFERROR(INDEX(DL_Exp,MATCH($CA197,DL_KEY,0)),"M") -> L | AE197: =IFERROR(INDEX(DL_Edu,MATCH($CA197,DL_KEY,0)),"M") -> L | AF197: M | AG197: M | AH197: M | AI197: M | AJ197: M | AK197: M | AL197: M | AM197: 0.583 | AN197: 0.16 | AO197: 0.09 | AP197: 0 | AQ197: 0.063 | AR197: 0.06 | AS197: 0.04 | AT197: 2–5 | AU197: Graduate; relevant certification preferred | AV197: None · guides 1–3 juniors informally | AW197: P2 · SFIA 3 Apply | AX197: S46–S51 Korn Ferry Hay evaluations · S04, S52 Mercer IPE · S53–S57 NHS, UK NJC/PSC, GLPC, SJC, US OPM point-factor plans · S58 McKinsey skills-based hiring · S60 WEF skills-first · S61 EY India 2026 · the Experience / Education split is an IRIS rule · S32 Google, Microsoft, Amazon · S33 Infosys · S35 Accenture India · IRIS experience guide · S01 Aon Radford · S02 Pave · S08 SFIA 9 · S03 Mercer career levels | AY197: A3 | AZ197: Band A · Practitioner · Senior Associate | BA197: Model A3 from the six ratings, the market-derived weights and rules R1–R13 · then No change · already below the manager | BB197: A3 | BC197: The six ratings on the market-average weights of Band A · all tracks score 2.65 → A3 · Hay, Mercer IPE and public plans · experience 6.9 yrs vs the A3 market range 2–5 | BD197: =IF(SUM(BM197,BN197,BO197,BP197,BQ197,BR197,BS197)=0,0,(BM197*BT197+BN197*BU197+BO197*BV197+BP197*BW197+BQ197*BX197+BR197*BY197+BS197*BZ197)/SUM(BM197,BN197,BO197,BP197,BQ197,BR197,BS197)) -> 0 | BE197: =IF(LEFT(AY197,1)="X",AY197,IF(OR(AY197="B+",AY197="C+"),INDEX(LAD_PC,MAX(1,MIN(14,MATCH(AY197,LAD_PC,0)+IF(BD197>=0.5,1,IF(BD197<=-0.5,-1,0))))),INDEX(LAD_STD,MAX(1,MIN(12,MATCH(AY197,LAD_STD,0)+IF(BD197>=0.5,1,IF(BD197<=-0.5,-1,0))))))) -> A3 | BG197: =IF(BF197<>"",BF197,BE197) -> A3 | BH197: =IFERROR(CHOOSE(INDEX(B_RANK,MATCH(BG197,B_LVL,0)),"Band A","Band B","B+ · Player-Coach","Band C","C+ · Player-Coach","Band D","Band E"),"Band X · Consultant") -> Band A | BI197: =IF(BG197=AY197,"• Same",IF(INDEX(B_VAL,MATCH(BG197,B_LVL,0))>INDEX(B_VAL,MATCH(AY197,B_LVL,0)),"▲ Up","▼ Down")) -> • Same | BJ197: =IF(OR($M197="",$M197="—",$M197="Not in this file"),"",IFERROR(INDEX($BG$7:$BG$592,MATCH($M197,$D$7:$D$592,0)),"")) -> B1 | BK197: =IFERROR(IF(BJ197="","—",IF(OR(LEFT(BG197,1)="X",LEFT(BJ197,1)="X"),"—",IF(AND(LEFT(BG197,1)="E",LEFT(BJ197,1)="E"),"Exception · Band E",IF(AND(INDEX(B_VAL,MATCH(BJ197,B_LVL,0))>=7,INDEX(B_RANK,MATCH(BG197,B_LVL,0))>=INDEX(B_RANK,MATCH(BJ197,B_LVL,0))),"⚠ Same band as a head manager",IF(INDEX(B_VAL,MATCH(BG197,B_LVL,0))>=INDEX(B_VAL,MATCH(BJ197,B_LVL,0)),"⚠ At or above the manager's level","OK"))))),"—") -> OK | BM197: =IFERROR(INDEX(LMH_PTS,MATCH(Y197,LMH_KEY,0)),0) -> 9 | BN197: =IFERROR(INDEX(LMH_PTS,MATCH(Z197,LMH_KEY,0)),0) -> 3 | BO197: =IFERROR(INDEX(LMH_PTS,MATCH(AA197,LMH_KEY,0)),0) -> 1 | BP197: =IFERROR(INDEX(LMH_PTS,MATCH(AB197,LMH_KEY,0)),0) -> 1 | BQ197: =IFERROR(INDEX(LMH_PTS,MATCH(AC197,LMH_KEY,0)),0) -> 1 | BR197: =IFERROR(INDEX(LMH_PTS,MATCH(AD197,LMH_KEY,0)),0) -> 1 | BS197: =IFERROR(INDEX(LMH_PTS,MATCH(AE197,LMH_KEY,0)),0) -> 1 | BT197: =IFERROR(INDEX(LMH_STEP,MATCH(AF197,LMH_KEY,0)),0) -> 0 | BU197: =IFERROR(INDEX(LMH_STEP,MATCH(AG197,LMH_KEY,0)),0) -> 0 | BV197: =IFERROR(INDEX(LMH_STEP,MATCH(AH197,LMH_KEY,0)),0) -> 0 | BW197: =IFERROR(INDEX(LMH_STEP,MATCH(AI197,LMH_KEY,0)),0) -> 0 | BX197: =IFERROR(INDEX(LMH_STEP,MATCH(AJ197,LMH_KEY,0)),0) -> 0 | BY197: =IFERROR(INDEX(LMH_STEP,MATCH(AK197,LMH_KEY,0)),0) -> 0 | BZ197: =IFERROR(INDEX(LMH_STEP,MATCH(AL197,LMH_KEY,0)),0) -> 0 | CA197: iDEAL|Technology|Senior Database Engineer|A3|A
A198: iDEAL | B198: Technology | C198: 4 | D198: IRIS2052 | E198: Akshata Sabale | F198: Software Engineer | G198: Senior Software Engineer | H198: Engineering & Development | I198: Backend Development | J198: IC | K198: RC-067 | L198: Jitendra Kumar | M198: IRIS0810 | N198: 5.1 | O198: 4.1 | P198: B.E | Q198: L3 – Professional / Associate | R198: A3 | S198: 20 of 20 | T198: Complexity: Evidence reads like A3: New features, bug fixes, code review, live-issue debugging, report development, unit testing on RPT application → moved up 0.5 Autonomy: Evidence reads like A2: Only 'code implementation' given as independent decision → matches the start Accountability: Evidence reads like A3: Code he ships to production; breakage means … | U198: Received · manager annual, quarterly, self · 1. AI-Assisted Development Adoption: Use AI coding assistants for at least 60% of development tasks , with no increase in bug-escape rate. 2. ownership: Take complete ownership of the iDEAL RPT ensuring timely delivery of client requirements, production support, and continuous improvements. 3. Test Coverage: Achieve … | V198: Latest rating: 3 · Potential: Medium · 9-box: Core Contributor · Readiness: Develop in role | W198: C M · Au L · Ac M · L L · BI M · Exp H · 5.1 yrs vs 2–4 yrs · Edu M · B.E | X198: Open ▸ | Y198: =IFERROR(INDEX(DL_C,MATCH($CA198,DL_KEY,0)),"M") -> H | Z198: =IFERROR(INDEX(DL_Au,MATCH($CA198,DL_KEY,0)),"M") -> M | AA198: =IFERROR(INDEX(DL_Ac,MATCH($CA198,DL_KEY,0)),"M") -> L | AB198: =IFERROR(INDEX(DL_L,MATCH($CA198,DL_KEY,0)),"M") -> L | AC198: =IFERROR(INDEX(DL_BI,MATCH($CA198,DL_KEY,0)),"M") -> L | AD198: =IFERROR(INDEX(DL_Exp,MATCH($CA198,DL_KEY,0)),"M") -> L | AE198: =IFERROR(INDEX(DL_Edu,MATCH($CA198,DL_KEY,0)),"M") -> L | AF198: M | AG198: M | AH198: M | AI198: M | AJ198: M | AK198: M | AL198: M | AM198: 0.583 | AN198: 0.16 | AO198: 0.09 | AP198: 0 | AQ198: 0.063 | AR198: 0.06 | AS198: 0.04 | AT198: 2–5 | AU198: Graduate; relevant certification preferred | AV198: None · guides 1–3 juniors informally | AW198: P2 · SFIA 3 Apply | AX198: S46–S51 Korn Ferry Hay evaluations · S04, S52 Mercer IPE · S53–S57 NHS, UK NJC/PSC, GLPC, SJC, US OPM point-factor plans · S58 McKinsey skills-based hiring · S60 WEF skills-first · S61 EY India 2026 · the Experience / Education split is an IRIS rule · S32 Google, Microsoft, Amazon · S33 Infosys · S35 Accenture India · IRIS experience guide · S01 Aon Radford · S02 Pave · S08 SFIA 9 · S03 Mercer career levels | AY198: A3 | AZ198: Band A · Practitioner · Senior Associate | BA198: Model A3 from the six ratings, the market-derived weights and rules R1–R13 · then No change · already below the manager | BB198: A3 | BC198: The six ratings on the market-average weights of Band A · all tracks score 2.57 → A3 · Hay, Mercer IPE and public plans · experience 5.1 yrs vs the A3 market range 2–5 | BD198: =IF(SUM(BM198,BN198,BO198,BP198,BQ198,BR198,BS198)=0,0,(BM198*BT198+BN198*BU198+BO198*BV198+BP198*BW198+BQ198*BX198+BR198*BY198+BS198*BZ198)/SUM(BM198,BN198,BO198,BP198,BQ198,BR198,BS198)) -> 0 | BE198: =IF(LEFT(AY198,1)="X",AY198,IF(OR(AY198="B+",AY198="C+"),INDEX(LAD_PC,MAX(1,MIN(14,MATCH(AY198,LAD_PC,0)+IF(BD198>=0.5,1,IF(BD198<=-0.5,-1,0))))),INDEX(LAD_STD,MAX(1,MIN(12,MATCH(AY198,LAD_STD,0)+IF(BD198>=0.5,1,IF(BD198<=-0.5,-1,0))))))) -> A3 | BG198: =IF(BF198<>"",BF198,BE198) -> A3 | BH198: =IFERROR(CHOOSE(INDEX(B_RANK,MATCH(BG198,B_LVL,0)),"Band A","Band B","B+ · Player-Coach","Band C","C+ · Player-Coach","Band D","Band E"),"Band X · Consultant") -> Band A | BI198: =IF(BG198=AY198,"• Same",IF(INDEX(B_VAL,MATCH(BG198,B_LVL,0))>INDEX(B_VAL,MATCH(AY198,B_LVL,0)),"▲ Up","▼ Down")) -> • Same | BJ198: =IF(OR($M198="",$M198="—",$M198="Not in this file"),"",IFERROR(INDEX($BG$7:$BG$592,MATCH($M198,$D$7:$D$592,0)),"")) -> B+ | BK198: =IFERROR(IF(BJ198="","—",IF(OR(LEFT(BG198,1)="X",LEFT(BJ198,1)="X"),"—",IF(AND(LEFT(BG198,1)="E",LEFT(BJ198,1)="E"),"Exception · Band E",IF(AND(INDEX(B_VAL,MATCH(BJ198,B_LVL,0))>=7,INDEX(B_RANK,MATCH(BG198,B_LVL,0))>=INDEX(B_RANK,MATCH(BJ198,B_LVL,0))),"⚠ Same band as a head manager",IF(INDEX(B_VAL,MATCH(BG198,B_LVL,0))>=INDEX(B_VAL,MATCH(BJ198,B_LVL,0)),"⚠ At or above the manager's level","OK"))))),"—") -> OK | BM198: =IFERROR(INDEX(LMH_PTS,MATCH(Y198,LMH_KEY,0)),0) -> 9 | BN198: =IFERROR(INDEX(LMH_PTS,MATCH(Z198,LMH_KEY,0)),0) -> 3 | BO198: =IFERROR(INDEX(LMH_PTS,MATCH(AA198,LMH_KEY,0)),0) -> 1 | BP198: =IFERROR(INDEX(LMH_PTS,MATCH(AB198,LMH_KEY,0)),0) -> 1 | BQ198: =IFERROR(INDEX(LMH_PTS,MATCH(AC198,LMH_KEY,0)),0) -> 1 | BR198: =IFERROR(INDEX(LMH_PTS,MATCH(AD198,LMH_KEY,0)),0) -> 1 | BS198: =IFERROR(INDEX(LMH_PTS,MATCH(AE198,LMH_KEY,0)),0) -> 1 | BT198: =IFERROR(INDEX(LMH_STEP,MATCH(AF198,LMH_KEY,0)),0) -> 0 | BU198: =IFERROR(INDEX(LMH_STEP,MATCH(AG198,LMH_KEY,0)),0) -> 0 | BV198: =IFERROR(INDEX(LMH_STEP,MATCH(AH198,LMH_KEY,0)),0) -> 0 | BW198: =IFERROR(INDEX(LMH_STEP,MATCH(AI198,LMH_KEY,0)),0) -> 0 | BX198: =IFERROR(INDEX(LMH_STEP,MATCH(AJ198,LMH_KEY,0)),0) -> 0 | BY198: =IFERROR(INDEX(LMH_STEP,MATCH(AK198,LMH_KEY,0)),0) -> 0 | BZ198: =IFERROR(INDEX(LMH_STEP,MATCH(AL198,LMH_KEY,0)),0) -> 0 | CA198: iDEAL|Technology|Senior Software Engineer|A3|A
A199: iDEAL | B199: Technology | C199: 4 | D199: IRIS1922 | E199: H Marenna | F199: Senior Software Engineer | G199: Senior Database Engineer | H199: Engineering & Development | I199: Data Engineering & Database Development | J199: IC | K199: RC-074 | L199: Jitendra Kumar | M199: IRIS0810 | N199: 9.2 | O199: 5.2 | P199: B.Tech | Q199: L4 – Senior | R199: A3 | S199: 20 of 20 | T199: Complexity: Evidence reads like A2: Database / ETL issue resolution on assigned work; no harder cases described → moved down 0.5 Autonomy: Evidence reads like A2: Only says troubleshooting issues is done independently → moved down 0.5 Accountability: Evidence reads like A2: own survey / KRA answers · summarised by the rater; not quoted → moved down … | U199: Received · manager annual, quarterly, self · 1.Promote best practices in database development, code quality, and performance optimization. 2.Drive team capability in handling database tasks independently with minimal supervision 3.Ensure timely and high-quality delivery of database development tasks across Oracle and SQL Server 4. Learn ETL tools like Apache Hop … | V199: Latest rating: 2 · Potential: Low · 9-box: Reliable Specialist · Readiness: Performance first | W199: C M · Au M · Ac M · L L · BI M · Exp H · 9.2 yrs vs 2–4 yrs · Edu M · B.Tech | X199: Open ▸ | Y199: =IFERROR(INDEX(DL_C,MATCH($CA199,DL_KEY,0)),"M") -> H | Z199: =IFERROR(INDEX(DL_Au,MATCH($CA199,DL_KEY,0)),"M") -> M | AA199: =IFERROR(INDEX(DL_Ac,MATCH($CA199,DL_KEY,0)),"M") -> L | AB199: =IFERROR(INDEX(DL_L,MATCH($CA199,DL_KEY,0)),"M") -> L | AC199: =IFERROR(INDEX(DL_BI,MATCH($CA199,DL_KEY,0)),"M") -> L | AD199: =IFERROR(INDEX(DL_Exp,MATCH($CA199,DL_KEY,0)),"M") -> L | AE199: =IFERROR(INDEX(DL_Edu,MATCH($CA199,DL_KEY,0)),"M") -> L | AF199: M | AG199: M | AH199: M | AI199: M | AJ199: M | AK199: M | AL199: M | AM199: 0.583 | AN199: 0.16 | AO199: 0.09 | AP199: 0 | AQ199: 0.063 | AR199: 0.06 | AS199: 0.04 | AT199: 2–5 | AU199: Graduate; relevant certification preferred | AV199: None · guides 1–3 juniors informally | AW199: P2 · SFIA 3 Apply | AX199: S46–S51 Korn Ferry Hay evaluations · S04, S52 Mercer IPE · S53–S57 NHS, UK NJC/PSC, GLPC, SJC, US OPM point-factor plans · S58 McKinsey skills-based hiring · S60 WEF skills-first · S61 EY India 2026 · the Experience / Education split is an IRIS rule · S32 Google, Microsoft, Amazon · S33 Infosys · S35 Accenture India · IRIS experience guide · S01 Aon Radford · S02 Pave · S08 SFIA 9 · S03 Mercer career levels | AY199: A3 | AZ199: Band A · Practitioner · Senior Associate | BA199: Model A3 from the six ratings, the market-derived weights and rules R1–R13 · then No change · already below the manager | BB199: A3 | BC199: The six ratings on the market-average weights of Band A · all tracks score 2.80 → A3 · Hay, Mercer IPE and public plans · experience 9.2 yrs vs the A3 market range 2–5 | BD199: =IF(SUM(BM199,BN199,BO199,BP199,BQ199,BR199,BS199)=0,0,(BM199*BT199+BN199*BU199+BO199*BV199+BP199*BW199+BQ199*BX199+BR199*BY199+BS199*BZ199)/SUM(BM199,BN199,BO199,BP199,BQ199,BR199,BS199)) -> 0 | BE199: =IF(LEFT(AY199,1)="X",AY199,IF(OR(AY199="B+",AY199="C+"),INDEX(LAD_PC,MAX(1,MIN(14,MATCH(AY199,LAD_PC,0)+IF(BD199>=0.5,1,IF(BD199<=-0.5,-1,0))))),INDEX(LAD_STD,MAX(1,MIN(12,MATCH(AY199,LAD_STD,0)+IF(BD199>=0.5,1,IF(BD199<=-0.5,-1,0))))))) -> A3 | BG199: =IF(BF199<>"",BF199,BE199) -> A3 | BH199: =IFERROR(CHOOSE(INDEX(B_RANK,MATCH(BG199,B_LVL,0)),"Band A","Band B","B+ · Player-Coach","Band C","C+ · Player-Coach","Band D","Band E"),"Band X · Consultant") -> Band A | BI199: =IF(BG199=AY199,"• Same",IF(INDEX(B_VAL,MATCH(BG199,B_LVL,0))>INDEX(B_VAL,MATCH(AY199,B_LVL,0)),"▲ Up","▼ Down")) -> • Same | BJ199: =IF(OR($M199="",$M199="—",$M199="Not in this file"),"",IFERROR(INDEX($BG$7:$BG$592,MATCH($M199,$D$7:$D$592,0)),"")) -> B+ | BK199: =IFERROR(IF(BJ199="","—",IF(OR(LEFT(BG199,1)="X",LEFT(BJ199,1)="X"),"—",IF(AND(LEFT(BG199,1)="E",LEFT(BJ199,1)="E"),"Exception · Band E",IF(AND(INDEX(B_VAL,MATCH(BJ199,B_LVL,0))>=7,INDEX(B_RANK,MATCH(BG199,B_LVL,0))>=INDEX(B_RANK,MATCH(BJ199,B_LVL,0))),"⚠ Same band as a head manager",IF(INDEX(B_VAL,MATCH(BG199,B_LVL,0))>=INDEX(B_VAL,MATCH(BJ199,B_LVL,0)),"⚠ At or above the manager's level","OK"))))),"—") -> OK | BM199: =IFERROR(INDEX(LMH_PTS,MATCH(Y199,LMH_KEY,0)),0) -> 9 | BN199: =IFERROR(INDEX(LMH_PTS,MATCH(Z199,LMH_KEY,0)),0) -> 3 | BO199: =IFERROR(INDEX(LMH_PTS,MATCH(AA199,LMH_KEY,0)),0) -> 1 | BP199: =IFERROR(INDEX(LMH_PTS,MATCH(AB199,LMH_KEY,0)),0) -> 1 | BQ199: =IFERROR(INDEX(LMH_PTS,MATCH(AC199,LMH_KEY,0)),0) -> 1 | BR199: =IFERROR(INDEX(LMH_PTS,MATCH(AD199,LMH_KEY,0)),0) -> 1 | BS199: =IFERROR(INDEX(LMH_PTS,MATCH(AE199,LMH_KEY,0)),0) -> 1 | BT199: =IFERROR(INDEX(LMH_STEP,MATCH(AF199,LMH_KEY,0)),0) -> 0 | BU199: =IFERROR(INDEX(LMH_STEP,MATCH(AG199,LMH_KEY,0)),0) -> 0 | BV199: =IFERROR(INDEX(LMH_STEP,MATCH(AH199,LMH_KEY,0)),0) -> 0 | BW199: =IFERROR(INDEX(LMH_STEP,MATCH(AI199,LMH_KEY,0)),0) -> 0 | BX199: =IFERROR(INDEX(LMH_STEP,MATCH(AJ199,LMH_KEY,0)),0) -> 0 | BY199: =IFERROR(INDEX(LMH_STEP,MATCH(AK199,LMH_KEY,0)),0) -> 0 | BZ199: =IFERROR(INDEX(LMH_STEP,MATCH(AL199,LMH_KEY,0)),0) -> 0 | CA199: iDEAL|Technology|Senior Database Engineer|A3|A
A200: iDEAL | B200: Technology | C200: 4 | D200: IRIS2530 | E200: Jay Gudhka | F200: Senior Software Engineer | G200: Technical Specialist | H200: Engineering & Development | I200: Full-Stack Development | J200: IC | K200: RC-085 | L200: Jitendra Kumar | M200: IRIS0810 | N200: 7.2 | O200: 0.4 | P200: B.E | Q200: L4 – Senior | R200: A3 | S200: 20 of 20 | T200: Complexity: Evidence reads like B1: Full-stack development, API design and RAG/LLM integration with no established internal process → moved up 0.5 Autonomy: Evidence reads like A3: Makes the tech and design choices on what is built → matches the start Accountability: Evidence reads like A3: own survey / KRA answers · summarised by the rater; not quoted → … | U200: Received · manager annual, quarterly, self · 1. AI Feature Architecture: Design and lead implementation of at least 1 AI-powered feature in the application · e.g. auto Mapping, from architecture through production rollout. 2. Mentorship in AI Practices: Train team members on effective AI-assisted coding practices, with measurable improvement in team's AI tool … | V200: Latest rating: 3 · Potential: Medium · 9-box: Emerging Talent · Readiness: Develop in role | W200: C M · Au M · Ac M · L M · BI M · Exp H · 7.2 yrs vs 2–4 yrs · Edu M · B.E | X200: Open ▸ | Y200: =IFERROR(INDEX(DL_C,MATCH($CA200,DL_KEY,0)),"M") -> H | Z200: =IFERROR(INDEX(DL_Au,MATCH($CA200,DL_KEY,0)),"M") -> M | AA200: =IFERROR(INDEX(DL_Ac,MATCH($CA200,DL_KEY,0)),"M") -> L | AB200: =IFERROR(INDEX(DL_L,MATCH($CA200,DL_KEY,0)),"M") -> L | AC200: =IFERROR(INDEX(DL_BI,MATCH($CA200,DL_KEY,0)),"M") -> L | AD200: =IFERROR(INDEX(DL_Exp,MATCH($CA200,DL_KEY,0)),"M") -> L | AE200: =IFERROR(INDEX(DL_Edu,MATCH($CA200,DL_KEY,0)),"M") -> L | AF200: M | AG200: M | AH200: M | AI200: M | AJ200: M | AK200: M | AL200: M | AM200: 0.583 | AN200: 0.16 | AO200: 0.09 | AP200: 0 | AQ200: 0.063 | AR200: 0.06 | AS200: 0.04 | AT200: 2–5 | AU200: Graduate; relevant certification preferred | AV200: None · guides 1–3 juniors informally | AW200: P2 · SFIA 3 Apply | AX200: S46–S51 Korn Ferry Hay evaluations · S04, S52 Mercer IPE · S53–S57 NHS, UK NJC/PSC, GLPC, SJC, US OPM point-factor plans · S58 McKinsey skills-based hiring · S60 WEF skills-first · S61 EY India 2026 · the Experience / Education split is an IRIS rule · S32 Google, Microsoft, Amazon · S33 Infosys · S35 Accenture India · IRIS experience guide · S01 Aon Radford · S02 Pave · S08 SFIA 9 · S03 Mercer career levels | AY200: A3 | AZ200: Band A · Practitioner · Senior Associate | BA200: Model A3 from the six ratings, the market-derived weights and rules R1–R13 · then No change · already below the manager | BB200: A3 | BC200: The six ratings on the market-average weights of Band A · all tracks score 3.49 → A3 · Hay, Mercer IPE and public plans · experience 7.2 yrs vs the A3 market range 2–5 | BD200: =IF(SUM(BM200,BN200,BO200,BP200,BQ200,BR200,BS200)=0,0,(BM200*BT200+BN200*BU200+BO200*BV200+BP200*BW200+BQ200*BX200+BR200*BY200+BS200*BZ200)/SUM(BM200,BN200,BO200,BP200,BQ200,BR200,BS200)) -> 0 | BE200: =IF(LEFT(AY200,1)="X",AY200,IF(OR(AY200="B+",AY200="C+"),INDEX(LAD_PC,MAX(1,MIN(14,MATCH(AY200,LAD_PC,0)+IF(BD200>=0.5,1,IF(BD200<=-0.5,-1,0))))),INDEX(LAD_STD,MAX(1,MIN(12,MATCH(AY200,LAD_STD,0)+IF(BD200>=0.5,1,IF(BD200<=-0.5,-1,0))))))) -> A3 | BG200: =IF(BF200<>"",BF200,BE200) -> A3 | BH200: =IFERROR(CHOOSE(INDEX(B_RANK,MATCH(BG200,B_LVL,0)),"Band A","Band B","B+ · Player-Coach","Band C","C+ · Player-Coach","Band D","Band E"),"Band X · Consultant") -> Band A | BI200: =IF(BG200=AY200,"• Same",IF(INDEX(B_VAL,MATCH(BG200,B_LVL,0))>INDEX(B_VAL,MATCH(AY200,B_LVL,0)),"▲ Up","▼ Down")) -> • Same | BJ200: =IF(OR($M200="",$M200="—",$M200="Not in this file"),"",IFERROR(INDEX($BG$7:$BG$592,MATCH($M200,$D$7:$D$592,0)),"")) -> B+ | BK200: =IFERROR(IF(BJ200="","—",IF(OR(LEFT(BG200,1)="X",LEFT(BJ200,1)="X"),"—",IF(AND(LEFT(BG200,1)="E",LEFT(BJ200,1)="E"),"Exception · Band E",IF(AND(INDEX(B_VAL,MATCH(BJ200,B_LVL,0))>=7,INDEX(B_RANK,MATCH(BG200,B_LVL,0))>=INDEX(B_RANK,MATCH(BJ200,B_LVL,0))),"⚠ Same band as a head manager",IF(INDEX(B_VAL,MATCH(BG200,B_LVL,0))>=INDEX(B_VAL,MATCH(BJ200,B_LVL,0)),"⚠ At or above the manager's level","OK"))))),"—") -> OK | BM200: =IFERROR(INDEX(LMH_PTS,MATCH(Y200,LMH_KEY,0)),0) -> 9 | BN200: =IFERROR(INDEX(LMH_PTS,MATCH(Z200,LMH_KEY,0)),0) -> 3 | BO200: =IFERROR(INDEX(LMH_PTS,MATCH(AA200,LMH_KEY,0)),0) -> 1 | BP200: =IFERROR(INDEX(LMH_PTS,MATCH(AB200,LMH_KEY,0)),0) -> 1 | BQ200: =IFERROR(INDEX(LMH_PTS,MATCH(AC200,LMH_KEY,0)),0) -> 1 | BR200: =IFERROR(INDEX(LMH_PTS,MATCH(AD200,LMH_KEY,0)),0) -> 1 | BS200: =IFERROR(INDEX(LMH_PTS,MATCH(AE200,LMH_KEY,0)),0) -> 1 | BT200: =IFERROR(INDEX(LMH_STEP,MATCH(AF200,LMH_KEY,0)),0) -> 0 | BU200: =IFERROR(INDEX(LMH_STEP,MATCH(AG200,LMH_KEY,0)),0) -> 0 | BV200: =IFERROR(INDEX(LMH_STEP,MATCH(AH200,LMH_KEY,0)),0) -> 0 | BW200: =IFERROR(INDEX(LMH_STEP,MATCH(AI200,LMH_KEY,0)),0) -> 0 | BX200: =IFERROR(INDEX(LMH_STEP,MATCH(AJ200,LMH_KEY,0)),0) -> 0 | BY200: =IFERROR(INDEX(LMH_STEP,MATCH(AK200,LMH_KEY,0)),0) -> 0 | BZ200: =IFERROR(INDEX(LMH_STEP,MATCH(AL200,LMH_KEY,0)),0) -> 0 | CA200: iDEAL|Technology|Technical Specialist|A3|A
