Workbook
Name LMH_KEY: 'Backend Data'!$A$6:$A$8
Name LMH_PTS: 'Backend Data'!$C$6:$C$8
Name LMH_STEP: 'Backend Data'!$D$6:$D$8
Name LIST_LMH: 'Backend Data'!$A$6:$A$8
Name B_LVL: 'Backend Data'!$A$11:$A$27
Name B_VAL: 'Backend Data'!$B$11:$B$27
Name B_RANK: 'Backend Data'!$D$11:$D$27
Name LAD_STD: 'Backend Data'!$E$11:$E$22
Name LAD_PC: 'Backend Data'!$F$11:$F$24
Name LIST_LEVELS: 'Backend Data'!$A$11:$A$27
Name LIST_PEOPLE: 'Backend Data'!$A$30:$A$615
Name PEOPLE_ID: 'Backend Data'!$B$30:$B$615
Name RM_KEY: '3. Role Model'!$A$7:$A$275
Name RM_I_C: '3. Role Model'!$I$7:$I$275
Name RM_M_C: '3. Role Model'!$P$7:$P$275
Name RM_L_C: '3. Role Model'!$W$7:$W$275
Name RM_E_C: '3. Role Model'!$AD$7:$AD$275
Name RM_I_Au: '3. Role Model'!$J$7:$J$275
Name RM_M_Au: '3. Role Model'!$Q$7:$Q$275
Name RM_L_Au: '3. Role Model'!$X$7:$X$275
Name RM_E_Au: '3. Role Model'!$AE$7:$AE$275
Name RM_I_Ac: '3. Role Model'!$K$7:$K$275
Name RM_M_Ac: '3. Role Model'!$R$7:$R$275
Name RM_L_Ac: '3. Role Model'!$Y$7:$Y$275
Name RM_E_Ac: '3. Role Model'!$AF$7:$AF$275
Name RM_I_L: '3. Role Model'!$L$7:$L$275
Name RM_M_L: '3. Role Model'!$S$7:$S$275
Name RM_L_L: '3. Role Model'!$Z$7:$Z$275
Name RM_E_L: '3. Role Model'!$AG$7:$AG$275
Name RM_I_BI: '3. Role Model'!$M$7:$M$275
Name RM_M_BI: '3. Role Model'!$T$7:$T$275
Name RM_L_BI: '3. Role Model'!$AA$7:$AA$275
Name RM_E_BI: '3. Role Model'!$AH$7:$AH$275
Name RM_I_Exp: '3. Role Model'!$N$7:$N$275
Name RM_M_Exp: '3. Role Model'!$U$7:$U$275
Name RM_L_Exp: '3. Role Model'!$AB$7:$AB$275
Name RM_E_Exp: '3. Role Model'!$AI$7:$AI$275
Name RM_I_Edu: '3. Role Model'!$O$7:$O$275
Name RM_M_Edu: '3. Role Model'!$V$7:$V$275
Name RM_L_Edu: '3. Role Model'!$AC$7:$AC$275
Name RM_E_Edu: '3. Role Model'!$AJ$7:$AJ$275
Name RM_LCNT: '3. Role Model'!$AK$7:$AK$275

Sheet 1. How it works
A1: IRIS Job Architecture Model — how it works
A2: Read this first · five steps, in the order they happened.
A3: IRIS · Job Architecture Model v2.0 · October 2026 · Internal — Confidential · HR and business leaders
A5: 1 · We asked | B5: The How We Grow survey: 20 questions to every employee about the work, decisions, accountability, skills and learning; and the managers' talent mapping: KRAs, rating, potential, 9-box. Where nothing came back, the cell is blank.
A6: 2 · We built the ladder | B6: There was no level framework. From the answers and the market we built one ladder of 12 levels in five bands, plus two Player-Coach steps. Each level has its own experience range, scope and span, so the levels do not overlap · sheet 2.
A7: 3 · We placed everyone | B7: Each person got a job family, a sub-family, a role and a level from the evidence. Then we moved the fewest people needed so that no one shares a band with their manager: 36 down, pay and title protected, and 39 up. Where a reporting chain is deeper than the bands, we flag it for a structure decision instead of forcing a level: 22 cases.
A8: 4 · We checked the market | B8: Every parameter's weight is set against published job-evaluation methods — Korn Ferry Hay, Mercer IPE and five public plans — and shown as Low / Medium / High with the numbers behind it · sheet 4. Levels map to Radford / Mercer codes, SFIA and peer experience ranges.
A9: 5 · Leaders give their view | B9: On sheet 5 you see, for each person, what IRIS proposes and why. Rate any parameter Low, Medium or High against the level; re-weight a role on sheet 3; or set any level with the override. Your proposed level and band appear as soon as you give an input, and the manager check updates live.
A10: The model in one line | B10: Each parameter is rated Low / Medium / High against the level; each role weights the parameters Low / Medium / High. If your weighted rating is half a level or more above IRIS's, the person moves one level up; half a level or more below, one level down.
A11: The seven parameters | B11: Complexity & Expertise · Autonomy & Decision · Accountability & Impact · Leadership & Strategy · Business Impact · Experience · Education.
A12: Low · Medium · High | B12: Rating: Low = works at the level below on this parameter; Medium = as the level is defined; High = already at the level above. Weightage: Low counts 1, Medium 3, High 9 — the shares follow the published methods within a few points.
A13: Colours | B13: Yellow = yours to fill · red = a structure decision · orange = a title to align · band colours on levels.
A14: Privacy | B14: HR and business leaders only. Personal fields are never written; pay is not in this file.
A16: The sheets
A17: 1. How it works
A18: 2. Ladder
A19: 3. Role Model
A20: 4. Market Benchmark
A21: 5. Talent Mapping
A22: 6. Person Card
A23: 7. Raw Data
A24: Backend Data

Sheet 2. Ladder
A1: Ladder — one level, one place | M1: ◂ Start
A2: Sheet 2 · Every level has its own experience range, scope and span — the ranges do not overlap, so each person fits one level by the evidence. Player-Coach steps B+ and C+ are set by the role, not by years. Titles follow HR's decisions.
A3: IRIS · Job Architecture Model v2.0 · October 2026 · Internal — Confidential · HR and business leaders
A5: LEVEL | E5: WHAT DEFINES IT — distinct by level | I5: MARKET | M5: PEOPLE
A6: Level | B6: Band | C6: IC title | D6: Manager title | E6: Experience · distinct range | F6: What the role owns | G6: Span of control | H6: Education | I6: Market experience · yrs | J6: Radford / Mercer | K6: SFIA 9 | L6: References | M6: People · IRIS proposed
A7: E2 | B7: Band E · Enterprise leadership | C7: — | D7: Chief Executive Officer | E7: 22+ yrs · board appointment | F7: The enterprise | G7: Executive team | H7: Postgraduate / professional qualification; proven business leadership | I7: — | J7: E6 | K7: 7 | L7: S01 Aon Radford · S02 Pave · S08 SFIA 9 · S03 Mercer career levels · S32 Google, Microsoft, Amazon · S33 Infosys · S35 Accenture India · IRIS experience guide · S09 McKinsey spans of control · S37 GitLab layers · S44 Google Tech Lead Manager | M7: 1
A8: E1 | B8: Band E · Enterprise leadership | C8: — | D8: CXO / President | E8: 22+ yrs | F8: An enterprise-wide function | G8: 5–8 function heads | H8: Postgraduate / professional qualification; business leadership record | I8: — | J8: E5 | K8: 7 | L8: S01 Aon Radford · S02 Pave · S08 SFIA 9 · S03 Mercer career levels · S32 Google, Microsoft, Amazon · S33 Infosys · S35 Accenture India · IRIS experience guide · S09 McKinsey spans of control · S37 GitLab layers · S44 Google Tech Lead Manager | M8: 4
A9: D2 | B9: Band D · Business leadership | C9: — | D9: Senior Vice President / Business Head | E9: 19–22 yrs | F9: Several business lines or an executive-scope enterprise function | G9: 5–8 AVPs / heads | H9: Postgraduate / professional qualification preferred | I9: — | J9: E3–E4 | K9: 7 Set strategy | L9: S01 Aon Radford · S02 Pave · S08 SFIA 9 · S03 Mercer career levels · S32 Google, Microsoft, Amazon · S33 Infosys · S35 Accenture India · IRIS experience guide · S09 McKinsey spans of control · S37 GitLab layers · S44 Google Tech Lead Manager | M9: 4
A10: D1 | B10: Band D · Business leadership | C10: Distinguished Principal | D10: Associate Vice President | E10: 16–19 yrs | F10: A business line P&L, region or enterprise function | G10: 5–8 heads | H10: Postgraduate / professional qualification preferred | I10: — | J10: E1–E2 | K10: 6–7 | L10: S01 Aon Radford · S02 Pave · S08 SFIA 9 · S03 Mercer career levels · S32 Google, Microsoft, Amazon · S33 Infosys · S35 Accenture India · IRIS experience guide · S09 McKinsey spans of control · S37 GitLab layers · S44 Google Tech Lead Manager | M10: 3
A11: C+ | B11: C+ · Player-Coach | C11: Group Head · Player-Coach | D11: Group Head · Player-Coach | E11: 13–17 yrs · Player-Coach, set by the role, not by years | F11: A function or group of practices: answers for its results and personally delivers or sells the most critical work · player-coach | G11: 4–8 managers / leads with ≥ 25% of time on own principal delivery | H11: Postgraduate / professional qualification preferred | I11: 15–18 | J11: M6 / E1 | K11: 6 Initiate, influence | L11: S01 Aon Radford · S02 Pave · S08 SFIA 9 · S03 Mercer career levels · S32 Google, Microsoft, Amazon · S33 Infosys · S35 Accenture India · IRIS experience guide · S09 McKinsey spans of control · S37 GitLab layers · S44 Google Tech Lead Manager | M11: 0
A12: C2 | B12: Band C · Principal / Head | C12: Senior Principal / Architect | D12: Head of Function | E12: 13–16 yrs | F12: A function or department, or a company-wide discipline | G12: 5–8 managers / associate heads | H12: Postgraduate / professional qualification preferred | I12: — | J12: P7 / M6 | K12: 6 Initiate, influence | L12: S01 Aon Radford · S02 Pave · S08 SFIA 9 · S03 Mercer career levels · S32 Google, Microsoft, Amazon · S33 Infosys · S35 Accenture India · IRIS experience guide · S09 McKinsey spans of control · S37 GitLab layers · S44 Google Tech Lead Manager | M12: 5
A13: C1 | B13: Band C · Principal / Head | C13: Principal | D13: Associate Head | E13: 10–13 yrs | F13: A sub-function, or principal authority across products | G13: 5–8, mostly managers | H13: Postgraduate / professional qualification preferred | I13: 12–17 | J13: P6 / M5 | K13: 5–6 | L13: S01 Aon Radford · S02 Pave · S08 SFIA 9 · S03 Mercer career levels · S32 Google, Microsoft, Amazon · S33 Infosys · S35 Accenture India · IRIS experience guide · S09 McKinsey spans of control · S37 GitLab layers · S44 Google Tech Lead Manager | M13: 27
A14: B+ | B14: B+ · Player-Coach | C14: Practice Lead · Player-Coach | D14: Practice Lead · Player-Coach | E14: 8–12 yrs · Player-Coach, set by the role, not by years | F14: A practice or product area: does the hardest hands-on work itself and leads 3–6 people · player-coach | G14: 3–6 direct reports with ≥ 40% of time on own delivery · McKinsey player/coach 3–5; Google Tech Lead Manager | H14: Postgraduate or professional qualification preferred | I14: 9–14 | J14: P5–P6 / M4–M5 | K14: 5 Ensure, advise | L14: S01 Aon Radford · S02 Pave · S08 SFIA 9 · S03 Mercer career levels · S32 Google, Microsoft, Amazon · S33 Infosys · S35 Accenture India · IRIS experience guide · S09 McKinsey spans of control · S37 GitLab layers · S44 Google Tech Lead Manager | M14: 5
A15: B3 | B15: Band B · Specialist / Manager | C15: Lead Specialist | D15: Senior Manager | E15: 8–10 yrs | F15: A practice, or several teams through team leads | G15: IC: none · People: 5–8 incl. team leads | H15: Postgraduate or professional qualification preferred | I15: 8–13 | J15: P5 / M4 | K15: 5 Ensure, advise | L15: S01 Aon Radford · S02 Pave · S08 SFIA 9 · S03 Mercer career levels · S32 Google, Microsoft, Amazon · S33 Infosys · S35 Accenture India · IRIS experience guide · S09 McKinsey spans of control · S37 GitLab layers · S44 Google Tech Lead Manager | M15: 13
A16: B2 | B16: Band B · Specialist / Manager | C16: Senior Specialist | D16: Manager | E16: 6–8 yrs | F16: Deep domain expertise, or one team | G16: IC: none · People: 6–8 knowledge work, 8–12 standardised delivery | H16: Graduate or postgraduate; professional qualification preferred | I16: 6–10 | J16: P4 / M3 | K16: 4–5 | L16: S01 Aon Radford · S02 Pave · S08 SFIA 9 · S03 Mercer career levels · S32 Google, Microsoft, Amazon · S33 Infosys · S35 Accenture India · IRIS experience guide · S09 McKinsey spans of control · S37 GitLab layers · S44 Google Tech Lead Manager | M16: 54
A17: B1 | B17: Band B · Specialist / Manager | C17: Specialist | D17: Team Lead / Asst Manager | E17: 4–6 yrs | F17: A domain / module, or a small team | G17: IC: none · Team Lead: 3–5 | H17: Graduate + relevant qualification or certification preferred | I17: 4–8 | J17: P3 / M2 | K17: 4 Enable | L17: S01 Aon Radford · S02 Pave · S08 SFIA 9 · S03 Mercer career levels · S32 Google, Microsoft, Amazon · S33 Infosys · S35 Accenture India · IRIS experience guide · S09 McKinsey spans of control · S37 GitLab layers · S44 Google Tech Lead Manager | M17: 78
A18: A3 | B18: Band A · Practitioner | C18: Senior Associate | D18: Senior Associate | E18: 2–4 yrs | F18: Varied work; reviews juniors; go-to for a process | G18: None · guides 1–3 juniors informally | H18: Graduate; relevant certification preferred | I18: 2–5 | J18: P2 | K18: 3 Apply | L18: S01 Aon Radford · S02 Pave · S08 SFIA 9 · S03 Mercer career levels · S32 Google, Microsoft, Amazon · S33 Infosys · S35 Accenture India · IRIS experience guide · S09 McKinsey spans of control · S37 GitLab layers · S44 Google Tech Lead Manager | M18: 289
... A20: A1 | B20: Band A · Practitioner | C20: Intern / Trainee | D20: Intern / Trainee | E20: Intern / trainee · first year | F20: Learning the role; all work reviewed | G20: No direct reports | H20: Pursuing or completed graduation / diploma | I20: — | J20: Entry / P1 · intern | K20: 1 Follow | L20: S01 Aon Radford · S02 Pave · S08 SFIA 9 · S03 Mercer career levels · S32 Google, Microsoft, Amazon · S33 Infosys · S35 Accenture India · IRIS experience guide · S09 McKinsey spans of control · S37 GitLab layers · S44 Google Tech Lead Manager | M20: 21

Sheet 3. Role Model
A1: Role Model — every role, its levels one below the other | O1: ◂ Start
A2: Sheet 3 · Role-based: a role is a sub-family done as an individual contributor or as a manager. The ROLE row carries the role's weightage: IRIS · Market · Leader. Type L, M or H in the yellow Leader cells and everyone in the role is re-weighted on Talent Mapping at once. The LEVEL rows below say what Low, Medium and High mean at each level. Filter column A or D by role.
A3: IRIS · Job Architecture Model v2.0 · October 2026 · Internal — Confidential · HR and business leaders
A4: Section colours: each column group has its own header colour and a matching light tint | E4: Changed vs current | G4: Level up | H4: Level down · pay & title protected | J4: Newly mapped | K4: Player-Coach · B+ · C+ | M4: RED = critical input needed · says what and who | P4: YELLOW = to complete or edit | R4: GREY = pay · set later
A5: ROLE | I5: WEIGHTAGE · IRIS — what we set | P5: WEIGHTAGE · MARKET — published evidence, sheet 4 | W5: WEIGHTAGE · LEADER — your update, blank = agree with IRIS | AD5: IN USE · leader if given, else IRIS | AL5: COMPLEXITY & EXPERTISE — what L / M / H mean at this level | AO5: AUTONOMY & DECISION — what L / M / H mean at this level | AR5: ACCOUNTABILITY & IMPACT — what L / M / H mean at this level | AU5: LEADERSHIP & STRATEGY — what L / M / H mean at this level | AX5: BUSINESS IMPACT — what L / M / H mean at this level | BA5: EXPERIENCE — what L / M / H mean at this level | BD5: EDUCATION — what L / M / H mean at this level
A6: Role ID | B6: Role | C6: Job family | D6: Track | E6: Row | F6: Level | G6: Standard title at this level | H6: People | I6: IRIS · Complexity & Expertise | J6: IRIS · Autonomy & Decision | K6: IRIS · Accountability & Impact | L6: IRIS · Leadership & Strategy | M6: IRIS · Business Impact | N6: IRIS · Experience | O6: IRIS · Education | P6: Market · Complexity & Expertise | Q6: Market · Autonomy & Decision | R6: Market · Accountability & Impact | S6: Market · Leadership & Strategy | T6: Market · Business Impact | U6: Market · Experience | V6: Market · Education | W6: Leader · Complexity & Expertise | X6: Leader · Autonomy & Decision | Y6: Leader · Accountability & Impact | Z6: Leader · Leadership & Strategy | AA6: Leader · Business Impact | AB6: Leader · Experience | AC6: Leader · Education | AD6: In use · Complexity & Expertise | AE6: In use · Autonomy & Decision | AF6: In use · Accountability & Impact | AG6: In use · Leadership & Strategy | AH6: In use · Business Impact | AI6: In use · Experience | AJ6: In use · Education | AK6: Leader updates | AL6: Complexity & Expertise · Low | AM6: Complexity & Expertise · Medium | AN6: Complexity & Expertise · High | AO6: Autonomy & Decision · Low | AP6: Autonomy & Decision · Medium | AQ6: Autonomy & Decision · High | AR6: Accountability & Impact · Low | AS6: Accountability & Impact · Medium | AT6: Accountability & Impact · High | AU6: Leadership & Strategy · Low | AV6: Leadership & Strategy · Medium | AW6: Leadership & Strategy · High | AX6: Business Impact · Low | AY6: Business Impact · Medium | AZ6: Business Impact · High | BA6: Experience · Low | BB6: Experience · Medium | BC6: Experience · High | BD6: Education · Low | BE6: Education · Medium | BF6: Education · High
A7: R001 | B7: Administration & Facilities · Consultant | C7: Administration, Legal & Secretarial | D7: Consultant | E7: ROLE | F7: X1 | G7: Consultant · outside the ladder · Corporate functions | H7: 1 | AD7: =IF(W7<>"",W7,I7) -> 0 | AE7: =IF(X7<>"",X7,J7) -> 0 | AF7: =IF(Y7<>"",Y7,K7) -> 0 | AG7: =IF(Z7<>"",Z7,L7) -> 0 | AH7: =IF(AA7<>"",AA7,M7) -> 0 | AI7: =IF(AB7<>"",AB7,N7) -> 0 | AJ7: =IF(AC7<>"",AC7,O7) -> 0 | AK7: =COUNTA(W7:AC7) -> 0
A8: R002 | B8: Administration & Facilities · IC | C8: Administration, Legal & Secretarial | D8: IC | E8: ROLE | F8: A3 | G8: Band A · all tracks · Corporate functions | H8: 4 | I8: H | J8: M | K8: M | L8: L | M8: L | N8: L | O8: M | P8: H | Q8: M | R8: M | S8: L | T8: L | U8: L | V8: L | AD8: =IF(W8<>"",W8,I8) -> H | AE8: =IF(X8<>"",X8,J8) -> M | AF8: =IF(Y8<>"",Y8,K8) -> M | AG8: =IF(Z8<>"",Z8,L8) -> L | AH8: =IF(AA8<>"",AA8,M8) -> L | AI8: =IF(AB8<>"",AB8,N8) -> L | AJ8: =IF(AC8<>"",AC8,O8) -> M | AK8: =COUNTA(W8:AC8) -> 0
A9: R002 | B9: Administration & Facilities · IC | C9: Administration, Legal & Secretarial | D9: IC | E9: level | F9: A3 | G9: Senior Administration Executive | H9: 4 | AL9: Works at A2: Standard work of the discipline | AM9: Varied and non-standard work; handles exceptions · in this role: Administration | AN9: Works at B1: Domain specialist work | AO9: Works at A2: Chooses own approach within standards | AP9: Technical / QC / client calls on own work | AQ9: Works at B1: Technical / QC / client calls for the domain | AR9: Works at A2: Own deliverables · accuracy, TAT | AS9: A module / process, or work with client or regulatory consequences | AT9: Works at B1: A domain or a small team | AU9: Works at A2: contributes alone; guides others only informally | AV9: Helps peers and newer people informally · None · guides 1–3 juniors informally | AW9: Works at B1: IC: mentors and reviews · People: hands-on team lead of 3–5 | AX9: Works at A2: Own deliverables feed a team's output and turnaround | AY9: A process or client deliverable depends on this work | AZ9: Works at B1: Moves a module's, product area's or client account's results | BA9: Less than 2–4 yrs | BB9: 2–4 yrs · market 2–5 yrs | BC9: More than 2–4 yrs | BD9: Below: Graduate · or diploma with experience | BE9: Graduate; relevant certification preferred · licence-to-practise roles: CA, CS, CMA or LLB as the role needs | BF9: Above: Graduate + relevant qualification or certification preferred
A10: R003 | B10: Administration & Facilities · Manager | C10: Administration, Legal & Secretarial | D10: Manager | E10: ROLE | F10: B2 | G10: Band B · People Manager · Corporate functions | H10: 1 | I10: H | J10: M | K10: M | L10: M | M10: L | N10: L | O10: L | P10: H | Q10: M | R10: M | S10: M | T10: L | U10: L | V10: L | AD10: =IF(W10<>"",W10,I10) -> H | AE10: =IF(X10<>"",X10,J10) -> M | AF10: =IF(Y10<>"",Y10,K10) -> M | AG10: =IF(Z10<>"",Z10,L10) -> M | AH10: =IF(AA10<>"",AA10,M10) -> L | AI10: =IF(AB10<>"",AB10,N10) -> L | AJ10: =IF(AC10<>"",AC10,O10) -> L | AK10: =COUNTA(W10:AC10) -> 0
A11: R003 | B11: Administration & Facilities · Manager | C11: Administration, Legal & Secretarial | D11: Manager | E11: level | F11: B2 | G11: Manager | H11: 1 | AL11: Works at B1: Domain specialist work | AM11: Hardest problems in the domain · in this role: Administration | AN11: Works at B3: Sets standards for a practice; cross-team problems | AO11: Works at B1: Technical / QC / client calls for the domain | AP11: Allocates people and sets team priorities | AQ11: Works at B3: Commercial / strategic calls for the unit | AR11: Works at B1: A domain or a small team | AS11: One team or a client portfolio | AT11: Works at B3: Several teams or a practice | AU11: Works at B1: IC: mentors and reviews · People: hands-on team lead of 3–5 | AV11: IC: guides others in the domain · People: manages a team of 6+ | AW11: Works at B3: IC: leads a practice · People: team leads / managers report in | AX11: Works at B1: Moves a module's, product area's or client account's results | AY11: Visible effect on a team's or client portfolio's revenue, quality or compliance | AZ11: Works at B3: Shapes the results of a practice or several teams | BA11: Less than 6–8 yrs | BB11: 6–8 yrs · market 6–10 yrs | BC11: More than 6–8 yrs | BD11: Below: Graduate + relevant qualification or certification preferred | BE11: Graduate or postgraduate; professional qualification preferred · licence-to-practise roles: CA, CS, CMA or LLB as the role needs | BF11: Above: Postgraduate or professional qualification preferred
A12: R004 | B12: Company Secretarial & Legal · IC | C12: Administration, Legal & Secretarial | D12: IC | E12: ROLE | F12: A1 · A2 · A3 | G12: Band A · all tracks · Corporate functions | H12: 2 | I12: H | J12: M | K12: M | L12: L | M12: L | N12: L | O12: M | P12: H | Q12: M | R12: M | S12: L | T12: L | U12: L | V12: L | AD12: =IF(W12<>"",W12,I12) -> H | AE12: =IF(X12<>"",X12,J12) -> M | AF12: =IF(Y12<>"",Y12,K12) -> M | AG12: =IF(Z12<>"",Z12,L12) -> L | AH12: =IF(AA12<>"",AA12,M12) -> L | AI12: =IF(AB12<>"",AB12,N12) -> L | AJ12: =IF(AC12<>"",AC12,O12) -> M | AK12: =COUNTA(W12:AC12) -> 0
A13: R004 | B13: Company Secretarial & Legal · IC | C13: Administration, Legal & Secretarial | D13: IC | E13: level | F13: A3 | G13: Senior Secretarial Executive | H13: 1 | AL13: Works at A2: Standard work of the discipline | AM13: Varied and non-standard work; handles exceptions · in this role: Secretarial · Legal | AN13: Works at B1: Domain specialist work | AO13: Works at A2: Chooses own approach within standards | AP13: Technical / QC / client calls on own work | AQ13: Works at B1: Technical / QC / client calls for the domain | AR13: Works at A2: Own deliverables · accuracy, TAT | AS13: A module / process, or work with client or regulatory consequences | AT13: Works at B1: A domain or a small team | AU13: Works at A2: contributes alone; guides others only informally | AV13: Helps peers and newer people informally · None · guides 1–3 juniors informally | AW13: Works at B1: IC: mentors and reviews · People: hands-on team lead of 3–5 | AX13: Works at A2: Own deliverables feed a team's output and turnaround | AY13: A process or client deliverable depends on this work | AZ13: Works at B1: Moves a module's, product area's or client account's results | BA13: Less than 2–4 yrs | BB13: 2–4 yrs · market 2–5 yrs | BC13: More than 2–4 yrs | BD13: Below: Graduate · or diploma with experience | BE13: Graduate; relevant certification preferred · licence-to-practise roles: CA, CS, CMA or LLB as the role needs | BF13: Above: Graduate + relevant qualification or certification preferred
A14: R004 | B14: Company Secretarial & Legal · IC | C14: Administration, Legal & Secretarial | D14: IC | E14: level | F14: A2 | G14: — no one at this level today | H14: 0 | AL14: Works at A1: Learning; follows worked examples | AM14: Standard work of the discipline | AN14: Works at A3: Varied and non-standard work; handles exceptions | AO14: Works at A1: Needs approval / close guidance | AP14: Chooses own approach within standards | AQ14: Works at A3: Technical / QC / client calls on own work | AR14: Works at A1: Learning tasks | AS14: Own deliverables · accuracy, TAT | AT14: Works at A3: A module / process, or work with client or regulatory consequences | AU14: Works at A1: contributes alone; guides others only informally | AV14: Helps peers and newer people informally · No direct reports | AW14: Works at A3: Not scored in Band A | AX14: Works at A1: Learning; little direct effect on business results yet | AY14: Own deliverables feed a team's output and turnaround | AZ14: Works at A3: A process or client deliverable depends on this work | BA14: Less than 0–2 yrs | BB14: 0–2 yrs · market 0–3 yrs | BC14: More than 0–2 yrs | BD14: Below: Pursuing or completed graduation / diploma | BE14: Graduate · or diploma with experience · licence-to-practise roles: CA, CS, CMA or LLB as the role needs | BF14: Above: Graduate; relevant certification preferred
A15: R004 | B15: Company Secretarial & Legal · IC | C15: Administration, Legal & Secretarial | D15: IC | E15: level | F15: A1 | G15: Intern | H15: 1 | AL15: Not yet at the entry standard | AM15: Learning; follows worked examples · in this role: Secretarial · Legal | AN15: Works at A2: Standard work of the discipline | AO15: Not yet at the entry standard | AP15: Needs approval / close guidance | AQ15: Works at A2: Chooses own approach within standards | AR15: Not yet at the entry standard | AS15: Learning tasks | AT15: Works at A2: Own deliverables · accuracy, TAT | AU15: Not yet at the entry standard | AV15: Helps peers and newer people informally · No direct reports | AW15: Works at A2: Not scored in Band A | AX15: Not yet at the entry standard | AY15: Learning; little direct effect on business results yet | AZ15: Works at A2: Own deliverables feed a team's output and turnaround | BA15: Less than Intern / trainee · first year | BB15: Intern / trainee · first year · market — yrs | BC15: More than Intern / trainee · first year | BD15: Still studying | BE15: Pursuing or completed graduation / diploma · licence-to-practise roles: CA, CS, CMA or LLB as the role needs | BF15: Above: Graduate · or diploma with experience
A16: R005 | B16: Business Analysis · IC | C16: Business Analysis | D16: IC | E16: ROLE | F16: A1 · A2 · A3 · B1 · B2 · B3 · C1 | G16: Band A · all tracks · Technology & engineering | H16: 27 | I16: H | J16: M | K16: L | L16: L | M16: L | N16: L | O16: L | P16: H | Q16: M | R16: M | S16: L | T16: L | U16: L | V16: L | AD16: =IF(W16<>"",W16,I16) -> H | AE16: =IF(X16<>"",X16,J16) -> M | AF16: =IF(Y16<>"",Y16,K16) -> L | AG16: =IF(Z16<>"",Z16,L16) -> L | AH16: =IF(AA16<>"",AA16,M16) -> L | AI16: =IF(AB16<>"",AB16,N16) -> L | AJ16: =IF(AC16<>"",AC16,O16) -> L | AK16: =COUNTA(W16:AC16) -> 0
A17: R005 | B17: Business Analysis · IC | C17: Business Analysis | D17: IC | E17: level | F17: C1 | G17: Principal – Business Analysis | H17: 1 | AL17: Works at B3: Sets standards for a practice; cross-team problems | AM17: Ambiguous, cross-product problems | AN17: Works at C2: Function-wide or company-wide problems; creates methods and standards | AO17: Works at B3: Commercial / strategic calls for the unit | AP17: Sets direction for a sub-function or domain | AQ17: Works at C2: Sets direction for a function | AR17: Works at B3: Several teams or a practice | AS17: Sub-function results or domain quality across products | AT17: Works at C2: Function results, budget and risk | AU17: Works at B3: IC: leads a practice · People: team leads / managers report in | AV17: Leads managers or a community of practice | AW17: Works at C2: Leads a function; shapes functional strategy | AX17: Works at B3: Shapes the results of a practice or several teams | AY17: Changes results across a sub-function or across products | AZ17: Works at C2: Drives a function's or department's results and costs | BA17: Less than 10–13 yrs | BB17: 10–13 yrs · market 12–17 yrs | BC17: More than 10–13 yrs | BD17: Below: Postgraduate or professional qualification preferred | BE17: Postgraduate / professional qualification preferred | BF17: Above: Postgraduate / professional qualification preferred
A18: R005 | B18: Business Analysis · IC | C18: Business Analysis | D18: IC | E18: level | F18: B3 | G18: — no one at this level today | H18: 0 | AL18: Works at B2: Hardest problems in the domain | AM18: Sets standards for a practice; cross-team problems | AN18: Works at C1: Ambiguous, cross-product problems | AO18: Works at B2: Allocates people and sets team priorities | AP18: Commercial / strategic calls for the unit | AQ18: Works at C1: Sets direction for a sub-function or domain | AR18: Works at B2: One team or a client portfolio | AS18: Several teams or a practice | AT18: Works at C1: Sub-function results or domain quality across products | AU18: Works at B2: IC: guides others in the domain · People: manages a team of 6+ | AV18: IC: leads a practice · People: team leads / managers report in | AW18: Works at C1: Leads managers or a community of practice | AX18: Works at B2: Visible effect on a team's or client portfolio's revenue, quality or compliance | AY18: Shapes the results of a practice or several teams | AZ18: Works at C1: Changes results across a sub-function or across products | BA18: Less than 8–10 yrs | BB18: 8–10 yrs · market 8–13 yrs | BC18: More than 8–10 yrs | BD18: Below: Graduate or postgraduate; professional qualification preferred | BE18: Postgraduate or professional qualification preferred | BF18: Above: Postgraduate / professional qualification preferred
A19: R005 | B19: Business Analysis · IC | C19: Business Analysis | D19: IC | E19: level | F19: B2 | G19: — no one at this level today | H19: 0 | AL19: Works at B1: Domain specialist work | AM19: Hardest problems in the domain · in this role: Business Analysis · Documentation · Requirement analysis · Stakeholder Management · communication · XBRL · Requirement Elicitation · … | AN19: Works at B3: Sets standards for a practice; cross-team problems | AO19: Works at B1: Technical / QC / client calls for the domain | AP19: Allocates people and sets team priorities | AQ19: Works at B3: Commercial / strategic calls for the unit | AR19: Works at B1: A domain or a small team | AS19: One team or a client portfolio | AT19: Works at B3: Several teams or a practice | AU19: Works at B1: IC: mentors and reviews · People: hands-on team lead of 3–5 | AV19: IC: guides others in the domain · People: manages a team of 6+ | AW19: Works at B3: IC: leads a practice · People: team leads / managers report in | AX19: Works at B1: Moves a module's, product area's or client account's results | AY19: Visible effect on a team's or client portfolio's revenue, quality or compliance | AZ19: Works at B3: Shapes the results of a practice or several teams | BA19: Less than 6–8 yrs | BB19: 6–8 yrs · market 6–10 yrs | BC19: More than 6–8 yrs | BD19: Below: Graduate + relevant qualification or certification preferred | BE19: Graduate or postgraduate; professional qualification preferred | BF19: Above: Postgraduate or professional qualification preferred
A20: R005 | B20: Business Analysis · IC | C20: Business Analysis | D20: IC | E20: level | F20: B1 | G20: Business Analysis Specialist | H20: 5 | AL20: Works at A3: Varied and non-standard work; handles exceptions | AM20: Domain specialist work · in this role: Business Analysis | AN20: Works at B2: Hardest problems in the domain | AO20: Works at A3: Technical / QC / client calls on own work | AP20: Technical / QC / client calls for the domain | AQ20: Works at B2: Allocates people and sets team priorities | AR20: Works at A3: A module / process, or work with client or regulatory consequences | AS20: A domain or a small team · KRA themes: Common themes in manager-set KRAs: releases · satisfaction · delivery · assigned · uat · requirement | AT20: Works at B2: One team or a client portfolio | AU20: Works at A3: contributes alone; guides others only informally | AV20: IC: mentors and reviews · People: hands-on team lead of 3–5 | AW20: Works at B2: IC: guides others in the domain · People: manages a team of 6+ | AX20: Works at A3: A process or client deliverable depends on this work | AY20: Moves a module's, product area's or client account's results | AZ20: Works at B2: Visible effect on a team's or client portfolio's revenue, quality or compliance | BA20: Less than 4–6 yrs | BB20: 4–6 yrs · market 4–8 yrs | BC20: More than 4–6 yrs | BD20: Below: Graduate; relevant certification preferred | BE20: Graduate + relevant qualification or certification preferred | BF20: Above: Graduate or postgraduate; professional qualification preferred
A21: R005 | B21: Business Analysis · IC | C21: Business Analysis | D21: IC | E21: level | F21: A3 | G21: Senior Business Analyst | H21: 18 | AL21: Works at A2: Standard work of the discipline | AM21: Varied and non-standard work; handles exceptions · in this role: Business Analysis · Documentation · Stakeholder management · Requirement analysis · communication · Communication skills | AN21: Works at B1: Domain specialist work | AO21: Works at A2: Chooses own approach within standards | AP21: Technical / QC / client calls on own work | AQ21: Works at B1: Technical / QC / client calls for the domain | AR21: Works at A2: Own deliverables · accuracy, TAT | AS21: A module / process, or work with client or regulatory consequences · KRA themes: Common themes in manager-set KRAs: delivery · assigned · uat · project · requests · satisfaction | AT21: Works at B1: A domain or a small team | AU21: Works at A2: contributes alone; guides others only informally | AV21: Helps peers and newer people informally · None · guides 1–3 juniors informally | AW21: Works at B1: IC: mentors and reviews · People: hands-on team lead of 3–5 | AX21: Works at A2: Own deliverables feed a team's output and turnaround | AY21: A process or client deliverable depends on this work | AZ21: Works at B1: Moves a module's, product area's or client account's results | BA21: Less than 2–4 yrs | BB21: 2–4 yrs · market 2–5 yrs | BC21: More than 2–4 yrs | BD21: Below: Graduate · or diploma with experience | BE21: Graduate; relevant certification preferred | BF21: Above: Graduate + relevant qualification or certification preferred
A22: R005 | B22: Business Analysis · IC | C22: Business Analysis | D22: IC | E22: level | F22: A2 | G22: Business Analyst | H22: 2 | AL22: Works at A1: Learning; follows worked examples | AM22: Standard work of the discipline · in this role: Business Analysis · Documentation · Requirement analysis · Stakeholder Management · communication · XBRL · Requirement Elicitation · … | AN22: Works at A3: Varied and non-standard work; handles exceptions | AO22: Works at A1: Needs approval / close guidance | AP22: Chooses own approach within standards | AQ22: Works at A3: Technical / QC / client calls on own work | AR22: Works at A1: Learning tasks | AS22: Own deliverables · accuracy, TAT | AT22: Works at A3: A module / process, or work with client or regulatory consequences | AU22: Works at A1: contributes alone; guides others only informally | AV22: Helps peers and newer people informally · No direct reports | AW22: Works at A3: Not scored in Band A | AX22: Works at A1: Learning; little direct effect on business results yet | AY22: Own deliverables feed a team's output and turnaround | AZ22: Works at A3: A process or client deliverable depends on this work | BA22: Less than 0–2 yrs | BB22: 0–2 yrs · market 0–3 yrs | BC22: More than 0–2 yrs | BD22: Below: Pursuing or completed graduation / diploma | BE22: Graduate · or diploma with experience | BF22: Above: Graduate; relevant certification preferred
A23: R005 | B23: Business Analysis · IC | C23: Business Analysis | D23: IC | E23: level | F23: A1 | G23: Trainee Business Analyst | H23: 1 | AL23: Not yet at the entry standard | AM23: Learning; follows worked examples · in this role: Business Analysis · Documentation · Requirement analysis · Stakeholder Management · communication · XBRL · Requirement Elicitation · … | AN23: Works at A2: Standard work of the discipline | AO23: Not yet at the entry standard | AP23: Needs approval / close guidance | AQ23: Works at A2: Chooses own approach within standards | AR23: Not yet at the entry standard | AS23: Learning tasks | AT23: Works at A2: Own deliverables · accuracy, TAT | AU23: Not yet at the entry standard | AV23: Helps peers and newer people informally · No direct reports | AW23: Works at A2: Not scored in Band A | AX23: Not yet at the entry standard | AY23: Learning; little direct effect on business results yet | AZ23: Works at A2: Own deliverables feed a team's output and turnaround | BA23: Less than Intern / trainee · first year | BB23: Intern / trainee · first year · market — yrs | BC23: More than Intern / trainee · first year | BD23: Still studying | BE23: Pursuing or completed graduation / diploma | BF23: Above: Graduate · or diploma with experience
A24: R006 | B24: Business Analysis · Manager | C24: Business Analysis | D24: Manager | E24: ROLE | F24: B1 | G24: Band B · People Manager · Technology & engineering | H24: 2 | I24: H | J24: M | K24: L | L24: M | M24: L | N24: L | O24: L | P24: H | Q24: M | R24: M | S24: M | T24: L | U24: L | V24: L | AD24: =IF(W24<>"",W24,I24) -> H | AE24: =IF(X24<>"",X24,J24) -> M | AF24: =IF(Y24<>"",Y24,K24) -> L | AG24: =IF(Z24<>"",Z24,L24) -> M | AH24: =IF(AA24<>"",AA24,M24) -> L | AI24: =IF(AB24<>"",AB24,N24) -> L | AJ24: =IF(AC24<>"",AC24,O24) -> L | AK24: =COUNTA(W24:AC24) -> 0
A25: R006 | B25: Business Analysis · Manager | C25: Business Analysis | D25: Manager | E25: level | F25: B1 | G25: Team Lead | H25: 2 | AL25: Works at A3: Varied and non-standard work; handles exceptions | AM25: Domain specialist work · in this role: Business Analysis | AN25: Works at B2: Hardest problems in the domain | AO25: Works at A3: Technical / QC / client calls on own work | AP25: Technical / QC / client calls for the domain | AQ25: Works at B2: Allocates people and sets team priorities | AR25: Works at A3: A module / process, or work with client or regulatory consequences | AS25: A domain or a small team · KRA themes: Common themes in manager-set KRAs: releases · satisfaction · delivery · assigned · uat · requirement | AT25: Works at B2: One team or a client portfolio | AU25: Works at A3: contributes alone; guides others only informally | AV25: IC: mentors and reviews · People: hands-on team lead of 3–5 | AW25: Works at B2: IC: guides others in the domain · People: manages a team of 6+ | AX25: Works at A3: A process or client deliverable depends on this work | AY25: Moves a module's, product area's or client account's results | AZ25: Works at B2: Visible effect on a team's or client portfolio's revenue, quality or compliance | BA25: Less than 4–6 yrs | BB25: 4–6 yrs · market 4–8 yrs | BC25: More than 4–6 yrs | BD25: Below: Graduate; relevant certification preferred | BE25: Graduate + relevant qualification or certification preferred | BF25: Above: Graduate or postgraduate; professional qualification preferred
A26: R007 | B26: Professional Services Leadership · Manager | C26: Consulting & Professional Services | D26: Manager | E26: ROLE | F26: C1 | G26: Band C · Head / manager · Service delivery & data operations | H26: 1 | I26: H | J26: M | K26: M | L26: M | M26: L | N26: L | O26: L | P26: H | Q26: M | R26: M | S26: M | T26: L | U26: L | V26: L | AD26: =IF(W26<>"",W26,I26) -> H | AE26: =IF(X26<>"",X26,J26) -> M | AF26: =IF(Y26<>"",Y26,K26) -> M | AG26: =IF(Z26<>"",Z26,L26) -> M | AH26: =IF(AA26<>"",AA26,M26) -> L | AI26: =IF(AB26<>"",AB26,N26) -> L | AJ26: =IF(AC26<>"",AC26,O26) -> L | AK26: =COUNTA(W26:AC26) -> 0
A27: R007 | B27: Professional Services Leadership · Manager | C27: Consulting & Professional Services | D27: Manager | E27: level | F27: C1 | G27: Associate Head | H27: 1 | AL27: Works at B3: Sets standards for a practice; cross-team problems | AM27: Ambiguous, cross-product problems · in this role: XBRL Domain | AN27: Works at C2: Function-wide or company-wide problems; creates methods and standards | AO27: Works at B3: Commercial / strategic calls for the unit | AP27: Sets direction for a sub-function or domain | AQ27: Works at C2: Sets direction for a function | AR27: Works at B3: Several teams or a practice | AS27: Sub-function results or domain quality across products | AT27: Works at C2: Function results, budget and risk | AU27: Works at B3: IC: leads a practice · People: team leads / managers report in | AV27: Leads managers or a community of practice | AW27: Works at C2: Leads a function; shapes functional strategy | AX27: Works at B3: Shapes the results of a practice or several teams | AY27: Changes results across a sub-function or across products | AZ27: Works at C2: Drives a function's or department's results and costs | BA27: Less than 10–13 yrs | BB27: 10–13 yrs · market 12–17 yrs | BC27: More than 10–13 yrs | BD27: Below: Postgraduate or professional qualification preferred | BE27: Postgraduate / professional qualification preferred | BF27: Above: Postgraduate / professional qualification preferred
A28: R008 | B28: Service Delivery Operations · IC | C28: Consulting & Professional Services | D28: IC | E28: ROLE | F28: A3 | G28: Band A · all tracks · Service delivery & data operations | H28: 2 | I28: H | J28: M | K28: M | L28: L | M28: L | N28: L | O28: L | P28: H | Q28: M | R28: M | S28: L | T28: L | U28: L | V28: L | AD28: =IF(W28<>"",W28,I28) -> H | AE28: =IF(X28<>"",X28,J28) -> M | AF28: =IF(Y28<>"",Y28,K28) -> M | AG28: =IF(Z28<>"",Z28,L28) -> L | AH28: =IF(AA28<>"",AA28,M28) -> L | AI28: =IF(AB28<>"",AB28,N28) -> L | AJ28: =IF(AC28<>"",AC28,O28) -> L | AK28: =COUNTA(W28:AC28) -> 0
A29: R008 | B29: Service Delivery Operations · IC | C29: Consulting & Professional Services | D29: IC | E29: level | F29: A3 | G29: Senior Service Delivery Analyst | H29: 2 | AL29: Works at A2: Standard work of the discipline | AM29: Varied and non-standard work; handles exceptions · in this role: XBRL Domain | AN29: Works at B1: Domain specialist work | AO29: Works at A2: Chooses own approach within standards | AP29: Technical / QC / client calls on own work | AQ29: Works at B1: Technical / QC / client calls for the domain | AR29: Works at A2: Own deliverables · accuracy, TAT | AS29: A module / process, or work with client or regulatory consequences | AT29: Works at B1: A domain or a small team | AU29: Works at A2: contributes alone; guides others only informally | AV29: Helps peers and newer people informally · None · guides 1–3 juniors informally | AW29: Works at B1: IC: mentors and reviews · People: hands-on team lead of 3–5 | AX29: Works at A2: Own deliverables feed a team's output and turnaround | AY29: A process or client deliverable depends on this work | AZ29: Works at B1: Moves a module's, product area's or client account's results | BA29: Less than 2–4 yrs | BB29: 2–4 yrs · market 2–5 yrs | BC29: More than 2–4 yrs | BD29: Below: Graduate · or diploma with experience | BE29: Graduate; relevant certification preferred | BF29: Above: Graduate + relevant qualification or certification preferred
A30: R009 | B30: Service Delivery Operations · Manager | C30: Consulting & Professional Services | D30: Manager | E30: ROLE | F30: B2 | G30: Band B · People Manager · Service delivery & data operations | H30: 1 | I30: H | J30: M | K30: M | L30: M | M30: L | N30: L | O30: L | P30: H | Q30: M | R30: M | S30: M | T30: L | U30: L | V30: L | AD30: =IF(W30<>"",W30,I30) -> H | AE30: =IF(X30<>"",X30,J30) -> M | AF30: =IF(Y30<>"",Y30,K30) -> M | AG30: =IF(Z30<>"",Z30,L30) -> M | AH30: =IF(AA30<>"",AA30,M30) -> L | AI30: =IF(AB30<>"",AB30,N30) -> L | AJ30: =IF(AC30<>"",AC30,O30) -> L | AK30: =COUNTA(W30:AC30) -> 0
A31: R009 | B31: Service Delivery Operations · Manager | C31: Consulting & Professional Services | D31: Manager | E31: level | F31: B2 | G31: Senior Manager | H31: 1 | AL31: Works at B1: Domain specialist work | AM31: Hardest problems in the domain · in this role: XBRL Domain | AN31: Works at B3: Sets standards for a practice; cross-team problems | AO31: Works at B1: Technical / QC / client calls for the domain | AP31: Allocates people and sets team priorities | AQ31: Works at B3: Commercial / strategic calls for the unit | AR31: Works at B1: A domain or a small team | AS31: One team or a client portfolio | AT31: Works at B3: Several teams or a practice | AU31: Works at B1: IC: mentors and reviews · People: hands-on team lead of 3–5 | AV31: IC: guides others in the domain · People: manages a team of 6+ | AW31: Works at B3: IC: leads a practice · People: team leads / managers report in | AX31: Works at B1: Moves a module's, product area's or client account's results | AY31: Visible effect on a team's or client portfolio's revenue, quality or compliance | AZ31: Works at B3: Shapes the results of a practice or several teams | BA31: Less than 6–8 yrs | BB31: 6–8 yrs · market 6–10 yrs | BC31: More than 6–8 yrs | BD31: Below: Graduate + relevant qualification or certification preferred | BE31: Graduate or postgraduate; professional qualification preferred | BF31: Above: Postgraduate or professional qualification preferred
A32: R010 | B32: Taxonomy Design & Regulatory Consulting · Consultant | C32: Consulting & Professional Services | D32: Consultant | E32: ROLE | F32: X1 | G32: Consultant · outside the ladder · Regulatory & domain consulting | H32: 1 | AD32: =IF(W32<>"",W32,I32) -> 0 | AE32: =IF(X32<>"",X32,J32) -> 0 | AF32: =IF(Y32<>"",Y32,K32) -> 0 | AG32: =IF(Z32<>"",Z32,L32) -> 0 | AH32: =IF(AA32<>"",AA32,M32) -> 0 | AI32: =IF(AB32<>"",AB32,N32) -> 0 | AJ32: =IF(AC32<>"",AC32,O32) -> 0 | AK32: =COUNTA(W32:AC32) -> 0
A33: R011 | B33: Taxonomy Design & Regulatory Consulting · IC | C33: Consulting & Professional Services | D33: IC | E33: ROLE | F33: A2 · A3 · B1 · B2 | G33: Band A · all tracks · Regulatory & domain consulting | H33: 22 | I33: H | J33: M | K33: M | L33: L | M33: L | N33: L | O33: L | P33: H | Q33: M | R33: M | S33: L | T33: L | U33: L | V33: L | AD33: =IF(W33<>"",W33,I33) -> H | AE33: =IF(X33<>"",X33,J33) -> M | AF33: =IF(Y33<>"",Y33,K33) -> M | AG33: =IF(Z33<>"",Z33,L33) -> L | AH33: =IF(AA33<>"",AA33,M33) -> L | AI33: =IF(AB33<>"",AB33,N33) -> L | AJ33: =IF(AC33<>"",AC33,O33) -> L | AK33: =COUNTA(W33:AC33) -> 0
A34: R011 | B34: Taxonomy Design & Regulatory Consulting · IC | C34: Consulting & Professional Services | D34: IC | E34: level | F34: B2 | G34: Senior Taxonomy Specialist | H34: 3 | AL34: Works at B1: Domain specialist work | AM34: Hardest problems in the domain · in this role: XBRL Domain | AN34: Works at B3: Sets standards for a practice; cross-team problems | AO34: Works at B1: Technical / QC / client calls for the domain | AP34: Allocates people and sets team priorities | AQ34: Works at B3: Commercial / strategic calls for the unit | AR34: Works at B1: A domain or a small team | AS34: One team or a client portfolio · KRA themes: Common themes in manager-set KRAs: ifile business · analyst contribute · resolve · domain delivery · serve analyst · milestones on-time | AT34: Works at B3: Several teams or a practice | AU34: Works at B1: IC: mentors and reviews · People: hands-on team lead of 3–5 | AV34: IC: guides others in the domain · People: manages a team of 6+ | AW34: Works at B3: IC: leads a practice · People: team leads / managers report in | AX34: Works at B1: Moves a module's, product area's or client account's results | AY34: Visible effect on a team's or client portfolio's revenue, quality or compliance | AZ34: Works at B3: Shapes the results of a practice or several teams | BA34: Less than 6–8 yrs | BB34: 6–8 yrs · market 6–10 yrs | BC34: More than 6–8 yrs | BD34: Below: Graduate + relevant qualification or certification preferred | BE34: Graduate or postgraduate; professional qualification preferred | BF34: Above: Postgraduate or professional qualification preferred
A35: R011 | B35: Taxonomy Design & Regulatory Consulting · IC | C35: Consulting & Professional Services | D35: IC | E35: level | F35: B1 | G35: Taxonomy Specialist | H35: 1 | AL35: Works at A3: Varied and non-standard work; handles exceptions | AM35: Domain specialist work · in this role: XBRL Domain | AN35: Works at B2: Hardest problems in the domain | AO35: Works at A3: Technical / QC / client calls on own work | AP35: Technical / QC / client calls for the domain | AQ35: Works at B2: Allocates people and sets team priorities | AR35: Works at A3: A module / process, or work with client or regulatory consequences | AS35: A domain or a small team · KRA themes: Common themes in manager-set KRAs: resolve · business · excel webform · deliver assigned · defect · critical | AT35: Works at B2: One team or a client portfolio | AU35: Works at A3: contributes alone; guides others only informally | AV35: IC: mentors and reviews · People: hands-on team lead of 3–5 | AW35: Works at B2: IC: guides others in the domain · People: manages a team of 6+ | AX35: Works at A3: A process or client deliverable depends on this work | AY35: Moves a module's, product area's or client account's results | AZ35: Works at B2: Visible effect on a team's or client portfolio's revenue, quality or compliance | BA35: Less than 4–6 yrs | BB35: 4–6 yrs · market 4–8 yrs | BC35: More than 4–6 yrs | BD35: Below: Graduate; relevant certification preferred | BE35: Graduate + relevant qualification or certification preferred | BF35: Above: Graduate or postgraduate; professional qualification preferred
A36: R011 | B36: Taxonomy Design & Regulatory Consulting · IC | C36: Consulting & Professional Services | D36: IC | E36: level | F36: A3 | G36: Senior Taxonomy Analyst | H36: 16 | AL36: Works at A2: Standard work of the discipline | AM36: Varied and non-standard work; handles exceptions · in this role: XBRL domain | AN36: Works at B1: Domain specialist work | AO36: Works at A2: Chooses own approach within standards | AP36: Technical / QC / client calls on own work | AQ36: Works at B1: Technical / QC / client calls for the domain | AR36: Works at A2: Own deliverables · accuracy, TAT | AS36: A module / process, or work with client or regulatory consequences · KRA themes: Common themes in manager-set KRAs: resolve · defect · deliver · complete · modules · testing | AT36: Works at B1: A domain or a small team | AU36: Works at A2: contributes alone; guides others only informally | AV36: Helps peers and newer people informally · None · guides 1–3 juniors informally | AW36: Works at B1: IC: mentors and reviews · People: hands-on team lead of 3–5 | AX36: Works at A2: Own deliverables feed a team's output and turnaround | AY36: A process or client deliverable depends on this work | AZ36: Works at B1: Moves a module's, product area's or client account's results | BA36: Less than 2–4 yrs | BB36: 2–4 yrs · market 2–5 yrs | BC36: More than 2–4 yrs | BD36: Below: Graduate · or diploma with experience | BE36: Graduate; relevant certification preferred | BF36: Above: Graduate + relevant qualification or certification preferred
A37: R011 | B37: Taxonomy Design & Regulatory Consulting · IC | C37: Consulting & Professional Services | D37: IC | E37: level | F37: A2 | G37: Taxonomy Analyst | H37: 2 | AL37: Works at A1: Learning; follows worked examples | AM37: Standard work of the discipline · in this role: XBRL domain · XBRL specifications · analytical skills · Domain knowledge · XBRL · XBRl knowledge · Academic strength | AN37: Works at A3: Varied and non-standard work; handles exceptions | AO37: Works at A1: Needs approval / close guidance | AP37: Chooses own approach within standards | AQ37: Works at A3: Technical / QC / client calls on own work | AR37: Works at A1: Learning tasks | AS37: Own deliverables · accuracy, TAT · KRA themes: Common themes in manager-set KRAs: complete iris · resolve · cycle full · accuracy targets · maintained · logs document | AT37: Works at A3: A module / process, or work with client or regulatory consequences | AU37: Works at A1: contributes alone; guides others only informally | AV37: Helps peers and newer people informally · No direct reports | AW37: Works at A3: Not scored in Band A | AX37: Works at A1: Learning; little direct effect on business results yet | AY37: Own deliverables feed a team's output and turnaround | AZ37: Works at A3: A process or client deliverable depends on this work | BA37: Less than 0–2 yrs | BB37: 0–2 yrs · market 0–3 yrs | BC37: More than 0–2 yrs | BD37: Below: Pursuing or completed graduation / diploma | BE37: Graduate · or diploma with experience | BF37: Above: Graduate; relevant certification preferred
A38: R012 | B38: Taxonomy Design & Regulatory Consulting · Manager | C38: Consulting & Professional Services | D38: Manager | E38: ROLE | F38: B2 | G38: Band B · People Manager · Regulatory & domain consulting | H38: 2 | I38: H | J38: M | K38: M | L38: M | M38: L | N38: L | O38: L | P38: H | Q38: M | R38: M | S38: M | T38: L | U38: L | V38: L | AD38: =IF(W38<>"",W38,I38) -> H | AE38: =IF(X38<>"",X38,J38) -> M | AF38: =IF(Y38<>"",Y38,K38) -> M | AG38: =IF(Z38<>"",Z38,L38) -> M | AH38: =IF(AA38<>"",AA38,M38) -> L | AI38: =IF(AB38<>"",AB38,N38) -> L | AJ38: =IF(AC38<>"",AC38,O38) -> L | AK38: =COUNTA(W38:AC38) -> 0
A39: R012 | B39: Taxonomy Design & Regulatory Consulting · Manager | C39: Consulting & Professional Services | D39: Manager | E39: level | F39: B2 | G39: Senior Manager | H39: 2 | AL39: Works at B1: Domain specialist work | AM39: Hardest problems in the domain · in this role: XBRL Domain | AN39: Works at B3: Sets standards for a practice; cross-team problems | AO39: Works at B1: Technical / QC / client calls for the domain | AP39: Allocates people and sets team priorities | AQ39: Works at B3: Commercial / strategic calls for the unit | AR39: Works at B1: A domain or a small team | AS39: One team or a client portfolio · KRA themes: Common themes in manager-set KRAs: ifile business · analyst contribute · resolve · domain delivery · serve analyst · milestones on-time | AT39: Works at B3: Several teams or a practice | AU39: Works at B1: IC: mentors and reviews · People: hands-on team lead of 3–5 | AV39: IC: guides others in the domain · People: manages a team of 6+ | AW39: Works at B3: IC: leads a practice · People: team leads / managers report in | AX39: Works at B1: Moves a module's, product area's or client account's results | AY39: Visible effect on a team's or client portfolio's revenue, quality or compliance | AZ39: Works at B3: Shapes the results of a practice or several teams | BA39: Less than 6–8 yrs | BB39: 6–8 yrs · market 6–10 yrs | BC39: More than 6–8 yrs | BD39: Below: Graduate + relevant qualification or certification preferred | BE39: Graduate or postgraduate; professional qualification preferred | BF39: Above: Postgraduate or professional qualification preferred
A40: R013 | B40: XBRL Tagging, Conversion & Filing · IC | C40: Consulting & Professional Services | D40: IC | E40: ROLE | F40: A2 · A3 · B1 | G40: Band A · all tracks · Service delivery & data operations | H40: 52 | I40: H | J40: M | K40: M | L40: L | M40: L | N40: L | O40: L | P40: H | Q40: M | R40: M | S40: L | T40: L | U40: L | V40: L | AD40: =IF(W40<>"",W40,I40) -> H | AE40: =IF(X40<>"",X40,J40) -> M | AF40: =IF(Y40<>"",Y40,K40) -> M | AG40: =IF(Z40<>"",Z40,L40) -> L | AH40: =IF(AA40<>"",AA40,M40) -> L | AI40: =IF(AB40<>"",AB40,N40) -> L | AJ40: =IF(AC40<>"",AC40,O40) -> L | AK40: =COUNTA(W40:AC40) -> 0
A41: R013 | B41: XBRL Tagging, Conversion & Filing · IC | C41: Consulting & Professional Services | D41: IC | E41: level | F41: B1 | G41: XBRL Specialist | H41: 4 | AL41: Works at A3: Varied and non-standard work; handles exceptions | AM41: Domain specialist work · in this role: XBRL Domain · Attention to detail · Advanced XBRL Mapping knowledge · Different region Taxonomy Knowledge · Financial Reporting Standards … | AN41: Works at B2: Hardest problems in the domain | AO41: Works at A3: Technical / QC / client calls on own work | AP41: Technical / QC / client calls for the domain | AQ41: Works at B2: Allocates people and sets team priorities | AR41: Works at A3: A module / process, or work with client or regulatory consequences | AS41: A domain or a small team | AT41: Works at B2: One team or a client portfolio | AU41: Works at A3: contributes alone; guides others only informally | AV41: IC: mentors and reviews · People: hands-on team lead of 3–5 | AW41: Works at B2: IC: guides others in the domain · People: manages a team of 6+ | AX41: Works at A3: A process or client deliverable depends on this work | AY41: Moves a module's, product area's or client account's results | AZ41: Works at B2: Visible effect on a team's or client portfolio's revenue, quality or compliance | BA41: Less than 4–6 yrs | BB41: 4–6 yrs · market 4–8 yrs | BC41: More than 4–6 yrs | BD41: Below: Graduate; relevant certification preferred | BE41: Graduate + relevant qualification or certification preferred | BF41: Above: Graduate or postgraduate; professional qualification preferred
A42: R013 | B42: XBRL Tagging, Conversion & Filing · IC | C42: Consulting & Professional Services | D42: IC | E42: level | F42: A3 | G42: Senior Financial Analyst | H42: 44 | AL42: Works at A2: Standard work of the discipline | AM42: Varied and non-standard work; handles exceptions · in this role: XBRL Domain · Taxonomy knowledge · attention to detail · validation · Problem-solving · filing procedures · XBRL concepts · QC | AN42: Works at B1: Domain specialist work | AO42: Works at A2: Chooses own approach within standards | AP42: Technical / QC / client calls on own work | AQ42: Works at B1: Technical / QC / client calls for the domain | AR42: Works at A2: Own deliverables · accuracy, TAT | AS42: A module / process, or work with client or regulatory consequences · KRA themes: Common themes in manager-set KRAs: resolve · full · coverage · cycles · defect · xbrl | AT42: Works at B1: A domain or a small team | AU42: Works at A2: contributes alone; guides others only informally | AV42: Helps peers and newer people informally · None · guides 1–3 juniors informally | AW42: Works at B1: IC: mentors and reviews · People: hands-on team lead of 3–5 | AX42: Works at A2: Own deliverables feed a team's output and turnaround | AY42: A process or client deliverable depends on this work | AZ42: Works at B1: Moves a module's, product area's or client account's results | BA42: Less than 2–4 yrs | BB42: 2–4 yrs · market 2–5 yrs | BC42: More than 2–4 yrs | BD42: Below: Graduate · or diploma with experience | BE42: Graduate; relevant certification preferred | BF42: Above: Graduate + relevant qualification or certification preferred
A43: R013 | B43: XBRL Tagging, Conversion & Filing · IC | C43: Consulting & Professional Services | D43: IC | E43: level | F43: A2 | G43: Financial Analyst | H43: 4 | AL43: Works at A1: Learning; follows worked examples | AM43: Standard work of the discipline · in this role: XBRL Domain | AN43: Works at A3: Varied and non-standard work; handles exceptions | AO43: Works at A1: Needs approval / close guidance | AP43: Chooses own approach within standards | AQ43: Works at A3: Technical / QC / client calls on own work | AR43: Works at A1: Learning tasks | AS43: Own deliverables · accuracy, TAT · KRA themes: Common themes in manager-set KRAs: complete iris · resolve · cycle full · accuracy targets · maintained · logs document | AT43: Works at A3: A module / process, or work with client or regulatory consequences | AU43: Works at A1: contributes alone; guides others only informally | AV43: Helps peers and newer people informally · No direct reports | AW43: Works at A3: Not scored in Band A | AX43: Works at A1: Learning; little direct effect on business results yet | AY43: Own deliverables feed a team's output and turnaround | AZ43: Works at A3: A process or client deliverable depends on this work | BA43: Less than 0–2 yrs | BB43: 0–2 yrs · market 0–3 yrs | BC43: More than 0–2 yrs | BD43: Below: Pursuing or completed graduation / diploma | BE43: Graduate · or diploma with experience | BF43: Above: Graduate; relevant certification preferred
A44: R014 | B44: XBRL Tagging, Conversion & Filing · Manager | C44: Consulting & Professional Services | D44: Manager | E44: ROLE | F44: B1 · B2 · B3 · C1 | G44: Band B · People Manager · Service delivery & data operations | H44: 6 | I44: H | J44: M | K44: M | L44: M | M44: L | N44: L | O44: L | P44: H | Q44: M | R44: M | S44: M | T44: L | U44: L | V44: L | AD44: =IF(W44<>"",W44,I44) -> H | AE44: =IF(X44<>"",X44,J44) -> M | AF44: =IF(Y44<>"",Y44,K44) -> M | AG44: =IF(Z44<>"",Z44,L44) -> M | AH44: =IF(AA44<>"",AA44,M44) -> L | AI44: =IF(AB44<>"",AB44,N44) -> L | AJ44: =IF(AC44<>"",AC44,O44) -> L | AK44: =COUNTA(W44:AC44) -> 0
A45: R014 | B45: XBRL Tagging, Conversion & Filing · Manager | C45: Consulting & Professional Services | D45: Manager | E45: level | F45: C1 | G45: Associate Head – XBRL Tagging, Conversion & Filing | H45: 1 | AL45: Works at B3: Sets standards for a practice; cross-team problems | AM45: Ambiguous, cross-product problems | AN45: Works at C2: Function-wide or company-wide problems; creates methods and standards | AO45: Works at B3: Commercial / strategic calls for the unit | AP45: Sets direction for a sub-function or domain | AQ45: Works at C2: Sets direction for a function | AR45: Works at B3: Several teams or a practice | AS45: Sub-function results or domain quality across products | AT45: Works at C2: Function results, budget and risk | AU45: Works at B3: IC: leads a practice · People: team leads / managers report in | AV45: Leads managers or a community of practice | AW45: Works at C2: Leads a function; shapes functional strategy | AX45: Works at B3: Shapes the results of a practice or several teams | AY45: Changes results across a sub-function or across products | AZ45: Works at C2: Drives a function's or department's results and costs | BA45: Less than 10–13 yrs | BB45: 10–13 yrs · market 12–17 yrs | BC45: More than 10–13 yrs | BD45: Below: Postgraduate or professional qualification preferred | BE45: Postgraduate / professional qualification preferred | BF45: Above: Postgraduate / professional qualification preferred
A46: R014 | B46: XBRL Tagging, Conversion & Filing · Manager | C46: Consulting & Professional Services | D46: Manager | E46: level | F46: B3 | G46: — no one at this level today | H46: 0 | AL46: Works at B2: Hardest problems in the domain | AM46: Sets standards for a practice; cross-team problems | AN46: Works at C1: Ambiguous, cross-product problems | AO46: Works at B2: Allocates people and sets team priorities | AP46: Commercial / strategic calls for the unit | AQ46: Works at C1: Sets direction for a sub-function or domain | AR46: Works at B2: One team or a client portfolio | AS46: Several teams or a practice | AT46: Works at C1: Sub-function results or domain quality across products | AU46: Works at B2: IC: guides others in the domain · People: manages a team of 6+ | AV46: IC: leads a practice · People: team leads / managers report in | AW46: Works at C1: Leads managers or a community of practice | AX46: Works at B2: Visible effect on a team's or client portfolio's revenue, quality or compliance | AY46: Shapes the results of a practice or several teams | AZ46: Works at C1: Changes results across a sub-function or across products | BA46: Less than 8–10 yrs | BB46: 8–10 yrs · market 8–13 yrs | BC46: More than 8–10 yrs | BD46: Below: Graduate or postgraduate; professional qualification preferred | BE46: Postgraduate or professional qualification preferred | BF46: Above: Postgraduate / professional qualification preferred
A47: R014 | B47: XBRL Tagging, Conversion & Filing · Manager | C47: Consulting & Professional Services | D47: Manager | E47: level | F47: B2 | G47: Manager | H47: 3 | AL47: Works at B1: Domain specialist work | AM47: Hardest problems in the domain · in this role: XBRL Domain · XBRL domain knowledge · Team management · Problem-solving · UAT Testing · process improvement | AN47: Works at B3: Sets standards for a practice; cross-team problems | AO47: Works at B1: Technical / QC / client calls for the domain | AP47: Allocates people and sets team priorities | AQ47: Works at B3: Commercial / strategic calls for the unit | AR47: Works at B1: A domain or a small team | AS47: One team or a client portfolio | AT47: Works at B3: Several teams or a practice | AU47: Works at B1: IC: mentors and reviews · People: hands-on team lead of 3–5 | AV47: IC: guides others in the domain · People: manages a team of 6+ | AW47: Works at B3: IC: leads a practice · People: team leads / managers report in | AX47: Works at B1: Moves a module's, product area's or client account's results | AY47: Visible effect on a team's or client portfolio's revenue, quality or compliance | AZ47: Works at B3: Shapes the results of a practice or several teams | BA47: Less than 6–8 yrs | BB47: 6–8 yrs · market 6–10 yrs | BC47: More than 6–8 yrs | BD47: Below: Graduate + relevant qualification or certification preferred | BE47: Graduate or postgraduate; professional qualification preferred | BF47: Above: Postgraduate or professional qualification preferred
A48: R014 | B48: XBRL Tagging, Conversion & Filing · Manager | C48: Consulting & Professional Services | D48: Manager | E48: level | F48: B1 | G48: Team Lead | H48: 2 | AL48: Works at A3: Varied and non-standard work; handles exceptions | AM48: Domain specialist work · in this role: XBRL Domain · Attention to detail · Advanced XBRL Mapping knowledge · Different region Taxonomy Knowledge · Financial Reporting Standards … | AN48: Works at B2: Hardest problems in the domain | AO48: Works at A3: Technical / QC / client calls on own work | AP48: Technical / QC / client calls for the domain | AQ48: Works at B2: Allocates people and sets team priorities | AR48: Works at A3: A module / process, or work with client or regulatory consequences | AS48: A domain or a small team | AT48: Works at B2: One team or a client portfolio | AU48: Works at A3: contributes alone; guides others only informally | AV48: IC: mentors and reviews · People: hands-on team lead of 3–5 | AW48: Works at B2: IC: guides others in the domain · People: manages a team of 6+ | AX48: Works at A3: A process or client deliverable depends on this work | AY48: Moves a module's, product area's or client account's results | AZ48: Works at B2: Visible effect on a team's or client portfolio's revenue, quality or compliance | BA48: Less than 4–6 yrs | BB48: 4–6 yrs · market 4–8 yrs | BC48: More than 4–6 yrs | BD48: Below: Graduate; relevant certification preferred | BE48: Graduate + relevant qualification or certification preferred | BF48: Above: Graduate or postgraduate; professional qualification preferred
A49: R015 | B49: Application & Product Support · IC | C49: Customer Success & Support | D49: IC | E49: ROLE | F49: A1 · A2 · A3 · B1 | G49: Band A · all tracks · Customer support & success | H49: 24 | I49: H | J49: M | K49: M | L49: L | M49: M | N49: L | O49: L | P49: H | Q49: M | R49: M | S49: L | T49: L | U49: L | V49: L | AD49: =IF(W49<>"",W49,I49) -> H | AE49: =IF(X49<>"",X49,J49) -> M | AF49: =IF(Y49<>"",Y49,K49) -> M | AG49: =IF(Z49<>"",Z49,L49) -> L | AH49: =IF(AA49<>"",AA49,M49) -> M | AI49: =IF(AB49<>"",AB49,N49) -> L | AJ49: =IF(AC49<>"",AC49,O49) -> L | AK49: =COUNTA(W49:AC49) -> 0
A50: R015 | B50: Application & Product Support · IC | C50: Customer Success & Support | D50: IC | E50: level | F50: B1 | G50: Functional Specialist | H50: 4 | AL50: Works at A3: Varied and non-standard work; handles exceptions | AM50: Domain specialist work · in this role: Tech Support | AN50: Works at B2: Hardest problems in the domain | AO50: Works at A3: Technical / QC / client calls on own work | AP50: Technical / QC / client calls for the domain | AQ50: Works at B2: Allocates people and sets team priorities | AR50: Works at A3: A module / process, or work with client or regulatory consequences | AS50: A domain or a small team · KRA themes: Common themes in manager-set KRAs: accounts · csat · documentation · reduce · drive · keep | AT50: Works at B2: One team or a client portfolio | AU50: Works at A3: contributes alone; guides others only informally | AV50: IC: mentors and reviews · People: hands-on team lead of 3–5 | AW50: Works at B2: IC: guides others in the domain · People: manages a team of 6+ | AX50: Works at A3: A process or client deliverable depends on this work | AY50: Moves a module's, product area's or client account's results | AZ50: Works at B2: Visible effect on a team's or client portfolio's revenue, quality or compliance | BA50: Less than 4–6 yrs | BB50: 4–6 yrs · market 4–8 yrs | BC50: More than 4–6 yrs | BD50: Below: Graduate; relevant certification preferred | BE50: Graduate + relevant qualification or certification preferred | BF50: Above: Graduate or postgraduate; professional qualification preferred
A51: R015 | B51: Application & Product Support · IC | C51: Customer Success & Support | D51: IC | E51: level | F51: A3 | G51: Senior Support Executive | H51: 16 | AL51: Works at A2: Standard work of the discipline | AM51: Varied and non-standard work; handles exceptions · in this role: Tech Support · Domain Support · Domain Knowledge · Platform knowledge · Business Analysis | AN51: Works at B1: Domain specialist work | AO51: Works at A2: Chooses own approach within standards | AP51: Technical / QC / client calls on own work | AQ51: Works at B1: Technical / QC / client calls for the domain | AR51: Works at A2: Own deliverables · accuracy, TAT | AS51: A module / process, or work with client or regulatory consequences · KRA themes: Common themes in manager-set KRAs: resolve · accounts · maintain accurate · accurate up-to-date · escalations owned · tickets/queries sla | AT51: Works at B1: A domain or a small team | AU51: Works at A2: contributes alone; guides others only informally | AV51: Helps peers and newer people informally · None · guides 1–3 juniors informally | AW51: Works at B1: IC: mentors and reviews · People: hands-on team lead of 3–5 | AX51: Works at A2: Own deliverables feed a team's output and turnaround | AY51: A process or client deliverable depends on this work | AZ51: Works at B1: Moves a module's, product area's or client account's results | BA51: Less than 2–4 yrs | BB51: 2–4 yrs · market 2–5 yrs | BC51: More than 2–4 yrs | BD51: Below: Graduate · or diploma with experience | BE51: Graduate; relevant certification preferred | BF51: Above: Graduate + relevant qualification or certification preferred
A52: R015 | B52: Application & Product Support · IC | C52: Customer Success & Support | D52: IC | E52: level | F52: A2 | G52: Support Executive | H52: 2 | AL52: Works at A1: Learning; follows worked examples | AM52: Standard work of the discipline · in this role: Tech Support · Domain Support · Communication · Domain Knowledge · Business Analysis · Platform knowledge · Sales | AN52: Works at A3: Varied and non-standard work; handles exceptions | AO52: Works at A1: Needs approval / close guidance | AP52: Chooses own approach within standards | AQ52: Works at A3: Technical / QC / client calls on own work | AR52: Works at A1: Learning tasks | AS52: Own deliverables · accuracy, TAT | AT52: Works at A3: A module / process, or work with client or regulatory consequences | AU52: Works at A1: contributes alone; guides others only informally | AV52: Helps peers and newer people informally · No direct reports | AW52: Works at A3: Not scored in Band A | AX52: Works at A1: Learning; little direct effect on business results yet | AY52: Own deliverables feed a team's output and turnaround | AZ52: Works at A3: A process or client deliverable depends on this work | BA52: Less than 0–2 yrs | BB52: 0–2 yrs · market 0–3 yrs | BC52: More than 0–2 yrs | BD52: Below: Pursuing or completed graduation / diploma | BE52: Graduate · or diploma with experience | BF52: Above: Graduate; relevant certification preferred
A53: R015 | B53: Application & Product Support · IC | C53: Customer Success & Support | D53: IC | E53: level | F53: A1 | G53: Intern | H53: 2 | AL53: Not yet at the entry standard | AM53: Learning; follows worked examples · in this role: Tech Support · Domain Support · Communication · Domain Knowledge · Business Analysis · Platform knowledge · Sales | AN53: Works at A2: Standard work of the discipline | AO53: Not yet at the entry standard | AP53: Needs approval / close guidance | AQ53: Works at A2: Chooses own approach within standards | AR53: Not yet at the entry standard | AS53: Learning tasks | AT53: Works at A2: Own deliverables · accuracy, TAT | AU53: Not yet at the entry standard | AV53: Helps peers and newer people informally · No direct reports | AW53: Works at A2: Not scored in Band A | AX53: Not yet at the entry standard | AY53: Learning; little direct effect on business results yet | AZ53: Works at A2: Own deliverables feed a team's output and turnaround | BA53: Less than Intern / trainee · first year | BB53: Intern / trainee · first year · market — yrs | BC53: More than Intern / trainee · first year | BD53: Still studying | BE53: Pursuing or completed graduation / diploma | BF53: Above: Graduate · or diploma with experience
A54: R016 | B54: Application & Product Support · Manager | C54: Customer Success & Support | D54: Manager | E54: ROLE | F54: C1 | G54: Band C · Head / manager · Customer support & success | H54: 1 | I54: H | J54: M | K54: M | L54: M | M54: M | N54: L | O54: L | P54: H | Q54: M | R54: M | S54: M | T54: L | U54: L | V54: L | AD54: =IF(W54<>"",W54,I54) -> H | AE54: =IF(X54<>"",X54,J54) -> M | AF54: =IF(Y54<>"",Y54,K54) -> M | AG54: =IF(Z54<>"",Z54,L54) -> M | AH54: =IF(AA54<>"",AA54,M54) -> M | AI54: =IF(AB54<>"",AB54,N54) -> L | AJ54: =IF(AC54<>"",AC54,O54) -> L | AK54: =COUNTA(W54:AC54) -> 0
A55: R016 | B55: Application & Product Support · Manager | C55: Customer Success & Support | D55: Manager | E55: level | F55: C1 | G55: Associate Head – Application & Product Support | H55: 1 | AL55: Works at B3: Sets standards for a practice; cross-team problems | AM55: Ambiguous, cross-product problems | AN55: Works at C2: Function-wide or company-wide problems; creates methods and standards | AO55: Works at B3: Commercial / strategic calls for the unit | AP55: Sets direction for a sub-function or domain | AQ55: Works at C2: Sets direction for a function | AR55: Works at B3: Several teams or a practice | AS55: Sub-function results or domain quality across products | AT55: Works at C2: Function results, budget and risk | AU55: Works at B3: IC: leads a practice · People: team leads / managers report in | AV55: Leads managers or a community of practice | AW55: Works at C2: Leads a function; shapes functional strategy | AX55: Works at B3: Shapes the results of a practice or several teams | AY55: Changes results across a sub-function or across products | AZ55: Works at C2: Drives a function's or department's results and costs | BA55: Less than 10–13 yrs | BB55: 10–13 yrs · market 12–17 yrs | BC55: More than 10–13 yrs | BD55: Below: Postgraduate or professional qualification preferred | BE55: Postgraduate / professional qualification preferred | BF55: Above: Postgraduate / professional qualification preferred
A56: R017 | B56: Customer Success & Account Management · Consultant | C56: Customer Success & Support | D56: Consultant | E56: ROLE | F56: X1 | G56: Consultant · outside the ladder · Customer support & success | H56: 1 | AD56: =IF(W56<>"",W56,I56) -> 0 | AE56: =IF(X56<>"",X56,J56) -> 0 | AF56: =IF(Y56<>"",Y56,K56) -> 0 | AG56: =IF(Z56<>"",Z56,L56) -> 0 | AH56: =IF(AA56<>"",AA56,M56) -> 0 | AI56: =IF(AB56<>"",AB56,N56) -> 0 | AJ56: =IF(AC56<>"",AC56,O56) -> 0 | AK56: =COUNTA(W56:AC56) -> 0
A57: R018 | B57: Customer Success & Account Management · IC | C57: Customer Success & Support | D57: IC | E57: ROLE | F57: A3 · B1 · B2 | G57: Band B · Specialist / POD Lead · Customer support & success | H57: 9 | I57: H | J57: M | K57: M | L57: L | M57: M | N57: L | O57: L | P57: H | Q57: M | R57: M | S57: L | T57: L | U57: L | V57: L | AD57: =IF(W57<>"",W57,I57) -> H | AE57: =IF(X57<>"",X57,J57) -> M | AF57: =IF(Y57<>"",Y57,K57) -> M | AG57: =IF(Z57<>"",Z57,L57) -> L | AH57: =IF(AA57<>"",AA57,M57) -> M | AI57: =IF(AB57<>"",AB57,N57) -> L | AJ57: =IF(AC57<>"",AC57,O57) -> L | AK57: =COUNTA(W57:AC57) -> 0
A58: R018 | B58: Customer Success & Account Management · IC | C58: Customer Success & Support | D58: IC | E58: level | F58: B2 | G58: Senior Customer Success Specialist | H58: 5 | AL58: Works at B1: Domain specialist work | AM58: Hardest problems in the domain · in this role: XBRL Domain | AN58: Works at B3: Sets standards for a practice; cross-team problems | AO58: Works at B1: Technical / QC / client calls for the domain | AP58: Allocates people and sets team priorities | AQ58: Works at B3: Commercial / strategic calls for the unit | AR58: Works at B1: A domain or a small team | AS58: One team or a client portfolio | AT58: Works at B3: Several teams or a practice | AU58: Works at B1: IC: mentors and reviews · People: hands-on team lead of 3–5 | AV58: IC: guides others in the domain · People: manages a team of 6+ | AW58: Works at B3: IC: leads a practice · People: team leads / managers report in | AX58: Works at B1: Moves a module's, product area's or client account's results | AY58: Visible effect on a team's or client portfolio's revenue, quality or compliance | AZ58: Works at B3: Shapes the results of a practice or several teams | BA58: Less than 6–8 yrs | BB58: 6–8 yrs · market 6–10 yrs | BC58: More than 6–8 yrs | BD58: Below: Graduate + relevant qualification or certification preferred | BE58: Graduate or postgraduate; professional qualification preferred | BF58: Above: Postgraduate or professional qualification preferred
A59: R018 | B59: Customer Success & Account Management · IC | C59: Customer Success & Support | D59: IC | E59: level | F59: B1 | G59: Specialist – Customer Success & Account Management | H59: 2 | AL59: Works at A3: Varied and non-standard work; handles exceptions | AM59: Domain specialist work · in this role: XBRL Domain · Communication | AN59: Works at B2: Hardest problems in the domain | AO59: Works at A3: Technical / QC / client calls on own work | AP59: Technical / QC / client calls for the domain | AQ59: Works at B2: Allocates people and sets team priorities | AR59: Works at A3: A module / process, or work with client or regulatory consequences | AS59: A domain or a small team | AT59: Works at B2: One team or a client portfolio | AU59: Works at A3: contributes alone; guides others only informally | AV59: IC: mentors and reviews · People: hands-on team lead of 3–5 | AW59: Works at B2: IC: guides others in the domain · People: manages a team of 6+ | AX59: Works at A3: A process or client deliverable depends on this work | AY59: Moves a module's, product area's or client account's results | AZ59: Works at B2: Visible effect on a team's or client portfolio's revenue, quality or compliance | BA59: Less than 4–6 yrs | BB59: 4–6 yrs · market 4–8 yrs | BC59: More than 4–6 yrs | BD59: Below: Graduate; relevant certification preferred | BE59: Graduate + relevant qualification or certification preferred | BF59: Above: Graduate or postgraduate; professional qualification preferred
A60: R018 | B60: Customer Success & Account Management · IC | C60: Customer Success & Support | D60: IC | E60: level | F60: A3 | G60: Senior Customer Success Executive | H60: 2 | AL60: Works at A2: Standard work of the discipline | AM60: Varied and non-standard work; handles exceptions · in this role: XBRL Domain · Communication | AN60: Works at B1: Domain specialist work | AO60: Works at A2: Chooses own approach within standards | AP60: Technical / QC / client calls on own work | AQ60: Works at B1: Technical / QC / client calls for the domain | AR60: Works at A2: Own deliverables · accuracy, TAT | AS60: A module / process, or work with client or regulatory consequences | AT60: Works at B1: A domain or a small team | AU60: Works at A2: contributes alone; guides others only informally | AV60: Helps peers and newer people informally · None · guides 1–3 juniors informally | AW60: Works at B1: IC: mentors and reviews · People: hands-on team lead of 3–5 | AX60: Works at A2: Own deliverables feed a team's output and turnaround | AY60: A process or client deliverable depends on this work | AZ60: Works at B1: Moves a module's, product area's or client account's results | BA60: Less than 2–4 yrs | BB60: 2–4 yrs · market 2–5 yrs | BC60: More than 2–4 yrs | BD60: Below: Graduate · or diploma with experience | BE60: Graduate; relevant certification preferred | BF60: Above: Graduate + relevant qualification or certification preferred
A61: R019 | B61: Customer Training & Enablement · IC | C61: Customer Success & Support | D61: IC | E61: ROLE | F61: B1 | G61: Band B · Specialist / POD Lead · Service delivery & data operations | H61: 1 | I61: H | J61: M | K61: M | L61: L | M61: L | N61: L | O61: L | P61: H | Q61: M | R61: M | S61: L | T61: L | U61: L | V61: L | AD61: =IF(W61<>"",W61,I61) -> H | AE61: =IF(X61<>"",X61,J61) -> M | AF61: =IF(Y61<>"",Y61,K61) -> M | AG61: =IF(Z61<>"",Z61,L61) -> L | AH61: =IF(AA61<>"",AA61,M61) -> L | AI61: =IF(AB61<>"",AB61,N61) -> L | AJ61: =IF(AC61<>"",AC61,O61) -> L | AK61: =COUNTA(W61:AC61) -> 0
A62: R019 | B62: Customer Training & Enablement · IC | C62: Customer Success & Support | D62: IC | E62: level | F62: B1 | G62: Customer Enablement Specialist | H62: 1 | AL62: Works at A3: Varied and non-standard work; handles exceptions | AM62: Domain specialist work | AN62: Works at B2: Hardest problems in the domain | AO62: Works at A3: Technical / QC / client calls on own work | AP62: Technical / QC / client calls for the domain | AQ62: Works at B2: Allocates people and sets team priorities | AR62: Works at A3: A module / process, or work with client or regulatory consequences | AS62: A domain or a small team | AT62: Works at B2: One team or a client portfolio | AU62: Works at A3: contributes alone; guides others only informally | AV62: IC: mentors and reviews · People: hands-on team lead of 3–5 | AW62: Works at B2: IC: guides others in the domain · People: manages a team of 6+ | AX62: Works at A3: A process or client deliverable depends on this work | AY62: Moves a module's, product area's or client account's results | AZ62: Works at B2: Visible effect on a team's or client portfolio's revenue, quality or compliance | BA62: Less than 4–6 yrs | BB62: 4–6 yrs · market 4–8 yrs | BC62: More than 4–6 yrs | BD62: Below: Graduate; relevant certification preferred | BE62: Graduate + relevant qualification or certification preferred | BF62: Above: Graduate or postgraduate; professional qualification preferred
A63: R020 | B63: Financial Data Processing · IC | C63: Data & Analytics | D63: IC | E63: ROLE | F63: A3 | G63: Band A · all tracks · Service delivery & data operations | H63: 8 | I63: H | J63: M | K63: M | L63: L | M63: L | N63: L | O63: L | P63: H | Q63: M | R63: M | S63: L | T63: L | U63: L | V63: L | AD63: =IF(W63<>"",W63,I63) -> H | AE63: =IF(X63<>"",X63,J63) -> M | AF63: =IF(Y63<>"",Y63,K63) -> M | AG63: =IF(Z63<>"",Z63,L63) -> L | AH63: =IF(AA63<>"",AA63,M63) -> L | AI63: =IF(AB63<>"",AB63,N63) -> L | AJ63: =IF(AC63<>"",AC63,O63) -> L | AK63: =COUNTA(W63:AC63) -> 0
A64: R020 | B64: Financial Data Processing · IC | C64: Data & Analytics | D64: IC | E64: level | F64: A3 | G64: Senior Data Analyst | H64: 8 | AL64: Works at A2: Standard work of the discipline | AM64: Varied and non-standard work; handles exceptions · in this role: Data Processing · Data validation | AN64: Works at B1: Domain specialist work | AO64: Works at A2: Chooses own approach within standards | AP64: Technical / QC / client calls on own work | AQ64: Works at B1: Technical / QC / client calls for the domain | AR64: Works at A2: Own deliverables · accuracy, TAT | AS64: A module / process, or work with client or regulatory consequences · KRA themes: Common themes in manager-set KRAs: business-day response · manual · contribute · delivery time · provide solutions · complete assigned | AT64: Works at B1: A domain or a small team | AU64: Works at A2: contributes alone; guides others only informally | AV64: Helps peers and newer people informally · None · guides 1–3 juniors informally | AW64: Works at B1: IC: mentors and reviews · People: hands-on team lead of 3–5 | AX64: Works at A2: Own deliverables feed a team's output and turnaround | AY64: A process or client deliverable depends on this work | AZ64: Works at B1: Moves a module's, product area's or client account's results | BA64: Less than 2–4 yrs | BB64: 2–4 yrs · market 2–5 yrs | BC64: More than 2–4 yrs | BD64: Below: Graduate · or diploma with experience | BE64: Graduate; relevant certification preferred | BF64: Above: Graduate + relevant qualification or certification preferred
A65: R021 | B65: Financial Data Processing · Manager | C65: Data & Analytics | D65: Manager | E65: ROLE | F65: B2 | G65: Band B · People Manager · Service delivery & data operations | H65: 1 | I65: H | J65: M | K65: M | L65: M | M65: L | N65: L | O65: L | P65: H | Q65: M | R65: M | S65: M | T65: L | U65: L | V65: L | AD65: =IF(W65<>"",W65,I65) -> H | AE65: =IF(X65<>"",X65,J65) -> M | AF65: =IF(Y65<>"",Y65,K65) -> M | AG65: =IF(Z65<>"",Z65,L65) -> M | AH65: =IF(AA65<>"",AA65,M65) -> L | AI65: =IF(AB65<>"",AB65,N65) -> L | AJ65: =IF(AC65<>"",AC65,O65) -> L | AK65: =COUNTA(W65:AC65) -> 0
A66: R021 | B66: Financial Data Processing · Manager | C66: Data & Analytics | D66: Manager | E66: level | F66: B2 | G66: Data Operations Manager | H66: 1 | AL66: Works at B1: Domain specialist work | AM66: Hardest problems in the domain · in this role: Data processing · Mutual fund · Data validation | AN66: Works at B3: Sets standards for a practice; cross-team problems | AO66: Works at B1: Technical / QC / client calls for the domain | AP66: Allocates people and sets team priorities | AQ66: Works at B3: Commercial / strategic calls for the unit | AR66: Works at B1: A domain or a small team | AS66: One team or a client portfolio | AT66: Works at B3: Several teams or a practice | AU66: Works at B1: IC: mentors and reviews · People: hands-on team lead of 3–5 | AV66: IC: guides others in the domain · People: manages a team of 6+ | AW66: Works at B3: IC: leads a practice · People: team leads / managers report in | AX66: Works at B1: Moves a module's, product area's or client account's results | AY66: Visible effect on a team's or client portfolio's revenue, quality or compliance | AZ66: Works at B3: Shapes the results of a practice or several teams | BA66: Less than 6–8 yrs | BB66: 6–8 yrs · market 6–10 yrs | BC66: More than 6–8 yrs | BD66: Below: Graduate + relevant qualification or certification preferred | BE66: Graduate or postgraduate; professional qualification preferred | BF66: Above: Postgraduate or professional qualification preferred
A67: R022 | B67: MIS & Business Reporting · IC | C67: Data & Analytics | D67: IC | E67: ROLE | F67: A2 · A3 | G67: Band A · all tracks · Customer support & success | H67: 2 | I67: H | J67: M | K67: M | L67: L | M67: M | N67: L | O67: L | P67: H | Q67: M | R67: M | S67: L | T67: L | U67: L | V67: L | AD67: =IF(W67<>"",W67,I67) -> H | AE67: =IF(X67<>"",X67,J67) -> M | AF67: =IF(Y67<>"",Y67,K67) -> M | AG67: =IF(Z67<>"",Z67,L67) -> L | AH67: =IF(AA67<>"",AA67,M67) -> M | AI67: =IF(AB67<>"",AB67,N67) -> L | AJ67: =IF(AC67<>"",AC67,O67) -> L | AK67: =COUNTA(W67:AC67) -> 0
A68: R022 | B68: MIS & Business Reporting · IC | C68: Data & Analytics | D68: IC | E68: level | F68: A3 | G68: MIS Specialist | H68: 1 | AL68: Works at A2: Standard work of the discipline | AM68: Varied and non-standard work; handles exceptions | AN68: Works at B1: Domain specialist work | AO68: Works at A2: Chooses own approach within standards | AP68: Technical / QC / client calls on own work | AQ68: Works at B1: Technical / QC / client calls for the domain | AR68: Works at A2: Own deliverables · accuracy, TAT | AS68: A module / process, or work with client or regulatory consequences | AT68: Works at B1: A domain or a small team | AU68: Works at A2: contributes alone; guides others only informally | AV68: Helps peers and newer people informally · None · guides 1–3 juniors informally | AW68: Works at B1: IC: mentors and reviews · People: hands-on team lead of 3–5 | AX68: Works at A2: Own deliverables feed a team's output and turnaround | AY68: A process or client deliverable depends on this work | AZ68: Works at B1: Moves a module's, product area's or client account's results | BA68: Less than 2–4 yrs | BB68: 2–4 yrs · market 2–5 yrs | BC68: More than 2–4 yrs | BD68: Below: Graduate · or diploma with experience | BE68: Graduate; relevant certification preferred | BF68: Above: Graduate + relevant qualification or certification preferred
A69: R022 | B69: MIS & Business Reporting · IC | C69: Data & Analytics | D69: IC | E69: level | F69: A2 | G69: MIS Associate | H69: 1 | AL69: Works at A1: Learning; follows worked examples | AM69: Standard work of the discipline | AN69: Works at A3: Varied and non-standard work; handles exceptions | AO69: Works at A1: Needs approval / close guidance | AP69: Chooses own approach within standards | AQ69: Works at A3: Technical / QC / client calls on own work | AR69: Works at A1: Learning tasks | AS69: Own deliverables · accuracy, TAT | AT69: Works at A3: A module / process, or work with client or regulatory consequences | AU69: Works at A1: contributes alone; guides others only informally | AV69: Helps peers and newer people informally · No direct reports | AW69: Works at A3: Not scored in Band A | AX69: Works at A1: Learning; little direct effect on business results yet | AY69: Own deliverables feed a team's output and turnaround | AZ69: Works at A3: A process or client deliverable depends on this work | BA69: Less than 0–2 yrs | BB69: 0–2 yrs · market 0–3 yrs | BC69: More than 0–2 yrs | BD69: Below: Pursuing or completed graduation / diploma | BE69: Graduate · or diploma with experience | BF69: Above: Graduate; relevant certification preferred
A70: R023 | B70: Document Conversion, Formatting & Web Publishing · IC | C70: Data Operations & Digitization | D70: IC | E70: ROLE | F70: A2 · A3 · B1 | G70: Band A · all tracks · Service delivery & data operations | H70: 28 | I70: H | J70: M | K70: M | L70: L | M70: L | N70: L | O70: L | P70: H | Q70: M | R70: M | S70: L | T70: L | U70: L | V70: L | AD70: =IF(W70<>"",W70,I70) -> H | AE70: =IF(X70<>"",X70,J70) -> M | AF70: =IF(Y70<>"",Y70,K70) -> M | AG70: =IF(Z70<>"",Z70,L70) -> L | AH70: =IF(AA70<>"",AA70,M70) -> L | AI70: =IF(AB70<>"",AB70,N70) -> L | AJ70: =IF(AC70<>"",AC70,O70) -> L | AK70: =COUNTA(W70:AC70) -> 0
A71: R023 | B71: Document Conversion, Formatting & Web Publishing · IC | C71: Data Operations & Digitization | D71: IC | E71: level | F71: B1 | G71: Digitization Specialist | H71: 3 | AL71: Works at A3: Varied and non-standard work; handles exceptions | AM71: Domain specialist work · in this role: OCR/Image procesing | AN71: Works at B2: Hardest problems in the domain | AO71: Works at A3: Technical / QC / client calls on own work | AP71: Technical / QC / client calls for the domain | AQ71: Works at B2: Allocates people and sets team priorities | AR71: Works at A3: A module / process, or work with client or regulatory consequences | AS71: A domain or a small team | AT71: Works at B2: One team or a client portfolio | AU71: Works at A3: contributes alone; guides others only informally | AV71: IC: mentors and reviews · People: hands-on team lead of 3–5 | AW71: Works at B2: IC: guides others in the domain · People: manages a team of 6+ | AX71: Works at A3: A process or client deliverable depends on this work | AY71: Moves a module's, product area's or client account's results | AZ71: Works at B2: Visible effect on a team's or client portfolio's revenue, quality or compliance | BA71: Less than 4–6 yrs | BB71: 4–6 yrs · market 4–8 yrs | BC71: More than 4–6 yrs | BD71: Below: Graduate; relevant certification preferred | BE71: Graduate + relevant qualification or certification preferred | BF71: Above: Graduate or postgraduate; professional qualification preferred
A72: R023 | B72: Document Conversion, Formatting & Web Publishing · IC | C72: Data Operations & Digitization | D72: IC | E72: level | F72: A3 | G72: Senior Digitization Associate | H72: 21 | AL72: Works at A2: Standard work of the discipline | AM72: Varied and non-standard work; handles exceptions · in this role: OCR/Image procesing · attention to detail · Excel · quality checking · HTML · timely delivery · OCR · Word | AN72: Works at B1: Domain specialist work | AO72: Works at A2: Chooses own approach within standards | AP72: Technical / QC / client calls on own work | AQ72: Works at B1: Technical / QC / client calls for the domain | AR72: Works at A2: Own deliverables · accuracy, TAT | AS72: A module / process, or work with client or regulatory consequences | AT72: Works at B1: A domain or a small team | AU72: Works at A2: contributes alone; guides others only informally | AV72: Helps peers and newer people informally · None · guides 1–3 juniors informally | AW72: Works at B1: IC: mentors and reviews · People: hands-on team lead of 3–5 | AX72: Works at A2: Own deliverables feed a team's output and turnaround | AY72: A process or client deliverable depends on this work | AZ72: Works at B1: Moves a module's, product area's or client account's results | BA72: Less than 2–4 yrs | BB72: 2–4 yrs · market 2–5 yrs | BC72: More than 2–4 yrs | BD72: Below: Graduate · or diploma with experience | BE72: Graduate; relevant certification preferred | BF72: Above: Graduate + relevant qualification or certification preferred
A73: R023 | B73: Document Conversion, Formatting & Web Publishing · IC | C73: Data Operations & Digitization | D73: IC | E73: level | F73: A2 | G73: Digitization Associate | H73: 4 | AL73: Works at A1: Learning; follows worked examples | AM73: Standard work of the discipline · in this role: OCR/Image procesing | AN73: Works at A3: Varied and non-standard work; handles exceptions | AO73: Works at A1: Needs approval / close guidance | AP73: Chooses own approach within standards | AQ73: Works at A3: Technical / QC / client calls on own work | AR73: Works at A1: Learning tasks | AS73: Own deliverables · accuracy, TAT | AT73: Works at A3: A module / process, or work with client or regulatory consequences | AU73: Works at A1: contributes alone; guides others only informally | AV73: Helps peers and newer people informally · No direct reports | AW73: Works at A3: Not scored in Band A | AX73: Works at A1: Learning; little direct effect on business results yet | AY73: Own deliverables feed a team's output and turnaround | AZ73: Works at A3: A process or client deliverable depends on this work | BA73: Less than 0–2 yrs | BB73: 0–2 yrs · market 0–3 yrs | BC73: More than 0–2 yrs | BD73: Below: Pursuing or completed graduation / diploma | BE73: Graduate · or diploma with experience | BF73: Above: Graduate; relevant certification preferred
A74: R024 | B74: Document Conversion, Formatting & Web Publishing · Manager | C74: Data Operations & Digitization | D74: Manager | E74: ROLE | F74: B2 | G74: Band B · People Manager · Service delivery & data operations | H74: 3 | I74: H | J74: M | K74: M | L74: M | M74: L | N74: L | O74: L | P74: H | Q74: M | R74: M | S74: M | T74: L | U74: L | V74: L | AD74: =IF(W74<>"",W74,I74) -> H | AE74: =IF(X74<>"",X74,J74) -> M | AF74: =IF(Y74<>"",Y74,K74) -> M | AG74: =IF(Z74<>"",Z74,L74) -> M | AH74: =IF(AA74<>"",AA74,M74) -> L | AI74: =IF(AB74<>"",AB74,N74) -> L | AJ74: =IF(AC74<>"",AC74,O74) -> L | AK74: =COUNTA(W74:AC74) -> 0
A75: R024 | B75: Document Conversion, Formatting & Web Publishing · Manager | C75: Data Operations & Digitization | D75: Manager | E75: level | F75: B2 | G75: Digitization Manager | H75: 3 | AL75: Works at B1: Domain specialist work | AM75: Hardest problems in the domain · in this role: OCR/Image procesing · attention to detail · quality checking · Excel · timely delivery · HTML · Word · ABYYY Fine Reader | AN75: Works at B3: Sets standards for a practice; cross-team problems | AO75: Works at B1: Technical / QC / client calls for the domain | AP75: Allocates people and sets team priorities | AQ75: Works at B3: Commercial / strategic calls for the unit | AR75: Works at B1: A domain or a small team | AS75: One team or a client portfolio | AT75: Works at B3: Several teams or a practice | AU75: Works at B1: IC: mentors and reviews · People: hands-on team lead of 3–5 | AV75: IC: guides others in the domain · People: manages a team of 6+ | AW75: Works at B3: IC: leads a practice · People: team leads / managers report in | AX75: Works at B1: Moves a module's, product area's or client account's results | AY75: Visible effect on a team's or client portfolio's revenue, quality or compliance | AZ75: Works at B3: Shapes the results of a practice or several teams | BA75: Less than 6–8 yrs | BB75: 6–8 yrs · market 6–10 yrs | BC75: More than 6–8 yrs | BD75: Below: Graduate + relevant qualification or certification preferred | BE75: Graduate or postgraduate; professional qualification preferred | BF75: Above: Postgraduate or professional qualification preferred
A76: R025 | B76: Brand, Graphic & Video Design · IC | C76: Design & Creative | D76: IC | E76: ROLE | F76: A2 · A3 · B1 | G76: Band A · all tracks · Sales & marketing | H76: 4 | I76: H | J76: M | K76: L | L76: L | M76: M | N76: L | O76: L | P76: H | Q76: M | R76: M | S76: L | T76: L | U76: L | V76: L | AD76: =IF(W76<>"",W76,I76) -> H | AE76: =IF(X76<>"",X76,J76) -> M | AF76: =IF(Y76<>"",Y76,K76) -> L | AG76: =IF(Z76<>"",Z76,L76) -> L | AH76: =IF(AA76<>"",AA76,M76) -> M | AI76: =IF(AB76<>"",AB76,N76) -> L | AJ76: =IF(AC76<>"",AC76,O76) -> L | AK76: =COUNTA(W76:AC76) -> 0
A77: R025 | B77: Brand, Graphic & Video Design · IC | C77: Design & Creative | D77: IC | E77: level | F77: B1 | G77: Design Specialist | H77: 1 | AL77: Works at A3: Varied and non-standard work; handles exceptions | AM77: Domain specialist work · in this role: Graphic design | AN77: Works at B2: Hardest problems in the domain | AO77: Works at A3: Technical / QC / client calls on own work | AP77: Technical / QC / client calls for the domain | AQ77: Works at B2: Allocates people and sets team priorities | AR77: Works at A3: A module / process, or work with client or regulatory consequences | AS77: A domain or a small team | AT77: Works at B2: One team or a client portfolio | AU77: Works at A3: contributes alone; guides others only informally | AV77: IC: mentors and reviews · People: hands-on team lead of 3–5 | AW77: Works at B2: IC: guides others in the domain · People: manages a team of 6+ | AX77: Works at A3: A process or client deliverable depends on this work | AY77: Moves a module's, product area's or client account's results | AZ77: Works at B2: Visible effect on a team's or client portfolio's revenue, quality or compliance | BA77: Less than 4–6 yrs | BB77: 4–6 yrs · market 4–8 yrs | BC77: More than 4–6 yrs | BD77: Below: Graduate; relevant certification preferred | BE77: Graduate + relevant qualification or certification preferred | BF77: Above: Graduate or postgraduate; professional qualification preferred
A78: R025 | B78: Brand, Graphic & Video Design · IC | C78: Design & Creative | D78: IC | E78: level | F78: A3 | G78: Senior Designer | H78: 2 | AL78: Works at A2: Standard work of the discipline | AM78: Varied and non-standard work; handles exceptions · in this role: Graphic design | AN78: Works at B1: Domain specialist work | AO78: Works at A2: Chooses own approach within standards | AP78: Technical / QC / client calls on own work | AQ78: Works at B1: Technical / QC / client calls for the domain | AR78: Works at A2: Own deliverables · accuracy, TAT | AS78: A module / process, or work with client or regulatory consequences | AT78: Works at B1: A domain or a small team | AU78: Works at A2: contributes alone; guides others only informally | AV78: Helps peers and newer people informally · None · guides 1–3 juniors informally | AW78: Works at B1: IC: mentors and reviews · People: hands-on team lead of 3–5 | AX78: Works at A2: Own deliverables feed a team's output and turnaround | AY78: A process or client deliverable depends on this work | AZ78: Works at B1: Moves a module's, product area's or client account's results | BA78: Less than 2–4 yrs | BB78: 2–4 yrs · market 2–5 yrs | BC78: More than 2–4 yrs | BD78: Below: Graduate · or diploma with experience | BE78: Graduate; relevant certification preferred | BF78: Above: Graduate + relevant qualification or certification preferred
A79: R025 | B79: Brand, Graphic & Video Design · IC | C79: Design & Creative | D79: IC | E79: level | F79: A2 | G79: Designer | H79: 1 | AL79: Works at A1: Learning; follows worked examples | AM79: Standard work of the discipline · in this role: Graphic design | AN79: Works at A3: Varied and non-standard work; handles exceptions | AO79: Works at A1: Needs approval / close guidance | AP79: Chooses own approach within standards | AQ79: Works at A3: Technical / QC / client calls on own work | AR79: Works at A1: Learning tasks | AS79: Own deliverables · accuracy, TAT | AT79: Works at A3: A module / process, or work with client or regulatory consequences | AU79: Works at A1: contributes alone; guides others only informally | AV79: Helps peers and newer people informally · No direct reports | AW79: Works at A3: Not scored in Band A | AX79: Works at A1: Learning; little direct effect on business results yet | AY79: Own deliverables feed a team's output and turnaround | AZ79: Works at A3: A process or client deliverable depends on this work | BA79: Less than 0–2 yrs | BB79: 0–2 yrs · market 0–3 yrs | BC79: More than 0–2 yrs | BD79: Below: Pursuing or completed graduation / diploma | BE79: Graduate · or diploma with experience | BF79: Above: Graduate; relevant certification preferred
A80: R026 | B80: UX / UI Design · IC | C80: Design & Creative | D80: IC | E80: ROLE | F80: A3 | G80: Band A · all tracks · Technology & engineering | H80: 2 | I80: H | J80: M | K80: L | L80: L | M80: L | N80: L | O80: L | P80: H | Q80: M | R80: M | S80: L | T80: L | U80: L | V80: L | AD80: =IF(W80<>"",W80,I80) -> H | AE80: =IF(X80<>"",X80,J80) -> M | AF80: =IF(Y80<>"",Y80,K80) -> L | AG80: =IF(Z80<>"",Z80,L80) -> L | AH80: =IF(AA80<>"",AA80,M80) -> L | AI80: =IF(AB80<>"",AB80,N80) -> L | AJ80: =IF(AC80<>"",AC80,O80) -> L | AK80: =COUNTA(W80:AC80) -> 0
A81: R026 | B81: UX / UI Design · IC | C81: Design & Creative | D81: IC | E81: level | F81: A3 | G81: Senior Product Designer | H81: 2 | AL81: Works at A2: Standard work of the discipline | AM81: Varied and non-standard work; handles exceptions | AN81: Works at B1: Domain specialist work | AO81: Works at A2: Chooses own approach within standards | AP81: Technical / QC / client calls on own work | AQ81: Works at B1: Technical / QC / client calls for the domain | AR81: Works at A2: Own deliverables · accuracy, TAT | AS81: A module / process, or work with client or regulatory consequences | AT81: Works at B1: A domain or a small team | AU81: Works at A2: contributes alone; guides others only informally | AV81: Helps peers and newer people informally · None · guides 1–3 juniors informally | AW81: Works at B1: IC: mentors and reviews · People: hands-on team lead of 3–5 | AX81: Works at A2: Own deliverables feed a team's output and turnaround | AY81: A process or client deliverable depends on this work | AZ81: Works at B1: Moves a module's, product area's or client account's results | BA81: Less than 2–4 yrs | BB81: 2–4 yrs · market 2–5 yrs | BC81: More than 2–4 yrs | BD81: Below: Graduate · or diploma with experience | BE81: Graduate; relevant certification preferred | BF81: Above: Graduate + relevant qualification or certification preferred
A82: R027 | B82: Solution & Technical Architecture · IC | C82: Engineering & Architecture | D82: IC | E82: ROLE | F82: B3 · C1 | G82: Band B · Specialist / POD Lead · Technology & engineering | H82: 5 | I82: H | J82: M | K82: L | L82: L | M82: L | N82: L | O82: L | P82: H | Q82: M | R82: M | S82: L | T82: L | U82: L | V82: L | AD82: =IF(W82<>"",W82,I82) -> H | AE82: =IF(X82<>"",X82,J82) -> M | AF82: =IF(Y82<>"",Y82,K82) -> L | AG82: =IF(Z82<>"",Z82,L82) -> L | AH82: =IF(AA82<>"",AA82,M82) -> L | AI82: =IF(AB82<>"",AB82,N82) -> L | AJ82: =IF(AC82<>"",AC82,O82) -> L | AK82: =COUNTA(W82:AC82) -> 0
A83: R027 | B83: Solution & Technical Architecture · IC | C83: Engineering & Architecture | D83: IC | E83: level | F83: C1 | G83: Technical Architect | H83: 2 | AL83: Works at B3: Sets standards for a practice; cross-team problems | AM83: Ambiguous, cross-product problems · in this role: Java · NET MVC · Spring Boot | AN83: Works at C2: Function-wide or company-wide problems; creates methods and standards | AO83: Works at B3: Commercial / strategic calls for the unit | AP83: Sets direction for a sub-function or domain | AQ83: Works at C2: Sets direction for a function | AR83: Works at B3: Several teams or a practice | AS83: Sub-function results or domain quality across products | AT83: Works at C2: Function results, budget and risk | AU83: Works at B3: IC: leads a practice · People: team leads / managers report in | AV83: Leads managers or a community of practice | AW83: Works at C2: Leads a function; shapes functional strategy | AX83: Works at B3: Shapes the results of a practice or several teams | AY83: Changes results across a sub-function or across products | AZ83: Works at C2: Drives a function's or department's results and costs | BA83: Less than 10–13 yrs | BB83: 10–13 yrs · market 12–17 yrs | BC83: More than 10–13 yrs | BD83: Below: Postgraduate or professional qualification preferred | BE83: Postgraduate / professional qualification preferred | BF83: Above: Postgraduate / professional qualification preferred
A84: R027 | B84: Solution & Technical Architecture · IC | C84: Engineering & Architecture | D84: IC | E84: level | F84: B3 | G84: Associate Technical Architect | H84: 3 | AL84: Works at B2: Hardest problems in the domain | AM84: Sets standards for a practice; cross-team problems · in this role: Java · NET MVC | AN84: Works at C1: Ambiguous, cross-product problems | AO84: Works at B2: Allocates people and sets team priorities | AP84: Commercial / strategic calls for the unit | AQ84: Works at C1: Sets direction for a sub-function or domain | AR84: Works at B2: One team or a client portfolio | AS84: Several teams or a practice · KRA themes: Common themes in manager-set KRAs: code · leakage qa/uat · defect · technical · quality · agreed | AT84: Works at C1: Sub-function results or domain quality across products | AU84: Works at B2: IC: guides others in the domain · People: manages a team of 6+ | AV84: IC: leads a practice · People: team leads / managers report in | AW84: Works at C1: Leads managers or a community of practice | AX84: Works at B2: Visible effect on a team's or client portfolio's revenue, quality or compliance | AY84: Shapes the results of a practice or several teams | AZ84: Works at C1: Changes results across a sub-function or across products | BA84: Less than 8–10 yrs | BB84: 8–10 yrs · market 8–13 yrs | BC84: More than 8–10 yrs | BD84: Below: Graduate or postgraduate; professional qualification preferred | BE84: Postgraduate or professional qualification preferred | BF84: Above: Postgraduate / professional qualification preferred
A85: R028 | B85: Solution & Technical Architecture · Manager | C85: Engineering & Architecture | D85: Manager | E85: ROLE | F85: B+ | G85: B+ · Player-Coach · Technology & engineering | H85: 5 | I85: H | J85: M | K85: L | L85: M | M85: L | N85: L | O85: L | P85: H | Q85: M | R85: M | S85: M | T85: L | U85: L | V85: L | AD85: =IF(W85<>"",W85,I85) -> H | AE85: =IF(X85<>"",X85,J85) -> M | AF85: =IF(Y85<>"",Y85,K85) -> L | AG85: =IF(Z85<>"",Z85,L85) -> M | AH85: =IF(AA85<>"",AA85,M85) -> L | AI85: =IF(AB85<>"",AB85,N85) -> L | AJ85: =IF(AC85<>"",AC85,O85) -> L | AK85: =COUNTA(W85:AC85) -> 0
A86: R028 | B86: Solution & Technical Architecture · Manager | C86: Engineering & Architecture | D86: Manager | E86: level | F86: B+ | G86: Practice Lead | H86: 5 | AL86: Works at B3: Sets standards for a practice; cross-team problems | AM86: Principal-level problems in own domain; sets technical or quality standards and still builds · in this role: Java · Spring Boot · NET MVC | AN86: Works at C1: Ambiguous, cross-product problems | AO86: Works at B3: Commercial / strategic calls for the unit | AP86: Decides approach and priorities for the practice; escalates only cross-function trade-offs | AQ86: Works at C1: Sets direction for a sub-function or domain | AR86: Works at B3: Several teams or a practice | AS86: Practice outcomes plus own deliverables; quality and delivery of the team · KRA themes: Common themes in manager-set KRAs: support · technical · project · completion · develop · year | AT86: Works at C1: Sub-function results or domain quality across products | AU86: Works at B3: IC: leads a practice · People: team leads / managers report in | AV86: Leads 3–6 people · or a pod while remaining a hands-on expert; coaches, allocates, reviews | AW86: Works at C1: Leads managers or a community of practice | AX86: Works at B3: Shapes the results of a practice or several teams | AY86: Drives a practice's results while delivering the hardest work | AZ86: Works at C1: Changes results across a sub-function or across products | BA86: Less than 8–12 yrs · Player-Coach, set by the role, not by years | BB86: 8–12 yrs · Player-Coach, set by the role, not by years · market 9–14 yrs | BC86: More than 8–12 yrs · Player-Coach, set by the role, not by years | BD86: Below: Postgraduate or professional qualification preferred | BE86: Postgraduate or professional qualification preferred | BF86: Above: Postgraduate / professional qualification preferred
A87: R029 | B87: AI / ML & GenAI Engineering · IC | C87: Engineering & Development | D87: IC | E87: ROLE | F87: A1 · A2 · A3 · B1 · B2 | G87: Band A · all tracks · Technology & engineering | H87: 12 | I87: H | J87: M | K87: L | L87: L | M87: L | N87: L | O87: L | P87: H | Q87: M | R87: M | S87: L | T87: L | U87: L | V87: L | AD87: =IF(W87<>"",W87,I87) -> H | AE87: =IF(X87<>"",X87,J87) -> M | AF87: =IF(Y87<>"",Y87,K87) -> L | AG87: =IF(Z87<>"",Z87,L87) -> L | AH87: =IF(AA87<>"",AA87,M87) -> L | AI87: =IF(AB87<>"",AB87,N87) -> L | AJ87: =IF(AC87<>"",AC87,O87) -> L | AK87: =COUNTA(W87:AC87) -> 0
A88: R029 | B88: AI / ML & GenAI Engineering · IC | C88: Engineering & Development | D88: IC | E88: level | F88: B2 | G88: Senior Specialist – AI / ML & GenAI Engineering | H88: 1 | AL88: Works at B1: Domain specialist work | AM88: Hardest problems in the domain | AN88: Works at B3: Sets standards for a practice; cross-team problems | AO88: Works at B1: Technical / QC / client calls for the domain | AP88: Allocates people and sets team priorities | AQ88: Works at B3: Commercial / strategic calls for the unit | AR88: Works at B1: A domain or a small team | AS88: One team or a client portfolio | AT88: Works at B3: Several teams or a practice | AU88: Works at B1: IC: mentors and reviews · People: hands-on team lead of 3–5 | AV88: IC: guides others in the domain · People: manages a team of 6+ | AW88: Works at B3: IC: leads a practice · People: team leads / managers report in | AX88: Works at B1: Moves a module's, product area's or client account's results | AY88: Visible effect on a team's or client portfolio's revenue, quality or compliance | AZ88: Works at B3: Shapes the results of a practice or several teams | BA88: Less than 6–8 yrs | BB88: 6–8 yrs · market 6–10 yrs | BC88: More than 6–8 yrs | BD88: Below: Graduate + relevant qualification or certification preferred | BE88: Graduate or postgraduate; professional qualification preferred | BF88: Above: Postgraduate or professional qualification preferred
A89: R029 | B89: AI / ML & GenAI Engineering · IC | C89: Engineering & Development | D89: IC | E89: level | F89: B1 | G89: AI/ML Specialist | H89: 3 | AL89: Works at A3: Varied and non-standard work; handles exceptions | AM89: Domain specialist work · in this role: AI/ML · Python | AN89: Works at B2: Hardest problems in the domain | AO89: Works at A3: Technical / QC / client calls on own work | AP89: Technical / QC / client calls for the domain | AQ89: Works at B2: Allocates people and sets team priorities | AR89: Works at A3: A module / process, or work with client or regulatory consequences | AS89: A domain or a small team | AT89: Works at B2: One team or a client portfolio | AU89: Works at A3: contributes alone; guides others only informally | AV89: IC: mentors and reviews · People: hands-on team lead of 3–5 | AW89: Works at B2: IC: guides others in the domain · People: manages a team of 6+ | AX89: Works at A3: A process or client deliverable depends on this work | AY89: Moves a module's, product area's or client account's results | AZ89: Works at B2: Visible effect on a team's or client portfolio's revenue, quality or compliance | BA89: Less than 4–6 yrs | BB89: 4–6 yrs · market 4–8 yrs | BC89: More than 4–6 yrs | BD89: Below: Graduate; relevant certification preferred | BE89: Graduate + relevant qualification or certification preferred | BF89: Above: Graduate or postgraduate; professional qualification preferred
A90: R029 | B90: AI / ML & GenAI Engineering · IC | C90: Engineering & Development | D90: IC | E90: level | F90: A3 | G90: Senior AI/ML Engineer | H90: 4 | AL90: Works at A2: Standard work of the discipline | AM90: Varied and non-standard work; handles exceptions · in this role: AI/ML · Python | AN90: Works at B1: Domain specialist work | AO90: Works at A2: Chooses own approach within standards | AP90: Technical / QC / client calls on own work | AQ90: Works at B1: Technical / QC / client calls for the domain | AR90: Works at A2: Own deliverables · accuracy, TAT | AS90: A module / process, or work with client or regulatory consequences | AT90: Works at B1: A domain or a small team | AU90: Works at A2: contributes alone; guides others only informally | AV90: Helps peers and newer people informally · None · guides 1–3 juniors informally | AW90: Works at B1: IC: mentors and reviews · People: hands-on team lead of 3–5 | AX90: Works at A2: Own deliverables feed a team's output and turnaround | AY90: A process or client deliverable depends on this work | AZ90: Works at B1: Moves a module's, product area's or client account's results | BA90: Less than 2–4 yrs | BB90: 2–4 yrs · market 2–5 yrs | BC90: More than 2–4 yrs | BD90: Below: Graduate · or diploma with experience | BE90: Graduate; relevant certification preferred | BF90: Above: Graduate + relevant qualification or certification preferred
A91: R029 | B91: AI / ML & GenAI Engineering · IC | C91: Engineering & Development | D91: IC | E91: level | F91: A2 | G91: AI/ML Engineer | H91: 3 | AL91: Works at A1: Learning; follows worked examples | AM91: Standard work of the discipline · in this role: AI/ML | AN91: Works at A3: Varied and non-standard work; handles exceptions | AO91: Works at A1: Needs approval / close guidance | AP91: Chooses own approach within standards | AQ91: Works at A3: Technical / QC / client calls on own work | AR91: Works at A1: Learning tasks | AS91: Own deliverables · accuracy, TAT | AT91: Works at A3: A module / process, or work with client or regulatory consequences | AU91: Works at A1: contributes alone; guides others only informally | AV91: Helps peers and newer people informally · No direct reports | AW91: Works at A3: Not scored in Band A | AX91: Works at A1: Learning; little direct effect on business results yet | AY91: Own deliverables feed a team's output and turnaround | AZ91: Works at A3: A process or client deliverable depends on this work | BA91: Less than 0–2 yrs | BB91: 0–2 yrs · market 0–3 yrs | BC91: More than 0–2 yrs | BD91: Below: Pursuing or completed graduation / diploma | BE91: Graduate · or diploma with experience | BF91: Above: Graduate; relevant certification preferred
A92: R029 | B92: AI / ML & GenAI Engineering · IC | C92: Engineering & Development | D92: IC | E92: level | F92: A1 | G92: Trainee AI/ML Engineer | H92: 1 | AL92: Not yet at the entry standard | AM92: Learning; follows worked examples · in this role: AI/ML · Python | AN92: Works at A2: Standard work of the discipline | AO92: Not yet at the entry standard | AP92: Needs approval / close guidance | AQ92: Works at A2: Chooses own approach within standards | AR92: Not yet at the entry standard | AS92: Learning tasks | AT92: Works at A2: Own deliverables · accuracy, TAT | AU92: Not yet at the entry standard | AV92: Helps peers and newer people informally · No direct reports | AW92: Works at A2: Not scored in Band A | AX92: Not yet at the entry standard | AY92: Learning; little direct effect on business results yet | AZ92: Works at A2: Own deliverables feed a team's output and turnaround | BA92: Less than Intern / trainee · first year | BB92: Intern / trainee · first year · market — yrs | BC92: More than Intern / trainee · first year | BD92: Still studying | BE92: Pursuing or completed graduation / diploma | BF92: Above: Graduate · or diploma with experience
A93: R030 | B93: Application Maintenance & Production Support · IC | C93: Engineering & Development | D93: IC | E93: ROLE | F93: A3 | G93: Band A · all tracks · Technology & engineering | H93: 6 | I93: H | J93: M | K93: L | L93: L | M93: L | N93: L | O93: L | P93: H | Q93: M | R93: M | S93: L | T93: L | U93: L | V93: L | AD93: =IF(W93<>"",W93,I93) -> H | AE93: =IF(X93<>"",X93,J93) -> M | AF93: =IF(Y93<>"",Y93,K93) -> L | AG93: =IF(Z93<>"",Z93,L93) -> L | AH93: =IF(AA93<>"",AA93,M93) -> L | AI93: =IF(AB93<>"",AB93,N93) -> L | AJ93: =IF(AC93<>"",AC93,O93) -> L | AK93: =COUNTA(W93:AC93) -> 0
A94: R030 | B94: Application Maintenance & Production Support · IC | C94: Engineering & Development | D94: IC | E94: level | F94: A3 | G94: Senior Software Engineer | H94: 6 | AL94: Works at A2: Standard work of the discipline | AM94: Varied and non-standard work; handles exceptions · in this role: NET MVC | AN94: Works at B1: Domain specialist work | AO94: Works at A2: Chooses own approach within standards | AP94: Technical / QC / client calls on own work | AQ94: Works at B1: Technical / QC / client calls for the domain | AR94: Works at A2: Own deliverables · accuracy, TAT | AS94: A module / process, or work with client or regulatory consequences · KRA themes: Common themes in manager-set KRAs: considering critical · stories considering · leakage qa/uat · production support · live production · … | AT94: Works at B1: A domain or a small team | AU94: Works at A2: contributes alone; guides others only informally | AV94: Helps peers and newer people informally · None · guides 1–3 juniors informally | AW94: Works at B1: IC: mentors and reviews · People: hands-on team lead of 3–5 | AX94: Works at A2: Own deliverables feed a team's output and turnaround | AY94: A process or client deliverable depends on this work | AZ94: Works at B1: Moves a module's, product area's or client account's results | BA94: Less than 2–4 yrs | BB94: 2–4 yrs · market 2–5 yrs | BC94: More than 2–4 yrs | BD94: Below: Graduate · or diploma with experience | BE94: Graduate; relevant certification preferred | BF94: Above: Graduate + relevant qualification or certification preferred
A95: R031 | B95: Backend Development · Consultant | C95: Engineering & Development | D95: Consultant | E95: ROLE | F95: X1 | G95: Consultant · outside the ladder · Technology & engineering | H95: 16 | AD95: =IF(W95<>"",W95,I95) -> 0 | AE95: =IF(X95<>"",X95,J95) -> 0 | AF95: =IF(Y95<>"",Y95,K95) -> 0 | AG95: =IF(Z95<>"",Z95,L95) -> 0 | AH95: =IF(AA95<>"",AA95,M95) -> 0 | AI95: =IF(AB95<>"",AB95,N95) -> 0 | AJ95: =IF(AC95<>"",AC95,O95) -> 0 | AK95: =COUNTA(W95:AC95) -> 0
A96: R032 | B96: Backend Development · IC | C96: Engineering & Development | D96: IC | E96: ROLE | F96: A1 · A2 · A3 · B1 · B2 · B3 · C1 | G96: Band A · all tracks · Technology & engineering | H96: 79 | I96: H | J96: M | K96: L | L96: L | M96: L | N96: L | O96: L | P96: H | Q96: M | R96: M | S96: L | T96: L | U96: L | V96: L | AD96: =IF(W96<>"",W96,I96) -> H | AE96: =IF(X96<>"",X96,J96) -> M | AF96: =IF(Y96<>"",Y96,K96) -> L | AG96: =IF(Z96<>"",Z96,L96) -> L | AH96: =IF(AA96<>"",AA96,M96) -> L | AI96: =IF(AB96<>"",AB96,N96) -> L | AJ96: =IF(AC96<>"",AC96,O96) -> L | AK96: =COUNTA(W96:AC96) -> 0
A97: R032 | B97: Backend Development · IC | C97: Engineering & Development | D97: IC | E97: level | F97: C1 | G97: Principal – Backend Development | H97: 2 | AL97: Works at B3: Sets standards for a practice; cross-team problems | AM97: Ambiguous, cross-product problems | AN97: Works at C2: Function-wide or company-wide problems; creates methods and standards | AO97: Works at B3: Commercial / strategic calls for the unit | AP97: Sets direction for a sub-function or domain | AQ97: Works at C2: Sets direction for a function | AR97: Works at B3: Several teams or a practice | AS97: Sub-function results or domain quality across products | AT97: Works at C2: Function results, budget and risk | AU97: Works at B3: IC: leads a practice · People: team leads / managers report in | AV97: Leads managers or a community of practice | AW97: Works at C2: Leads a function; shapes functional strategy | AX97: Works at B3: Shapes the results of a practice or several teams | AY97: Changes results across a sub-function or across products | AZ97: Works at C2: Drives a function's or department's results and costs | BA97: Less than 10–13 yrs | BB97: 10–13 yrs · market 12–17 yrs | BC97: More than 10–13 yrs | BD97: Below: Postgraduate or professional qualification preferred | BE97: Postgraduate / professional qualification preferred | BF97: Above: Postgraduate / professional qualification preferred
A98: R032 | B98: Backend Development · IC | C98: Engineering & Development | D98: IC | E98: level | F98: B3 | G98: Lead Software Engineer | H98: 3 | AL98: Works at B2: Hardest problems in the domain | AM98: Sets standards for a practice; cross-team problems · in this role: Java · NET MVC | AN98: Works at C1: Ambiguous, cross-product problems | AO98: Works at B2: Allocates people and sets team priorities | AP98: Commercial / strategic calls for the unit | AQ98: Works at C1: Sets direction for a sub-function or domain | AR98: Works at B2: One team or a client portfolio | AS98: Several teams or a practice · KRA themes: Common themes in manager-set KRAs: technical · defect · quality · agreed · deliver · reviews | AT98: Works at C1: Sub-function results or domain quality across products | AU98: Works at B2: IC: guides others in the domain · People: manages a team of 6+ | AV98: IC: leads a practice · People: team leads / managers report in | AW98: Works at C1: Leads managers or a community of practice | AX98: Works at B2: Visible effect on a team's or client portfolio's revenue, quality or compliance | AY98: Shapes the results of a practice or several teams | AZ98: Works at C1: Changes results across a sub-function or across products | BA98: Less than 8–10 yrs | BB98: 8–10 yrs · market 8–13 yrs | BC98: More than 8–10 yrs | BD98: Below: Graduate or postgraduate; professional qualification preferred | BE98: Postgraduate or professional qualification preferred | BF98: Above: Postgraduate / professional qualification preferred
A99: R032 | B99: Backend Development · IC | C99: Engineering & Development | D99: IC | E99: level | F99: B2 | G99: Senior Technical Specialist | H99: 7 | AL99: Works at B1: Domain specialist work | AM99: Hardest problems in the domain · in this role: NET MVC · Java | AN99: Works at B3: Sets standards for a practice; cross-team problems | AO99: Works at B1: Technical / QC / client calls for the domain | AP99: Allocates people and sets team priorities | AQ99: Works at B3: Commercial / strategic calls for the unit | AR99: Works at B1: A domain or a small team | AS99: One team or a client portfolio · KRA themes: Common themes in manager-set KRAs: modules · coverage · complete · components · committed · sprint | AT99: Works at B3: Several teams or a practice | AU99: Works at B1: IC: mentors and reviews · People: hands-on team lead of 3–5 | AV99: IC: guides others in the domain · People: manages a team of 6+ | AW99: Works at B3: IC: leads a practice · People: team leads / managers report in | AX99: Works at B1: Moves a module's, product area's or client account's results | AY99: Visible effect on a team's or client portfolio's revenue, quality or compliance | AZ99: Works at B3: Shapes the results of a practice or several teams | BA99: Less than 6–8 yrs | BB99: 6–8 yrs · market 6–10 yrs | BC99: More than 6–8 yrs | BD99: Below: Graduate + relevant qualification or certification preferred | BE99: Graduate or postgraduate; professional qualification preferred | BF99: Above: Postgraduate or professional qualification preferred
A100: R032 | B100: Backend Development · IC | C100: Engineering & Development | D100: IC | E100: level | F100: B1 | G100: Technical Specialist | H100: 10 | AL100: Works at A3: Varied and non-standard work; handles exceptions | AM100: Domain specialist work · in this role: Problem Solving · NET MVC · Java · Database Management · Production Support | AN100: Works at B2: Hardest problems in the domain | AO100: Works at A3: Technical / QC / client calls on own work | AP100: Technical / QC / client calls for the domain | AQ100: Works at B2: Allocates people and sets team priorities | AR100: Works at A3: A module / process, or work with client or regulatory consequences | AS100: A domain or a small team · KRA themes: Common themes in manager-set KRAs: reduce · production · time · quarterly · incidents resolved · stability critical | AT100: Works at B2: One team or a client portfolio | AU100: Works at A3: contributes alone; guides others only informally | AV100: IC: mentors and reviews · People: hands-on team lead of 3–5 | AW100: Works at B2: IC: guides others in the domain · People: manages a team of 6+ | AX100: Works at A3: A process or client deliverable depends on this work | AY100: Moves a module's, product area's or client account's results | AZ100: Works at B2: Visible effect on a team's or client portfolio's revenue, quality or compliance | BA100: Less than 4–6 yrs | BB100: 4–6 yrs · market 4–8 yrs | BC100: More than 4–6 yrs | BD100: Below: Graduate; relevant certification preferred | BE100: Graduate + relevant qualification or certification preferred | BF100: Above: Graduate or postgraduate; professional qualification preferred
...

Sheet 4. Market Benchmark
A1: Market Benchmark — Low / Medium / High, with the evidence behind each | M1: ◂ Start
A2: Sheet 4 · How much each parameter counts in published job-evaluation methods, by role group, turned into Low / Medium / High. Rule: a share of 30% or more of the points is High; 9% to under 30% is Medium; under 9% is Low. Each row shows the published numbers it rests on. Experience and Education: every method folds them into knowledge, so the market weights them Low on their own.
A3: IRIS · Job Architecture Model v2.0 · October 2026 · Internal — Confidential · HR and business leaders
A5: 1 · Weightage by role group and parameter
A6: Role group | B6: Parameter | C6: Market · L/M/H | D6: Korn Ferry Hay | E6: Mercer IPE | F6: Public plans · average of 5 | G6: Market average | H6: Why this rating | I6: References
A7: Band A · all tracks | B7: Complexity & Expertise | C7: H | D7: 81% | E7: 62% | F7: 63% | G7: 69% | H7: Average 69% of the points · at or above 30% → High · Complexity here includes knowledge and experience, as the methods publish it | I7: S46–S51 Korn Ferry Hay evaluations · S04, S52 Mercer IPE · S53–S57 NHS, UK NJC/PSC, GLPC, SJC, US OPM point-factor plans
A8: Band A · all tracks | B8: Autonomy & Decision | C8: M | D8: 11% | E8: 22% | F8: 15% | G8: 16% | H8: Average 16% of the points · below 30% and at or above 9% → Medium | I8: S46–S51 Korn Ferry Hay evaluations · S04, S52 Mercer IPE · S53–S57 NHS, UK NJC/PSC, GLPC, SJC, US OPM point-factor plans
A9: Band A · all tracks | B9: Accountability & Impact | C9: M | D9: 4% | E9: 8% | F9: 15% | G9: 9% | H9: Average 9% of the points · below 30% and at or above 9% → Medium | I9: S46–S51 Korn Ferry Hay evaluations · S04, S52 Mercer IPE · S53–S57 NHS, UK NJC/PSC, GLPC, SJC, US OPM point-factor plans
A10: Band A · all tracks | B10: Leadership & Strategy | C10: L | D10: 0% | E10: 0% | F10: 0% | G10: 0% | H10: Average 0% of the points · below 30% and below 9% → Low | I10: S46–S51 Korn Ferry Hay evaluations · S04, S52 Mercer IPE · S53–S57 NHS, UK NJC/PSC, GLPC, SJC, US OPM point-factor plans
A11: Band A · all tracks | B11: Business Impact | C11: L | D11: 4% | E11: 8% | F11: 7% | G11: 6% | H11: Average 6% of the points · below 30% and below 9% → Low | I11: S46–S51 Korn Ferry Hay evaluations · S04, S52 Mercer IPE · S53–S57 NHS, UK NJC/PSC, GLPC, SJC, US OPM point-factor plans
A12: Band A · all tracks | B12: Experience | C12: L | D12: in know-how | E12: in knowledge | F12: in knowledge / KTE | G12: not separate | H12: No published method weights it on its own: Hay know-how includes all knowledge and experience however acquired; Mercer IPE knowledge; NHS knowledge, training and experience. Skills-first evidence argues for a low weight. | I12: S05, S49 Hay · S04, S52 Mercer IPE · S53 NHS · S58 McKinsey · S59 Deloitte · S60 WEF · S61 EY India
A13: Band A · all tracks | B13: Education | C13: L | D13: in know-how | E13: in knowledge | F13: in knowledge / KTE | G13: not separate | H13: No published method weights it on its own: Hay know-how includes all knowledge and experience however acquired; Mercer IPE knowledge; NHS knowledge, training and experience. Skills-first evidence argues for a low weight. | I13: S05, S49 Hay · S04, S52 Mercer IPE · S53 NHS · S58 McKinsey · S59 Deloitte · S60 WEF · S61 EY India
A14: Band B · Specialist / POD Lead | B14: Complexity & Expertise | C14: H | D14: 64% | E14: 61% | F14: 58% | G14: 61% | H14: Average 61% of the points · at or above 30% → High · Complexity here includes knowledge and experience, as the methods publish it | I14: S46–S51 Korn Ferry Hay evaluations · S04, S52 Mercer IPE · S53–S57 NHS, UK NJC/PSC, GLPC, SJC, US OPM point-factor plans
A15: Band B · Specialist / POD Lead | B15: Autonomy & Decision | C15: M | D15: 19% | E15: 18% | F15: 15% | G15: 17% | H15: Average 17% of the points · below 30% and at or above 9% → Medium | I15: S46–S51 Korn Ferry Hay evaluations · S04, S52 Mercer IPE · S53–S57 NHS, UK NJC/PSC, GLPC, SJC, US OPM point-factor plans
A16: Band B · Specialist / POD Lead | B16: Accountability & Impact | C16: M | D16: 6% | E16: 8% | F16: 15% | G16: 10% | H16: Average 10% of the points · below 30% and at or above 9% → Medium | I16: S46–S51 Korn Ferry Hay evaluations · S04, S52 Mercer IPE · S53–S57 NHS, UK NJC/PSC, GLPC, SJC, US OPM point-factor plans
A17: Band B · Specialist / POD Lead | B17: Leadership & Strategy | C17: L | D17: 5% | E17: 5% | F17: 5% | G17: 5% | H17: Average 5% of the points · below 30% and below 9% → Low | I17: S46–S51 Korn Ferry Hay evaluations · S04, S52 Mercer IPE · S53–S57 NHS, UK NJC/PSC, GLPC, SJC, US OPM point-factor plans
... A62: Bands D–E · Leadership | B62: Education | C62: L | D62: in know-how | E62: in knowledge | F62: in knowledge / KTE | G62: not separate | H62: No published method weights it on its own: Hay know-how includes all knowledge and experience however acquired; Mercer IPE knowledge; NHS knowledge, training and experience. Skills-first evidence argues for a low weight. | I62: S05, S49 Hay · S04, S52 Mercer IPE · S53 NHS · S58 McKinsey · S59 Deloitte · S60 WEF · S61 EY India
A64: 2 · The public point-factor plans — published factor shares
A65: Plan | B65: Complexity & Expertise | C65: Autonomy & Decision | D65: Accountability & Impact | E65: Leadership & Strategy | F65: Business Impact | G65: Effort and conditions removed | H65: Source
A66: NHS Agenda for Change Job Evaluation Scheme · 16 factors, 1,000 points | B66: 40.0% | C66: 6.7% | D66: 20.0% | E66: 26.7% | F66: 6.7% | G66: 10.0% | H66: NHS Job Evaluation Handbook, ch. 6 para 1.5 — nhsemployers.org/sites/default/files/pdf/22/165.pdf
A67: UK local government 13-factor scheme · Police Staff Council version of the NJC scheme, 1,000 points | B67: 38.3% | C67: 13.0% | D67: 19.5% | E67: 19.5% | F67: 9.8% | G67: 20.0% | H67: PSC Handbook pp. 47–48 — lb2.local.gov.uk/sites/default/files/documents/police-staff-council-13-f-342.pdf · NJC's own table sits behind the LGA log-in · Exact for PSC; NJC assumed equal
A68: Greater London Provincial Council scheme · 11 factors, 948 points | B68: 45.0% | C68: 12.1% | D68: 6.0% | E68: 29.7% | F68: 7.2% | G68: 12.7% | H68: GLPC points weighting — sirddinbych.gov.uk/en/documents/jobs-and-employees/my-employment/reorganisation-and-change/glpc-points-weighting.pdf
A69: Scottish Joint Council scheme · 13 factors, 1,000 points | B69: 38.3% | C69: 13.0% | D69: 19.5% | E69: 19.5% | F69: 9.8% | G69: 20.0% | H69: Highland Council SJC scoring matrix — highland.gov.uk/download/downloads/id/3889/scoring_matrix.pdf
A70: US OPM Factor Evaluation System · 9 factors, 4,480 points | B70: 52.5% | C70: 29.7% | D70: 10.3% | E70: 7.5% | F70: 0.0% | G70: 2.2% | H70: OPM Introduction to the Position Classification Standards, Appendix 3 — opm.gov/…/positionclassificationintro.pdf
A71: Average of the five plans | B71: 42.8% | C71: 14.9% | D71: 15.1% | E71: 20.6% | F71: 6.7% | G71: Experience as a separate factor: none of the five
A72: Range | B72: 38–52% | C72: 7–30% | D72: 6–20% | E72: 8–30% | F72: 0–10%
A74: Plan | B74: How its factors were mapped to the IRIS factors
A76: 3 · Level benchmarks — the market data the ratings are checked against
A77: Level | B77: IRIS experience · distinct | C77: Market experience | D77: Accenture India | E77: Infosys | F77: Microsoft / Amazon | G77: Radford / Mercer | H77: SFIA 9 | I77: Span norm · McKinsey | J77: References
A78: E2 | B78: 22+ yrs · board appointment | C78: — | D78: — | E78: — | F78: — | G78: E6 | H78: 7 | I78: Executive team | J78: S32 Google, Microsoft, Amazon · S33 Infosys · S35 Accenture India · IRIS experience guide · S01 Aon Radford · S02 Pave · S08 SFIA 9 · S03 Mercer career levels · S09 McKinsey spans of control · S37 GitLab layers · S44 Google Tech Lead Manager
A79: E1 | B79: 22+ yrs | C79: — | D79: — | E79: — | F79: — | G79: E5 | H79: 7 | I79: 5–8 function heads | J79: S32 Google, Microsoft, Amazon · S33 Infosys · S35 Accenture India · IRIS experience guide · S01 Aon Radford · S02 Pave · S08 SFIA 9 · S03 Mercer career levels · S09 McKinsey spans of control · S37 GitLab layers · S44 Google Tech Lead Manager
A80: D2 | B80: 19–22 yrs | C80: — | D80: — | E80: — | F80: — | G80: E3–E4 | H80: 7 Set strategy | I80: 5–8 AVPs / heads | J80: S32 Google, Microsoft, Amazon · S33 Infosys · S35 Accenture India · IRIS experience guide · S01 Aon Radford · S02 Pave · S08 SFIA 9 · S03 Mercer career levels · S09 McKinsey spans of control · S37 GitLab layers · S44 Google Tech Lead Manager
A81: D1 | B81: 16–19 yrs | C81: — | D81: — | E81: — | F81: — | G81: E1–E2 | H81: 6–7 | I81: 5–8 heads | J81: S32 Google, Microsoft, Amazon · S33 Infosys · S35 Accenture India · IRIS experience guide · S01 Aon Radford · S02 Pave · S08 SFIA 9 · S03 Mercer career levels · S09 McKinsey spans of control · S37 GitLab layers · S44 Google Tech Lead Manager
A82: C+ | B82: 13–17 yrs · Player-Coach, set by the role, not by years | C82: 15–18 | D82: 15+ | E82: 15+ | F82: — | G82: M6 / E1 | H82: 6 Initiate, influence | I82: 4–8 managers / leads with ≥ 25% of time on own principal delivery | J82: S32 Google, Microsoft, Amazon · S33 Infosys · S35 Accenture India · IRIS experience guide · S01 Aon Radford · S02 Pave · S08 SFIA 9 · S03 Mercer career levels · S09 McKinsey spans of control · S37 GitLab layers · S44 Google Tech Lead Manager
A83: C2 | B83: 13–16 yrs | C83: — | D83: — | E83: — | F83: — | G83: P7 / M6 | H83: 6 Initiate, influence | I83: 5–8 managers / associate heads | J83: S32 Google, Microsoft, Amazon · S33 Infosys · S35 Accenture India · IRIS experience guide · S01 Aon Radford · S02 Pave · S08 SFIA 9 · S03 Mercer career levels · S09 McKinsey spans of control · S37 GitLab layers · S44 Google Tech Lead Manager
A84: C1 | B84: 10–13 yrs | C84: 12–17 | D84: 12–16 | E84: 12–18 | F84: — | G84: P6 / M5 | H84: 5–6 | I84: 5–8, mostly managers | J84: S32 Google, Microsoft, Amazon · S33 Infosys · S35 Accenture India · IRIS experience guide · S01 Aon Radford · S02 Pave · S08 SFIA 9 · S03 Mercer career levels · S09 McKinsey spans of control · S37 GitLab layers · S44 Google Tech Lead Manager
A85: B+ | B85: 8–12 yrs · Player-Coach, set by the role, not by years | C85: 9–14 | D85: 9–13 | E85: 9–14 | F85: ≈ 8+ · Amazon L6 / Google TLM | G85: P5–P6 / M4–M5 | H85: 5 Ensure, advise | I85: 3–6 direct reports with ≥ 40% of time on own delivery · McKinsey player/coach 3–5; Google Tech Lead Manager | J85: S32 Google, Microsoft, Amazon · S33 Infosys · S35 Accenture India · IRIS experience guide · S01 Aon Radford · S02 Pave · S08 SFIA 9 · S03 Mercer career levels · S09 McKinsey spans of control · S37 GitLab layers · S44 Google Tech Lead Manager
A86: B3 | B86: 8–10 yrs | C86: 8–13 | D86: 9–13 | E86: 9–14 | F86: ≈ 8 · Amazon L6 | G86: P5 / M4 | H86: 5 Ensure, advise | I86: IC: none · People: 5–8 incl. team leads | J86: S32 Google, Microsoft, Amazon · S33 Infosys · S35 Accenture India · IRIS experience guide · S01 Aon Radford · S02 Pave · S08 SFIA 9 · S03 Mercer career levels · S09 McKinsey spans of control · S37 GitLab layers · S44 Google Tech Lead Manager
A87: B2 | B87: 6–8 yrs | C87: 6–10 | D87: 7–10 | E87: 6–11 | F87: 5–8+ · MS 63 | G87: P4 / M3 | H87: 4–5 | I87: IC: none · People: 6–8 knowledge work, 8–12 standardised delivery | J87: S32 Google, Microsoft, Amazon · S33 Infosys · S35 Accenture India · IRIS experience guide · S01 Aon Radford · S02 Pave · S08 SFIA 9 · S03 Mercer career levels · S09 McKinsey spans of control · S37 GitLab layers · S44 Google Tech Lead Manager
A88: B1 | B88: 4–6 yrs | C88: 4–8 | D88: 5–8 | E88: 4–8 | F88: 2–3+ · Amazon L5 | G88: P3 / M2 | H88: 4 Enable | I88: IC: none · Team Lead: 3–5 | J88: S32 Google, Microsoft, Amazon · S33 Infosys · S35 Accenture India · IRIS experience guide · S01 Aon Radford · S02 Pave · S08 SFIA 9 · S03 Mercer career levels · S09 McKinsey spans of control · S37 GitLab layers · S44 Google Tech Lead Manager
... A91: A1 | B91: Intern / trainee · first year | C91: — | D91: — | E91: — | F91: — | G91: Entry / P1 · intern | H91: 1 Follow | I91: No direct reports | J91: S32 Google, Microsoft, Amazon · S33 Infosys · S35 Accenture India · IRIS experience guide · S01 Aon Radford · S02 Pave · S08 SFIA 9 · S03 Mercer career levels · S09 McKinsey spans of control · S37 GitLab layers · S44 Google Tech Lead Manager

Sheet 5. Talent Mapping
A1: Talent Mapping — every person, top down | Q1: ◂ Start
A2: Sheet 5 · Read left to right: who they are → what they and their manager told us → where IRIS placed them → what the market says → how much each parameter counts · IRIS, Market, Leader → how they rate · IRIS, then yours → your proposed level and band. Blank = nothing received. Yellow = yours. Your columns stay blank until you give an input.
A3: IRIS · Job Architecture Model v2.0 · October 2026 · Internal — Confidential · HR and business leaders
A4: Section colours: each column group has its own header colour and a matching light tint | E4: Changed vs current | G4: Level up | H4: Level down · pay & title protected | J4: Newly mapped | K4: Player-Coach · B+ · C+ | M4: RED = critical input needed · says what and who | P4: YELLOW = to complete or edit | R4: GREY = pay · set later
A5: WHO | L5: WHAT THEY TOLD US — blank = not received | S5: IRIS PLACEMENT | AC5: MARKET | AG5: WEIGHTAGE · IRIS | AN5: WEIGHTAGE · MARKET | AU5: WEIGHTAGE · LEADER — set on 3. Role Model | BB5: RATING · IRIS — vs the level · blank = no input | BI5: RATING · LEADER — yours · L / M / H vs the level | BP5: LEADER PROPOSAL — blank until you give an input | BW5: ENGINE
A6: Business | B6: Department | C6: Layer from the CEO | D6: Emp ID | E6: Employee name | F6: Current designation | G6: Reporting manager | H6: Manager Emp ID | I6: Total exp. · yrs | J6: Qualification | K6: Current level · as is | L6: Survey · questions answered | M6: What they shared | N6: KRAs from the manager | O6: Performance · rating · potential · 9-box | P6: Evidence used for the ratings | Q6: All their data ▸ | R6: Person card ▸ | S6: Job family | T6: Sub-family | U6: Role ID | V6: Role | W6: IRIS proposed level | X6: IRIS proposed band | Y6: Standard title for the role and level | Z6: Title change | AA6: How IRIS placed them | AB6: Structure flag | AC6: Market level · published weights | AD6: Experience vs the level · market | AE6: Span vs the norm | AF6: Radford / Mercer · SFIA 9 | AG6: Weightage IRIS · Complexity & Expertise | AH6: Weightage IRIS · Autonomy & Decision | AI6: Weightage IRIS · Accountability & Impact | AJ6: Weightage IRIS · Leadership & Strategy | AK6: Weightage IRIS · Business Impact | AL6: Weightage IRIS · Experience | AM6: Weightage IRIS · Education | AN6: Weightage Market · Complexity & Expertise | AO6: Weightage Market · Autonomy & Decision | AP6: Weightage Market · Accountability & Impact | AQ6: Weightage Market · Leadership & Strategy | AR6: Weightage Market · Business Impact | AS6: Weightage Market · Experience | AT6: Weightage Market · Education | AU6: Weightage Leader · Complexity & Expertise | AV6: Weightage Leader · Autonomy & Decision | AW6: Weightage Leader · Accountability & Impact | AX6: Weightage Leader · Leadership & Strategy | AY6: Weightage Leader · Business Impact | AZ6: Weightage Leader · Experience | BA6: Weightage Leader · Education | BB6: Rating IRIS · Complexity & Expertise | BC6: Rating IRIS · Autonomy & Decision | BD6: Rating IRIS · Accountability & Impact | BE6: Rating IRIS · Leadership & Strategy | BF6: Rating IRIS · Business Impact | BG6: Rating IRIS · Experience | BH6: Rating IRIS · Education | BI6: Rating Leader · Complexity & Expertise | BJ6: Rating Leader · Autonomy & Decision | BK6: Rating Leader · Accountability & Impact | BL6: Rating Leader · Leadership & Strategy | BM6: Rating Leader · Business Impact | BN6: Rating Leader · Experience | BO6: Rating Leader · Education | BP6: Leader override · any level | BQ6: Leader proposed level | BR6: Leader proposed band | BS6: Move vs IRIS | BT6: Level in force · leader if given, else IRIS | BU6: Manager check · live | BV6: Leader comment | BW6: pI C | BX6: pI Au | BY6: pI Ac | BZ6: pI L | CA6: pI BI | CB6: pI Exp | CC6: pI Edu | CD6: pE C | CE6: pE Au | CF6: pE Ac | CG6: pE L | CH6: pE BI | CI6: pE Exp | CJ6: pE Edu | CK6: dI C | CL6: dI Au | CM6: dI Ac | CN6: dI L | CO6: dI BI | CP6: dI Exp | CQ6: dI Edu | CR6: dE C | CS6: dE Au | CT6: dE Ac | CU6: dE L | CV6: dE BI | CW6: dE Exp | CX6: dE Edu | CY6: Inputs | CZ6: Net IRIS | DA6: Net leader
A7: Corporate | B7: Management | C7: 0 | D7: IRIS0001 | E7: Balachandran K | F7: CEO | G7: — · top of the organisation | I7: 32.1 | J7: MBA | O7: Latest rating: Not rated · manager · 9-box: Not placed · manager | Q7: Open ▸ | R7: Card ▸ | S7: Enterprise Leadership | T7: Chief Executive | U7: R039 | V7: Chief Executive · Manager | W7: E2 | X7: Band E · Enterprise leadership | Y7: Chief Executive Officer | AA7: Placed at E2 by the evidence: six ratings × market-derived weights and rules R1–R13 · no move needed for the reporting line · Band E · Enterprise Leadership | AC7: E2 | AE7: 6 direct reports · norm Executive team | AF7: E6 · SFIA 7 | AG7: =IFERROR(IF(INDEX(RM_I_C,MATCH($U7,RM_KEY,0))="","",INDEX(RM_I_C,MATCH($U7,RM_KEY,0))),"") -> H | AH7: =IFERROR(IF(INDEX(RM_I_Au,MATCH($U7,RM_KEY,0))="","",INDEX(RM_I_Au,MATCH($U7,RM_KEY,0))),"") -> M | AI7: =IFERROR(IF(INDEX(RM_I_Ac,MATCH($U7,RM_KEY,0))="","",INDEX(RM_I_Ac,MATCH($U7,RM_KEY,0))),"") -> M | AJ7: =IFERROR(IF(INDEX(RM_I_L,MATCH($U7,RM_KEY,0))="","",INDEX(RM_I_L,MATCH($U7,RM_KEY,0))),"") -> M | AK7: =IFERROR(IF(INDEX(RM_I_BI,MATCH($U7,RM_KEY,0))="","",INDEX(RM_I_BI,MATCH($U7,RM_KEY,0))),"") -> L | AL7: =IFERROR(IF(INDEX(RM_I_Exp,MATCH($U7,RM_KEY,0))="","",INDEX(RM_I_Exp,MATCH($U7,RM_KEY,0))),"") -> L | AM7: =IFERROR(IF(INDEX(RM_I_Edu,MATCH($U7,RM_KEY,0))="","",INDEX(RM_I_Edu,MATCH($U7,RM_KEY,0))),"") -> L | AN7: =IFERROR(IF(INDEX(RM_M_C,MATCH($U7,RM_KEY,0))="","",INDEX(RM_M_C,MATCH($U7,RM_KEY,0))),"") -> H | AO7: =IFERROR(IF(INDEX(RM_M_Au,MATCH($U7,RM_KEY,0))="","",INDEX(RM_M_Au,MATCH($U7,RM_KEY,0))),"") -> M | AP7: =IFERROR(IF(INDEX(RM_M_Ac,MATCH($U7,RM_KEY,0))="","",INDEX(RM_M_Ac,MATCH($U7,RM_KEY,0))),"") -> M | AQ7: =IFERROR(IF(INDEX(RM_M_L,MATCH($U7,RM_KEY,0))="","",INDEX(RM_M_L,MATCH($U7,RM_KEY,0))),"") -> M | AR7: =IFERROR(IF(INDEX(RM_M_BI,MATCH($U7,RM_KEY,0))="","",INDEX(RM_M_BI,MATCH($U7,RM_KEY,0))),"") -> L | AS7: =IFERROR(IF(INDEX(RM_M_Exp,MATCH($U7,RM_KEY,0))="","",INDEX(RM_M_Exp,MATCH($U7,RM_KEY,0))),"") -> L | AT7: =IFERROR(IF(INDEX(RM_M_Edu,MATCH($U7,RM_KEY,0))="","",INDEX(RM_M_Edu,MATCH($U7,RM_KEY,0))),"") -> L | AU7: =IFERROR(IF(INDEX(RM_L_C,MATCH($U7,RM_KEY,0))="","",INDEX(RM_L_C,MATCH($U7,RM_KEY,0))),"") | AV7: =IFERROR(IF(INDEX(RM_L_Au,MATCH($U7,RM_KEY,0))="","",INDEX(RM_L_Au,MATCH($U7,RM_KEY,0))),"") | AW7: =IFERROR(IF(INDEX(RM_L_Ac,MATCH($U7,RM_KEY,0))="","",INDEX(RM_L_Ac,MATCH($U7,RM_KEY,0))),"") | AX7: =IFERROR(IF(INDEX(RM_L_L,MATCH($U7,RM_KEY,0))="","",INDEX(RM_L_L,MATCH($U7,RM_KEY,0))),"") | AY7: =IFERROR(IF(INDEX(RM_L_BI,MATCH($U7,RM_KEY,0))="","",INDEX(RM_L_BI,MATCH($U7,RM_KEY,0))),"") | AZ7: =IFERROR(IF(INDEX(RM_L_Exp,MATCH($U7,RM_KEY,0))="","",INDEX(RM_L_Exp,MATCH($U7,RM_KEY,0))),"") | BA7: =IFERROR(IF(INDEX(RM_L_Edu,MATCH($U7,RM_KEY,0))="","",INDEX(RM_L_Edu,MATCH($U7,RM_KEY,0))),"") | BG7: M | BH7: M | BQ7: =IF(CY7=0,"",IF(BP7<>"",BP7,IF(LEFT(W7,1)="X",W7,IF(OR(W7="B+",W7="C+"),INDEX(LAD_PC,MAX(1,MIN(14,MATCH(W7,LAD_PC,0)+IF((DA7-CZ7)>=0.5,1,IF((DA7-CZ7)<=-0.5,-1,0))))),INDEX(LAD_STD,MAX(1,MIN(12,MATCH(W7,LAD_STD,0)+IF((DA7-CZ7)>=0.5,1,IF((DA7-CZ7)<=-0.5,-1,0))))))))) | BR7: =IF(BQ7="","",IFERROR(CHOOSE(INDEX(B_RANK,MATCH(BQ7,B_LVL,0)),"Band A · Practitioner","Band B · Specialist / Manager","B+ · Player-Coach","Band C · Principal / Head","C+ · Player-Coach","Band D · Business leadership","Band E · Enterprise leadership"),"Band X · Consultant")) | BS7: =IF(BQ7="","",IF(BQ7=W7,"• Same",IF(INDEX(B_VAL,MATCH(BQ7,B_LVL,0))>INDEX(B_VAL,MATCH(W7,B_LVL,0)),"▲ Up","▼ Down"))) | BT7: =IF(BQ7<>"",BQ7,W7) -> E2 | BU7: =IFERROR(IF($H7="","—",IF(OR(LEFT(BT7,1)="X",LEFT(INDEX($BT$7:$BT$592,MATCH($H7,$D$7:$D$592,0)),1)="X"),"—",IF(AND(LEFT(BT7,1)="E",LEFT(INDEX($BT$7:$BT$592,MATCH($H7,$D$7:$D$592,0)),1)="E"),"Exception · Band E",IF(INDEX(B_VAL,MATCH(BT7,B_LVL,0))>=INDEX(B_VAL,MATCH(INDEX($BT$7:$BT$592,MATCH($H7,$D$7:$D$592,0)),B_LVL,0)),"⚠ At or above the manager",IF(INDEX(B_RANK,MATCH(BT7,B_LVL,0))=INDEX(B_RANK,MATCH(INDEX($BT$7:$BT$592,MATCH($H7,$D$7:$D$592,0)),B_LVL,0)),"⚠ Same band as the manager","OK"))))),"—") -> — | BW7: =IFERROR(INDEX(LMH_PTS,MATCH(AG7,LMH_KEY,0)),0) -> 9 | BX7: =IFERROR(INDEX(LMH_PTS,MATCH(AH7,LMH_KEY,0)),0) -> 3 | BY7: =IFERROR(INDEX(LMH_PTS,MATCH(AI7,LMH_KEY,0)),0) -> 3 | BZ7: =IFERROR(INDEX(LMH_PTS,MATCH(AJ7,LMH_KEY,0)),0) -> 3 | CA7: =IFERROR(INDEX(LMH_PTS,MATCH(AK7,LMH_KEY,0)),0) -> 1 | CB7: =IFERROR(INDEX(LMH_PTS,MATCH(AL7,LMH_KEY,0)),0) -> 1 | CC7: =IFERROR(INDEX(LMH_PTS,MATCH(AM7,LMH_KEY,0)),0) -> 1 | CD7: =IFERROR(INDEX(LMH_PTS,MATCH(IF(AU7<>"",AU7,AG7),LMH_KEY,0)),0) -> 9 | CE7: =IFERROR(INDEX(LMH_PTS,MATCH(IF(AV7<>"",AV7,AH7),LMH_KEY,0)),0) -> 3 | CF7: =IFERROR(INDEX(LMH_PTS,MATCH(IF(AW7<>"",AW7,AI7),LMH_KEY,0)),0) -> 3 | CG7: =IFERROR(INDEX(LMH_PTS,MATCH(IF(AX7<>"",AX7,AJ7),LMH_KEY,0)),0) -> 3 | CH7: =IFERROR(INDEX(LMH_PTS,MATCH(IF(AY7<>"",AY7,AK7),LMH_KEY,0)),0) -> 1 | CI7: =IFERROR(INDEX(LMH_PTS,MATCH(IF(AZ7<>"",AZ7,AL7),LMH_KEY,0)),0) -> 1 | CJ7: =IFERROR(INDEX(LMH_PTS,MATCH(IF(BA7<>"",BA7,AM7),LMH_KEY,0)),0) -> 1 | CK7: =IF(BB7="",0,IFERROR(INDEX(LMH_STEP,MATCH(BB7,LMH_KEY,0)),0)) -> 0 | CL7: =IF(BC7="",0,IFERROR(INDEX(LMH_STEP,MATCH(BC7,LMH_KEY,0)),0)) -> 0 | CM7: =IF(BD7="",0,IFERROR(INDEX(LMH_STEP,MATCH(BD7,LMH_KEY,0)),0)) -> 0 | CN7: =IF(BE7="",0,IFERROR(INDEX(LMH_STEP,MATCH(BE7,LMH_KEY,0)),0)) -> 0 | CO7: =IF(BF7="",0,IFERROR(INDEX(LMH_STEP,MATCH(BF7,LMH_KEY,0)),0)) -> 0 | CP7: =IF(BG7="",0,IFERROR(INDEX(LMH_STEP,MATCH(BG7,LMH_KEY,0)),0)) -> 0 | CQ7: =IF(BH7="",0,IFERROR(INDEX(LMH_STEP,MATCH(BH7,LMH_KEY,0)),0)) -> 0 | CR7: =IF(BI7<>"",IFERROR(INDEX(LMH_STEP,MATCH(BI7,LMH_KEY,0)),0),CK7) -> 0 | CS7: =IF(BJ7<>"",IFERROR(INDEX(LMH_STEP,MATCH(BJ7,LMH_KEY,0)),0),CL7) -> 0 | CT7: =IF(BK7<>"",IFERROR(INDEX(LMH_STEP,MATCH(BK7,LMH_KEY,0)),0),CM7) -> 0 | CU7: =IF(BL7<>"",IFERROR(INDEX(LMH_STEP,MATCH(BL7,LMH_KEY,0)),0),CN7) -> 0 | CV7: =IF(BM7<>"",IFERROR(INDEX(LMH_STEP,MATCH(BM7,LMH_KEY,0)),0),CO7) -> 0 | CW7: =IF(BN7<>"",IFERROR(INDEX(LMH_STEP,MATCH(BN7,LMH_KEY,0)),0),CP7) -> 0 | CX7: =IF(BO7<>"",IFERROR(INDEX(LMH_STEP,MATCH(BO7,LMH_KEY,0)),0),CQ7) -> 0 | CY7: =COUNTA(BI7:BO7)+IF(BP7<>"",1,0)+IFERROR(INDEX(RM_LCNT,MATCH($U7,RM_KEY,0)),0) -> 0 | CZ7: =IF((BW7+BX7+BY7+BZ7+CA7+CB7+CC7)=0,0,(BW7*CK7+BX7*CL7+BY7*CM7+BZ7*CN7+CA7*CO7+CB7*CP7+CC7*CQ7)/(BW7+BX7+BY7+BZ7+CA7+CB7+CC7)) -> 0 | DA7: =IF((CD7+CE7+CF7+CG7+CH7+CI7+CJ7)=0,0,(CD7*CR7+CE7*CS7+CF7*CT7+CG7*CU7+CH7*CV7+CI7*CW7+CJ7*CX7)/(CD7+CE7+CF7+CG7+CH7+CI7+CJ7)) -> 0
A8: CARBON | B8: CRO - Carbon | C8: 1 | D8: IRIS2478 | E8: Dixit Jasani | F8: Chief Revenue Officer- Enterprise Division | G8: Balachandran K | H8: IRIS0001 | I8: 27.9 | J8: PGDM | O8: Latest rating: Not rated · manager · 9-box: Not placed · manager | Q8: Open ▸ | R8: Card ▸ | S8: Enterprise Leadership | T8: Chief Officers · CXO | U8: R040 | V8: Chief Officers · CXO · Manager | W8: E1 | X8: Band E · Enterprise leadership | Y8: Chief Revenue Officer | AA8: Placed at E1 by the evidence: six ratings × market-derived weights and rules R1–R13 · no move needed for the reporting line · Band E · Enterprise Leadership | AC8: E1 | AE8: 1 direct reports · norm 5–8 function heads | AF8: E5 · SFIA 7 | AG8: =IFERROR(IF(INDEX(RM_I_C,MATCH($U8,RM_KEY,0))="","",INDEX(RM_I_C,MATCH($U8,RM_KEY,0))),"") -> H | AH8: =IFERROR(IF(INDEX(RM_I_Au,MATCH($U8,RM_KEY,0))="","",INDEX(RM_I_Au,MATCH($U8,RM_KEY,0))),"") -> M | AI8: =IFERROR(IF(INDEX(RM_I_Ac,MATCH($U8,RM_KEY,0))="","",INDEX(RM_I_Ac,MATCH($U8,RM_KEY,0))),"") -> M | AJ8: =IFERROR(IF(INDEX(RM_I_L,MATCH($U8,RM_KEY,0))="","",INDEX(RM_I_L,MATCH($U8,RM_KEY,0))),"") -> M | AK8: =IFERROR(IF(INDEX(RM_I_BI,MATCH($U8,RM_KEY,0))="","",INDEX(RM_I_BI,MATCH($U8,RM_KEY,0))),"") -> L | AL8: =IFERROR(IF(INDEX(RM_I_Exp,MATCH($U8,RM_KEY,0))="","",INDEX(RM_I_Exp,MATCH($U8,RM_KEY,0))),"") -> L | AM8: =IFERROR(IF(INDEX(RM_I_Edu,MATCH($U8,RM_KEY,0))="","",INDEX(RM_I_Edu,MATCH($U8,RM_KEY,0))),"") -> L | AN8: =IFERROR(IF(INDEX(RM_M_C,MATCH($U8,RM_KEY,0))="","",INDEX(RM_M_C,MATCH($U8,RM_KEY,0))),"") -> H | AO8: =IFERROR(IF(INDEX(RM_M_Au,MATCH($U8,RM_KEY,0))="","",INDEX(RM_M_Au,MATCH($U8,RM_KEY,0))),"") -> M | AP8: =IFERROR(IF(INDEX(RM_M_Ac,MATCH($U8,RM_KEY,0))="","",INDEX(RM_M_Ac,MATCH($U8,RM_KEY,0))),"") -> M | AQ8: =IFERROR(IF(INDEX(RM_M_L,MATCH($U8,RM_KEY,0))="","",INDEX(RM_M_L,MATCH($U8,RM_KEY,0))),"") -> M | AR8: =IFERROR(IF(INDEX(RM_M_BI,MATCH($U8,RM_KEY,0))="","",INDEX(RM_M_BI,MATCH($U8,RM_KEY,0))),"") -> L | AS8: =IFERROR(IF(INDEX(RM_M_Exp,MATCH($U8,RM_KEY,0))="","",INDEX(RM_M_Exp,MATCH($U8,RM_KEY,0))),"") -> L | AT8: =IFERROR(IF(INDEX(RM_M_Edu,MATCH($U8,RM_KEY,0))="","",INDEX(RM_M_Edu,MATCH($U8,RM_KEY,0))),"") -> L | AU8: =IFERROR(IF(INDEX(RM_L_C,MATCH($U8,RM_KEY,0))="","",INDEX(RM_L_C,MATCH($U8,RM_KEY,0))),"") | AV8: =IFERROR(IF(INDEX(RM_L_Au,MATCH($U8,RM_KEY,0))="","",INDEX(RM_L_Au,MATCH($U8,RM_KEY,0))),"") | AW8: =IFERROR(IF(INDEX(RM_L_Ac,MATCH($U8,RM_KEY,0))="","",INDEX(RM_L_Ac,MATCH($U8,RM_KEY,0))),"") | AX8: =IFERROR(IF(INDEX(RM_L_L,MATCH($U8,RM_KEY,0))="","",INDEX(RM_L_L,MATCH($U8,RM_KEY,0))),"") | AY8: =IFERROR(IF(INDEX(RM_L_BI,MATCH($U8,RM_KEY,0))="","",INDEX(RM_L_BI,MATCH($U8,RM_KEY,0))),"") | AZ8: =IFERROR(IF(INDEX(RM_L_Exp,MATCH($U8,RM_KEY,0))="","",INDEX(RM_L_Exp,MATCH($U8,RM_KEY,0))),"") | BA8: =IFERROR(IF(INDEX(RM_L_Edu,MATCH($U8,RM_KEY,0))="","",INDEX(RM_L_Edu,MATCH($U8,RM_KEY,0))),"") | BG8: M | BH8: M | BQ8: =IF(CY8=0,"",IF(BP8<>"",BP8,IF(LEFT(W8,1)="X",W8,IF(OR(W8="B+",W8="C+"),INDEX(LAD_PC,MAX(1,MIN(14,MATCH(W8,LAD_PC,0)+IF((DA8-CZ8)>=0.5,1,IF((DA8-CZ8)<=-0.5,-1,0))))),INDEX(LAD_STD,MAX(1,MIN(12,MATCH(W8,LAD_STD,0)+IF((DA8-CZ8)>=0.5,1,IF((DA8-CZ8)<=-0.5,-1,0))))))))) | BR8: =IF(BQ8="","",IFERROR(CHOOSE(INDEX(B_RANK,MATCH(BQ8,B_LVL,0)),"Band A · Practitioner","Band B · Specialist / Manager","B+ · Player-Coach","Band C · Principal / Head","C+ · Player-Coach","Band D · Business leadership","Band E · Enterprise leadership"),"Band X · Consultant")) | BS8: =IF(BQ8="","",IF(BQ8=W8,"• Same",IF(INDEX(B_VAL,MATCH(BQ8,B_LVL,0))>INDEX(B_VAL,MATCH(W8,B_LVL,0)),"▲ Up","▼ Down"))) | BT8: =IF(BQ8<>"",BQ8,W8) -> E1 | BU8: =IFERROR(IF($H8="","—",IF(OR(LEFT(BT8,1)="X",LEFT(INDEX($BT$7:$BT$592,MATCH($H8,$D$7:$D$592,0)),1)="X"),"—",IF(AND(LEFT(BT8,1)="E",LEFT(INDEX($BT$7:$BT$592,MATCH($H8,$D$7:$D$592,0)),1)="E"),"Exception · Band E",IF(INDEX(B_VAL,MATCH(BT8,B_LVL,0))>=INDEX(B_VAL,MATCH(INDEX($BT$7:$BT$592,MATCH($H8,$D$7:$D$592,0)),B_LVL,0)),"⚠ At or above the manager",IF(INDEX(B_RANK,MATCH(BT8,B_LVL,0))=INDEX(B_RANK,MATCH(INDEX($BT$7:$BT$592,MATCH($H8,$D$7:$D$592,0)),B_LVL,0)),"⚠ Same band as the manager","OK"))))),"—") -> Exception · Band E | BW8: =IFERROR(INDEX(LMH_PTS,MATCH(AG8,LMH_KEY,0)),0) -> 9 | BX8: =IFERROR(INDEX(LMH_PTS,MATCH(AH8,LMH_KEY,0)),0) -> 3 | BY8: =IFERROR(INDEX(LMH_PTS,MATCH(AI8,LMH_KEY,0)),0) -> 3 | BZ8: =IFERROR(INDEX(LMH_PTS,MATCH(AJ8,LMH_KEY,0)),0) -> 3 | CA8: =IFERROR(INDEX(LMH_PTS,MATCH(AK8,LMH_KEY,0)),0) -> 1 | CB8: =IFERROR(INDEX(LMH_PTS,MATCH(AL8,LMH_KEY,0)),0) -> 1 | CC8: =IFERROR(INDEX(LMH_PTS,MATCH(AM8,LMH_KEY,0)),0) -> 1 | CD8: =IFERROR(INDEX(LMH_PTS,MATCH(IF(AU8<>"",AU8,AG8),LMH_KEY,0)),0) -> 9 | CE8: =IFERROR(INDEX(LMH_PTS,MATCH(IF(AV8<>"",AV8,AH8),LMH_KEY,0)),0) -> 3 | CF8: =IFERROR(INDEX(LMH_PTS,MATCH(IF(AW8<>"",AW8,AI8),LMH_KEY,0)),0) -> 3 | CG8: =IFERROR(INDEX(LMH_PTS,MATCH(IF(AX8<>"",AX8,AJ8),LMH_KEY,0)),0) -> 3 | CH8: =IFERROR(INDEX(LMH_PTS,MATCH(IF(AY8<>"",AY8,AK8),LMH_KEY,0)),0) -> 1 | CI8: =IFERROR(INDEX(LMH_PTS,MATCH(IF(AZ8<>"",AZ8,AL8),LMH_KEY,0)),0) -> 1 | CJ8: =IFERROR(INDEX(LMH_PTS,MATCH(IF(BA8<>"",BA8,AM8),LMH_KEY,0)),0) -> 1 | CK8: =IF(BB8="",0,IFERROR(INDEX(LMH_STEP,MATCH(BB8,LMH_KEY,0)),0)) -> 0 | CL8: =IF(BC8="",0,IFERROR(INDEX(LMH_STEP,MATCH(BC8,LMH_KEY,0)),0)) -> 0 | CM8: =IF(BD8="",0,IFERROR(INDEX(LMH_STEP,MATCH(BD8,LMH_KEY,0)),0)) -> 0 | CN8: =IF(BE8="",0,IFERROR(INDEX(LMH_STEP,MATCH(BE8,LMH_KEY,0)),0)) -> 0 | CO8: =IF(BF8="",0,IFERROR(INDEX(LMH_STEP,MATCH(BF8,LMH_KEY,0)),0)) -> 0 | CP8: =IF(BG8="",0,IFERROR(INDEX(LMH_STEP,MATCH(BG8,LMH_KEY,0)),0)) -> 0 | CQ8: =IF(BH8="",0,IFERROR(INDEX(LMH_STEP,MATCH(BH8,LMH_KEY,0)),0)) -> 0 | CR8: =IF(BI8<>"",IFERROR(INDEX(LMH_STEP,MATCH(BI8,LMH_KEY,0)),0),CK8) -> 0 | CS8: =IF(BJ8<>"",IFERROR(INDEX(LMH_STEP,MATCH(BJ8,LMH_KEY,0)),0),CL8) -> 0 | CT8: =IF(BK8<>"",IFERROR(INDEX(LMH_STEP,MATCH(BK8,LMH_KEY,0)),0),CM8) -> 0 | CU8: =IF(BL8<>"",IFERROR(INDEX(LMH_STEP,MATCH(BL8,LMH_KEY,0)),0),CN8) -> 0 | CV8: =IF(BM8<>"",IFERROR(INDEX(LMH_STEP,MATCH(BM8,LMH_KEY,0)),0),CO8) -> 0 | CW8: =IF(BN8<>"",IFERROR(INDEX(LMH_STEP,MATCH(BN8,LMH_KEY,0)),0),CP8) -> 0 | CX8: =IF(BO8<>"",IFERROR(INDEX(LMH_STEP,MATCH(BO8,LMH_KEY,0)),0),CQ8) -> 0 | CY8: =COUNTA(BI8:BO8)+IF(BP8<>"",1,0)+IFERROR(INDEX(RM_LCNT,MATCH($U8,RM_KEY,0)),0) -> 0 | CZ8: =IF((BW8+BX8+BY8+BZ8+CA8+CB8+CC8)=0,0,(BW8*CK8+BX8*CL8+BY8*CM8+BZ8*CN8+CA8*CO8+CB8*CP8+CC8*CQ8)/(BW8+BX8+BY8+BZ8+CA8+CB8+CC8)) -> 0 | DA8: =IF((CD8+CE8+CF8+CG8+CH8+CI8+CJ8)=0,0,(CD8*CR8+CE8*CS8+CF8*CT8+CG8*CU8+CH8*CV8+CI8*CW8+CJ8*CX8)/(CD8+CE8+CF8+CG8+CH8+CI8+CJ8)) -> 0
A9: CARBON | B9: CARBON Business Head | C9: 2 | D9: IRIS0391 | E9: Anuradha RK | F9: Business Head | G9: Dixit Jasani | H9: IRIS2478 | I9: 17.1 | J9: MBA | O9: Latest rating: Not rated · manager · 9-box: Not placed · manager | Q9: Open ▸ | R9: Card ▸ | S9: Executive Leadership | T9: Business Head | U9: R042 | V9: Business Head · Manager | W9: D2 | X9: Band D · Business leadership | Y9: Business Head | AA9: Placed at D2 by the evidence: six ratings × market-derived weights and rules R1–R13 · no move needed for the reporting line · department head · Executive Leadership · Business Head | AC9: D1 | AE9: 8 direct reports · norm 5–8 AVPs / heads | AF9: E3–E4 · SFIA 7 Set strategy | AG9: =IFERROR(IF(INDEX(RM_I_C,MATCH($U9,RM_KEY,0))="","",INDEX(RM_I_C,MATCH($U9,RM_KEY,0))),"") -> H | AH9: =IFERROR(IF(INDEX(RM_I_Au,MATCH($U9,RM_KEY,0))="","",INDEX(RM_I_Au,MATCH($U9,RM_KEY,0))),"") -> M | AI9: =IFERROR(IF(INDEX(RM_I_Ac,MATCH($U9,RM_KEY,0))="","",INDEX(RM_I_Ac,MATCH($U9,RM_KEY,0))),"") -> M | AJ9: =IFERROR(IF(INDEX(RM_I_L,MATCH($U9,RM_KEY,0))="","",INDEX(RM_I_L,MATCH($U9,RM_KEY,0))),"") -> M | AK9: =IFERROR(IF(INDEX(RM_I_BI,MATCH($U9,RM_KEY,0))="","",INDEX(RM_I_BI,MATCH($U9,RM_KEY,0))),"") -> L | AL9: =IFERROR(IF(INDEX(RM_I_Exp,MATCH($U9,RM_KEY,0))="","",INDEX(RM_I_Exp,MATCH($U9,RM_KEY,0))),"") -> L | AM9: =IFERROR(IF(INDEX(RM_I_Edu,MATCH($U9,RM_KEY,0))="","",INDEX(RM_I_Edu,MATCH($U9,RM_KEY,0))),"") -> L | AN9: =IFERROR(IF(INDEX(RM_M_C,MATCH($U9,RM_KEY,0))="","",INDEX(RM_M_C,MATCH($U9,RM_KEY,0))),"") -> H | AO9: =IFERROR(IF(INDEX(RM_M_Au,MATCH($U9,RM_KEY,0))="","",INDEX(RM_M_Au,MATCH($U9,RM_KEY,0))),"") -> M | AP9: =IFERROR(IF(INDEX(RM_M_Ac,MATCH($U9,RM_KEY,0))="","",INDEX(RM_M_Ac,MATCH($U9,RM_KEY,0))),"") -> M | AQ9: =IFERROR(IF(INDEX(RM_M_L,MATCH($U9,RM_KEY,0))="","",INDEX(RM_M_L,MATCH($U9,RM_KEY,0))),"") -> M | AR9: =IFERROR(IF(INDEX(RM_M_BI,MATCH($U9,RM_KEY,0))="","",INDEX(RM_M_BI,MATCH($U9,RM_KEY,0))),"") -> L | AS9: =IFERROR(IF(INDEX(RM_M_Exp,MATCH($U9,RM_KEY,0))="","",INDEX(RM_M_Exp,MATCH($U9,RM_KEY,0))),"") -> L | AT9: =IFERROR(IF(INDEX(RM_M_Edu,MATCH($U9,RM_KEY,0))="","",INDEX(RM_M_Edu,MATCH($U9,RM_KEY,0))),"") -> L | AU9: =IFERROR(IF(INDEX(RM_L_C,MATCH($U9,RM_KEY,0))="","",INDEX(RM_L_C,MATCH($U9,RM_KEY,0))),"") | AV9: =IFERROR(IF(INDEX(RM_L_Au,MATCH($U9,RM_KEY,0))="","",INDEX(RM_L_Au,MATCH($U9,RM_KEY,0))),"") | AW9: =IFERROR(IF(INDEX(RM_L_Ac,MATCH($U9,RM_KEY,0))="","",INDEX(RM_L_Ac,MATCH($U9,RM_KEY,0))),"") | AX9: =IFERROR(IF(INDEX(RM_L_L,MATCH($U9,RM_KEY,0))="","",INDEX(RM_L_L,MATCH($U9,RM_KEY,0))),"") | AY9: =IFERROR(IF(INDEX(RM_L_BI,MATCH($U9,RM_KEY,0))="","",INDEX(RM_L_BI,MATCH($U9,RM_KEY,0))),"") | AZ9: =IFERROR(IF(INDEX(RM_L_Exp,MATCH($U9,RM_KEY,0))="","",INDEX(RM_L_Exp,MATCH($U9,RM_KEY,0))),"") | BA9: =IFERROR(IF(INDEX(RM_L_Edu,MATCH($U9,RM_KEY,0))="","",INDEX(RM_L_Edu,MATCH($U9,RM_KEY,0))),"") | BG9: L | BH9: M | BQ9: =IF(CY9=0,"",IF(BP9<>"",BP9,IF(LEFT(W9,1)="X",W9,IF(OR(W9="B+",W9="C+"),INDEX(LAD_PC,MAX(1,MIN(14,MATCH(W9,LAD_PC,0)+IF((DA9-CZ9)>=0.5,1,IF((DA9-CZ9)<=-0.5,-1,0))))),INDEX(LAD_STD,MAX(1,MIN(12,MATCH(W9,LAD_STD,0)+IF((DA9-CZ9)>=0.5,1,IF((DA9-CZ9)<=-0.5,-1,0))))))))) | BR9: =IF(BQ9="","",IFERROR(CHOOSE(INDEX(B_RANK,MATCH(BQ9,B_LVL,0)),"Band A · Practitioner","Band B · Specialist / Manager","B+ · Player-Coach","Band C · Principal / Head","C+ · Player-Coach","Band D · Business leadership","Band E · Enterprise leadership"),"Band X · Consultant")) | BS9: =IF(BQ9="","",IF(BQ9=W9,"• Same",IF(INDEX(B_VAL,MATCH(BQ9,B_LVL,0))>INDEX(B_VAL,MATCH(W9,B_LVL,0)),"▲ Up","▼ Down"))) | BT9: =IF(BQ9<>"",BQ9,W9) -> D2 | BU9: =IFERROR(IF($H9="","—",IF(OR(LEFT(BT9,1)="X",LEFT(INDEX($BT$7:$BT$592,MATCH($H9,$D$7:$D$592,0)),1)="X"),"—",IF(AND(LEFT(BT9,1)="E",LEFT(INDEX($BT$7:$BT$592,MATCH($H9,$D$7:$D$592,0)),1)="E"),"Exception · Band E",IF(INDEX(B_VAL,MATCH(BT9,B_LVL,0))>=INDEX(B_VAL,MATCH(INDEX($BT$7:$BT$592,MATCH($H9,$D$7:$D$592,0)),B_LVL,0)),"⚠ At or above the manager",IF(INDEX(B_RANK,MATCH(BT9,B_LVL,0))=INDEX(B_RANK,MATCH(INDEX($BT$7:$BT$592,MATCH($H9,$D$7:$D$592,0)),B_LVL,0)),"⚠ Same band as the manager","OK"))))),"—") -> OK | BW9: =IFERROR(INDEX(LMH_PTS,MATCH(AG9,LMH_KEY,0)),0) -> 9 | BX9: =IFERROR(INDEX(LMH_PTS,MATCH(AH9,LMH_KEY,0)),0) -> 3 | BY9: =IFERROR(INDEX(LMH_PTS,MATCH(AI9,LMH_KEY,0)),0) -> 3 | BZ9: =IFERROR(INDEX(LMH_PTS,MATCH(AJ9,LMH_KEY,0)),0) -> 3 | CA9: =IFERROR(INDEX(LMH_PTS,MATCH(AK9,LMH_KEY,0)),0) -> 1 | CB9: =IFERROR(INDEX(LMH_PTS,MATCH(AL9,LMH_KEY,0)),0) -> 1 | CC9: =IFERROR(INDEX(LMH_PTS,MATCH(AM9,LMH_KEY,0)),0) -> 1 | CD9: =IFERROR(INDEX(LMH_PTS,MATCH(IF(AU9<>"",AU9,AG9),LMH_KEY,0)),0) -> 9 | CE9: =IFERROR(INDEX(LMH_PTS,MATCH(IF(AV9<>"",AV9,AH9),LMH_KEY,0)),0) -> 3 | CF9: =IFERROR(INDEX(LMH_PTS,MATCH(IF(AW9<>"",AW9,AI9),LMH_KEY,0)),0) -> 3 | CG9: =IFERROR(INDEX(LMH_PTS,MATCH(IF(AX9<>"",AX9,AJ9),LMH_KEY,0)),0) -> 3 | CH9: =IFERROR(INDEX(LMH_PTS,MATCH(IF(AY9<>"",AY9,AK9),LMH_KEY,0)),0) -> 1 | CI9: =IFERROR(INDEX(LMH_PTS,MATCH(IF(AZ9<>"",AZ9,AL9),LMH_KEY,0)),0) -> 1 | CJ9: =IFERROR(INDEX(LMH_PTS,MATCH(IF(BA9<>"",BA9,AM9),LMH_KEY,0)),0) -> 1 | CK9: =IF(BB9="",0,IFERROR(INDEX(LMH_STEP,MATCH(BB9,LMH_KEY,0)),0)) -> 0 | CL9: =IF(BC9="",0,IFERROR(INDEX(LMH_STEP,MATCH(BC9,LMH_KEY,0)),0)) -> 0 | CM9: =IF(BD9="",0,IFERROR(INDEX(LMH_STEP,MATCH(BD9,LMH_KEY,0)),0)) -> 0 | CN9: =IF(BE9="",0,IFERROR(INDEX(LMH_STEP,MATCH(BE9,LMH_KEY,0)),0)) -> 0 | CO9: =IF(BF9="",0,IFERROR(INDEX(LMH_STEP,MATCH(BF9,LMH_KEY,0)),0)) -> 0 | CP9: =IF(BG9="",0,IFERROR(INDEX(LMH_STEP,MATCH(BG9,LMH_KEY,0)),0)) -> -1 | CQ9: =IF(BH9="",0,IFERROR(INDEX(LMH_STEP,MATCH(BH9,LMH_KEY,0)),0)) -> 0 | CR9: =IF(BI9<>"",IFERROR(INDEX(LMH_STEP,MATCH(BI9,LMH_KEY,0)),0),CK9) -> 0 | CS9: =IF(BJ9<>"",IFERROR(INDEX(LMH_STEP,MATCH(BJ9,LMH_KEY,0)),0),CL9) -> 0 | CT9: =IF(BK9<>"",IFERROR(INDEX(LMH_STEP,MATCH(BK9,LMH_KEY,0)),0),CM9) -> 0 | CU9: =IF(BL9<>"",IFERROR(INDEX(LMH_STEP,MATCH(BL9,LMH_KEY,0)),0),CN9) -> 0 | CV9: =IF(BM9<>"",IFERROR(INDEX(LMH_STEP,MATCH(BM9,LMH_KEY,0)),0),CO9) -> 0 | CW9: =IF(BN9<>"",IFERROR(INDEX(LMH_STEP,MATCH(BN9,LMH_KEY,0)),0),CP9) -> -1 | CX9: =IF(BO9<>"",IFERROR(INDEX(LMH_STEP,MATCH(BO9,LMH_KEY,0)),0),CQ9) -> 0 | CY9: =COUNTA(BI9:BO9)+IF(BP9<>"",1,0)+IFERROR(INDEX(RM_LCNT,MATCH($U9,RM_KEY,0)),0) -> 0 | CZ9: =IF((BW9+BX9+BY9+BZ9+CA9+CB9+CC9)=0,0,(BW9*CK9+BX9*CL9+BY9*CM9+BZ9*CN9+CA9*CO9+CB9*CP9+CC9*CQ9)/(BW9+BX9+BY9+BZ9+CA9+CB9+CC9)) -> -0.047619048 | DA9: =IF((CD9+CE9+CF9+CG9+CH9+CI9+CJ9)=0,0,(CD9*CR9+CE9*CS9+CF9*CT9+CG9*CU9+CH9*CV9+CI9*CW9+CJ9*CX9)/(CD9+CE9+CF9+CG9+CH9+CI9+CJ9)) -> -0.047619048
A10: CARBON | B10: Customer Experience | C10: 3 | D10: IRIS2359 | E10: Suman Adhikary | F10: Senior Vice President - Customer Experience | G10: Anuradha RK | H10: IRIS0391 | I10: 28.7 | J10: B.E | O10: Latest rating: Not rated · manager · 9-box: Underperformer / Exit Risk | Q10: Open ▸ | R10: Card ▸ | S10: Executive Leadership | T10: Business Head | U10: R042 | V10: Business Head · Manager | W10: D1 | X10: Band D · Business leadership | Y10: Senior Vice President – Customer Experience | AA10: Placed at D1 by the evidence: six ratings × market-derived weights and rules R1–R13 · no move needed for the reporting line · department head · Executive Leadership · Business Head | AB10: Deep chain: shares a band with manager Anuradha RK · D2 · decide: report to the next manager up, or merge this layer | AC10: D2 | AE10: 8 direct reports · norm 5–8 heads | AF10: E1–E2 · SFIA 6–7 | AG10: =IFERROR(IF(INDEX(RM_I_C,MATCH($U10,RM_KEY,0))="","",INDEX(RM_I_C,MATCH($U10,RM_KEY,0))),"") -> H | AH10: =IFERROR(IF(INDEX(RM_I_Au,MATCH($U10,RM_KEY,0))="","",INDEX(RM_I_Au,MATCH($U10,RM_KEY,0))),"") -> M | AI10: =IFERROR(IF(INDEX(RM_I_Ac,MATCH($U10,RM_KEY,0))="","",INDEX(RM_I_Ac,MATCH($U10,RM_KEY,0))),"") -> M | AJ10: =IFERROR(IF(INDEX(RM_I_L,MATCH($U10,RM_KEY,0))="","",INDEX(RM_I_L,MATCH($U10,RM_KEY,0))),"") -> M | AK10: =IFERROR(IF(INDEX(RM_I_BI,MATCH($U10,RM_KEY,0))="","",INDEX(RM_I_BI,MATCH($U10,RM_KEY,0))),"") -> L | AL10: =IFERROR(IF(INDEX(RM_I_Exp,MATCH($U10,RM_KEY,0))="","",INDEX(RM_I_Exp,MATCH($U10,RM_KEY,0))),"") -> L | AM10: =IFERROR(IF(INDEX(RM_I_Edu,MATCH($U10,RM_KEY,0))="","",INDEX(RM_I_Edu,MATCH($U10,RM_KEY,0))),"") -> L | AN10: =IFERROR(IF(INDEX(RM_M_C,MATCH($U10,RM_KEY,0))="","",INDEX(RM_M_C,MATCH($U10,RM_KEY,0))),"") -> H | AO10: =IFERROR(IF(INDEX(RM_M_Au,MATCH($U10,RM_KEY,0))="","",INDEX(RM_M_Au,MATCH($U10,RM_KEY,0))),"") -> M | AP10: =IFERROR(IF(INDEX(RM_M_Ac,MATCH($U10,RM_KEY,0))="","",INDEX(RM_M_Ac,MATCH($U10,RM_KEY,0))),"") -> M | AQ10: =IFERROR(IF(INDEX(RM_M_L,MATCH($U10,RM_KEY,0))="","",INDEX(RM_M_L,MATCH($U10,RM_KEY,0))),"") -> M | AR10: =IFERROR(IF(INDEX(RM_M_BI,MATCH($U10,RM_KEY,0))="","",INDEX(RM_M_BI,MATCH($U10,RM_KEY,0))),"") -> L | AS10: =IFERROR(IF(INDEX(RM_M_Exp,MATCH($U10,RM_KEY,0))="","",INDEX(RM_M_Exp,MATCH($U10,RM_KEY,0))),"") -> L | AT10: =IFERROR(IF(INDEX(RM_M_Edu,MATCH($U10,RM_KEY,0))="","",INDEX(RM_M_Edu,MATCH($U10,RM_KEY,0))),"") -> L | AU10: =IFERROR(IF(INDEX(RM_L_C,MATCH($U10,RM_KEY,0))="","",INDEX(RM_L_C,MATCH($U10,RM_KEY,0))),"") | AV10: =IFERROR(IF(INDEX(RM_L_Au,MATCH($U10,RM_KEY,0))="","",INDEX(RM_L_Au,MATCH($U10,RM_KEY,0))),"") | AW10: =IFERROR(IF(INDEX(RM_L_Ac,MATCH($U10,RM_KEY,0))="","",INDEX(RM_L_Ac,MATCH($U10,RM_KEY,0))),"") | AX10: =IFERROR(IF(INDEX(RM_L_L,MATCH($U10,RM_KEY,0))="","",INDEX(RM_L_L,MATCH($U10,RM_KEY,0))),"") | AY10: =IFERROR(IF(INDEX(RM_L_BI,MATCH($U10,RM_KEY,0))="","",INDEX(RM_L_BI,MATCH($U10,RM_KEY,0))),"") | AZ10: =IFERROR(IF(INDEX(RM_L_Exp,MATCH($U10,RM_KEY,0))="","",INDEX(RM_L_Exp,MATCH($U10,RM_KEY,0))),"") | BA10: =IFERROR(IF(INDEX(RM_L_Edu,MATCH($U10,RM_KEY,0))="","",INDEX(RM_L_Edu,MATCH($U10,RM_KEY,0))),"") | BG10: H | BH10: L | BQ10: =IF(CY10=0,"",IF(BP10<>"",BP10,IF(LEFT(W10,1)="X",W10,IF(OR(W10="B+",W10="C+"),INDEX(LAD_PC,MAX(1,MIN(14,MATCH(W10,LAD_PC,0)+IF((DA10-CZ10)>=0.5,1,IF((DA10-CZ10)<=-0.5,-1,0))))),INDEX(LAD_STD,MAX(1,MIN(12,MATCH(W10,LAD_STD,0)+IF((DA10-CZ10)>=0.5,1,IF((DA10-CZ10)<=-0.5,-1,0))))))))) | BR10: =IF(BQ10="","",IFERROR(CHOOSE(INDEX(B_RANK,MATCH(BQ10,B_LVL,0)),"Band A · Practitioner","Band B · Specialist / Manager","B+ · Player-Coach","Band C · Principal / Head","C+ · Player-Coach","Band D · Business leadership","Band E · Enterprise leadership"),"Band X · Consultant")) | BS10: =IF(BQ10="","",IF(BQ10=W10,"• Same",IF(INDEX(B_VAL,MATCH(BQ10,B_LVL,0))>INDEX(B_VAL,MATCH(W10,B_LVL,0)),"▲ Up","▼ Down"))) | BT10: =IF(BQ10<>"",BQ10,W10) -> D1 | BU10: =IFERROR(IF($H10="","—",IF(OR(LEFT(BT10,1)="X",LEFT(INDEX($BT$7:$BT$592,MATCH($H10,$D$7:$D$592,0)),1)="X"),"—",IF(AND(LEFT(BT10,1)="E",LEFT(INDEX($BT$7:$BT$592,MATCH($H10,$D$7:$D$592,0)),1)="E"),"Exception · Band E",IF(INDEX(B_VAL,MATCH(BT10,B_LVL,0))>=INDEX(B_VAL,MATCH(INDEX($BT$7:$BT$592,MATCH($H10,$D$7:$D$592,0)),B_LVL,0)),"⚠ At or above the manager",IF(INDEX(B_RANK,MATCH(BT10,B_LVL,0))=INDEX(B_RANK,MATCH(INDEX($BT$7:$BT$592,MATCH($H10,$D$7:$D$592,0)),B_LVL,0)),"⚠ Same band as the manager","OK"))))),"—") -> ⚠ Same band as the manager | BW10: =IFERROR(INDEX(LMH_PTS,MATCH(AG10,LMH_KEY,0)),0) -> 9 | BX10: =IFERROR(INDEX(LMH_PTS,MATCH(AH10,LMH_KEY,0)),0) -> 3 | BY10: =IFERROR(INDEX(LMH_PTS,MATCH(AI10,LMH_KEY,0)),0) -> 3 | BZ10: =IFERROR(INDEX(LMH_PTS,MATCH(AJ10,LMH_KEY,0)),0) -> 3 | CA10: =IFERROR(INDEX(LMH_PTS,MATCH(AK10,LMH_KEY,0)),0) -> 1 | CB10: =IFERROR(INDEX(LMH_PTS,MATCH(AL10,LMH_KEY,0)),0) -> 1 | CC10: =IFERROR(INDEX(LMH_PTS,MATCH(AM10,LMH_KEY,0)),0) -> 1 | CD10: =IFERROR(INDEX(LMH_PTS,MATCH(IF(AU10<>"",AU10,AG10),LMH_KEY,0)),0) -> 9 | CE10: =IFERROR(INDEX(LMH_PTS,MATCH(IF(AV10<>"",AV10,AH10),LMH_KEY,0)),0) -> 3 | CF10: =IFERROR(INDEX(LMH_PTS,MATCH(IF(AW10<>"",AW10,AI10),LMH_KEY,0)),0) -> 3 | CG10: =IFERROR(INDEX(LMH_PTS,MATCH(IF(AX10<>"",AX10,AJ10),LMH_KEY,0)),0) -> 3 | CH10: =IFERROR(INDEX(LMH_PTS,MATCH(IF(AY10<>"",AY10,AK10),LMH_KEY,0)),0) -> 1 | CI10: =IFERROR(INDEX(LMH_PTS,MATCH(IF(AZ10<>"",AZ10,AL10),LMH_KEY,0)),0) -> 1 | CJ10: =IFERROR(INDEX(LMH_PTS,MATCH(IF(BA10<>"",BA10,AM10),LMH_KEY,0)),0) -> 1 | CK10: =IF(BB10="",0,IFERROR(INDEX(LMH_STEP,MATCH(BB10,LMH_KEY,0)),0)) -> 0 | CL10: =IF(BC10="",0,IFERROR(INDEX(LMH_STEP,MATCH(BC10,LMH_KEY,0)),0)) -> 0 | CM10: =IF(BD10="",0,IFERROR(INDEX(LMH_STEP,MATCH(BD10,LMH_KEY,0)),0)) -> 0 | CN10: =IF(BE10="",0,IFERROR(INDEX(LMH_STEP,MATCH(BE10,LMH_KEY,0)),0)) -> 0 | CO10: =IF(BF10="",0,IFERROR(INDEX(LMH_STEP,MATCH(BF10,LMH_KEY,0)),0)) -> 0 | CP10: =IF(BG10="",0,IFERROR(INDEX(LMH_STEP,MATCH(BG10,LMH_KEY,0)),0)) -> 1 | CQ10: =IF(BH10="",0,IFERROR(INDEX(LMH_STEP,MATCH(BH10,LMH_KEY,0)),0)) -> -1 | CR10: =IF(BI10<>"",IFERROR(INDEX(LMH_STEP,MATCH(BI10,LMH_KEY,0)),0),CK10) -> 0 | CS10: =IF(BJ10<>"",IFERROR(INDEX(LMH_STEP,MATCH(BJ10,LMH_KEY,0)),0),CL10) -> 0 | CT10: =IF(BK10<>"",IFERROR(INDEX(LMH_STEP,MATCH(BK10,LMH_KEY,0)),0),CM10) -> 0 | CU10: =IF(BL10<>"",IFERROR(INDEX(LMH_STEP,MATCH(BL10,LMH_KEY,0)),0),CN10) -> 0 | CV10: =IF(BM10<>"",IFERROR(INDEX(LMH_STEP,MATCH(BM10,LMH_KEY,0)),0),CO10) -> 0 | CW10: =IF(BN10<>"",IFERROR(INDEX(LMH_STEP,MATCH(BN10,LMH_KEY,0)),0),CP10) -> 1 | CX10: =IF(BO10<>"",IFERROR(INDEX(LMH_STEP,MATCH(BO10,LMH_KEY,0)),0),CQ10) -> -1 | CY10: =COUNTA(BI10:BO10)+IF(BP10<>"",1,0)+IFERROR(INDEX(RM_LCNT,MATCH($U10,RM_KEY,0)),0) -> 0 | CZ10: =IF((BW10+BX10+BY10+BZ10+CA10+CB10+CC10)=0,0,(BW10*CK10+BX10*CL10+BY10*CM10+BZ10*CN10+CA10*CO10+CB10*CP10+CC10*CQ10)/(BW10+BX10+BY10+BZ10+CA10+CB10+CC10)) -> 0 | DA10: =IF((CD10+CE10+CF10+CG10+CH10+CI10+CJ10)=0,0,(CD10*CR10+CE10*CS10+CF10*CT10+CG10*CU10+CH10*CV10+CI10*CW10+CJ10*CX10)/(CD10+CE10+CF10+CG10+CH10+CI10+CJ10)) -> 0
A11: CARBON | B11: Support | C11: 4 | D11: IRIS1335 | E11: Anushree Aparajit | F11: Global Customer Success Head | G11: Suman Adhikary | H11: IRIS2359 | I11: 14.6 | J11: CA | K11: L7 – Head / Sr Director | N11: Annual · set by manager: Net Revenue Retention ≥100–105% Target ARR - to be achieved - INR 2.35 CR 90% reach value milestone in 90 days Develop advocates · Promoter per CEM Produce case studies annually CSAT ≥90% NPS ≥30 100% QBR coverage for accounts 100% CRM hygiene maintained Renewal forecast accuracy ≥95% Outstanding receivables ≤45 days Enablement and Training Share at least 3 structured customer insights with Product/Engineering per quarter. Drive price increase in renewals Mentor or … | O11: Latest rating: 4 · Potential: Medium · 9-box: High Impact / Growth Talent | Q11: Open ▸ | R11: Card ▸ | S11: Executive Leadership | T11: Business Head | U11: R042 | V11: Business Head · Manager | W11: C1 | X11: Band C · Principal / Head | Y11: Associate Head – Customer Success | AA11: Placed at C1 by the evidence: six ratings × market-derived weights and rules R1–R13 · no move needed for the reporting line · department head · Executive Leadership · Business Head | AC11: C2 | AD11: Medium · 14.6 yrs vs market 12–17 yrs for C1 | AE11: 7 direct reports · norm 5–8, mostly managers | AF11: P6 / M5 · SFIA 5–6 | AG11: =IFERROR(IF(INDEX(RM_I_C,MATCH($U11,RM_KEY,0))="","",INDEX(RM_I_C,MATCH($U11,RM_KEY,0))),"") -> H | AH11: =IFERROR(IF(INDEX(RM_I_Au,MATCH($U11,RM_KEY,0))="","",INDEX(RM_I_Au,MATCH($U11,RM_KEY,0))),"") -> M | AI11: =IFERROR(IF(INDEX(RM_I_Ac,MATCH($U11,RM_KEY,0))="","",INDEX(RM_I_Ac,MATCH($U11,RM_KEY,0))),"") -> M | AJ11: =IFERROR(IF(INDEX(RM_I_L,MATCH($U11,RM_KEY,0))="","",INDEX(RM_I_L,MATCH($U11,RM_KEY,0))),"") -> M | AK11: =IFERROR(IF(INDEX(RM_I_BI,MATCH($U11,RM_KEY,0))="","",INDEX(RM_I_BI,MATCH($U11,RM_KEY,0))),"") -> L | AL11: =IFERROR(IF(INDEX(RM_I_Exp,MATCH($U11,RM_KEY,0))="","",INDEX(RM_I_Exp,MATCH($U11,RM_KEY,0))),"") -> L | AM11: =IFERROR(IF(INDEX(RM_I_Edu,MATCH($U11,RM_KEY,0))="","",INDEX(RM_I_Edu,MATCH($U11,RM_KEY,0))),"") -> L | AN11: =IFERROR(IF(INDEX(RM_M_C,MATCH($U11,RM_KEY,0))="","",INDEX(RM_M_C,MATCH($U11,RM_KEY,0))),"") -> H | AO11: =IFERROR(IF(INDEX(RM_M_Au,MATCH($U11,RM_KEY,0))="","",INDEX(RM_M_Au,MATCH($U11,RM_KEY,0))),"") -> M | AP11: =IFERROR(IF(INDEX(RM_M_Ac,MATCH($U11,RM_KEY,0))="","",INDEX(RM_M_Ac,MATCH($U11,RM_KEY,0))),"") -> M | AQ11: =IFERROR(IF(INDEX(RM_M_L,MATCH($U11,RM_KEY,0))="","",INDEX(RM_M_L,MATCH($U11,RM_KEY,0))),"") -> M | AR11: =IFERROR(IF(INDEX(RM_M_BI,MATCH($U11,RM_KEY,0))="","",INDEX(RM_M_BI,MATCH($U11,RM_KEY,0))),"") -> L | AS11: =IFERROR(IF(INDEX(RM_M_Exp,MATCH($U11,RM_KEY,0))="","",INDEX(RM_M_Exp,MATCH($U11,RM_KEY,0))),"") -> L | AT11: =IFERROR(IF(INDEX(RM_M_Edu,MATCH($U11,RM_KEY,0))="","",INDEX(RM_M_Edu,MATCH($U11,RM_KEY,0))),"") -> L | AU11: =IFERROR(IF(INDEX(RM_L_C,MATCH($U11,RM_KEY,0))="","",INDEX(RM_L_C,MATCH($U11,RM_KEY,0))),"") | AV11: =IFERROR(IF(INDEX(RM_L_Au,MATCH($U11,RM_KEY,0))="","",INDEX(RM_L_Au,MATCH($U11,RM_KEY,0))),"") | AW11: =IFERROR(IF(INDEX(RM_L_Ac,MATCH($U11,RM_KEY,0))="","",INDEX(RM_L_Ac,MATCH($U11,RM_KEY,0))),"") | AX11: =IFERROR(IF(INDEX(RM_L_L,MATCH($U11,RM_KEY,0))="","",INDEX(RM_L_L,MATCH($U11,RM_KEY,0))),"") | AY11: =IFERROR(IF(INDEX(RM_L_BI,MATCH($U11,RM_KEY,0))="","",INDEX(RM_L_BI,MATCH($U11,RM_KEY,0))),"") | AZ11: =IFERROR(IF(INDEX(RM_L_Exp,MATCH($U11,RM_KEY,0))="","",INDEX(RM_L_Exp,MATCH($U11,RM_KEY,0))),"") | BA11: =IFERROR(IF(INDEX(RM_L_Edu,MATCH($U11,RM_KEY,0))="","",INDEX(RM_L_Edu,MATCH($U11,RM_KEY,0))),"") | BF11: M | BG11: H | BH11: H | BQ11: =IF(CY11=0,"",IF(BP11<>"",BP11,IF(LEFT(W11,1)="X",W11,IF(OR(W11="B+",W11="C+"),INDEX(LAD_PC,MAX(1,MIN(14,MATCH(W11,LAD_PC,0)+IF((DA11-CZ11)>=0.5,1,IF((DA11-CZ11)<=-0.5,-1,0))))),INDEX(LAD_STD,MAX(1,MIN(12,MATCH(W11,LAD_STD,0)+IF((DA11-CZ11)>=0.5,1,IF((DA11-CZ11)<=-0.5,-1,0))))))))) | BR11: =IF(BQ11="","",IFERROR(CHOOSE(INDEX(B_RANK,MATCH(BQ11,B_LVL,0)),"Band A · Practitioner","Band B · Specialist / Manager","B+ · Player-Coach","Band C · Principal / Head","C+ · Player-Coach","Band D · Business leadership","Band E · Enterprise leadership"),"Band X · Consultant")) | BS11: =IF(BQ11="","",IF(BQ11=W11,"• Same",IF(INDEX(B_VAL,MATCH(BQ11,B_LVL,0))>INDEX(B_VAL,MATCH(W11,B_LVL,0)),"▲ Up","▼ Down"))) | BT11: =IF(BQ11<>"",BQ11,W11) -> C1 | BU11: =IFERROR(IF($H11="","—",IF(OR(LEFT(BT11,1)="X",LEFT(INDEX($BT$7:$BT$592,MATCH($H11,$D$7:$D$592,0)),1)="X"),"—",IF(AND(LEFT(BT11,1)="E",LEFT(INDEX($BT$7:$BT$592,MATCH($H11,$D$7:$D$592,0)),1)="E"),"Exception · Band E",IF(INDEX(B_VAL,MATCH(BT11,B_LVL,0))>=INDEX(B_VAL,MATCH(INDEX($BT$7:$BT$592,MATCH($H11,$D$7:$D$592,0)),B_LVL,0)),"⚠ At or above the manager",IF(INDEX(B_RANK,MATCH(BT11,B_LVL,0))=INDEX(B_RANK,MATCH(INDEX($BT$7:$BT$592,MATCH($H11,$D$7:$D$592,0)),B_LVL,0)),"⚠ Same band as the manager","OK"))))),"—") -> OK | BW11: =IFERROR(INDEX(LMH_PTS,MATCH(AG11,LMH_KEY,0)),0) -> 9 | BX11: =IFERROR(INDEX(LMH_PTS,MATCH(AH11,LMH_KEY,0)),0) -> 3 | BY11: =IFERROR(INDEX(LMH_PTS,MATCH(AI11,LMH_KEY,0)),0) -> 3 | BZ11: =IFERROR(INDEX(LMH_PTS,MATCH(AJ11,LMH_KEY,0)),0) -> 3 | CA11: =IFERROR(INDEX(LMH_PTS,MATCH(AK11,LMH_KEY,0)),0) -> 1 | CB11: =IFERROR(INDEX(LMH_PTS,MATCH(AL11,LMH_KEY,0)),0) -> 1 | CC11: =IFERROR(INDEX(LMH_PTS,MATCH(AM11,LMH_KEY,0)),0) -> 1 | CD11: =IFERROR(INDEX(LMH_PTS,MATCH(IF(AU11<>"",AU11,AG11),LMH_KEY,0)),0) -> 9 | CE11: =IFERROR(INDEX(LMH_PTS,MATCH(IF(AV11<>"",AV11,AH11),LMH_KEY,0)),0) -> 3 | CF11: =IFERROR(INDEX(LMH_PTS,MATCH(IF(AW11<>"",AW11,AI11),LMH_KEY,0)),0) -> 3 | CG11: =IFERROR(INDEX(LMH_PTS,MATCH(IF(AX11<>"",AX11,AJ11),LMH_KEY,0)),0) -> 3 | CH11: =IFERROR(INDEX(LMH_PTS,MATCH(IF(AY11<>"",AY11,AK11),LMH_KEY,0)),0) -> 1 | CI11: =IFERROR(INDEX(LMH_PTS,MATCH(IF(AZ11<>"",AZ11,AL11),LMH_KEY,0)),0) -> 1 | CJ11: =IFERROR(INDEX(LMH_PTS,MATCH(IF(BA11<>"",BA11,AM11),LMH_KEY,0)),0) -> 1 | CK11: =IF(BB11="",0,IFERROR(INDEX(LMH_STEP,MATCH(BB11,LMH_KEY,0)),0)) -> 0 | CL11: =IF(BC11="",0,IFERROR(INDEX(LMH_STEP,MATCH(BC11,LMH_KEY,0)),0)) -> 0 | CM11: =IF(BD11="",0,IFERROR(INDEX(LMH_STEP,MATCH(BD11,LMH_KEY,0)),0)) -> 0 | CN11: =IF(BE11="",0,IFERROR(INDEX(LMH_STEP,MATCH(BE11,LMH_KEY,0)),0)) -> 0 | CO11: =IF(BF11="",0,IFERROR(INDEX(LMH_STEP,MATCH(BF11,LMH_KEY,0)),0)) -> 0 | CP11: =IF(BG11="",0,IFERROR(INDEX(LMH_STEP,MATCH(BG11,LMH_KEY,0)),0)) -> 1 | CQ11: =IF(BH11="",0,IFERROR(INDEX(LMH_STEP,MATCH(BH11,LMH_KEY,0)),0)) -> 1 | CR11: =IF(BI11<>"",IFERROR(INDEX(LMH_STEP,MATCH(BI11,LMH_KEY,0)),0),CK11) -> 0 | CS11: =IF(BJ11<>"",IFERROR(INDEX(LMH_STEP,MATCH(BJ11,LMH_KEY,0)),0),CL11) -> 0 | CT11: =IF(BK11<>"",IFERROR(INDEX(LMH_STEP,MATCH(BK11,LMH_KEY,0)),0),CM11) -> 0 | CU11: =IF(BL11<>"",IFERROR(INDEX(LMH_STEP,MATCH(BL11,LMH_KEY,0)),0),CN11) -> 0 | CV11: =IF(BM11<>"",IFERROR(INDEX(LMH_STEP,MATCH(BM11,LMH_KEY,0)),0),CO11) -> 0 | CW11: =IF(BN11<>"",IFERROR(INDEX(LMH_STEP,MATCH(BN11,LMH_KEY,0)),0),CP11) -> 1 | CX11: =IF(BO11<>"",IFERROR(INDEX(LMH_STEP,MATCH(BO11,LMH_KEY,0)),0),CQ11) -> 1 | CY11: =COUNTA(BI11:BO11)+IF(BP11<>"",1,0)+IFERROR(INDEX(RM_LCNT,MATCH($U11,RM_KEY,0)),0) -> 0 | CZ11: =IF((BW11+BX11+BY11+BZ11+CA11+CB11+CC11)=0,0,(BW11*CK11+BX11*CL11+BY11*CM11+BZ11*CN11+CA11*CO11+CB11*CP11+CC11*CQ11)/(BW11+BX11+BY11+BZ11+CA11+CB11+CC11)) -> 0.095238095 | DA11: =IF((CD11+CE11+CF11+CG11+CH11+CI11+CJ11)=0,0,(CD11*CR11+CE11*CS11+CF11*CT11+CG11*CU11+CH11*CV11+CI11*CW11+CJ11*CX11)/(CD11+CE11+CF11+CG11+CH11+CI11+CJ11)) -> 0.095238095
A12: CARBON | B12: Support | C12: 5 | D12: IRIS1935 | E12: Chinmayi Patil | F12: Customer Success Manager | G12: Anushree Aparajit | H12: IRIS1335 | I12: 5.2 | J12: MMS | K12: L5 – Manager | L12: 20 of 20 | M12: • Role / sub-team: Support — Customer Success Manager. • Core purpose: Post sales customer journey, retention and renewal, up sell and cross sell of other products for account expansion and revenue growth. • Decision-making autonomy: Can independently product training material. • Is this something only they do: Most of us. • What's different about this role: Product self help videos. | N12: Annual · set by manager: Net Revenue Retention ≥100–105% Target ARR - to be achieved: INR 3000000 90% reach value milestone in 90 days Develop advocates · Promoter per CEM Produce case studies annually CSAT ≥90% NPS ≥30 100% QBR coverage for accounts 100% CRM hygiene maintained Renewal forecast accuracy ≥95% Outstanding receivables ≤45 days Enablement and Training Share at least 3 structured customer insights with Product/Engineering per quarter. Drive price increase in renewals Mentor or … | O12: Latest rating: 4 · Potential: High · 9-box: Future Leader | P12: Complexity & Expertise: A2: Listed duties are tracker updates and product self-help videos; basic finance knowledge → moved down 0.5 Autonomy & Decision: A2: Decides independently only on product training material → moved down 0.5 Accountability & Impact: B1: Account retention and renewal, invoicing and timely payment for own accounts → moved down 0.5 Leadership & Strategy: A1: No guidance of others described → moved down 0.5 | Q12: Open ▸ | R12: Card ▸ | S12: Customer Success & Support | T12: Customer Success & Account Management | U12: R018 | V12: Customer Success & Account Management · IC | W12: B2 | X12: Band B · Specialist / Manager | Y12: Senior Customer Success Specialist | Z12: Customer Success Specialist → Senior Customer Success Specialist | AA12: Placed at B2 by the evidence: six ratings × market-derived weights and rules R1–R13 · no move needed for the reporting line | AC12: B1 | AD12: Low · 5.2 yrs vs market 6–10 yrs for B2 | AF12: P4 / M3 · SFIA 4–5 | AG12: =IFERROR(IF(INDEX(RM_I_C,MATCH($U12,RM_KEY,0))="","",INDEX(RM_I_C,MATCH($U12,RM_KEY,0))),"") -> H | AH12: =IFERROR(IF(INDEX(RM_I_Au,MATCH($U12,RM_KEY,0))="","",INDEX(RM_I_Au,MATCH($U12,RM_KEY,0))),"") -> M | AI12: =IFERROR(IF(INDEX(RM_I_Ac,MATCH($U12,RM_KEY,0))="","",INDEX(RM_I_Ac,MATCH($U12,RM_KEY,0))),"") -> M | AJ12: =IFERROR(IF(INDEX(RM_I_L,MATCH($U12,RM_KEY,0))="","",INDEX(RM_I_L,MATCH($U12,RM_KEY,0))),"") -> L | AK12: =IFERROR(IF(INDEX(RM_I_BI,MATCH($U12,RM_KEY,0))="","",INDEX(RM_I_BI,MATCH($U12,RM_KEY,0))),"") -> M | AL12: =IFERROR(IF(INDEX(RM_I_Exp,MATCH($U12,RM_KEY,0))="","",INDEX(RM_I_Exp,MATCH($U12,RM_KEY,0))),"") -> L | AM12: =IFERROR(IF(INDEX(RM_I_Edu,MATCH($U12,RM_KEY,0))="","",INDEX(RM_I_Edu,MATCH($U12,RM_KEY,0))),"") -> L | AN12: =IFERROR(IF(INDEX(RM_M_C,MATCH($U12,RM_KEY,0))="","",INDEX(RM_M_C,MATCH($U12,RM_KEY,0))),"") -> H | AO12: =IFERROR(IF(INDEX(RM_M_Au,MATCH($U12,RM_KEY,0))="","",INDEX(RM_M_Au,MATCH($U12,RM_KEY,0))),"") -> M | AP12: =IFERROR(IF(INDEX(RM_M_Ac,MATCH($U12,RM_KEY,0))="","",INDEX(RM_M_Ac,MATCH($U12,RM_KEY,0))),"") -> M | AQ12: =IFERROR(IF(INDEX(RM_M_L,MATCH($U12,RM_KEY,0))="","",INDEX(RM_M_L,MATCH($U12,RM_KEY,0))),"") -> L | AR12: =IFERROR(IF(INDEX(RM_M_BI,MATCH($U12,RM_KEY,0))="","",INDEX(RM_M_BI,MATCH($U12,RM_KEY,0))),"") -> L | AS12: =IFERROR(IF(INDEX(RM_M_Exp,MATCH($U12,RM_KEY,0))="","",INDEX(RM_M_Exp,MATCH($U12,RM_KEY,0))),"") -> L | AT12: =IFERROR(IF(INDEX(RM_M_Edu,MATCH($U12,RM_KEY,0))="","",INDEX(RM_M_Edu,MATCH($U12,RM_KEY,0))),"") -> L | AU12: =IFERROR(IF(INDEX(RM_L_C,MATCH($U12,RM_KEY,0))="","",INDEX(RM_L_C,MATCH($U12,RM_KEY,0))),"") | AV12: =IFERROR(IF(INDEX(RM_L_Au,MATCH($U12,RM_KEY,0))="","",INDEX(RM_L_Au,MATCH($U12,RM_KEY,0))),"") | AW12: =IFERROR(IF(INDEX(RM_L_Ac,MATCH($U12,RM_KEY,0))="","",INDEX(RM_L_Ac,MATCH($U12,RM_KEY,0))),"") | AX12: =IFERROR(IF(INDEX(RM_L_L,MATCH($U12,RM_KEY,0))="","",INDEX(RM_L_L,MATCH($U12,RM_KEY,0))),"") | AY12: =IFERROR(IF(INDEX(RM_L_BI,MATCH($U12,RM_KEY,0))="","",INDEX(RM_L_BI,MATCH($U12,RM_KEY,0))),"") | AZ12: =IFERROR(IF(INDEX(RM_L_Exp,MATCH($U12,RM_KEY,0))="","",INDEX(RM_L_Exp,MATCH($U12,RM_KEY,0))),"") | BA12: =IFERROR(IF(INDEX(RM_L_Edu,MATCH($U12,RM_KEY,0))="","",INDEX(RM_L_Edu,MATCH($U12,RM_KEY,0))),"") | BB12: M | BC12: M | BD12: M | BE12: L | BF12: M | BG12: L | BH12: H | BQ12: =IF(CY12=0,"",IF(BP12<>"",BP12,IF(LEFT(W12,1)="X",W12,IF(OR(W12="B+",W12="C+"),INDEX(LAD_PC,MAX(1,MIN(14,MATCH(W12,LAD_PC,0)+IF((DA12-CZ12)>=0.5,1,IF((DA12-CZ12)<=-0.5,-1,0))))),INDEX(LAD_STD,MAX(1,MIN(12,MATCH(W12,LAD_STD,0)+IF((DA12-CZ12)>=0.5,1,IF((DA12-CZ12)<=-0.5,-1,0))))))))) | BR12: =IF(BQ12="","",IFERROR(CHOOSE(INDEX(B_RANK,MATCH(BQ12,B_LVL,0)),"Band A · Practitioner","Band B · Specialist / Manager","B+ · Player-Coach","Band C · Principal / Head","C+ · Player-Coach","Band D · Business leadership","Band E · Enterprise leadership"),"Band X · Consultant")) | BS12: =IF(BQ12="","",IF(BQ12=W12,"• Same",IF(INDEX(B_VAL,MATCH(BQ12,B_LVL,0))>INDEX(B_VAL,MATCH(W12,B_LVL,0)),"▲ Up","▼ Down"))) | BT12: =IF(BQ12<>"",BQ12,W12) -> B2 | BU12: =IFERROR(IF($H12="","—",IF(OR(LEFT(BT12,1)="X",LEFT(INDEX($BT$7:$BT$592,MATCH($H12,$D$7:$D$592,0)),1)="X"),"—",IF(AND(LEFT(BT12,1)="E",LEFT(INDEX($BT$7:$BT$592,MATCH($H12,$D$7:$D$592,0)),1)="E"),"Exception · Band E",IF(INDEX(B_VAL,MATCH(BT12,B_LVL,0))>=INDEX(B_VAL,MATCH(INDEX($BT$7:$BT$592,MATCH($H12,$D$7:$D$592,0)),B_LVL,0)),"⚠ At or above the manager",IF(INDEX(B_RANK,MATCH(BT12,B_LVL,0))=INDEX(B_RANK,MATCH(INDEX($BT$7:$BT$592,MATCH($H12,$D$7:$D$592,0)),B_LVL,0)),"⚠ Same band as the manager","OK"))))),"—") -> OK | BW12: =IFERROR(INDEX(LMH_PTS,MATCH(AG12,LMH_KEY,0)),0) -> 9 | BX12: =IFERROR(INDEX(LMH_PTS,MATCH(AH12,LMH_KEY,0)),0) -> 3 | BY12: =IFERROR(INDEX(LMH_PTS,MATCH(AI12,LMH_KEY,0)),0) -> 3 | BZ12: =IFERROR(INDEX(LMH_PTS,MATCH(AJ12,LMH_KEY,0)),0) -> 1 | CA12: =IFERROR(INDEX(LMH_PTS,MATCH(AK12,LMH_KEY,0)),0) -> 3 | CB12: =IFERROR(INDEX(LMH_PTS,MATCH(AL12,LMH_KEY,0)),0) -> 1 | CC12: =IFERROR(INDEX(LMH_PTS,MATCH(AM12,LMH_KEY,0)),0) -> 1 | CD12: =IFERROR(INDEX(LMH_PTS,MATCH(IF(AU12<>"",AU12,AG12),LMH_KEY,0)),0) -> 9 | CE12: =IFERROR(INDEX(LMH_PTS,MATCH(IF(AV12<>"",AV12,AH12),LMH_KEY,0)),0) -> 3 | CF12: =IFERROR(INDEX(LMH_PTS,MATCH(IF(AW12<>"",AW12,AI12),LMH_KEY,0)),0) -> 3 | CG12: =IFERROR(INDEX(LMH_PTS,MATCH(IF(AX12<>"",AX12,AJ12),LMH_KEY,0)),0) -> 1 | CH12: =IFERROR(INDEX(LMH_PTS,MATCH(IF(AY12<>"",AY12,AK12),LMH_KEY,0)),0) -> 3 | CI12: =IFERROR(INDEX(LMH_PTS,MATCH(IF(AZ12<>"",AZ12,AL12),LMH_KEY,0)),0) -> 1 | CJ12: =IFERROR(INDEX(LMH_PTS,MATCH(IF(BA12<>"",BA12,AM12),LMH_KEY,0)),0) -> 1 | CK12: =IF(BB12="",0,IFERROR(INDEX(LMH_STEP,MATCH(BB12,LMH_KEY,0)),0)) -> 0 | CL12: =IF(BC12="",0,IFERROR(INDEX(LMH_STEP,MATCH(BC12,LMH_KEY,0)),0)) -> 0 | CM12: =IF(BD12="",0,IFERROR(INDEX(LMH_STEP,MATCH(BD12,LMH_KEY,0)),0)) -> 0 | CN12: =IF(BE12="",0,IFERROR(INDEX(LMH_STEP,MATCH(BE12,LMH_KEY,0)),0)) -> -1 | CO12: =IF(BF12="",0,IFERROR(INDEX(LMH_STEP,MATCH(BF12,LMH_KEY,0)),0)) -> 0 | CP12: =IF(BG12="",0,IFERROR(INDEX(LMH_STEP,MATCH(BG12,LMH_KEY,0)),0)) -> -1 | CQ12: =IF(BH12="",0,IFERROR(INDEX(LMH_STEP,MATCH(BH12,LMH_KEY,0)),0)) -> 1 | CR12: =IF(BI12<>"",IFERROR(INDEX(LMH_STEP,MATCH(BI12,LMH_KEY,0)),0),CK12) -> 0 | CS12: =IF(BJ12<>"",IFERROR(INDEX(LMH_STEP,MATCH(BJ12,LMH_KEY,0)),0),CL12) -> 0 | CT12: =IF(BK12<>"",IFERROR(INDEX(LMH_STEP,MATCH(BK12,LMH_KEY,0)),0),CM12) -> 0 | CU12: =IF(BL12<>"",IFERROR(INDEX(LMH_STEP,MATCH(BL12,LMH_KEY,0)),0),CN12) -> -1 | CV12: =IF(BM12<>"",IFERROR(INDEX(LMH_STEP,MATCH(BM12,LMH_KEY,0)),0),CO12) -> 0 | CW12: =IF(BN12<>"",IFERROR(INDEX(LMH_STEP,MATCH(BN12,LMH_KEY,0)),0),CP12) -> -1 | CX12: =IF(BO12<>"",IFERROR(INDEX(LMH_STEP,MATCH(BO12,LMH_KEY,0)),0),CQ12) -> 1 | CY12: =COUNTA(BI12:BO12)+IF(BP12<>"",1,0)+IFERROR(INDEX(RM_LCNT,MATCH($U12,RM_KEY,0)),0) -> 0 | CZ12: =IF((BW12+BX12+BY12+BZ12+CA12+CB12+CC12)=0,0,(BW12*CK12+BX12*CL12+BY12*CM12+BZ12*CN12+CA12*CO12+CB12*CP12+CC12*CQ12)/(BW12+BX12+BY12+BZ12+CA12+CB12+CC12)) -> -0.047619048 | DA12: =IF((CD12+CE12+CF12+CG12+CH12+CI12+CJ12)=0,0,(CD12*CR12+CE12*CS12+CF12*CT12+CG12*CU12+CH12*CV12+CI12*CW12+CJ12*CX12)/(CD12+CE12+CF12+CG12+CH12+CI12+CJ12)) -> -0.047619048
A13: CARBON | B13: Support | C13: 5 | D13: IRIS1963 | E13: Neha Gajbhiye | F13: Manager- Customer Engagement | G13: Anushree Aparajit | H13: IRIS1335 | I13: 16.2 | J13: MBA | K13: L5 – Manager | L13: 20 of 20 | M13: • Role / sub-team: Support — Manager- Customer Engagement. • Core purpose: Client interaction, Domain expertise, Go live, platform enablement, training and end to end hypercare. • Decision-making autonomy: Can independently trainings only. • Is this something only they do: Everyone does the same but in different geos. • What's different about this role: Handling Muliple Geos, mandates and countries. | N13: Annual · set by manager: Net Revenue Retention ≥100–105% Target ARR - to be achieved: INR 1700000 90% reach value milestone in 90 days Develop advocates · Promoter per CEM Produce case studies annually CSAT ≥90% NPS ≥30 100% QBR coverage for accounts 100% CRM hygiene maintained Renewal forecast accuracy ≥95% Outstanding receivables ≤45 days Enablement and Training Share at least 3 structured customer insights with Product/Engineering per quarter. Drive price increase in renewals Mentor or … | O13: Latest rating: 4 · Potential: High · 9-box: High Impact / Growth Talent | P13: Complexity & Expertise: A3: own survey / KRA answers · summarised by the rater; not quoted → moved down 1 Autonomy & Decision: A2: States can decide independently on 'trainings only' → moved down 1 Accountability & Impact: B2: Renewals, upsell, cross-sell, outstanding payments and NPS/CSAT across multi-country accounts → moved up 0.2 Leadership & Strategy: A1: No guidance described despite one report → moved down 1 | Q13: Open ▸ | R13: Card ▸ | S13: Customer Success & Support | T13: Customer Success & Account Management | U13: R018 | V13: Customer Success & Account Management · IC | W13: B2 | X13: Band B · Specialist / Manager | Y13: Senior Customer Success Specialist – POD Lead | AA13: Placed at B2 by the evidence: six ratings × market-derived weights and rules R1–R13 · no move needed for the reporting line | AC13: B2 | AD13: High · 16.2 yrs vs market 6–10 yrs for B2 | AE13: 1 direct reports · norm IC: none · People: 6–8 knowledge work, 8–12 standardised delivery | AF13: P4 / M3 · SFIA 4–5 | AG13: =IFERROR(IF(INDEX(RM_I_C,MATCH($U13,RM_KEY,0))="","",INDEX(RM_I_C,MATCH($U13,RM_KEY,0))),"") -> H | AH13: =IFERROR(IF(INDEX(RM_I_Au,MATCH($U13,RM_KEY,0))="","",INDEX(RM_I_Au,MATCH($U13,RM_KEY,0))),"") -> M | AI13: =IFERROR(IF(INDEX(RM_I_Ac,MATCH($U13,RM_KEY,0))="","",INDEX(RM_I_Ac,MATCH($U13,RM_KEY,0))),"") -> M | AJ13: =IFERROR(IF(INDEX(RM_I_L,MATCH($U13,RM_KEY,0))="","",INDEX(RM_I_L,MATCH($U13,RM_KEY,0))),"") -> L | AK13: =IFERROR(IF(INDEX(RM_I_BI,MATCH($U13,RM_KEY,0))="","",INDEX(RM_I_BI,MATCH($U13,RM_KEY,0))),"") -> M | AL13: =IFERROR(IF(INDEX(RM_I_Exp,MATCH($U13,RM_KEY,0))="","",INDEX(RM_I_Exp,MATCH($U13,RM_KEY,0))),"") -> L | AM13: =IFERROR(IF(INDEX(RM_I_Edu,MATCH($U13,RM_KEY,0))="","",INDEX(RM_I_Edu,MATCH($U13,RM_KEY,0))),"") -> L | AN13: =IFERROR(IF(INDEX(RM_M_C,MATCH($U13,RM_KEY,0))="","",INDEX(RM_M_C,MATCH($U13,RM_KEY,0))),"") -> H | AO13: =IFERROR(IF(INDEX(RM_M_Au,MATCH($U13,RM_KEY,0))="","",INDEX(RM_M_Au,MATCH($U13,RM_KEY,0))),"") -> M | AP13: =IFERROR(IF(INDEX(RM_M_Ac,MATCH($U13,RM_KEY,0))="","",INDEX(RM_M_Ac,MATCH($U13,RM_KEY,0))),"") -> M | AQ13: =IFERROR(IF(INDEX(RM_M_L,MATCH($U13,RM_KEY,0))="","",INDEX(RM_M_L,MATCH($U13,RM_KEY,0))),"") -> L | AR13: =IFERROR(IF(INDEX(RM_M_BI,MATCH($U13,RM_KEY,0))="","",INDEX(RM_M_BI,MATCH($U13,RM_KEY,0))),"") -> L | AS13: =IFERROR(IF(INDEX(RM_M_Exp,MATCH($U13,RM_KEY,0))="","",INDEX(RM_M_Exp,MATCH($U13,RM_KEY,0))),"") -> L | AT13: =IFERROR(IF(INDEX(RM_M_Edu,MATCH($U13,RM_KEY,0))="","",INDEX(RM_M_Edu,MATCH($U13,RM_KEY,0))),"") -> L | AU13: =IFERROR(IF(INDEX(RM_L_C,MATCH($U13,RM_KEY,0))="","",INDEX(RM_L_C,MATCH($U13,RM_KEY,0))),"") | AV13: =IFERROR(IF(INDEX(RM_L_Au,MATCH($U13,RM_KEY,0))="","",INDEX(RM_L_Au,MATCH($U13,RM_KEY,0))),"") | AW13: =IFERROR(IF(INDEX(RM_L_Ac,MATCH($U13,RM_KEY,0))="","",INDEX(RM_L_Ac,MATCH($U13,RM_KEY,0))),"") | AX13: =IFERROR(IF(INDEX(RM_L_L,MATCH($U13,RM_KEY,0))="","",INDEX(RM_L_L,MATCH($U13,RM_KEY,0))),"") | AY13: =IFERROR(IF(INDEX(RM_L_BI,MATCH($U13,RM_KEY,0))="","",INDEX(RM_L_BI,MATCH($U13,RM_KEY,0))),"") | AZ13: =IFERROR(IF(INDEX(RM_L_Exp,MATCH($U13,RM_KEY,0))="","",INDEX(RM_L_Exp,MATCH($U13,RM_KEY,0))),"") | BA13: =IFERROR(IF(INDEX(RM_L_Edu,MATCH($U13,RM_KEY,0))="","",INDEX(RM_L_Edu,MATCH($U13,RM_KEY,0))),"") | BB13: L | BC13: L | BD13: M | BE13: L | BF13: M | BG13: H | BH13: H | BQ13: =IF(CY13=0,"",IF(BP13<>"",BP13,IF(LEFT(W13,1)="X",W13,IF(OR(W13="B+",W13="C+"),INDEX(LAD_PC,MAX(1,MIN(14,MATCH(W13,LAD_PC,0)+IF((DA13-CZ13)>=0.5,1,IF((DA13-CZ13)<=-0.5,-1,0))))),INDEX(LAD_STD,MAX(1,MIN(12,MATCH(W13,LAD_STD,0)+IF((DA13-CZ13)>=0.5,1,IF((DA13-CZ13)<=-0.5,-1,0))))))))) | BR13: =IF(BQ13="","",IFERROR(CHOOSE(INDEX(B_RANK,MATCH(BQ13,B_LVL,0)),"Band A · Practitioner","Band B · Specialist / Manager","B+ · Player-Coach","Band C · Principal / Head","C+ · Player-Coach","Band D · Business leadership","Band E · Enterprise leadership"),"Band X · Consultant")) | BS13: =IF(BQ13="","",IF(BQ13=W13,"• Same",IF(INDEX(B_VAL,MATCH(BQ13,B_LVL,0))>INDEX(B_VAL,MATCH(W13,B_LVL,0)),"▲ Up","▼ Down"))) | BT13: =IF(BQ13<>"",BQ13,W13) -> B2 | BU13: =IFERROR(IF($H13="","—",IF(OR(LEFT(BT13,1)="X",LEFT(INDEX($BT$7:$BT$592,MATCH($H13,$D$7:$D$592,0)),1)="X"),"—",IF(AND(LEFT(BT13,1)="E",LEFT(INDEX($BT$7:$BT$592,MATCH($H13,$D$7:$D$592,0)),1)="E"),"Exception · Band E",IF(INDEX(B_VAL,MATCH(BT13,B_LVL,0))>=INDEX(B_VAL,MATCH(INDEX($BT$7:$BT$592,MATCH($H13,$D$7:$D$592,0)),B_LVL,0)),"⚠ At or above the manager",IF(INDEX(B_RANK,MATCH(BT13,B_LVL,0))=INDEX(B_RANK,MATCH(INDEX($BT$7:$BT$592,MATCH($H13,$D$7:$D$592,0)),B_LVL,0)),"⚠ Same band as the manager","OK"))))),"—") -> OK | BW13: =IFERROR(INDEX(LMH_PTS,MATCH(AG13,LMH_KEY,0)),0) -> 9 | BX13: =IFERROR(INDEX(LMH_PTS,MATCH(AH13,LMH_KEY,0)),0) -> 3 | BY13: =IFERROR(INDEX(LMH_PTS,MATCH(AI13,LMH_KEY,0)),0) -> 3 | BZ13: =IFERROR(INDEX(LMH_PTS,MATCH(AJ13,LMH_KEY,0)),0) -> 1 | CA13: =IFERROR(INDEX(LMH_PTS,MATCH(AK13,LMH_KEY,0)),0) -> 3 | CB13: =IFERROR(INDEX(LMH_PTS,MATCH(AL13,LMH_KEY,0)),0) -> 1 | CC13: =IFERROR(INDEX(LMH_PTS,MATCH(AM13,LMH_KEY,0)),0) -> 1 | CD13: =IFERROR(INDEX(LMH_PTS,MATCH(IF(AU13<>"",AU13,AG13),LMH_KEY,0)),0) -> 9 | CE13: =IFERROR(INDEX(LMH_PTS,MATCH(IF(AV13<>"",AV13,AH13),LMH_KEY,0)),0) -> 3 | CF13: =IFERROR(INDEX(LMH_PTS,MATCH(IF(AW13<>"",AW13,AI13),LMH_KEY,0)),0) -> 3 | CG13: =IFERROR(INDEX(LMH_PTS,MATCH(IF(AX13<>"",AX13,AJ13),LMH_KEY,0)),0) -> 1 | CH13: =IFERROR(INDEX(LMH_PTS,MATCH(IF(AY13<>"",AY13,AK13),LMH_KEY,0)),0) -> 3 | CI13: =IFERROR(INDEX(LMH_PTS,MATCH(IF(AZ13<>"",AZ13,AL13),LMH_KEY,0)),0) -> 1 | CJ13: =IFERROR(INDEX(LMH_PTS,MATCH(IF(BA13<>"",BA13,AM13),LMH_KEY,0)),0) -> 1 | CK13: =IF(BB13="",0,IFERROR(INDEX(LMH_STEP,MATCH(BB13,LMH_KEY,0)),0)) -> -1 | CL13: =IF(BC13="",0,IFERROR(INDEX(LMH_STEP,MATCH(BC13,LMH_KEY,0)),0)) -> -1 | CM13: =IF(BD13="",0,IFERROR(INDEX(LMH_STEP,MATCH(BD13,LMH_KEY,0)),0)) -> 0 | CN13: =IF(BE13="",0,IFERROR(INDEX(LMH_STEP,MATCH(BE13,LMH_KEY,0)),0)) -> -1 | CO13: =IF(BF13="",0,IFERROR(INDEX(LMH_STEP,MATCH(BF13,LMH_KEY,0)),0)) -> 0 | CP13: =IF(BG13="",0,IFERROR(INDEX(LMH_STEP,MATCH(BG13,LMH_KEY,0)),0)) -> 1 | CQ13: =IF(BH13="",0,IFERROR(INDEX(LMH_STEP,MATCH(BH13,LMH_KEY,0)),0)) -> 1 | CR13: =IF(BI13<>"",IFERROR(INDEX(LMH_STEP,MATCH(BI13,LMH_KEY,0)),0),CK13) -> -1 | CS13: =IF(BJ13<>"",IFERROR(INDEX(LMH_STEP,MATCH(BJ13,LMH_KEY,0)),0),CL13) -> -1 | CT13: =IF(BK13<>"",IFERROR(INDEX(LMH_STEP,MATCH(BK13,LMH_KEY,0)),0),CM13) -> 0 | CU13: =IF(BL13<>"",IFERROR(INDEX(LMH_STEP,MATCH(BL13,LMH_KEY,0)),0),CN13) -> -1 | CV13: =IF(BM13<>"",IFERROR(INDEX(LMH_STEP,MATCH(BM13,LMH_KEY,0)),0),CO13) -> 0 | CW13: =IF(BN13<>"",IFERROR(INDEX(LMH_STEP,MATCH(BN13,LMH_KEY,0)),0),CP13) -> 1 | CX13: =IF(BO13<>"",IFERROR(INDEX(LMH_STEP,MATCH(BO13,LMH_KEY,0)),0),CQ13) -> 1 | CY13: =COUNTA(BI13:BO13)+IF(BP13<>"",1,0)+IFERROR(INDEX(RM_LCNT,MATCH($U13,RM_KEY,0)),0) -> 0 | CZ13: =IF((BW13+BX13+BY13+BZ13+CA13+CB13+CC13)=0,0,(BW13*CK13+BX13*CL13+BY13*CM13+BZ13*CN13+CA13*CO13+CB13*CP13+CC13*CQ13)/(BW13+BX13+BY13+BZ13+CA13+CB13+CC13)) -> -0.52380952 | DA13: =IF((CD13+CE13+CF13+CG13+CH13+CI13+CJ13)=0,0,(CD13*CR13+CE13*CS13+CF13*CT13+CG13*CU13+CH13*CV13+CI13*CW13+CJ13*CX13)/(CD13+CE13+CF13+CG13+CH13+CI13+CJ13)) -> -0.52380952
